package asm.org.bouncycastle.crypto.digests;
import org.objectweb.asm.AnnotationVisitor;
import org.objectweb.asm.Attribute;
import org.objectweb.asm.ClassReader;
import org.objectweb.asm.ClassWriter;
import org.objectweb.asm.ConstantDynamic;
import org.objectweb.asm.FieldVisitor;
import org.objectweb.asm.Handle;
import org.objectweb.asm.Label;
import org.objectweb.asm.MethodVisitor;
import org.objectweb.asm.Opcodes;
import org.objectweb.asm.RecordComponentVisitor;
import org.objectweb.asm.Type;
import org.objectweb.asm.TypePath;
public class SHA1DigestDump implements Opcodes {

public static byte[] dump () throws Exception {

ClassWriter classWriter = new ClassWriter(0);
FieldVisitor fieldVisitor;
RecordComponentVisitor recordComponentVisitor;
MethodVisitor methodVisitor;
AnnotationVisitor annotationVisitor0;

classWriter.visit(V1_5, ACC_PUBLIC | ACC_SUPER, "org/bouncycastle/crypto/digests/SHA1Digest", null, "org/bouncycastle/crypto/digests/GeneralDigest", new String[] { "org/bouncycastle/crypto/digests/EncodableDigest" });

{
fieldVisitor = classWriter.visitField(ACC_PRIVATE | ACC_FINAL | ACC_STATIC, "DIGEST_LENGTH", "I", null, new Integer(20));
fieldVisitor.visitEnd();
}
{
fieldVisitor = classWriter.visitField(ACC_PRIVATE, "H1", "I", null, null);
fieldVisitor.visitEnd();
}
{
fieldVisitor = classWriter.visitField(ACC_PRIVATE, "H2", "I", null, null);
fieldVisitor.visitEnd();
}
{
fieldVisitor = classWriter.visitField(ACC_PRIVATE, "H3", "I", null, null);
fieldVisitor.visitEnd();
}
{
fieldVisitor = classWriter.visitField(ACC_PRIVATE, "H4", "I", null, null);
fieldVisitor.visitEnd();
}
{
fieldVisitor = classWriter.visitField(ACC_PRIVATE, "H5", "I", null, null);
fieldVisitor.visitEnd();
}
{
fieldVisitor = classWriter.visitField(ACC_PRIVATE, "X", "[I", null, null);
fieldVisitor.visitEnd();
}
{
fieldVisitor = classWriter.visitField(ACC_PRIVATE, "xOff", "I", null, null);
fieldVisitor.visitEnd();
}
{
fieldVisitor = classWriter.visitField(ACC_PRIVATE | ACC_FINAL | ACC_STATIC, "Y1", "I", null, new Integer(1518500249));
fieldVisitor.visitEnd();
}
{
fieldVisitor = classWriter.visitField(ACC_PRIVATE | ACC_FINAL | ACC_STATIC, "Y2", "I", null, new Integer(1859775393));
fieldVisitor.visitEnd();
}
{
fieldVisitor = classWriter.visitField(ACC_PRIVATE | ACC_FINAL | ACC_STATIC, "Y3", "I", null, new Integer(-1894007588));
fieldVisitor.visitEnd();
}
{
fieldVisitor = classWriter.visitField(ACC_PRIVATE | ACC_FINAL | ACC_STATIC, "Y4", "I", null, new Integer(-899497514));
fieldVisitor.visitEnd();
}
{
methodVisitor = classWriter.visitMethod(ACC_PUBLIC, "<init>", "()V", null, null);
methodVisitor.visitCode();
methodVisitor.visitVarInsn(ALOAD, 0);
methodVisitor.visitMethodInsn(INVOKESPECIAL, "org/bouncycastle/crypto/digests/GeneralDigest", "<init>", "()V", false);
methodVisitor.visitVarInsn(ALOAD, 0);
methodVisitor.visitIntInsn(BIPUSH, 80);
methodVisitor.visitIntInsn(NEWARRAY, T_INT);
methodVisitor.visitFieldInsn(PUTFIELD, "org/bouncycastle/crypto/digests/SHA1Digest", "X", "[I");
methodVisitor.visitVarInsn(ALOAD, 0);
methodVisitor.visitMethodInsn(INVOKEVIRTUAL, "org/bouncycastle/crypto/digests/SHA1Digest", "reset", "()V", false);
methodVisitor.visitInsn(RETURN);
methodVisitor.visitMaxs(2, 1);
methodVisitor.visitEnd();
}
{
methodVisitor = classWriter.visitMethod(ACC_PUBLIC, "<init>", "(Lorg/bouncycastle/crypto/digests/SHA1Digest;)V", null, null);
methodVisitor.visitCode();
methodVisitor.visitVarInsn(ALOAD, 0);
methodVisitor.visitVarInsn(ALOAD, 1);
methodVisitor.visitMethodInsn(INVOKESPECIAL, "org/bouncycastle/crypto/digests/GeneralDigest", "<init>", "(Lorg/bouncycastle/crypto/digests/GeneralDigest;)V", false);
methodVisitor.visitVarInsn(ALOAD, 0);
methodVisitor.visitIntInsn(BIPUSH, 80);
methodVisitor.visitIntInsn(NEWARRAY, T_INT);
methodVisitor.visitFieldInsn(PUTFIELD, "org/bouncycastle/crypto/digests/SHA1Digest", "X", "[I");
methodVisitor.visitVarInsn(ALOAD, 0);
methodVisitor.visitVarInsn(ALOAD, 1);
methodVisitor.visitMethodInsn(INVOKESPECIAL, "org/bouncycastle/crypto/digests/SHA1Digest", "copyIn", "(Lorg/bouncycastle/crypto/digests/SHA1Digest;)V", false);
methodVisitor.visitInsn(RETURN);
methodVisitor.visitMaxs(2, 2);
methodVisitor.visitEnd();
}
{
methodVisitor = classWriter.visitMethod(ACC_PUBLIC, "<init>", "([B)V", null, null);
methodVisitor.visitCode();
methodVisitor.visitVarInsn(ALOAD, 0);
methodVisitor.visitVarInsn(ALOAD, 1);
methodVisitor.visitMethodInsn(INVOKESPECIAL, "org/bouncycastle/crypto/digests/GeneralDigest", "<init>", "([B)V", false);
methodVisitor.visitVarInsn(ALOAD, 0);
methodVisitor.visitIntInsn(BIPUSH, 80);
methodVisitor.visitIntInsn(NEWARRAY, T_INT);
methodVisitor.visitFieldInsn(PUTFIELD, "org/bouncycastle/crypto/digests/SHA1Digest", "X", "[I");
methodVisitor.visitVarInsn(ALOAD, 0);
methodVisitor.visitVarInsn(ALOAD, 1);
methodVisitor.visitIntInsn(BIPUSH, 16);
methodVisitor.visitMethodInsn(INVOKESTATIC, "org/bouncycastle/util/Pack", "bigEndianToInt", "([BI)I", false);
methodVisitor.visitFieldInsn(PUTFIELD, "org/bouncycastle/crypto/digests/SHA1Digest", "H1", "I");
methodVisitor.visitVarInsn(ALOAD, 0);
methodVisitor.visitVarInsn(ALOAD, 1);
methodVisitor.visitIntInsn(BIPUSH, 20);
methodVisitor.visitMethodInsn(INVOKESTATIC, "org/bouncycastle/util/Pack", "bigEndianToInt", "([BI)I", false);
methodVisitor.visitFieldInsn(PUTFIELD, "org/bouncycastle/crypto/digests/SHA1Digest", "H2", "I");
methodVisitor.visitVarInsn(ALOAD, 0);
methodVisitor.visitVarInsn(ALOAD, 1);
methodVisitor.visitIntInsn(BIPUSH, 24);
methodVisitor.visitMethodInsn(INVOKESTATIC, "org/bouncycastle/util/Pack", "bigEndianToInt", "([BI)I", false);
methodVisitor.visitFieldInsn(PUTFIELD, "org/bouncycastle/crypto/digests/SHA1Digest", "H3", "I");
methodVisitor.visitVarInsn(ALOAD, 0);
methodVisitor.visitVarInsn(ALOAD, 1);
methodVisitor.visitIntInsn(BIPUSH, 28);
methodVisitor.visitMethodInsn(INVOKESTATIC, "org/bouncycastle/util/Pack", "bigEndianToInt", "([BI)I", false);
methodVisitor.visitFieldInsn(PUTFIELD, "org/bouncycastle/crypto/digests/SHA1Digest", "H4", "I");
methodVisitor.visitVarInsn(ALOAD, 0);
methodVisitor.visitVarInsn(ALOAD, 1);
methodVisitor.visitIntInsn(BIPUSH, 32);
methodVisitor.visitMethodInsn(INVOKESTATIC, "org/bouncycastle/util/Pack", "bigEndianToInt", "([BI)I", false);
methodVisitor.visitFieldInsn(PUTFIELD, "org/bouncycastle/crypto/digests/SHA1Digest", "H5", "I");
methodVisitor.visitVarInsn(ALOAD, 0);
methodVisitor.visitVarInsn(ALOAD, 1);
methodVisitor.visitIntInsn(BIPUSH, 36);
methodVisitor.visitMethodInsn(INVOKESTATIC, "org/bouncycastle/util/Pack", "bigEndianToInt", "([BI)I", false);
methodVisitor.visitFieldInsn(PUTFIELD, "org/bouncycastle/crypto/digests/SHA1Digest", "xOff", "I");
methodVisitor.visitInsn(ICONST_0);
methodVisitor.visitVarInsn(ISTORE, 2);
Label label0 = new Label();
methodVisitor.visitLabel(label0);
methodVisitor.visitVarInsn(ILOAD, 2);
methodVisitor.visitVarInsn(ALOAD, 0);
methodVisitor.visitFieldInsn(GETFIELD, "org/bouncycastle/crypto/digests/SHA1Digest", "xOff", "I");
Label label1 = new Label();
methodVisitor.visitJumpInsn(IF_ICMPEQ, label1);
methodVisitor.visitVarInsn(ALOAD, 0);
methodVisitor.visitFieldInsn(GETFIELD, "org/bouncycastle/crypto/digests/SHA1Digest", "X", "[I");
methodVisitor.visitVarInsn(ILOAD, 2);
methodVisitor.visitVarInsn(ALOAD, 1);
methodVisitor.visitIntInsn(BIPUSH, 40);
methodVisitor.visitVarInsn(ILOAD, 2);
methodVisitor.visitInsn(ICONST_4);
methodVisitor.visitInsn(IMUL);
methodVisitor.visitInsn(IADD);
methodVisitor.visitMethodInsn(INVOKESTATIC, "org/bouncycastle/util/Pack", "bigEndianToInt", "([BI)I", false);
methodVisitor.visitInsn(IASTORE);
methodVisitor.visitIincInsn(2, 1);
methodVisitor.visitJumpInsn(GOTO, label0);
methodVisitor.visitLabel(label1);
methodVisitor.visitInsn(RETURN);
methodVisitor.visitMaxs(6, 3);
methodVisitor.visitEnd();
}
{
methodVisitor = classWriter.visitMethod(ACC_PRIVATE, "copyIn", "(Lorg/bouncycastle/crypto/digests/SHA1Digest;)V", null, null);
methodVisitor.visitCode();
methodVisitor.visitVarInsn(ALOAD, 0);
methodVisitor.visitVarInsn(ALOAD, 1);
methodVisitor.visitFieldInsn(GETFIELD, "org/bouncycastle/crypto/digests/SHA1Digest", "H1", "I");
methodVisitor.visitFieldInsn(PUTFIELD, "org/bouncycastle/crypto/digests/SHA1Digest", "H1", "I");
methodVisitor.visitVarInsn(ALOAD, 0);
methodVisitor.visitVarInsn(ALOAD, 1);
methodVisitor.visitFieldInsn(GETFIELD, "org/bouncycastle/crypto/digests/SHA1Digest", "H2", "I");
methodVisitor.visitFieldInsn(PUTFIELD, "org/bouncycastle/crypto/digests/SHA1Digest", "H2", "I");
methodVisitor.visitVarInsn(ALOAD, 0);
methodVisitor.visitVarInsn(ALOAD, 1);
methodVisitor.visitFieldInsn(GETFIELD, "org/bouncycastle/crypto/digests/SHA1Digest", "H3", "I");
methodVisitor.visitFieldInsn(PUTFIELD, "org/bouncycastle/crypto/digests/SHA1Digest", "H3", "I");
methodVisitor.visitVarInsn(ALOAD, 0);
methodVisitor.visitVarInsn(ALOAD, 1);
methodVisitor.visitFieldInsn(GETFIELD, "org/bouncycastle/crypto/digests/SHA1Digest", "H4", "I");
methodVisitor.visitFieldInsn(PUTFIELD, "org/bouncycastle/crypto/digests/SHA1Digest", "H4", "I");
methodVisitor.visitVarInsn(ALOAD, 0);
methodVisitor.visitVarInsn(ALOAD, 1);
methodVisitor.visitFieldInsn(GETFIELD, "org/bouncycastle/crypto/digests/SHA1Digest", "H5", "I");
methodVisitor.visitFieldInsn(PUTFIELD, "org/bouncycastle/crypto/digests/SHA1Digest", "H5", "I");
methodVisitor.visitVarInsn(ALOAD, 1);
methodVisitor.visitFieldInsn(GETFIELD, "org/bouncycastle/crypto/digests/SHA1Digest", "X", "[I");
methodVisitor.visitInsn(ICONST_0);
methodVisitor.visitVarInsn(ALOAD, 0);
methodVisitor.visitFieldInsn(GETFIELD, "org/bouncycastle/crypto/digests/SHA1Digest", "X", "[I");
methodVisitor.visitInsn(ICONST_0);
methodVisitor.visitVarInsn(ALOAD, 1);
methodVisitor.visitFieldInsn(GETFIELD, "org/bouncycastle/crypto/digests/SHA1Digest", "X", "[I");
methodVisitor.visitInsn(ARRAYLENGTH);
methodVisitor.visitMethodInsn(INVOKESTATIC, "java/lang/System", "arraycopy", "(Ljava/lang/Object;ILjava/lang/Object;II)V", false);
methodVisitor.visitVarInsn(ALOAD, 0);
methodVisitor.visitVarInsn(ALOAD, 1);
methodVisitor.visitFieldInsn(GETFIELD, "org/bouncycastle/crypto/digests/SHA1Digest", "xOff", "I");
methodVisitor.visitFieldInsn(PUTFIELD, "org/bouncycastle/crypto/digests/SHA1Digest", "xOff", "I");
methodVisitor.visitInsn(RETURN);
methodVisitor.visitMaxs(5, 2);
methodVisitor.visitEnd();
}
{
methodVisitor = classWriter.visitMethod(ACC_PUBLIC, "getAlgorithmName", "()Ljava/lang/String;", null, null);
methodVisitor.visitCode();
methodVisitor.visitLdcInsn("SHA-1");
methodVisitor.visitInsn(ARETURN);
methodVisitor.visitMaxs(1, 1);
methodVisitor.visitEnd();
}
{
methodVisitor = classWriter.visitMethod(ACC_PUBLIC, "getDigestSize", "()I", null, null);
methodVisitor.visitCode();
methodVisitor.visitIntInsn(BIPUSH, 20);
methodVisitor.visitInsn(IRETURN);
methodVisitor.visitMaxs(1, 1);
methodVisitor.visitEnd();
}
{
methodVisitor = classWriter.visitMethod(ACC_PROTECTED, "processWord", "([BI)V", null, null);
methodVisitor.visitCode();
methodVisitor.visitVarInsn(ALOAD, 1);
methodVisitor.visitVarInsn(ILOAD, 2);
methodVisitor.visitInsn(BALOAD);
methodVisitor.visitIntInsn(BIPUSH, 24);
methodVisitor.visitInsn(ISHL);
methodVisitor.visitVarInsn(ISTORE, 3);
methodVisitor.visitVarInsn(ILOAD, 3);
methodVisitor.visitVarInsn(ALOAD, 1);
methodVisitor.visitIincInsn(2, 1);
methodVisitor.visitVarInsn(ILOAD, 2);
methodVisitor.visitInsn(BALOAD);
methodVisitor.visitIntInsn(SIPUSH, 255);
methodVisitor.visitInsn(IAND);
methodVisitor.visitIntInsn(BIPUSH, 16);
methodVisitor.visitInsn(ISHL);
methodVisitor.visitInsn(IOR);
methodVisitor.visitVarInsn(ISTORE, 3);
methodVisitor.visitVarInsn(ILOAD, 3);
methodVisitor.visitVarInsn(ALOAD, 1);
methodVisitor.visitIincInsn(2, 1);
methodVisitor.visitVarInsn(ILOAD, 2);
methodVisitor.visitInsn(BALOAD);
methodVisitor.visitIntInsn(SIPUSH, 255);
methodVisitor.visitInsn(IAND);
methodVisitor.visitIntInsn(BIPUSH, 8);
methodVisitor.visitInsn(ISHL);
methodVisitor.visitInsn(IOR);
methodVisitor.visitVarInsn(ISTORE, 3);
methodVisitor.visitVarInsn(ILOAD, 3);
methodVisitor.visitVarInsn(ALOAD, 1);
methodVisitor.visitIincInsn(2, 1);
methodVisitor.visitVarInsn(ILOAD, 2);
methodVisitor.visitInsn(BALOAD);
methodVisitor.visitIntInsn(SIPUSH, 255);
methodVisitor.visitInsn(IAND);
methodVisitor.visitInsn(IOR);
methodVisitor.visitVarInsn(ISTORE, 3);
methodVisitor.visitVarInsn(ALOAD, 0);
methodVisitor.visitFieldInsn(GETFIELD, "org/bouncycastle/crypto/digests/SHA1Digest", "X", "[I");
methodVisitor.visitVarInsn(ALOAD, 0);
methodVisitor.visitFieldInsn(GETFIELD, "org/bouncycastle/crypto/digests/SHA1Digest", "xOff", "I");
methodVisitor.visitVarInsn(ILOAD, 3);
methodVisitor.visitInsn(IASTORE);
methodVisitor.visitVarInsn(ALOAD, 0);
methodVisitor.visitInsn(DUP);
methodVisitor.visitFieldInsn(GETFIELD, "org/bouncycastle/crypto/digests/SHA1Digest", "xOff", "I");
methodVisitor.visitInsn(ICONST_1);
methodVisitor.visitInsn(IADD);
methodVisitor.visitInsn(DUP_X1);
methodVisitor.visitFieldInsn(PUTFIELD, "org/bouncycastle/crypto/digests/SHA1Digest", "xOff", "I");
methodVisitor.visitIntInsn(BIPUSH, 16);
Label label0 = new Label();
methodVisitor.visitJumpInsn(IF_ICMPNE, label0);
methodVisitor.visitVarInsn(ALOAD, 0);
methodVisitor.visitMethodInsn(INVOKEVIRTUAL, "org/bouncycastle/crypto/digests/SHA1Digest", "processBlock", "()V", false);
methodVisitor.visitLabel(label0);
methodVisitor.visitInsn(RETURN);
methodVisitor.visitMaxs(3, 4);
methodVisitor.visitEnd();
}
{
methodVisitor = classWriter.visitMethod(ACC_PROTECTED, "processLength", "(J)V", null, null);
methodVisitor.visitCode();
methodVisitor.visitVarInsn(ALOAD, 0);
methodVisitor.visitFieldInsn(GETFIELD, "org/bouncycastle/crypto/digests/SHA1Digest", "xOff", "I");
methodVisitor.visitIntInsn(BIPUSH, 14);
Label label0 = new Label();
methodVisitor.visitJumpInsn(IF_ICMPLE, label0);
methodVisitor.visitVarInsn(ALOAD, 0);
methodVisitor.visitMethodInsn(INVOKEVIRTUAL, "org/bouncycastle/crypto/digests/SHA1Digest", "processBlock", "()V", false);
methodVisitor.visitLabel(label0);
methodVisitor.visitVarInsn(ALOAD, 0);
methodVisitor.visitFieldInsn(GETFIELD, "org/bouncycastle/crypto/digests/SHA1Digest", "X", "[I");
methodVisitor.visitIntInsn(BIPUSH, 14);
methodVisitor.visitVarInsn(LLOAD, 1);
methodVisitor.visitIntInsn(BIPUSH, 32);
methodVisitor.visitInsn(LUSHR);
methodVisitor.visitInsn(L2I);
methodVisitor.visitInsn(IASTORE);
methodVisitor.visitVarInsn(ALOAD, 0);
methodVisitor.visitFieldInsn(GETFIELD, "org/bouncycastle/crypto/digests/SHA1Digest", "X", "[I");
methodVisitor.visitIntInsn(BIPUSH, 15);
methodVisitor.visitVarInsn(LLOAD, 1);
methodVisitor.visitInsn(L2I);
methodVisitor.visitInsn(IASTORE);
methodVisitor.visitInsn(RETURN);
methodVisitor.visitMaxs(5, 3);
methodVisitor.visitEnd();
}
{
methodVisitor = classWriter.visitMethod(ACC_PUBLIC, "doFinal", "([BI)I", null, null);
methodVisitor.visitCode();
methodVisitor.visitVarInsn(ALOAD, 0);
methodVisitor.visitMethodInsn(INVOKEVIRTUAL, "org/bouncycastle/crypto/digests/SHA1Digest", "finish", "()V", false);
methodVisitor.visitVarInsn(ALOAD, 0);
methodVisitor.visitFieldInsn(GETFIELD, "org/bouncycastle/crypto/digests/SHA1Digest", "H1", "I");
methodVisitor.visitVarInsn(ALOAD, 1);
methodVisitor.visitVarInsn(ILOAD, 2);
methodVisitor.visitMethodInsn(INVOKESTATIC, "org/bouncycastle/util/Pack", "intToBigEndian", "(I[BI)V", false);
methodVisitor.visitVarInsn(ALOAD, 0);
methodVisitor.visitFieldInsn(GETFIELD, "org/bouncycastle/crypto/digests/SHA1Digest", "H2", "I");
methodVisitor.visitVarInsn(ALOAD, 1);
methodVisitor.visitVarInsn(ILOAD, 2);
methodVisitor.visitInsn(ICONST_4);
methodVisitor.visitInsn(IADD);
methodVisitor.visitMethodInsn(INVOKESTATIC, "org/bouncycastle/util/Pack", "intToBigEndian", "(I[BI)V", false);
methodVisitor.visitVarInsn(ALOAD, 0);
methodVisitor.visitFieldInsn(GETFIELD, "org/bouncycastle/crypto/digests/SHA1Digest", "H3", "I");
methodVisitor.visitVarInsn(ALOAD, 1);
methodVisitor.visitVarInsn(ILOAD, 2);
methodVisitor.visitIntInsn(BIPUSH, 8);
methodVisitor.visitInsn(IADD);
methodVisitor.visitMethodInsn(INVOKESTATIC, "org/bouncycastle/util/Pack", "intToBigEndian", "(I[BI)V", false);
methodVisitor.visitVarInsn(ALOAD, 0);
methodVisitor.visitFieldInsn(GETFIELD, "org/bouncycastle/crypto/digests/SHA1Digest", "H4", "I");
methodVisitor.visitVarInsn(ALOAD, 1);
methodVisitor.visitVarInsn(ILOAD, 2);
methodVisitor.visitIntInsn(BIPUSH, 12);
methodVisitor.visitInsn(IADD);
methodVisitor.visitMethodInsn(INVOKESTATIC, "org/bouncycastle/util/Pack", "intToBigEndian", "(I[BI)V", false);
methodVisitor.visitVarInsn(ALOAD, 0);
methodVisitor.visitFieldInsn(GETFIELD, "org/bouncycastle/crypto/digests/SHA1Digest", "H5", "I");
methodVisitor.visitVarInsn(ALOAD, 1);
methodVisitor.visitVarInsn(ILOAD, 2);
methodVisitor.visitIntInsn(BIPUSH, 16);
methodVisitor.visitInsn(IADD);
methodVisitor.visitMethodInsn(INVOKESTATIC, "org/bouncycastle/util/Pack", "intToBigEndian", "(I[BI)V", false);
methodVisitor.visitVarInsn(ALOAD, 0);
methodVisitor.visitMethodInsn(INVOKEVIRTUAL, "org/bouncycastle/crypto/digests/SHA1Digest", "reset", "()V", false);
methodVisitor.visitIntInsn(BIPUSH, 20);
methodVisitor.visitInsn(IRETURN);
methodVisitor.visitMaxs(4, 3);
methodVisitor.visitEnd();
}
{
methodVisitor = classWriter.visitMethod(ACC_PUBLIC, "reset", "()V", null, null);
methodVisitor.visitCode();
methodVisitor.visitVarInsn(ALOAD, 0);
methodVisitor.visitMethodInsn(INVOKESPECIAL, "org/bouncycastle/crypto/digests/GeneralDigest", "reset", "()V", false);
methodVisitor.visitVarInsn(ALOAD, 0);
methodVisitor.visitLdcInsn(new Integer(1732584193));
methodVisitor.visitFieldInsn(PUTFIELD, "org/bouncycastle/crypto/digests/SHA1Digest", "H1", "I");
methodVisitor.visitVarInsn(ALOAD, 0);
methodVisitor.visitLdcInsn(new Integer(-271733879));
methodVisitor.visitFieldInsn(PUTFIELD, "org/bouncycastle/crypto/digests/SHA1Digest", "H2", "I");
methodVisitor.visitVarInsn(ALOAD, 0);
methodVisitor.visitLdcInsn(new Integer(-1732584194));
methodVisitor.visitFieldInsn(PUTFIELD, "org/bouncycastle/crypto/digests/SHA1Digest", "H3", "I");
methodVisitor.visitVarInsn(ALOAD, 0);
methodVisitor.visitLdcInsn(new Integer(271733878));
methodVisitor.visitFieldInsn(PUTFIELD, "org/bouncycastle/crypto/digests/SHA1Digest", "H4", "I");
methodVisitor.visitVarInsn(ALOAD, 0);
methodVisitor.visitLdcInsn(new Integer(-1009589776));
methodVisitor.visitFieldInsn(PUTFIELD, "org/bouncycastle/crypto/digests/SHA1Digest", "H5", "I");
methodVisitor.visitVarInsn(ALOAD, 0);
methodVisitor.visitInsn(ICONST_0);
methodVisitor.visitFieldInsn(PUTFIELD, "org/bouncycastle/crypto/digests/SHA1Digest", "xOff", "I");
methodVisitor.visitInsn(ICONST_0);
methodVisitor.visitVarInsn(ISTORE, 1);
Label label0 = new Label();
methodVisitor.visitLabel(label0);
methodVisitor.visitVarInsn(ILOAD, 1);
methodVisitor.visitVarInsn(ALOAD, 0);
methodVisitor.visitFieldInsn(GETFIELD, "org/bouncycastle/crypto/digests/SHA1Digest", "X", "[I");
methodVisitor.visitInsn(ARRAYLENGTH);
Label label1 = new Label();
methodVisitor.visitJumpInsn(IF_ICMPEQ, label1);
methodVisitor.visitVarInsn(ALOAD, 0);
methodVisitor.visitFieldInsn(GETFIELD, "org/bouncycastle/crypto/digests/SHA1Digest", "X", "[I");
methodVisitor.visitVarInsn(ILOAD, 1);
methodVisitor.visitInsn(ICONST_0);
methodVisitor.visitInsn(IASTORE);
methodVisitor.visitIincInsn(1, 1);
methodVisitor.visitJumpInsn(GOTO, label0);
methodVisitor.visitLabel(label1);
methodVisitor.visitInsn(RETURN);
methodVisitor.visitMaxs(3, 2);
methodVisitor.visitEnd();
}
{
methodVisitor = classWriter.visitMethod(ACC_PRIVATE, "f", "(III)I", null, null);
methodVisitor.visitCode();
methodVisitor.visitVarInsn(ILOAD, 1);
methodVisitor.visitVarInsn(ILOAD, 2);
methodVisitor.visitInsn(IAND);
methodVisitor.visitVarInsn(ILOAD, 1);
methodVisitor.visitInsn(ICONST_M1);
methodVisitor.visitInsn(IXOR);
methodVisitor.visitVarInsn(ILOAD, 3);
methodVisitor.visitInsn(IAND);
methodVisitor.visitInsn(IOR);
methodVisitor.visitInsn(IRETURN);
methodVisitor.visitMaxs(3, 4);
methodVisitor.visitEnd();
}
{
methodVisitor = classWriter.visitMethod(ACC_PRIVATE, "h", "(III)I", null, null);
methodVisitor.visitCode();
methodVisitor.visitVarInsn(ILOAD, 1);
methodVisitor.visitVarInsn(ILOAD, 2);
methodVisitor.visitInsn(IXOR);
methodVisitor.visitVarInsn(ILOAD, 3);
methodVisitor.visitInsn(IXOR);
methodVisitor.visitInsn(IRETURN);
methodVisitor.visitMaxs(2, 4);
methodVisitor.visitEnd();
}
{
methodVisitor = classWriter.visitMethod(ACC_PRIVATE, "g", "(III)I", null, null);
methodVisitor.visitCode();
methodVisitor.visitVarInsn(ILOAD, 1);
methodVisitor.visitVarInsn(ILOAD, 2);
methodVisitor.visitInsn(IAND);
methodVisitor.visitVarInsn(ILOAD, 1);
methodVisitor.visitVarInsn(ILOAD, 3);
methodVisitor.visitInsn(IAND);
methodVisitor.visitInsn(IOR);
methodVisitor.visitVarInsn(ILOAD, 2);
methodVisitor.visitVarInsn(ILOAD, 3);
methodVisitor.visitInsn(IAND);
methodVisitor.visitInsn(IOR);
methodVisitor.visitInsn(IRETURN);
methodVisitor.visitMaxs(3, 4);
methodVisitor.visitEnd();
}
{
methodVisitor = classWriter.visitMethod(ACC_PROTECTED, "processBlock", "()V", null, null);
methodVisitor.visitCode();
methodVisitor.visitIntInsn(BIPUSH, 16);
methodVisitor.visitVarInsn(ISTORE, 1);
Label label0 = new Label();
methodVisitor.visitLabel(label0);
methodVisitor.visitVarInsn(ILOAD, 1);
methodVisitor.visitIntInsn(BIPUSH, 80);
Label label1 = new Label();
methodVisitor.visitJumpInsn(IF_ICMPGE, label1);
methodVisitor.visitVarInsn(ALOAD, 0);
methodVisitor.visitFieldInsn(GETFIELD, "org/bouncycastle/crypto/digests/SHA1Digest", "X", "[I");
methodVisitor.visitVarInsn(ILOAD, 1);
methodVisitor.visitInsn(ICONST_3);
methodVisitor.visitInsn(ISUB);
methodVisitor.visitInsn(IALOAD);
methodVisitor.visitVarInsn(ALOAD, 0);
methodVisitor.visitFieldInsn(GETFIELD, "org/bouncycastle/crypto/digests/SHA1Digest", "X", "[I");
methodVisitor.visitVarInsn(ILOAD, 1);
methodVisitor.visitIntInsn(BIPUSH, 8);
methodVisitor.visitInsn(ISUB);
methodVisitor.visitInsn(IALOAD);
methodVisitor.visitInsn(IXOR);
methodVisitor.visitVarInsn(ALOAD, 0);
methodVisitor.visitFieldInsn(GETFIELD, "org/bouncycastle/crypto/digests/SHA1Digest", "X", "[I");
methodVisitor.visitVarInsn(ILOAD, 1);
methodVisitor.visitIntInsn(BIPUSH, 14);
methodVisitor.visitInsn(ISUB);
methodVisitor.visitInsn(IALOAD);
methodVisitor.visitInsn(IXOR);
methodVisitor.visitVarInsn(ALOAD, 0);
methodVisitor.visitFieldInsn(GETFIELD, "org/bouncycastle/crypto/digests/SHA1Digest", "X", "[I");
methodVisitor.visitVarInsn(ILOAD, 1);
methodVisitor.visitIntInsn(BIPUSH, 16);
methodVisitor.visitInsn(ISUB);
methodVisitor.visitInsn(IALOAD);
methodVisitor.visitInsn(IXOR);
methodVisitor.visitVarInsn(ISTORE, 2);
methodVisitor.visitVarInsn(ALOAD, 0);
methodVisitor.visitFieldInsn(GETFIELD, "org/bouncycastle/crypto/digests/SHA1Digest", "X", "[I");
methodVisitor.visitVarInsn(ILOAD, 1);
methodVisitor.visitVarInsn(ILOAD, 2);
methodVisitor.visitInsn(ICONST_1);
methodVisitor.visitInsn(ISHL);
methodVisitor.visitVarInsn(ILOAD, 2);
methodVisitor.visitIntInsn(BIPUSH, 31);
methodVisitor.visitInsn(IUSHR);
methodVisitor.visitInsn(IOR);
methodVisitor.visitInsn(IASTORE);
methodVisitor.visitIincInsn(1, 1);
methodVisitor.visitJumpInsn(GOTO, label0);
methodVisitor.visitLabel(label1);
methodVisitor.visitVarInsn(ALOAD, 0);
methodVisitor.visitFieldInsn(GETFIELD, "org/bouncycastle/crypto/digests/SHA1Digest", "H1", "I");
methodVisitor.visitVarInsn(ISTORE, 1);
methodVisitor.visitVarInsn(ALOAD, 0);
methodVisitor.visitFieldInsn(GETFIELD, "org/bouncycastle/crypto/digests/SHA1Digest", "H2", "I");
methodVisitor.visitVarInsn(ISTORE, 2);
methodVisitor.visitVarInsn(ALOAD, 0);
methodVisitor.visitFieldInsn(GETFIELD, "org/bouncycastle/crypto/digests/SHA1Digest", "H3", "I");
methodVisitor.visitVarInsn(ISTORE, 3);
methodVisitor.visitVarInsn(ALOAD, 0);
methodVisitor.visitFieldInsn(GETFIELD, "org/bouncycastle/crypto/digests/SHA1Digest", "H4", "I");
methodVisitor.visitVarInsn(ISTORE, 4);
methodVisitor.visitVarInsn(ALOAD, 0);
methodVisitor.visitFieldInsn(GETFIELD, "org/bouncycastle/crypto/digests/SHA1Digest", "H5", "I");
methodVisitor.visitVarInsn(ISTORE, 5);
methodVisitor.visitInsn(ICONST_0);
methodVisitor.visitVarInsn(ISTORE, 6);
methodVisitor.visitInsn(ICONST_0);
methodVisitor.visitVarInsn(ISTORE, 7);
Label label2 = new Label();
methodVisitor.visitLabel(label2);
methodVisitor.visitVarInsn(ILOAD, 7);
methodVisitor.visitInsn(ICONST_4);
Label label3 = new Label();
methodVisitor.visitJumpInsn(IF_ICMPGE, label3);
methodVisitor.visitVarInsn(ILOAD, 5);
methodVisitor.visitVarInsn(ILOAD, 1);
methodVisitor.visitInsn(ICONST_5);
methodVisitor.visitInsn(ISHL);
methodVisitor.visitVarInsn(ILOAD, 1);
methodVisitor.visitIntInsn(BIPUSH, 27);
methodVisitor.visitInsn(IUSHR);
methodVisitor.visitInsn(IOR);
methodVisitor.visitVarInsn(ALOAD, 0);
methodVisitor.visitVarInsn(ILOAD, 2);
methodVisitor.visitVarInsn(ILOAD, 3);
methodVisitor.visitVarInsn(ILOAD, 4);
methodVisitor.visitMethodInsn(INVOKESPECIAL, "org/bouncycastle/crypto/digests/SHA1Digest", "f", "(III)I", false);
methodVisitor.visitInsn(IADD);
methodVisitor.visitVarInsn(ALOAD, 0);
methodVisitor.visitFieldInsn(GETFIELD, "org/bouncycastle/crypto/digests/SHA1Digest", "X", "[I");
methodVisitor.visitVarInsn(ILOAD, 6);
methodVisitor.visitIincInsn(6, 1);
methodVisitor.visitInsn(IALOAD);
methodVisitor.visitInsn(IADD);
methodVisitor.visitLdcInsn(new Integer(1518500249));
methodVisitor.visitInsn(IADD);
methodVisitor.visitInsn(IADD);
methodVisitor.visitVarInsn(ISTORE, 5);
methodVisitor.visitVarInsn(ILOAD, 2);
methodVisitor.visitIntInsn(BIPUSH, 30);
methodVisitor.visitInsn(ISHL);
methodVisitor.visitVarInsn(ILOAD, 2);
methodVisitor.visitInsn(ICONST_2);
methodVisitor.visitInsn(IUSHR);
methodVisitor.visitInsn(IOR);
methodVisitor.visitVarInsn(ISTORE, 2);
methodVisitor.visitVarInsn(ILOAD, 4);
methodVisitor.visitVarInsn(ILOAD, 5);
methodVisitor.visitInsn(ICONST_5);
methodVisitor.visitInsn(ISHL);
methodVisitor.visitVarInsn(ILOAD, 5);
methodVisitor.visitIntInsn(BIPUSH, 27);
methodVisitor.visitInsn(IUSHR);
methodVisitor.visitInsn(IOR);
methodVisitor.visitVarInsn(ALOAD, 0);
methodVisitor.visitVarInsn(ILOAD, 1);
methodVisitor.visitVarInsn(ILOAD, 2);
methodVisitor.visitVarInsn(ILOAD, 3);
methodVisitor.visitMethodInsn(INVOKESPECIAL, "org/bouncycastle/crypto/digests/SHA1Digest", "f", "(III)I", false);
methodVisitor.visitInsn(IADD);
methodVisitor.visitVarInsn(ALOAD, 0);
methodVisitor.visitFieldInsn(GETFIELD, "org/bouncycastle/crypto/digests/SHA1Digest", "X", "[I");
methodVisitor.visitVarInsn(ILOAD, 6);
methodVisitor.visitIincInsn(6, 1);
methodVisitor.visitInsn(IALOAD);
methodVisitor.visitInsn(IADD);
methodVisitor.visitLdcInsn(new Integer(1518500249));
methodVisitor.visitInsn(IADD);
methodVisitor.visitInsn(IADD);
methodVisitor.visitVarInsn(ISTORE, 4);
methodVisitor.visitVarInsn(ILOAD, 1);
methodVisitor.visitIntInsn(BIPUSH, 30);
methodVisitor.visitInsn(ISHL);
methodVisitor.visitVarInsn(ILOAD, 1);
methodVisitor.visitInsn(ICONST_2);
methodVisitor.visitInsn(IUSHR);
methodVisitor.visitInsn(IOR);
methodVisitor.visitVarInsn(ISTORE, 1);
methodVisitor.visitVarInsn(ILOAD, 3);
methodVisitor.visitVarInsn(ILOAD, 4);
methodVisitor.visitInsn(ICONST_5);
methodVisitor.visitInsn(ISHL);
methodVisitor.visitVarInsn(ILOAD, 4);
methodVisitor.visitIntInsn(BIPUSH, 27);
methodVisitor.visitInsn(IUSHR);
methodVisitor.visitInsn(IOR);
methodVisitor.visitVarInsn(ALOAD, 0);
methodVisitor.visitVarInsn(ILOAD, 5);
methodVisitor.visitVarInsn(ILOAD, 1);
methodVisitor.visitVarInsn(ILOAD, 2);
methodVisitor.visitMethodInsn(INVOKESPECIAL, "org/bouncycastle/crypto/digests/SHA1Digest", "f", "(III)I", false);
methodVisitor.visitInsn(IADD);
methodVisitor.visitVarInsn(ALOAD, 0);
methodVisitor.visitFieldInsn(GETFIELD, "org/bouncycastle/crypto/digests/SHA1Digest", "X", "[I");
methodVisitor.visitVarInsn(ILOAD, 6);
methodVisitor.visitIincInsn(6, 1);
methodVisitor.visitInsn(IALOAD);
methodVisitor.visitInsn(IADD);
methodVisitor.visitLdcInsn(new Integer(1518500249));
methodVisitor.visitInsn(IADD);
methodVisitor.visitInsn(IADD);
methodVisitor.visitVarInsn(ISTORE, 3);
methodVisitor.visitVarInsn(ILOAD, 5);
methodVisitor.visitIntInsn(BIPUSH, 30);
methodVisitor.visitInsn(ISHL);
methodVisitor.visitVarInsn(ILOAD, 5);
methodVisitor.visitInsn(ICONST_2);
methodVisitor.visitInsn(IUSHR);
methodVisitor.visitInsn(IOR);
methodVisitor.visitVarInsn(ISTORE, 5);
methodVisitor.visitVarInsn(ILOAD, 2);
methodVisitor.visitVarInsn(ILOAD, 3);
methodVisitor.visitInsn(ICONST_5);
methodVisitor.visitInsn(ISHL);
methodVisitor.visitVarInsn(ILOAD, 3);
methodVisitor.visitIntInsn(BIPUSH, 27);
methodVisitor.visitInsn(IUSHR);
methodVisitor.visitInsn(IOR);
methodVisitor.visitVarInsn(ALOAD, 0);
methodVisitor.visitVarInsn(ILOAD, 4);
methodVisitor.visitVarInsn(ILOAD, 5);
methodVisitor.visitVarInsn(ILOAD, 1);
methodVisitor.visitMethodInsn(INVOKESPECIAL, "org/bouncycastle/crypto/digests/SHA1Digest", "f", "(III)I", false);
methodVisitor.visitInsn(IADD);
methodVisitor.visitVarInsn(ALOAD, 0);
methodVisitor.visitFieldInsn(GETFIELD, "org/bouncycastle/crypto/digests/SHA1Digest", "X", "[I");
methodVisitor.visitVarInsn(ILOAD, 6);
methodVisitor.visitIincInsn(6, 1);
methodVisitor.visitInsn(IALOAD);
methodVisitor.visitInsn(IADD);
methodVisitor.visitLdcInsn(new Integer(1518500249));
methodVisitor.visitInsn(IADD);
methodVisitor.visitInsn(IADD);
methodVisitor.visitVarInsn(ISTORE, 2);
methodVisitor.visitVarInsn(ILOAD, 4);
methodVisitor.visitIntInsn(BIPUSH, 30);
methodVisitor.visitInsn(ISHL);
methodVisitor.visitVarInsn(ILOAD, 4);
methodVisitor.visitInsn(ICONST_2);
methodVisitor.visitInsn(IUSHR);
methodVisitor.visitInsn(IOR);
methodVisitor.visitVarInsn(ISTORE, 4);
methodVisitor.visitVarInsn(ILOAD, 1);
methodVisitor.visitVarInsn(ILOAD, 2);
methodVisitor.visitInsn(ICONST_5);
methodVisitor.visitInsn(ISHL);
methodVisitor.visitVarInsn(ILOAD, 2);
methodVisitor.visitIntInsn(BIPUSH, 27);
methodVisitor.visitInsn(IUSHR);
methodVisitor.visitInsn(IOR);
methodVisitor.visitVarInsn(ALOAD, 0);
methodVisitor.visitVarInsn(ILOAD, 3);
methodVisitor.visitVarInsn(ILOAD, 4);
methodVisitor.visitVarInsn(ILOAD, 5);
methodVisitor.visitMethodInsn(INVOKESPECIAL, "org/bouncycastle/crypto/digests/SHA1Digest", "f", "(III)I", false);
methodVisitor.visitInsn(IADD);
methodVisitor.visitVarInsn(ALOAD, 0);
methodVisitor.visitFieldInsn(GETFIELD, "org/bouncycastle/crypto/digests/SHA1Digest", "X", "[I");
methodVisitor.visitVarInsn(ILOAD, 6);
methodVisitor.visitIincInsn(6, 1);
methodVisitor.visitInsn(IALOAD);
methodVisitor.visitInsn(IADD);
methodVisitor.visitLdcInsn(new Integer(1518500249));
methodVisitor.visitInsn(IADD);
methodVisitor.visitInsn(IADD);
methodVisitor.visitVarInsn(ISTORE, 1);
methodVisitor.visitVarInsn(ILOAD, 3);
methodVisitor.visitIntInsn(BIPUSH, 30);
methodVisitor.visitInsn(ISHL);
methodVisitor.visitVarInsn(ILOAD, 3);
methodVisitor.visitInsn(ICONST_2);
methodVisitor.visitInsn(IUSHR);
methodVisitor.visitInsn(IOR);
methodVisitor.visitVarInsn(ISTORE, 3);
methodVisitor.visitIincInsn(7, 1);
methodVisitor.visitJumpInsn(GOTO, label2);
methodVisitor.visitLabel(label3);
methodVisitor.visitInsn(ICONST_0);
methodVisitor.visitVarInsn(ISTORE, 7);
Label label4 = new Label();
methodVisitor.visitLabel(label4);
methodVisitor.visitVarInsn(ILOAD, 7);
methodVisitor.visitInsn(ICONST_4);
Label label5 = new Label();
methodVisitor.visitJumpInsn(IF_ICMPGE, label5);
methodVisitor.visitVarInsn(ILOAD, 5);
methodVisitor.visitVarInsn(ILOAD, 1);
methodVisitor.visitInsn(ICONST_5);
methodVisitor.visitInsn(ISHL);
methodVisitor.visitVarInsn(ILOAD, 1);
methodVisitor.visitIntInsn(BIPUSH, 27);
methodVisitor.visitInsn(IUSHR);
methodVisitor.visitInsn(IOR);
methodVisitor.visitVarInsn(ALOAD, 0);
methodVisitor.visitVarInsn(ILOAD, 2);
methodVisitor.visitVarInsn(ILOAD, 3);
methodVisitor.visitVarInsn(ILOAD, 4);
methodVisitor.visitMethodInsn(INVOKESPECIAL, "org/bouncycastle/crypto/digests/SHA1Digest", "h", "(III)I", false);
methodVisitor.visitInsn(IADD);
methodVisitor.visitVarInsn(ALOAD, 0);
methodVisitor.visitFieldInsn(GETFIELD, "org/bouncycastle/crypto/digests/SHA1Digest", "X", "[I");
methodVisitor.visitVarInsn(ILOAD, 6);
methodVisitor.visitIincInsn(6, 1);
methodVisitor.visitInsn(IALOAD);
methodVisitor.visitInsn(IADD);
methodVisitor.visitLdcInsn(new Integer(1859775393));
methodVisitor.visitInsn(IADD);
methodVisitor.visitInsn(IADD);
methodVisitor.visitVarInsn(ISTORE, 5);
methodVisitor.visitVarInsn(ILOAD, 2);
methodVisitor.visitIntInsn(BIPUSH, 30);
methodVisitor.visitInsn(ISHL);
methodVisitor.visitVarInsn(ILOAD, 2);
methodVisitor.visitInsn(ICONST_2);
methodVisitor.visitInsn(IUSHR);
methodVisitor.visitInsn(IOR);
methodVisitor.visitVarInsn(ISTORE, 2);
methodVisitor.visitVarInsn(ILOAD, 4);
methodVisitor.visitVarInsn(ILOAD, 5);
methodVisitor.visitInsn(ICONST_5);
methodVisitor.visitInsn(ISHL);
methodVisitor.visitVarInsn(ILOAD, 5);
methodVisitor.visitIntInsn(BIPUSH, 27);
methodVisitor.visitInsn(IUSHR);
methodVisitor.visitInsn(IOR);
methodVisitor.visitVarInsn(ALOAD, 0);
methodVisitor.visitVarInsn(ILOAD, 1);
methodVisitor.visitVarInsn(ILOAD, 2);
methodVisitor.visitVarInsn(ILOAD, 3);
methodVisitor.visitMethodInsn(INVOKESPECIAL, "org/bouncycastle/crypto/digests/SHA1Digest", "h", "(III)I", false);
methodVisitor.visitInsn(IADD);
methodVisitor.visitVarInsn(ALOAD, 0);
methodVisitor.visitFieldInsn(GETFIELD, "org/bouncycastle/crypto/digests/SHA1Digest", "X", "[I");
methodVisitor.visitVarInsn(ILOAD, 6);
methodVisitor.visitIincInsn(6, 1);
methodVisitor.visitInsn(IALOAD);
methodVisitor.visitInsn(IADD);
methodVisitor.visitLdcInsn(new Integer(1859775393));
methodVisitor.visitInsn(IADD);
methodVisitor.visitInsn(IADD);
methodVisitor.visitVarInsn(ISTORE, 4);
methodVisitor.visitVarInsn(ILOAD, 1);
methodVisitor.visitIntInsn(BIPUSH, 30);
methodVisitor.visitInsn(ISHL);
methodVisitor.visitVarInsn(ILOAD, 1);
methodVisitor.visitInsn(ICONST_2);
methodVisitor.visitInsn(IUSHR);
methodVisitor.visitInsn(IOR);
methodVisitor.visitVarInsn(ISTORE, 1);
methodVisitor.visitVarInsn(ILOAD, 3);
methodVisitor.visitVarInsn(ILOAD, 4);
methodVisitor.visitInsn(ICONST_5);
methodVisitor.visitInsn(ISHL);
methodVisitor.visitVarInsn(ILOAD, 4);
methodVisitor.visitIntInsn(BIPUSH, 27);
methodVisitor.visitInsn(IUSHR);
methodVisitor.visitInsn(IOR);
methodVisitor.visitVarInsn(ALOAD, 0);
methodVisitor.visitVarInsn(ILOAD, 5);
methodVisitor.visitVarInsn(ILOAD, 1);
methodVisitor.visitVarInsn(ILOAD, 2);
methodVisitor.visitMethodInsn(INVOKESPECIAL, "org/bouncycastle/crypto/digests/SHA1Digest", "h", "(III)I", false);
methodVisitor.visitInsn(IADD);
methodVisitor.visitVarInsn(ALOAD, 0);
methodVisitor.visitFieldInsn(GETFIELD, "org/bouncycastle/crypto/digests/SHA1Digest", "X", "[I");
methodVisitor.visitVarInsn(ILOAD, 6);
methodVisitor.visitIincInsn(6, 1);
methodVisitor.visitInsn(IALOAD);
methodVisitor.visitInsn(IADD);
methodVisitor.visitLdcInsn(new Integer(1859775393));
methodVisitor.visitInsn(IADD);
methodVisitor.visitInsn(IADD);
methodVisitor.visitVarInsn(ISTORE, 3);
methodVisitor.visitVarInsn(ILOAD, 5);
methodVisitor.visitIntInsn(BIPUSH, 30);
methodVisitor.visitInsn(ISHL);
methodVisitor.visitVarInsn(ILOAD, 5);
methodVisitor.visitInsn(ICONST_2);
methodVisitor.visitInsn(IUSHR);
methodVisitor.visitInsn(IOR);
methodVisitor.visitVarInsn(ISTORE, 5);
methodVisitor.visitVarInsn(ILOAD, 2);
methodVisitor.visitVarInsn(ILOAD, 3);
methodVisitor.visitInsn(ICONST_5);
methodVisitor.visitInsn(ISHL);
methodVisitor.visitVarInsn(ILOAD, 3);
methodVisitor.visitIntInsn(BIPUSH, 27);
methodVisitor.visitInsn(IUSHR);
methodVisitor.visitInsn(IOR);
methodVisitor.visitVarInsn(ALOAD, 0);
methodVisitor.visitVarInsn(ILOAD, 4);
methodVisitor.visitVarInsn(ILOAD, 5);
methodVisitor.visitVarInsn(ILOAD, 1);
methodVisitor.visitMethodInsn(INVOKESPECIAL, "org/bouncycastle/crypto/digests/SHA1Digest", "h", "(III)I", false);
methodVisitor.visitInsn(IADD);
methodVisitor.visitVarInsn(ALOAD, 0);
methodVisitor.visitFieldInsn(GETFIELD, "org/bouncycastle/crypto/digests/SHA1Digest", "X", "[I");
methodVisitor.visitVarInsn(ILOAD, 6);
methodVisitor.visitIincInsn(6, 1);
methodVisitor.visitInsn(IALOAD);
methodVisitor.visitInsn(IADD);
methodVisitor.visitLdcInsn(new Integer(1859775393));
methodVisitor.visitInsn(IADD);
methodVisitor.visitInsn(IADD);
methodVisitor.visitVarInsn(ISTORE, 2);
methodVisitor.visitVarInsn(ILOAD, 4);
methodVisitor.visitIntInsn(BIPUSH, 30);
methodVisitor.visitInsn(ISHL);
methodVisitor.visitVarInsn(ILOAD, 4);
methodVisitor.visitInsn(ICONST_2);
methodVisitor.visitInsn(IUSHR);
methodVisitor.visitInsn(IOR);
methodVisitor.visitVarInsn(ISTORE, 4);
methodVisitor.visitVarInsn(ILOAD, 1);
methodVisitor.visitVarInsn(ILOAD, 2);
methodVisitor.visitInsn(ICONST_5);
methodVisitor.visitInsn(ISHL);
methodVisitor.visitVarInsn(ILOAD, 2);
methodVisitor.visitIntInsn(BIPUSH, 27);
methodVisitor.visitInsn(IUSHR);
methodVisitor.visitInsn(IOR);
methodVisitor.visitVarInsn(ALOAD, 0);
methodVisitor.visitVarInsn(ILOAD, 3);
methodVisitor.visitVarInsn(ILOAD, 4);
methodVisitor.visitVarInsn(ILOAD, 5);
methodVisitor.visitMethodInsn(INVOKESPECIAL, "org/bouncycastle/crypto/digests/SHA1Digest", "h", "(III)I", false);
methodVisitor.visitInsn(IADD);
methodVisitor.visitVarInsn(ALOAD, 0);
methodVisitor.visitFieldInsn(GETFIELD, "org/bouncycastle/crypto/digests/SHA1Digest", "X", "[I");
methodVisitor.visitVarInsn(ILOAD, 6);
methodVisitor.visitIincInsn(6, 1);
methodVisitor.visitInsn(IALOAD);
methodVisitor.visitInsn(IADD);
methodVisitor.visitLdcInsn(new Integer(1859775393));
methodVisitor.visitInsn(IADD);
methodVisitor.visitInsn(IADD);
methodVisitor.visitVarInsn(ISTORE, 1);
methodVisitor.visitVarInsn(ILOAD, 3);
methodVisitor.visitIntInsn(BIPUSH, 30);
methodVisitor.visitInsn(ISHL);
methodVisitor.visitVarInsn(ILOAD, 3);
methodVisitor.visitInsn(ICONST_2);
methodVisitor.visitInsn(IUSHR);
methodVisitor.visitInsn(IOR);
methodVisitor.visitVarInsn(ISTORE, 3);
methodVisitor.visitIincInsn(7, 1);
methodVisitor.visitJumpInsn(GOTO, label4);
methodVisitor.visitLabel(label5);
methodVisitor.visitInsn(ICONST_0);
methodVisitor.visitVarInsn(ISTORE, 7);
Label label6 = new Label();
methodVisitor.visitLabel(label6);
methodVisitor.visitVarInsn(ILOAD, 7);
methodVisitor.visitInsn(ICONST_4);
Label label7 = new Label();
methodVisitor.visitJumpInsn(IF_ICMPGE, label7);
methodVisitor.visitVarInsn(ILOAD, 5);
methodVisitor.visitVarInsn(ILOAD, 1);
methodVisitor.visitInsn(ICONST_5);
methodVisitor.visitInsn(ISHL);
methodVisitor.visitVarInsn(ILOAD, 1);
methodVisitor.visitIntInsn(BIPUSH, 27);
methodVisitor.visitInsn(IUSHR);
methodVisitor.visitInsn(IOR);
methodVisitor.visitVarInsn(ALOAD, 0);
methodVisitor.visitVarInsn(ILOAD, 2);
methodVisitor.visitVarInsn(ILOAD, 3);
methodVisitor.visitVarInsn(ILOAD, 4);
methodVisitor.visitMethodInsn(INVOKESPECIAL, "org/bouncycastle/crypto/digests/SHA1Digest", "g", "(III)I", false);
methodVisitor.visitInsn(IADD);
methodVisitor.visitVarInsn(ALOAD, 0);
methodVisitor.visitFieldInsn(GETFIELD, "org/bouncycastle/crypto/digests/SHA1Digest", "X", "[I");
methodVisitor.visitVarInsn(ILOAD, 6);
methodVisitor.visitIincInsn(6, 1);
methodVisitor.visitInsn(IALOAD);
methodVisitor.visitInsn(IADD);
methodVisitor.visitLdcInsn(new Integer(-1894007588));
methodVisitor.visitInsn(IADD);
methodVisitor.visitInsn(IADD);
methodVisitor.visitVarInsn(ISTORE, 5);
methodVisitor.visitVarInsn(ILOAD, 2);
methodVisitor.visitIntInsn(BIPUSH, 30);
methodVisitor.visitInsn(ISHL);
methodVisitor.visitVarInsn(ILOAD, 2);
methodVisitor.visitInsn(ICONST_2);
methodVisitor.visitInsn(IUSHR);
methodVisitor.visitInsn(IOR);
methodVisitor.visitVarInsn(ISTORE, 2);
methodVisitor.visitVarInsn(ILOAD, 4);
methodVisitor.visitVarInsn(ILOAD, 5);
methodVisitor.visitInsn(ICONST_5);
methodVisitor.visitInsn(ISHL);
methodVisitor.visitVarInsn(ILOAD, 5);
methodVisitor.visitIntInsn(BIPUSH, 27);
methodVisitor.visitInsn(IUSHR);
methodVisitor.visitInsn(IOR);
methodVisitor.visitVarInsn(ALOAD, 0);
methodVisitor.visitVarInsn(ILOAD, 1);
methodVisitor.visitVarInsn(ILOAD, 2);
methodVisitor.visitVarInsn(ILOAD, 3);
methodVisitor.visitMethodInsn(INVOKESPECIAL, "org/bouncycastle/crypto/digests/SHA1Digest", "g", "(III)I", false);
methodVisitor.visitInsn(IADD);
methodVisitor.visitVarInsn(ALOAD, 0);
methodVisitor.visitFieldInsn(GETFIELD, "org/bouncycastle/crypto/digests/SHA1Digest", "X", "[I");
methodVisitor.visitVarInsn(ILOAD, 6);
methodVisitor.visitIincInsn(6, 1);
methodVisitor.visitInsn(IALOAD);
methodVisitor.visitInsn(IADD);
methodVisitor.visitLdcInsn(new Integer(-1894007588));
methodVisitor.visitInsn(IADD);
methodVisitor.visitInsn(IADD);
methodVisitor.visitVarInsn(ISTORE, 4);
methodVisitor.visitVarInsn(ILOAD, 1);
methodVisitor.visitIntInsn(BIPUSH, 30);
methodVisitor.visitInsn(ISHL);
methodVisitor.visitVarInsn(ILOAD, 1);
methodVisitor.visitInsn(ICONST_2);
methodVisitor.visitInsn(IUSHR);
methodVisitor.visitInsn(IOR);
methodVisitor.visitVarInsn(ISTORE, 1);
methodVisitor.visitVarInsn(ILOAD, 3);
methodVisitor.visitVarInsn(ILOAD, 4);
methodVisitor.visitInsn(ICONST_5);
methodVisitor.visitInsn(ISHL);
methodVisitor.visitVarInsn(ILOAD, 4);
methodVisitor.visitIntInsn(BIPUSH, 27);
methodVisitor.visitInsn(IUSHR);
methodVisitor.visitInsn(IOR);
methodVisitor.visitVarInsn(ALOAD, 0);
methodVisitor.visitVarInsn(ILOAD, 5);
methodVisitor.visitVarInsn(ILOAD, 1);
methodVisitor.visitVarInsn(ILOAD, 2);
methodVisitor.visitMethodInsn(INVOKESPECIAL, "org/bouncycastle/crypto/digests/SHA1Digest", "g", "(III)I", false);
methodVisitor.visitInsn(IADD);
methodVisitor.visitVarInsn(ALOAD, 0);
methodVisitor.visitFieldInsn(GETFIELD, "org/bouncycastle/crypto/digests/SHA1Digest", "X", "[I");
methodVisitor.visitVarInsn(ILOAD, 6);
methodVisitor.visitIincInsn(6, 1);
methodVisitor.visitInsn(IALOAD);
methodVisitor.visitInsn(IADD);
methodVisitor.visitLdcInsn(new Integer(-1894007588));
methodVisitor.visitInsn(IADD);
methodVisitor.visitInsn(IADD);
methodVisitor.visitVarInsn(ISTORE, 3);
methodVisitor.visitVarInsn(ILOAD, 5);
methodVisitor.visitIntInsn(BIPUSH, 30);
methodVisitor.visitInsn(ISHL);
methodVisitor.visitVarInsn(ILOAD, 5);
methodVisitor.visitInsn(ICONST_2);
methodVisitor.visitInsn(IUSHR);
methodVisitor.visitInsn(IOR);
methodVisitor.visitVarInsn(ISTORE, 5);
methodVisitor.visitVarInsn(ILOAD, 2);
methodVisitor.visitVarInsn(ILOAD, 3);
methodVisitor.visitInsn(ICONST_5);
methodVisitor.visitInsn(ISHL);
methodVisitor.visitVarInsn(ILOAD, 3);
methodVisitor.visitIntInsn(BIPUSH, 27);
methodVisitor.visitInsn(IUSHR);
methodVisitor.visitInsn(IOR);
methodVisitor.visitVarInsn(ALOAD, 0);
methodVisitor.visitVarInsn(ILOAD, 4);
methodVisitor.visitVarInsn(ILOAD, 5);
methodVisitor.visitVarInsn(ILOAD, 1);
methodVisitor.visitMethodInsn(INVOKESPECIAL, "org/bouncycastle/crypto/digests/SHA1Digest", "g", "(III)I", false);
methodVisitor.visitInsn(IADD);
methodVisitor.visitVarInsn(ALOAD, 0);
methodVisitor.visitFieldInsn(GETFIELD, "org/bouncycastle/crypto/digests/SHA1Digest", "X", "[I");
methodVisitor.visitVarInsn(ILOAD, 6);
methodVisitor.visitIincInsn(6, 1);
methodVisitor.visitInsn(IALOAD);
methodVisitor.visitInsn(IADD);
methodVisitor.visitLdcInsn(new Integer(-1894007588));
methodVisitor.visitInsn(IADD);
methodVisitor.visitInsn(IADD);
methodVisitor.visitVarInsn(ISTORE, 2);
methodVisitor.visitVarInsn(ILOAD, 4);
methodVisitor.visitIntInsn(BIPUSH, 30);
methodVisitor.visitInsn(ISHL);
methodVisitor.visitVarInsn(ILOAD, 4);
methodVisitor.visitInsn(ICONST_2);
methodVisitor.visitInsn(IUSHR);
methodVisitor.visitInsn(IOR);
methodVisitor.visitVarInsn(ISTORE, 4);
methodVisitor.visitVarInsn(ILOAD, 1);
methodVisitor.visitVarInsn(ILOAD, 2);
methodVisitor.visitInsn(ICONST_5);
methodVisitor.visitInsn(ISHL);
methodVisitor.visitVarInsn(ILOAD, 2);
methodVisitor.visitIntInsn(BIPUSH, 27);
methodVisitor.visitInsn(IUSHR);
methodVisitor.visitInsn(IOR);
methodVisitor.visitVarInsn(ALOAD, 0);
methodVisitor.visitVarInsn(ILOAD, 3);
methodVisitor.visitVarInsn(ILOAD, 4);
methodVisitor.visitVarInsn(ILOAD, 5);
methodVisitor.visitMethodInsn(INVOKESPECIAL, "org/bouncycastle/crypto/digests/SHA1Digest", "g", "(III)I", false);
methodVisitor.visitInsn(IADD);
methodVisitor.visitVarInsn(ALOAD, 0);
methodVisitor.visitFieldInsn(GETFIELD, "org/bouncycastle/crypto/digests/SHA1Digest", "X", "[I");
methodVisitor.visitVarInsn(ILOAD, 6);
methodVisitor.visitIincInsn(6, 1);
methodVisitor.visitInsn(IALOAD);
methodVisitor.visitInsn(IADD);
methodVisitor.visitLdcInsn(new Integer(-1894007588));
methodVisitor.visitInsn(IADD);
methodVisitor.visitInsn(IADD);
methodVisitor.visitVarInsn(ISTORE, 1);
methodVisitor.visitVarInsn(ILOAD, 3);
methodVisitor.visitIntInsn(BIPUSH, 30);
methodVisitor.visitInsn(ISHL);
methodVisitor.visitVarInsn(ILOAD, 3);
methodVisitor.visitInsn(ICONST_2);
methodVisitor.visitInsn(IUSHR);
methodVisitor.visitInsn(IOR);
methodVisitor.visitVarInsn(ISTORE, 3);
methodVisitor.visitIincInsn(7, 1);
methodVisitor.visitJumpInsn(GOTO, label6);
methodVisitor.visitLabel(label7);
methodVisitor.visitInsn(ICONST_0);
methodVisitor.visitVarInsn(ISTORE, 7);
Label label8 = new Label();
methodVisitor.visitLabel(label8);
methodVisitor.visitVarInsn(ILOAD, 7);
methodVisitor.visitInsn(ICONST_3);
Label label9 = new Label();
methodVisitor.visitJumpInsn(IF_ICMPGT, label9);
methodVisitor.visitVarInsn(ILOAD, 5);
methodVisitor.visitVarInsn(ILOAD, 1);
methodVisitor.visitInsn(ICONST_5);
methodVisitor.visitInsn(ISHL);
methodVisitor.visitVarInsn(ILOAD, 1);
methodVisitor.visitIntInsn(BIPUSH, 27);
methodVisitor.visitInsn(IUSHR);
methodVisitor.visitInsn(IOR);
methodVisitor.visitVarInsn(ALOAD, 0);
methodVisitor.visitVarInsn(ILOAD, 2);
methodVisitor.visitVarInsn(ILOAD, 3);
methodVisitor.visitVarInsn(ILOAD, 4);
methodVisitor.visitMethodInsn(INVOKESPECIAL, "org/bouncycastle/crypto/digests/SHA1Digest", "h", "(III)I", false);
methodVisitor.visitInsn(IADD);
methodVisitor.visitVarInsn(ALOAD, 0);
methodVisitor.visitFieldInsn(GETFIELD, "org/bouncycastle/crypto/digests/SHA1Digest", "X", "[I");
methodVisitor.visitVarInsn(ILOAD, 6);
methodVisitor.visitIincInsn(6, 1);
methodVisitor.visitInsn(IALOAD);
methodVisitor.visitInsn(IADD);
methodVisitor.visitLdcInsn(new Integer(-899497514));
methodVisitor.visitInsn(IADD);
methodVisitor.visitInsn(IADD);
methodVisitor.visitVarInsn(ISTORE, 5);
methodVisitor.visitVarInsn(ILOAD, 2);
methodVisitor.visitIntInsn(BIPUSH, 30);
methodVisitor.visitInsn(ISHL);
methodVisitor.visitVarInsn(ILOAD, 2);
methodVisitor.visitInsn(ICONST_2);
methodVisitor.visitInsn(IUSHR);
methodVisitor.visitInsn(IOR);
methodVisitor.visitVarInsn(ISTORE, 2);
methodVisitor.visitVarInsn(ILOAD, 4);
methodVisitor.visitVarInsn(ILOAD, 5);
methodVisitor.visitInsn(ICONST_5);
methodVisitor.visitInsn(ISHL);
methodVisitor.visitVarInsn(ILOAD, 5);
methodVisitor.visitIntInsn(BIPUSH, 27);
methodVisitor.visitInsn(IUSHR);
methodVisitor.visitInsn(IOR);
methodVisitor.visitVarInsn(ALOAD, 0);
methodVisitor.visitVarInsn(ILOAD, 1);
methodVisitor.visitVarInsn(ILOAD, 2);
methodVisitor.visitVarInsn(ILOAD, 3);
methodVisitor.visitMethodInsn(INVOKESPECIAL, "org/bouncycastle/crypto/digests/SHA1Digest", "h", "(III)I", false);
methodVisitor.visitInsn(IADD);
methodVisitor.visitVarInsn(ALOAD, 0);
methodVisitor.visitFieldInsn(GETFIELD, "org/bouncycastle/crypto/digests/SHA1Digest", "X", "[I");
methodVisitor.visitVarInsn(ILOAD, 6);
methodVisitor.visitIincInsn(6, 1);
methodVisitor.visitInsn(IALOAD);
methodVisitor.visitInsn(IADD);
methodVisitor.visitLdcInsn(new Integer(-899497514));
methodVisitor.visitInsn(IADD);
methodVisitor.visitInsn(IADD);
methodVisitor.visitVarInsn(ISTORE, 4);
methodVisitor.visitVarInsn(ILOAD, 1);
methodVisitor.visitIntInsn(BIPUSH, 30);
methodVisitor.visitInsn(ISHL);
methodVisitor.visitVarInsn(ILOAD, 1);
methodVisitor.visitInsn(ICONST_2);
methodVisitor.visitInsn(IUSHR);
methodVisitor.visitInsn(IOR);
methodVisitor.visitVarInsn(ISTORE, 1);
methodVisitor.visitVarInsn(ILOAD, 3);
methodVisitor.visitVarInsn(ILOAD, 4);
methodVisitor.visitInsn(ICONST_5);
methodVisitor.visitInsn(ISHL);
methodVisitor.visitVarInsn(ILOAD, 4);
methodVisitor.visitIntInsn(BIPUSH, 27);
methodVisitor.visitInsn(IUSHR);
methodVisitor.visitInsn(IOR);
methodVisitor.visitVarInsn(ALOAD, 0);
methodVisitor.visitVarInsn(ILOAD, 5);
methodVisitor.visitVarInsn(ILOAD, 1);
methodVisitor.visitVarInsn(ILOAD, 2);
methodVisitor.visitMethodInsn(INVOKESPECIAL, "org/bouncycastle/crypto/digests/SHA1Digest", "h", "(III)I", false);
methodVisitor.visitInsn(IADD);
methodVisitor.visitVarInsn(ALOAD, 0);
methodVisitor.visitFieldInsn(GETFIELD, "org/bouncycastle/crypto/digests/SHA1Digest", "X", "[I");
methodVisitor.visitVarInsn(ILOAD, 6);
methodVisitor.visitIincInsn(6, 1);
methodVisitor.visitInsn(IALOAD);
methodVisitor.visitInsn(IADD);
methodVisitor.visitLdcInsn(new Integer(-899497514));
methodVisitor.visitInsn(IADD);
methodVisitor.visitInsn(IADD);
methodVisitor.visitVarInsn(ISTORE, 3);
methodVisitor.visitVarInsn(ILOAD, 5);
methodVisitor.visitIntInsn(BIPUSH, 30);
methodVisitor.visitInsn(ISHL);
methodVisitor.visitVarInsn(ILOAD, 5);
methodVisitor.visitInsn(ICONST_2);
methodVisitor.visitInsn(IUSHR);
methodVisitor.visitInsn(IOR);
methodVisitor.visitVarInsn(ISTORE, 5);
methodVisitor.visitVarInsn(ILOAD, 2);
methodVisitor.visitVarInsn(ILOAD, 3);
methodVisitor.visitInsn(ICONST_5);
methodVisitor.visitInsn(ISHL);
methodVisitor.visitVarInsn(ILOAD, 3);
methodVisitor.visitIntInsn(BIPUSH, 27);
methodVisitor.visitInsn(IUSHR);
methodVisitor.visitInsn(IOR);
methodVisitor.visitVarInsn(ALOAD, 0);
methodVisitor.visitVarInsn(ILOAD, 4);
methodVisitor.visitVarInsn(ILOAD, 5);
methodVisitor.visitVarInsn(ILOAD, 1);
methodVisitor.visitMethodInsn(INVOKESPECIAL, "org/bouncycastle/crypto/digests/SHA1Digest", "h", "(III)I", false);
methodVisitor.visitInsn(IADD);
methodVisitor.visitVarInsn(ALOAD, 0);
methodVisitor.visitFieldInsn(GETFIELD, "org/bouncycastle/crypto/digests/SHA1Digest", "X", "[I");
methodVisitor.visitVarInsn(ILOAD, 6);
methodVisitor.visitIincInsn(6, 1);
methodVisitor.visitInsn(IALOAD);
methodVisitor.visitInsn(IADD);
methodVisitor.visitLdcInsn(new Integer(-899497514));
methodVisitor.visitInsn(IADD);
methodVisitor.visitInsn(IADD);
methodVisitor.visitVarInsn(ISTORE, 2);
methodVisitor.visitVarInsn(ILOAD, 4);
methodVisitor.visitIntInsn(BIPUSH, 30);
methodVisitor.visitInsn(ISHL);
methodVisitor.visitVarInsn(ILOAD, 4);
methodVisitor.visitInsn(ICONST_2);
methodVisitor.visitInsn(IUSHR);
methodVisitor.visitInsn(IOR);
methodVisitor.visitVarInsn(ISTORE, 4);
methodVisitor.visitVarInsn(ILOAD, 1);
methodVisitor.visitVarInsn(ILOAD, 2);
methodVisitor.visitInsn(ICONST_5);
methodVisitor.visitInsn(ISHL);
methodVisitor.visitVarInsn(ILOAD, 2);
methodVisitor.visitIntInsn(BIPUSH, 27);
methodVisitor.visitInsn(IUSHR);
methodVisitor.visitInsn(IOR);
methodVisitor.visitVarInsn(ALOAD, 0);
methodVisitor.visitVarInsn(ILOAD, 3);
methodVisitor.visitVarInsn(ILOAD, 4);
methodVisitor.visitVarInsn(ILOAD, 5);
methodVisitor.visitMethodInsn(INVOKESPECIAL, "org/bouncycastle/crypto/digests/SHA1Digest", "h", "(III)I", false);
methodVisitor.visitInsn(IADD);
methodVisitor.visitVarInsn(ALOAD, 0);
methodVisitor.visitFieldInsn(GETFIELD, "org/bouncycastle/crypto/digests/SHA1Digest", "X", "[I");
methodVisitor.visitVarInsn(ILOAD, 6);
methodVisitor.visitIincInsn(6, 1);
methodVisitor.visitInsn(IALOAD);
methodVisitor.visitInsn(IADD);
methodVisitor.visitLdcInsn(new Integer(-899497514));
methodVisitor.visitInsn(IADD);
methodVisitor.visitInsn(IADD);
methodVisitor.visitVarInsn(ISTORE, 1);
methodVisitor.visitVarInsn(ILOAD, 3);
methodVisitor.visitIntInsn(BIPUSH, 30);
methodVisitor.visitInsn(ISHL);
methodVisitor.visitVarInsn(ILOAD, 3);
methodVisitor.visitInsn(ICONST_2);
methodVisitor.visitInsn(IUSHR);
methodVisitor.visitInsn(IOR);
methodVisitor.visitVarInsn(ISTORE, 3);
methodVisitor.visitIincInsn(7, 1);
methodVisitor.visitJumpInsn(GOTO, label8);
methodVisitor.visitLabel(label9);
methodVisitor.visitVarInsn(ALOAD, 0);
methodVisitor.visitInsn(DUP);
methodVisitor.visitFieldInsn(GETFIELD, "org/bouncycastle/crypto/digests/SHA1Digest", "H1", "I");
methodVisitor.visitVarInsn(ILOAD, 1);
methodVisitor.visitInsn(IADD);
methodVisitor.visitFieldInsn(PUTFIELD, "org/bouncycastle/crypto/digests/SHA1Digest", "H1", "I");
methodVisitor.visitVarInsn(ALOAD, 0);
methodVisitor.visitInsn(DUP);
methodVisitor.visitFieldInsn(GETFIELD, "org/bouncycastle/crypto/digests/SHA1Digest", "H2", "I");
methodVisitor.visitVarInsn(ILOAD, 2);
methodVisitor.visitInsn(IADD);
methodVisitor.visitFieldInsn(PUTFIELD, "org/bouncycastle/crypto/digests/SHA1Digest", "H2", "I");
methodVisitor.visitVarInsn(ALOAD, 0);
methodVisitor.visitInsn(DUP);
methodVisitor.visitFieldInsn(GETFIELD, "org/bouncycastle/crypto/digests/SHA1Digest", "H3", "I");
methodVisitor.visitVarInsn(ILOAD, 3);
methodVisitor.visitInsn(IADD);
methodVisitor.visitFieldInsn(PUTFIELD, "org/bouncycastle/crypto/digests/SHA1Digest", "H3", "I");
methodVisitor.visitVarInsn(ALOAD, 0);
methodVisitor.visitInsn(DUP);
methodVisitor.visitFieldInsn(GETFIELD, "org/bouncycastle/crypto/digests/SHA1Digest", "H4", "I");
methodVisitor.visitVarInsn(ILOAD, 4);
methodVisitor.visitInsn(IADD);
methodVisitor.visitFieldInsn(PUTFIELD, "org/bouncycastle/crypto/digests/SHA1Digest", "H4", "I");
methodVisitor.visitVarInsn(ALOAD, 0);
methodVisitor.visitInsn(DUP);
methodVisitor.visitFieldInsn(GETFIELD, "org/bouncycastle/crypto/digests/SHA1Digest", "H5", "I");
methodVisitor.visitVarInsn(ILOAD, 5);
methodVisitor.visitInsn(IADD);
methodVisitor.visitFieldInsn(PUTFIELD, "org/bouncycastle/crypto/digests/SHA1Digest", "H5", "I");
methodVisitor.visitVarInsn(ALOAD, 0);
methodVisitor.visitInsn(ICONST_0);
methodVisitor.visitFieldInsn(PUTFIELD, "org/bouncycastle/crypto/digests/SHA1Digest", "xOff", "I");
methodVisitor.visitInsn(ICONST_0);
methodVisitor.visitVarInsn(ISTORE, 7);
Label label10 = new Label();
methodVisitor.visitLabel(label10);
methodVisitor.visitVarInsn(ILOAD, 7);
methodVisitor.visitIntInsn(BIPUSH, 16);
Label label11 = new Label();
methodVisitor.visitJumpInsn(IF_ICMPGE, label11);
methodVisitor.visitVarInsn(ALOAD, 0);
methodVisitor.visitFieldInsn(GETFIELD, "org/bouncycastle/crypto/digests/SHA1Digest", "X", "[I");
methodVisitor.visitVarInsn(ILOAD, 7);
methodVisitor.visitInsn(ICONST_0);
methodVisitor.visitInsn(IASTORE);
methodVisitor.visitIincInsn(7, 1);
methodVisitor.visitJumpInsn(GOTO, label10);
methodVisitor.visitLabel(label11);
methodVisitor.visitInsn(RETURN);
methodVisitor.visitMaxs(6, 8);
methodVisitor.visitEnd();
}
{
methodVisitor = classWriter.visitMethod(ACC_PUBLIC, "copy", "()Lorg/bouncycastle/util/Memoable;", null, null);
methodVisitor.visitCode();
methodVisitor.visitTypeInsn(NEW, "org/bouncycastle/crypto/digests/SHA1Digest");
methodVisitor.visitInsn(DUP);
methodVisitor.visitVarInsn(ALOAD, 0);
methodVisitor.visitMethodInsn(INVOKESPECIAL, "org/bouncycastle/crypto/digests/SHA1Digest", "<init>", "(Lorg/bouncycastle/crypto/digests/SHA1Digest;)V", false);
methodVisitor.visitInsn(ARETURN);
methodVisitor.visitMaxs(3, 1);
methodVisitor.visitEnd();
}
{
methodVisitor = classWriter.visitMethod(ACC_PUBLIC, "reset", "(Lorg/bouncycastle/util/Memoable;)V", null, null);
methodVisitor.visitCode();
methodVisitor.visitVarInsn(ALOAD, 1);
methodVisitor.visitTypeInsn(CHECKCAST, "org/bouncycastle/crypto/digests/SHA1Digest");
methodVisitor.visitVarInsn(ASTORE, 2);
methodVisitor.visitVarInsn(ALOAD, 0);
methodVisitor.visitVarInsn(ALOAD, 2);
methodVisitor.visitMethodInsn(INVOKESPECIAL, "org/bouncycastle/crypto/digests/GeneralDigest", "copyIn", "(Lorg/bouncycastle/crypto/digests/GeneralDigest;)V", false);
methodVisitor.visitVarInsn(ALOAD, 0);
methodVisitor.visitVarInsn(ALOAD, 2);
methodVisitor.visitMethodInsn(INVOKESPECIAL, "org/bouncycastle/crypto/digests/SHA1Digest", "copyIn", "(Lorg/bouncycastle/crypto/digests/SHA1Digest;)V", false);
methodVisitor.visitInsn(RETURN);
methodVisitor.visitMaxs(2, 3);
methodVisitor.visitEnd();
}
{
methodVisitor = classWriter.visitMethod(ACC_PUBLIC, "getEncodedState", "()[B", null, null);
methodVisitor.visitCode();
methodVisitor.visitIntInsn(BIPUSH, 40);
methodVisitor.visitVarInsn(ALOAD, 0);
methodVisitor.visitFieldInsn(GETFIELD, "org/bouncycastle/crypto/digests/SHA1Digest", "xOff", "I");
methodVisitor.visitInsn(ICONST_4);
methodVisitor.visitInsn(IMUL);
methodVisitor.visitInsn(IADD);
methodVisitor.visitIntInsn(NEWARRAY, T_BYTE);
methodVisitor.visitVarInsn(ASTORE, 1);
methodVisitor.visitVarInsn(ALOAD, 0);
methodVisitor.visitVarInsn(ALOAD, 1);
methodVisitor.visitMethodInsn(INVOKESPECIAL, "org/bouncycastle/crypto/digests/GeneralDigest", "populateState", "([B)V", false);
methodVisitor.visitVarInsn(ALOAD, 0);
methodVisitor.visitFieldInsn(GETFIELD, "org/bouncycastle/crypto/digests/SHA1Digest", "H1", "I");
methodVisitor.visitVarInsn(ALOAD, 1);
methodVisitor.visitIntInsn(BIPUSH, 16);
methodVisitor.visitMethodInsn(INVOKESTATIC, "org/bouncycastle/util/Pack", "intToBigEndian", "(I[BI)V", false);
methodVisitor.visitVarInsn(ALOAD, 0);
methodVisitor.visitFieldInsn(GETFIELD, "org/bouncycastle/crypto/digests/SHA1Digest", "H2", "I");
methodVisitor.visitVarInsn(ALOAD, 1);
methodVisitor.visitIntInsn(BIPUSH, 20);
methodVisitor.visitMethodInsn(INVOKESTATIC, "org/bouncycastle/util/Pack", "intToBigEndian", "(I[BI)V", false);
methodVisitor.visitVarInsn(ALOAD, 0);
methodVisitor.visitFieldInsn(GETFIELD, "org/bouncycastle/crypto/digests/SHA1Digest", "H3", "I");
methodVisitor.visitVarInsn(ALOAD, 1);
methodVisitor.visitIntInsn(BIPUSH, 24);
methodVisitor.visitMethodInsn(INVOKESTATIC, "org/bouncycastle/util/Pack", "intToBigEndian", "(I[BI)V", false);
methodVisitor.visitVarInsn(ALOAD, 0);
methodVisitor.visitFieldInsn(GETFIELD, "org/bouncycastle/crypto/digests/SHA1Digest", "H4", "I");
methodVisitor.visitVarInsn(ALOAD, 1);
methodVisitor.visitIntInsn(BIPUSH, 28);
methodVisitor.visitMethodInsn(INVOKESTATIC, "org/bouncycastle/util/Pack", "intToBigEndian", "(I[BI)V", false);
methodVisitor.visitVarInsn(ALOAD, 0);
methodVisitor.visitFieldInsn(GETFIELD, "org/bouncycastle/crypto/digests/SHA1Digest", "H5", "I");
methodVisitor.visitVarInsn(ALOAD, 1);
methodVisitor.visitIntInsn(BIPUSH, 32);
methodVisitor.visitMethodInsn(INVOKESTATIC, "org/bouncycastle/util/Pack", "intToBigEndian", "(I[BI)V", false);
methodVisitor.visitVarInsn(ALOAD, 0);
methodVisitor.visitFieldInsn(GETFIELD, "org/bouncycastle/crypto/digests/SHA1Digest", "xOff", "I");
methodVisitor.visitVarInsn(ALOAD, 1);
methodVisitor.visitIntInsn(BIPUSH, 36);
methodVisitor.visitMethodInsn(INVOKESTATIC, "org/bouncycastle/util/Pack", "intToBigEndian", "(I[BI)V", false);
methodVisitor.visitInsn(ICONST_0);
methodVisitor.visitVarInsn(ISTORE, 2);
Label label0 = new Label();
methodVisitor.visitLabel(label0);
methodVisitor.visitVarInsn(ILOAD, 2);
methodVisitor.visitVarInsn(ALOAD, 0);
methodVisitor.visitFieldInsn(GETFIELD, "org/bouncycastle/crypto/digests/SHA1Digest", "xOff", "I");
Label label1 = new Label();
methodVisitor.visitJumpInsn(IF_ICMPEQ, label1);
methodVisitor.visitVarInsn(ALOAD, 0);
methodVisitor.visitFieldInsn(GETFIELD, "org/bouncycastle/crypto/digests/SHA1Digest", "X", "[I");
methodVisitor.visitVarInsn(ILOAD, 2);
methodVisitor.visitInsn(IALOAD);
methodVisitor.visitVarInsn(ALOAD, 1);
methodVisitor.visitIntInsn(BIPUSH, 40);
methodVisitor.visitVarInsn(ILOAD, 2);
methodVisitor.visitInsn(ICONST_4);
methodVisitor.visitInsn(IMUL);
methodVisitor.visitInsn(IADD);
methodVisitor.visitMethodInsn(INVOKESTATIC, "org/bouncycastle/util/Pack", "intToBigEndian", "(I[BI)V", false);
methodVisitor.visitIincInsn(2, 1);
methodVisitor.visitJumpInsn(GOTO, label0);
methodVisitor.visitLabel(label1);
methodVisitor.visitVarInsn(ALOAD, 1);
methodVisitor.visitInsn(ARETURN);
methodVisitor.visitMaxs(5, 3);
methodVisitor.visitEnd();
}
classWriter.visitEnd();

return classWriter.toByteArray();
}
}
