package asm.org.bouncycastle.util.test;
import org.objectweb.asm.AnnotationVisitor;
import org.objectweb.asm.Attribute;
import org.objectweb.asm.ClassReader;
import org.objectweb.asm.ClassWriter;
import org.objectweb.asm.ConstantDynamic;
import org.objectweb.asm.FieldVisitor;
import org.objectweb.asm.Handle;
import org.objectweb.asm.Label;
import org.objectweb.asm.MethodVisitor;
import org.objectweb.asm.Opcodes;
import org.objectweb.asm.RecordComponentVisitor;
import org.objectweb.asm.Type;
import org.objectweb.asm.TypePath;
public class NumberParsingDump implements Opcodes {

public static byte[] dump () throws Exception {

ClassWriter classWriter = new ClassWriter(0);
FieldVisitor fieldVisitor;
RecordComponentVisitor recordComponentVisitor;
MethodVisitor methodVisitor;
AnnotationVisitor annotationVisitor0;

classWriter.visit(V1_5, ACC_PUBLIC | ACC_FINAL | ACC_SUPER, "org/bouncycastle/util/test/NumberParsing", null, "java/lang/Object", null);

{
methodVisitor = classWriter.visitMethod(ACC_PRIVATE, "<init>", "()V", null, null);
methodVisitor.visitCode();
methodVisitor.visitVarInsn(ALOAD, 0);
methodVisitor.visitMethodInsn(INVOKESPECIAL, "java/lang/Object", "<init>", "()V", false);
methodVisitor.visitInsn(RETURN);
methodVisitor.visitMaxs(1, 1);
methodVisitor.visitEnd();
}
{
methodVisitor = classWriter.visitMethod(ACC_PUBLIC | ACC_STATIC, "decodeLongFromHex", "(Ljava/lang/String;)J", null, null);
methodVisitor.visitCode();
methodVisitor.visitVarInsn(ALOAD, 0);
methodVisitor.visitInsn(ICONST_1);
methodVisitor.visitMethodInsn(INVOKEVIRTUAL, "java/lang/String", "charAt", "(I)C", false);
methodVisitor.visitIntInsn(BIPUSH, 120);
Label label0 = new Label();
methodVisitor.visitJumpInsn(IF_ICMPEQ, label0);
methodVisitor.visitVarInsn(ALOAD, 0);
methodVisitor.visitInsn(ICONST_1);
methodVisitor.visitMethodInsn(INVOKEVIRTUAL, "java/lang/String", "charAt", "(I)C", false);
methodVisitor.visitIntInsn(BIPUSH, 88);
Label label1 = new Label();
methodVisitor.visitJumpInsn(IF_ICMPNE, label1);
methodVisitor.visitLabel(label0);
methodVisitor.visitVarInsn(ALOAD, 0);
methodVisitor.visitInsn(ICONST_2);
methodVisitor.visitMethodInsn(INVOKEVIRTUAL, "java/lang/String", "substring", "(I)Ljava/lang/String;", false);
methodVisitor.visitIntInsn(BIPUSH, 16);
methodVisitor.visitMethodInsn(INVOKESTATIC, "java/lang/Long", "parseLong", "(Ljava/lang/String;I)J", false);
methodVisitor.visitInsn(LRETURN);
methodVisitor.visitLabel(label1);
methodVisitor.visitVarInsn(ALOAD, 0);
methodVisitor.visitIntInsn(BIPUSH, 16);
methodVisitor.visitMethodInsn(INVOKESTATIC, "java/lang/Long", "parseLong", "(Ljava/lang/String;I)J", false);
methodVisitor.visitInsn(LRETURN);
methodVisitor.visitMaxs(2, 1);
methodVisitor.visitEnd();
}
{
methodVisitor = classWriter.visitMethod(ACC_PUBLIC | ACC_STATIC, "decodeIntFromHex", "(Ljava/lang/String;)I", null, null);
methodVisitor.visitCode();
methodVisitor.visitVarInsn(ALOAD, 0);
methodVisitor.visitInsn(ICONST_1);
methodVisitor.visitMethodInsn(INVOKEVIRTUAL, "java/lang/String", "charAt", "(I)C", false);
methodVisitor.visitIntInsn(BIPUSH, 120);
Label label0 = new Label();
methodVisitor.visitJumpInsn(IF_ICMPEQ, label0);
methodVisitor.visitVarInsn(ALOAD, 0);
methodVisitor.visitInsn(ICONST_1);
methodVisitor.visitMethodInsn(INVOKEVIRTUAL, "java/lang/String", "charAt", "(I)C", false);
methodVisitor.visitIntInsn(BIPUSH, 88);
Label label1 = new Label();
methodVisitor.visitJumpInsn(IF_ICMPNE, label1);
methodVisitor.visitLabel(label0);
methodVisitor.visitVarInsn(ALOAD, 0);
methodVisitor.visitInsn(ICONST_2);
methodVisitor.visitMethodInsn(INVOKEVIRTUAL, "java/lang/String", "substring", "(I)Ljava/lang/String;", false);
methodVisitor.visitIntInsn(BIPUSH, 16);
methodVisitor.visitMethodInsn(INVOKESTATIC, "java/lang/Integer", "parseInt", "(Ljava/lang/String;I)I", false);
methodVisitor.visitInsn(IRETURN);
methodVisitor.visitLabel(label1);
methodVisitor.visitVarInsn(ALOAD, 0);
methodVisitor.visitIntInsn(BIPUSH, 16);
methodVisitor.visitMethodInsn(INVOKESTATIC, "java/lang/Integer", "parseInt", "(Ljava/lang/String;I)I", false);
methodVisitor.visitInsn(IRETURN);
methodVisitor.visitMaxs(2, 1);
methodVisitor.visitEnd();
}
classWriter.visitEnd();

return classWriter.toByteArray();
}
}
