package asm.org.bouncycastle.util;
import org.objectweb.asm.AnnotationVisitor;
import org.objectweb.asm.Attribute;
import org.objectweb.asm.ClassReader;
import org.objectweb.asm.ClassWriter;
import org.objectweb.asm.ConstantDynamic;
import org.objectweb.asm.FieldVisitor;
import org.objectweb.asm.Handle;
import org.objectweb.asm.Label;
import org.objectweb.asm.MethodVisitor;
import org.objectweb.asm.Opcodes;
import org.objectweb.asm.RecordComponentVisitor;
import org.objectweb.asm.Type;
import org.objectweb.asm.TypePath;
public class PackDump implements Opcodes {

public static byte[] dump () throws Exception {

ClassWriter classWriter = new ClassWriter(0);
FieldVisitor fieldVisitor;
RecordComponentVisitor recordComponentVisitor;
MethodVisitor methodVisitor;
AnnotationVisitor annotationVisitor0;

classWriter.visit(V1_5, ACC_PUBLIC | ACC_SUPER | ACC_ABSTRACT, "org/bouncycastle/util/Pack", null, "java/lang/Object", null);

{
methodVisitor = classWriter.visitMethod(ACC_PUBLIC, "<init>", "()V", null, null);
methodVisitor.visitCode();
methodVisitor.visitVarInsn(ALOAD, 0);
methodVisitor.visitMethodInsn(INVOKESPECIAL, "java/lang/Object", "<init>", "()V", false);
methodVisitor.visitInsn(RETURN);
methodVisitor.visitMaxs(1, 1);
methodVisitor.visitEnd();
}
{
methodVisitor = classWriter.visitMethod(ACC_PUBLIC | ACC_STATIC, "bigEndianToShort", "([BI)S", null, null);
methodVisitor.visitCode();
methodVisitor.visitVarInsn(ALOAD, 0);
methodVisitor.visitVarInsn(ILOAD, 1);
methodVisitor.visitInsn(BALOAD);
methodVisitor.visitIntInsn(SIPUSH, 255);
methodVisitor.visitInsn(IAND);
methodVisitor.visitIntInsn(BIPUSH, 8);
methodVisitor.visitInsn(ISHL);
methodVisitor.visitVarInsn(ISTORE, 2);
methodVisitor.visitVarInsn(ILOAD, 2);
methodVisitor.visitVarInsn(ALOAD, 0);
methodVisitor.visitIincInsn(1, 1);
methodVisitor.visitVarInsn(ILOAD, 1);
methodVisitor.visitInsn(BALOAD);
methodVisitor.visitIntInsn(SIPUSH, 255);
methodVisitor.visitInsn(IAND);
methodVisitor.visitInsn(IOR);
methodVisitor.visitVarInsn(ISTORE, 2);
methodVisitor.visitVarInsn(ILOAD, 2);
methodVisitor.visitInsn(I2S);
methodVisitor.visitInsn(IRETURN);
methodVisitor.visitMaxs(3, 3);
methodVisitor.visitEnd();
}
{
methodVisitor = classWriter.visitMethod(ACC_PUBLIC | ACC_STATIC, "bigEndianToInt", "([BI)I", null, null);
methodVisitor.visitCode();
methodVisitor.visitVarInsn(ALOAD, 0);
methodVisitor.visitVarInsn(ILOAD, 1);
methodVisitor.visitInsn(BALOAD);
methodVisitor.visitIntInsn(BIPUSH, 24);
methodVisitor.visitInsn(ISHL);
methodVisitor.visitVarInsn(ISTORE, 2);
methodVisitor.visitVarInsn(ILOAD, 2);
methodVisitor.visitVarInsn(ALOAD, 0);
methodVisitor.visitIincInsn(1, 1);
methodVisitor.visitVarInsn(ILOAD, 1);
methodVisitor.visitInsn(BALOAD);
methodVisitor.visitIntInsn(SIPUSH, 255);
methodVisitor.visitInsn(IAND);
methodVisitor.visitIntInsn(BIPUSH, 16);
methodVisitor.visitInsn(ISHL);
methodVisitor.visitInsn(IOR);
methodVisitor.visitVarInsn(ISTORE, 2);
methodVisitor.visitVarInsn(ILOAD, 2);
methodVisitor.visitVarInsn(ALOAD, 0);
methodVisitor.visitIincInsn(1, 1);
methodVisitor.visitVarInsn(ILOAD, 1);
methodVisitor.visitInsn(BALOAD);
methodVisitor.visitIntInsn(SIPUSH, 255);
methodVisitor.visitInsn(IAND);
methodVisitor.visitIntInsn(BIPUSH, 8);
methodVisitor.visitInsn(ISHL);
methodVisitor.visitInsn(IOR);
methodVisitor.visitVarInsn(ISTORE, 2);
methodVisitor.visitVarInsn(ILOAD, 2);
methodVisitor.visitVarInsn(ALOAD, 0);
methodVisitor.visitIincInsn(1, 1);
methodVisitor.visitVarInsn(ILOAD, 1);
methodVisitor.visitInsn(BALOAD);
methodVisitor.visitIntInsn(SIPUSH, 255);
methodVisitor.visitInsn(IAND);
methodVisitor.visitInsn(IOR);
methodVisitor.visitVarInsn(ISTORE, 2);
methodVisitor.visitVarInsn(ILOAD, 2);
methodVisitor.visitInsn(IRETURN);
methodVisitor.visitMaxs(3, 3);
methodVisitor.visitEnd();
}
{
methodVisitor = classWriter.visitMethod(ACC_PUBLIC | ACC_STATIC, "bigEndianToInt", "([BI[I)V", null, null);
methodVisitor.visitCode();
methodVisitor.visitInsn(ICONST_0);
methodVisitor.visitVarInsn(ISTORE, 3);
Label label0 = new Label();
methodVisitor.visitLabel(label0);
methodVisitor.visitVarInsn(ILOAD, 3);
methodVisitor.visitVarInsn(ALOAD, 2);
methodVisitor.visitInsn(ARRAYLENGTH);
Label label1 = new Label();
methodVisitor.visitJumpInsn(IF_ICMPGE, label1);
methodVisitor.visitVarInsn(ALOAD, 2);
methodVisitor.visitVarInsn(ILOAD, 3);
methodVisitor.visitVarInsn(ALOAD, 0);
methodVisitor.visitVarInsn(ILOAD, 1);
methodVisitor.visitMethodInsn(INVOKESTATIC, "org/bouncycastle/util/Pack", "bigEndianToInt", "([BI)I", false);
methodVisitor.visitInsn(IASTORE);
methodVisitor.visitIincInsn(1, 4);
methodVisitor.visitIincInsn(3, 1);
methodVisitor.visitJumpInsn(GOTO, label0);
methodVisitor.visitLabel(label1);
methodVisitor.visitInsn(RETURN);
methodVisitor.visitMaxs(4, 4);
methodVisitor.visitEnd();
}
{
methodVisitor = classWriter.visitMethod(ACC_PUBLIC | ACC_STATIC, "intToBigEndian", "(I)[B", null, null);
methodVisitor.visitCode();
methodVisitor.visitInsn(ICONST_4);
methodVisitor.visitIntInsn(NEWARRAY, T_BYTE);
methodVisitor.visitVarInsn(ASTORE, 1);
methodVisitor.visitVarInsn(ILOAD, 0);
methodVisitor.visitVarInsn(ALOAD, 1);
methodVisitor.visitInsn(ICONST_0);
methodVisitor.visitMethodInsn(INVOKESTATIC, "org/bouncycastle/util/Pack", "intToBigEndian", "(I[BI)V", false);
methodVisitor.visitVarInsn(ALOAD, 1);
methodVisitor.visitInsn(ARETURN);
methodVisitor.visitMaxs(3, 2);
methodVisitor.visitEnd();
}
{
methodVisitor = classWriter.visitMethod(ACC_PUBLIC | ACC_STATIC, "intToBigEndian", "(I[BI)V", null, null);
methodVisitor.visitCode();
methodVisitor.visitVarInsn(ALOAD, 1);
methodVisitor.visitVarInsn(ILOAD, 2);
methodVisitor.visitVarInsn(ILOAD, 0);
methodVisitor.visitIntInsn(BIPUSH, 24);
methodVisitor.visitInsn(IUSHR);
methodVisitor.visitInsn(I2B);
methodVisitor.visitInsn(BASTORE);
methodVisitor.visitVarInsn(ALOAD, 1);
methodVisitor.visitIincInsn(2, 1);
methodVisitor.visitVarInsn(ILOAD, 2);
methodVisitor.visitVarInsn(ILOAD, 0);
methodVisitor.visitIntInsn(BIPUSH, 16);
methodVisitor.visitInsn(IUSHR);
methodVisitor.visitInsn(I2B);
methodVisitor.visitInsn(BASTORE);
methodVisitor.visitVarInsn(ALOAD, 1);
methodVisitor.visitIincInsn(2, 1);
methodVisitor.visitVarInsn(ILOAD, 2);
methodVisitor.visitVarInsn(ILOAD, 0);
methodVisitor.visitIntInsn(BIPUSH, 8);
methodVisitor.visitInsn(IUSHR);
methodVisitor.visitInsn(I2B);
methodVisitor.visitInsn(BASTORE);
methodVisitor.visitVarInsn(ALOAD, 1);
methodVisitor.visitIincInsn(2, 1);
methodVisitor.visitVarInsn(ILOAD, 2);
methodVisitor.visitVarInsn(ILOAD, 0);
methodVisitor.visitInsn(I2B);
methodVisitor.visitInsn(BASTORE);
methodVisitor.visitInsn(RETURN);
methodVisitor.visitMaxs(4, 3);
methodVisitor.visitEnd();
}
{
methodVisitor = classWriter.visitMethod(ACC_PUBLIC | ACC_STATIC, "intToBigEndian", "([I)[B", null, null);
methodVisitor.visitCode();
methodVisitor.visitInsn(ICONST_4);
methodVisitor.visitVarInsn(ALOAD, 0);
methodVisitor.visitInsn(ARRAYLENGTH);
methodVisitor.visitInsn(IMUL);
methodVisitor.visitIntInsn(NEWARRAY, T_BYTE);
methodVisitor.visitVarInsn(ASTORE, 1);
methodVisitor.visitVarInsn(ALOAD, 0);
methodVisitor.visitVarInsn(ALOAD, 1);
methodVisitor.visitInsn(ICONST_0);
methodVisitor.visitMethodInsn(INVOKESTATIC, "org/bouncycastle/util/Pack", "intToBigEndian", "([I[BI)V", false);
methodVisitor.visitVarInsn(ALOAD, 1);
methodVisitor.visitInsn(ARETURN);
methodVisitor.visitMaxs(3, 2);
methodVisitor.visitEnd();
}
{
methodVisitor = classWriter.visitMethod(ACC_PUBLIC | ACC_STATIC, "intToBigEndian", "([I[BI)V", null, null);
methodVisitor.visitCode();
methodVisitor.visitInsn(ICONST_0);
methodVisitor.visitVarInsn(ISTORE, 3);
Label label0 = new Label();
methodVisitor.visitLabel(label0);
methodVisitor.visitVarInsn(ILOAD, 3);
methodVisitor.visitVarInsn(ALOAD, 0);
methodVisitor.visitInsn(ARRAYLENGTH);
Label label1 = new Label();
methodVisitor.visitJumpInsn(IF_ICMPGE, label1);
methodVisitor.visitVarInsn(ALOAD, 0);
methodVisitor.visitVarInsn(ILOAD, 3);
methodVisitor.visitInsn(IALOAD);
methodVisitor.visitVarInsn(ALOAD, 1);
methodVisitor.visitVarInsn(ILOAD, 2);
methodVisitor.visitMethodInsn(INVOKESTATIC, "org/bouncycastle/util/Pack", "intToBigEndian", "(I[BI)V", false);
methodVisitor.visitIincInsn(2, 4);
methodVisitor.visitIincInsn(3, 1);
methodVisitor.visitJumpInsn(GOTO, label0);
methodVisitor.visitLabel(label1);
methodVisitor.visitInsn(RETURN);
methodVisitor.visitMaxs(3, 4);
methodVisitor.visitEnd();
}
{
methodVisitor = classWriter.visitMethod(ACC_PUBLIC | ACC_STATIC, "bigEndianToLong", "([BI)J", null, null);
methodVisitor.visitCode();
methodVisitor.visitVarInsn(ALOAD, 0);
methodVisitor.visitVarInsn(ILOAD, 1);
methodVisitor.visitMethodInsn(INVOKESTATIC, "org/bouncycastle/util/Pack", "bigEndianToInt", "([BI)I", false);
methodVisitor.visitVarInsn(ISTORE, 2);
methodVisitor.visitVarInsn(ALOAD, 0);
methodVisitor.visitVarInsn(ILOAD, 1);
methodVisitor.visitInsn(ICONST_4);
methodVisitor.visitInsn(IADD);
methodVisitor.visitMethodInsn(INVOKESTATIC, "org/bouncycastle/util/Pack", "bigEndianToInt", "([BI)I", false);
methodVisitor.visitVarInsn(ISTORE, 3);
methodVisitor.visitVarInsn(ILOAD, 2);
methodVisitor.visitInsn(I2L);
methodVisitor.visitLdcInsn(new Long(4294967295L));
methodVisitor.visitInsn(LAND);
methodVisitor.visitIntInsn(BIPUSH, 32);
methodVisitor.visitInsn(LSHL);
methodVisitor.visitVarInsn(ILOAD, 3);
methodVisitor.visitInsn(I2L);
methodVisitor.visitLdcInsn(new Long(4294967295L));
methodVisitor.visitInsn(LAND);
methodVisitor.visitInsn(LOR);
methodVisitor.visitInsn(LRETURN);
methodVisitor.visitMaxs(6, 4);
methodVisitor.visitEnd();
}
{
methodVisitor = classWriter.visitMethod(ACC_PUBLIC | ACC_STATIC, "bigEndianToLong", "([BI[J)V", null, null);
methodVisitor.visitCode();
methodVisitor.visitInsn(ICONST_0);
methodVisitor.visitVarInsn(ISTORE, 3);
Label label0 = new Label();
methodVisitor.visitLabel(label0);
methodVisitor.visitVarInsn(ILOAD, 3);
methodVisitor.visitVarInsn(ALOAD, 2);
methodVisitor.visitInsn(ARRAYLENGTH);
Label label1 = new Label();
methodVisitor.visitJumpInsn(IF_ICMPGE, label1);
methodVisitor.visitVarInsn(ALOAD, 2);
methodVisitor.visitVarInsn(ILOAD, 3);
methodVisitor.visitVarInsn(ALOAD, 0);
methodVisitor.visitVarInsn(ILOAD, 1);
methodVisitor.visitMethodInsn(INVOKESTATIC, "org/bouncycastle/util/Pack", "bigEndianToLong", "([BI)J", false);
methodVisitor.visitInsn(LASTORE);
methodVisitor.visitIincInsn(1, 8);
methodVisitor.visitIincInsn(3, 1);
methodVisitor.visitJumpInsn(GOTO, label0);
methodVisitor.visitLabel(label1);
methodVisitor.visitInsn(RETURN);
methodVisitor.visitMaxs(4, 4);
methodVisitor.visitEnd();
}
{
methodVisitor = classWriter.visitMethod(ACC_PUBLIC | ACC_STATIC, "longToBigEndian", "(J)[B", null, null);
methodVisitor.visitCode();
methodVisitor.visitIntInsn(BIPUSH, 8);
methodVisitor.visitIntInsn(NEWARRAY, T_BYTE);
methodVisitor.visitVarInsn(ASTORE, 2);
methodVisitor.visitVarInsn(LLOAD, 0);
methodVisitor.visitVarInsn(ALOAD, 2);
methodVisitor.visitInsn(ICONST_0);
methodVisitor.visitMethodInsn(INVOKESTATIC, "org/bouncycastle/util/Pack", "longToBigEndian", "(J[BI)V", false);
methodVisitor.visitVarInsn(ALOAD, 2);
methodVisitor.visitInsn(ARETURN);
methodVisitor.visitMaxs(4, 3);
methodVisitor.visitEnd();
}
{
methodVisitor = classWriter.visitMethod(ACC_PUBLIC | ACC_STATIC, "longToBigEndian", "(J[BI)V", null, null);
methodVisitor.visitCode();
methodVisitor.visitVarInsn(LLOAD, 0);
methodVisitor.visitIntInsn(BIPUSH, 32);
methodVisitor.visitInsn(LUSHR);
methodVisitor.visitInsn(L2I);
methodVisitor.visitVarInsn(ALOAD, 2);
methodVisitor.visitVarInsn(ILOAD, 3);
methodVisitor.visitMethodInsn(INVOKESTATIC, "org/bouncycastle/util/Pack", "intToBigEndian", "(I[BI)V", false);
methodVisitor.visitVarInsn(LLOAD, 0);
methodVisitor.visitLdcInsn(new Long(4294967295L));
methodVisitor.visitInsn(LAND);
methodVisitor.visitInsn(L2I);
methodVisitor.visitVarInsn(ALOAD, 2);
methodVisitor.visitVarInsn(ILOAD, 3);
methodVisitor.visitInsn(ICONST_4);
methodVisitor.visitInsn(IADD);
methodVisitor.visitMethodInsn(INVOKESTATIC, "org/bouncycastle/util/Pack", "intToBigEndian", "(I[BI)V", false);
methodVisitor.visitInsn(RETURN);
methodVisitor.visitMaxs(4, 4);
methodVisitor.visitEnd();
}
{
methodVisitor = classWriter.visitMethod(ACC_PUBLIC | ACC_STATIC, "longToBigEndian", "([J)[B", null, null);
methodVisitor.visitCode();
methodVisitor.visitIntInsn(BIPUSH, 8);
methodVisitor.visitVarInsn(ALOAD, 0);
methodVisitor.visitInsn(ARRAYLENGTH);
methodVisitor.visitInsn(IMUL);
methodVisitor.visitIntInsn(NEWARRAY, T_BYTE);
methodVisitor.visitVarInsn(ASTORE, 1);
methodVisitor.visitVarInsn(ALOAD, 0);
methodVisitor.visitVarInsn(ALOAD, 1);
methodVisitor.visitInsn(ICONST_0);
methodVisitor.visitMethodInsn(INVOKESTATIC, "org/bouncycastle/util/Pack", "longToBigEndian", "([J[BI)V", false);
methodVisitor.visitVarInsn(ALOAD, 1);
methodVisitor.visitInsn(ARETURN);
methodVisitor.visitMaxs(3, 2);
methodVisitor.visitEnd();
}
{
methodVisitor = classWriter.visitMethod(ACC_PUBLIC | ACC_STATIC, "longToBigEndian", "([J[BI)V", null, null);
methodVisitor.visitCode();
methodVisitor.visitInsn(ICONST_0);
methodVisitor.visitVarInsn(ISTORE, 3);
Label label0 = new Label();
methodVisitor.visitLabel(label0);
methodVisitor.visitVarInsn(ILOAD, 3);
methodVisitor.visitVarInsn(ALOAD, 0);
methodVisitor.visitInsn(ARRAYLENGTH);
Label label1 = new Label();
methodVisitor.visitJumpInsn(IF_ICMPGE, label1);
methodVisitor.visitVarInsn(ALOAD, 0);
methodVisitor.visitVarInsn(ILOAD, 3);
methodVisitor.visitInsn(LALOAD);
methodVisitor.visitVarInsn(ALOAD, 1);
methodVisitor.visitVarInsn(ILOAD, 2);
methodVisitor.visitMethodInsn(INVOKESTATIC, "org/bouncycastle/util/Pack", "longToBigEndian", "(J[BI)V", false);
methodVisitor.visitIincInsn(2, 8);
methodVisitor.visitIincInsn(3, 1);
methodVisitor.visitJumpInsn(GOTO, label0);
methodVisitor.visitLabel(label1);
methodVisitor.visitInsn(RETURN);
methodVisitor.visitMaxs(4, 4);
methodVisitor.visitEnd();
}
{
methodVisitor = classWriter.visitMethod(ACC_PUBLIC | ACC_STATIC, "littleEndianToShort", "([BI)S", null, null);
methodVisitor.visitCode();
methodVisitor.visitVarInsn(ALOAD, 0);
methodVisitor.visitVarInsn(ILOAD, 1);
methodVisitor.visitInsn(BALOAD);
methodVisitor.visitIntInsn(SIPUSH, 255);
methodVisitor.visitInsn(IAND);
methodVisitor.visitVarInsn(ISTORE, 2);
methodVisitor.visitVarInsn(ILOAD, 2);
methodVisitor.visitVarInsn(ALOAD, 0);
methodVisitor.visitIincInsn(1, 1);
methodVisitor.visitVarInsn(ILOAD, 1);
methodVisitor.visitInsn(BALOAD);
methodVisitor.visitIntInsn(SIPUSH, 255);
methodVisitor.visitInsn(IAND);
methodVisitor.visitIntInsn(BIPUSH, 8);
methodVisitor.visitInsn(ISHL);
methodVisitor.visitInsn(IOR);
methodVisitor.visitVarInsn(ISTORE, 2);
methodVisitor.visitVarInsn(ILOAD, 2);
methodVisitor.visitInsn(I2S);
methodVisitor.visitInsn(IRETURN);
methodVisitor.visitMaxs(3, 3);
methodVisitor.visitEnd();
}
{
methodVisitor = classWriter.visitMethod(ACC_PUBLIC | ACC_STATIC, "littleEndianToInt", "([BI)I", null, null);
methodVisitor.visitCode();
methodVisitor.visitVarInsn(ALOAD, 0);
methodVisitor.visitVarInsn(ILOAD, 1);
methodVisitor.visitInsn(BALOAD);
methodVisitor.visitIntInsn(SIPUSH, 255);
methodVisitor.visitInsn(IAND);
methodVisitor.visitVarInsn(ISTORE, 2);
methodVisitor.visitVarInsn(ILOAD, 2);
methodVisitor.visitVarInsn(ALOAD, 0);
methodVisitor.visitIincInsn(1, 1);
methodVisitor.visitVarInsn(ILOAD, 1);
methodVisitor.visitInsn(BALOAD);
methodVisitor.visitIntInsn(SIPUSH, 255);
methodVisitor.visitInsn(IAND);
methodVisitor.visitIntInsn(BIPUSH, 8);
methodVisitor.visitInsn(ISHL);
methodVisitor.visitInsn(IOR);
methodVisitor.visitVarInsn(ISTORE, 2);
methodVisitor.visitVarInsn(ILOAD, 2);
methodVisitor.visitVarInsn(ALOAD, 0);
methodVisitor.visitIincInsn(1, 1);
methodVisitor.visitVarInsn(ILOAD, 1);
methodVisitor.visitInsn(BALOAD);
methodVisitor.visitIntInsn(SIPUSH, 255);
methodVisitor.visitInsn(IAND);
methodVisitor.visitIntInsn(BIPUSH, 16);
methodVisitor.visitInsn(ISHL);
methodVisitor.visitInsn(IOR);
methodVisitor.visitVarInsn(ISTORE, 2);
methodVisitor.visitVarInsn(ILOAD, 2);
methodVisitor.visitVarInsn(ALOAD, 0);
methodVisitor.visitIincInsn(1, 1);
methodVisitor.visitVarInsn(ILOAD, 1);
methodVisitor.visitInsn(BALOAD);
methodVisitor.visitIntInsn(BIPUSH, 24);
methodVisitor.visitInsn(ISHL);
methodVisitor.visitInsn(IOR);
methodVisitor.visitVarInsn(ISTORE, 2);
methodVisitor.visitVarInsn(ILOAD, 2);
methodVisitor.visitInsn(IRETURN);
methodVisitor.visitMaxs(3, 3);
methodVisitor.visitEnd();
}
{
methodVisitor = classWriter.visitMethod(ACC_PUBLIC | ACC_STATIC, "littleEndianToInt", "([BI[I)V", null, null);
methodVisitor.visitCode();
methodVisitor.visitInsn(ICONST_0);
methodVisitor.visitVarInsn(ISTORE, 3);
Label label0 = new Label();
methodVisitor.visitLabel(label0);
methodVisitor.visitVarInsn(ILOAD, 3);
methodVisitor.visitVarInsn(ALOAD, 2);
methodVisitor.visitInsn(ARRAYLENGTH);
Label label1 = new Label();
methodVisitor.visitJumpInsn(IF_ICMPGE, label1);
methodVisitor.visitVarInsn(ALOAD, 2);
methodVisitor.visitVarInsn(ILOAD, 3);
methodVisitor.visitVarInsn(ALOAD, 0);
methodVisitor.visitVarInsn(ILOAD, 1);
methodVisitor.visitMethodInsn(INVOKESTATIC, "org/bouncycastle/util/Pack", "littleEndianToInt", "([BI)I", false);
methodVisitor.visitInsn(IASTORE);
methodVisitor.visitIincInsn(1, 4);
methodVisitor.visitIincInsn(3, 1);
methodVisitor.visitJumpInsn(GOTO, label0);
methodVisitor.visitLabel(label1);
methodVisitor.visitInsn(RETURN);
methodVisitor.visitMaxs(4, 4);
methodVisitor.visitEnd();
}
{
methodVisitor = classWriter.visitMethod(ACC_PUBLIC | ACC_STATIC, "littleEndianToInt", "([BI[III)V", null, null);
methodVisitor.visitCode();
methodVisitor.visitInsn(ICONST_0);
methodVisitor.visitVarInsn(ISTORE, 5);
Label label0 = new Label();
methodVisitor.visitLabel(label0);
methodVisitor.visitVarInsn(ILOAD, 5);
methodVisitor.visitVarInsn(ILOAD, 4);
Label label1 = new Label();
methodVisitor.visitJumpInsn(IF_ICMPGE, label1);
methodVisitor.visitVarInsn(ALOAD, 2);
methodVisitor.visitVarInsn(ILOAD, 3);
methodVisitor.visitVarInsn(ILOAD, 5);
methodVisitor.visitInsn(IADD);
methodVisitor.visitVarInsn(ALOAD, 0);
methodVisitor.visitVarInsn(ILOAD, 1);
methodVisitor.visitMethodInsn(INVOKESTATIC, "org/bouncycastle/util/Pack", "littleEndianToInt", "([BI)I", false);
methodVisitor.visitInsn(IASTORE);
methodVisitor.visitIincInsn(1, 4);
methodVisitor.visitIincInsn(5, 1);
methodVisitor.visitJumpInsn(GOTO, label0);
methodVisitor.visitLabel(label1);
methodVisitor.visitInsn(RETURN);
methodVisitor.visitMaxs(4, 6);
methodVisitor.visitEnd();
}
{
methodVisitor = classWriter.visitMethod(ACC_PUBLIC | ACC_STATIC, "littleEndianToInt", "([BII)[I", null, null);
methodVisitor.visitCode();
methodVisitor.visitVarInsn(ILOAD, 2);
methodVisitor.visitIntInsn(NEWARRAY, T_INT);
methodVisitor.visitVarInsn(ASTORE, 3);
methodVisitor.visitInsn(ICONST_0);
methodVisitor.visitVarInsn(ISTORE, 4);
Label label0 = new Label();
methodVisitor.visitLabel(label0);
methodVisitor.visitVarInsn(ILOAD, 4);
methodVisitor.visitVarInsn(ALOAD, 3);
methodVisitor.visitInsn(ARRAYLENGTH);
Label label1 = new Label();
methodVisitor.visitJumpInsn(IF_ICMPGE, label1);
methodVisitor.visitVarInsn(ALOAD, 3);
methodVisitor.visitVarInsn(ILOAD, 4);
methodVisitor.visitVarInsn(ALOAD, 0);
methodVisitor.visitVarInsn(ILOAD, 1);
methodVisitor.visitMethodInsn(INVOKESTATIC, "org/bouncycastle/util/Pack", "littleEndianToInt", "([BI)I", false);
methodVisitor.visitInsn(IASTORE);
methodVisitor.visitIincInsn(1, 4);
methodVisitor.visitIincInsn(4, 1);
methodVisitor.visitJumpInsn(GOTO, label0);
methodVisitor.visitLabel(label1);
methodVisitor.visitVarInsn(ALOAD, 3);
methodVisitor.visitInsn(ARETURN);
methodVisitor.visitMaxs(4, 5);
methodVisitor.visitEnd();
}
{
methodVisitor = classWriter.visitMethod(ACC_PUBLIC | ACC_STATIC, "shortToLittleEndian", "(S)[B", null, null);
methodVisitor.visitCode();
methodVisitor.visitInsn(ICONST_2);
methodVisitor.visitIntInsn(NEWARRAY, T_BYTE);
methodVisitor.visitVarInsn(ASTORE, 1);
methodVisitor.visitVarInsn(ILOAD, 0);
methodVisitor.visitVarInsn(ALOAD, 1);
methodVisitor.visitInsn(ICONST_0);
methodVisitor.visitMethodInsn(INVOKESTATIC, "org/bouncycastle/util/Pack", "shortToLittleEndian", "(S[BI)V", false);
methodVisitor.visitVarInsn(ALOAD, 1);
methodVisitor.visitInsn(ARETURN);
methodVisitor.visitMaxs(3, 2);
methodVisitor.visitEnd();
}
{
methodVisitor = classWriter.visitMethod(ACC_PUBLIC | ACC_STATIC, "shortToLittleEndian", "(S[BI)V", null, null);
methodVisitor.visitCode();
methodVisitor.visitVarInsn(ALOAD, 1);
methodVisitor.visitVarInsn(ILOAD, 2);
methodVisitor.visitVarInsn(ILOAD, 0);
methodVisitor.visitInsn(I2B);
methodVisitor.visitInsn(BASTORE);
methodVisitor.visitVarInsn(ALOAD, 1);
methodVisitor.visitIincInsn(2, 1);
methodVisitor.visitVarInsn(ILOAD, 2);
methodVisitor.visitVarInsn(ILOAD, 0);
methodVisitor.visitIntInsn(BIPUSH, 8);
methodVisitor.visitInsn(IUSHR);
methodVisitor.visitInsn(I2B);
methodVisitor.visitInsn(BASTORE);
methodVisitor.visitInsn(RETURN);
methodVisitor.visitMaxs(4, 3);
methodVisitor.visitEnd();
}
{
methodVisitor = classWriter.visitMethod(ACC_PUBLIC | ACC_STATIC, "intToLittleEndian", "(I)[B", null, null);
methodVisitor.visitCode();
methodVisitor.visitInsn(ICONST_4);
methodVisitor.visitIntInsn(NEWARRAY, T_BYTE);
methodVisitor.visitVarInsn(ASTORE, 1);
methodVisitor.visitVarInsn(ILOAD, 0);
methodVisitor.visitVarInsn(ALOAD, 1);
methodVisitor.visitInsn(ICONST_0);
methodVisitor.visitMethodInsn(INVOKESTATIC, "org/bouncycastle/util/Pack", "intToLittleEndian", "(I[BI)V", false);
methodVisitor.visitVarInsn(ALOAD, 1);
methodVisitor.visitInsn(ARETURN);
methodVisitor.visitMaxs(3, 2);
methodVisitor.visitEnd();
}
{
methodVisitor = classWriter.visitMethod(ACC_PUBLIC | ACC_STATIC, "intToLittleEndian", "(I[BI)V", null, null);
methodVisitor.visitCode();
methodVisitor.visitVarInsn(ALOAD, 1);
methodVisitor.visitVarInsn(ILOAD, 2);
methodVisitor.visitVarInsn(ILOAD, 0);
methodVisitor.visitInsn(I2B);
methodVisitor.visitInsn(BASTORE);
methodVisitor.visitVarInsn(ALOAD, 1);
methodVisitor.visitIincInsn(2, 1);
methodVisitor.visitVarInsn(ILOAD, 2);
methodVisitor.visitVarInsn(ILOAD, 0);
methodVisitor.visitIntInsn(BIPUSH, 8);
methodVisitor.visitInsn(IUSHR);
methodVisitor.visitInsn(I2B);
methodVisitor.visitInsn(BASTORE);
methodVisitor.visitVarInsn(ALOAD, 1);
methodVisitor.visitIincInsn(2, 1);
methodVisitor.visitVarInsn(ILOAD, 2);
methodVisitor.visitVarInsn(ILOAD, 0);
methodVisitor.visitIntInsn(BIPUSH, 16);
methodVisitor.visitInsn(IUSHR);
methodVisitor.visitInsn(I2B);
methodVisitor.visitInsn(BASTORE);
methodVisitor.visitVarInsn(ALOAD, 1);
methodVisitor.visitIincInsn(2, 1);
methodVisitor.visitVarInsn(ILOAD, 2);
methodVisitor.visitVarInsn(ILOAD, 0);
methodVisitor.visitIntInsn(BIPUSH, 24);
methodVisitor.visitInsn(IUSHR);
methodVisitor.visitInsn(I2B);
methodVisitor.visitInsn(BASTORE);
methodVisitor.visitInsn(RETURN);
methodVisitor.visitMaxs(4, 3);
methodVisitor.visitEnd();
}
{
methodVisitor = classWriter.visitMethod(ACC_PUBLIC | ACC_STATIC, "intToLittleEndian", "([I)[B", null, null);
methodVisitor.visitCode();
methodVisitor.visitInsn(ICONST_4);
methodVisitor.visitVarInsn(ALOAD, 0);
methodVisitor.visitInsn(ARRAYLENGTH);
methodVisitor.visitInsn(IMUL);
methodVisitor.visitIntInsn(NEWARRAY, T_BYTE);
methodVisitor.visitVarInsn(ASTORE, 1);
methodVisitor.visitVarInsn(ALOAD, 0);
methodVisitor.visitVarInsn(ALOAD, 1);
methodVisitor.visitInsn(ICONST_0);
methodVisitor.visitMethodInsn(INVOKESTATIC, "org/bouncycastle/util/Pack", "intToLittleEndian", "([I[BI)V", false);
methodVisitor.visitVarInsn(ALOAD, 1);
methodVisitor.visitInsn(ARETURN);
methodVisitor.visitMaxs(3, 2);
methodVisitor.visitEnd();
}
{
methodVisitor = classWriter.visitMethod(ACC_PUBLIC | ACC_STATIC, "intToLittleEndian", "([I[BI)V", null, null);
methodVisitor.visitCode();
methodVisitor.visitInsn(ICONST_0);
methodVisitor.visitVarInsn(ISTORE, 3);
Label label0 = new Label();
methodVisitor.visitLabel(label0);
methodVisitor.visitVarInsn(ILOAD, 3);
methodVisitor.visitVarInsn(ALOAD, 0);
methodVisitor.visitInsn(ARRAYLENGTH);
Label label1 = new Label();
methodVisitor.visitJumpInsn(IF_ICMPGE, label1);
methodVisitor.visitVarInsn(ALOAD, 0);
methodVisitor.visitVarInsn(ILOAD, 3);
methodVisitor.visitInsn(IALOAD);
methodVisitor.visitVarInsn(ALOAD, 1);
methodVisitor.visitVarInsn(ILOAD, 2);
methodVisitor.visitMethodInsn(INVOKESTATIC, "org/bouncycastle/util/Pack", "intToLittleEndian", "(I[BI)V", false);
methodVisitor.visitIincInsn(2, 4);
methodVisitor.visitIincInsn(3, 1);
methodVisitor.visitJumpInsn(GOTO, label0);
methodVisitor.visitLabel(label1);
methodVisitor.visitInsn(RETURN);
methodVisitor.visitMaxs(3, 4);
methodVisitor.visitEnd();
}
{
methodVisitor = classWriter.visitMethod(ACC_PUBLIC | ACC_STATIC, "littleEndianToLong", "([BI)J", null, null);
methodVisitor.visitCode();
methodVisitor.visitVarInsn(ALOAD, 0);
methodVisitor.visitVarInsn(ILOAD, 1);
methodVisitor.visitMethodInsn(INVOKESTATIC, "org/bouncycastle/util/Pack", "littleEndianToInt", "([BI)I", false);
methodVisitor.visitVarInsn(ISTORE, 2);
methodVisitor.visitVarInsn(ALOAD, 0);
methodVisitor.visitVarInsn(ILOAD, 1);
methodVisitor.visitInsn(ICONST_4);
methodVisitor.visitInsn(IADD);
methodVisitor.visitMethodInsn(INVOKESTATIC, "org/bouncycastle/util/Pack", "littleEndianToInt", "([BI)I", false);
methodVisitor.visitVarInsn(ISTORE, 3);
methodVisitor.visitVarInsn(ILOAD, 3);
methodVisitor.visitInsn(I2L);
methodVisitor.visitLdcInsn(new Long(4294967295L));
methodVisitor.visitInsn(LAND);
methodVisitor.visitIntInsn(BIPUSH, 32);
methodVisitor.visitInsn(LSHL);
methodVisitor.visitVarInsn(ILOAD, 2);
methodVisitor.visitInsn(I2L);
methodVisitor.visitLdcInsn(new Long(4294967295L));
methodVisitor.visitInsn(LAND);
methodVisitor.visitInsn(LOR);
methodVisitor.visitInsn(LRETURN);
methodVisitor.visitMaxs(6, 4);
methodVisitor.visitEnd();
}
{
methodVisitor = classWriter.visitMethod(ACC_PUBLIC | ACC_STATIC, "littleEndianToLong", "([BI[J)V", null, null);
methodVisitor.visitCode();
methodVisitor.visitInsn(ICONST_0);
methodVisitor.visitVarInsn(ISTORE, 3);
Label label0 = new Label();
methodVisitor.visitLabel(label0);
methodVisitor.visitVarInsn(ILOAD, 3);
methodVisitor.visitVarInsn(ALOAD, 2);
methodVisitor.visitInsn(ARRAYLENGTH);
Label label1 = new Label();
methodVisitor.visitJumpInsn(IF_ICMPGE, label1);
methodVisitor.visitVarInsn(ALOAD, 2);
methodVisitor.visitVarInsn(ILOAD, 3);
methodVisitor.visitVarInsn(ALOAD, 0);
methodVisitor.visitVarInsn(ILOAD, 1);
methodVisitor.visitMethodInsn(INVOKESTATIC, "org/bouncycastle/util/Pack", "littleEndianToLong", "([BI)J", false);
methodVisitor.visitInsn(LASTORE);
methodVisitor.visitIincInsn(1, 8);
methodVisitor.visitIincInsn(3, 1);
methodVisitor.visitJumpInsn(GOTO, label0);
methodVisitor.visitLabel(label1);
methodVisitor.visitInsn(RETURN);
methodVisitor.visitMaxs(4, 4);
methodVisitor.visitEnd();
}
{
methodVisitor = classWriter.visitMethod(ACC_PUBLIC | ACC_STATIC, "littleEndianToLong", "([BI[JII)V", null, null);
methodVisitor.visitCode();
methodVisitor.visitInsn(ICONST_0);
methodVisitor.visitVarInsn(ISTORE, 5);
Label label0 = new Label();
methodVisitor.visitLabel(label0);
methodVisitor.visitVarInsn(ILOAD, 5);
methodVisitor.visitVarInsn(ILOAD, 4);
Label label1 = new Label();
methodVisitor.visitJumpInsn(IF_ICMPGE, label1);
methodVisitor.visitVarInsn(ALOAD, 2);
methodVisitor.visitVarInsn(ILOAD, 3);
methodVisitor.visitVarInsn(ILOAD, 5);
methodVisitor.visitInsn(IADD);
methodVisitor.visitVarInsn(ALOAD, 0);
methodVisitor.visitVarInsn(ILOAD, 1);
methodVisitor.visitMethodInsn(INVOKESTATIC, "org/bouncycastle/util/Pack", "littleEndianToLong", "([BI)J", false);
methodVisitor.visitInsn(LASTORE);
methodVisitor.visitIincInsn(1, 8);
methodVisitor.visitIincInsn(5, 1);
methodVisitor.visitJumpInsn(GOTO, label0);
methodVisitor.visitLabel(label1);
methodVisitor.visitInsn(RETURN);
methodVisitor.visitMaxs(4, 6);
methodVisitor.visitEnd();
}
{
methodVisitor = classWriter.visitMethod(ACC_PUBLIC | ACC_STATIC, "longToLittleEndian", "(J)[B", null, null);
methodVisitor.visitCode();
methodVisitor.visitIntInsn(BIPUSH, 8);
methodVisitor.visitIntInsn(NEWARRAY, T_BYTE);
methodVisitor.visitVarInsn(ASTORE, 2);
methodVisitor.visitVarInsn(LLOAD, 0);
methodVisitor.visitVarInsn(ALOAD, 2);
methodVisitor.visitInsn(ICONST_0);
methodVisitor.visitMethodInsn(INVOKESTATIC, "org/bouncycastle/util/Pack", "longToLittleEndian", "(J[BI)V", false);
methodVisitor.visitVarInsn(ALOAD, 2);
methodVisitor.visitInsn(ARETURN);
methodVisitor.visitMaxs(4, 3);
methodVisitor.visitEnd();
}
{
methodVisitor = classWriter.visitMethod(ACC_PUBLIC | ACC_STATIC, "longToLittleEndian", "(J[BI)V", null, null);
methodVisitor.visitCode();
methodVisitor.visitVarInsn(LLOAD, 0);
methodVisitor.visitLdcInsn(new Long(4294967295L));
methodVisitor.visitInsn(LAND);
methodVisitor.visitInsn(L2I);
methodVisitor.visitVarInsn(ALOAD, 2);
methodVisitor.visitVarInsn(ILOAD, 3);
methodVisitor.visitMethodInsn(INVOKESTATIC, "org/bouncycastle/util/Pack", "intToLittleEndian", "(I[BI)V", false);
methodVisitor.visitVarInsn(LLOAD, 0);
methodVisitor.visitIntInsn(BIPUSH, 32);
methodVisitor.visitInsn(LUSHR);
methodVisitor.visitInsn(L2I);
methodVisitor.visitVarInsn(ALOAD, 2);
methodVisitor.visitVarInsn(ILOAD, 3);
methodVisitor.visitInsn(ICONST_4);
methodVisitor.visitInsn(IADD);
methodVisitor.visitMethodInsn(INVOKESTATIC, "org/bouncycastle/util/Pack", "intToLittleEndian", "(I[BI)V", false);
methodVisitor.visitInsn(RETURN);
methodVisitor.visitMaxs(4, 4);
methodVisitor.visitEnd();
}
{
methodVisitor = classWriter.visitMethod(ACC_PUBLIC | ACC_STATIC, "longToLittleEndian", "([J)[B", null, null);
methodVisitor.visitCode();
methodVisitor.visitIntInsn(BIPUSH, 8);
methodVisitor.visitVarInsn(ALOAD, 0);
methodVisitor.visitInsn(ARRAYLENGTH);
methodVisitor.visitInsn(IMUL);
methodVisitor.visitIntInsn(NEWARRAY, T_BYTE);
methodVisitor.visitVarInsn(ASTORE, 1);
methodVisitor.visitVarInsn(ALOAD, 0);
methodVisitor.visitVarInsn(ALOAD, 1);
methodVisitor.visitInsn(ICONST_0);
methodVisitor.visitMethodInsn(INVOKESTATIC, "org/bouncycastle/util/Pack", "longToLittleEndian", "([J[BI)V", false);
methodVisitor.visitVarInsn(ALOAD, 1);
methodVisitor.visitInsn(ARETURN);
methodVisitor.visitMaxs(3, 2);
methodVisitor.visitEnd();
}
{
methodVisitor = classWriter.visitMethod(ACC_PUBLIC | ACC_STATIC, "longToLittleEndian", "([J[BI)V", null, null);
methodVisitor.visitCode();
methodVisitor.visitInsn(ICONST_0);
methodVisitor.visitVarInsn(ISTORE, 3);
Label label0 = new Label();
methodVisitor.visitLabel(label0);
methodVisitor.visitVarInsn(ILOAD, 3);
methodVisitor.visitVarInsn(ALOAD, 0);
methodVisitor.visitInsn(ARRAYLENGTH);
Label label1 = new Label();
methodVisitor.visitJumpInsn(IF_ICMPGE, label1);
methodVisitor.visitVarInsn(ALOAD, 0);
methodVisitor.visitVarInsn(ILOAD, 3);
methodVisitor.visitInsn(LALOAD);
methodVisitor.visitVarInsn(ALOAD, 1);
methodVisitor.visitVarInsn(ILOAD, 2);
methodVisitor.visitMethodInsn(INVOKESTATIC, "org/bouncycastle/util/Pack", "longToLittleEndian", "(J[BI)V", false);
methodVisitor.visitIincInsn(2, 8);
methodVisitor.visitIincInsn(3, 1);
methodVisitor.visitJumpInsn(GOTO, label0);
methodVisitor.visitLabel(label1);
methodVisitor.visitInsn(RETURN);
methodVisitor.visitMaxs(4, 4);
methodVisitor.visitEnd();
}
{
methodVisitor = classWriter.visitMethod(ACC_PUBLIC | ACC_STATIC, "longToLittleEndian", "([JII[BI)V", null, null);
methodVisitor.visitCode();
methodVisitor.visitInsn(ICONST_0);
methodVisitor.visitVarInsn(ISTORE, 5);
Label label0 = new Label();
methodVisitor.visitLabel(label0);
methodVisitor.visitVarInsn(ILOAD, 5);
methodVisitor.visitVarInsn(ILOAD, 2);
Label label1 = new Label();
methodVisitor.visitJumpInsn(IF_ICMPGE, label1);
methodVisitor.visitVarInsn(ALOAD, 0);
methodVisitor.visitVarInsn(ILOAD, 1);
methodVisitor.visitVarInsn(ILOAD, 5);
methodVisitor.visitInsn(IADD);
methodVisitor.visitInsn(LALOAD);
methodVisitor.visitVarInsn(ALOAD, 3);
methodVisitor.visitVarInsn(ILOAD, 4);
methodVisitor.visitMethodInsn(INVOKESTATIC, "org/bouncycastle/util/Pack", "longToLittleEndian", "(J[BI)V", false);
methodVisitor.visitIincInsn(4, 8);
methodVisitor.visitIincInsn(5, 1);
methodVisitor.visitJumpInsn(GOTO, label0);
methodVisitor.visitLabel(label1);
methodVisitor.visitInsn(RETURN);
methodVisitor.visitMaxs(4, 6);
methodVisitor.visitEnd();
}
classWriter.visitEnd();

return classWriter.toByteArray();
}
}
