package asm.org.eclipse.persistence.jaxb.compiler;
import org.objectweb.asm.AnnotationVisitor;
import org.objectweb.asm.Attribute;
import org.objectweb.asm.ClassReader;
import org.objectweb.asm.ClassWriter;
import org.objectweb.asm.ConstantDynamic;
import org.objectweb.asm.FieldVisitor;
import org.objectweb.asm.Handle;
import org.objectweb.asm.Label;
import org.objectweb.asm.MethodVisitor;
import org.objectweb.asm.Opcodes;
import org.objectweb.asm.RecordComponentVisitor;
import org.objectweb.asm.Type;
import org.objectweb.asm.TypePath;
public class SchemaGenerator$RegexMutator$1Dump implements Opcodes {

public static byte[] dump () throws Exception {

ClassWriter classWriter = new ClassWriter(0);
FieldVisitor fieldVisitor;
RecordComponentVisitor recordComponentVisitor;
MethodVisitor methodVisitor;
AnnotationVisitor annotationVisitor0;

classWriter.visit(V1_8, ACC_SUPER, "org/eclipse/persistence/jaxb/compiler/SchemaGenerator$RegexMutator$1", "Ljava/util/LinkedHashMap<Ljava/util/regex/Pattern;Ljava/lang/String;>;", "java/util/LinkedHashMap", null);

classWriter.visitOuterClass("org/eclipse/persistence/jaxb/compiler/SchemaGenerator$RegexMutator", null, null);

classWriter.visitInnerClass("org/eclipse/persistence/jaxb/compiler/SchemaGenerator$RegexMutator", "org/eclipse/persistence/jaxb/compiler/SchemaGenerator", "RegexMutator", ACC_PRIVATE | ACC_FINAL | ACC_STATIC);

classWriter.visitInnerClass("org/eclipse/persistence/jaxb/compiler/SchemaGenerator$RegexMutator$1", null, null, 0);

{
methodVisitor = classWriter.visitMethod(0, "<init>", "(I)V", null, null);
methodVisitor.visitCode();
methodVisitor.visitVarInsn(ALOAD, 0);
methodVisitor.visitVarInsn(ILOAD, 1);
methodVisitor.visitMethodInsn(INVOKESPECIAL, "java/util/LinkedHashMap", "<init>", "(I)V", false);
methodVisitor.visitVarInsn(ALOAD, 0);
methodVisitor.visitLdcInsn("[:A-Z_a-z\\u00C0-\\u00D6\\u00D8-\\u00F6\\u00F8-\\u02FF\\u0370-\\u037D\\u037F-\\u1FFF\\u200C-\\u200D\\u2070-\\u218F\\u2C00-\\u2FEF\\u3001-\\uD7FF\\uF900-\\uFDCF\\uFDF0-\\uFFFD]");
methodVisitor.visitIntInsn(BIPUSH, 16);
methodVisitor.visitMethodInsn(INVOKESTATIC, "java/util/regex/Pattern", "compile", "(Ljava/lang/String;I)Ljava/util/regex/Pattern;", false);
methodVisitor.visitLdcInsn("\\\\i");
methodVisitor.visitMethodInsn(INVOKEVIRTUAL, "org/eclipse/persistence/jaxb/compiler/SchemaGenerator$RegexMutator$1", "put", "(Ljava/lang/Object;Ljava/lang/Object;)Ljava/lang/Object;", false);
methodVisitor.visitInsn(POP);
methodVisitor.visitVarInsn(ALOAD, 0);
methodVisitor.visitLdcInsn("[^:A-Z_a-z\\u00C0-\\u00D6\\u00D8-\\u00F6\\u00F8-\\u02FF\\u0370-\\u037D\\u037F-\\u1FFF\\u200C-\\u200D\\u2070-\\u218F\\u2C00-\\u2FEF\\u3001-\\uD7FF\\uF900-\\uFDCF\\uFDF0-\\uFFFD]");
methodVisitor.visitIntInsn(BIPUSH, 16);
methodVisitor.visitMethodInsn(INVOKESTATIC, "java/util/regex/Pattern", "compile", "(Ljava/lang/String;I)Ljava/util/regex/Pattern;", false);
methodVisitor.visitLdcInsn("\\\\I");
methodVisitor.visitMethodInsn(INVOKEVIRTUAL, "org/eclipse/persistence/jaxb/compiler/SchemaGenerator$RegexMutator$1", "put", "(Ljava/lang/Object;Ljava/lang/Object;)Ljava/lang/Object;", false);
methodVisitor.visitInsn(POP);
methodVisitor.visitVarInsn(ALOAD, 0);
methodVisitor.visitLdcInsn("[-.0-9:A-Z_a-z\\u00B7\\u00C0-\\u00D6\\u00D8-\\u00F6\\u00F8-\\u037D\\u037F-\\u1FFF\\u200C-\\u200D\\u203F\\u2040\\u2070-\\u218F\\u2C00-\\u2FEF\\u3001-\\uD7FF\\uF900-\\uFDCF\\uFDF0-\\uFFFD]");
methodVisitor.visitIntInsn(BIPUSH, 16);
methodVisitor.visitMethodInsn(INVOKESTATIC, "java/util/regex/Pattern", "compile", "(Ljava/lang/String;I)Ljava/util/regex/Pattern;", false);
methodVisitor.visitLdcInsn("\\\\c");
methodVisitor.visitMethodInsn(INVOKEVIRTUAL, "org/eclipse/persistence/jaxb/compiler/SchemaGenerator$RegexMutator$1", "put", "(Ljava/lang/Object;Ljava/lang/Object;)Ljava/lang/Object;", false);
methodVisitor.visitInsn(POP);
methodVisitor.visitVarInsn(ALOAD, 0);
methodVisitor.visitLdcInsn("[^-.0-9:A-Z_a-z\\u00B7\\u00C0-\\u00D6\\u00D8-\\u00F6\\u00F8-\\u037D\\u037F-\\u1FFF\\u200C-\\u200D\\u203F\\u2040\\u2070-\\u218F\\u2C00-\\u2FEF\\u3001-\\uD7FF\\uF900-\\uFDCF\\uFDF0-\\uFFFD]");
methodVisitor.visitIntInsn(BIPUSH, 16);
methodVisitor.visitMethodInsn(INVOKESTATIC, "java/util/regex/Pattern", "compile", "(Ljava/lang/String;I)Ljava/util/regex/Pattern;", false);
methodVisitor.visitLdcInsn("\\\\C");
methodVisitor.visitMethodInsn(INVOKEVIRTUAL, "org/eclipse/persistence/jaxb/compiler/SchemaGenerator$RegexMutator$1", "put", "(Ljava/lang/Object;Ljava/lang/Object;)Ljava/lang/Object;", false);
methodVisitor.visitInsn(POP);
methodVisitor.visitVarInsn(ALOAD, 0);
methodVisitor.visitLdcInsn("[\\u0009-\\u000D\\u0020\\u0085\\u00A0\\u1680\\u180E\\u2000-\\u200A\\u2028\\u2029\\u202F\\u205F\\u3000]");
methodVisitor.visitIntInsn(BIPUSH, 16);
methodVisitor.visitMethodInsn(INVOKESTATIC, "java/util/regex/Pattern", "compile", "(Ljava/lang/String;I)Ljava/util/regex/Pattern;", false);
methodVisitor.visitLdcInsn("\\\\s");
methodVisitor.visitMethodInsn(INVOKEVIRTUAL, "org/eclipse/persistence/jaxb/compiler/SchemaGenerator$RegexMutator$1", "put", "(Ljava/lang/Object;Ljava/lang/Object;)Ljava/lang/Object;", false);
methodVisitor.visitInsn(POP);
methodVisitor.visitVarInsn(ALOAD, 0);
methodVisitor.visitLdcInsn("[^\\u0009-\\u000D\\u0020\\u0085\\u00A0\\u1680\\u180E\\u2000-\\u200A\\u2028\\u2029\\u202F\\u205F\\u3000]");
methodVisitor.visitIntInsn(BIPUSH, 16);
methodVisitor.visitMethodInsn(INVOKESTATIC, "java/util/regex/Pattern", "compile", "(Ljava/lang/String;I)Ljava/util/regex/Pattern;", false);
methodVisitor.visitLdcInsn("\\\\S");
methodVisitor.visitMethodInsn(INVOKEVIRTUAL, "org/eclipse/persistence/jaxb/compiler/SchemaGenerator$RegexMutator$1", "put", "(Ljava/lang/Object;Ljava/lang/Object;)Ljava/lang/Object;", false);
methodVisitor.visitInsn(POP);
methodVisitor.visitVarInsn(ALOAD, 0);
methodVisitor.visitLdcInsn("[\\u000A-\\u000D\\u0085\\u2028\\u2029]");
methodVisitor.visitIntInsn(BIPUSH, 16);
methodVisitor.visitMethodInsn(INVOKESTATIC, "java/util/regex/Pattern", "compile", "(Ljava/lang/String;I)Ljava/util/regex/Pattern;", false);
methodVisitor.visitLdcInsn("\\\\v");
methodVisitor.visitMethodInsn(INVOKEVIRTUAL, "org/eclipse/persistence/jaxb/compiler/SchemaGenerator$RegexMutator$1", "put", "(Ljava/lang/Object;Ljava/lang/Object;)Ljava/lang/Object;", false);
methodVisitor.visitInsn(POP);
methodVisitor.visitVarInsn(ALOAD, 0);
methodVisitor.visitLdcInsn("[^\\u000A-\\u000D\\u0085\\u2028\\u2029]");
methodVisitor.visitIntInsn(BIPUSH, 16);
methodVisitor.visitMethodInsn(INVOKESTATIC, "java/util/regex/Pattern", "compile", "(Ljava/lang/String;I)Ljava/util/regex/Pattern;", false);
methodVisitor.visitLdcInsn("\\\\V");
methodVisitor.visitMethodInsn(INVOKEVIRTUAL, "org/eclipse/persistence/jaxb/compiler/SchemaGenerator$RegexMutator$1", "put", "(Ljava/lang/Object;Ljava/lang/Object;)Ljava/lang/Object;", false);
methodVisitor.visitInsn(POP);
methodVisitor.visitVarInsn(ALOAD, 0);
methodVisitor.visitLdcInsn("[\\u0009\\u0020\\u00A0\\u1680\\u180E\\u2000-\\u200A\\u202F\\u205F\\u3000]");
methodVisitor.visitIntInsn(BIPUSH, 16);
methodVisitor.visitMethodInsn(INVOKESTATIC, "java/util/regex/Pattern", "compile", "(Ljava/lang/String;I)Ljava/util/regex/Pattern;", false);
methodVisitor.visitLdcInsn("\\\\h");
methodVisitor.visitMethodInsn(INVOKEVIRTUAL, "org/eclipse/persistence/jaxb/compiler/SchemaGenerator$RegexMutator$1", "put", "(Ljava/lang/Object;Ljava/lang/Object;)Ljava/lang/Object;", false);
methodVisitor.visitInsn(POP);
methodVisitor.visitVarInsn(ALOAD, 0);
methodVisitor.visitLdcInsn("[^\\u0009\\u0020\\u00A0\\u1680\\u180E\\u2000\\u2001-\\u200A\\u202F\\u205F\\u3000]");
methodVisitor.visitIntInsn(BIPUSH, 16);
methodVisitor.visitMethodInsn(INVOKESTATIC, "java/util/regex/Pattern", "compile", "(Ljava/lang/String;I)Ljava/util/regex/Pattern;", false);
methodVisitor.visitLdcInsn("\\\\H");
methodVisitor.visitMethodInsn(INVOKEVIRTUAL, "org/eclipse/persistence/jaxb/compiler/SchemaGenerator$RegexMutator$1", "put", "(Ljava/lang/Object;Ljava/lang/Object;)Ljava/lang/Object;", false);
methodVisitor.visitInsn(POP);
methodVisitor.visitVarInsn(ALOAD, 0);
methodVisitor.visitLdcInsn("[\\pL\\pM\\p{Nd}\\p{Nl}\\p{Pc}[\\p{InEnclosedAlphanumerics}&&\\p{So}]]");
methodVisitor.visitIntInsn(BIPUSH, 16);
methodVisitor.visitMethodInsn(INVOKESTATIC, "java/util/regex/Pattern", "compile", "(Ljava/lang/String;I)Ljava/util/regex/Pattern;", false);
methodVisitor.visitLdcInsn("\\\\w");
methodVisitor.visitMethodInsn(INVOKEVIRTUAL, "org/eclipse/persistence/jaxb/compiler/SchemaGenerator$RegexMutator$1", "put", "(Ljava/lang/Object;Ljava/lang/Object;)Ljava/lang/Object;", false);
methodVisitor.visitInsn(POP);
methodVisitor.visitVarInsn(ALOAD, 0);
methodVisitor.visitLdcInsn("[^\\pL\\pM\\p{Nd}\\p{Nl}\\p{Pc}[\\p{InEnclosedAlphanumerics}&&\\p{So}]]");
methodVisitor.visitIntInsn(BIPUSH, 16);
methodVisitor.visitMethodInsn(INVOKESTATIC, "java/util/regex/Pattern", "compile", "(Ljava/lang/String;I)Ljava/util/regex/Pattern;", false);
methodVisitor.visitLdcInsn("\\\\W");
methodVisitor.visitMethodInsn(INVOKEVIRTUAL, "org/eclipse/persistence/jaxb/compiler/SchemaGenerator$RegexMutator$1", "put", "(Ljava/lang/Object;Ljava/lang/Object;)Ljava/lang/Object;", false);
methodVisitor.visitInsn(POP);
methodVisitor.visitVarInsn(ALOAD, 0);
methodVisitor.visitLdcInsn("(?:(?<=[\\pL\\pM\\p{Nd}\\p{Nl}\\p{Pc}[\\p{InEnclosedAlphanumerics}&&\\p{So}]])(?![\\pL\\pM\\p{Nd}\\p{Nl}\\p{Pc}[\\p{InEnclosedAlphanumerics}&&\\p{So}]])|(?<![\\pL\\pM\\p{Nd}\\p{Nl}\\p{Pc}[\\p{InEnclosedAlphanumerics}&&\\p{So}]])(?=[\\pL\\pM\\p{Nd}\\p{Nl}\\p{Pc}[\\p{InEnclosedAlphanumerics}&&\\p{So}]]))");
methodVisitor.visitIntInsn(BIPUSH, 16);
methodVisitor.visitMethodInsn(INVOKESTATIC, "java/util/regex/Pattern", "compile", "(Ljava/lang/String;I)Ljava/util/regex/Pattern;", false);
methodVisitor.visitLdcInsn("\\\\b");
methodVisitor.visitMethodInsn(INVOKEVIRTUAL, "org/eclipse/persistence/jaxb/compiler/SchemaGenerator$RegexMutator$1", "put", "(Ljava/lang/Object;Ljava/lang/Object;)Ljava/lang/Object;", false);
methodVisitor.visitInsn(POP);
methodVisitor.visitVarInsn(ALOAD, 0);
methodVisitor.visitLdcInsn("(?:(?<=[\\pL\\pM\\p{Nd}\\p{Nl}\\p{Pc}[\\p{InEnclosedAlphanumerics}&&\\p{So}]])(?=[\\pL\\pM\\p{Nd}\\p{Nl}\\p{Pc}[\\p{InEnclosedAlphanumerics}&&\\p{So}]])|(?<![\\pL\\pM\\p{Nd}\\p{Nl}\\p{Pc}[\\p{InEnclosedAlphanumerics}&&\\p{So}]])(?![\\pL\\pM\\p{Nd}\\p{Nl}\\p{Pc}[\\p{InEnclosedAlphanumerics}&&\\p{So}]]))");
methodVisitor.visitIntInsn(BIPUSH, 16);
methodVisitor.visitMethodInsn(INVOKESTATIC, "java/util/regex/Pattern", "compile", "(Ljava/lang/String;I)Ljava/util/regex/Pattern;", false);
methodVisitor.visitLdcInsn("\\\\B");
methodVisitor.visitMethodInsn(INVOKEVIRTUAL, "org/eclipse/persistence/jaxb/compiler/SchemaGenerator$RegexMutator$1", "put", "(Ljava/lang/Object;Ljava/lang/Object;)Ljava/lang/Object;", false);
methodVisitor.visitInsn(POP);
methodVisitor.visitVarInsn(ALOAD, 0);
methodVisitor.visitLdcInsn("\\p{Nd}");
methodVisitor.visitIntInsn(BIPUSH, 16);
methodVisitor.visitMethodInsn(INVOKESTATIC, "java/util/regex/Pattern", "compile", "(Ljava/lang/String;I)Ljava/util/regex/Pattern;", false);
methodVisitor.visitLdcInsn("\\\\d");
methodVisitor.visitMethodInsn(INVOKEVIRTUAL, "org/eclipse/persistence/jaxb/compiler/SchemaGenerator$RegexMutator$1", "put", "(Ljava/lang/Object;Ljava/lang/Object;)Ljava/lang/Object;", false);
methodVisitor.visitInsn(POP);
methodVisitor.visitVarInsn(ALOAD, 0);
methodVisitor.visitLdcInsn("\\P{Nd}");
methodVisitor.visitIntInsn(BIPUSH, 16);
methodVisitor.visitMethodInsn(INVOKESTATIC, "java/util/regex/Pattern", "compile", "(Ljava/lang/String;I)Ljava/util/regex/Pattern;", false);
methodVisitor.visitLdcInsn("\\\\D");
methodVisitor.visitMethodInsn(INVOKEVIRTUAL, "org/eclipse/persistence/jaxb/compiler/SchemaGenerator$RegexMutator$1", "put", "(Ljava/lang/Object;Ljava/lang/Object;)Ljava/lang/Object;", false);
methodVisitor.visitInsn(POP);
methodVisitor.visitVarInsn(ALOAD, 0);
methodVisitor.visitLdcInsn("(?:(?>\\u000D\\u000A)|[\\u000A\\u000B\\u000C\\u000D\\u0085\\u2028\\u2029])");
methodVisitor.visitIntInsn(BIPUSH, 16);
methodVisitor.visitMethodInsn(INVOKESTATIC, "java/util/regex/Pattern", "compile", "(Ljava/lang/String;I)Ljava/util/regex/Pattern;", false);
methodVisitor.visitLdcInsn("\\\\R");
methodVisitor.visitMethodInsn(INVOKEVIRTUAL, "org/eclipse/persistence/jaxb/compiler/SchemaGenerator$RegexMutator$1", "put", "(Ljava/lang/Object;Ljava/lang/Object;)Ljava/lang/Object;", false);
methodVisitor.visitInsn(POP);
methodVisitor.visitVarInsn(ALOAD, 0);
methodVisitor.visitLdcInsn("(?:(?:\\u000D\\u000A)|(?:[\\u0E40\\u0E41\\u0E42\\u0E43\\u0E44\\u0EC0\\u0EC1\\u0EC2\\u0EC3\\u0EC4\\uAAB5\\uAAB6\\uAAB9\\uAABB\\uAABC]*(?:[\\u1100-\\u115F\\uA960-\\uA97C]+|([\\u1100-\\u115F\\uA960-\\uA97C]*((?:[[\\u1160-\\u11A2\\uD7B0-\\uD7C6][\\uAC00\\uAC1C\\uAC38]][\\u1160-\\u11A2\\uD7B0-\\uD7C6]*|[\\uAC01\\uAC02\\uAC03\\uAC04])[\\u11A8-\\u11F9\\uD7CB-\\uD7FB]*))|[\\u11A8-\\u11F9\\uD7CB-\\uD7FB]+|[^[\\p{Zl}\\p{Zp}\\p{Cc}\\p{Cf}&&[^\\u000D\\u000A\\u200C\\u200D]]\\u000D\\u000A])[[\\p{Mn}\\p{Me}\\u200C\\u200D\\u0488\\u0489\\u20DD\\u20DE\\u20DF\\u20E0\\u20E2\\u20E3\\u20E4\\uA670\\uA671\\uA672\\uFF9E\\uFF9F][\\p{Mc}\\u0E30\\u0E32\\u0E33\\u0E45\\u0EB0\\u0EB2\\u0EB3]]*)|(?s:.))");
methodVisitor.visitIntInsn(BIPUSH, 16);
methodVisitor.visitMethodInsn(INVOKESTATIC, "java/util/regex/Pattern", "compile", "(Ljava/lang/String;I)Ljava/util/regex/Pattern;", false);
methodVisitor.visitLdcInsn("\\\\X");
methodVisitor.visitMethodInsn(INVOKEVIRTUAL, "org/eclipse/persistence/jaxb/compiler/SchemaGenerator$RegexMutator$1", "put", "(Ljava/lang/Object;Ljava/lang/Object;)Ljava/lang/Object;", false);
methodVisitor.visitInsn(POP);
methodVisitor.visitVarInsn(ALOAD, 0);
methodVisitor.visitLdcInsn("[_:A-Za-z]");
methodVisitor.visitIntInsn(BIPUSH, 16);
methodVisitor.visitMethodInsn(INVOKESTATIC, "java/util/regex/Pattern", "compile", "(Ljava/lang/String;I)Ljava/util/regex/Pattern;", false);
methodVisitor.visitLdcInsn("\\\\i");
methodVisitor.visitMethodInsn(INVOKEVIRTUAL, "org/eclipse/persistence/jaxb/compiler/SchemaGenerator$RegexMutator$1", "put", "(Ljava/lang/Object;Ljava/lang/Object;)Ljava/lang/Object;", false);
methodVisitor.visitInsn(POP);
methodVisitor.visitVarInsn(ALOAD, 0);
methodVisitor.visitLdcInsn("[^:A-Z_a-z]");
methodVisitor.visitIntInsn(BIPUSH, 16);
methodVisitor.visitMethodInsn(INVOKESTATIC, "java/util/regex/Pattern", "compile", "(Ljava/lang/String;I)Ljava/util/regex/Pattern;", false);
methodVisitor.visitLdcInsn("\\\\I");
methodVisitor.visitMethodInsn(INVOKEVIRTUAL, "org/eclipse/persistence/jaxb/compiler/SchemaGenerator$RegexMutator$1", "put", "(Ljava/lang/Object;Ljava/lang/Object;)Ljava/lang/Object;", false);
methodVisitor.visitInsn(POP);
methodVisitor.visitVarInsn(ALOAD, 0);
methodVisitor.visitLdcInsn("[-.0-9:A-Z_a-z]");
methodVisitor.visitIntInsn(BIPUSH, 16);
methodVisitor.visitMethodInsn(INVOKESTATIC, "java/util/regex/Pattern", "compile", "(Ljava/lang/String;I)Ljava/util/regex/Pattern;", false);
methodVisitor.visitLdcInsn("\\\\c");
methodVisitor.visitMethodInsn(INVOKEVIRTUAL, "org/eclipse/persistence/jaxb/compiler/SchemaGenerator$RegexMutator$1", "put", "(Ljava/lang/Object;Ljava/lang/Object;)Ljava/lang/Object;", false);
methodVisitor.visitInsn(POP);
methodVisitor.visitVarInsn(ALOAD, 0);
methodVisitor.visitLdcInsn("[^-.0-9:A-Z_a-z]");
methodVisitor.visitIntInsn(BIPUSH, 16);
methodVisitor.visitMethodInsn(INVOKESTATIC, "java/util/regex/Pattern", "compile", "(Ljava/lang/String;I)Ljava/util/regex/Pattern;", false);
methodVisitor.visitLdcInsn("\\\\C");
methodVisitor.visitMethodInsn(INVOKEVIRTUAL, "org/eclipse/persistence/jaxb/compiler/SchemaGenerator$RegexMutator$1", "put", "(Ljava/lang/Object;Ljava/lang/Object;)Ljava/lang/Object;", false);
methodVisitor.visitInsn(POP);
methodVisitor.visitInsn(RETURN);
methodVisitor.visitMaxs(3, 2);
methodVisitor.visitEnd();
}
classWriter.visitEnd();

return classWriter.toByteArray();
}
}
