package asm.org.bouncycastle.asn1.ua;
import org.objectweb.asm.AnnotationVisitor;
import org.objectweb.asm.Attribute;
import org.objectweb.asm.ClassReader;
import org.objectweb.asm.ClassWriter;
import org.objectweb.asm.ConstantDynamic;
import org.objectweb.asm.FieldVisitor;
import org.objectweb.asm.Handle;
import org.objectweb.asm.Label;
import org.objectweb.asm.MethodVisitor;
import org.objectweb.asm.Opcodes;
import org.objectweb.asm.RecordComponentVisitor;
import org.objectweb.asm.Type;
import org.objectweb.asm.TypePath;
public class DSTU4145NamedCurvesDump implements Opcodes {

public static byte[] dump () throws Exception {

ClassWriter classWriter = new ClassWriter(0);
FieldVisitor fieldVisitor;
RecordComponentVisitor recordComponentVisitor;
MethodVisitor methodVisitor;
AnnotationVisitor annotationVisitor0;

classWriter.visit(V1_5, ACC_PUBLIC | ACC_SUPER, "org/bouncycastle/asn1/ua/DSTU4145NamedCurves", null, "java/lang/Object", null);

classWriter.visitInnerClass("org/bouncycastle/math/ec/ECCurve$F2m", "org/bouncycastle/math/ec/ECCurve", "F2m", ACC_PUBLIC | ACC_STATIC);

{
fieldVisitor = classWriter.visitField(ACC_PRIVATE | ACC_FINAL | ACC_STATIC, "ZERO", "Ljava/math/BigInteger;", null, null);
fieldVisitor.visitEnd();
}
{
fieldVisitor = classWriter.visitField(ACC_PRIVATE | ACC_FINAL | ACC_STATIC, "ONE", "Ljava/math/BigInteger;", null, null);
fieldVisitor.visitEnd();
}
{
fieldVisitor = classWriter.visitField(ACC_FINAL | ACC_STATIC, "params", "[Lorg/bouncycastle/crypto/params/ECDomainParameters;", null, null);
fieldVisitor.visitEnd();
}
{
fieldVisitor = classWriter.visitField(ACC_FINAL | ACC_STATIC, "oids", "[Lorg/bouncycastle/asn1/ASN1ObjectIdentifier;", null, null);
fieldVisitor.visitEnd();
}
{
fieldVisitor = classWriter.visitField(ACC_FINAL | ACC_STATIC, "oidBase", "Ljava/lang/String;", null, null);
fieldVisitor.visitEnd();
}
{
methodVisitor = classWriter.visitMethod(ACC_PUBLIC, "<init>", "()V", null, null);
methodVisitor.visitCode();
methodVisitor.visitVarInsn(ALOAD, 0);
methodVisitor.visitMethodInsn(INVOKESPECIAL, "java/lang/Object", "<init>", "()V", false);
methodVisitor.visitInsn(RETURN);
methodVisitor.visitMaxs(1, 1);
methodVisitor.visitEnd();
}
{
methodVisitor = classWriter.visitMethod(ACC_PUBLIC | ACC_STATIC, "getOIDs", "()[Lorg/bouncycastle/asn1/ASN1ObjectIdentifier;", null, null);
methodVisitor.visitCode();
methodVisitor.visitFieldInsn(GETSTATIC, "org/bouncycastle/asn1/ua/DSTU4145NamedCurves", "oids", "[Lorg/bouncycastle/asn1/ASN1ObjectIdentifier;");
methodVisitor.visitInsn(ARETURN);
methodVisitor.visitMaxs(1, 0);
methodVisitor.visitEnd();
}
{
methodVisitor = classWriter.visitMethod(ACC_PUBLIC | ACC_STATIC, "getByOID", "(Lorg/bouncycastle/asn1/ASN1ObjectIdentifier;)Lorg/bouncycastle/crypto/params/ECDomainParameters;", null, null);
methodVisitor.visitCode();
methodVisitor.visitVarInsn(ALOAD, 0);
methodVisitor.visitMethodInsn(INVOKEVIRTUAL, "org/bouncycastle/asn1/ASN1ObjectIdentifier", "getId", "()Ljava/lang/String;", false);
methodVisitor.visitVarInsn(ASTORE, 1);
methodVisitor.visitVarInsn(ALOAD, 1);
methodVisitor.visitFieldInsn(GETSTATIC, "org/bouncycastle/asn1/ua/DSTU4145NamedCurves", "oidBase", "Ljava/lang/String;");
methodVisitor.visitMethodInsn(INVOKEVIRTUAL, "java/lang/String", "startsWith", "(Ljava/lang/String;)Z", false);
Label label0 = new Label();
methodVisitor.visitJumpInsn(IFEQ, label0);
methodVisitor.visitVarInsn(ALOAD, 1);
methodVisitor.visitVarInsn(ALOAD, 1);
methodVisitor.visitIntInsn(BIPUSH, 46);
methodVisitor.visitMethodInsn(INVOKEVIRTUAL, "java/lang/String", "lastIndexOf", "(I)I", false);
methodVisitor.visitInsn(ICONST_1);
methodVisitor.visitInsn(IADD);
methodVisitor.visitMethodInsn(INVOKEVIRTUAL, "java/lang/String", "substring", "(I)Ljava/lang/String;", false);
methodVisitor.visitMethodInsn(INVOKESTATIC, "java/lang/Integer", "parseInt", "(Ljava/lang/String;)I", false);
methodVisitor.visitVarInsn(ISTORE, 2);
methodVisitor.visitVarInsn(ILOAD, 2);
Label label1 = new Label();
methodVisitor.visitJumpInsn(IFLT, label1);
methodVisitor.visitVarInsn(ILOAD, 2);
methodVisitor.visitFieldInsn(GETSTATIC, "org/bouncycastle/asn1/ua/DSTU4145NamedCurves", "params", "[Lorg/bouncycastle/crypto/params/ECDomainParameters;");
methodVisitor.visitInsn(ARRAYLENGTH);
methodVisitor.visitJumpInsn(IF_ICMPGE, label1);
methodVisitor.visitFieldInsn(GETSTATIC, "org/bouncycastle/asn1/ua/DSTU4145NamedCurves", "params", "[Lorg/bouncycastle/crypto/params/ECDomainParameters;");
methodVisitor.visitVarInsn(ILOAD, 2);
methodVisitor.visitInsn(AALOAD);
Label label2 = new Label();
methodVisitor.visitJumpInsn(GOTO, label2);
methodVisitor.visitLabel(label1);
methodVisitor.visitInsn(ACONST_NULL);
methodVisitor.visitLabel(label2);
methodVisitor.visitInsn(ARETURN);
methodVisitor.visitLabel(label0);
methodVisitor.visitInsn(ACONST_NULL);
methodVisitor.visitInsn(ARETURN);
methodVisitor.visitMaxs(3, 3);
methodVisitor.visitEnd();
}
{
methodVisitor = classWriter.visitMethod(ACC_STATIC, "<clinit>", "()V", null, null);
methodVisitor.visitCode();
methodVisitor.visitInsn(LCONST_0);
methodVisitor.visitMethodInsn(INVOKESTATIC, "java/math/BigInteger", "valueOf", "(J)Ljava/math/BigInteger;", false);
methodVisitor.visitFieldInsn(PUTSTATIC, "org/bouncycastle/asn1/ua/DSTU4145NamedCurves", "ZERO", "Ljava/math/BigInteger;");
methodVisitor.visitInsn(LCONST_1);
methodVisitor.visitMethodInsn(INVOKESTATIC, "java/math/BigInteger", "valueOf", "(J)Ljava/math/BigInteger;", false);
methodVisitor.visitFieldInsn(PUTSTATIC, "org/bouncycastle/asn1/ua/DSTU4145NamedCurves", "ONE", "Ljava/math/BigInteger;");
methodVisitor.visitIntInsn(BIPUSH, 10);
methodVisitor.visitTypeInsn(ANEWARRAY, "org/bouncycastle/crypto/params/ECDomainParameters");
methodVisitor.visitFieldInsn(PUTSTATIC, "org/bouncycastle/asn1/ua/DSTU4145NamedCurves", "params", "[Lorg/bouncycastle/crypto/params/ECDomainParameters;");
methodVisitor.visitIntInsn(BIPUSH, 10);
methodVisitor.visitTypeInsn(ANEWARRAY, "org/bouncycastle/asn1/ASN1ObjectIdentifier");
methodVisitor.visitFieldInsn(PUTSTATIC, "org/bouncycastle/asn1/ua/DSTU4145NamedCurves", "oids", "[Lorg/bouncycastle/asn1/ASN1ObjectIdentifier;");
methodVisitor.visitTypeInsn(NEW, "java/lang/StringBuilder");
methodVisitor.visitInsn(DUP);
methodVisitor.visitMethodInsn(INVOKESPECIAL, "java/lang/StringBuilder", "<init>", "()V", false);
methodVisitor.visitFieldInsn(GETSTATIC, "org/bouncycastle/asn1/ua/UAObjectIdentifiers", "dstu4145le", "Lorg/bouncycastle/asn1/ASN1ObjectIdentifier;");
methodVisitor.visitMethodInsn(INVOKEVIRTUAL, "org/bouncycastle/asn1/ASN1ObjectIdentifier", "getId", "()Ljava/lang/String;", false);
methodVisitor.visitMethodInsn(INVOKEVIRTUAL, "java/lang/StringBuilder", "append", "(Ljava/lang/String;)Ljava/lang/StringBuilder;", false);
methodVisitor.visitLdcInsn(".2.");
methodVisitor.visitMethodInsn(INVOKEVIRTUAL, "java/lang/StringBuilder", "append", "(Ljava/lang/String;)Ljava/lang/StringBuilder;", false);
methodVisitor.visitMethodInsn(INVOKEVIRTUAL, "java/lang/StringBuilder", "toString", "()Ljava/lang/String;", false);
methodVisitor.visitFieldInsn(PUTSTATIC, "org/bouncycastle/asn1/ua/DSTU4145NamedCurves", "oidBase", "Ljava/lang/String;");
methodVisitor.visitIntInsn(BIPUSH, 10);
methodVisitor.visitTypeInsn(ANEWARRAY, "java/math/BigInteger");
methodVisitor.visitVarInsn(ASTORE, 0);
methodVisitor.visitVarInsn(ALOAD, 0);
methodVisitor.visitInsn(ICONST_0);
methodVisitor.visitTypeInsn(NEW, "java/math/BigInteger");
methodVisitor.visitInsn(DUP);
methodVisitor.visitLdcInsn("400000000000000000002BEC12BE2262D39BCF14D");
methodVisitor.visitIntInsn(BIPUSH, 16);
methodVisitor.visitMethodInsn(INVOKESPECIAL, "java/math/BigInteger", "<init>", "(Ljava/lang/String;I)V", false);
methodVisitor.visitInsn(AASTORE);
methodVisitor.visitVarInsn(ALOAD, 0);
methodVisitor.visitInsn(ICONST_1);
methodVisitor.visitTypeInsn(NEW, "java/math/BigInteger");
methodVisitor.visitInsn(DUP);
methodVisitor.visitLdcInsn("3FFFFFFFFFFFFFFFFFFFFFB12EBCC7D7F29FF7701F");
methodVisitor.visitIntInsn(BIPUSH, 16);
methodVisitor.visitMethodInsn(INVOKESPECIAL, "java/math/BigInteger", "<init>", "(Ljava/lang/String;I)V", false);
methodVisitor.visitInsn(AASTORE);
methodVisitor.visitVarInsn(ALOAD, 0);
methodVisitor.visitInsn(ICONST_2);
methodVisitor.visitTypeInsn(NEW, "java/math/BigInteger");
methodVisitor.visitInsn(DUP);
methodVisitor.visitLdcInsn("800000000000000000000189B4E67606E3825BB2831");
methodVisitor.visitIntInsn(BIPUSH, 16);
methodVisitor.visitMethodInsn(INVOKESPECIAL, "java/math/BigInteger", "<init>", "(Ljava/lang/String;I)V", false);
methodVisitor.visitInsn(AASTORE);
methodVisitor.visitVarInsn(ALOAD, 0);
methodVisitor.visitInsn(ICONST_3);
methodVisitor.visitTypeInsn(NEW, "java/math/BigInteger");
methodVisitor.visitInsn(DUP);
methodVisitor.visitLdcInsn("3FFFFFFFFFFFFFFFFFFFFFFB981960435FE5AB64236EF");
methodVisitor.visitIntInsn(BIPUSH, 16);
methodVisitor.visitMethodInsn(INVOKESPECIAL, "java/math/BigInteger", "<init>", "(Ljava/lang/String;I)V", false);
methodVisitor.visitInsn(AASTORE);
methodVisitor.visitVarInsn(ALOAD, 0);
methodVisitor.visitInsn(ICONST_4);
methodVisitor.visitTypeInsn(NEW, "java/math/BigInteger");
methodVisitor.visitInsn(DUP);
methodVisitor.visitLdcInsn("40000000000000000000000069A779CAC1DABC6788F7474F");
methodVisitor.visitIntInsn(BIPUSH, 16);
methodVisitor.visitMethodInsn(INVOKESPECIAL, "java/math/BigInteger", "<init>", "(Ljava/lang/String;I)V", false);
methodVisitor.visitInsn(AASTORE);
methodVisitor.visitVarInsn(ALOAD, 0);
methodVisitor.visitInsn(ICONST_5);
methodVisitor.visitTypeInsn(NEW, "java/math/BigInteger");
methodVisitor.visitInsn(DUP);
methodVisitor.visitLdcInsn("1000000000000000000000000000013E974E72F8A6922031D2603CFE0D7");
methodVisitor.visitIntInsn(BIPUSH, 16);
methodVisitor.visitMethodInsn(INVOKESPECIAL, "java/math/BigInteger", "<init>", "(Ljava/lang/String;I)V", false);
methodVisitor.visitInsn(AASTORE);
methodVisitor.visitVarInsn(ALOAD, 0);
methodVisitor.visitIntInsn(BIPUSH, 6);
methodVisitor.visitTypeInsn(NEW, "java/math/BigInteger");
methodVisitor.visitInsn(DUP);
methodVisitor.visitLdcInsn("800000000000000000000000000000006759213AF182E987D3E17714907D470D");
methodVisitor.visitIntInsn(BIPUSH, 16);
methodVisitor.visitMethodInsn(INVOKESPECIAL, "java/math/BigInteger", "<init>", "(Ljava/lang/String;I)V", false);
methodVisitor.visitInsn(AASTORE);
methodVisitor.visitVarInsn(ALOAD, 0);
methodVisitor.visitIntInsn(BIPUSH, 7);
methodVisitor.visitTypeInsn(NEW, "java/math/BigInteger");
methodVisitor.visitInsn(DUP);
methodVisitor.visitLdcInsn("3FFFFFFFFFFFFFFFFFFFFFFFFFFFFFFFFFFFFFFC079C2F3825DA70D390FBBA588D4604022B7B7");
methodVisitor.visitIntInsn(BIPUSH, 16);
methodVisitor.visitMethodInsn(INVOKESPECIAL, "java/math/BigInteger", "<init>", "(Ljava/lang/String;I)V", false);
methodVisitor.visitInsn(AASTORE);
methodVisitor.visitVarInsn(ALOAD, 0);
methodVisitor.visitIntInsn(BIPUSH, 8);
methodVisitor.visitTypeInsn(NEW, "java/math/BigInteger");
methodVisitor.visitInsn(DUP);
methodVisitor.visitLdcInsn("40000000000000000000000000000000000000000000009C300B75A3FA824F22428FD28CE8812245EF44049B2D49");
methodVisitor.visitIntInsn(BIPUSH, 16);
methodVisitor.visitMethodInsn(INVOKESPECIAL, "java/math/BigInteger", "<init>", "(Ljava/lang/String;I)V", false);
methodVisitor.visitInsn(AASTORE);
methodVisitor.visitVarInsn(ALOAD, 0);
methodVisitor.visitIntInsn(BIPUSH, 9);
methodVisitor.visitTypeInsn(NEW, "java/math/BigInteger");
methodVisitor.visitInsn(DUP);
methodVisitor.visitLdcInsn("3FFFFFFFFFFFFFFFFFFFFFFFFFFFFFFFFFFFFFFFFFFFFFFFFFFFFFBA3175458009A8C0A724F02F81AA8A1FCBAF80D90C7A95110504CF");
methodVisitor.visitIntInsn(BIPUSH, 16);
methodVisitor.visitMethodInsn(INVOKESPECIAL, "java/math/BigInteger", "<init>", "(Ljava/lang/String;I)V", false);
methodVisitor.visitInsn(AASTORE);
methodVisitor.visitIntInsn(BIPUSH, 10);
methodVisitor.visitTypeInsn(ANEWARRAY, "java/math/BigInteger");
methodVisitor.visitVarInsn(ASTORE, 1);
methodVisitor.visitVarInsn(ALOAD, 1);
methodVisitor.visitInsn(ICONST_0);
methodVisitor.visitLdcInsn(new Long(2L));
methodVisitor.visitMethodInsn(INVOKESTATIC, "java/math/BigInteger", "valueOf", "(J)Ljava/math/BigInteger;", false);
methodVisitor.visitInsn(AASTORE);
methodVisitor.visitVarInsn(ALOAD, 1);
methodVisitor.visitInsn(ICONST_1);
methodVisitor.visitLdcInsn(new Long(2L));
methodVisitor.visitMethodInsn(INVOKESTATIC, "java/math/BigInteger", "valueOf", "(J)Ljava/math/BigInteger;", false);
methodVisitor.visitInsn(AASTORE);
methodVisitor.visitVarInsn(ALOAD, 1);
methodVisitor.visitInsn(ICONST_2);
methodVisitor.visitLdcInsn(new Long(4L));
methodVisitor.visitMethodInsn(INVOKESTATIC, "java/math/BigInteger", "valueOf", "(J)Ljava/math/BigInteger;", false);
methodVisitor.visitInsn(AASTORE);
methodVisitor.visitVarInsn(ALOAD, 1);
methodVisitor.visitInsn(ICONST_3);
methodVisitor.visitLdcInsn(new Long(2L));
methodVisitor.visitMethodInsn(INVOKESTATIC, "java/math/BigInteger", "valueOf", "(J)Ljava/math/BigInteger;", false);
methodVisitor.visitInsn(AASTORE);
methodVisitor.visitVarInsn(ALOAD, 1);
methodVisitor.visitInsn(ICONST_4);
methodVisitor.visitLdcInsn(new Long(2L));
methodVisitor.visitMethodInsn(INVOKESTATIC, "java/math/BigInteger", "valueOf", "(J)Ljava/math/BigInteger;", false);
methodVisitor.visitInsn(AASTORE);
methodVisitor.visitVarInsn(ALOAD, 1);
methodVisitor.visitInsn(ICONST_5);
methodVisitor.visitLdcInsn(new Long(2L));
methodVisitor.visitMethodInsn(INVOKESTATIC, "java/math/BigInteger", "valueOf", "(J)Ljava/math/BigInteger;", false);
methodVisitor.visitInsn(AASTORE);
methodVisitor.visitVarInsn(ALOAD, 1);
methodVisitor.visitIntInsn(BIPUSH, 6);
methodVisitor.visitLdcInsn(new Long(4L));
methodVisitor.visitMethodInsn(INVOKESTATIC, "java/math/BigInteger", "valueOf", "(J)Ljava/math/BigInteger;", false);
methodVisitor.visitInsn(AASTORE);
methodVisitor.visitVarInsn(ALOAD, 1);
methodVisitor.visitIntInsn(BIPUSH, 7);
methodVisitor.visitLdcInsn(new Long(2L));
methodVisitor.visitMethodInsn(INVOKESTATIC, "java/math/BigInteger", "valueOf", "(J)Ljava/math/BigInteger;", false);
methodVisitor.visitInsn(AASTORE);
methodVisitor.visitVarInsn(ALOAD, 1);
methodVisitor.visitIntInsn(BIPUSH, 8);
methodVisitor.visitLdcInsn(new Long(2L));
methodVisitor.visitMethodInsn(INVOKESTATIC, "java/math/BigInteger", "valueOf", "(J)Ljava/math/BigInteger;", false);
methodVisitor.visitInsn(AASTORE);
methodVisitor.visitVarInsn(ALOAD, 1);
methodVisitor.visitIntInsn(BIPUSH, 9);
methodVisitor.visitLdcInsn(new Long(2L));
methodVisitor.visitMethodInsn(INVOKESTATIC, "java/math/BigInteger", "valueOf", "(J)Ljava/math/BigInteger;", false);
methodVisitor.visitInsn(AASTORE);
methodVisitor.visitIntInsn(BIPUSH, 10);
methodVisitor.visitTypeInsn(ANEWARRAY, "org/bouncycastle/math/ec/ECCurve$F2m");
methodVisitor.visitVarInsn(ASTORE, 2);
methodVisitor.visitVarInsn(ALOAD, 2);
methodVisitor.visitInsn(ICONST_0);
methodVisitor.visitTypeInsn(NEW, "org/bouncycastle/math/ec/ECCurve$F2m");
methodVisitor.visitInsn(DUP);
methodVisitor.visitIntInsn(SIPUSH, 163);
methodVisitor.visitInsn(ICONST_3);
methodVisitor.visitIntInsn(BIPUSH, 6);
methodVisitor.visitIntInsn(BIPUSH, 7);
methodVisitor.visitFieldInsn(GETSTATIC, "org/bouncycastle/asn1/ua/DSTU4145NamedCurves", "ONE", "Ljava/math/BigInteger;");
methodVisitor.visitTypeInsn(NEW, "java/math/BigInteger");
methodVisitor.visitInsn(DUP);
methodVisitor.visitLdcInsn("5FF6108462A2DC8210AB403925E638A19C1455D21");
methodVisitor.visitIntInsn(BIPUSH, 16);
methodVisitor.visitMethodInsn(INVOKESPECIAL, "java/math/BigInteger", "<init>", "(Ljava/lang/String;I)V", false);
methodVisitor.visitVarInsn(ALOAD, 0);
methodVisitor.visitInsn(ICONST_0);
methodVisitor.visitInsn(AALOAD);
methodVisitor.visitVarInsn(ALOAD, 1);
methodVisitor.visitInsn(ICONST_0);
methodVisitor.visitInsn(AALOAD);
methodVisitor.visitMethodInsn(INVOKESPECIAL, "org/bouncycastle/math/ec/ECCurve$F2m", "<init>", "(IIIILjava/math/BigInteger;Ljava/math/BigInteger;Ljava/math/BigInteger;Ljava/math/BigInteger;)V", false);
methodVisitor.visitInsn(AASTORE);
methodVisitor.visitVarInsn(ALOAD, 2);
methodVisitor.visitInsn(ICONST_1);
methodVisitor.visitTypeInsn(NEW, "org/bouncycastle/math/ec/ECCurve$F2m");
methodVisitor.visitInsn(DUP);
methodVisitor.visitIntInsn(SIPUSH, 167);
methodVisitor.visitIntInsn(BIPUSH, 6);
methodVisitor.visitFieldInsn(GETSTATIC, "org/bouncycastle/asn1/ua/DSTU4145NamedCurves", "ONE", "Ljava/math/BigInteger;");
methodVisitor.visitTypeInsn(NEW, "java/math/BigInteger");
methodVisitor.visitInsn(DUP);
methodVisitor.visitLdcInsn("6EE3CEEB230811759F20518A0930F1A4315A827DAC");
methodVisitor.visitIntInsn(BIPUSH, 16);
methodVisitor.visitMethodInsn(INVOKESPECIAL, "java/math/BigInteger", "<init>", "(Ljava/lang/String;I)V", false);
methodVisitor.visitVarInsn(ALOAD, 0);
methodVisitor.visitInsn(ICONST_1);
methodVisitor.visitInsn(AALOAD);
methodVisitor.visitVarInsn(ALOAD, 1);
methodVisitor.visitInsn(ICONST_1);
methodVisitor.visitInsn(AALOAD);
methodVisitor.visitMethodInsn(INVOKESPECIAL, "org/bouncycastle/math/ec/ECCurve$F2m", "<init>", "(IILjava/math/BigInteger;Ljava/math/BigInteger;Ljava/math/BigInteger;Ljava/math/BigInteger;)V", false);
methodVisitor.visitInsn(AASTORE);
methodVisitor.visitVarInsn(ALOAD, 2);
methodVisitor.visitInsn(ICONST_2);
methodVisitor.visitTypeInsn(NEW, "org/bouncycastle/math/ec/ECCurve$F2m");
methodVisitor.visitInsn(DUP);
methodVisitor.visitIntInsn(SIPUSH, 173);
methodVisitor.visitInsn(ICONST_1);
methodVisitor.visitInsn(ICONST_2);
methodVisitor.visitIntInsn(BIPUSH, 10);
methodVisitor.visitFieldInsn(GETSTATIC, "org/bouncycastle/asn1/ua/DSTU4145NamedCurves", "ZERO", "Ljava/math/BigInteger;");
methodVisitor.visitTypeInsn(NEW, "java/math/BigInteger");
methodVisitor.visitInsn(DUP);
methodVisitor.visitLdcInsn("108576C80499DB2FC16EDDF6853BBB278F6B6FB437D9");
methodVisitor.visitIntInsn(BIPUSH, 16);
methodVisitor.visitMethodInsn(INVOKESPECIAL, "java/math/BigInteger", "<init>", "(Ljava/lang/String;I)V", false);
methodVisitor.visitVarInsn(ALOAD, 0);
methodVisitor.visitInsn(ICONST_2);
methodVisitor.visitInsn(AALOAD);
methodVisitor.visitVarInsn(ALOAD, 1);
methodVisitor.visitInsn(ICONST_2);
methodVisitor.visitInsn(AALOAD);
methodVisitor.visitMethodInsn(INVOKESPECIAL, "org/bouncycastle/math/ec/ECCurve$F2m", "<init>", "(IIIILjava/math/BigInteger;Ljava/math/BigInteger;Ljava/math/BigInteger;Ljava/math/BigInteger;)V", false);
methodVisitor.visitInsn(AASTORE);
methodVisitor.visitVarInsn(ALOAD, 2);
methodVisitor.visitInsn(ICONST_3);
methodVisitor.visitTypeInsn(NEW, "org/bouncycastle/math/ec/ECCurve$F2m");
methodVisitor.visitInsn(DUP);
methodVisitor.visitIntInsn(SIPUSH, 179);
methodVisitor.visitInsn(ICONST_1);
methodVisitor.visitInsn(ICONST_2);
methodVisitor.visitInsn(ICONST_4);
methodVisitor.visitFieldInsn(GETSTATIC, "org/bouncycastle/asn1/ua/DSTU4145NamedCurves", "ONE", "Ljava/math/BigInteger;");
methodVisitor.visitTypeInsn(NEW, "java/math/BigInteger");
methodVisitor.visitInsn(DUP);
methodVisitor.visitLdcInsn("4A6E0856526436F2F88DD07A341E32D04184572BEB710");
methodVisitor.visitIntInsn(BIPUSH, 16);
methodVisitor.visitMethodInsn(INVOKESPECIAL, "java/math/BigInteger", "<init>", "(Ljava/lang/String;I)V", false);
methodVisitor.visitVarInsn(ALOAD, 0);
methodVisitor.visitInsn(ICONST_3);
methodVisitor.visitInsn(AALOAD);
methodVisitor.visitVarInsn(ALOAD, 1);
methodVisitor.visitInsn(ICONST_3);
methodVisitor.visitInsn(AALOAD);
methodVisitor.visitMethodInsn(INVOKESPECIAL, "org/bouncycastle/math/ec/ECCurve$F2m", "<init>", "(IIIILjava/math/BigInteger;Ljava/math/BigInteger;Ljava/math/BigInteger;Ljava/math/BigInteger;)V", false);
methodVisitor.visitInsn(AASTORE);
methodVisitor.visitVarInsn(ALOAD, 2);
methodVisitor.visitInsn(ICONST_4);
methodVisitor.visitTypeInsn(NEW, "org/bouncycastle/math/ec/ECCurve$F2m");
methodVisitor.visitInsn(DUP);
methodVisitor.visitIntInsn(SIPUSH, 191);
methodVisitor.visitIntInsn(BIPUSH, 9);
methodVisitor.visitFieldInsn(GETSTATIC, "org/bouncycastle/asn1/ua/DSTU4145NamedCurves", "ONE", "Ljava/math/BigInteger;");
methodVisitor.visitTypeInsn(NEW, "java/math/BigInteger");
methodVisitor.visitInsn(DUP);
methodVisitor.visitLdcInsn("7BC86E2102902EC4D5890E8B6B4981ff27E0482750FEFC03");
methodVisitor.visitIntInsn(BIPUSH, 16);
methodVisitor.visitMethodInsn(INVOKESPECIAL, "java/math/BigInteger", "<init>", "(Ljava/lang/String;I)V", false);
methodVisitor.visitVarInsn(ALOAD, 0);
methodVisitor.visitInsn(ICONST_4);
methodVisitor.visitInsn(AALOAD);
methodVisitor.visitVarInsn(ALOAD, 1);
methodVisitor.visitInsn(ICONST_4);
methodVisitor.visitInsn(AALOAD);
methodVisitor.visitMethodInsn(INVOKESPECIAL, "org/bouncycastle/math/ec/ECCurve$F2m", "<init>", "(IILjava/math/BigInteger;Ljava/math/BigInteger;Ljava/math/BigInteger;Ljava/math/BigInteger;)V", false);
methodVisitor.visitInsn(AASTORE);
methodVisitor.visitVarInsn(ALOAD, 2);
methodVisitor.visitInsn(ICONST_5);
methodVisitor.visitTypeInsn(NEW, "org/bouncycastle/math/ec/ECCurve$F2m");
methodVisitor.visitInsn(DUP);
methodVisitor.visitIntInsn(SIPUSH, 233);
methodVisitor.visitInsn(ICONST_1);
methodVisitor.visitInsn(ICONST_4);
methodVisitor.visitIntInsn(BIPUSH, 9);
methodVisitor.visitFieldInsn(GETSTATIC, "org/bouncycastle/asn1/ua/DSTU4145NamedCurves", "ONE", "Ljava/math/BigInteger;");
methodVisitor.visitTypeInsn(NEW, "java/math/BigInteger");
methodVisitor.visitInsn(DUP);
methodVisitor.visitLdcInsn("06973B15095675534C7CF7E64A21BD54EF5DD3B8A0326AA936ECE454D2C");
methodVisitor.visitIntInsn(BIPUSH, 16);
methodVisitor.visitMethodInsn(INVOKESPECIAL, "java/math/BigInteger", "<init>", "(Ljava/lang/String;I)V", false);
methodVisitor.visitVarInsn(ALOAD, 0);
methodVisitor.visitInsn(ICONST_5);
methodVisitor.visitInsn(AALOAD);
methodVisitor.visitVarInsn(ALOAD, 1);
methodVisitor.visitInsn(ICONST_5);
methodVisitor.visitInsn(AALOAD);
methodVisitor.visitMethodInsn(INVOKESPECIAL, "org/bouncycastle/math/ec/ECCurve$F2m", "<init>", "(IIIILjava/math/BigInteger;Ljava/math/BigInteger;Ljava/math/BigInteger;Ljava/math/BigInteger;)V", false);
methodVisitor.visitInsn(AASTORE);
methodVisitor.visitVarInsn(ALOAD, 2);
methodVisitor.visitIntInsn(BIPUSH, 6);
methodVisitor.visitTypeInsn(NEW, "org/bouncycastle/math/ec/ECCurve$F2m");
methodVisitor.visitInsn(DUP);
methodVisitor.visitIntInsn(SIPUSH, 257);
methodVisitor.visitIntInsn(BIPUSH, 12);
methodVisitor.visitFieldInsn(GETSTATIC, "org/bouncycastle/asn1/ua/DSTU4145NamedCurves", "ZERO", "Ljava/math/BigInteger;");
methodVisitor.visitTypeInsn(NEW, "java/math/BigInteger");
methodVisitor.visitInsn(DUP);
methodVisitor.visitLdcInsn("1CEF494720115657E18F938D7A7942394FF9425C1458C57861F9EEA6ADBE3BE10");
methodVisitor.visitIntInsn(BIPUSH, 16);
methodVisitor.visitMethodInsn(INVOKESPECIAL, "java/math/BigInteger", "<init>", "(Ljava/lang/String;I)V", false);
methodVisitor.visitVarInsn(ALOAD, 0);
methodVisitor.visitIntInsn(BIPUSH, 6);
methodVisitor.visitInsn(AALOAD);
methodVisitor.visitVarInsn(ALOAD, 1);
methodVisitor.visitIntInsn(BIPUSH, 6);
methodVisitor.visitInsn(AALOAD);
methodVisitor.visitMethodInsn(INVOKESPECIAL, "org/bouncycastle/math/ec/ECCurve$F2m", "<init>", "(IILjava/math/BigInteger;Ljava/math/BigInteger;Ljava/math/BigInteger;Ljava/math/BigInteger;)V", false);
methodVisitor.visitInsn(AASTORE);
methodVisitor.visitVarInsn(ALOAD, 2);
methodVisitor.visitIntInsn(BIPUSH, 7);
methodVisitor.visitTypeInsn(NEW, "org/bouncycastle/math/ec/ECCurve$F2m");
methodVisitor.visitInsn(DUP);
methodVisitor.visitIntInsn(SIPUSH, 307);
methodVisitor.visitInsn(ICONST_2);
methodVisitor.visitInsn(ICONST_4);
methodVisitor.visitIntInsn(BIPUSH, 8);
methodVisitor.visitFieldInsn(GETSTATIC, "org/bouncycastle/asn1/ua/DSTU4145NamedCurves", "ONE", "Ljava/math/BigInteger;");
methodVisitor.visitTypeInsn(NEW, "java/math/BigInteger");
methodVisitor.visitInsn(DUP);
methodVisitor.visitLdcInsn("393C7F7D53666B5054B5E6C6D3DE94F4296C0C599E2E2E241050DF18B6090BDC90186904968BB");
methodVisitor.visitIntInsn(BIPUSH, 16);
methodVisitor.visitMethodInsn(INVOKESPECIAL, "java/math/BigInteger", "<init>", "(Ljava/lang/String;I)V", false);
methodVisitor.visitVarInsn(ALOAD, 0);
methodVisitor.visitIntInsn(BIPUSH, 7);
methodVisitor.visitInsn(AALOAD);
methodVisitor.visitVarInsn(ALOAD, 1);
methodVisitor.visitIntInsn(BIPUSH, 7);
methodVisitor.visitInsn(AALOAD);
methodVisitor.visitMethodInsn(INVOKESPECIAL, "org/bouncycastle/math/ec/ECCurve$F2m", "<init>", "(IIIILjava/math/BigInteger;Ljava/math/BigInteger;Ljava/math/BigInteger;Ljava/math/BigInteger;)V", false);
methodVisitor.visitInsn(AASTORE);
methodVisitor.visitVarInsn(ALOAD, 2);
methodVisitor.visitIntInsn(BIPUSH, 8);
methodVisitor.visitTypeInsn(NEW, "org/bouncycastle/math/ec/ECCurve$F2m");
methodVisitor.visitInsn(DUP);
methodVisitor.visitIntInsn(SIPUSH, 367);
methodVisitor.visitIntInsn(BIPUSH, 21);
methodVisitor.visitFieldInsn(GETSTATIC, "org/bouncycastle/asn1/ua/DSTU4145NamedCurves", "ONE", "Ljava/math/BigInteger;");
methodVisitor.visitTypeInsn(NEW, "java/math/BigInteger");
methodVisitor.visitInsn(DUP);
methodVisitor.visitLdcInsn("43FC8AD242B0B7A6F3D1627AD5654447556B47BF6AA4A64B0C2AFE42CADAB8F93D92394C79A79755437B56995136");
methodVisitor.visitIntInsn(BIPUSH, 16);
methodVisitor.visitMethodInsn(INVOKESPECIAL, "java/math/BigInteger", "<init>", "(Ljava/lang/String;I)V", false);
methodVisitor.visitVarInsn(ALOAD, 0);
methodVisitor.visitIntInsn(BIPUSH, 8);
methodVisitor.visitInsn(AALOAD);
methodVisitor.visitVarInsn(ALOAD, 1);
methodVisitor.visitIntInsn(BIPUSH, 8);
methodVisitor.visitInsn(AALOAD);
methodVisitor.visitMethodInsn(INVOKESPECIAL, "org/bouncycastle/math/ec/ECCurve$F2m", "<init>", "(IILjava/math/BigInteger;Ljava/math/BigInteger;Ljava/math/BigInteger;Ljava/math/BigInteger;)V", false);
methodVisitor.visitInsn(AASTORE);
methodVisitor.visitVarInsn(ALOAD, 2);
methodVisitor.visitIntInsn(BIPUSH, 9);
methodVisitor.visitTypeInsn(NEW, "org/bouncycastle/math/ec/ECCurve$F2m");
methodVisitor.visitInsn(DUP);
methodVisitor.visitIntInsn(SIPUSH, 431);
methodVisitor.visitInsn(ICONST_1);
methodVisitor.visitInsn(ICONST_3);
methodVisitor.visitInsn(ICONST_5);
methodVisitor.visitFieldInsn(GETSTATIC, "org/bouncycastle/asn1/ua/DSTU4145NamedCurves", "ONE", "Ljava/math/BigInteger;");
methodVisitor.visitTypeInsn(NEW, "java/math/BigInteger");
methodVisitor.visitInsn(DUP);
methodVisitor.visitLdcInsn("03CE10490F6A708FC26DFE8C3D27C4F94E690134D5BFF988D8D28AAEAEDE975936C66BAC536B18AE2DC312CA493117DAA469C640CAF3");
methodVisitor.visitIntInsn(BIPUSH, 16);
methodVisitor.visitMethodInsn(INVOKESPECIAL, "java/math/BigInteger", "<init>", "(Ljava/lang/String;I)V", false);
methodVisitor.visitVarInsn(ALOAD, 0);
methodVisitor.visitIntInsn(BIPUSH, 9);
methodVisitor.visitInsn(AALOAD);
methodVisitor.visitVarInsn(ALOAD, 1);
methodVisitor.visitIntInsn(BIPUSH, 9);
methodVisitor.visitInsn(AALOAD);
methodVisitor.visitMethodInsn(INVOKESPECIAL, "org/bouncycastle/math/ec/ECCurve$F2m", "<init>", "(IIIILjava/math/BigInteger;Ljava/math/BigInteger;Ljava/math/BigInteger;Ljava/math/BigInteger;)V", false);
methodVisitor.visitInsn(AASTORE);
methodVisitor.visitIntInsn(BIPUSH, 10);
methodVisitor.visitTypeInsn(ANEWARRAY, "org/bouncycastle/math/ec/ECPoint");
methodVisitor.visitVarInsn(ASTORE, 3);
methodVisitor.visitVarInsn(ALOAD, 3);
methodVisitor.visitInsn(ICONST_0);
methodVisitor.visitVarInsn(ALOAD, 2);
methodVisitor.visitInsn(ICONST_0);
methodVisitor.visitInsn(AALOAD);
methodVisitor.visitTypeInsn(NEW, "java/math/BigInteger");
methodVisitor.visitInsn(DUP);
methodVisitor.visitLdcInsn("2E2F85F5DD74CE983A5C4237229DAF8A3F35823BE");
methodVisitor.visitIntInsn(BIPUSH, 16);
methodVisitor.visitMethodInsn(INVOKESPECIAL, "java/math/BigInteger", "<init>", "(Ljava/lang/String;I)V", false);
methodVisitor.visitTypeInsn(NEW, "java/math/BigInteger");
methodVisitor.visitInsn(DUP);
methodVisitor.visitLdcInsn("3826F008A8C51D7B95284D9D03FF0E00CE2CD723A");
methodVisitor.visitIntInsn(BIPUSH, 16);
methodVisitor.visitMethodInsn(INVOKESPECIAL, "java/math/BigInteger", "<init>", "(Ljava/lang/String;I)V", false);
methodVisitor.visitMethodInsn(INVOKEVIRTUAL, "org/bouncycastle/math/ec/ECCurve$F2m", "createPoint", "(Ljava/math/BigInteger;Ljava/math/BigInteger;)Lorg/bouncycastle/math/ec/ECPoint;", false);
methodVisitor.visitInsn(AASTORE);
methodVisitor.visitVarInsn(ALOAD, 3);
methodVisitor.visitInsn(ICONST_1);
methodVisitor.visitVarInsn(ALOAD, 2);
methodVisitor.visitInsn(ICONST_1);
methodVisitor.visitInsn(AALOAD);
methodVisitor.visitTypeInsn(NEW, "java/math/BigInteger");
methodVisitor.visitInsn(DUP);
methodVisitor.visitLdcInsn("7A1F6653786A68192803910A3D30B2A2018B21CD54");
methodVisitor.visitIntInsn(BIPUSH, 16);
methodVisitor.visitMethodInsn(INVOKESPECIAL, "java/math/BigInteger", "<init>", "(Ljava/lang/String;I)V", false);
methodVisitor.visitTypeInsn(NEW, "java/math/BigInteger");
methodVisitor.visitInsn(DUP);
methodVisitor.visitLdcInsn("5F49EB26781C0EC6B8909156D98ED435E45FD59918");
methodVisitor.visitIntInsn(BIPUSH, 16);
methodVisitor.visitMethodInsn(INVOKESPECIAL, "java/math/BigInteger", "<init>", "(Ljava/lang/String;I)V", false);
methodVisitor.visitMethodInsn(INVOKEVIRTUAL, "org/bouncycastle/math/ec/ECCurve$F2m", "createPoint", "(Ljava/math/BigInteger;Ljava/math/BigInteger;)Lorg/bouncycastle/math/ec/ECPoint;", false);
methodVisitor.visitInsn(AASTORE);
methodVisitor.visitVarInsn(ALOAD, 3);
methodVisitor.visitInsn(ICONST_2);
methodVisitor.visitVarInsn(ALOAD, 2);
methodVisitor.visitInsn(ICONST_2);
methodVisitor.visitInsn(AALOAD);
methodVisitor.visitTypeInsn(NEW, "java/math/BigInteger");
methodVisitor.visitInsn(DUP);
methodVisitor.visitLdcInsn("4D41A619BCC6EADF0448FA22FAD567A9181D37389CA");
methodVisitor.visitIntInsn(BIPUSH, 16);
methodVisitor.visitMethodInsn(INVOKESPECIAL, "java/math/BigInteger", "<init>", "(Ljava/lang/String;I)V", false);
methodVisitor.visitTypeInsn(NEW, "java/math/BigInteger");
methodVisitor.visitInsn(DUP);
methodVisitor.visitLdcInsn("10B51CC12849B234C75E6DD2028BF7FF5C1CE0D991A1");
methodVisitor.visitIntInsn(BIPUSH, 16);
methodVisitor.visitMethodInsn(INVOKESPECIAL, "java/math/BigInteger", "<init>", "(Ljava/lang/String;I)V", false);
methodVisitor.visitMethodInsn(INVOKEVIRTUAL, "org/bouncycastle/math/ec/ECCurve$F2m", "createPoint", "(Ljava/math/BigInteger;Ljava/math/BigInteger;)Lorg/bouncycastle/math/ec/ECPoint;", false);
methodVisitor.visitInsn(AASTORE);
methodVisitor.visitVarInsn(ALOAD, 3);
methodVisitor.visitInsn(ICONST_3);
methodVisitor.visitVarInsn(ALOAD, 2);
methodVisitor.visitInsn(ICONST_3);
methodVisitor.visitInsn(AALOAD);
methodVisitor.visitTypeInsn(NEW, "java/math/BigInteger");
methodVisitor.visitInsn(DUP);
methodVisitor.visitLdcInsn("6BA06FE51464B2BD26DC57F48819BA9954667022C7D03");
methodVisitor.visitIntInsn(BIPUSH, 16);
methodVisitor.visitMethodInsn(INVOKESPECIAL, "java/math/BigInteger", "<init>", "(Ljava/lang/String;I)V", false);
methodVisitor.visitTypeInsn(NEW, "java/math/BigInteger");
methodVisitor.visitInsn(DUP);
methodVisitor.visitLdcInsn("25FBC363582DCEC065080CA8287AAFF09788A66DC3A9E");
methodVisitor.visitIntInsn(BIPUSH, 16);
methodVisitor.visitMethodInsn(INVOKESPECIAL, "java/math/BigInteger", "<init>", "(Ljava/lang/String;I)V", false);
methodVisitor.visitMethodInsn(INVOKEVIRTUAL, "org/bouncycastle/math/ec/ECCurve$F2m", "createPoint", "(Ljava/math/BigInteger;Ljava/math/BigInteger;)Lorg/bouncycastle/math/ec/ECPoint;", false);
methodVisitor.visitInsn(AASTORE);
methodVisitor.visitVarInsn(ALOAD, 3);
methodVisitor.visitInsn(ICONST_4);
methodVisitor.visitVarInsn(ALOAD, 2);
methodVisitor.visitInsn(ICONST_4);
methodVisitor.visitInsn(AALOAD);
methodVisitor.visitTypeInsn(NEW, "java/math/BigInteger");
methodVisitor.visitInsn(DUP);
methodVisitor.visitLdcInsn("714114B762F2FF4A7912A6D2AC58B9B5C2FCFE76DAEB7129");
methodVisitor.visitIntInsn(BIPUSH, 16);
methodVisitor.visitMethodInsn(INVOKESPECIAL, "java/math/BigInteger", "<init>", "(Ljava/lang/String;I)V", false);
methodVisitor.visitTypeInsn(NEW, "java/math/BigInteger");
methodVisitor.visitInsn(DUP);
methodVisitor.visitLdcInsn("29C41E568B77C617EFE5902F11DB96FA9613CD8D03DB08DA");
methodVisitor.visitIntInsn(BIPUSH, 16);
methodVisitor.visitMethodInsn(INVOKESPECIAL, "java/math/BigInteger", "<init>", "(Ljava/lang/String;I)V", false);
methodVisitor.visitMethodInsn(INVOKEVIRTUAL, "org/bouncycastle/math/ec/ECCurve$F2m", "createPoint", "(Ljava/math/BigInteger;Ljava/math/BigInteger;)Lorg/bouncycastle/math/ec/ECPoint;", false);
methodVisitor.visitInsn(AASTORE);
methodVisitor.visitVarInsn(ALOAD, 3);
methodVisitor.visitInsn(ICONST_5);
methodVisitor.visitVarInsn(ALOAD, 2);
methodVisitor.visitInsn(ICONST_5);
methodVisitor.visitInsn(AALOAD);
methodVisitor.visitTypeInsn(NEW, "java/math/BigInteger");
methodVisitor.visitInsn(DUP);
methodVisitor.visitLdcInsn("3FCDA526B6CDF83BA1118DF35B3C31761D3545F32728D003EEB25EFE96");
methodVisitor.visitIntInsn(BIPUSH, 16);
methodVisitor.visitMethodInsn(INVOKESPECIAL, "java/math/BigInteger", "<init>", "(Ljava/lang/String;I)V", false);
methodVisitor.visitTypeInsn(NEW, "java/math/BigInteger");
methodVisitor.visitInsn(DUP);
methodVisitor.visitLdcInsn("9CA8B57A934C54DEEDA9E54A7BBAD95E3B2E91C54D32BE0B9DF96D8D35");
methodVisitor.visitIntInsn(BIPUSH, 16);
methodVisitor.visitMethodInsn(INVOKESPECIAL, "java/math/BigInteger", "<init>", "(Ljava/lang/String;I)V", false);
methodVisitor.visitMethodInsn(INVOKEVIRTUAL, "org/bouncycastle/math/ec/ECCurve$F2m", "createPoint", "(Ljava/math/BigInteger;Ljava/math/BigInteger;)Lorg/bouncycastle/math/ec/ECPoint;", false);
methodVisitor.visitInsn(AASTORE);
methodVisitor.visitVarInsn(ALOAD, 3);
methodVisitor.visitIntInsn(BIPUSH, 6);
methodVisitor.visitVarInsn(ALOAD, 2);
methodVisitor.visitIntInsn(BIPUSH, 6);
methodVisitor.visitInsn(AALOAD);
methodVisitor.visitTypeInsn(NEW, "java/math/BigInteger");
methodVisitor.visitInsn(DUP);
methodVisitor.visitLdcInsn("02A29EF207D0E9B6C55CD260B306C7E007AC491CA1B10C62334A9E8DCD8D20FB7");
methodVisitor.visitIntInsn(BIPUSH, 16);
methodVisitor.visitMethodInsn(INVOKESPECIAL, "java/math/BigInteger", "<init>", "(Ljava/lang/String;I)V", false);
methodVisitor.visitTypeInsn(NEW, "java/math/BigInteger");
methodVisitor.visitInsn(DUP);
methodVisitor.visitLdcInsn("10686D41FF744D4449FCCF6D8EEA03102E6812C93A9D60B978B702CF156D814EF");
methodVisitor.visitIntInsn(BIPUSH, 16);
methodVisitor.visitMethodInsn(INVOKESPECIAL, "java/math/BigInteger", "<init>", "(Ljava/lang/String;I)V", false);
methodVisitor.visitMethodInsn(INVOKEVIRTUAL, "org/bouncycastle/math/ec/ECCurve$F2m", "createPoint", "(Ljava/math/BigInteger;Ljava/math/BigInteger;)Lorg/bouncycastle/math/ec/ECPoint;", false);
methodVisitor.visitInsn(AASTORE);
methodVisitor.visitVarInsn(ALOAD, 3);
methodVisitor.visitIntInsn(BIPUSH, 7);
methodVisitor.visitVarInsn(ALOAD, 2);
methodVisitor.visitIntInsn(BIPUSH, 7);
methodVisitor.visitInsn(AALOAD);
methodVisitor.visitTypeInsn(NEW, "java/math/BigInteger");
methodVisitor.visitInsn(DUP);
methodVisitor.visitLdcInsn("216EE8B189D291A0224984C1E92F1D16BF75CCD825A087A239B276D3167743C52C02D6E7232AA");
methodVisitor.visitIntInsn(BIPUSH, 16);
methodVisitor.visitMethodInsn(INVOKESPECIAL, "java/math/BigInteger", "<init>", "(Ljava/lang/String;I)V", false);
methodVisitor.visitTypeInsn(NEW, "java/math/BigInteger");
methodVisitor.visitInsn(DUP);
methodVisitor.visitLdcInsn("5D9306BACD22B7FAEB09D2E049C6E2866C5D1677762A8F2F2DC9A11C7F7BE8340AB2237C7F2A0");
methodVisitor.visitIntInsn(BIPUSH, 16);
methodVisitor.visitMethodInsn(INVOKESPECIAL, "java/math/BigInteger", "<init>", "(Ljava/lang/String;I)V", false);
methodVisitor.visitMethodInsn(INVOKEVIRTUAL, "org/bouncycastle/math/ec/ECCurve$F2m", "createPoint", "(Ljava/math/BigInteger;Ljava/math/BigInteger;)Lorg/bouncycastle/math/ec/ECPoint;", false);
methodVisitor.visitInsn(AASTORE);
methodVisitor.visitVarInsn(ALOAD, 3);
methodVisitor.visitIntInsn(BIPUSH, 8);
methodVisitor.visitVarInsn(ALOAD, 2);
methodVisitor.visitIntInsn(BIPUSH, 8);
methodVisitor.visitInsn(AALOAD);
methodVisitor.visitTypeInsn(NEW, "java/math/BigInteger");
methodVisitor.visitInsn(DUP);
methodVisitor.visitLdcInsn("324A6EDDD512F08C49A99AE0D3F961197A76413E7BE81A400CA681E09639B5FE12E59A109F78BF4A373541B3B9A1");
methodVisitor.visitIntInsn(BIPUSH, 16);
methodVisitor.visitMethodInsn(INVOKESPECIAL, "java/math/BigInteger", "<init>", "(Ljava/lang/String;I)V", false);
methodVisitor.visitTypeInsn(NEW, "java/math/BigInteger");
methodVisitor.visitInsn(DUP);
methodVisitor.visitLdcInsn("1AB597A5B4477F59E39539007C7F977D1A567B92B043A49C6B61984C3FE3481AAF454CD41BA1F051626442B3C10");
methodVisitor.visitIntInsn(BIPUSH, 16);
methodVisitor.visitMethodInsn(INVOKESPECIAL, "java/math/BigInteger", "<init>", "(Ljava/lang/String;I)V", false);
methodVisitor.visitMethodInsn(INVOKEVIRTUAL, "org/bouncycastle/math/ec/ECCurve$F2m", "createPoint", "(Ljava/math/BigInteger;Ljava/math/BigInteger;)Lorg/bouncycastle/math/ec/ECPoint;", false);
methodVisitor.visitInsn(AASTORE);
methodVisitor.visitVarInsn(ALOAD, 3);
methodVisitor.visitIntInsn(BIPUSH, 9);
methodVisitor.visitVarInsn(ALOAD, 2);
methodVisitor.visitIntInsn(BIPUSH, 9);
methodVisitor.visitInsn(AALOAD);
methodVisitor.visitTypeInsn(NEW, "java/math/BigInteger");
methodVisitor.visitInsn(DUP);
methodVisitor.visitLdcInsn("1A62BA79D98133A16BBAE7ED9A8E03C32E0824D57AEF72F88986874E5AAE49C27BED49A2A95058068426C2171E99FD3B43C5947C857D");
methodVisitor.visitIntInsn(BIPUSH, 16);
methodVisitor.visitMethodInsn(INVOKESPECIAL, "java/math/BigInteger", "<init>", "(Ljava/lang/String;I)V", false);
methodVisitor.visitTypeInsn(NEW, "java/math/BigInteger");
methodVisitor.visitInsn(DUP);
methodVisitor.visitLdcInsn("70B5E1E14031C1F70BBEFE96BDDE66F451754B4CA5F48DA241F331AA396B8D1839A855C1769B1EA14BA53308B5E2723724E090E02DB9");
methodVisitor.visitIntInsn(BIPUSH, 16);
methodVisitor.visitMethodInsn(INVOKESPECIAL, "java/math/BigInteger", "<init>", "(Ljava/lang/String;I)V", false);
methodVisitor.visitMethodInsn(INVOKEVIRTUAL, "org/bouncycastle/math/ec/ECCurve$F2m", "createPoint", "(Ljava/math/BigInteger;Ljava/math/BigInteger;)Lorg/bouncycastle/math/ec/ECPoint;", false);
methodVisitor.visitInsn(AASTORE);
methodVisitor.visitInsn(ICONST_0);
methodVisitor.visitVarInsn(ISTORE, 4);
Label label0 = new Label();
methodVisitor.visitLabel(label0);
methodVisitor.visitVarInsn(ILOAD, 4);
methodVisitor.visitFieldInsn(GETSTATIC, "org/bouncycastle/asn1/ua/DSTU4145NamedCurves", "params", "[Lorg/bouncycastle/crypto/params/ECDomainParameters;");
methodVisitor.visitInsn(ARRAYLENGTH);
Label label1 = new Label();
methodVisitor.visitJumpInsn(IF_ICMPGE, label1);
methodVisitor.visitFieldInsn(GETSTATIC, "org/bouncycastle/asn1/ua/DSTU4145NamedCurves", "params", "[Lorg/bouncycastle/crypto/params/ECDomainParameters;");
methodVisitor.visitVarInsn(ILOAD, 4);
methodVisitor.visitTypeInsn(NEW, "org/bouncycastle/crypto/params/ECDomainParameters");
methodVisitor.visitInsn(DUP);
methodVisitor.visitVarInsn(ALOAD, 2);
methodVisitor.visitVarInsn(ILOAD, 4);
methodVisitor.visitInsn(AALOAD);
methodVisitor.visitVarInsn(ALOAD, 3);
methodVisitor.visitVarInsn(ILOAD, 4);
methodVisitor.visitInsn(AALOAD);
methodVisitor.visitVarInsn(ALOAD, 0);
methodVisitor.visitVarInsn(ILOAD, 4);
methodVisitor.visitInsn(AALOAD);
methodVisitor.visitVarInsn(ALOAD, 1);
methodVisitor.visitVarInsn(ILOAD, 4);
methodVisitor.visitInsn(AALOAD);
methodVisitor.visitMethodInsn(INVOKESPECIAL, "org/bouncycastle/crypto/params/ECDomainParameters", "<init>", "(Lorg/bouncycastle/math/ec/ECCurve;Lorg/bouncycastle/math/ec/ECPoint;Ljava/math/BigInteger;Ljava/math/BigInteger;)V", false);
methodVisitor.visitInsn(AASTORE);
methodVisitor.visitIincInsn(4, 1);
methodVisitor.visitJumpInsn(GOTO, label0);
methodVisitor.visitLabel(label1);
methodVisitor.visitInsn(ICONST_0);
methodVisitor.visitVarInsn(ISTORE, 4);
Label label2 = new Label();
methodVisitor.visitLabel(label2);
methodVisitor.visitVarInsn(ILOAD, 4);
methodVisitor.visitFieldInsn(GETSTATIC, "org/bouncycastle/asn1/ua/DSTU4145NamedCurves", "oids", "[Lorg/bouncycastle/asn1/ASN1ObjectIdentifier;");
methodVisitor.visitInsn(ARRAYLENGTH);
Label label3 = new Label();
methodVisitor.visitJumpInsn(IF_ICMPGE, label3);
methodVisitor.visitFieldInsn(GETSTATIC, "org/bouncycastle/asn1/ua/DSTU4145NamedCurves", "oids", "[Lorg/bouncycastle/asn1/ASN1ObjectIdentifier;");
methodVisitor.visitVarInsn(ILOAD, 4);
methodVisitor.visitTypeInsn(NEW, "org/bouncycastle/asn1/ASN1ObjectIdentifier");
methodVisitor.visitInsn(DUP);
methodVisitor.visitTypeInsn(NEW, "java/lang/StringBuilder");
methodVisitor.visitInsn(DUP);
methodVisitor.visitMethodInsn(INVOKESPECIAL, "java/lang/StringBuilder", "<init>", "()V", false);
methodVisitor.visitFieldInsn(GETSTATIC, "org/bouncycastle/asn1/ua/DSTU4145NamedCurves", "oidBase", "Ljava/lang/String;");
methodVisitor.visitMethodInsn(INVOKEVIRTUAL, "java/lang/StringBuilder", "append", "(Ljava/lang/String;)Ljava/lang/StringBuilder;", false);
methodVisitor.visitVarInsn(ILOAD, 4);
methodVisitor.visitMethodInsn(INVOKEVIRTUAL, "java/lang/StringBuilder", "append", "(I)Ljava/lang/StringBuilder;", false);
methodVisitor.visitMethodInsn(INVOKEVIRTUAL, "java/lang/StringBuilder", "toString", "()Ljava/lang/String;", false);
methodVisitor.visitMethodInsn(INVOKESPECIAL, "org/bouncycastle/asn1/ASN1ObjectIdentifier", "<init>", "(Ljava/lang/String;)V", false);
methodVisitor.visitInsn(AASTORE);
methodVisitor.visitIincInsn(4, 1);
methodVisitor.visitJumpInsn(GOTO, label2);
methodVisitor.visitLabel(label3);
methodVisitor.visitInsn(RETURN);
methodVisitor.visitMaxs(13, 5);
methodVisitor.visitEnd();
}
classWriter.visitEnd();

return classWriter.toByteArray();
}
}
