package asm.org.apache.activemq.command;
import org.objectweb.asm.AnnotationVisitor;
import org.objectweb.asm.Attribute;
import org.objectweb.asm.ClassReader;
import org.objectweb.asm.ClassWriter;
import org.objectweb.asm.ConstantDynamic;
import org.objectweb.asm.FieldVisitor;
import org.objectweb.asm.Handle;
import org.objectweb.asm.Label;
import org.objectweb.asm.MethodVisitor;
import org.objectweb.asm.Opcodes;
import org.objectweb.asm.RecordComponentVisitor;
import org.objectweb.asm.Type;
import org.objectweb.asm.TypePath;
public class XATransactionIdDump implements Opcodes {

public static byte[] dump () throws Exception {

ClassWriter classWriter = new ClassWriter(0);
FieldVisitor fieldVisitor;
RecordComponentVisitor recordComponentVisitor;
MethodVisitor methodVisitor;
AnnotationVisitor annotationVisitor0;

classWriter.visit(V1_8, ACC_PUBLIC | ACC_SUPER, "org/apache/activemq/command/XATransactionId", null, "org/apache/activemq/command/TransactionId", new String[] { "javax/transaction/xa/Xid", "java/lang/Comparable" });

{
fieldVisitor = classWriter.visitField(ACC_PUBLIC | ACC_FINAL | ACC_STATIC, "DATA_STRUCTURE_TYPE", "B", null, new Integer(112));
fieldVisitor.visitEnd();
}
{
fieldVisitor = classWriter.visitField(ACC_PRIVATE, "formatId", "I", null, null);
fieldVisitor.visitEnd();
}
{
fieldVisitor = classWriter.visitField(ACC_PRIVATE, "branchQualifier", "[B", null, null);
fieldVisitor.visitEnd();
}
{
fieldVisitor = classWriter.visitField(ACC_PRIVATE, "globalTransactionId", "[B", null, null);
fieldVisitor.visitEnd();
}
{
fieldVisitor = classWriter.visitField(ACC_PRIVATE | ACC_TRANSIENT, "outputStream", "Lorg/apache/activemq/util/DataByteArrayOutputStream;", null, null);
fieldVisitor.visitEnd();
}
{
fieldVisitor = classWriter.visitField(ACC_PRIVATE | ACC_TRANSIENT, "encodedXidBytes", "[B", null, null);
fieldVisitor.visitEnd();
}
{
fieldVisitor = classWriter.visitField(ACC_PRIVATE | ACC_TRANSIENT, "hash", "I", null, null);
fieldVisitor.visitEnd();
}
{
fieldVisitor = classWriter.visitField(ACC_PRIVATE | ACC_TRANSIENT, "transactionKey", "Ljava/lang/String;", null, null);
fieldVisitor.visitEnd();
}
{
fieldVisitor = classWriter.visitField(ACC_PRIVATE | ACC_TRANSIENT, "preparedAcks", "Ljava/util/ArrayList;", "Ljava/util/ArrayList<Lorg/apache/activemq/command/MessageAck;>;", null);
fieldVisitor.visitEnd();
}
{
fieldVisitor = classWriter.visitField(ACC_FINAL, "XID_PREFIX_SIZE", "I", null, new Integer(16));
fieldVisitor.visitEnd();
}
{
methodVisitor = classWriter.visitMethod(ACC_PUBLIC, "<init>", "()V", null, null);
methodVisitor.visitCode();
methodVisitor.visitVarInsn(ALOAD, 0);
methodVisitor.visitMethodInsn(INVOKESPECIAL, "org/apache/activemq/command/TransactionId", "<init>", "()V", false);
methodVisitor.visitVarInsn(ALOAD, 0);
methodVisitor.visitIntInsn(BIPUSH, 16);
methodVisitor.visitFieldInsn(PUTFIELD, "org/apache/activemq/command/XATransactionId", "XID_PREFIX_SIZE", "I");
methodVisitor.visitInsn(RETURN);
methodVisitor.visitMaxs(2, 1);
methodVisitor.visitEnd();
}
{
methodVisitor = classWriter.visitMethod(ACC_PUBLIC, "<init>", "(Ljavax/transaction/xa/Xid;)V", null, null);
methodVisitor.visitCode();
methodVisitor.visitVarInsn(ALOAD, 0);
methodVisitor.visitMethodInsn(INVOKESPECIAL, "org/apache/activemq/command/TransactionId", "<init>", "()V", false);
methodVisitor.visitVarInsn(ALOAD, 0);
methodVisitor.visitIntInsn(BIPUSH, 16);
methodVisitor.visitFieldInsn(PUTFIELD, "org/apache/activemq/command/XATransactionId", "XID_PREFIX_SIZE", "I");
methodVisitor.visitVarInsn(ALOAD, 0);
methodVisitor.visitVarInsn(ALOAD, 1);
methodVisitor.visitMethodInsn(INVOKEINTERFACE, "javax/transaction/xa/Xid", "getFormatId", "()I", true);
methodVisitor.visitFieldInsn(PUTFIELD, "org/apache/activemq/command/XATransactionId", "formatId", "I");
methodVisitor.visitVarInsn(ALOAD, 0);
methodVisitor.visitVarInsn(ALOAD, 1);
methodVisitor.visitMethodInsn(INVOKEINTERFACE, "javax/transaction/xa/Xid", "getGlobalTransactionId", "()[B", true);
methodVisitor.visitFieldInsn(PUTFIELD, "org/apache/activemq/command/XATransactionId", "globalTransactionId", "[B");
methodVisitor.visitVarInsn(ALOAD, 0);
methodVisitor.visitVarInsn(ALOAD, 1);
methodVisitor.visitMethodInsn(INVOKEINTERFACE, "javax/transaction/xa/Xid", "getBranchQualifier", "()[B", true);
methodVisitor.visitFieldInsn(PUTFIELD, "org/apache/activemq/command/XATransactionId", "branchQualifier", "[B");
methodVisitor.visitInsn(RETURN);
methodVisitor.visitMaxs(2, 2);
methodVisitor.visitEnd();
}
{
methodVisitor = classWriter.visitMethod(ACC_PUBLIC, "<init>", "([B)V", null, new String[] { "java/io/IOException" });
methodVisitor.visitCode();
methodVisitor.visitVarInsn(ALOAD, 0);
methodVisitor.visitMethodInsn(INVOKESPECIAL, "org/apache/activemq/command/TransactionId", "<init>", "()V", false);
methodVisitor.visitVarInsn(ALOAD, 0);
methodVisitor.visitIntInsn(BIPUSH, 16);
methodVisitor.visitFieldInsn(PUTFIELD, "org/apache/activemq/command/XATransactionId", "XID_PREFIX_SIZE", "I");
methodVisitor.visitVarInsn(ALOAD, 0);
methodVisitor.visitVarInsn(ALOAD, 1);
methodVisitor.visitFieldInsn(PUTFIELD, "org/apache/activemq/command/XATransactionId", "encodedXidBytes", "[B");
methodVisitor.visitVarInsn(ALOAD, 0);
methodVisitor.visitMethodInsn(INVOKESPECIAL, "org/apache/activemq/command/XATransactionId", "initFromEncodedBytes", "()V", false);
methodVisitor.visitInsn(RETURN);
methodVisitor.visitMaxs(2, 2);
methodVisitor.visitEnd();
}
{
methodVisitor = classWriter.visitMethod(ACC_PUBLIC, "getDataStructureType", "()B", null, null);
methodVisitor.visitCode();
methodVisitor.visitIntInsn(BIPUSH, 112);
methodVisitor.visitInsn(IRETURN);
methodVisitor.visitMaxs(1, 1);
methodVisitor.visitEnd();
}
{
methodVisitor = classWriter.visitMethod(ACC_PRIVATE, "initFromEncodedBytes", "()V", null, new String[] { "java/io/IOException" });
methodVisitor.visitCode();
Label label0 = new Label();
Label label1 = new Label();
Label label2 = new Label();
methodVisitor.visitTryCatchBlock(label0, label1, label2, "java/io/IOException");
methodVisitor.visitTypeInsn(NEW, "org/apache/activemq/util/DataByteArrayInputStream");
methodVisitor.visitInsn(DUP);
methodVisitor.visitVarInsn(ALOAD, 0);
methodVisitor.visitFieldInsn(GETFIELD, "org/apache/activemq/command/XATransactionId", "encodedXidBytes", "[B");
methodVisitor.visitMethodInsn(INVOKESPECIAL, "org/apache/activemq/util/DataByteArrayInputStream", "<init>", "([B)V", false);
methodVisitor.visitVarInsn(ASTORE, 1);
methodVisitor.visitVarInsn(ALOAD, 1);
methodVisitor.visitIntInsn(BIPUSH, 10);
methodVisitor.visitMethodInsn(INVOKEVIRTUAL, "org/apache/activemq/util/DataByteArrayInputStream", "skipBytes", "(I)I", false);
methodVisitor.visitInsn(POP);
methodVisitor.visitVarInsn(ALOAD, 0);
methodVisitor.visitVarInsn(ALOAD, 1);
methodVisitor.visitMethodInsn(INVOKEVIRTUAL, "org/apache/activemq/util/DataByteArrayInputStream", "readInt", "()I", false);
methodVisitor.visitFieldInsn(PUTFIELD, "org/apache/activemq/command/XATransactionId", "formatId", "I");
methodVisitor.visitVarInsn(ALOAD, 1);
methodVisitor.visitMethodInsn(INVOKEVIRTUAL, "org/apache/activemq/util/DataByteArrayInputStream", "readShort", "()S", false);
methodVisitor.visitVarInsn(ISTORE, 2);
methodVisitor.visitVarInsn(ALOAD, 0);
methodVisitor.visitVarInsn(ILOAD, 2);
methodVisitor.visitIntInsn(NEWARRAY, T_BYTE);
methodVisitor.visitFieldInsn(PUTFIELD, "org/apache/activemq/command/XATransactionId", "globalTransactionId", "[B");
methodVisitor.visitLabel(label0);
methodVisitor.visitVarInsn(ALOAD, 1);
methodVisitor.visitVarInsn(ALOAD, 0);
methodVisitor.visitFieldInsn(GETFIELD, "org/apache/activemq/command/XATransactionId", "globalTransactionId", "[B");
methodVisitor.visitMethodInsn(INVOKEVIRTUAL, "org/apache/activemq/util/DataByteArrayInputStream", "read", "([B)I", false);
methodVisitor.visitInsn(POP);
methodVisitor.visitVarInsn(ALOAD, 0);
methodVisitor.visitVarInsn(ALOAD, 1);
methodVisitor.visitMethodInsn(INVOKEVIRTUAL, "org/apache/activemq/util/DataByteArrayInputStream", "available", "()I", false);
methodVisitor.visitIntInsn(NEWARRAY, T_BYTE);
methodVisitor.visitFieldInsn(PUTFIELD, "org/apache/activemq/command/XATransactionId", "branchQualifier", "[B");
methodVisitor.visitVarInsn(ALOAD, 1);
methodVisitor.visitVarInsn(ALOAD, 0);
methodVisitor.visitFieldInsn(GETFIELD, "org/apache/activemq/command/XATransactionId", "branchQualifier", "[B");
methodVisitor.visitMethodInsn(INVOKEVIRTUAL, "org/apache/activemq/util/DataByteArrayInputStream", "read", "([B)I", false);
methodVisitor.visitInsn(POP);
methodVisitor.visitLabel(label1);
Label label3 = new Label();
methodVisitor.visitJumpInsn(GOTO, label3);
methodVisitor.visitLabel(label2);
methodVisitor.visitFrame(Opcodes.F_FULL, 3, new Object[] {"org/apache/activemq/command/XATransactionId", "org/apache/activemq/util/DataByteArrayInputStream", Opcodes.INTEGER}, 1, new Object[] {"java/io/IOException"});
methodVisitor.visitVarInsn(ASTORE, 3);
methodVisitor.visitTypeInsn(NEW, "java/lang/RuntimeException");
methodVisitor.visitInsn(DUP);
methodVisitor.visitTypeInsn(NEW, "java/lang/StringBuilder");
methodVisitor.visitInsn(DUP);
methodVisitor.visitMethodInsn(INVOKESPECIAL, "java/lang/StringBuilder", "<init>", "()V", false);
methodVisitor.visitVarInsn(ALOAD, 0);
methodVisitor.visitMethodInsn(INVOKEVIRTUAL, "java/lang/StringBuilder", "append", "(Ljava/lang/Object;)Ljava/lang/StringBuilder;", false);
methodVisitor.visitLdcInsn(", failed to decode:");
methodVisitor.visitMethodInsn(INVOKEVIRTUAL, "java/lang/StringBuilder", "append", "(Ljava/lang/String;)Ljava/lang/StringBuilder;", false);
methodVisitor.visitMethodInsn(INVOKEVIRTUAL, "java/lang/StringBuilder", "toString", "()Ljava/lang/String;", false);
methodVisitor.visitVarInsn(ALOAD, 3);
methodVisitor.visitMethodInsn(INVOKESPECIAL, "java/lang/RuntimeException", "<init>", "(Ljava/lang/String;Ljava/lang/Throwable;)V", false);
methodVisitor.visitInsn(ATHROW);
methodVisitor.visitLabel(label3);
methodVisitor.visitFrame(Opcodes.F_SAME, 0, null, 0, null);
methodVisitor.visitInsn(RETURN);
methodVisitor.visitMaxs(4, 4);
methodVisitor.visitEnd();
}
{
methodVisitor = classWriter.visitMethod(ACC_PUBLIC | ACC_SYNCHRONIZED, "getEncodedXidBytes", "()[B", null, null);
methodVisitor.visitCode();
Label label0 = new Label();
Label label1 = new Label();
Label label2 = new Label();
methodVisitor.visitTryCatchBlock(label0, label1, label2, "java/io/IOException");
methodVisitor.visitVarInsn(ALOAD, 0);
methodVisitor.visitFieldInsn(GETFIELD, "org/apache/activemq/command/XATransactionId", "encodedXidBytes", "[B");
Label label3 = new Label();
methodVisitor.visitJumpInsn(IFNONNULL, label3);
methodVisitor.visitVarInsn(ALOAD, 0);
methodVisitor.visitTypeInsn(NEW, "org/apache/activemq/util/DataByteArrayOutputStream");
methodVisitor.visitInsn(DUP);
methodVisitor.visitIntInsn(BIPUSH, 16);
methodVisitor.visitVarInsn(ALOAD, 0);
methodVisitor.visitFieldInsn(GETFIELD, "org/apache/activemq/command/XATransactionId", "globalTransactionId", "[B");
methodVisitor.visitInsn(ARRAYLENGTH);
methodVisitor.visitInsn(IADD);
methodVisitor.visitVarInsn(ALOAD, 0);
methodVisitor.visitFieldInsn(GETFIELD, "org/apache/activemq/command/XATransactionId", "branchQualifier", "[B");
methodVisitor.visitInsn(ARRAYLENGTH);
methodVisitor.visitInsn(IADD);
methodVisitor.visitMethodInsn(INVOKESPECIAL, "org/apache/activemq/util/DataByteArrayOutputStream", "<init>", "(I)V", false);
methodVisitor.visitFieldInsn(PUTFIELD, "org/apache/activemq/command/XATransactionId", "outputStream", "Lorg/apache/activemq/util/DataByteArrayOutputStream;");
methodVisitor.visitVarInsn(ALOAD, 0);
methodVisitor.visitFieldInsn(GETFIELD, "org/apache/activemq/command/XATransactionId", "outputStream", "Lorg/apache/activemq/util/DataByteArrayOutputStream;");
methodVisitor.visitIntInsn(BIPUSH, 10);
methodVisitor.visitMethodInsn(INVOKEVIRTUAL, "org/apache/activemq/util/DataByteArrayOutputStream", "position", "(I)V", false);
methodVisitor.visitVarInsn(ALOAD, 0);
methodVisitor.visitFieldInsn(GETFIELD, "org/apache/activemq/command/XATransactionId", "outputStream", "Lorg/apache/activemq/util/DataByteArrayOutputStream;");
methodVisitor.visitVarInsn(ALOAD, 0);
methodVisitor.visitFieldInsn(GETFIELD, "org/apache/activemq/command/XATransactionId", "formatId", "I");
methodVisitor.visitMethodInsn(INVOKEVIRTUAL, "org/apache/activemq/util/DataByteArrayOutputStream", "writeInt", "(I)V", false);
methodVisitor.visitVarInsn(ALOAD, 0);
methodVisitor.visitFieldInsn(GETFIELD, "org/apache/activemq/command/XATransactionId", "outputStream", "Lorg/apache/activemq/util/DataByteArrayOutputStream;");
methodVisitor.visitVarInsn(ALOAD, 0);
methodVisitor.visitFieldInsn(GETFIELD, "org/apache/activemq/command/XATransactionId", "globalTransactionId", "[B");
methodVisitor.visitInsn(ARRAYLENGTH);
methodVisitor.visitMethodInsn(INVOKEVIRTUAL, "org/apache/activemq/util/DataByteArrayOutputStream", "writeShort", "(I)V", false);
methodVisitor.visitLabel(label0);
methodVisitor.visitVarInsn(ALOAD, 0);
methodVisitor.visitFieldInsn(GETFIELD, "org/apache/activemq/command/XATransactionId", "outputStream", "Lorg/apache/activemq/util/DataByteArrayOutputStream;");
methodVisitor.visitVarInsn(ALOAD, 0);
methodVisitor.visitFieldInsn(GETFIELD, "org/apache/activemq/command/XATransactionId", "globalTransactionId", "[B");
methodVisitor.visitMethodInsn(INVOKEVIRTUAL, "org/apache/activemq/util/DataByteArrayOutputStream", "write", "([B)V", false);
methodVisitor.visitVarInsn(ALOAD, 0);
methodVisitor.visitFieldInsn(GETFIELD, "org/apache/activemq/command/XATransactionId", "outputStream", "Lorg/apache/activemq/util/DataByteArrayOutputStream;");
methodVisitor.visitVarInsn(ALOAD, 0);
methodVisitor.visitFieldInsn(GETFIELD, "org/apache/activemq/command/XATransactionId", "branchQualifier", "[B");
methodVisitor.visitMethodInsn(INVOKEVIRTUAL, "org/apache/activemq/util/DataByteArrayOutputStream", "write", "([B)V", false);
methodVisitor.visitLabel(label1);
Label label4 = new Label();
methodVisitor.visitJumpInsn(GOTO, label4);
methodVisitor.visitLabel(label2);
methodVisitor.visitFrame(Opcodes.F_SAME1, 0, null, 1, new Object[] {"java/io/IOException"});
methodVisitor.visitVarInsn(ASTORE, 1);
methodVisitor.visitTypeInsn(NEW, "java/lang/RuntimeException");
methodVisitor.visitInsn(DUP);
methodVisitor.visitTypeInsn(NEW, "java/lang/StringBuilder");
methodVisitor.visitInsn(DUP);
methodVisitor.visitMethodInsn(INVOKESPECIAL, "java/lang/StringBuilder", "<init>", "()V", false);
methodVisitor.visitVarInsn(ALOAD, 0);
methodVisitor.visitMethodInsn(INVOKEVIRTUAL, "java/lang/StringBuilder", "append", "(Ljava/lang/Object;)Ljava/lang/StringBuilder;", false);
methodVisitor.visitLdcInsn(", failed to encode:");
methodVisitor.visitMethodInsn(INVOKEVIRTUAL, "java/lang/StringBuilder", "append", "(Ljava/lang/String;)Ljava/lang/StringBuilder;", false);
methodVisitor.visitMethodInsn(INVOKEVIRTUAL, "java/lang/StringBuilder", "toString", "()Ljava/lang/String;", false);
methodVisitor.visitVarInsn(ALOAD, 1);
methodVisitor.visitMethodInsn(INVOKESPECIAL, "java/lang/RuntimeException", "<init>", "(Ljava/lang/String;Ljava/lang/Throwable;)V", false);
methodVisitor.visitInsn(ATHROW);
methodVisitor.visitLabel(label4);
methodVisitor.visitFrame(Opcodes.F_SAME, 0, null, 0, null);
methodVisitor.visitVarInsn(ALOAD, 0);
methodVisitor.visitVarInsn(ALOAD, 0);
methodVisitor.visitFieldInsn(GETFIELD, "org/apache/activemq/command/XATransactionId", "outputStream", "Lorg/apache/activemq/util/DataByteArrayOutputStream;");
methodVisitor.visitMethodInsn(INVOKEVIRTUAL, "org/apache/activemq/util/DataByteArrayOutputStream", "getData", "()[B", false);
methodVisitor.visitFieldInsn(PUTFIELD, "org/apache/activemq/command/XATransactionId", "encodedXidBytes", "[B");
methodVisitor.visitLabel(label3);
methodVisitor.visitFrame(Opcodes.F_SAME, 0, null, 0, null);
methodVisitor.visitVarInsn(ALOAD, 0);
methodVisitor.visitFieldInsn(GETFIELD, "org/apache/activemq/command/XATransactionId", "encodedXidBytes", "[B");
methodVisitor.visitInsn(ARETURN);
methodVisitor.visitMaxs(5, 2);
methodVisitor.visitEnd();
}
{
methodVisitor = classWriter.visitMethod(ACC_PUBLIC, "internalOutputStream", "()Lorg/apache/activemq/util/DataByteArrayOutputStream;", null, null);
methodVisitor.visitCode();
methodVisitor.visitVarInsn(ALOAD, 0);
methodVisitor.visitFieldInsn(GETFIELD, "org/apache/activemq/command/XATransactionId", "outputStream", "Lorg/apache/activemq/util/DataByteArrayOutputStream;");
methodVisitor.visitInsn(ARETURN);
methodVisitor.visitMaxs(1, 1);
methodVisitor.visitEnd();
}
{
methodVisitor = classWriter.visitMethod(ACC_PUBLIC | ACC_SYNCHRONIZED, "getTransactionKey", "()Ljava/lang/String;", null, null);
methodVisitor.visitCode();
methodVisitor.visitVarInsn(ALOAD, 0);
methodVisitor.visitFieldInsn(GETFIELD, "org/apache/activemq/command/XATransactionId", "transactionKey", "Ljava/lang/String;");
Label label0 = new Label();
methodVisitor.visitJumpInsn(IFNONNULL, label0);
methodVisitor.visitTypeInsn(NEW, "java/lang/StringBuffer");
methodVisitor.visitInsn(DUP);
methodVisitor.visitMethodInsn(INVOKESPECIAL, "java/lang/StringBuffer", "<init>", "()V", false);
methodVisitor.visitVarInsn(ASTORE, 1);
methodVisitor.visitVarInsn(ALOAD, 1);
methodVisitor.visitTypeInsn(NEW, "java/lang/StringBuilder");
methodVisitor.visitInsn(DUP);
methodVisitor.visitMethodInsn(INVOKESPECIAL, "java/lang/StringBuilder", "<init>", "()V", false);
methodVisitor.visitLdcInsn("XID:[");
methodVisitor.visitMethodInsn(INVOKEVIRTUAL, "java/lang/StringBuilder", "append", "(Ljava/lang/String;)Ljava/lang/StringBuilder;", false);
methodVisitor.visitVarInsn(ALOAD, 0);
methodVisitor.visitFieldInsn(GETFIELD, "org/apache/activemq/command/XATransactionId", "formatId", "I");
methodVisitor.visitMethodInsn(INVOKEVIRTUAL, "java/lang/StringBuilder", "append", "(I)Ljava/lang/StringBuilder;", false);
methodVisitor.visitLdcInsn(",globalId=");
methodVisitor.visitMethodInsn(INVOKEVIRTUAL, "java/lang/StringBuilder", "append", "(Ljava/lang/String;)Ljava/lang/StringBuilder;", false);
methodVisitor.visitMethodInsn(INVOKEVIRTUAL, "java/lang/StringBuilder", "toString", "()Ljava/lang/String;", false);
methodVisitor.visitMethodInsn(INVOKEVIRTUAL, "java/lang/StringBuffer", "append", "(Ljava/lang/String;)Ljava/lang/StringBuffer;", false);
methodVisitor.visitInsn(POP);
methodVisitor.visitVarInsn(ALOAD, 1);
methodVisitor.visitVarInsn(ALOAD, 0);
methodVisitor.visitVarInsn(ALOAD, 0);
methodVisitor.visitFieldInsn(GETFIELD, "org/apache/activemq/command/XATransactionId", "formatId", "I");
methodVisitor.visitVarInsn(ALOAD, 0);
methodVisitor.visitFieldInsn(GETFIELD, "org/apache/activemq/command/XATransactionId", "globalTransactionId", "[B");
methodVisitor.visitMethodInsn(INVOKESPECIAL, "org/apache/activemq/command/XATransactionId", "stringForm", "(I[B)Ljava/lang/String;", false);
methodVisitor.visitMethodInsn(INVOKEVIRTUAL, "java/lang/StringBuffer", "append", "(Ljava/lang/String;)Ljava/lang/StringBuffer;", false);
methodVisitor.visitInsn(POP);
methodVisitor.visitVarInsn(ALOAD, 1);
methodVisitor.visitLdcInsn(",branchId=");
methodVisitor.visitMethodInsn(INVOKEVIRTUAL, "java/lang/StringBuffer", "append", "(Ljava/lang/String;)Ljava/lang/StringBuffer;", false);
methodVisitor.visitInsn(POP);
methodVisitor.visitVarInsn(ALOAD, 1);
methodVisitor.visitVarInsn(ALOAD, 0);
methodVisitor.visitVarInsn(ALOAD, 0);
methodVisitor.visitFieldInsn(GETFIELD, "org/apache/activemq/command/XATransactionId", "formatId", "I");
methodVisitor.visitVarInsn(ALOAD, 0);
methodVisitor.visitFieldInsn(GETFIELD, "org/apache/activemq/command/XATransactionId", "branchQualifier", "[B");
methodVisitor.visitMethodInsn(INVOKESPECIAL, "org/apache/activemq/command/XATransactionId", "stringForm", "(I[B)Ljava/lang/String;", false);
methodVisitor.visitMethodInsn(INVOKEVIRTUAL, "java/lang/StringBuffer", "append", "(Ljava/lang/String;)Ljava/lang/StringBuffer;", false);
methodVisitor.visitInsn(POP);
methodVisitor.visitVarInsn(ALOAD, 1);
methodVisitor.visitLdcInsn("]");
methodVisitor.visitMethodInsn(INVOKEVIRTUAL, "java/lang/StringBuffer", "append", "(Ljava/lang/String;)Ljava/lang/StringBuffer;", false);
methodVisitor.visitInsn(POP);
methodVisitor.visitVarInsn(ALOAD, 0);
methodVisitor.visitVarInsn(ALOAD, 1);
methodVisitor.visitMethodInsn(INVOKEVIRTUAL, "java/lang/StringBuffer", "toString", "()Ljava/lang/String;", false);
methodVisitor.visitFieldInsn(PUTFIELD, "org/apache/activemq/command/XATransactionId", "transactionKey", "Ljava/lang/String;");
methodVisitor.visitLabel(label0);
methodVisitor.visitFrame(Opcodes.F_SAME, 0, null, 0, null);
methodVisitor.visitVarInsn(ALOAD, 0);
methodVisitor.visitFieldInsn(GETFIELD, "org/apache/activemq/command/XATransactionId", "transactionKey", "Ljava/lang/String;");
methodVisitor.visitInsn(ARETURN);
methodVisitor.visitMaxs(4, 2);
methodVisitor.visitEnd();
}
{
methodVisitor = classWriter.visitMethod(ACC_PRIVATE, "stringForm", "(I[B)Ljava/lang/String;", null, null);
methodVisitor.visitCode();
methodVisitor.visitTypeInsn(NEW, "java/lang/StringBuffer");
methodVisitor.visitInsn(DUP);
methodVisitor.visitMethodInsn(INVOKESPECIAL, "java/lang/StringBuffer", "<init>", "()V", false);
methodVisitor.visitVarInsn(ASTORE, 3);
methodVisitor.visitVarInsn(ILOAD, 1);
Label label0 = new Label();
Label label1 = new Label();
methodVisitor.visitLookupSwitchInsn(label1, new int[] { 131077 }, new Label[] { label0 });
methodVisitor.visitLabel(label0);
methodVisitor.visitFrame(Opcodes.F_APPEND,1, new Object[] {"java/lang/StringBuffer"}, 0, null);
methodVisitor.visitVarInsn(ALOAD, 0);
methodVisitor.visitVarInsn(ALOAD, 3);
methodVisitor.visitVarInsn(ALOAD, 2);
methodVisitor.visitMethodInsn(INVOKESPECIAL, "org/apache/activemq/command/XATransactionId", "stringFormArj", "(Ljava/lang/StringBuffer;[B)V", false);
Label label2 = new Label();
methodVisitor.visitJumpInsn(GOTO, label2);
methodVisitor.visitLabel(label1);
methodVisitor.visitFrame(Opcodes.F_SAME, 0, null, 0, null);
methodVisitor.visitVarInsn(ALOAD, 0);
methodVisitor.visitVarInsn(ALOAD, 3);
methodVisitor.visitVarInsn(ALOAD, 2);
methodVisitor.visitMethodInsn(INVOKESPECIAL, "org/apache/activemq/command/XATransactionId", "stringFormDefault", "(Ljava/lang/StringBuffer;[B)V", false);
methodVisitor.visitLabel(label2);
methodVisitor.visitFrame(Opcodes.F_SAME, 0, null, 0, null);
methodVisitor.visitVarInsn(ALOAD, 3);
methodVisitor.visitMethodInsn(INVOKEVIRTUAL, "java/lang/StringBuffer", "toString", "()Ljava/lang/String;", false);
methodVisitor.visitInsn(ARETURN);
methodVisitor.visitMaxs(3, 4);
methodVisitor.visitEnd();
}
{
methodVisitor = classWriter.visitMethod(ACC_PRIVATE, "stringFormDefault", "(Ljava/lang/StringBuffer;[B)V", null, null);
methodVisitor.visitCode();
methodVisitor.visitInsn(ICONST_0);
methodVisitor.visitVarInsn(ISTORE, 3);
Label label0 = new Label();
methodVisitor.visitLabel(label0);
methodVisitor.visitFrame(Opcodes.F_APPEND,1, new Object[] {Opcodes.INTEGER}, 0, null);
methodVisitor.visitVarInsn(ILOAD, 3);
methodVisitor.visitVarInsn(ALOAD, 2);
methodVisitor.visitInsn(ARRAYLENGTH);
Label label1 = new Label();
methodVisitor.visitJumpInsn(IF_ICMPGE, label1);
methodVisitor.visitVarInsn(ALOAD, 1);
methodVisitor.visitVarInsn(ALOAD, 2);
methodVisitor.visitVarInsn(ILOAD, 3);
methodVisitor.visitInsn(BALOAD);
methodVisitor.visitMethodInsn(INVOKESTATIC, "java/lang/Integer", "toHexString", "(I)Ljava/lang/String;", false);
methodVisitor.visitMethodInsn(INVOKEVIRTUAL, "java/lang/StringBuffer", "append", "(Ljava/lang/String;)Ljava/lang/StringBuffer;", false);
methodVisitor.visitInsn(POP);
methodVisitor.visitIincInsn(3, 1);
methodVisitor.visitJumpInsn(GOTO, label0);
methodVisitor.visitLabel(label1);
methodVisitor.visitFrame(Opcodes.F_CHOP,1, null, 0, null);
methodVisitor.visitInsn(RETURN);
methodVisitor.visitMaxs(3, 4);
methodVisitor.visitEnd();
}
{
methodVisitor = classWriter.visitMethod(ACC_PRIVATE, "stringFormArj", "(Ljava/lang/StringBuffer;[B)V", null, null);
methodVisitor.visitCode();
Label label0 = new Label();
Label label1 = new Label();
Label label2 = new Label();
methodVisitor.visitTryCatchBlock(label0, label1, label2, "java/lang/Exception");
methodVisitor.visitLabel(label0);
methodVisitor.visitTypeInsn(NEW, "org/apache/activemq/util/DataByteArrayInputStream");
methodVisitor.visitInsn(DUP);
methodVisitor.visitVarInsn(ALOAD, 2);
methodVisitor.visitMethodInsn(INVOKESPECIAL, "org/apache/activemq/util/DataByteArrayInputStream", "<init>", "([B)V", false);
methodVisitor.visitVarInsn(ASTORE, 3);
methodVisitor.visitVarInsn(ALOAD, 1);
methodVisitor.visitVarInsn(ALOAD, 3);
methodVisitor.visitMethodInsn(INVOKEVIRTUAL, "org/apache/activemq/util/DataByteArrayInputStream", "readLong", "()J", false);
methodVisitor.visitIntInsn(BIPUSH, 16);
methodVisitor.visitMethodInsn(INVOKESTATIC, "java/lang/Long", "toString", "(JI)Ljava/lang/String;", false);
methodVisitor.visitMethodInsn(INVOKEVIRTUAL, "java/lang/StringBuffer", "append", "(Ljava/lang/String;)Ljava/lang/StringBuffer;", false);
methodVisitor.visitInsn(POP);
methodVisitor.visitVarInsn(ALOAD, 1);
methodVisitor.visitIntInsn(BIPUSH, 58);
methodVisitor.visitMethodInsn(INVOKEVIRTUAL, "java/lang/StringBuffer", "append", "(C)Ljava/lang/StringBuffer;", false);
methodVisitor.visitInsn(POP);
methodVisitor.visitVarInsn(ALOAD, 1);
methodVisitor.visitVarInsn(ALOAD, 3);
methodVisitor.visitMethodInsn(INVOKEVIRTUAL, "org/apache/activemq/util/DataByteArrayInputStream", "readLong", "()J", false);
methodVisitor.visitIntInsn(BIPUSH, 16);
methodVisitor.visitMethodInsn(INVOKESTATIC, "java/lang/Long", "toString", "(JI)Ljava/lang/String;", false);
methodVisitor.visitMethodInsn(INVOKEVIRTUAL, "java/lang/StringBuffer", "append", "(Ljava/lang/String;)Ljava/lang/StringBuffer;", false);
methodVisitor.visitInsn(POP);
methodVisitor.visitVarInsn(ALOAD, 1);
methodVisitor.visitIntInsn(BIPUSH, 58);
methodVisitor.visitMethodInsn(INVOKEVIRTUAL, "java/lang/StringBuffer", "append", "(C)Ljava/lang/StringBuffer;", false);
methodVisitor.visitInsn(POP);
methodVisitor.visitVarInsn(ALOAD, 1);
methodVisitor.visitVarInsn(ALOAD, 3);
methodVisitor.visitMethodInsn(INVOKEVIRTUAL, "org/apache/activemq/util/DataByteArrayInputStream", "readInt", "()I", false);
methodVisitor.visitIntInsn(BIPUSH, 16);
methodVisitor.visitMethodInsn(INVOKESTATIC, "java/lang/Integer", "toString", "(II)Ljava/lang/String;", false);
methodVisitor.visitMethodInsn(INVOKEVIRTUAL, "java/lang/StringBuffer", "append", "(Ljava/lang/String;)Ljava/lang/StringBuffer;", false);
methodVisitor.visitInsn(POP);
methodVisitor.visitVarInsn(ALOAD, 1);
methodVisitor.visitIntInsn(BIPUSH, 58);
methodVisitor.visitMethodInsn(INVOKEVIRTUAL, "java/lang/StringBuffer", "append", "(C)Ljava/lang/StringBuffer;", false);
methodVisitor.visitInsn(POP);
methodVisitor.visitVarInsn(ALOAD, 1);
methodVisitor.visitVarInsn(ALOAD, 3);
methodVisitor.visitMethodInsn(INVOKEVIRTUAL, "org/apache/activemq/util/DataByteArrayInputStream", "readInt", "()I", false);
methodVisitor.visitIntInsn(BIPUSH, 16);
methodVisitor.visitMethodInsn(INVOKESTATIC, "java/lang/Integer", "toString", "(II)Ljava/lang/String;", false);
methodVisitor.visitMethodInsn(INVOKEVIRTUAL, "java/lang/StringBuffer", "append", "(Ljava/lang/String;)Ljava/lang/StringBuffer;", false);
methodVisitor.visitInsn(POP);
methodVisitor.visitVarInsn(ALOAD, 1);
methodVisitor.visitIntInsn(BIPUSH, 58);
methodVisitor.visitMethodInsn(INVOKEVIRTUAL, "java/lang/StringBuffer", "append", "(C)Ljava/lang/StringBuffer;", false);
methodVisitor.visitInsn(POP);
methodVisitor.visitVarInsn(ALOAD, 1);
methodVisitor.visitVarInsn(ALOAD, 3);
methodVisitor.visitMethodInsn(INVOKEVIRTUAL, "org/apache/activemq/util/DataByteArrayInputStream", "readInt", "()I", false);
methodVisitor.visitIntInsn(BIPUSH, 16);
methodVisitor.visitMethodInsn(INVOKESTATIC, "java/lang/Integer", "toString", "(II)Ljava/lang/String;", false);
methodVisitor.visitMethodInsn(INVOKEVIRTUAL, "java/lang/StringBuffer", "append", "(Ljava/lang/String;)Ljava/lang/StringBuffer;", false);
methodVisitor.visitInsn(POP);
methodVisitor.visitLabel(label1);
Label label3 = new Label();
methodVisitor.visitJumpInsn(GOTO, label3);
methodVisitor.visitLabel(label2);
methodVisitor.visitFrame(Opcodes.F_SAME1, 0, null, 1, new Object[] {"java/lang/Exception"});
methodVisitor.visitVarInsn(ASTORE, 3);
methodVisitor.visitVarInsn(ALOAD, 0);
methodVisitor.visitVarInsn(ALOAD, 1);
methodVisitor.visitVarInsn(ALOAD, 2);
methodVisitor.visitMethodInsn(INVOKESPECIAL, "org/apache/activemq/command/XATransactionId", "stringFormDefault", "(Ljava/lang/StringBuffer;[B)V", false);
methodVisitor.visitLabel(label3);
methodVisitor.visitFrame(Opcodes.F_SAME, 0, null, 0, null);
methodVisitor.visitInsn(RETURN);
methodVisitor.visitMaxs(4, 4);
methodVisitor.visitEnd();
}
{
methodVisitor = classWriter.visitMethod(ACC_PUBLIC, "toString", "()Ljava/lang/String;", null, null);
methodVisitor.visitCode();
methodVisitor.visitVarInsn(ALOAD, 0);
methodVisitor.visitMethodInsn(INVOKEVIRTUAL, "org/apache/activemq/command/XATransactionId", "getTransactionKey", "()Ljava/lang/String;", false);
methodVisitor.visitInsn(ARETURN);
methodVisitor.visitMaxs(1, 1);
methodVisitor.visitEnd();
}
{
methodVisitor = classWriter.visitMethod(ACC_PUBLIC, "isXATransaction", "()Z", null, null);
methodVisitor.visitCode();
methodVisitor.visitInsn(ICONST_1);
methodVisitor.visitInsn(IRETURN);
methodVisitor.visitMaxs(1, 1);
methodVisitor.visitEnd();
}
{
methodVisitor = classWriter.visitMethod(ACC_PUBLIC, "isLocalTransaction", "()Z", null, null);
methodVisitor.visitCode();
methodVisitor.visitInsn(ICONST_0);
methodVisitor.visitInsn(IRETURN);
methodVisitor.visitMaxs(1, 1);
methodVisitor.visitEnd();
}
{
methodVisitor = classWriter.visitMethod(ACC_PUBLIC, "getFormatId", "()I", null, null);
methodVisitor.visitCode();
methodVisitor.visitVarInsn(ALOAD, 0);
methodVisitor.visitFieldInsn(GETFIELD, "org/apache/activemq/command/XATransactionId", "formatId", "I");
methodVisitor.visitInsn(IRETURN);
methodVisitor.visitMaxs(1, 1);
methodVisitor.visitEnd();
}
{
methodVisitor = classWriter.visitMethod(ACC_PUBLIC, "getGlobalTransactionId", "()[B", null, null);
methodVisitor.visitCode();
methodVisitor.visitVarInsn(ALOAD, 0);
methodVisitor.visitFieldInsn(GETFIELD, "org/apache/activemq/command/XATransactionId", "globalTransactionId", "[B");
methodVisitor.visitInsn(ARETURN);
methodVisitor.visitMaxs(1, 1);
methodVisitor.visitEnd();
}
{
methodVisitor = classWriter.visitMethod(ACC_PUBLIC, "getBranchQualifier", "()[B", null, null);
methodVisitor.visitCode();
methodVisitor.visitVarInsn(ALOAD, 0);
methodVisitor.visitFieldInsn(GETFIELD, "org/apache/activemq/command/XATransactionId", "branchQualifier", "[B");
methodVisitor.visitInsn(ARETURN);
methodVisitor.visitMaxs(1, 1);
methodVisitor.visitEnd();
}
{
methodVisitor = classWriter.visitMethod(ACC_PUBLIC, "setBranchQualifier", "([B)V", null, null);
methodVisitor.visitCode();
methodVisitor.visitVarInsn(ALOAD, 0);
methodVisitor.visitVarInsn(ALOAD, 1);
methodVisitor.visitFieldInsn(PUTFIELD, "org/apache/activemq/command/XATransactionId", "branchQualifier", "[B");
methodVisitor.visitVarInsn(ALOAD, 0);
methodVisitor.visitInsn(ICONST_0);
methodVisitor.visitFieldInsn(PUTFIELD, "org/apache/activemq/command/XATransactionId", "hash", "I");
methodVisitor.visitInsn(RETURN);
methodVisitor.visitMaxs(2, 2);
methodVisitor.visitEnd();
}
{
methodVisitor = classWriter.visitMethod(ACC_PUBLIC, "setFormatId", "(I)V", null, null);
methodVisitor.visitCode();
methodVisitor.visitVarInsn(ALOAD, 0);
methodVisitor.visitVarInsn(ILOAD, 1);
methodVisitor.visitFieldInsn(PUTFIELD, "org/apache/activemq/command/XATransactionId", "formatId", "I");
methodVisitor.visitVarInsn(ALOAD, 0);
methodVisitor.visitInsn(ICONST_0);
methodVisitor.visitFieldInsn(PUTFIELD, "org/apache/activemq/command/XATransactionId", "hash", "I");
methodVisitor.visitInsn(RETURN);
methodVisitor.visitMaxs(2, 2);
methodVisitor.visitEnd();
}
{
methodVisitor = classWriter.visitMethod(ACC_PUBLIC, "setGlobalTransactionId", "([B)V", null, null);
methodVisitor.visitCode();
methodVisitor.visitVarInsn(ALOAD, 0);
methodVisitor.visitVarInsn(ALOAD, 1);
methodVisitor.visitFieldInsn(PUTFIELD, "org/apache/activemq/command/XATransactionId", "globalTransactionId", "[B");
methodVisitor.visitVarInsn(ALOAD, 0);
methodVisitor.visitInsn(ICONST_0);
methodVisitor.visitFieldInsn(PUTFIELD, "org/apache/activemq/command/XATransactionId", "hash", "I");
methodVisitor.visitInsn(RETURN);
methodVisitor.visitMaxs(2, 2);
methodVisitor.visitEnd();
}
{
methodVisitor = classWriter.visitMethod(ACC_PUBLIC, "hashCode", "()I", null, null);
methodVisitor.visitCode();
methodVisitor.visitVarInsn(ALOAD, 0);
methodVisitor.visitFieldInsn(GETFIELD, "org/apache/activemq/command/XATransactionId", "hash", "I");
Label label0 = new Label();
methodVisitor.visitJumpInsn(IFNE, label0);
methodVisitor.visitVarInsn(ALOAD, 0);
methodVisitor.visitVarInsn(ALOAD, 0);
methodVisitor.visitFieldInsn(GETFIELD, "org/apache/activemq/command/XATransactionId", "formatId", "I");
methodVisitor.visitFieldInsn(PUTFIELD, "org/apache/activemq/command/XATransactionId", "hash", "I");
methodVisitor.visitMethodInsn(INVOKESTATIC, "org/apache/activemq/util/JenkinsHash", "getInstance", "()Lorg/apache/activemq/util/JenkinsHash;", false);
methodVisitor.visitVarInsn(ASTORE, 1);
methodVisitor.visitVarInsn(ALOAD, 0);
methodVisitor.visitVarInsn(ALOAD, 1);
methodVisitor.visitVarInsn(ALOAD, 0);
methodVisitor.visitFieldInsn(GETFIELD, "org/apache/activemq/command/XATransactionId", "globalTransactionId", "[B");
methodVisitor.visitVarInsn(ALOAD, 0);
methodVisitor.visitFieldInsn(GETFIELD, "org/apache/activemq/command/XATransactionId", "hash", "I");
methodVisitor.visitMethodInsn(INVOKEVIRTUAL, "org/apache/activemq/util/JenkinsHash", "hash", "([BI)I", false);
methodVisitor.visitFieldInsn(PUTFIELD, "org/apache/activemq/command/XATransactionId", "hash", "I");
methodVisitor.visitVarInsn(ALOAD, 0);
methodVisitor.visitVarInsn(ALOAD, 1);
methodVisitor.visitVarInsn(ALOAD, 0);
methodVisitor.visitFieldInsn(GETFIELD, "org/apache/activemq/command/XATransactionId", "branchQualifier", "[B");
methodVisitor.visitVarInsn(ALOAD, 0);
methodVisitor.visitFieldInsn(GETFIELD, "org/apache/activemq/command/XATransactionId", "hash", "I");
methodVisitor.visitMethodInsn(INVOKEVIRTUAL, "org/apache/activemq/util/JenkinsHash", "hash", "([BI)I", false);
methodVisitor.visitFieldInsn(PUTFIELD, "org/apache/activemq/command/XATransactionId", "hash", "I");
methodVisitor.visitVarInsn(ALOAD, 0);
methodVisitor.visitFieldInsn(GETFIELD, "org/apache/activemq/command/XATransactionId", "hash", "I");
methodVisitor.visitJumpInsn(IFNE, label0);
methodVisitor.visitVarInsn(ALOAD, 0);
methodVisitor.visitLdcInsn(new Integer(11332302));
methodVisitor.visitFieldInsn(PUTFIELD, "org/apache/activemq/command/XATransactionId", "hash", "I");
methodVisitor.visitLabel(label0);
methodVisitor.visitFrame(Opcodes.F_SAME, 0, null, 0, null);
methodVisitor.visitVarInsn(ALOAD, 0);
methodVisitor.visitFieldInsn(GETFIELD, "org/apache/activemq/command/XATransactionId", "hash", "I");
methodVisitor.visitInsn(IRETURN);
methodVisitor.visitMaxs(4, 2);
methodVisitor.visitEnd();
}
{
methodVisitor = classWriter.visitMethod(ACC_PUBLIC, "equals", "(Ljava/lang/Object;)Z", null, null);
methodVisitor.visitCode();
methodVisitor.visitVarInsn(ALOAD, 1);
Label label0 = new Label();
methodVisitor.visitJumpInsn(IFNULL, label0);
methodVisitor.visitVarInsn(ALOAD, 1);
methodVisitor.visitMethodInsn(INVOKEVIRTUAL, "java/lang/Object", "getClass", "()Ljava/lang/Class;", false);
methodVisitor.visitLdcInsn(Type.getType("Lorg/apache/activemq/command/XATransactionId;"));
Label label1 = new Label();
methodVisitor.visitJumpInsn(IF_ACMPEQ, label1);
methodVisitor.visitLabel(label0);
methodVisitor.visitFrame(Opcodes.F_SAME, 0, null, 0, null);
methodVisitor.visitInsn(ICONST_0);
methodVisitor.visitInsn(IRETURN);
methodVisitor.visitLabel(label1);
methodVisitor.visitFrame(Opcodes.F_SAME, 0, null, 0, null);
methodVisitor.visitVarInsn(ALOAD, 1);
methodVisitor.visitTypeInsn(CHECKCAST, "org/apache/activemq/command/XATransactionId");
methodVisitor.visitVarInsn(ASTORE, 2);
methodVisitor.visitVarInsn(ALOAD, 2);
methodVisitor.visitFieldInsn(GETFIELD, "org/apache/activemq/command/XATransactionId", "formatId", "I");
methodVisitor.visitVarInsn(ALOAD, 0);
methodVisitor.visitFieldInsn(GETFIELD, "org/apache/activemq/command/XATransactionId", "formatId", "I");
Label label2 = new Label();
methodVisitor.visitJumpInsn(IF_ICMPNE, label2);
methodVisitor.visitVarInsn(ALOAD, 2);
methodVisitor.visitFieldInsn(GETFIELD, "org/apache/activemq/command/XATransactionId", "globalTransactionId", "[B");
methodVisitor.visitVarInsn(ALOAD, 0);
methodVisitor.visitFieldInsn(GETFIELD, "org/apache/activemq/command/XATransactionId", "globalTransactionId", "[B");
methodVisitor.visitMethodInsn(INVOKESTATIC, "java/util/Arrays", "equals", "([B[B)Z", false);
methodVisitor.visitJumpInsn(IFEQ, label2);
methodVisitor.visitVarInsn(ALOAD, 2);
methodVisitor.visitFieldInsn(GETFIELD, "org/apache/activemq/command/XATransactionId", "branchQualifier", "[B");
methodVisitor.visitVarInsn(ALOAD, 0);
methodVisitor.visitFieldInsn(GETFIELD, "org/apache/activemq/command/XATransactionId", "branchQualifier", "[B");
methodVisitor.visitMethodInsn(INVOKESTATIC, "java/util/Arrays", "equals", "([B[B)Z", false);
methodVisitor.visitJumpInsn(IFEQ, label2);
methodVisitor.visitInsn(ICONST_1);
Label label3 = new Label();
methodVisitor.visitJumpInsn(GOTO, label3);
methodVisitor.visitLabel(label2);
methodVisitor.visitFrame(Opcodes.F_APPEND,1, new Object[] {"org/apache/activemq/command/XATransactionId"}, 0, null);
methodVisitor.visitInsn(ICONST_0);
methodVisitor.visitLabel(label3);
methodVisitor.visitFrame(Opcodes.F_SAME1, 0, null, 1, new Object[] {Opcodes.INTEGER});
methodVisitor.visitInsn(IRETURN);
methodVisitor.visitMaxs(2, 3);
methodVisitor.visitEnd();
}
{
methodVisitor = classWriter.visitMethod(ACC_PUBLIC, "compareTo", "(Ljava/lang/Object;)I", null, null);
methodVisitor.visitCode();
methodVisitor.visitVarInsn(ALOAD, 1);
Label label0 = new Label();
methodVisitor.visitJumpInsn(IFNULL, label0);
methodVisitor.visitVarInsn(ALOAD, 1);
methodVisitor.visitMethodInsn(INVOKEVIRTUAL, "java/lang/Object", "getClass", "()Ljava/lang/Class;", false);
methodVisitor.visitLdcInsn(Type.getType("Lorg/apache/activemq/command/XATransactionId;"));
Label label1 = new Label();
methodVisitor.visitJumpInsn(IF_ACMPEQ, label1);
methodVisitor.visitLabel(label0);
methodVisitor.visitFrame(Opcodes.F_SAME, 0, null, 0, null);
methodVisitor.visitInsn(ICONST_M1);
methodVisitor.visitInsn(IRETURN);
methodVisitor.visitLabel(label1);
methodVisitor.visitFrame(Opcodes.F_SAME, 0, null, 0, null);
methodVisitor.visitVarInsn(ALOAD, 1);
methodVisitor.visitTypeInsn(CHECKCAST, "org/apache/activemq/command/XATransactionId");
methodVisitor.visitVarInsn(ASTORE, 2);
methodVisitor.visitVarInsn(ALOAD, 0);
methodVisitor.visitMethodInsn(INVOKEVIRTUAL, "org/apache/activemq/command/XATransactionId", "getTransactionKey", "()Ljava/lang/String;", false);
methodVisitor.visitVarInsn(ALOAD, 2);
methodVisitor.visitMethodInsn(INVOKEVIRTUAL, "org/apache/activemq/command/XATransactionId", "getTransactionKey", "()Ljava/lang/String;", false);
methodVisitor.visitMethodInsn(INVOKEVIRTUAL, "java/lang/String", "compareTo", "(Ljava/lang/String;)I", false);
methodVisitor.visitInsn(IRETURN);
methodVisitor.visitMaxs(2, 3);
methodVisitor.visitEnd();
}
{
methodVisitor = classWriter.visitMethod(ACC_PUBLIC, "setPreparedAcks", "(Ljava/util/ArrayList;)V", "(Ljava/util/ArrayList<Lorg/apache/activemq/command/MessageAck;>;)V", null);
methodVisitor.visitCode();
methodVisitor.visitVarInsn(ALOAD, 0);
methodVisitor.visitVarInsn(ALOAD, 1);
methodVisitor.visitFieldInsn(PUTFIELD, "org/apache/activemq/command/XATransactionId", "preparedAcks", "Ljava/util/ArrayList;");
methodVisitor.visitInsn(RETURN);
methodVisitor.visitMaxs(2, 2);
methodVisitor.visitEnd();
}
{
methodVisitor = classWriter.visitMethod(ACC_PUBLIC, "getPreparedAcks", "()Ljava/util/ArrayList;", "()Ljava/util/ArrayList<Lorg/apache/activemq/command/MessageAck;>;", null);
methodVisitor.visitCode();
methodVisitor.visitVarInsn(ALOAD, 0);
methodVisitor.visitFieldInsn(GETFIELD, "org/apache/activemq/command/XATransactionId", "preparedAcks", "Ljava/util/ArrayList;");
methodVisitor.visitInsn(ARETURN);
methodVisitor.visitMaxs(1, 1);
methodVisitor.visitEnd();
}
classWriter.visitEnd();

return classWriter.toByteArray();
}
}
