package asm.org.bouncycastle.math.ec.custom.sec;
import org.objectweb.asm.AnnotationVisitor;
import org.objectweb.asm.Attribute;
import org.objectweb.asm.ClassReader;
import org.objectweb.asm.ClassWriter;
import org.objectweb.asm.ConstantDynamic;
import org.objectweb.asm.FieldVisitor;
import org.objectweb.asm.Handle;
import org.objectweb.asm.Label;
import org.objectweb.asm.MethodVisitor;
import org.objectweb.asm.Opcodes;
import org.objectweb.asm.RecordComponentVisitor;
import org.objectweb.asm.Type;
import org.objectweb.asm.TypePath;
public class SecT571FieldDump implements Opcodes {

public static byte[] dump () throws Exception {

ClassWriter classWriter = new ClassWriter(0);
FieldVisitor fieldVisitor;
RecordComponentVisitor recordComponentVisitor;
MethodVisitor methodVisitor;
AnnotationVisitor annotationVisitor0;

classWriter.visit(V1_5, ACC_PUBLIC | ACC_SUPER, "org/bouncycastle/math/ec/custom/sec/SecT571Field", null, "java/lang/Object", null);

{
fieldVisitor = classWriter.visitField(ACC_PRIVATE | ACC_FINAL | ACC_STATIC, "M59", "J", null, new Long(576460752303423487L));
fieldVisitor.visitEnd();
}
{
fieldVisitor = classWriter.visitField(ACC_PRIVATE | ACC_FINAL | ACC_STATIC, "RM", "J", null, new Long(-1190112520884487202L));
fieldVisitor.visitEnd();
}
{
fieldVisitor = classWriter.visitField(ACC_PRIVATE | ACC_FINAL | ACC_STATIC, "ROOT_Z", "[J", null, null);
fieldVisitor.visitEnd();
}
{
methodVisitor = classWriter.visitMethod(ACC_PUBLIC, "<init>", "()V", null, null);
methodVisitor.visitCode();
methodVisitor.visitVarInsn(ALOAD, 0);
methodVisitor.visitMethodInsn(INVOKESPECIAL, "java/lang/Object", "<init>", "()V", false);
methodVisitor.visitInsn(RETURN);
methodVisitor.visitMaxs(1, 1);
methodVisitor.visitEnd();
}
{
methodVisitor = classWriter.visitMethod(ACC_PUBLIC | ACC_STATIC, "add", "([J[J[J)V", null, null);
methodVisitor.visitCode();
methodVisitor.visitInsn(ICONST_0);
methodVisitor.visitVarInsn(ISTORE, 3);
Label label0 = new Label();
methodVisitor.visitLabel(label0);
methodVisitor.visitVarInsn(ILOAD, 3);
methodVisitor.visitIntInsn(BIPUSH, 9);
Label label1 = new Label();
methodVisitor.visitJumpInsn(IF_ICMPGE, label1);
methodVisitor.visitVarInsn(ALOAD, 2);
methodVisitor.visitVarInsn(ILOAD, 3);
methodVisitor.visitVarInsn(ALOAD, 0);
methodVisitor.visitVarInsn(ILOAD, 3);
methodVisitor.visitInsn(LALOAD);
methodVisitor.visitVarInsn(ALOAD, 1);
methodVisitor.visitVarInsn(ILOAD, 3);
methodVisitor.visitInsn(LALOAD);
methodVisitor.visitInsn(LXOR);
methodVisitor.visitInsn(LASTORE);
methodVisitor.visitIincInsn(3, 1);
methodVisitor.visitJumpInsn(GOTO, label0);
methodVisitor.visitLabel(label1);
methodVisitor.visitInsn(RETURN);
methodVisitor.visitMaxs(6, 4);
methodVisitor.visitEnd();
}
{
methodVisitor = classWriter.visitMethod(ACC_PRIVATE | ACC_STATIC, "add", "([JI[JI[JI)V", null, null);
methodVisitor.visitCode();
methodVisitor.visitInsn(ICONST_0);
methodVisitor.visitVarInsn(ISTORE, 6);
Label label0 = new Label();
methodVisitor.visitLabel(label0);
methodVisitor.visitVarInsn(ILOAD, 6);
methodVisitor.visitIntInsn(BIPUSH, 9);
Label label1 = new Label();
methodVisitor.visitJumpInsn(IF_ICMPGE, label1);
methodVisitor.visitVarInsn(ALOAD, 4);
methodVisitor.visitVarInsn(ILOAD, 5);
methodVisitor.visitVarInsn(ILOAD, 6);
methodVisitor.visitInsn(IADD);
methodVisitor.visitVarInsn(ALOAD, 0);
methodVisitor.visitVarInsn(ILOAD, 1);
methodVisitor.visitVarInsn(ILOAD, 6);
methodVisitor.visitInsn(IADD);
methodVisitor.visitInsn(LALOAD);
methodVisitor.visitVarInsn(ALOAD, 2);
methodVisitor.visitVarInsn(ILOAD, 3);
methodVisitor.visitVarInsn(ILOAD, 6);
methodVisitor.visitInsn(IADD);
methodVisitor.visitInsn(LALOAD);
methodVisitor.visitInsn(LXOR);
methodVisitor.visitInsn(LASTORE);
methodVisitor.visitIincInsn(6, 1);
methodVisitor.visitJumpInsn(GOTO, label0);
methodVisitor.visitLabel(label1);
methodVisitor.visitInsn(RETURN);
methodVisitor.visitMaxs(7, 7);
methodVisitor.visitEnd();
}
{
methodVisitor = classWriter.visitMethod(ACC_PUBLIC | ACC_STATIC, "addBothTo", "([J[J[J)V", null, null);
methodVisitor.visitCode();
methodVisitor.visitInsn(ICONST_0);
methodVisitor.visitVarInsn(ISTORE, 3);
Label label0 = new Label();
methodVisitor.visitLabel(label0);
methodVisitor.visitVarInsn(ILOAD, 3);
methodVisitor.visitIntInsn(BIPUSH, 9);
Label label1 = new Label();
methodVisitor.visitJumpInsn(IF_ICMPGE, label1);
methodVisitor.visitVarInsn(ALOAD, 2);
methodVisitor.visitVarInsn(ILOAD, 3);
methodVisitor.visitInsn(DUP2);
methodVisitor.visitInsn(LALOAD);
methodVisitor.visitVarInsn(ALOAD, 0);
methodVisitor.visitVarInsn(ILOAD, 3);
methodVisitor.visitInsn(LALOAD);
methodVisitor.visitVarInsn(ALOAD, 1);
methodVisitor.visitVarInsn(ILOAD, 3);
methodVisitor.visitInsn(LALOAD);
methodVisitor.visitInsn(LXOR);
methodVisitor.visitInsn(LXOR);
methodVisitor.visitInsn(LASTORE);
methodVisitor.visitIincInsn(3, 1);
methodVisitor.visitJumpInsn(GOTO, label0);
methodVisitor.visitLabel(label1);
methodVisitor.visitInsn(RETURN);
methodVisitor.visitMaxs(8, 4);
methodVisitor.visitEnd();
}
{
methodVisitor = classWriter.visitMethod(ACC_PRIVATE | ACC_STATIC, "addBothTo", "([JI[JI[JI)V", null, null);
methodVisitor.visitCode();
methodVisitor.visitInsn(ICONST_0);
methodVisitor.visitVarInsn(ISTORE, 6);
Label label0 = new Label();
methodVisitor.visitLabel(label0);
methodVisitor.visitVarInsn(ILOAD, 6);
methodVisitor.visitIntInsn(BIPUSH, 9);
Label label1 = new Label();
methodVisitor.visitJumpInsn(IF_ICMPGE, label1);
methodVisitor.visitVarInsn(ALOAD, 4);
methodVisitor.visitVarInsn(ILOAD, 5);
methodVisitor.visitVarInsn(ILOAD, 6);
methodVisitor.visitInsn(IADD);
methodVisitor.visitInsn(DUP2);
methodVisitor.visitInsn(LALOAD);
methodVisitor.visitVarInsn(ALOAD, 0);
methodVisitor.visitVarInsn(ILOAD, 1);
methodVisitor.visitVarInsn(ILOAD, 6);
methodVisitor.visitInsn(IADD);
methodVisitor.visitInsn(LALOAD);
methodVisitor.visitVarInsn(ALOAD, 2);
methodVisitor.visitVarInsn(ILOAD, 3);
methodVisitor.visitVarInsn(ILOAD, 6);
methodVisitor.visitInsn(IADD);
methodVisitor.visitInsn(LALOAD);
methodVisitor.visitInsn(LXOR);
methodVisitor.visitInsn(LXOR);
methodVisitor.visitInsn(LASTORE);
methodVisitor.visitIincInsn(6, 1);
methodVisitor.visitJumpInsn(GOTO, label0);
methodVisitor.visitLabel(label1);
methodVisitor.visitInsn(RETURN);
methodVisitor.visitMaxs(9, 7);
methodVisitor.visitEnd();
}
{
methodVisitor = classWriter.visitMethod(ACC_PUBLIC | ACC_STATIC, "addExt", "([J[J[J)V", null, null);
methodVisitor.visitCode();
methodVisitor.visitInsn(ICONST_0);
methodVisitor.visitVarInsn(ISTORE, 3);
Label label0 = new Label();
methodVisitor.visitLabel(label0);
methodVisitor.visitVarInsn(ILOAD, 3);
methodVisitor.visitIntInsn(BIPUSH, 18);
Label label1 = new Label();
methodVisitor.visitJumpInsn(IF_ICMPGE, label1);
methodVisitor.visitVarInsn(ALOAD, 2);
methodVisitor.visitVarInsn(ILOAD, 3);
methodVisitor.visitVarInsn(ALOAD, 0);
methodVisitor.visitVarInsn(ILOAD, 3);
methodVisitor.visitInsn(LALOAD);
methodVisitor.visitVarInsn(ALOAD, 1);
methodVisitor.visitVarInsn(ILOAD, 3);
methodVisitor.visitInsn(LALOAD);
methodVisitor.visitInsn(LXOR);
methodVisitor.visitInsn(LASTORE);
methodVisitor.visitIincInsn(3, 1);
methodVisitor.visitJumpInsn(GOTO, label0);
methodVisitor.visitLabel(label1);
methodVisitor.visitInsn(RETURN);
methodVisitor.visitMaxs(6, 4);
methodVisitor.visitEnd();
}
{
methodVisitor = classWriter.visitMethod(ACC_PUBLIC | ACC_STATIC, "addOne", "([J[J)V", null, null);
methodVisitor.visitCode();
methodVisitor.visitVarInsn(ALOAD, 1);
methodVisitor.visitInsn(ICONST_0);
methodVisitor.visitVarInsn(ALOAD, 0);
methodVisitor.visitInsn(ICONST_0);
methodVisitor.visitInsn(LALOAD);
methodVisitor.visitInsn(LCONST_1);
methodVisitor.visitInsn(LXOR);
methodVisitor.visitInsn(LASTORE);
methodVisitor.visitInsn(ICONST_1);
methodVisitor.visitVarInsn(ISTORE, 2);
Label label0 = new Label();
methodVisitor.visitLabel(label0);
methodVisitor.visitVarInsn(ILOAD, 2);
methodVisitor.visitIntInsn(BIPUSH, 9);
Label label1 = new Label();
methodVisitor.visitJumpInsn(IF_ICMPGE, label1);
methodVisitor.visitVarInsn(ALOAD, 1);
methodVisitor.visitVarInsn(ILOAD, 2);
methodVisitor.visitVarInsn(ALOAD, 0);
methodVisitor.visitVarInsn(ILOAD, 2);
methodVisitor.visitInsn(LALOAD);
methodVisitor.visitInsn(LASTORE);
methodVisitor.visitIincInsn(2, 1);
methodVisitor.visitJumpInsn(GOTO, label0);
methodVisitor.visitLabel(label1);
methodVisitor.visitInsn(RETURN);
methodVisitor.visitMaxs(6, 3);
methodVisitor.visitEnd();
}
{
methodVisitor = classWriter.visitMethod(ACC_PRIVATE | ACC_STATIC, "addTo", "([J[J)V", null, null);
methodVisitor.visitCode();
methodVisitor.visitInsn(ICONST_0);
methodVisitor.visitVarInsn(ISTORE, 2);
Label label0 = new Label();
methodVisitor.visitLabel(label0);
methodVisitor.visitVarInsn(ILOAD, 2);
methodVisitor.visitIntInsn(BIPUSH, 9);
Label label1 = new Label();
methodVisitor.visitJumpInsn(IF_ICMPGE, label1);
methodVisitor.visitVarInsn(ALOAD, 1);
methodVisitor.visitVarInsn(ILOAD, 2);
methodVisitor.visitInsn(DUP2);
methodVisitor.visitInsn(LALOAD);
methodVisitor.visitVarInsn(ALOAD, 0);
methodVisitor.visitVarInsn(ILOAD, 2);
methodVisitor.visitInsn(LALOAD);
methodVisitor.visitInsn(LXOR);
methodVisitor.visitInsn(LASTORE);
methodVisitor.visitIincInsn(2, 1);
methodVisitor.visitJumpInsn(GOTO, label0);
methodVisitor.visitLabel(label1);
methodVisitor.visitInsn(RETURN);
methodVisitor.visitMaxs(6, 3);
methodVisitor.visitEnd();
}
{
methodVisitor = classWriter.visitMethod(ACC_PUBLIC | ACC_STATIC, "fromBigInteger", "(Ljava/math/BigInteger;)[J", null, null);
methodVisitor.visitCode();
methodVisitor.visitIntInsn(SIPUSH, 571);
methodVisitor.visitVarInsn(ALOAD, 0);
methodVisitor.visitMethodInsn(INVOKESTATIC, "org/bouncycastle/math/raw/Nat", "fromBigInteger64", "(ILjava/math/BigInteger;)[J", false);
methodVisitor.visitInsn(ARETURN);
methodVisitor.visitMaxs(2, 1);
methodVisitor.visitEnd();
}
{
methodVisitor = classWriter.visitMethod(ACC_PUBLIC | ACC_STATIC, "halfTrace", "([J[J)V", null, null);
methodVisitor.visitCode();
methodVisitor.visitMethodInsn(INVOKESTATIC, "org/bouncycastle/math/raw/Nat576", "createExt64", "()[J", false);
methodVisitor.visitVarInsn(ASTORE, 2);
methodVisitor.visitVarInsn(ALOAD, 0);
methodVisitor.visitVarInsn(ALOAD, 1);
methodVisitor.visitMethodInsn(INVOKESTATIC, "org/bouncycastle/math/raw/Nat576", "copy64", "([J[J)V", false);
methodVisitor.visitInsn(ICONST_1);
methodVisitor.visitVarInsn(ISTORE, 3);
Label label0 = new Label();
methodVisitor.visitLabel(label0);
methodVisitor.visitVarInsn(ILOAD, 3);
methodVisitor.visitIntInsn(SIPUSH, 571);
Label label1 = new Label();
methodVisitor.visitJumpInsn(IF_ICMPGE, label1);
methodVisitor.visitVarInsn(ALOAD, 1);
methodVisitor.visitVarInsn(ALOAD, 2);
methodVisitor.visitMethodInsn(INVOKESTATIC, "org/bouncycastle/math/ec/custom/sec/SecT571Field", "implSquare", "([J[J)V", false);
methodVisitor.visitVarInsn(ALOAD, 2);
methodVisitor.visitVarInsn(ALOAD, 1);
methodVisitor.visitMethodInsn(INVOKESTATIC, "org/bouncycastle/math/ec/custom/sec/SecT571Field", "reduce", "([J[J)V", false);
methodVisitor.visitVarInsn(ALOAD, 1);
methodVisitor.visitVarInsn(ALOAD, 2);
methodVisitor.visitMethodInsn(INVOKESTATIC, "org/bouncycastle/math/ec/custom/sec/SecT571Field", "implSquare", "([J[J)V", false);
methodVisitor.visitVarInsn(ALOAD, 2);
methodVisitor.visitVarInsn(ALOAD, 1);
methodVisitor.visitMethodInsn(INVOKESTATIC, "org/bouncycastle/math/ec/custom/sec/SecT571Field", "reduce", "([J[J)V", false);
methodVisitor.visitVarInsn(ALOAD, 0);
methodVisitor.visitVarInsn(ALOAD, 1);
methodVisitor.visitMethodInsn(INVOKESTATIC, "org/bouncycastle/math/ec/custom/sec/SecT571Field", "addTo", "([J[J)V", false);
methodVisitor.visitIincInsn(3, 2);
methodVisitor.visitJumpInsn(GOTO, label0);
methodVisitor.visitLabel(label1);
methodVisitor.visitInsn(RETURN);
methodVisitor.visitMaxs(2, 4);
methodVisitor.visitEnd();
}
{
methodVisitor = classWriter.visitMethod(ACC_PUBLIC | ACC_STATIC, "invert", "([J[J)V", null, null);
methodVisitor.visitCode();
methodVisitor.visitVarInsn(ALOAD, 0);
methodVisitor.visitMethodInsn(INVOKESTATIC, "org/bouncycastle/math/raw/Nat576", "isZero64", "([J)Z", false);
Label label0 = new Label();
methodVisitor.visitJumpInsn(IFEQ, label0);
methodVisitor.visitTypeInsn(NEW, "java/lang/IllegalStateException");
methodVisitor.visitInsn(DUP);
methodVisitor.visitMethodInsn(INVOKESPECIAL, "java/lang/IllegalStateException", "<init>", "()V", false);
methodVisitor.visitInsn(ATHROW);
methodVisitor.visitLabel(label0);
methodVisitor.visitMethodInsn(INVOKESTATIC, "org/bouncycastle/math/raw/Nat576", "create64", "()[J", false);
methodVisitor.visitVarInsn(ASTORE, 2);
methodVisitor.visitMethodInsn(INVOKESTATIC, "org/bouncycastle/math/raw/Nat576", "create64", "()[J", false);
methodVisitor.visitVarInsn(ASTORE, 3);
methodVisitor.visitMethodInsn(INVOKESTATIC, "org/bouncycastle/math/raw/Nat576", "create64", "()[J", false);
methodVisitor.visitVarInsn(ASTORE, 4);
methodVisitor.visitVarInsn(ALOAD, 0);
methodVisitor.visitVarInsn(ALOAD, 4);
methodVisitor.visitMethodInsn(INVOKESTATIC, "org/bouncycastle/math/ec/custom/sec/SecT571Field", "square", "([J[J)V", false);
methodVisitor.visitVarInsn(ALOAD, 4);
methodVisitor.visitVarInsn(ALOAD, 2);
methodVisitor.visitMethodInsn(INVOKESTATIC, "org/bouncycastle/math/ec/custom/sec/SecT571Field", "square", "([J[J)V", false);
methodVisitor.visitVarInsn(ALOAD, 2);
methodVisitor.visitVarInsn(ALOAD, 3);
methodVisitor.visitMethodInsn(INVOKESTATIC, "org/bouncycastle/math/ec/custom/sec/SecT571Field", "square", "([J[J)V", false);
methodVisitor.visitVarInsn(ALOAD, 2);
methodVisitor.visitVarInsn(ALOAD, 3);
methodVisitor.visitVarInsn(ALOAD, 2);
methodVisitor.visitMethodInsn(INVOKESTATIC, "org/bouncycastle/math/ec/custom/sec/SecT571Field", "multiply", "([J[J[J)V", false);
methodVisitor.visitVarInsn(ALOAD, 2);
methodVisitor.visitInsn(ICONST_2);
methodVisitor.visitVarInsn(ALOAD, 3);
methodVisitor.visitMethodInsn(INVOKESTATIC, "org/bouncycastle/math/ec/custom/sec/SecT571Field", "squareN", "([JI[J)V", false);
methodVisitor.visitVarInsn(ALOAD, 2);
methodVisitor.visitVarInsn(ALOAD, 3);
methodVisitor.visitVarInsn(ALOAD, 2);
methodVisitor.visitMethodInsn(INVOKESTATIC, "org/bouncycastle/math/ec/custom/sec/SecT571Field", "multiply", "([J[J[J)V", false);
methodVisitor.visitVarInsn(ALOAD, 2);
methodVisitor.visitVarInsn(ALOAD, 4);
methodVisitor.visitVarInsn(ALOAD, 2);
methodVisitor.visitMethodInsn(INVOKESTATIC, "org/bouncycastle/math/ec/custom/sec/SecT571Field", "multiply", "([J[J[J)V", false);
methodVisitor.visitVarInsn(ALOAD, 2);
methodVisitor.visitInsn(ICONST_5);
methodVisitor.visitVarInsn(ALOAD, 3);
methodVisitor.visitMethodInsn(INVOKESTATIC, "org/bouncycastle/math/ec/custom/sec/SecT571Field", "squareN", "([JI[J)V", false);
methodVisitor.visitVarInsn(ALOAD, 2);
methodVisitor.visitVarInsn(ALOAD, 3);
methodVisitor.visitVarInsn(ALOAD, 2);
methodVisitor.visitMethodInsn(INVOKESTATIC, "org/bouncycastle/math/ec/custom/sec/SecT571Field", "multiply", "([J[J[J)V", false);
methodVisitor.visitVarInsn(ALOAD, 3);
methodVisitor.visitInsn(ICONST_5);
methodVisitor.visitVarInsn(ALOAD, 3);
methodVisitor.visitMethodInsn(INVOKESTATIC, "org/bouncycastle/math/ec/custom/sec/SecT571Field", "squareN", "([JI[J)V", false);
methodVisitor.visitVarInsn(ALOAD, 2);
methodVisitor.visitVarInsn(ALOAD, 3);
methodVisitor.visitVarInsn(ALOAD, 2);
methodVisitor.visitMethodInsn(INVOKESTATIC, "org/bouncycastle/math/ec/custom/sec/SecT571Field", "multiply", "([J[J[J)V", false);
methodVisitor.visitVarInsn(ALOAD, 2);
methodVisitor.visitIntInsn(BIPUSH, 15);
methodVisitor.visitVarInsn(ALOAD, 3);
methodVisitor.visitMethodInsn(INVOKESTATIC, "org/bouncycastle/math/ec/custom/sec/SecT571Field", "squareN", "([JI[J)V", false);
methodVisitor.visitVarInsn(ALOAD, 2);
methodVisitor.visitVarInsn(ALOAD, 3);
methodVisitor.visitVarInsn(ALOAD, 4);
methodVisitor.visitMethodInsn(INVOKESTATIC, "org/bouncycastle/math/ec/custom/sec/SecT571Field", "multiply", "([J[J[J)V", false);
methodVisitor.visitVarInsn(ALOAD, 4);
methodVisitor.visitIntInsn(BIPUSH, 30);
methodVisitor.visitVarInsn(ALOAD, 2);
methodVisitor.visitMethodInsn(INVOKESTATIC, "org/bouncycastle/math/ec/custom/sec/SecT571Field", "squareN", "([JI[J)V", false);
methodVisitor.visitVarInsn(ALOAD, 2);
methodVisitor.visitIntInsn(BIPUSH, 30);
methodVisitor.visitVarInsn(ALOAD, 3);
methodVisitor.visitMethodInsn(INVOKESTATIC, "org/bouncycastle/math/ec/custom/sec/SecT571Field", "squareN", "([JI[J)V", false);
methodVisitor.visitVarInsn(ALOAD, 2);
methodVisitor.visitVarInsn(ALOAD, 3);
methodVisitor.visitVarInsn(ALOAD, 2);
methodVisitor.visitMethodInsn(INVOKESTATIC, "org/bouncycastle/math/ec/custom/sec/SecT571Field", "multiply", "([J[J[J)V", false);
methodVisitor.visitVarInsn(ALOAD, 2);
methodVisitor.visitIntInsn(BIPUSH, 60);
methodVisitor.visitVarInsn(ALOAD, 3);
methodVisitor.visitMethodInsn(INVOKESTATIC, "org/bouncycastle/math/ec/custom/sec/SecT571Field", "squareN", "([JI[J)V", false);
methodVisitor.visitVarInsn(ALOAD, 2);
methodVisitor.visitVarInsn(ALOAD, 3);
methodVisitor.visitVarInsn(ALOAD, 2);
methodVisitor.visitMethodInsn(INVOKESTATIC, "org/bouncycastle/math/ec/custom/sec/SecT571Field", "multiply", "([J[J[J)V", false);
methodVisitor.visitVarInsn(ALOAD, 3);
methodVisitor.visitIntInsn(BIPUSH, 60);
methodVisitor.visitVarInsn(ALOAD, 3);
methodVisitor.visitMethodInsn(INVOKESTATIC, "org/bouncycastle/math/ec/custom/sec/SecT571Field", "squareN", "([JI[J)V", false);
methodVisitor.visitVarInsn(ALOAD, 2);
methodVisitor.visitVarInsn(ALOAD, 3);
methodVisitor.visitVarInsn(ALOAD, 2);
methodVisitor.visitMethodInsn(INVOKESTATIC, "org/bouncycastle/math/ec/custom/sec/SecT571Field", "multiply", "([J[J[J)V", false);
methodVisitor.visitVarInsn(ALOAD, 2);
methodVisitor.visitIntInsn(SIPUSH, 180);
methodVisitor.visitVarInsn(ALOAD, 3);
methodVisitor.visitMethodInsn(INVOKESTATIC, "org/bouncycastle/math/ec/custom/sec/SecT571Field", "squareN", "([JI[J)V", false);
methodVisitor.visitVarInsn(ALOAD, 2);
methodVisitor.visitVarInsn(ALOAD, 3);
methodVisitor.visitVarInsn(ALOAD, 2);
methodVisitor.visitMethodInsn(INVOKESTATIC, "org/bouncycastle/math/ec/custom/sec/SecT571Field", "multiply", "([J[J[J)V", false);
methodVisitor.visitVarInsn(ALOAD, 3);
methodVisitor.visitIntInsn(SIPUSH, 180);
methodVisitor.visitVarInsn(ALOAD, 3);
methodVisitor.visitMethodInsn(INVOKESTATIC, "org/bouncycastle/math/ec/custom/sec/SecT571Field", "squareN", "([JI[J)V", false);
methodVisitor.visitVarInsn(ALOAD, 2);
methodVisitor.visitVarInsn(ALOAD, 3);
methodVisitor.visitVarInsn(ALOAD, 2);
methodVisitor.visitMethodInsn(INVOKESTATIC, "org/bouncycastle/math/ec/custom/sec/SecT571Field", "multiply", "([J[J[J)V", false);
methodVisitor.visitVarInsn(ALOAD, 2);
methodVisitor.visitVarInsn(ALOAD, 4);
methodVisitor.visitVarInsn(ALOAD, 1);
methodVisitor.visitMethodInsn(INVOKESTATIC, "org/bouncycastle/math/ec/custom/sec/SecT571Field", "multiply", "([J[J[J)V", false);
methodVisitor.visitInsn(RETURN);
methodVisitor.visitMaxs(3, 5);
methodVisitor.visitEnd();
}
{
methodVisitor = classWriter.visitMethod(ACC_PUBLIC | ACC_STATIC, "multiply", "([J[J[J)V", null, null);
methodVisitor.visitCode();
methodVisitor.visitMethodInsn(INVOKESTATIC, "org/bouncycastle/math/raw/Nat576", "createExt64", "()[J", false);
methodVisitor.visitVarInsn(ASTORE, 3);
methodVisitor.visitVarInsn(ALOAD, 0);
methodVisitor.visitVarInsn(ALOAD, 1);
methodVisitor.visitVarInsn(ALOAD, 3);
methodVisitor.visitMethodInsn(INVOKESTATIC, "org/bouncycastle/math/ec/custom/sec/SecT571Field", "implMultiply", "([J[J[J)V", false);
methodVisitor.visitVarInsn(ALOAD, 3);
methodVisitor.visitVarInsn(ALOAD, 2);
methodVisitor.visitMethodInsn(INVOKESTATIC, "org/bouncycastle/math/ec/custom/sec/SecT571Field", "reduce", "([J[J)V", false);
methodVisitor.visitInsn(RETURN);
methodVisitor.visitMaxs(3, 4);
methodVisitor.visitEnd();
}
{
methodVisitor = classWriter.visitMethod(ACC_PUBLIC | ACC_STATIC, "multiplyAddToExt", "([J[J[J)V", null, null);
methodVisitor.visitCode();
methodVisitor.visitMethodInsn(INVOKESTATIC, "org/bouncycastle/math/raw/Nat576", "createExt64", "()[J", false);
methodVisitor.visitVarInsn(ASTORE, 3);
methodVisitor.visitVarInsn(ALOAD, 0);
methodVisitor.visitVarInsn(ALOAD, 1);
methodVisitor.visitVarInsn(ALOAD, 3);
methodVisitor.visitMethodInsn(INVOKESTATIC, "org/bouncycastle/math/ec/custom/sec/SecT571Field", "implMultiply", "([J[J[J)V", false);
methodVisitor.visitVarInsn(ALOAD, 2);
methodVisitor.visitVarInsn(ALOAD, 3);
methodVisitor.visitVarInsn(ALOAD, 2);
methodVisitor.visitMethodInsn(INVOKESTATIC, "org/bouncycastle/math/ec/custom/sec/SecT571Field", "addExt", "([J[J[J)V", false);
methodVisitor.visitInsn(RETURN);
methodVisitor.visitMaxs(3, 4);
methodVisitor.visitEnd();
}
{
methodVisitor = classWriter.visitMethod(ACC_PUBLIC | ACC_STATIC, "multiplyPrecomp", "([J[J[J)V", null, null);
methodVisitor.visitCode();
methodVisitor.visitMethodInsn(INVOKESTATIC, "org/bouncycastle/math/raw/Nat576", "createExt64", "()[J", false);
methodVisitor.visitVarInsn(ASTORE, 3);
methodVisitor.visitVarInsn(ALOAD, 0);
methodVisitor.visitVarInsn(ALOAD, 1);
methodVisitor.visitVarInsn(ALOAD, 3);
methodVisitor.visitMethodInsn(INVOKESTATIC, "org/bouncycastle/math/ec/custom/sec/SecT571Field", "implMultiplyPrecomp", "([J[J[J)V", false);
methodVisitor.visitVarInsn(ALOAD, 3);
methodVisitor.visitVarInsn(ALOAD, 2);
methodVisitor.visitMethodInsn(INVOKESTATIC, "org/bouncycastle/math/ec/custom/sec/SecT571Field", "reduce", "([J[J)V", false);
methodVisitor.visitInsn(RETURN);
methodVisitor.visitMaxs(3, 4);
methodVisitor.visitEnd();
}
{
methodVisitor = classWriter.visitMethod(ACC_PUBLIC | ACC_STATIC, "multiplyPrecompAddToExt", "([J[J[J)V", null, null);
methodVisitor.visitCode();
methodVisitor.visitMethodInsn(INVOKESTATIC, "org/bouncycastle/math/raw/Nat576", "createExt64", "()[J", false);
methodVisitor.visitVarInsn(ASTORE, 3);
methodVisitor.visitVarInsn(ALOAD, 0);
methodVisitor.visitVarInsn(ALOAD, 1);
methodVisitor.visitVarInsn(ALOAD, 3);
methodVisitor.visitMethodInsn(INVOKESTATIC, "org/bouncycastle/math/ec/custom/sec/SecT571Field", "implMultiplyPrecomp", "([J[J[J)V", false);
methodVisitor.visitVarInsn(ALOAD, 2);
methodVisitor.visitVarInsn(ALOAD, 3);
methodVisitor.visitVarInsn(ALOAD, 2);
methodVisitor.visitMethodInsn(INVOKESTATIC, "org/bouncycastle/math/ec/custom/sec/SecT571Field", "addExt", "([J[J[J)V", false);
methodVisitor.visitInsn(RETURN);
methodVisitor.visitMaxs(3, 4);
methodVisitor.visitEnd();
}
{
methodVisitor = classWriter.visitMethod(ACC_PUBLIC | ACC_STATIC, "precompMultiplicand", "([J)[J", null, null);
methodVisitor.visitCode();
methodVisitor.visitIntInsn(SIPUSH, 144);
methodVisitor.visitVarInsn(ISTORE, 1);
methodVisitor.visitVarInsn(ILOAD, 1);
methodVisitor.visitInsn(ICONST_1);
methodVisitor.visitInsn(ISHL);
methodVisitor.visitIntInsn(NEWARRAY, T_LONG);
methodVisitor.visitVarInsn(ASTORE, 2);
methodVisitor.visitVarInsn(ALOAD, 0);
methodVisitor.visitInsn(ICONST_0);
methodVisitor.visitVarInsn(ALOAD, 2);
methodVisitor.visitIntInsn(BIPUSH, 9);
methodVisitor.visitIntInsn(BIPUSH, 9);
methodVisitor.visitMethodInsn(INVOKESTATIC, "java/lang/System", "arraycopy", "(Ljava/lang/Object;ILjava/lang/Object;II)V", false);
methodVisitor.visitInsn(ICONST_0);
methodVisitor.visitVarInsn(ISTORE, 3);
methodVisitor.visitIntInsn(BIPUSH, 7);
methodVisitor.visitVarInsn(ISTORE, 4);
Label label0 = new Label();
methodVisitor.visitLabel(label0);
methodVisitor.visitVarInsn(ILOAD, 4);
Label label1 = new Label();
methodVisitor.visitJumpInsn(IFLE, label1);
methodVisitor.visitIincInsn(3, 18);
methodVisitor.visitIntInsn(BIPUSH, 9);
methodVisitor.visitVarInsn(ALOAD, 2);
methodVisitor.visitVarInsn(ILOAD, 3);
methodVisitor.visitInsn(ICONST_1);
methodVisitor.visitInsn(IUSHR);
methodVisitor.visitInsn(LCONST_0);
methodVisitor.visitVarInsn(ALOAD, 2);
methodVisitor.visitVarInsn(ILOAD, 3);
methodVisitor.visitMethodInsn(INVOKESTATIC, "org/bouncycastle/math/raw/Nat", "shiftUpBit64", "(I[JIJ[JI)J", false);
methodVisitor.visitInsn(POP2);
methodVisitor.visitVarInsn(ALOAD, 2);
methodVisitor.visitVarInsn(ILOAD, 3);
methodVisitor.visitMethodInsn(INVOKESTATIC, "org/bouncycastle/math/ec/custom/sec/SecT571Field", "reduce5", "([JI)V", false);
methodVisitor.visitVarInsn(ALOAD, 2);
methodVisitor.visitIntInsn(BIPUSH, 9);
methodVisitor.visitVarInsn(ALOAD, 2);
methodVisitor.visitVarInsn(ILOAD, 3);
methodVisitor.visitVarInsn(ALOAD, 2);
methodVisitor.visitVarInsn(ILOAD, 3);
methodVisitor.visitIntInsn(BIPUSH, 9);
methodVisitor.visitInsn(IADD);
methodVisitor.visitMethodInsn(INVOKESTATIC, "org/bouncycastle/math/ec/custom/sec/SecT571Field", "add", "([JI[JI[JI)V", false);
methodVisitor.visitIincInsn(4, -1);
methodVisitor.visitJumpInsn(GOTO, label0);
methodVisitor.visitLabel(label1);
methodVisitor.visitVarInsn(ILOAD, 1);
methodVisitor.visitVarInsn(ALOAD, 2);
methodVisitor.visitInsn(ICONST_0);
methodVisitor.visitInsn(ICONST_4);
methodVisitor.visitInsn(LCONST_0);
methodVisitor.visitVarInsn(ALOAD, 2);
methodVisitor.visitVarInsn(ILOAD, 1);
methodVisitor.visitMethodInsn(INVOKESTATIC, "org/bouncycastle/math/raw/Nat", "shiftUpBits64", "(I[JIIJ[JI)J", false);
methodVisitor.visitInsn(POP2);
methodVisitor.visitVarInsn(ALOAD, 2);
methodVisitor.visitInsn(ARETURN);
methodVisitor.visitMaxs(8, 5);
methodVisitor.visitEnd();
}
{
methodVisitor = classWriter.visitMethod(ACC_PUBLIC | ACC_STATIC, "reduce", "([J[J)V", null, null);
methodVisitor.visitCode();
methodVisitor.visitVarInsn(ALOAD, 0);
methodVisitor.visitIntInsn(BIPUSH, 9);
methodVisitor.visitInsn(LALOAD);
methodVisitor.visitVarInsn(LSTORE, 2);
methodVisitor.visitVarInsn(ALOAD, 0);
methodVisitor.visitIntInsn(BIPUSH, 17);
methodVisitor.visitInsn(LALOAD);
methodVisitor.visitVarInsn(LSTORE, 4);
methodVisitor.visitVarInsn(LLOAD, 2);
methodVisitor.visitVarInsn(LSTORE, 6);
methodVisitor.visitVarInsn(LLOAD, 6);
methodVisitor.visitVarInsn(LLOAD, 4);
methodVisitor.visitIntInsn(BIPUSH, 59);
methodVisitor.visitInsn(LUSHR);
methodVisitor.visitInsn(LXOR);
methodVisitor.visitVarInsn(LLOAD, 4);
methodVisitor.visitIntInsn(BIPUSH, 57);
methodVisitor.visitInsn(LUSHR);
methodVisitor.visitInsn(LXOR);
methodVisitor.visitVarInsn(LLOAD, 4);
methodVisitor.visitIntInsn(BIPUSH, 54);
methodVisitor.visitInsn(LUSHR);
methodVisitor.visitInsn(LXOR);
methodVisitor.visitVarInsn(LLOAD, 4);
methodVisitor.visitIntInsn(BIPUSH, 49);
methodVisitor.visitInsn(LUSHR);
methodVisitor.visitInsn(LXOR);
methodVisitor.visitVarInsn(LSTORE, 2);
methodVisitor.visitVarInsn(ALOAD, 0);
methodVisitor.visitIntInsn(BIPUSH, 8);
methodVisitor.visitInsn(LALOAD);
methodVisitor.visitVarInsn(LLOAD, 4);
methodVisitor.visitInsn(ICONST_5);
methodVisitor.visitInsn(LSHL);
methodVisitor.visitInsn(LXOR);
methodVisitor.visitVarInsn(LLOAD, 4);
methodVisitor.visitIntInsn(BIPUSH, 7);
methodVisitor.visitInsn(LSHL);
methodVisitor.visitInsn(LXOR);
methodVisitor.visitVarInsn(LLOAD, 4);
methodVisitor.visitIntInsn(BIPUSH, 10);
methodVisitor.visitInsn(LSHL);
methodVisitor.visitInsn(LXOR);
methodVisitor.visitVarInsn(LLOAD, 4);
methodVisitor.visitIntInsn(BIPUSH, 15);
methodVisitor.visitInsn(LSHL);
methodVisitor.visitInsn(LXOR);
methodVisitor.visitVarInsn(LSTORE, 6);
methodVisitor.visitIntInsn(BIPUSH, 16);
methodVisitor.visitVarInsn(ISTORE, 8);
Label label0 = new Label();
methodVisitor.visitLabel(label0);
methodVisitor.visitVarInsn(ILOAD, 8);
methodVisitor.visitIntInsn(BIPUSH, 10);
Label label1 = new Label();
methodVisitor.visitJumpInsn(IF_ICMPLT, label1);
methodVisitor.visitVarInsn(ALOAD, 0);
methodVisitor.visitVarInsn(ILOAD, 8);
methodVisitor.visitInsn(LALOAD);
methodVisitor.visitVarInsn(LSTORE, 4);
methodVisitor.visitVarInsn(ALOAD, 1);
methodVisitor.visitVarInsn(ILOAD, 8);
methodVisitor.visitIntInsn(BIPUSH, 8);
methodVisitor.visitInsn(ISUB);
methodVisitor.visitVarInsn(LLOAD, 6);
methodVisitor.visitVarInsn(LLOAD, 4);
methodVisitor.visitIntInsn(BIPUSH, 59);
methodVisitor.visitInsn(LUSHR);
methodVisitor.visitInsn(LXOR);
methodVisitor.visitVarInsn(LLOAD, 4);
methodVisitor.visitIntInsn(BIPUSH, 57);
methodVisitor.visitInsn(LUSHR);
methodVisitor.visitInsn(LXOR);
methodVisitor.visitVarInsn(LLOAD, 4);
methodVisitor.visitIntInsn(BIPUSH, 54);
methodVisitor.visitInsn(LUSHR);
methodVisitor.visitInsn(LXOR);
methodVisitor.visitVarInsn(LLOAD, 4);
methodVisitor.visitIntInsn(BIPUSH, 49);
methodVisitor.visitInsn(LUSHR);
methodVisitor.visitInsn(LXOR);
methodVisitor.visitInsn(LASTORE);
methodVisitor.visitVarInsn(ALOAD, 0);
methodVisitor.visitVarInsn(ILOAD, 8);
methodVisitor.visitIntInsn(BIPUSH, 9);
methodVisitor.visitInsn(ISUB);
methodVisitor.visitInsn(LALOAD);
methodVisitor.visitVarInsn(LLOAD, 4);
methodVisitor.visitInsn(ICONST_5);
methodVisitor.visitInsn(LSHL);
methodVisitor.visitInsn(LXOR);
methodVisitor.visitVarInsn(LLOAD, 4);
methodVisitor.visitIntInsn(BIPUSH, 7);
methodVisitor.visitInsn(LSHL);
methodVisitor.visitInsn(LXOR);
methodVisitor.visitVarInsn(LLOAD, 4);
methodVisitor.visitIntInsn(BIPUSH, 10);
methodVisitor.visitInsn(LSHL);
methodVisitor.visitInsn(LXOR);
methodVisitor.visitVarInsn(LLOAD, 4);
methodVisitor.visitIntInsn(BIPUSH, 15);
methodVisitor.visitInsn(LSHL);
methodVisitor.visitInsn(LXOR);
methodVisitor.visitVarInsn(LSTORE, 6);
methodVisitor.visitIincInsn(8, -1);
methodVisitor.visitJumpInsn(GOTO, label0);
methodVisitor.visitLabel(label1);
methodVisitor.visitVarInsn(LLOAD, 2);
methodVisitor.visitVarInsn(LSTORE, 4);
methodVisitor.visitVarInsn(ALOAD, 1);
methodVisitor.visitInsn(ICONST_1);
methodVisitor.visitVarInsn(LLOAD, 6);
methodVisitor.visitVarInsn(LLOAD, 4);
methodVisitor.visitIntInsn(BIPUSH, 59);
methodVisitor.visitInsn(LUSHR);
methodVisitor.visitInsn(LXOR);
methodVisitor.visitVarInsn(LLOAD, 4);
methodVisitor.visitIntInsn(BIPUSH, 57);
methodVisitor.visitInsn(LUSHR);
methodVisitor.visitInsn(LXOR);
methodVisitor.visitVarInsn(LLOAD, 4);
methodVisitor.visitIntInsn(BIPUSH, 54);
methodVisitor.visitInsn(LUSHR);
methodVisitor.visitInsn(LXOR);
methodVisitor.visitVarInsn(LLOAD, 4);
methodVisitor.visitIntInsn(BIPUSH, 49);
methodVisitor.visitInsn(LUSHR);
methodVisitor.visitInsn(LXOR);
methodVisitor.visitInsn(LASTORE);
methodVisitor.visitVarInsn(ALOAD, 0);
methodVisitor.visitInsn(ICONST_0);
methodVisitor.visitInsn(LALOAD);
methodVisitor.visitVarInsn(LLOAD, 4);
methodVisitor.visitInsn(ICONST_5);
methodVisitor.visitInsn(LSHL);
methodVisitor.visitInsn(LXOR);
methodVisitor.visitVarInsn(LLOAD, 4);
methodVisitor.visitIntInsn(BIPUSH, 7);
methodVisitor.visitInsn(LSHL);
methodVisitor.visitInsn(LXOR);
methodVisitor.visitVarInsn(LLOAD, 4);
methodVisitor.visitIntInsn(BIPUSH, 10);
methodVisitor.visitInsn(LSHL);
methodVisitor.visitInsn(LXOR);
methodVisitor.visitVarInsn(LLOAD, 4);
methodVisitor.visitIntInsn(BIPUSH, 15);
methodVisitor.visitInsn(LSHL);
methodVisitor.visitInsn(LXOR);
methodVisitor.visitVarInsn(LSTORE, 6);
methodVisitor.visitVarInsn(ALOAD, 1);
methodVisitor.visitIntInsn(BIPUSH, 8);
methodVisitor.visitInsn(LALOAD);
methodVisitor.visitVarInsn(LSTORE, 8);
methodVisitor.visitVarInsn(LLOAD, 8);
methodVisitor.visitIntInsn(BIPUSH, 59);
methodVisitor.visitInsn(LUSHR);
methodVisitor.visitVarInsn(LSTORE, 10);
methodVisitor.visitVarInsn(ALOAD, 1);
methodVisitor.visitInsn(ICONST_0);
methodVisitor.visitVarInsn(LLOAD, 6);
methodVisitor.visitVarInsn(LLOAD, 10);
methodVisitor.visitInsn(LXOR);
methodVisitor.visitVarInsn(LLOAD, 10);
methodVisitor.visitInsn(ICONST_2);
methodVisitor.visitInsn(LSHL);
methodVisitor.visitInsn(LXOR);
methodVisitor.visitVarInsn(LLOAD, 10);
methodVisitor.visitInsn(ICONST_5);
methodVisitor.visitInsn(LSHL);
methodVisitor.visitInsn(LXOR);
methodVisitor.visitVarInsn(LLOAD, 10);
methodVisitor.visitIntInsn(BIPUSH, 10);
methodVisitor.visitInsn(LSHL);
methodVisitor.visitInsn(LXOR);
methodVisitor.visitInsn(LASTORE);
methodVisitor.visitVarInsn(ALOAD, 1);
methodVisitor.visitIntInsn(BIPUSH, 8);
methodVisitor.visitVarInsn(LLOAD, 8);
methodVisitor.visitLdcInsn(new Long(576460752303423487L));
methodVisitor.visitInsn(LAND);
methodVisitor.visitInsn(LASTORE);
methodVisitor.visitInsn(RETURN);
methodVisitor.visitMaxs(7, 12);
methodVisitor.visitEnd();
}
{
methodVisitor = classWriter.visitMethod(ACC_PUBLIC | ACC_STATIC, "reduce5", "([JI)V", null, null);
methodVisitor.visitCode();
methodVisitor.visitVarInsn(ALOAD, 0);
methodVisitor.visitVarInsn(ILOAD, 1);
methodVisitor.visitIntInsn(BIPUSH, 8);
methodVisitor.visitInsn(IADD);
methodVisitor.visitInsn(LALOAD);
methodVisitor.visitVarInsn(LSTORE, 2);
methodVisitor.visitVarInsn(LLOAD, 2);
methodVisitor.visitIntInsn(BIPUSH, 59);
methodVisitor.visitInsn(LUSHR);
methodVisitor.visitVarInsn(LSTORE, 4);
methodVisitor.visitVarInsn(ALOAD, 0);
methodVisitor.visitVarInsn(ILOAD, 1);
methodVisitor.visitInsn(DUP2);
methodVisitor.visitInsn(LALOAD);
methodVisitor.visitVarInsn(LLOAD, 4);
methodVisitor.visitVarInsn(LLOAD, 4);
methodVisitor.visitInsn(ICONST_2);
methodVisitor.visitInsn(LSHL);
methodVisitor.visitInsn(LXOR);
methodVisitor.visitVarInsn(LLOAD, 4);
methodVisitor.visitInsn(ICONST_5);
methodVisitor.visitInsn(LSHL);
methodVisitor.visitInsn(LXOR);
methodVisitor.visitVarInsn(LLOAD, 4);
methodVisitor.visitIntInsn(BIPUSH, 10);
methodVisitor.visitInsn(LSHL);
methodVisitor.visitInsn(LXOR);
methodVisitor.visitInsn(LXOR);
methodVisitor.visitInsn(LASTORE);
methodVisitor.visitVarInsn(ALOAD, 0);
methodVisitor.visitVarInsn(ILOAD, 1);
methodVisitor.visitIntInsn(BIPUSH, 8);
methodVisitor.visitInsn(IADD);
methodVisitor.visitVarInsn(LLOAD, 2);
methodVisitor.visitLdcInsn(new Long(576460752303423487L));
methodVisitor.visitInsn(LAND);
methodVisitor.visitInsn(LASTORE);
methodVisitor.visitInsn(RETURN);
methodVisitor.visitMaxs(9, 6);
methodVisitor.visitEnd();
}
{
methodVisitor = classWriter.visitMethod(ACC_PUBLIC | ACC_STATIC, "sqrt", "([J[J)V", null, null);
methodVisitor.visitCode();
methodVisitor.visitMethodInsn(INVOKESTATIC, "org/bouncycastle/math/raw/Nat576", "create64", "()[J", false);
methodVisitor.visitVarInsn(ASTORE, 2);
methodVisitor.visitMethodInsn(INVOKESTATIC, "org/bouncycastle/math/raw/Nat576", "create64", "()[J", false);
methodVisitor.visitVarInsn(ASTORE, 3);
methodVisitor.visitInsn(ICONST_0);
methodVisitor.visitVarInsn(ISTORE, 4);
methodVisitor.visitInsn(ICONST_0);
methodVisitor.visitVarInsn(ISTORE, 5);
Label label0 = new Label();
methodVisitor.visitLabel(label0);
methodVisitor.visitVarInsn(ILOAD, 5);
methodVisitor.visitInsn(ICONST_4);
Label label1 = new Label();
methodVisitor.visitJumpInsn(IF_ICMPGE, label1);
methodVisitor.visitVarInsn(ALOAD, 0);
methodVisitor.visitVarInsn(ILOAD, 4);
methodVisitor.visitIincInsn(4, 1);
methodVisitor.visitInsn(LALOAD);
methodVisitor.visitMethodInsn(INVOKESTATIC, "org/bouncycastle/math/raw/Interleave", "unshuffle", "(J)J", false);
methodVisitor.visitVarInsn(LSTORE, 6);
methodVisitor.visitVarInsn(ALOAD, 0);
methodVisitor.visitVarInsn(ILOAD, 4);
methodVisitor.visitIincInsn(4, 1);
methodVisitor.visitInsn(LALOAD);
methodVisitor.visitMethodInsn(INVOKESTATIC, "org/bouncycastle/math/raw/Interleave", "unshuffle", "(J)J", false);
methodVisitor.visitVarInsn(LSTORE, 8);
methodVisitor.visitVarInsn(ALOAD, 2);
methodVisitor.visitVarInsn(ILOAD, 5);
methodVisitor.visitVarInsn(LLOAD, 6);
methodVisitor.visitLdcInsn(new Long(4294967295L));
methodVisitor.visitInsn(LAND);
methodVisitor.visitVarInsn(LLOAD, 8);
methodVisitor.visitIntInsn(BIPUSH, 32);
methodVisitor.visitInsn(LSHL);
methodVisitor.visitInsn(LOR);
methodVisitor.visitInsn(LASTORE);
methodVisitor.visitVarInsn(ALOAD, 3);
methodVisitor.visitVarInsn(ILOAD, 5);
methodVisitor.visitVarInsn(LLOAD, 6);
methodVisitor.visitIntInsn(BIPUSH, 32);
methodVisitor.visitInsn(LUSHR);
methodVisitor.visitVarInsn(LLOAD, 8);
methodVisitor.visitLdcInsn(new Long(-4294967296L));
methodVisitor.visitInsn(LAND);
methodVisitor.visitInsn(LOR);
methodVisitor.visitInsn(LASTORE);
methodVisitor.visitIincInsn(5, 1);
methodVisitor.visitJumpInsn(GOTO, label0);
methodVisitor.visitLabel(label1);
methodVisitor.visitVarInsn(ALOAD, 0);
methodVisitor.visitVarInsn(ILOAD, 4);
methodVisitor.visitInsn(LALOAD);
methodVisitor.visitMethodInsn(INVOKESTATIC, "org/bouncycastle/math/raw/Interleave", "unshuffle", "(J)J", false);
methodVisitor.visitVarInsn(LSTORE, 5);
methodVisitor.visitVarInsn(ALOAD, 2);
methodVisitor.visitInsn(ICONST_4);
methodVisitor.visitVarInsn(LLOAD, 5);
methodVisitor.visitLdcInsn(new Long(4294967295L));
methodVisitor.visitInsn(LAND);
methodVisitor.visitInsn(LASTORE);
methodVisitor.visitVarInsn(ALOAD, 3);
methodVisitor.visitInsn(ICONST_4);
methodVisitor.visitVarInsn(LLOAD, 5);
methodVisitor.visitIntInsn(BIPUSH, 32);
methodVisitor.visitInsn(LUSHR);
methodVisitor.visitInsn(LASTORE);
methodVisitor.visitVarInsn(ALOAD, 3);
methodVisitor.visitFieldInsn(GETSTATIC, "org/bouncycastle/math/ec/custom/sec/SecT571Field", "ROOT_Z", "[J");
methodVisitor.visitVarInsn(ALOAD, 1);
methodVisitor.visitMethodInsn(INVOKESTATIC, "org/bouncycastle/math/ec/custom/sec/SecT571Field", "multiply", "([J[J[J)V", false);
methodVisitor.visitVarInsn(ALOAD, 1);
methodVisitor.visitVarInsn(ALOAD, 2);
methodVisitor.visitVarInsn(ALOAD, 1);
methodVisitor.visitMethodInsn(INVOKESTATIC, "org/bouncycastle/math/ec/custom/sec/SecT571Field", "add", "([J[J[J)V", false);
methodVisitor.visitInsn(RETURN);
methodVisitor.visitMaxs(8, 10);
methodVisitor.visitEnd();
}
{
methodVisitor = classWriter.visitMethod(ACC_PUBLIC | ACC_STATIC, "square", "([J[J)V", null, null);
methodVisitor.visitCode();
methodVisitor.visitMethodInsn(INVOKESTATIC, "org/bouncycastle/math/raw/Nat576", "createExt64", "()[J", false);
methodVisitor.visitVarInsn(ASTORE, 2);
methodVisitor.visitVarInsn(ALOAD, 0);
methodVisitor.visitVarInsn(ALOAD, 2);
methodVisitor.visitMethodInsn(INVOKESTATIC, "org/bouncycastle/math/ec/custom/sec/SecT571Field", "implSquare", "([J[J)V", false);
methodVisitor.visitVarInsn(ALOAD, 2);
methodVisitor.visitVarInsn(ALOAD, 1);
methodVisitor.visitMethodInsn(INVOKESTATIC, "org/bouncycastle/math/ec/custom/sec/SecT571Field", "reduce", "([J[J)V", false);
methodVisitor.visitInsn(RETURN);
methodVisitor.visitMaxs(2, 3);
methodVisitor.visitEnd();
}
{
methodVisitor = classWriter.visitMethod(ACC_PUBLIC | ACC_STATIC, "squareAddToExt", "([J[J)V", null, null);
methodVisitor.visitCode();
methodVisitor.visitMethodInsn(INVOKESTATIC, "org/bouncycastle/math/raw/Nat576", "createExt64", "()[J", false);
methodVisitor.visitVarInsn(ASTORE, 2);
methodVisitor.visitVarInsn(ALOAD, 0);
methodVisitor.visitVarInsn(ALOAD, 2);
methodVisitor.visitMethodInsn(INVOKESTATIC, "org/bouncycastle/math/ec/custom/sec/SecT571Field", "implSquare", "([J[J)V", false);
methodVisitor.visitVarInsn(ALOAD, 1);
methodVisitor.visitVarInsn(ALOAD, 2);
methodVisitor.visitVarInsn(ALOAD, 1);
methodVisitor.visitMethodInsn(INVOKESTATIC, "org/bouncycastle/math/ec/custom/sec/SecT571Field", "addExt", "([J[J[J)V", false);
methodVisitor.visitInsn(RETURN);
methodVisitor.visitMaxs(3, 3);
methodVisitor.visitEnd();
}
{
methodVisitor = classWriter.visitMethod(ACC_PUBLIC | ACC_STATIC, "squareN", "([JI[J)V", null, null);
methodVisitor.visitCode();
methodVisitor.visitMethodInsn(INVOKESTATIC, "org/bouncycastle/math/raw/Nat576", "createExt64", "()[J", false);
methodVisitor.visitVarInsn(ASTORE, 3);
methodVisitor.visitVarInsn(ALOAD, 0);
methodVisitor.visitVarInsn(ALOAD, 3);
methodVisitor.visitMethodInsn(INVOKESTATIC, "org/bouncycastle/math/ec/custom/sec/SecT571Field", "implSquare", "([J[J)V", false);
methodVisitor.visitVarInsn(ALOAD, 3);
methodVisitor.visitVarInsn(ALOAD, 2);
methodVisitor.visitMethodInsn(INVOKESTATIC, "org/bouncycastle/math/ec/custom/sec/SecT571Field", "reduce", "([J[J)V", false);
Label label0 = new Label();
methodVisitor.visitLabel(label0);
methodVisitor.visitIincInsn(1, -1);
methodVisitor.visitVarInsn(ILOAD, 1);
Label label1 = new Label();
methodVisitor.visitJumpInsn(IFLE, label1);
methodVisitor.visitVarInsn(ALOAD, 2);
methodVisitor.visitVarInsn(ALOAD, 3);
methodVisitor.visitMethodInsn(INVOKESTATIC, "org/bouncycastle/math/ec/custom/sec/SecT571Field", "implSquare", "([J[J)V", false);
methodVisitor.visitVarInsn(ALOAD, 3);
methodVisitor.visitVarInsn(ALOAD, 2);
methodVisitor.visitMethodInsn(INVOKESTATIC, "org/bouncycastle/math/ec/custom/sec/SecT571Field", "reduce", "([J[J)V", false);
methodVisitor.visitJumpInsn(GOTO, label0);
methodVisitor.visitLabel(label1);
methodVisitor.visitInsn(RETURN);
methodVisitor.visitMaxs(2, 4);
methodVisitor.visitEnd();
}
{
methodVisitor = classWriter.visitMethod(ACC_PUBLIC | ACC_STATIC, "trace", "([J)I", null, null);
methodVisitor.visitCode();
methodVisitor.visitVarInsn(ALOAD, 0);
methodVisitor.visitInsn(ICONST_0);
methodVisitor.visitInsn(LALOAD);
methodVisitor.visitVarInsn(ALOAD, 0);
methodVisitor.visitIntInsn(BIPUSH, 8);
methodVisitor.visitInsn(LALOAD);
methodVisitor.visitIntInsn(BIPUSH, 49);
methodVisitor.visitInsn(LUSHR);
methodVisitor.visitInsn(LXOR);
methodVisitor.visitVarInsn(ALOAD, 0);
methodVisitor.visitIntInsn(BIPUSH, 8);
methodVisitor.visitInsn(LALOAD);
methodVisitor.visitIntInsn(BIPUSH, 57);
methodVisitor.visitInsn(LUSHR);
methodVisitor.visitInsn(LXOR);
methodVisitor.visitInsn(L2I);
methodVisitor.visitInsn(ICONST_1);
methodVisitor.visitInsn(IAND);
methodVisitor.visitInsn(IRETURN);
methodVisitor.visitMaxs(5, 1);
methodVisitor.visitEnd();
}
{
methodVisitor = classWriter.visitMethod(ACC_PROTECTED | ACC_STATIC, "implMultiply", "([J[J[J)V", null, null);
methodVisitor.visitCode();
methodVisitor.visitVarInsn(ALOAD, 1);
methodVisitor.visitMethodInsn(INVOKESTATIC, "org/bouncycastle/math/ec/custom/sec/SecT571Field", "precompMultiplicand", "([J)[J", false);
methodVisitor.visitVarInsn(ASTORE, 3);
methodVisitor.visitVarInsn(ALOAD, 0);
methodVisitor.visitVarInsn(ALOAD, 3);
methodVisitor.visitVarInsn(ALOAD, 2);
methodVisitor.visitMethodInsn(INVOKESTATIC, "org/bouncycastle/math/ec/custom/sec/SecT571Field", "implMultiplyPrecomp", "([J[J[J)V", false);
methodVisitor.visitInsn(RETURN);
methodVisitor.visitMaxs(3, 4);
methodVisitor.visitEnd();
}
{
methodVisitor = classWriter.visitMethod(ACC_PROTECTED | ACC_STATIC, "implMultiplyPrecomp", "([J[J[J)V", null, null);
methodVisitor.visitCode();
methodVisitor.visitIntInsn(BIPUSH, 15);
methodVisitor.visitVarInsn(ISTORE, 3);
methodVisitor.visitIntInsn(BIPUSH, 56);
methodVisitor.visitVarInsn(ISTORE, 4);
Label label0 = new Label();
methodVisitor.visitLabel(label0);
methodVisitor.visitVarInsn(ILOAD, 4);
Label label1 = new Label();
methodVisitor.visitJumpInsn(IFLT, label1);
methodVisitor.visitInsn(ICONST_1);
methodVisitor.visitVarInsn(ISTORE, 5);
Label label2 = new Label();
methodVisitor.visitLabel(label2);
methodVisitor.visitVarInsn(ILOAD, 5);
methodVisitor.visitIntInsn(BIPUSH, 9);
Label label3 = new Label();
methodVisitor.visitJumpInsn(IF_ICMPGE, label3);
methodVisitor.visitVarInsn(ALOAD, 0);
methodVisitor.visitVarInsn(ILOAD, 5);
methodVisitor.visitInsn(LALOAD);
methodVisitor.visitVarInsn(ILOAD, 4);
methodVisitor.visitInsn(LUSHR);
methodVisitor.visitInsn(L2I);
methodVisitor.visitVarInsn(ISTORE, 6);
methodVisitor.visitVarInsn(ILOAD, 6);
methodVisitor.visitVarInsn(ILOAD, 3);
methodVisitor.visitInsn(IAND);
methodVisitor.visitVarInsn(ISTORE, 7);
methodVisitor.visitVarInsn(ILOAD, 6);
methodVisitor.visitInsn(ICONST_4);
methodVisitor.visitInsn(IUSHR);
methodVisitor.visitVarInsn(ILOAD, 3);
methodVisitor.visitInsn(IAND);
methodVisitor.visitVarInsn(ISTORE, 8);
methodVisitor.visitVarInsn(ALOAD, 1);
methodVisitor.visitIntInsn(BIPUSH, 9);
methodVisitor.visitVarInsn(ILOAD, 7);
methodVisitor.visitInsn(IMUL);
methodVisitor.visitVarInsn(ALOAD, 1);
methodVisitor.visitIntInsn(BIPUSH, 9);
methodVisitor.visitVarInsn(ILOAD, 8);
methodVisitor.visitIntInsn(BIPUSH, 16);
methodVisitor.visitInsn(IADD);
methodVisitor.visitInsn(IMUL);
methodVisitor.visitVarInsn(ALOAD, 2);
methodVisitor.visitVarInsn(ILOAD, 5);
methodVisitor.visitInsn(ICONST_1);
methodVisitor.visitInsn(ISUB);
methodVisitor.visitMethodInsn(INVOKESTATIC, "org/bouncycastle/math/ec/custom/sec/SecT571Field", "addBothTo", "([JI[JI[JI)V", false);
methodVisitor.visitIincInsn(5, 2);
methodVisitor.visitJumpInsn(GOTO, label2);
methodVisitor.visitLabel(label3);
methodVisitor.visitIntInsn(BIPUSH, 16);
methodVisitor.visitVarInsn(ALOAD, 2);
methodVisitor.visitInsn(ICONST_0);
methodVisitor.visitIntInsn(BIPUSH, 8);
methodVisitor.visitInsn(LCONST_0);
methodVisitor.visitMethodInsn(INVOKESTATIC, "org/bouncycastle/math/raw/Nat", "shiftUpBits64", "(I[JIIJ)J", false);
methodVisitor.visitInsn(POP2);
methodVisitor.visitIincInsn(4, -8);
methodVisitor.visitJumpInsn(GOTO, label0);
methodVisitor.visitLabel(label1);
methodVisitor.visitIntInsn(BIPUSH, 56);
methodVisitor.visitVarInsn(ISTORE, 4);
Label label4 = new Label();
methodVisitor.visitLabel(label4);
methodVisitor.visitVarInsn(ILOAD, 4);
Label label5 = new Label();
methodVisitor.visitJumpInsn(IFLT, label5);
methodVisitor.visitInsn(ICONST_0);
methodVisitor.visitVarInsn(ISTORE, 5);
Label label6 = new Label();
methodVisitor.visitLabel(label6);
methodVisitor.visitVarInsn(ILOAD, 5);
methodVisitor.visitIntInsn(BIPUSH, 9);
Label label7 = new Label();
methodVisitor.visitJumpInsn(IF_ICMPGE, label7);
methodVisitor.visitVarInsn(ALOAD, 0);
methodVisitor.visitVarInsn(ILOAD, 5);
methodVisitor.visitInsn(LALOAD);
methodVisitor.visitVarInsn(ILOAD, 4);
methodVisitor.visitInsn(LUSHR);
methodVisitor.visitInsn(L2I);
methodVisitor.visitVarInsn(ISTORE, 6);
methodVisitor.visitVarInsn(ILOAD, 6);
methodVisitor.visitVarInsn(ILOAD, 3);
methodVisitor.visitInsn(IAND);
methodVisitor.visitVarInsn(ISTORE, 7);
methodVisitor.visitVarInsn(ILOAD, 6);
methodVisitor.visitInsn(ICONST_4);
methodVisitor.visitInsn(IUSHR);
methodVisitor.visitVarInsn(ILOAD, 3);
methodVisitor.visitInsn(IAND);
methodVisitor.visitVarInsn(ISTORE, 8);
methodVisitor.visitVarInsn(ALOAD, 1);
methodVisitor.visitIntInsn(BIPUSH, 9);
methodVisitor.visitVarInsn(ILOAD, 7);
methodVisitor.visitInsn(IMUL);
methodVisitor.visitVarInsn(ALOAD, 1);
methodVisitor.visitIntInsn(BIPUSH, 9);
methodVisitor.visitVarInsn(ILOAD, 8);
methodVisitor.visitIntInsn(BIPUSH, 16);
methodVisitor.visitInsn(IADD);
methodVisitor.visitInsn(IMUL);
methodVisitor.visitVarInsn(ALOAD, 2);
methodVisitor.visitVarInsn(ILOAD, 5);
methodVisitor.visitMethodInsn(INVOKESTATIC, "org/bouncycastle/math/ec/custom/sec/SecT571Field", "addBothTo", "([JI[JI[JI)V", false);
methodVisitor.visitIincInsn(5, 2);
methodVisitor.visitJumpInsn(GOTO, label6);
methodVisitor.visitLabel(label7);
methodVisitor.visitVarInsn(ILOAD, 4);
Label label8 = new Label();
methodVisitor.visitJumpInsn(IFLE, label8);
methodVisitor.visitIntInsn(BIPUSH, 18);
methodVisitor.visitVarInsn(ALOAD, 2);
methodVisitor.visitInsn(ICONST_0);
methodVisitor.visitIntInsn(BIPUSH, 8);
methodVisitor.visitInsn(LCONST_0);
methodVisitor.visitMethodInsn(INVOKESTATIC, "org/bouncycastle/math/raw/Nat", "shiftUpBits64", "(I[JIIJ)J", false);
methodVisitor.visitInsn(POP2);
methodVisitor.visitLabel(label8);
methodVisitor.visitIincInsn(4, -8);
methodVisitor.visitJumpInsn(GOTO, label4);
methodVisitor.visitLabel(label5);
methodVisitor.visitInsn(RETURN);
methodVisitor.visitMaxs(7, 9);
methodVisitor.visitEnd();
}
{
methodVisitor = classWriter.visitMethod(ACC_PROTECTED | ACC_STATIC, "implMulwAcc", "([JJ[JI)V", null, null);
methodVisitor.visitCode();
methodVisitor.visitIntInsn(BIPUSH, 32);
methodVisitor.visitIntInsn(NEWARRAY, T_LONG);
methodVisitor.visitVarInsn(ASTORE, 5);
methodVisitor.visitVarInsn(ALOAD, 5);
methodVisitor.visitInsn(ICONST_1);
methodVisitor.visitVarInsn(LLOAD, 1);
methodVisitor.visitInsn(LASTORE);
methodVisitor.visitInsn(ICONST_2);
methodVisitor.visitVarInsn(ISTORE, 6);
Label label0 = new Label();
methodVisitor.visitLabel(label0);
methodVisitor.visitVarInsn(ILOAD, 6);
methodVisitor.visitIntInsn(BIPUSH, 32);
Label label1 = new Label();
methodVisitor.visitJumpInsn(IF_ICMPGE, label1);
methodVisitor.visitVarInsn(ALOAD, 5);
methodVisitor.visitVarInsn(ILOAD, 6);
methodVisitor.visitVarInsn(ALOAD, 5);
methodVisitor.visitVarInsn(ILOAD, 6);
methodVisitor.visitInsn(ICONST_1);
methodVisitor.visitInsn(IUSHR);
methodVisitor.visitInsn(LALOAD);
methodVisitor.visitInsn(ICONST_1);
methodVisitor.visitInsn(LSHL);
methodVisitor.visitInsn(LASTORE);
methodVisitor.visitVarInsn(ALOAD, 5);
methodVisitor.visitVarInsn(ILOAD, 6);
methodVisitor.visitInsn(ICONST_1);
methodVisitor.visitInsn(IADD);
methodVisitor.visitVarInsn(ALOAD, 5);
methodVisitor.visitVarInsn(ILOAD, 6);
methodVisitor.visitInsn(LALOAD);
methodVisitor.visitVarInsn(LLOAD, 1);
methodVisitor.visitInsn(LXOR);
methodVisitor.visitInsn(LASTORE);
methodVisitor.visitIincInsn(6, 2);
methodVisitor.visitJumpInsn(GOTO, label0);
methodVisitor.visitLabel(label1);
methodVisitor.visitInsn(LCONST_0);
methodVisitor.visitVarInsn(LSTORE, 6);
methodVisitor.visitInsn(ICONST_0);
methodVisitor.visitVarInsn(ISTORE, 8);
Label label2 = new Label();
methodVisitor.visitLabel(label2);
methodVisitor.visitVarInsn(ILOAD, 8);
methodVisitor.visitIntInsn(BIPUSH, 9);
Label label3 = new Label();
methodVisitor.visitJumpInsn(IF_ICMPGE, label3);
methodVisitor.visitVarInsn(ALOAD, 0);
methodVisitor.visitVarInsn(ILOAD, 8);
methodVisitor.visitInsn(LALOAD);
methodVisitor.visitVarInsn(LSTORE, 9);
methodVisitor.visitVarInsn(LLOAD, 9);
methodVisitor.visitInsn(L2I);
methodVisitor.visitVarInsn(ISTORE, 11);
methodVisitor.visitVarInsn(LLOAD, 6);
methodVisitor.visitVarInsn(ALOAD, 5);
methodVisitor.visitVarInsn(ILOAD, 11);
methodVisitor.visitIntInsn(BIPUSH, 31);
methodVisitor.visitInsn(IAND);
methodVisitor.visitInsn(LALOAD);
methodVisitor.visitInsn(LXOR);
methodVisitor.visitVarInsn(LSTORE, 6);
methodVisitor.visitInsn(LCONST_0);
methodVisitor.visitVarInsn(LSTORE, 14);
methodVisitor.visitIntInsn(BIPUSH, 60);
methodVisitor.visitVarInsn(ISTORE, 16);
Label label4 = new Label();
methodVisitor.visitLabel(label4);
methodVisitor.visitVarInsn(LLOAD, 9);
methodVisitor.visitVarInsn(ILOAD, 16);
methodVisitor.visitInsn(LUSHR);
methodVisitor.visitInsn(L2I);
methodVisitor.visitVarInsn(ISTORE, 11);
methodVisitor.visitVarInsn(ALOAD, 5);
methodVisitor.visitVarInsn(ILOAD, 11);
methodVisitor.visitIntInsn(BIPUSH, 31);
methodVisitor.visitInsn(IAND);
methodVisitor.visitInsn(LALOAD);
methodVisitor.visitVarInsn(LSTORE, 12);
methodVisitor.visitVarInsn(LLOAD, 6);
methodVisitor.visitVarInsn(LLOAD, 12);
methodVisitor.visitVarInsn(ILOAD, 16);
methodVisitor.visitInsn(LSHL);
methodVisitor.visitInsn(LXOR);
methodVisitor.visitVarInsn(LSTORE, 6);
methodVisitor.visitVarInsn(LLOAD, 14);
methodVisitor.visitVarInsn(LLOAD, 12);
methodVisitor.visitVarInsn(ILOAD, 16);
methodVisitor.visitInsn(INEG);
methodVisitor.visitInsn(LUSHR);
methodVisitor.visitInsn(LXOR);
methodVisitor.visitVarInsn(LSTORE, 14);
methodVisitor.visitIincInsn(16, -5);
methodVisitor.visitVarInsn(ILOAD, 16);
methodVisitor.visitJumpInsn(IFGT, label4);
methodVisitor.visitInsn(ICONST_0);
methodVisitor.visitVarInsn(ISTORE, 17);
Label label5 = new Label();
methodVisitor.visitLabel(label5);
methodVisitor.visitVarInsn(ILOAD, 17);
methodVisitor.visitInsn(ICONST_4);
Label label6 = new Label();
methodVisitor.visitJumpInsn(IF_ICMPGE, label6);
methodVisitor.visitVarInsn(LLOAD, 9);
methodVisitor.visitLdcInsn(new Long(-1190112520884487202L));
methodVisitor.visitInsn(LAND);
methodVisitor.visitInsn(ICONST_1);
methodVisitor.visitInsn(LUSHR);
methodVisitor.visitVarInsn(LSTORE, 9);
methodVisitor.visitVarInsn(LLOAD, 14);
methodVisitor.visitVarInsn(LLOAD, 9);
methodVisitor.visitVarInsn(LLOAD, 1);
methodVisitor.visitVarInsn(ILOAD, 17);
methodVisitor.visitInsn(LSHL);
methodVisitor.visitIntInsn(BIPUSH, 63);
methodVisitor.visitInsn(LSHR);
methodVisitor.visitInsn(LAND);
methodVisitor.visitInsn(LXOR);
methodVisitor.visitVarInsn(LSTORE, 14);
methodVisitor.visitIincInsn(17, 1);
methodVisitor.visitJumpInsn(GOTO, label5);
methodVisitor.visitLabel(label6);
methodVisitor.visitVarInsn(ALOAD, 3);
methodVisitor.visitVarInsn(ILOAD, 4);
methodVisitor.visitVarInsn(ILOAD, 8);
methodVisitor.visitInsn(IADD);
methodVisitor.visitInsn(DUP2);
methodVisitor.visitInsn(LALOAD);
methodVisitor.visitVarInsn(LLOAD, 6);
methodVisitor.visitInsn(LXOR);
methodVisitor.visitInsn(LASTORE);
methodVisitor.visitVarInsn(LLOAD, 14);
methodVisitor.visitVarInsn(LSTORE, 6);
methodVisitor.visitIincInsn(8, 1);
methodVisitor.visitJumpInsn(GOTO, label2);
methodVisitor.visitLabel(label3);
methodVisitor.visitVarInsn(ALOAD, 3);
methodVisitor.visitVarInsn(ILOAD, 4);
methodVisitor.visitIntInsn(BIPUSH, 9);
methodVisitor.visitInsn(IADD);
methodVisitor.visitInsn(DUP2);
methodVisitor.visitInsn(LALOAD);
methodVisitor.visitVarInsn(LLOAD, 6);
methodVisitor.visitInsn(LXOR);
methodVisitor.visitInsn(LASTORE);
methodVisitor.visitInsn(RETURN);
methodVisitor.visitMaxs(7, 18);
methodVisitor.visitEnd();
}
{
methodVisitor = classWriter.visitMethod(ACC_PROTECTED | ACC_STATIC, "implSquare", "([J[J)V", null, null);
methodVisitor.visitCode();
methodVisitor.visitVarInsn(ALOAD, 0);
methodVisitor.visitInsn(ICONST_0);
methodVisitor.visitInsn(LALOAD);
methodVisitor.visitVarInsn(ALOAD, 1);
methodVisitor.visitInsn(ICONST_0);
methodVisitor.visitMethodInsn(INVOKESTATIC, "org/bouncycastle/math/raw/Interleave", "expand64To128", "(J[JI)V", false);
methodVisitor.visitVarInsn(ALOAD, 0);
methodVisitor.visitInsn(ICONST_1);
methodVisitor.visitInsn(LALOAD);
methodVisitor.visitVarInsn(ALOAD, 1);
methodVisitor.visitInsn(ICONST_2);
methodVisitor.visitMethodInsn(INVOKESTATIC, "org/bouncycastle/math/raw/Interleave", "expand64To128", "(J[JI)V", false);
methodVisitor.visitVarInsn(ALOAD, 0);
methodVisitor.visitInsn(ICONST_2);
methodVisitor.visitInsn(LALOAD);
methodVisitor.visitVarInsn(ALOAD, 1);
methodVisitor.visitInsn(ICONST_4);
methodVisitor.visitMethodInsn(INVOKESTATIC, "org/bouncycastle/math/raw/Interleave", "expand64To128", "(J[JI)V", false);
methodVisitor.visitVarInsn(ALOAD, 0);
methodVisitor.visitInsn(ICONST_3);
methodVisitor.visitInsn(LALOAD);
methodVisitor.visitVarInsn(ALOAD, 1);
methodVisitor.visitIntInsn(BIPUSH, 6);
methodVisitor.visitMethodInsn(INVOKESTATIC, "org/bouncycastle/math/raw/Interleave", "expand64To128", "(J[JI)V", false);
methodVisitor.visitVarInsn(ALOAD, 0);
methodVisitor.visitInsn(ICONST_4);
methodVisitor.visitInsn(LALOAD);
methodVisitor.visitVarInsn(ALOAD, 1);
methodVisitor.visitIntInsn(BIPUSH, 8);
methodVisitor.visitMethodInsn(INVOKESTATIC, "org/bouncycastle/math/raw/Interleave", "expand64To128", "(J[JI)V", false);
methodVisitor.visitVarInsn(ALOAD, 0);
methodVisitor.visitInsn(ICONST_5);
methodVisitor.visitInsn(LALOAD);
methodVisitor.visitVarInsn(ALOAD, 1);
methodVisitor.visitIntInsn(BIPUSH, 10);
methodVisitor.visitMethodInsn(INVOKESTATIC, "org/bouncycastle/math/raw/Interleave", "expand64To128", "(J[JI)V", false);
methodVisitor.visitVarInsn(ALOAD, 0);
methodVisitor.visitIntInsn(BIPUSH, 6);
methodVisitor.visitInsn(LALOAD);
methodVisitor.visitVarInsn(ALOAD, 1);
methodVisitor.visitIntInsn(BIPUSH, 12);
methodVisitor.visitMethodInsn(INVOKESTATIC, "org/bouncycastle/math/raw/Interleave", "expand64To128", "(J[JI)V", false);
methodVisitor.visitVarInsn(ALOAD, 0);
methodVisitor.visitIntInsn(BIPUSH, 7);
methodVisitor.visitInsn(LALOAD);
methodVisitor.visitVarInsn(ALOAD, 1);
methodVisitor.visitIntInsn(BIPUSH, 14);
methodVisitor.visitMethodInsn(INVOKESTATIC, "org/bouncycastle/math/raw/Interleave", "expand64To128", "(J[JI)V", false);
methodVisitor.visitVarInsn(ALOAD, 0);
methodVisitor.visitIntInsn(BIPUSH, 8);
methodVisitor.visitInsn(LALOAD);
methodVisitor.visitVarInsn(ALOAD, 1);
methodVisitor.visitIntInsn(BIPUSH, 16);
methodVisitor.visitMethodInsn(INVOKESTATIC, "org/bouncycastle/math/raw/Interleave", "expand64To128", "(J[JI)V", false);
methodVisitor.visitInsn(RETURN);
methodVisitor.visitMaxs(4, 2);
methodVisitor.visitEnd();
}
{
methodVisitor = classWriter.visitMethod(ACC_STATIC, "<clinit>", "()V", null, null);
methodVisitor.visitCode();
methodVisitor.visitIntInsn(BIPUSH, 9);
methodVisitor.visitIntInsn(NEWARRAY, T_LONG);
methodVisitor.visitInsn(DUP);
methodVisitor.visitInsn(ICONST_0);
methodVisitor.visitLdcInsn(new Long(3161836309350906777L));
methodVisitor.visitInsn(LASTORE);
methodVisitor.visitInsn(DUP);
methodVisitor.visitInsn(ICONST_1);
methodVisitor.visitLdcInsn(new Long(-7642453882179322845L));
methodVisitor.visitInsn(LASTORE);
methodVisitor.visitInsn(DUP);
methodVisitor.visitInsn(ICONST_2);
methodVisitor.visitLdcInsn(new Long(-3821226941089661423L));
methodVisitor.visitInsn(LASTORE);
methodVisitor.visitInsn(DUP);
methodVisitor.visitInsn(ICONST_3);
methodVisitor.visitLdcInsn(new Long(7312758566309945096L));
methodVisitor.visitInsn(LASTORE);
methodVisitor.visitInsn(DUP);
methodVisitor.visitInsn(ICONST_4);
methodVisitor.visitLdcInsn(new Long(-556661012383879292L));
methodVisitor.visitInsn(LASTORE);
methodVisitor.visitInsn(DUP);
methodVisitor.visitInsn(ICONST_5);
methodVisitor.visitLdcInsn(new Long(8945041530681231562L));
methodVisitor.visitInsn(LASTORE);
methodVisitor.visitInsn(DUP);
methodVisitor.visitIntInsn(BIPUSH, 6);
methodVisitor.visitLdcInsn(new Long(-4750851271514160027L));
methodVisitor.visitInsn(LASTORE);
methodVisitor.visitInsn(DUP);
methodVisitor.visitIntInsn(BIPUSH, 7);
methodVisitor.visitLdcInsn(new Long(6847946401097695794L));
methodVisitor.visitInsn(LASTORE);
methodVisitor.visitInsn(DUP);
methodVisitor.visitIntInsn(BIPUSH, 8);
methodVisitor.visitLdcInsn(new Long(541669439031730457L));
methodVisitor.visitInsn(LASTORE);
methodVisitor.visitFieldInsn(PUTSTATIC, "org/bouncycastle/math/ec/custom/sec/SecT571Field", "ROOT_Z", "[J");
methodVisitor.visitInsn(RETURN);
methodVisitor.visitMaxs(5, 0);
methodVisitor.visitEnd();
}
classWriter.visitEnd();

return classWriter.toByteArray();
}
}
