package asm.org.fusesource.hawtbuf;
import org.objectweb.asm.AnnotationVisitor;
import org.objectweb.asm.Attribute;
import org.objectweb.asm.ClassReader;
import org.objectweb.asm.ClassWriter;
import org.objectweb.asm.ConstantDynamic;
import org.objectweb.asm.FieldVisitor;
import org.objectweb.asm.Handle;
import org.objectweb.asm.Label;
import org.objectweb.asm.MethodVisitor;
import org.objectweb.asm.Opcodes;
import org.objectweb.asm.RecordComponentVisitor;
import org.objectweb.asm.Type;
import org.objectweb.asm.TypePath;
public class BufferEditor$BigEndianBufferEditorDump implements Opcodes {

public static byte[] dump () throws Exception {

ClassWriter classWriter = new ClassWriter(0);
FieldVisitor fieldVisitor;
RecordComponentVisitor recordComponentVisitor;
MethodVisitor methodVisitor;
AnnotationVisitor annotationVisitor0;

classWriter.visit(V1_5, ACC_SUPER, "org/fusesource/hawtbuf/BufferEditor$BigEndianBufferEditor", null, "org/fusesource/hawtbuf/BufferEditor", null);

classWriter.visitInnerClass("org/fusesource/hawtbuf/BufferEditor$BigEndianBufferEditor", "org/fusesource/hawtbuf/BufferEditor", "BigEndianBufferEditor", ACC_STATIC);

classWriter.visitInnerClass("org/fusesource/hawtbuf/BufferEditor$1", "org/fusesource/hawtbuf/BufferEditor", null, ACC_STATIC | ACC_SYNTHETIC);

{
fieldVisitor = classWriter.visitField(ACC_FINAL | ACC_STATIC | ACC_SYNTHETIC, "$assertionsDisabled", "Z", null, null);
fieldVisitor.visitEnd();
}
{
methodVisitor = classWriter.visitMethod(0, "<init>", "(Lorg/fusesource/hawtbuf/Buffer;)V", null, null);
methodVisitor.visitCode();
methodVisitor.visitVarInsn(ALOAD, 0);
methodVisitor.visitVarInsn(ALOAD, 1);
methodVisitor.visitInsn(ACONST_NULL);
methodVisitor.visitMethodInsn(INVOKESPECIAL, "org/fusesource/hawtbuf/BufferEditor", "<init>", "(Lorg/fusesource/hawtbuf/Buffer;Lorg/fusesource/hawtbuf/BufferEditor$1;)V", false);
methodVisitor.visitInsn(RETURN);
methodVisitor.visitMaxs(3, 2);
methodVisitor.visitEnd();
}
{
methodVisitor = classWriter.visitMethod(ACC_PUBLIC, "readShort", "()S", null, null);
methodVisitor.visitCode();
methodVisitor.visitFieldInsn(GETSTATIC, "org/fusesource/hawtbuf/BufferEditor$BigEndianBufferEditor", "$assertionsDisabled", "Z");
Label label0 = new Label();
methodVisitor.visitJumpInsn(IFNE, label0);
methodVisitor.visitVarInsn(ALOAD, 0);
methodVisitor.visitInsn(ICONST_2);
methodVisitor.visitMethodInsn(INVOKEVIRTUAL, "org/fusesource/hawtbuf/BufferEditor$BigEndianBufferEditor", "hasCapacity", "(I)Z", false);
methodVisitor.visitJumpInsn(IFNE, label0);
methodVisitor.visitTypeInsn(NEW, "java/lang/AssertionError");
methodVisitor.visitInsn(DUP);
methodVisitor.visitMethodInsn(INVOKESPECIAL, "java/lang/AssertionError", "<init>", "()V", false);
methodVisitor.visitInsn(ATHROW);
methodVisitor.visitLabel(label0);
methodVisitor.visitVarInsn(ALOAD, 0);
methodVisitor.visitMethodInsn(INVOKEVIRTUAL, "org/fusesource/hawtbuf/BufferEditor$BigEndianBufferEditor", "read", "()I", false);
methodVisitor.visitIntInsn(BIPUSH, 8);
methodVisitor.visitInsn(ISHL);
methodVisitor.visitVarInsn(ALOAD, 0);
methodVisitor.visitMethodInsn(INVOKEVIRTUAL, "org/fusesource/hawtbuf/BufferEditor$BigEndianBufferEditor", "read", "()I", false);
methodVisitor.visitInsn(ICONST_0);
methodVisitor.visitInsn(ISHL);
methodVisitor.visitInsn(IADD);
methodVisitor.visitInsn(I2S);
methodVisitor.visitInsn(IRETURN);
methodVisitor.visitMaxs(3, 1);
methodVisitor.visitEnd();
}
{
methodVisitor = classWriter.visitMethod(ACC_PUBLIC, "readUnsignedShort", "()I", null, null);
methodVisitor.visitCode();
methodVisitor.visitFieldInsn(GETSTATIC, "org/fusesource/hawtbuf/BufferEditor$BigEndianBufferEditor", "$assertionsDisabled", "Z");
Label label0 = new Label();
methodVisitor.visitJumpInsn(IFNE, label0);
methodVisitor.visitVarInsn(ALOAD, 0);
methodVisitor.visitInsn(ICONST_2);
methodVisitor.visitMethodInsn(INVOKEVIRTUAL, "org/fusesource/hawtbuf/BufferEditor$BigEndianBufferEditor", "hasCapacity", "(I)Z", false);
methodVisitor.visitJumpInsn(IFNE, label0);
methodVisitor.visitTypeInsn(NEW, "java/lang/AssertionError");
methodVisitor.visitInsn(DUP);
methodVisitor.visitMethodInsn(INVOKESPECIAL, "java/lang/AssertionError", "<init>", "()V", false);
methodVisitor.visitInsn(ATHROW);
methodVisitor.visitLabel(label0);
methodVisitor.visitVarInsn(ALOAD, 0);
methodVisitor.visitMethodInsn(INVOKEVIRTUAL, "org/fusesource/hawtbuf/BufferEditor$BigEndianBufferEditor", "read", "()I", false);
methodVisitor.visitIntInsn(BIPUSH, 8);
methodVisitor.visitInsn(ISHL);
methodVisitor.visitVarInsn(ALOAD, 0);
methodVisitor.visitMethodInsn(INVOKEVIRTUAL, "org/fusesource/hawtbuf/BufferEditor$BigEndianBufferEditor", "read", "()I", false);
methodVisitor.visitInsn(ICONST_0);
methodVisitor.visitInsn(ISHL);
methodVisitor.visitInsn(IADD);
methodVisitor.visitInsn(IRETURN);
methodVisitor.visitMaxs(3, 1);
methodVisitor.visitEnd();
}
{
methodVisitor = classWriter.visitMethod(ACC_PUBLIC, "readChar", "()C", null, null);
methodVisitor.visitCode();
methodVisitor.visitFieldInsn(GETSTATIC, "org/fusesource/hawtbuf/BufferEditor$BigEndianBufferEditor", "$assertionsDisabled", "Z");
Label label0 = new Label();
methodVisitor.visitJumpInsn(IFNE, label0);
methodVisitor.visitVarInsn(ALOAD, 0);
methodVisitor.visitInsn(ICONST_2);
methodVisitor.visitMethodInsn(INVOKEVIRTUAL, "org/fusesource/hawtbuf/BufferEditor$BigEndianBufferEditor", "hasCapacity", "(I)Z", false);
methodVisitor.visitJumpInsn(IFNE, label0);
methodVisitor.visitTypeInsn(NEW, "java/lang/AssertionError");
methodVisitor.visitInsn(DUP);
methodVisitor.visitMethodInsn(INVOKESPECIAL, "java/lang/AssertionError", "<init>", "()V", false);
methodVisitor.visitInsn(ATHROW);
methodVisitor.visitLabel(label0);
methodVisitor.visitVarInsn(ALOAD, 0);
methodVisitor.visitMethodInsn(INVOKEVIRTUAL, "org/fusesource/hawtbuf/BufferEditor$BigEndianBufferEditor", "read", "()I", false);
methodVisitor.visitIntInsn(BIPUSH, 8);
methodVisitor.visitInsn(ISHL);
methodVisitor.visitVarInsn(ALOAD, 0);
methodVisitor.visitMethodInsn(INVOKEVIRTUAL, "org/fusesource/hawtbuf/BufferEditor$BigEndianBufferEditor", "read", "()I", false);
methodVisitor.visitInsn(ICONST_0);
methodVisitor.visitInsn(ISHL);
methodVisitor.visitInsn(IADD);
methodVisitor.visitInsn(I2C);
methodVisitor.visitInsn(IRETURN);
methodVisitor.visitMaxs(3, 1);
methodVisitor.visitEnd();
}
{
methodVisitor = classWriter.visitMethod(ACC_PUBLIC, "readInt", "()I", null, null);
methodVisitor.visitCode();
methodVisitor.visitFieldInsn(GETSTATIC, "org/fusesource/hawtbuf/BufferEditor$BigEndianBufferEditor", "$assertionsDisabled", "Z");
Label label0 = new Label();
methodVisitor.visitJumpInsn(IFNE, label0);
methodVisitor.visitVarInsn(ALOAD, 0);
methodVisitor.visitInsn(ICONST_4);
methodVisitor.visitMethodInsn(INVOKEVIRTUAL, "org/fusesource/hawtbuf/BufferEditor$BigEndianBufferEditor", "hasCapacity", "(I)Z", false);
methodVisitor.visitJumpInsn(IFNE, label0);
methodVisitor.visitTypeInsn(NEW, "java/lang/AssertionError");
methodVisitor.visitInsn(DUP);
methodVisitor.visitMethodInsn(INVOKESPECIAL, "java/lang/AssertionError", "<init>", "()V", false);
methodVisitor.visitInsn(ATHROW);
methodVisitor.visitLabel(label0);
methodVisitor.visitVarInsn(ALOAD, 0);
methodVisitor.visitMethodInsn(INVOKEVIRTUAL, "org/fusesource/hawtbuf/BufferEditor$BigEndianBufferEditor", "read", "()I", false);
methodVisitor.visitIntInsn(BIPUSH, 24);
methodVisitor.visitInsn(ISHL);
methodVisitor.visitVarInsn(ALOAD, 0);
methodVisitor.visitMethodInsn(INVOKEVIRTUAL, "org/fusesource/hawtbuf/BufferEditor$BigEndianBufferEditor", "read", "()I", false);
methodVisitor.visitIntInsn(BIPUSH, 16);
methodVisitor.visitInsn(ISHL);
methodVisitor.visitInsn(IADD);
methodVisitor.visitVarInsn(ALOAD, 0);
methodVisitor.visitMethodInsn(INVOKEVIRTUAL, "org/fusesource/hawtbuf/BufferEditor$BigEndianBufferEditor", "read", "()I", false);
methodVisitor.visitIntInsn(BIPUSH, 8);
methodVisitor.visitInsn(ISHL);
methodVisitor.visitInsn(IADD);
methodVisitor.visitVarInsn(ALOAD, 0);
methodVisitor.visitMethodInsn(INVOKEVIRTUAL, "org/fusesource/hawtbuf/BufferEditor$BigEndianBufferEditor", "read", "()I", false);
methodVisitor.visitInsn(ICONST_0);
methodVisitor.visitInsn(ISHL);
methodVisitor.visitInsn(IADD);
methodVisitor.visitInsn(IRETURN);
methodVisitor.visitMaxs(3, 1);
methodVisitor.visitEnd();
}
{
methodVisitor = classWriter.visitMethod(ACC_PUBLIC, "readLong", "()J", null, null);
methodVisitor.visitCode();
methodVisitor.visitFieldInsn(GETSTATIC, "org/fusesource/hawtbuf/BufferEditor$BigEndianBufferEditor", "$assertionsDisabled", "Z");
Label label0 = new Label();
methodVisitor.visitJumpInsn(IFNE, label0);
methodVisitor.visitVarInsn(ALOAD, 0);
methodVisitor.visitIntInsn(BIPUSH, 8);
methodVisitor.visitMethodInsn(INVOKEVIRTUAL, "org/fusesource/hawtbuf/BufferEditor$BigEndianBufferEditor", "hasCapacity", "(I)Z", false);
methodVisitor.visitJumpInsn(IFNE, label0);
methodVisitor.visitTypeInsn(NEW, "java/lang/AssertionError");
methodVisitor.visitInsn(DUP);
methodVisitor.visitMethodInsn(INVOKESPECIAL, "java/lang/AssertionError", "<init>", "()V", false);
methodVisitor.visitInsn(ATHROW);
methodVisitor.visitLabel(label0);
methodVisitor.visitVarInsn(ALOAD, 0);
methodVisitor.visitMethodInsn(INVOKEVIRTUAL, "org/fusesource/hawtbuf/BufferEditor$BigEndianBufferEditor", "read", "()I", false);
methodVisitor.visitInsn(I2L);
methodVisitor.visitIntInsn(BIPUSH, 56);
methodVisitor.visitInsn(LSHL);
methodVisitor.visitVarInsn(ALOAD, 0);
methodVisitor.visitMethodInsn(INVOKEVIRTUAL, "org/fusesource/hawtbuf/BufferEditor$BigEndianBufferEditor", "read", "()I", false);
methodVisitor.visitInsn(I2L);
methodVisitor.visitIntInsn(BIPUSH, 48);
methodVisitor.visitInsn(LSHL);
methodVisitor.visitInsn(LADD);
methodVisitor.visitVarInsn(ALOAD, 0);
methodVisitor.visitMethodInsn(INVOKEVIRTUAL, "org/fusesource/hawtbuf/BufferEditor$BigEndianBufferEditor", "read", "()I", false);
methodVisitor.visitInsn(I2L);
methodVisitor.visitIntInsn(BIPUSH, 40);
methodVisitor.visitInsn(LSHL);
methodVisitor.visitInsn(LADD);
methodVisitor.visitVarInsn(ALOAD, 0);
methodVisitor.visitMethodInsn(INVOKEVIRTUAL, "org/fusesource/hawtbuf/BufferEditor$BigEndianBufferEditor", "read", "()I", false);
methodVisitor.visitInsn(I2L);
methodVisitor.visitIntInsn(BIPUSH, 32);
methodVisitor.visitInsn(LSHL);
methodVisitor.visitInsn(LADD);
methodVisitor.visitVarInsn(ALOAD, 0);
methodVisitor.visitMethodInsn(INVOKEVIRTUAL, "org/fusesource/hawtbuf/BufferEditor$BigEndianBufferEditor", "read", "()I", false);
methodVisitor.visitInsn(I2L);
methodVisitor.visitIntInsn(BIPUSH, 24);
methodVisitor.visitInsn(LSHL);
methodVisitor.visitInsn(LADD);
methodVisitor.visitVarInsn(ALOAD, 0);
methodVisitor.visitMethodInsn(INVOKEVIRTUAL, "org/fusesource/hawtbuf/BufferEditor$BigEndianBufferEditor", "read", "()I", false);
methodVisitor.visitIntInsn(BIPUSH, 16);
methodVisitor.visitInsn(ISHL);
methodVisitor.visitInsn(I2L);
methodVisitor.visitInsn(LADD);
methodVisitor.visitVarInsn(ALOAD, 0);
methodVisitor.visitMethodInsn(INVOKEVIRTUAL, "org/fusesource/hawtbuf/BufferEditor$BigEndianBufferEditor", "read", "()I", false);
methodVisitor.visitIntInsn(BIPUSH, 8);
methodVisitor.visitInsn(ISHL);
methodVisitor.visitInsn(I2L);
methodVisitor.visitInsn(LADD);
methodVisitor.visitVarInsn(ALOAD, 0);
methodVisitor.visitMethodInsn(INVOKEVIRTUAL, "org/fusesource/hawtbuf/BufferEditor$BigEndianBufferEditor", "read", "()I", false);
methodVisitor.visitInsn(ICONST_0);
methodVisitor.visitInsn(ISHL);
methodVisitor.visitInsn(I2L);
methodVisitor.visitInsn(LADD);
methodVisitor.visitInsn(LRETURN);
methodVisitor.visitMaxs(5, 1);
methodVisitor.visitEnd();
}
{
methodVisitor = classWriter.visitMethod(ACC_PUBLIC, "readDouble", "()D", null, null);
methodVisitor.visitCode();
methodVisitor.visitVarInsn(ALOAD, 0);
methodVisitor.visitMethodInsn(INVOKEVIRTUAL, "org/fusesource/hawtbuf/BufferEditor$BigEndianBufferEditor", "readLong", "()J", false);
methodVisitor.visitMethodInsn(INVOKESTATIC, "java/lang/Double", "longBitsToDouble", "(J)D", false);
methodVisitor.visitInsn(DRETURN);
methodVisitor.visitMaxs(2, 1);
methodVisitor.visitEnd();
}
{
methodVisitor = classWriter.visitMethod(ACC_PUBLIC, "readFloat", "()F", null, null);
methodVisitor.visitCode();
methodVisitor.visitVarInsn(ALOAD, 0);
methodVisitor.visitMethodInsn(INVOKEVIRTUAL, "org/fusesource/hawtbuf/BufferEditor$BigEndianBufferEditor", "readInt", "()I", false);
methodVisitor.visitMethodInsn(INVOKESTATIC, "java/lang/Float", "intBitsToFloat", "(I)F", false);
methodVisitor.visitInsn(FRETURN);
methodVisitor.visitMaxs(1, 1);
methodVisitor.visitEnd();
}
{
methodVisitor = classWriter.visitMethod(ACC_PUBLIC, "writeShort", "(I)V", null, null);
methodVisitor.visitCode();
methodVisitor.visitFieldInsn(GETSTATIC, "org/fusesource/hawtbuf/BufferEditor$BigEndianBufferEditor", "$assertionsDisabled", "Z");
Label label0 = new Label();
methodVisitor.visitJumpInsn(IFNE, label0);
methodVisitor.visitVarInsn(ALOAD, 0);
methodVisitor.visitInsn(ICONST_2);
methodVisitor.visitMethodInsn(INVOKEVIRTUAL, "org/fusesource/hawtbuf/BufferEditor$BigEndianBufferEditor", "hasCapacity", "(I)Z", false);
methodVisitor.visitJumpInsn(IFNE, label0);
methodVisitor.visitTypeInsn(NEW, "java/lang/AssertionError");
methodVisitor.visitInsn(DUP);
methodVisitor.visitMethodInsn(INVOKESPECIAL, "java/lang/AssertionError", "<init>", "()V", false);
methodVisitor.visitInsn(ATHROW);
methodVisitor.visitLabel(label0);
methodVisitor.visitVarInsn(ALOAD, 0);
methodVisitor.visitVarInsn(ILOAD, 1);
methodVisitor.visitIntInsn(BIPUSH, 8);
methodVisitor.visitInsn(IUSHR);
methodVisitor.visitIntInsn(SIPUSH, 255);
methodVisitor.visitInsn(IAND);
methodVisitor.visitMethodInsn(INVOKEVIRTUAL, "org/fusesource/hawtbuf/BufferEditor$BigEndianBufferEditor", "write", "(I)V", false);
methodVisitor.visitVarInsn(ALOAD, 0);
methodVisitor.visitVarInsn(ILOAD, 1);
methodVisitor.visitInsn(ICONST_0);
methodVisitor.visitInsn(IUSHR);
methodVisitor.visitIntInsn(SIPUSH, 255);
methodVisitor.visitInsn(IAND);
methodVisitor.visitMethodInsn(INVOKEVIRTUAL, "org/fusesource/hawtbuf/BufferEditor$BigEndianBufferEditor", "write", "(I)V", false);
methodVisitor.visitInsn(RETURN);
methodVisitor.visitMaxs(3, 2);
methodVisitor.visitEnd();
}
{
methodVisitor = classWriter.visitMethod(ACC_PUBLIC, "writeChar", "(I)V", null, null);
methodVisitor.visitCode();
methodVisitor.visitFieldInsn(GETSTATIC, "org/fusesource/hawtbuf/BufferEditor$BigEndianBufferEditor", "$assertionsDisabled", "Z");
Label label0 = new Label();
methodVisitor.visitJumpInsn(IFNE, label0);
methodVisitor.visitVarInsn(ALOAD, 0);
methodVisitor.visitInsn(ICONST_2);
methodVisitor.visitMethodInsn(INVOKEVIRTUAL, "org/fusesource/hawtbuf/BufferEditor$BigEndianBufferEditor", "hasCapacity", "(I)Z", false);
methodVisitor.visitJumpInsn(IFNE, label0);
methodVisitor.visitTypeInsn(NEW, "java/lang/AssertionError");
methodVisitor.visitInsn(DUP);
methodVisitor.visitMethodInsn(INVOKESPECIAL, "java/lang/AssertionError", "<init>", "()V", false);
methodVisitor.visitInsn(ATHROW);
methodVisitor.visitLabel(label0);
methodVisitor.visitVarInsn(ALOAD, 0);
methodVisitor.visitVarInsn(ILOAD, 1);
methodVisitor.visitIntInsn(BIPUSH, 8);
methodVisitor.visitInsn(IUSHR);
methodVisitor.visitIntInsn(SIPUSH, 255);
methodVisitor.visitInsn(IAND);
methodVisitor.visitMethodInsn(INVOKEVIRTUAL, "org/fusesource/hawtbuf/BufferEditor$BigEndianBufferEditor", "write", "(I)V", false);
methodVisitor.visitVarInsn(ALOAD, 0);
methodVisitor.visitVarInsn(ILOAD, 1);
methodVisitor.visitInsn(ICONST_0);
methodVisitor.visitInsn(IUSHR);
methodVisitor.visitIntInsn(SIPUSH, 255);
methodVisitor.visitInsn(IAND);
methodVisitor.visitMethodInsn(INVOKEVIRTUAL, "org/fusesource/hawtbuf/BufferEditor$BigEndianBufferEditor", "write", "(I)V", false);
methodVisitor.visitInsn(RETURN);
methodVisitor.visitMaxs(3, 2);
methodVisitor.visitEnd();
}
{
methodVisitor = classWriter.visitMethod(ACC_PUBLIC, "writeInt", "(I)V", null, null);
methodVisitor.visitCode();
methodVisitor.visitFieldInsn(GETSTATIC, "org/fusesource/hawtbuf/BufferEditor$BigEndianBufferEditor", "$assertionsDisabled", "Z");
Label label0 = new Label();
methodVisitor.visitJumpInsn(IFNE, label0);
methodVisitor.visitVarInsn(ALOAD, 0);
methodVisitor.visitInsn(ICONST_4);
methodVisitor.visitMethodInsn(INVOKEVIRTUAL, "org/fusesource/hawtbuf/BufferEditor$BigEndianBufferEditor", "hasCapacity", "(I)Z", false);
methodVisitor.visitJumpInsn(IFNE, label0);
methodVisitor.visitTypeInsn(NEW, "java/lang/AssertionError");
methodVisitor.visitInsn(DUP);
methodVisitor.visitMethodInsn(INVOKESPECIAL, "java/lang/AssertionError", "<init>", "()V", false);
methodVisitor.visitInsn(ATHROW);
methodVisitor.visitLabel(label0);
methodVisitor.visitVarInsn(ALOAD, 0);
methodVisitor.visitVarInsn(ILOAD, 1);
methodVisitor.visitIntInsn(BIPUSH, 24);
methodVisitor.visitInsn(IUSHR);
methodVisitor.visitIntInsn(SIPUSH, 255);
methodVisitor.visitInsn(IAND);
methodVisitor.visitMethodInsn(INVOKEVIRTUAL, "org/fusesource/hawtbuf/BufferEditor$BigEndianBufferEditor", "write", "(I)V", false);
methodVisitor.visitVarInsn(ALOAD, 0);
methodVisitor.visitVarInsn(ILOAD, 1);
methodVisitor.visitIntInsn(BIPUSH, 16);
methodVisitor.visitInsn(IUSHR);
methodVisitor.visitIntInsn(SIPUSH, 255);
methodVisitor.visitInsn(IAND);
methodVisitor.visitMethodInsn(INVOKEVIRTUAL, "org/fusesource/hawtbuf/BufferEditor$BigEndianBufferEditor", "write", "(I)V", false);
methodVisitor.visitVarInsn(ALOAD, 0);
methodVisitor.visitVarInsn(ILOAD, 1);
methodVisitor.visitIntInsn(BIPUSH, 8);
methodVisitor.visitInsn(IUSHR);
methodVisitor.visitIntInsn(SIPUSH, 255);
methodVisitor.visitInsn(IAND);
methodVisitor.visitMethodInsn(INVOKEVIRTUAL, "org/fusesource/hawtbuf/BufferEditor$BigEndianBufferEditor", "write", "(I)V", false);
methodVisitor.visitVarInsn(ALOAD, 0);
methodVisitor.visitVarInsn(ILOAD, 1);
methodVisitor.visitInsn(ICONST_0);
methodVisitor.visitInsn(IUSHR);
methodVisitor.visitIntInsn(SIPUSH, 255);
methodVisitor.visitInsn(IAND);
methodVisitor.visitMethodInsn(INVOKEVIRTUAL, "org/fusesource/hawtbuf/BufferEditor$BigEndianBufferEditor", "write", "(I)V", false);
methodVisitor.visitInsn(RETURN);
methodVisitor.visitMaxs(3, 2);
methodVisitor.visitEnd();
}
{
methodVisitor = classWriter.visitMethod(ACC_PUBLIC, "writeLong", "(J)V", null, null);
methodVisitor.visitCode();
methodVisitor.visitFieldInsn(GETSTATIC, "org/fusesource/hawtbuf/BufferEditor$BigEndianBufferEditor", "$assertionsDisabled", "Z");
Label label0 = new Label();
methodVisitor.visitJumpInsn(IFNE, label0);
methodVisitor.visitVarInsn(ALOAD, 0);
methodVisitor.visitIntInsn(BIPUSH, 8);
methodVisitor.visitMethodInsn(INVOKEVIRTUAL, "org/fusesource/hawtbuf/BufferEditor$BigEndianBufferEditor", "hasCapacity", "(I)Z", false);
methodVisitor.visitJumpInsn(IFNE, label0);
methodVisitor.visitTypeInsn(NEW, "java/lang/AssertionError");
methodVisitor.visitInsn(DUP);
methodVisitor.visitMethodInsn(INVOKESPECIAL, "java/lang/AssertionError", "<init>", "()V", false);
methodVisitor.visitInsn(ATHROW);
methodVisitor.visitLabel(label0);
methodVisitor.visitVarInsn(ALOAD, 0);
methodVisitor.visitVarInsn(LLOAD, 1);
methodVisitor.visitIntInsn(BIPUSH, 56);
methodVisitor.visitInsn(LUSHR);
methodVisitor.visitInsn(L2I);
methodVisitor.visitIntInsn(SIPUSH, 255);
methodVisitor.visitInsn(IAND);
methodVisitor.visitMethodInsn(INVOKEVIRTUAL, "org/fusesource/hawtbuf/BufferEditor$BigEndianBufferEditor", "write", "(I)V", false);
methodVisitor.visitVarInsn(ALOAD, 0);
methodVisitor.visitVarInsn(LLOAD, 1);
methodVisitor.visitIntInsn(BIPUSH, 48);
methodVisitor.visitInsn(LUSHR);
methodVisitor.visitInsn(L2I);
methodVisitor.visitIntInsn(SIPUSH, 255);
methodVisitor.visitInsn(IAND);
methodVisitor.visitMethodInsn(INVOKEVIRTUAL, "org/fusesource/hawtbuf/BufferEditor$BigEndianBufferEditor", "write", "(I)V", false);
methodVisitor.visitVarInsn(ALOAD, 0);
methodVisitor.visitVarInsn(LLOAD, 1);
methodVisitor.visitIntInsn(BIPUSH, 40);
methodVisitor.visitInsn(LUSHR);
methodVisitor.visitInsn(L2I);
methodVisitor.visitIntInsn(SIPUSH, 255);
methodVisitor.visitInsn(IAND);
methodVisitor.visitMethodInsn(INVOKEVIRTUAL, "org/fusesource/hawtbuf/BufferEditor$BigEndianBufferEditor", "write", "(I)V", false);
methodVisitor.visitVarInsn(ALOAD, 0);
methodVisitor.visitVarInsn(LLOAD, 1);
methodVisitor.visitIntInsn(BIPUSH, 32);
methodVisitor.visitInsn(LUSHR);
methodVisitor.visitInsn(L2I);
methodVisitor.visitIntInsn(SIPUSH, 255);
methodVisitor.visitInsn(IAND);
methodVisitor.visitMethodInsn(INVOKEVIRTUAL, "org/fusesource/hawtbuf/BufferEditor$BigEndianBufferEditor", "write", "(I)V", false);
methodVisitor.visitVarInsn(ALOAD, 0);
methodVisitor.visitVarInsn(LLOAD, 1);
methodVisitor.visitIntInsn(BIPUSH, 24);
methodVisitor.visitInsn(LUSHR);
methodVisitor.visitInsn(L2I);
methodVisitor.visitIntInsn(SIPUSH, 255);
methodVisitor.visitInsn(IAND);
methodVisitor.visitMethodInsn(INVOKEVIRTUAL, "org/fusesource/hawtbuf/BufferEditor$BigEndianBufferEditor", "write", "(I)V", false);
methodVisitor.visitVarInsn(ALOAD, 0);
methodVisitor.visitVarInsn(LLOAD, 1);
methodVisitor.visitIntInsn(BIPUSH, 16);
methodVisitor.visitInsn(LUSHR);
methodVisitor.visitInsn(L2I);
methodVisitor.visitIntInsn(SIPUSH, 255);
methodVisitor.visitInsn(IAND);
methodVisitor.visitMethodInsn(INVOKEVIRTUAL, "org/fusesource/hawtbuf/BufferEditor$BigEndianBufferEditor", "write", "(I)V", false);
methodVisitor.visitVarInsn(ALOAD, 0);
methodVisitor.visitVarInsn(LLOAD, 1);
methodVisitor.visitIntInsn(BIPUSH, 8);
methodVisitor.visitInsn(LUSHR);
methodVisitor.visitInsn(L2I);
methodVisitor.visitIntInsn(SIPUSH, 255);
methodVisitor.visitInsn(IAND);
methodVisitor.visitMethodInsn(INVOKEVIRTUAL, "org/fusesource/hawtbuf/BufferEditor$BigEndianBufferEditor", "write", "(I)V", false);
methodVisitor.visitVarInsn(ALOAD, 0);
methodVisitor.visitVarInsn(LLOAD, 1);
methodVisitor.visitInsn(ICONST_0);
methodVisitor.visitInsn(LUSHR);
methodVisitor.visitInsn(L2I);
methodVisitor.visitIntInsn(SIPUSH, 255);
methodVisitor.visitInsn(IAND);
methodVisitor.visitMethodInsn(INVOKEVIRTUAL, "org/fusesource/hawtbuf/BufferEditor$BigEndianBufferEditor", "write", "(I)V", false);
methodVisitor.visitInsn(RETURN);
methodVisitor.visitMaxs(4, 3);
methodVisitor.visitEnd();
}
{
methodVisitor = classWriter.visitMethod(ACC_PUBLIC, "writeDouble", "(D)V", null, null);
methodVisitor.visitCode();
methodVisitor.visitVarInsn(ALOAD, 0);
methodVisitor.visitVarInsn(DLOAD, 1);
methodVisitor.visitMethodInsn(INVOKESTATIC, "java/lang/Double", "doubleToLongBits", "(D)J", false);
methodVisitor.visitMethodInsn(INVOKEVIRTUAL, "org/fusesource/hawtbuf/BufferEditor$BigEndianBufferEditor", "writeLong", "(J)V", false);
methodVisitor.visitInsn(RETURN);
methodVisitor.visitMaxs(3, 3);
methodVisitor.visitEnd();
}
{
methodVisitor = classWriter.visitMethod(ACC_PUBLIC, "writeFloat", "(F)V", null, null);
methodVisitor.visitCode();
methodVisitor.visitVarInsn(ALOAD, 0);
methodVisitor.visitVarInsn(FLOAD, 1);
methodVisitor.visitMethodInsn(INVOKESTATIC, "java/lang/Float", "floatToIntBits", "(F)I", false);
methodVisitor.visitMethodInsn(INVOKEVIRTUAL, "org/fusesource/hawtbuf/BufferEditor$BigEndianBufferEditor", "writeInt", "(I)V", false);
methodVisitor.visitInsn(RETURN);
methodVisitor.visitMaxs(2, 2);
methodVisitor.visitEnd();
}
{
methodVisitor = classWriter.visitMethod(ACC_PUBLIC, "writeRawDouble", "(D)V", null, null);
methodVisitor.visitCode();
methodVisitor.visitVarInsn(ALOAD, 0);
methodVisitor.visitVarInsn(DLOAD, 1);
methodVisitor.visitMethodInsn(INVOKESTATIC, "java/lang/Double", "doubleToRawLongBits", "(D)J", false);
methodVisitor.visitMethodInsn(INVOKEVIRTUAL, "org/fusesource/hawtbuf/BufferEditor$BigEndianBufferEditor", "writeLong", "(J)V", false);
methodVisitor.visitInsn(RETURN);
methodVisitor.visitMaxs(3, 3);
methodVisitor.visitEnd();
}
{
methodVisitor = classWriter.visitMethod(ACC_PUBLIC, "writeRawFloat", "(F)V", null, null);
methodVisitor.visitCode();
methodVisitor.visitVarInsn(ALOAD, 0);
methodVisitor.visitVarInsn(FLOAD, 1);
methodVisitor.visitMethodInsn(INVOKESTATIC, "java/lang/Float", "floatToRawIntBits", "(F)I", false);
methodVisitor.visitMethodInsn(INVOKEVIRTUAL, "org/fusesource/hawtbuf/BufferEditor$BigEndianBufferEditor", "writeInt", "(I)V", false);
methodVisitor.visitInsn(RETURN);
methodVisitor.visitMaxs(2, 2);
methodVisitor.visitEnd();
}
{
methodVisitor = classWriter.visitMethod(ACC_STATIC, "<clinit>", "()V", null, null);
methodVisitor.visitCode();
methodVisitor.visitLdcInsn(Type.getType("Lorg/fusesource/hawtbuf/BufferEditor;"));
methodVisitor.visitMethodInsn(INVOKEVIRTUAL, "java/lang/Class", "desiredAssertionStatus", "()Z", false);
Label label0 = new Label();
methodVisitor.visitJumpInsn(IFNE, label0);
methodVisitor.visitInsn(ICONST_1);
Label label1 = new Label();
methodVisitor.visitJumpInsn(GOTO, label1);
methodVisitor.visitLabel(label0);
methodVisitor.visitInsn(ICONST_0);
methodVisitor.visitLabel(label1);
methodVisitor.visitFieldInsn(PUTSTATIC, "org/fusesource/hawtbuf/BufferEditor$BigEndianBufferEditor", "$assertionsDisabled", "Z");
methodVisitor.visitInsn(RETURN);
methodVisitor.visitMaxs(1, 0);
methodVisitor.visitEnd();
}
classWriter.visitEnd();

return classWriter.toByteArray();
}
}
