package asm.org.bouncycastle.crypto.generators;
import org.objectweb.asm.AnnotationVisitor;
import org.objectweb.asm.Attribute;
import org.objectweb.asm.ClassReader;
import org.objectweb.asm.ClassWriter;
import org.objectweb.asm.ConstantDynamic;
import org.objectweb.asm.FieldVisitor;
import org.objectweb.asm.Handle;
import org.objectweb.asm.Label;
import org.objectweb.asm.MethodVisitor;
import org.objectweb.asm.Opcodes;
import org.objectweb.asm.RecordComponentVisitor;
import org.objectweb.asm.Type;
import org.objectweb.asm.TypePath;
public class OpenBSDBCryptDump implements Opcodes {

public static byte[] dump () throws Exception {

ClassWriter classWriter = new ClassWriter(0);
FieldVisitor fieldVisitor;
RecordComponentVisitor recordComponentVisitor;
MethodVisitor methodVisitor;
AnnotationVisitor annotationVisitor0;

classWriter.visit(V1_5, ACC_PUBLIC | ACC_SUPER, "org/bouncycastle/crypto/generators/OpenBSDBCrypt", null, "java/lang/Object", null);

{
fieldVisitor = classWriter.visitField(ACC_PRIVATE | ACC_FINAL | ACC_STATIC, "encodingTable", "[B", null, null);
fieldVisitor.visitEnd();
}
{
fieldVisitor = classWriter.visitField(ACC_PRIVATE | ACC_FINAL | ACC_STATIC, "decodingTable", "[B", null, null);
fieldVisitor.visitEnd();
}
{
fieldVisitor = classWriter.visitField(ACC_PRIVATE | ACC_FINAL | ACC_STATIC, "defaultVersion", "Ljava/lang/String;", null, "2y");
fieldVisitor.visitEnd();
}
{
fieldVisitor = classWriter.visitField(ACC_PRIVATE | ACC_FINAL | ACC_STATIC, "allowedVersions", "Ljava/util/Set;", "Ljava/util/Set<Ljava/lang/String;>;", null);
fieldVisitor.visitEnd();
}
{
methodVisitor = classWriter.visitMethod(ACC_PUBLIC, "<init>", "()V", null, null);
methodVisitor.visitCode();
methodVisitor.visitVarInsn(ALOAD, 0);
methodVisitor.visitMethodInsn(INVOKESPECIAL, "java/lang/Object", "<init>", "()V", false);
methodVisitor.visitInsn(RETURN);
methodVisitor.visitMaxs(1, 1);
methodVisitor.visitEnd();
}
{
methodVisitor = classWriter.visitMethod(ACC_PRIVATE | ACC_STATIC, "createBcryptString", "(Ljava/lang/String;[B[BI)Ljava/lang/String;", null, null);
methodVisitor.visitCode();
methodVisitor.visitFieldInsn(GETSTATIC, "org/bouncycastle/crypto/generators/OpenBSDBCrypt", "allowedVersions", "Ljava/util/Set;");
methodVisitor.visitVarInsn(ALOAD, 0);
methodVisitor.visitMethodInsn(INVOKEINTERFACE, "java/util/Set", "contains", "(Ljava/lang/Object;)Z", true);
Label label0 = new Label();
methodVisitor.visitJumpInsn(IFNE, label0);
methodVisitor.visitTypeInsn(NEW, "java/lang/IllegalArgumentException");
methodVisitor.visitInsn(DUP);
methodVisitor.visitTypeInsn(NEW, "java/lang/StringBuilder");
methodVisitor.visitInsn(DUP);
methodVisitor.visitMethodInsn(INVOKESPECIAL, "java/lang/StringBuilder", "<init>", "()V", false);
methodVisitor.visitLdcInsn("Version ");
methodVisitor.visitMethodInsn(INVOKEVIRTUAL, "java/lang/StringBuilder", "append", "(Ljava/lang/String;)Ljava/lang/StringBuilder;", false);
methodVisitor.visitVarInsn(ALOAD, 0);
methodVisitor.visitMethodInsn(INVOKEVIRTUAL, "java/lang/StringBuilder", "append", "(Ljava/lang/String;)Ljava/lang/StringBuilder;", false);
methodVisitor.visitLdcInsn(" is not accepted by this implementation.");
methodVisitor.visitMethodInsn(INVOKEVIRTUAL, "java/lang/StringBuilder", "append", "(Ljava/lang/String;)Ljava/lang/StringBuilder;", false);
methodVisitor.visitMethodInsn(INVOKEVIRTUAL, "java/lang/StringBuilder", "toString", "()Ljava/lang/String;", false);
methodVisitor.visitMethodInsn(INVOKESPECIAL, "java/lang/IllegalArgumentException", "<init>", "(Ljava/lang/String;)V", false);
methodVisitor.visitInsn(ATHROW);
methodVisitor.visitLabel(label0);
methodVisitor.visitTypeInsn(NEW, "java/lang/StringBuffer");
methodVisitor.visitInsn(DUP);
methodVisitor.visitIntInsn(BIPUSH, 60);
methodVisitor.visitMethodInsn(INVOKESPECIAL, "java/lang/StringBuffer", "<init>", "(I)V", false);
methodVisitor.visitVarInsn(ASTORE, 4);
methodVisitor.visitVarInsn(ALOAD, 4);
methodVisitor.visitIntInsn(BIPUSH, 36);
methodVisitor.visitMethodInsn(INVOKEVIRTUAL, "java/lang/StringBuffer", "append", "(C)Ljava/lang/StringBuffer;", false);
methodVisitor.visitInsn(POP);
methodVisitor.visitVarInsn(ALOAD, 4);
methodVisitor.visitVarInsn(ALOAD, 0);
methodVisitor.visitMethodInsn(INVOKEVIRTUAL, "java/lang/StringBuffer", "append", "(Ljava/lang/String;)Ljava/lang/StringBuffer;", false);
methodVisitor.visitInsn(POP);
methodVisitor.visitVarInsn(ALOAD, 4);
methodVisitor.visitIntInsn(BIPUSH, 36);
methodVisitor.visitMethodInsn(INVOKEVIRTUAL, "java/lang/StringBuffer", "append", "(C)Ljava/lang/StringBuffer;", false);
methodVisitor.visitInsn(POP);
methodVisitor.visitVarInsn(ALOAD, 4);
methodVisitor.visitVarInsn(ILOAD, 3);
methodVisitor.visitIntInsn(BIPUSH, 10);
Label label1 = new Label();
methodVisitor.visitJumpInsn(IF_ICMPGE, label1);
methodVisitor.visitTypeInsn(NEW, "java/lang/StringBuilder");
methodVisitor.visitInsn(DUP);
methodVisitor.visitMethodInsn(INVOKESPECIAL, "java/lang/StringBuilder", "<init>", "()V", false);
methodVisitor.visitLdcInsn("0");
methodVisitor.visitMethodInsn(INVOKEVIRTUAL, "java/lang/StringBuilder", "append", "(Ljava/lang/String;)Ljava/lang/StringBuilder;", false);
methodVisitor.visitVarInsn(ILOAD, 3);
methodVisitor.visitMethodInsn(INVOKEVIRTUAL, "java/lang/StringBuilder", "append", "(I)Ljava/lang/StringBuilder;", false);
methodVisitor.visitMethodInsn(INVOKEVIRTUAL, "java/lang/StringBuilder", "toString", "()Ljava/lang/String;", false);
Label label2 = new Label();
methodVisitor.visitJumpInsn(GOTO, label2);
methodVisitor.visitLabel(label1);
methodVisitor.visitVarInsn(ILOAD, 3);
methodVisitor.visitMethodInsn(INVOKESTATIC, "java/lang/Integer", "toString", "(I)Ljava/lang/String;", false);
methodVisitor.visitLabel(label2);
methodVisitor.visitMethodInsn(INVOKEVIRTUAL, "java/lang/StringBuffer", "append", "(Ljava/lang/String;)Ljava/lang/StringBuffer;", false);
methodVisitor.visitInsn(POP);
methodVisitor.visitVarInsn(ALOAD, 4);
methodVisitor.visitIntInsn(BIPUSH, 36);
methodVisitor.visitMethodInsn(INVOKEVIRTUAL, "java/lang/StringBuffer", "append", "(C)Ljava/lang/StringBuffer;", false);
methodVisitor.visitInsn(POP);
methodVisitor.visitVarInsn(ALOAD, 4);
methodVisitor.visitVarInsn(ALOAD, 2);
methodVisitor.visitMethodInsn(INVOKESTATIC, "org/bouncycastle/crypto/generators/OpenBSDBCrypt", "encodeData", "([B)Ljava/lang/String;", false);
methodVisitor.visitMethodInsn(INVOKEVIRTUAL, "java/lang/StringBuffer", "append", "(Ljava/lang/String;)Ljava/lang/StringBuffer;", false);
methodVisitor.visitInsn(POP);
methodVisitor.visitVarInsn(ALOAD, 1);
methodVisitor.visitVarInsn(ALOAD, 2);
methodVisitor.visitVarInsn(ILOAD, 3);
methodVisitor.visitMethodInsn(INVOKESTATIC, "org/bouncycastle/crypto/generators/BCrypt", "generate", "([B[BI)[B", false);
methodVisitor.visitVarInsn(ASTORE, 5);
methodVisitor.visitVarInsn(ALOAD, 4);
methodVisitor.visitVarInsn(ALOAD, 5);
methodVisitor.visitMethodInsn(INVOKESTATIC, "org/bouncycastle/crypto/generators/OpenBSDBCrypt", "encodeData", "([B)Ljava/lang/String;", false);
methodVisitor.visitMethodInsn(INVOKEVIRTUAL, "java/lang/StringBuffer", "append", "(Ljava/lang/String;)Ljava/lang/StringBuffer;", false);
methodVisitor.visitInsn(POP);
methodVisitor.visitVarInsn(ALOAD, 4);
methodVisitor.visitMethodInsn(INVOKEVIRTUAL, "java/lang/StringBuffer", "toString", "()Ljava/lang/String;", false);
methodVisitor.visitInsn(ARETURN);
methodVisitor.visitMaxs(4, 6);
methodVisitor.visitEnd();
}
{
methodVisitor = classWriter.visitMethod(ACC_PUBLIC | ACC_STATIC, "generate", "([C[BI)Ljava/lang/String;", null, null);
methodVisitor.visitCode();
methodVisitor.visitLdcInsn("2y");
methodVisitor.visitVarInsn(ALOAD, 0);
methodVisitor.visitVarInsn(ALOAD, 1);
methodVisitor.visitVarInsn(ILOAD, 2);
methodVisitor.visitMethodInsn(INVOKESTATIC, "org/bouncycastle/crypto/generators/OpenBSDBCrypt", "generate", "(Ljava/lang/String;[C[BI)Ljava/lang/String;", false);
methodVisitor.visitInsn(ARETURN);
methodVisitor.visitMaxs(4, 3);
methodVisitor.visitEnd();
}
{
methodVisitor = classWriter.visitMethod(ACC_PUBLIC | ACC_STATIC, "generate", "(Ljava/lang/String;[C[BI)Ljava/lang/String;", null, null);
methodVisitor.visitCode();
methodVisitor.visitFieldInsn(GETSTATIC, "org/bouncycastle/crypto/generators/OpenBSDBCrypt", "allowedVersions", "Ljava/util/Set;");
methodVisitor.visitVarInsn(ALOAD, 0);
methodVisitor.visitMethodInsn(INVOKEINTERFACE, "java/util/Set", "contains", "(Ljava/lang/Object;)Z", true);
Label label0 = new Label();
methodVisitor.visitJumpInsn(IFNE, label0);
methodVisitor.visitTypeInsn(NEW, "java/lang/IllegalArgumentException");
methodVisitor.visitInsn(DUP);
methodVisitor.visitTypeInsn(NEW, "java/lang/StringBuilder");
methodVisitor.visitInsn(DUP);
methodVisitor.visitMethodInsn(INVOKESPECIAL, "java/lang/StringBuilder", "<init>", "()V", false);
methodVisitor.visitLdcInsn("Version ");
methodVisitor.visitMethodInsn(INVOKEVIRTUAL, "java/lang/StringBuilder", "append", "(Ljava/lang/String;)Ljava/lang/StringBuilder;", false);
methodVisitor.visitVarInsn(ALOAD, 0);
methodVisitor.visitMethodInsn(INVOKEVIRTUAL, "java/lang/StringBuilder", "append", "(Ljava/lang/String;)Ljava/lang/StringBuilder;", false);
methodVisitor.visitLdcInsn(" is not accepted by this implementation.");
methodVisitor.visitMethodInsn(INVOKEVIRTUAL, "java/lang/StringBuilder", "append", "(Ljava/lang/String;)Ljava/lang/StringBuilder;", false);
methodVisitor.visitMethodInsn(INVOKEVIRTUAL, "java/lang/StringBuilder", "toString", "()Ljava/lang/String;", false);
methodVisitor.visitMethodInsn(INVOKESPECIAL, "java/lang/IllegalArgumentException", "<init>", "(Ljava/lang/String;)V", false);
methodVisitor.visitInsn(ATHROW);
methodVisitor.visitLabel(label0);
methodVisitor.visitVarInsn(ALOAD, 1);
Label label1 = new Label();
methodVisitor.visitJumpInsn(IFNONNULL, label1);
methodVisitor.visitTypeInsn(NEW, "java/lang/IllegalArgumentException");
methodVisitor.visitInsn(DUP);
methodVisitor.visitLdcInsn("Password required.");
methodVisitor.visitMethodInsn(INVOKESPECIAL, "java/lang/IllegalArgumentException", "<init>", "(Ljava/lang/String;)V", false);
methodVisitor.visitInsn(ATHROW);
methodVisitor.visitLabel(label1);
methodVisitor.visitVarInsn(ALOAD, 2);
Label label2 = new Label();
methodVisitor.visitJumpInsn(IFNONNULL, label2);
methodVisitor.visitTypeInsn(NEW, "java/lang/IllegalArgumentException");
methodVisitor.visitInsn(DUP);
methodVisitor.visitLdcInsn("Salt required.");
methodVisitor.visitMethodInsn(INVOKESPECIAL, "java/lang/IllegalArgumentException", "<init>", "(Ljava/lang/String;)V", false);
methodVisitor.visitInsn(ATHROW);
methodVisitor.visitLabel(label2);
methodVisitor.visitVarInsn(ALOAD, 2);
methodVisitor.visitInsn(ARRAYLENGTH);
methodVisitor.visitIntInsn(BIPUSH, 16);
Label label3 = new Label();
methodVisitor.visitJumpInsn(IF_ICMPEQ, label3);
methodVisitor.visitTypeInsn(NEW, "org/bouncycastle/crypto/DataLengthException");
methodVisitor.visitInsn(DUP);
methodVisitor.visitTypeInsn(NEW, "java/lang/StringBuilder");
methodVisitor.visitInsn(DUP);
methodVisitor.visitMethodInsn(INVOKESPECIAL, "java/lang/StringBuilder", "<init>", "()V", false);
methodVisitor.visitLdcInsn("16 byte salt required: ");
methodVisitor.visitMethodInsn(INVOKEVIRTUAL, "java/lang/StringBuilder", "append", "(Ljava/lang/String;)Ljava/lang/StringBuilder;", false);
methodVisitor.visitVarInsn(ALOAD, 2);
methodVisitor.visitInsn(ARRAYLENGTH);
methodVisitor.visitMethodInsn(INVOKEVIRTUAL, "java/lang/StringBuilder", "append", "(I)Ljava/lang/StringBuilder;", false);
methodVisitor.visitMethodInsn(INVOKEVIRTUAL, "java/lang/StringBuilder", "toString", "()Ljava/lang/String;", false);
methodVisitor.visitMethodInsn(INVOKESPECIAL, "org/bouncycastle/crypto/DataLengthException", "<init>", "(Ljava/lang/String;)V", false);
methodVisitor.visitInsn(ATHROW);
methodVisitor.visitLabel(label3);
methodVisitor.visitVarInsn(ILOAD, 3);
methodVisitor.visitInsn(ICONST_4);
Label label4 = new Label();
methodVisitor.visitJumpInsn(IF_ICMPLT, label4);
methodVisitor.visitVarInsn(ILOAD, 3);
methodVisitor.visitIntInsn(BIPUSH, 31);
Label label5 = new Label();
methodVisitor.visitJumpInsn(IF_ICMPLE, label5);
methodVisitor.visitLabel(label4);
methodVisitor.visitTypeInsn(NEW, "java/lang/IllegalArgumentException");
methodVisitor.visitInsn(DUP);
methodVisitor.visitLdcInsn("Invalid cost factor.");
methodVisitor.visitMethodInsn(INVOKESPECIAL, "java/lang/IllegalArgumentException", "<init>", "(Ljava/lang/String;)V", false);
methodVisitor.visitInsn(ATHROW);
methodVisitor.visitLabel(label5);
methodVisitor.visitVarInsn(ALOAD, 1);
methodVisitor.visitMethodInsn(INVOKESTATIC, "org/bouncycastle/util/Strings", "toUTF8ByteArray", "([C)[B", false);
methodVisitor.visitVarInsn(ASTORE, 4);
methodVisitor.visitVarInsn(ALOAD, 4);
methodVisitor.visitInsn(ARRAYLENGTH);
methodVisitor.visitIntInsn(BIPUSH, 72);
Label label6 = new Label();
methodVisitor.visitJumpInsn(IF_ICMPLT, label6);
methodVisitor.visitIntInsn(BIPUSH, 72);
Label label7 = new Label();
methodVisitor.visitJumpInsn(GOTO, label7);
methodVisitor.visitLabel(label6);
methodVisitor.visitVarInsn(ALOAD, 4);
methodVisitor.visitInsn(ARRAYLENGTH);
methodVisitor.visitInsn(ICONST_1);
methodVisitor.visitInsn(IADD);
methodVisitor.visitLabel(label7);
methodVisitor.visitIntInsn(NEWARRAY, T_BYTE);
methodVisitor.visitVarInsn(ASTORE, 5);
methodVisitor.visitVarInsn(ALOAD, 5);
methodVisitor.visitInsn(ARRAYLENGTH);
methodVisitor.visitVarInsn(ALOAD, 4);
methodVisitor.visitInsn(ARRAYLENGTH);
Label label8 = new Label();
methodVisitor.visitJumpInsn(IF_ICMPLE, label8);
methodVisitor.visitVarInsn(ALOAD, 4);
methodVisitor.visitInsn(ICONST_0);
methodVisitor.visitVarInsn(ALOAD, 5);
methodVisitor.visitInsn(ICONST_0);
methodVisitor.visitVarInsn(ALOAD, 4);
methodVisitor.visitInsn(ARRAYLENGTH);
methodVisitor.visitMethodInsn(INVOKESTATIC, "java/lang/System", "arraycopy", "(Ljava/lang/Object;ILjava/lang/Object;II)V", false);
Label label9 = new Label();
methodVisitor.visitJumpInsn(GOTO, label9);
methodVisitor.visitLabel(label8);
methodVisitor.visitVarInsn(ALOAD, 4);
methodVisitor.visitInsn(ICONST_0);
methodVisitor.visitVarInsn(ALOAD, 5);
methodVisitor.visitInsn(ICONST_0);
methodVisitor.visitVarInsn(ALOAD, 5);
methodVisitor.visitInsn(ARRAYLENGTH);
methodVisitor.visitMethodInsn(INVOKESTATIC, "java/lang/System", "arraycopy", "(Ljava/lang/Object;ILjava/lang/Object;II)V", false);
methodVisitor.visitLabel(label9);
methodVisitor.visitVarInsn(ALOAD, 4);
methodVisitor.visitInsn(ICONST_0);
methodVisitor.visitMethodInsn(INVOKESTATIC, "org/bouncycastle/util/Arrays", "fill", "([BB)V", false);
methodVisitor.visitVarInsn(ALOAD, 0);
methodVisitor.visitVarInsn(ALOAD, 5);
methodVisitor.visitVarInsn(ALOAD, 2);
methodVisitor.visitVarInsn(ILOAD, 3);
methodVisitor.visitMethodInsn(INVOKESTATIC, "org/bouncycastle/crypto/generators/OpenBSDBCrypt", "createBcryptString", "(Ljava/lang/String;[B[BI)Ljava/lang/String;", false);
methodVisitor.visitVarInsn(ASTORE, 6);
methodVisitor.visitVarInsn(ALOAD, 5);
methodVisitor.visitInsn(ICONST_0);
methodVisitor.visitMethodInsn(INVOKESTATIC, "org/bouncycastle/util/Arrays", "fill", "([BB)V", false);
methodVisitor.visitVarInsn(ALOAD, 6);
methodVisitor.visitInsn(ARETURN);
methodVisitor.visitMaxs(5, 7);
methodVisitor.visitEnd();
}
{
methodVisitor = classWriter.visitMethod(ACC_PUBLIC | ACC_STATIC, "checkPassword", "(Ljava/lang/String;[C)Z", null, null);
methodVisitor.visitCode();
Label label0 = new Label();
Label label1 = new Label();
Label label2 = new Label();
methodVisitor.visitTryCatchBlock(label0, label1, label2, "java/lang/NumberFormatException");
methodVisitor.visitVarInsn(ALOAD, 0);
methodVisitor.visitMethodInsn(INVOKEVIRTUAL, "java/lang/String", "length", "()I", false);
methodVisitor.visitIntInsn(BIPUSH, 60);
Label label3 = new Label();
methodVisitor.visitJumpInsn(IF_ICMPEQ, label3);
methodVisitor.visitTypeInsn(NEW, "org/bouncycastle/crypto/DataLengthException");
methodVisitor.visitInsn(DUP);
methodVisitor.visitTypeInsn(NEW, "java/lang/StringBuilder");
methodVisitor.visitInsn(DUP);
methodVisitor.visitMethodInsn(INVOKESPECIAL, "java/lang/StringBuilder", "<init>", "()V", false);
methodVisitor.visitLdcInsn("Bcrypt String length: ");
methodVisitor.visitMethodInsn(INVOKEVIRTUAL, "java/lang/StringBuilder", "append", "(Ljava/lang/String;)Ljava/lang/StringBuilder;", false);
methodVisitor.visitVarInsn(ALOAD, 0);
methodVisitor.visitMethodInsn(INVOKEVIRTUAL, "java/lang/String", "length", "()I", false);
methodVisitor.visitMethodInsn(INVOKEVIRTUAL, "java/lang/StringBuilder", "append", "(I)Ljava/lang/StringBuilder;", false);
methodVisitor.visitLdcInsn(", 60 required.");
methodVisitor.visitMethodInsn(INVOKEVIRTUAL, "java/lang/StringBuilder", "append", "(Ljava/lang/String;)Ljava/lang/StringBuilder;", false);
methodVisitor.visitMethodInsn(INVOKEVIRTUAL, "java/lang/StringBuilder", "toString", "()Ljava/lang/String;", false);
methodVisitor.visitMethodInsn(INVOKESPECIAL, "org/bouncycastle/crypto/DataLengthException", "<init>", "(Ljava/lang/String;)V", false);
methodVisitor.visitInsn(ATHROW);
methodVisitor.visitLabel(label3);
methodVisitor.visitVarInsn(ALOAD, 0);
methodVisitor.visitInsn(ICONST_0);
methodVisitor.visitMethodInsn(INVOKEVIRTUAL, "java/lang/String", "charAt", "(I)C", false);
methodVisitor.visitIntInsn(BIPUSH, 36);
Label label4 = new Label();
methodVisitor.visitJumpInsn(IF_ICMPNE, label4);
methodVisitor.visitVarInsn(ALOAD, 0);
methodVisitor.visitInsn(ICONST_3);
methodVisitor.visitMethodInsn(INVOKEVIRTUAL, "java/lang/String", "charAt", "(I)C", false);
methodVisitor.visitIntInsn(BIPUSH, 36);
methodVisitor.visitJumpInsn(IF_ICMPNE, label4);
methodVisitor.visitVarInsn(ALOAD, 0);
methodVisitor.visitIntInsn(BIPUSH, 6);
methodVisitor.visitMethodInsn(INVOKEVIRTUAL, "java/lang/String", "charAt", "(I)C", false);
methodVisitor.visitIntInsn(BIPUSH, 36);
Label label5 = new Label();
methodVisitor.visitJumpInsn(IF_ICMPEQ, label5);
methodVisitor.visitLabel(label4);
methodVisitor.visitTypeInsn(NEW, "java/lang/IllegalArgumentException");
methodVisitor.visitInsn(DUP);
methodVisitor.visitLdcInsn("Invalid Bcrypt String format.");
methodVisitor.visitMethodInsn(INVOKESPECIAL, "java/lang/IllegalArgumentException", "<init>", "(Ljava/lang/String;)V", false);
methodVisitor.visitInsn(ATHROW);
methodVisitor.visitLabel(label5);
methodVisitor.visitVarInsn(ALOAD, 0);
methodVisitor.visitInsn(ICONST_1);
methodVisitor.visitInsn(ICONST_3);
methodVisitor.visitMethodInsn(INVOKEVIRTUAL, "java/lang/String", "substring", "(II)Ljava/lang/String;", false);
methodVisitor.visitVarInsn(ASTORE, 2);
methodVisitor.visitFieldInsn(GETSTATIC, "org/bouncycastle/crypto/generators/OpenBSDBCrypt", "allowedVersions", "Ljava/util/Set;");
methodVisitor.visitVarInsn(ALOAD, 2);
methodVisitor.visitMethodInsn(INVOKEINTERFACE, "java/util/Set", "contains", "(Ljava/lang/Object;)Z", true);
Label label6 = new Label();
methodVisitor.visitJumpInsn(IFNE, label6);
methodVisitor.visitTypeInsn(NEW, "java/lang/IllegalArgumentException");
methodVisitor.visitInsn(DUP);
methodVisitor.visitTypeInsn(NEW, "java/lang/StringBuilder");
methodVisitor.visitInsn(DUP);
methodVisitor.visitMethodInsn(INVOKESPECIAL, "java/lang/StringBuilder", "<init>", "()V", false);
methodVisitor.visitLdcInsn("Bcrypt version '");
methodVisitor.visitMethodInsn(INVOKEVIRTUAL, "java/lang/StringBuilder", "append", "(Ljava/lang/String;)Ljava/lang/StringBuilder;", false);
methodVisitor.visitVarInsn(ALOAD, 2);
methodVisitor.visitMethodInsn(INVOKEVIRTUAL, "java/lang/StringBuilder", "append", "(Ljava/lang/String;)Ljava/lang/StringBuilder;", false);
methodVisitor.visitLdcInsn("' is not supported by this implementation");
methodVisitor.visitMethodInsn(INVOKEVIRTUAL, "java/lang/StringBuilder", "append", "(Ljava/lang/String;)Ljava/lang/StringBuilder;", false);
methodVisitor.visitMethodInsn(INVOKEVIRTUAL, "java/lang/StringBuilder", "toString", "()Ljava/lang/String;", false);
methodVisitor.visitMethodInsn(INVOKESPECIAL, "java/lang/IllegalArgumentException", "<init>", "(Ljava/lang/String;)V", false);
methodVisitor.visitInsn(ATHROW);
methodVisitor.visitLabel(label6);
methodVisitor.visitInsn(ICONST_0);
methodVisitor.visitVarInsn(ISTORE, 3);
methodVisitor.visitVarInsn(ALOAD, 0);
methodVisitor.visitInsn(ICONST_4);
methodVisitor.visitIntInsn(BIPUSH, 6);
methodVisitor.visitMethodInsn(INVOKEVIRTUAL, "java/lang/String", "substring", "(II)Ljava/lang/String;", false);
methodVisitor.visitVarInsn(ASTORE, 4);
methodVisitor.visitLabel(label0);
methodVisitor.visitVarInsn(ALOAD, 4);
methodVisitor.visitMethodInsn(INVOKESTATIC, "java/lang/Integer", "parseInt", "(Ljava/lang/String;)I", false);
methodVisitor.visitVarInsn(ISTORE, 3);
methodVisitor.visitLabel(label1);
Label label7 = new Label();
methodVisitor.visitJumpInsn(GOTO, label7);
methodVisitor.visitLabel(label2);
methodVisitor.visitVarInsn(ASTORE, 5);
methodVisitor.visitTypeInsn(NEW, "java/lang/IllegalArgumentException");
methodVisitor.visitInsn(DUP);
methodVisitor.visitTypeInsn(NEW, "java/lang/StringBuilder");
methodVisitor.visitInsn(DUP);
methodVisitor.visitMethodInsn(INVOKESPECIAL, "java/lang/StringBuilder", "<init>", "()V", false);
methodVisitor.visitLdcInsn("Invalid cost factor: ");
methodVisitor.visitMethodInsn(INVOKEVIRTUAL, "java/lang/StringBuilder", "append", "(Ljava/lang/String;)Ljava/lang/StringBuilder;", false);
methodVisitor.visitVarInsn(ALOAD, 4);
methodVisitor.visitMethodInsn(INVOKEVIRTUAL, "java/lang/StringBuilder", "append", "(Ljava/lang/String;)Ljava/lang/StringBuilder;", false);
methodVisitor.visitMethodInsn(INVOKEVIRTUAL, "java/lang/StringBuilder", "toString", "()Ljava/lang/String;", false);
methodVisitor.visitMethodInsn(INVOKESPECIAL, "java/lang/IllegalArgumentException", "<init>", "(Ljava/lang/String;)V", false);
methodVisitor.visitInsn(ATHROW);
methodVisitor.visitLabel(label7);
methodVisitor.visitVarInsn(ILOAD, 3);
methodVisitor.visitInsn(ICONST_4);
Label label8 = new Label();
methodVisitor.visitJumpInsn(IF_ICMPLT, label8);
methodVisitor.visitVarInsn(ILOAD, 3);
methodVisitor.visitIntInsn(BIPUSH, 31);
Label label9 = new Label();
methodVisitor.visitJumpInsn(IF_ICMPLE, label9);
methodVisitor.visitLabel(label8);
methodVisitor.visitTypeInsn(NEW, "java/lang/IllegalArgumentException");
methodVisitor.visitInsn(DUP);
methodVisitor.visitTypeInsn(NEW, "java/lang/StringBuilder");
methodVisitor.visitInsn(DUP);
methodVisitor.visitMethodInsn(INVOKESPECIAL, "java/lang/StringBuilder", "<init>", "()V", false);
methodVisitor.visitLdcInsn("Invalid cost factor: ");
methodVisitor.visitMethodInsn(INVOKEVIRTUAL, "java/lang/StringBuilder", "append", "(Ljava/lang/String;)Ljava/lang/StringBuilder;", false);
methodVisitor.visitVarInsn(ILOAD, 3);
methodVisitor.visitMethodInsn(INVOKEVIRTUAL, "java/lang/StringBuilder", "append", "(I)Ljava/lang/StringBuilder;", false);
methodVisitor.visitLdcInsn(", 4 < cost < 31 expected.");
methodVisitor.visitMethodInsn(INVOKEVIRTUAL, "java/lang/StringBuilder", "append", "(Ljava/lang/String;)Ljava/lang/StringBuilder;", false);
methodVisitor.visitMethodInsn(INVOKEVIRTUAL, "java/lang/StringBuilder", "toString", "()Ljava/lang/String;", false);
methodVisitor.visitMethodInsn(INVOKESPECIAL, "java/lang/IllegalArgumentException", "<init>", "(Ljava/lang/String;)V", false);
methodVisitor.visitInsn(ATHROW);
methodVisitor.visitLabel(label9);
methodVisitor.visitVarInsn(ALOAD, 1);
Label label10 = new Label();
methodVisitor.visitJumpInsn(IFNONNULL, label10);
methodVisitor.visitTypeInsn(NEW, "java/lang/IllegalArgumentException");
methodVisitor.visitInsn(DUP);
methodVisitor.visitLdcInsn("Missing password.");
methodVisitor.visitMethodInsn(INVOKESPECIAL, "java/lang/IllegalArgumentException", "<init>", "(Ljava/lang/String;)V", false);
methodVisitor.visitInsn(ATHROW);
methodVisitor.visitLabel(label10);
methodVisitor.visitVarInsn(ALOAD, 0);
methodVisitor.visitVarInsn(ALOAD, 0);
methodVisitor.visitIntInsn(BIPUSH, 36);
methodVisitor.visitMethodInsn(INVOKEVIRTUAL, "java/lang/String", "lastIndexOf", "(I)I", false);
methodVisitor.visitInsn(ICONST_1);
methodVisitor.visitInsn(IADD);
methodVisitor.visitVarInsn(ALOAD, 0);
methodVisitor.visitMethodInsn(INVOKEVIRTUAL, "java/lang/String", "length", "()I", false);
methodVisitor.visitIntInsn(BIPUSH, 31);
methodVisitor.visitInsn(ISUB);
methodVisitor.visitMethodInsn(INVOKEVIRTUAL, "java/lang/String", "substring", "(II)Ljava/lang/String;", false);
methodVisitor.visitMethodInsn(INVOKESTATIC, "org/bouncycastle/crypto/generators/OpenBSDBCrypt", "decodeSaltString", "(Ljava/lang/String;)[B", false);
methodVisitor.visitVarInsn(ASTORE, 5);
methodVisitor.visitVarInsn(ALOAD, 2);
methodVisitor.visitVarInsn(ALOAD, 1);
methodVisitor.visitVarInsn(ALOAD, 5);
methodVisitor.visitVarInsn(ILOAD, 3);
methodVisitor.visitMethodInsn(INVOKESTATIC, "org/bouncycastle/crypto/generators/OpenBSDBCrypt", "generate", "(Ljava/lang/String;[C[BI)Ljava/lang/String;", false);
methodVisitor.visitVarInsn(ASTORE, 6);
methodVisitor.visitVarInsn(ALOAD, 0);
methodVisitor.visitVarInsn(ALOAD, 6);
methodVisitor.visitMethodInsn(INVOKEVIRTUAL, "java/lang/String", "equals", "(Ljava/lang/Object;)Z", false);
methodVisitor.visitInsn(IRETURN);
methodVisitor.visitMaxs(4, 7);
methodVisitor.visitEnd();
}
{
methodVisitor = classWriter.visitMethod(ACC_PRIVATE | ACC_STATIC, "encodeData", "([B)Ljava/lang/String;", null, null);
methodVisitor.visitCode();
methodVisitor.visitVarInsn(ALOAD, 0);
methodVisitor.visitInsn(ARRAYLENGTH);
methodVisitor.visitIntInsn(BIPUSH, 24);
Label label0 = new Label();
methodVisitor.visitJumpInsn(IF_ICMPEQ, label0);
methodVisitor.visitVarInsn(ALOAD, 0);
methodVisitor.visitInsn(ARRAYLENGTH);
methodVisitor.visitIntInsn(BIPUSH, 16);
methodVisitor.visitJumpInsn(IF_ICMPEQ, label0);
methodVisitor.visitTypeInsn(NEW, "org/bouncycastle/crypto/DataLengthException");
methodVisitor.visitInsn(DUP);
methodVisitor.visitTypeInsn(NEW, "java/lang/StringBuilder");
methodVisitor.visitInsn(DUP);
methodVisitor.visitMethodInsn(INVOKESPECIAL, "java/lang/StringBuilder", "<init>", "()V", false);
methodVisitor.visitLdcInsn("Invalid length: ");
methodVisitor.visitMethodInsn(INVOKEVIRTUAL, "java/lang/StringBuilder", "append", "(Ljava/lang/String;)Ljava/lang/StringBuilder;", false);
methodVisitor.visitVarInsn(ALOAD, 0);
methodVisitor.visitInsn(ARRAYLENGTH);
methodVisitor.visitMethodInsn(INVOKEVIRTUAL, "java/lang/StringBuilder", "append", "(I)Ljava/lang/StringBuilder;", false);
methodVisitor.visitLdcInsn(", 24 for key or 16 for salt expected");
methodVisitor.visitMethodInsn(INVOKEVIRTUAL, "java/lang/StringBuilder", "append", "(Ljava/lang/String;)Ljava/lang/StringBuilder;", false);
methodVisitor.visitMethodInsn(INVOKEVIRTUAL, "java/lang/StringBuilder", "toString", "()Ljava/lang/String;", false);
methodVisitor.visitMethodInsn(INVOKESPECIAL, "org/bouncycastle/crypto/DataLengthException", "<init>", "(Ljava/lang/String;)V", false);
methodVisitor.visitInsn(ATHROW);
methodVisitor.visitLabel(label0);
methodVisitor.visitInsn(ICONST_0);
methodVisitor.visitVarInsn(ISTORE, 1);
methodVisitor.visitVarInsn(ALOAD, 0);
methodVisitor.visitInsn(ARRAYLENGTH);
methodVisitor.visitIntInsn(BIPUSH, 16);
Label label1 = new Label();
methodVisitor.visitJumpInsn(IF_ICMPNE, label1);
methodVisitor.visitInsn(ICONST_1);
methodVisitor.visitVarInsn(ISTORE, 1);
methodVisitor.visitIntInsn(BIPUSH, 18);
methodVisitor.visitIntInsn(NEWARRAY, T_BYTE);
methodVisitor.visitVarInsn(ASTORE, 2);
methodVisitor.visitVarInsn(ALOAD, 0);
methodVisitor.visitInsn(ICONST_0);
methodVisitor.visitVarInsn(ALOAD, 2);
methodVisitor.visitInsn(ICONST_0);
methodVisitor.visitVarInsn(ALOAD, 0);
methodVisitor.visitInsn(ARRAYLENGTH);
methodVisitor.visitMethodInsn(INVOKESTATIC, "java/lang/System", "arraycopy", "(Ljava/lang/Object;ILjava/lang/Object;II)V", false);
methodVisitor.visitVarInsn(ALOAD, 2);
methodVisitor.visitVarInsn(ASTORE, 0);
Label label2 = new Label();
methodVisitor.visitJumpInsn(GOTO, label2);
methodVisitor.visitLabel(label1);
methodVisitor.visitVarInsn(ALOAD, 0);
methodVisitor.visitVarInsn(ALOAD, 0);
methodVisitor.visitInsn(ARRAYLENGTH);
methodVisitor.visitInsn(ICONST_1);
methodVisitor.visitInsn(ISUB);
methodVisitor.visitInsn(ICONST_0);
methodVisitor.visitInsn(BASTORE);
methodVisitor.visitLabel(label2);
methodVisitor.visitTypeInsn(NEW, "java/io/ByteArrayOutputStream");
methodVisitor.visitInsn(DUP);
methodVisitor.visitMethodInsn(INVOKESPECIAL, "java/io/ByteArrayOutputStream", "<init>", "()V", false);
methodVisitor.visitVarInsn(ASTORE, 2);
methodVisitor.visitVarInsn(ALOAD, 0);
methodVisitor.visitInsn(ARRAYLENGTH);
methodVisitor.visitVarInsn(ISTORE, 3);
methodVisitor.visitInsn(ICONST_0);
methodVisitor.visitVarInsn(ISTORE, 7);
Label label3 = new Label();
methodVisitor.visitLabel(label3);
methodVisitor.visitVarInsn(ILOAD, 7);
methodVisitor.visitVarInsn(ILOAD, 3);
Label label4 = new Label();
methodVisitor.visitJumpInsn(IF_ICMPGE, label4);
methodVisitor.visitVarInsn(ALOAD, 0);
methodVisitor.visitVarInsn(ILOAD, 7);
methodVisitor.visitInsn(BALOAD);
methodVisitor.visitIntInsn(SIPUSH, 255);
methodVisitor.visitInsn(IAND);
methodVisitor.visitVarInsn(ISTORE, 4);
methodVisitor.visitVarInsn(ALOAD, 0);
methodVisitor.visitVarInsn(ILOAD, 7);
methodVisitor.visitInsn(ICONST_1);
methodVisitor.visitInsn(IADD);
methodVisitor.visitInsn(BALOAD);
methodVisitor.visitIntInsn(SIPUSH, 255);
methodVisitor.visitInsn(IAND);
methodVisitor.visitVarInsn(ISTORE, 5);
methodVisitor.visitVarInsn(ALOAD, 0);
methodVisitor.visitVarInsn(ILOAD, 7);
methodVisitor.visitInsn(ICONST_2);
methodVisitor.visitInsn(IADD);
methodVisitor.visitInsn(BALOAD);
methodVisitor.visitIntInsn(SIPUSH, 255);
methodVisitor.visitInsn(IAND);
methodVisitor.visitVarInsn(ISTORE, 6);
methodVisitor.visitVarInsn(ALOAD, 2);
methodVisitor.visitFieldInsn(GETSTATIC, "org/bouncycastle/crypto/generators/OpenBSDBCrypt", "encodingTable", "[B");
methodVisitor.visitVarInsn(ILOAD, 4);
methodVisitor.visitInsn(ICONST_2);
methodVisitor.visitInsn(IUSHR);
methodVisitor.visitIntInsn(BIPUSH, 63);
methodVisitor.visitInsn(IAND);
methodVisitor.visitInsn(BALOAD);
methodVisitor.visitMethodInsn(INVOKEVIRTUAL, "java/io/ByteArrayOutputStream", "write", "(I)V", false);
methodVisitor.visitVarInsn(ALOAD, 2);
methodVisitor.visitFieldInsn(GETSTATIC, "org/bouncycastle/crypto/generators/OpenBSDBCrypt", "encodingTable", "[B");
methodVisitor.visitVarInsn(ILOAD, 4);
methodVisitor.visitInsn(ICONST_4);
methodVisitor.visitInsn(ISHL);
methodVisitor.visitVarInsn(ILOAD, 5);
methodVisitor.visitInsn(ICONST_4);
methodVisitor.visitInsn(IUSHR);
methodVisitor.visitInsn(IOR);
methodVisitor.visitIntInsn(BIPUSH, 63);
methodVisitor.visitInsn(IAND);
methodVisitor.visitInsn(BALOAD);
methodVisitor.visitMethodInsn(INVOKEVIRTUAL, "java/io/ByteArrayOutputStream", "write", "(I)V", false);
methodVisitor.visitVarInsn(ALOAD, 2);
methodVisitor.visitFieldInsn(GETSTATIC, "org/bouncycastle/crypto/generators/OpenBSDBCrypt", "encodingTable", "[B");
methodVisitor.visitVarInsn(ILOAD, 5);
methodVisitor.visitInsn(ICONST_2);
methodVisitor.visitInsn(ISHL);
methodVisitor.visitVarInsn(ILOAD, 6);
methodVisitor.visitIntInsn(BIPUSH, 6);
methodVisitor.visitInsn(IUSHR);
methodVisitor.visitInsn(IOR);
methodVisitor.visitIntInsn(BIPUSH, 63);
methodVisitor.visitInsn(IAND);
methodVisitor.visitInsn(BALOAD);
methodVisitor.visitMethodInsn(INVOKEVIRTUAL, "java/io/ByteArrayOutputStream", "write", "(I)V", false);
methodVisitor.visitVarInsn(ALOAD, 2);
methodVisitor.visitFieldInsn(GETSTATIC, "org/bouncycastle/crypto/generators/OpenBSDBCrypt", "encodingTable", "[B");
methodVisitor.visitVarInsn(ILOAD, 6);
methodVisitor.visitIntInsn(BIPUSH, 63);
methodVisitor.visitInsn(IAND);
methodVisitor.visitInsn(BALOAD);
methodVisitor.visitMethodInsn(INVOKEVIRTUAL, "java/io/ByteArrayOutputStream", "write", "(I)V", false);
methodVisitor.visitIincInsn(7, 3);
methodVisitor.visitJumpInsn(GOTO, label3);
methodVisitor.visitLabel(label4);
methodVisitor.visitVarInsn(ALOAD, 2);
methodVisitor.visitMethodInsn(INVOKEVIRTUAL, "java/io/ByteArrayOutputStream", "toByteArray", "()[B", false);
methodVisitor.visitMethodInsn(INVOKESTATIC, "org/bouncycastle/util/Strings", "fromByteArray", "([B)Ljava/lang/String;", false);
methodVisitor.visitVarInsn(ASTORE, 8);
methodVisitor.visitVarInsn(ILOAD, 1);
methodVisitor.visitInsn(ICONST_1);
Label label5 = new Label();
methodVisitor.visitJumpInsn(IF_ICMPNE, label5);
methodVisitor.visitVarInsn(ALOAD, 8);
methodVisitor.visitInsn(ICONST_0);
methodVisitor.visitIntInsn(BIPUSH, 22);
methodVisitor.visitMethodInsn(INVOKEVIRTUAL, "java/lang/String", "substring", "(II)Ljava/lang/String;", false);
methodVisitor.visitInsn(ARETURN);
methodVisitor.visitLabel(label5);
methodVisitor.visitVarInsn(ALOAD, 8);
methodVisitor.visitInsn(ICONST_0);
methodVisitor.visitVarInsn(ALOAD, 8);
methodVisitor.visitMethodInsn(INVOKEVIRTUAL, "java/lang/String", "length", "()I", false);
methodVisitor.visitInsn(ICONST_1);
methodVisitor.visitInsn(ISUB);
methodVisitor.visitMethodInsn(INVOKEVIRTUAL, "java/lang/String", "substring", "(II)Ljava/lang/String;", false);
methodVisitor.visitInsn(ARETURN);
methodVisitor.visitMaxs(5, 9);
methodVisitor.visitEnd();
}
{
methodVisitor = classWriter.visitMethod(ACC_PRIVATE | ACC_STATIC, "decodeSaltString", "(Ljava/lang/String;)[B", null, null);
methodVisitor.visitCode();
methodVisitor.visitVarInsn(ALOAD, 0);
methodVisitor.visitMethodInsn(INVOKEVIRTUAL, "java/lang/String", "toCharArray", "()[C", false);
methodVisitor.visitVarInsn(ASTORE, 1);
methodVisitor.visitTypeInsn(NEW, "java/io/ByteArrayOutputStream");
methodVisitor.visitInsn(DUP);
methodVisitor.visitIntInsn(BIPUSH, 16);
methodVisitor.visitMethodInsn(INVOKESPECIAL, "java/io/ByteArrayOutputStream", "<init>", "(I)V", false);
methodVisitor.visitVarInsn(ASTORE, 2);
methodVisitor.visitVarInsn(ALOAD, 1);
methodVisitor.visitInsn(ARRAYLENGTH);
methodVisitor.visitIntInsn(BIPUSH, 22);
Label label0 = new Label();
methodVisitor.visitJumpInsn(IF_ICMPEQ, label0);
methodVisitor.visitTypeInsn(NEW, "org/bouncycastle/crypto/DataLengthException");
methodVisitor.visitInsn(DUP);
methodVisitor.visitTypeInsn(NEW, "java/lang/StringBuilder");
methodVisitor.visitInsn(DUP);
methodVisitor.visitMethodInsn(INVOKESPECIAL, "java/lang/StringBuilder", "<init>", "()V", false);
methodVisitor.visitLdcInsn("Invalid base64 salt length: ");
methodVisitor.visitMethodInsn(INVOKEVIRTUAL, "java/lang/StringBuilder", "append", "(Ljava/lang/String;)Ljava/lang/StringBuilder;", false);
methodVisitor.visitVarInsn(ALOAD, 1);
methodVisitor.visitInsn(ARRAYLENGTH);
methodVisitor.visitMethodInsn(INVOKEVIRTUAL, "java/lang/StringBuilder", "append", "(I)Ljava/lang/StringBuilder;", false);
methodVisitor.visitLdcInsn(" , 22 required.");
methodVisitor.visitMethodInsn(INVOKEVIRTUAL, "java/lang/StringBuilder", "append", "(Ljava/lang/String;)Ljava/lang/StringBuilder;", false);
methodVisitor.visitMethodInsn(INVOKEVIRTUAL, "java/lang/StringBuilder", "toString", "()Ljava/lang/String;", false);
methodVisitor.visitMethodInsn(INVOKESPECIAL, "org/bouncycastle/crypto/DataLengthException", "<init>", "(Ljava/lang/String;)V", false);
methodVisitor.visitInsn(ATHROW);
methodVisitor.visitLabel(label0);
methodVisitor.visitInsn(ICONST_0);
methodVisitor.visitVarInsn(ISTORE, 7);
Label label1 = new Label();
methodVisitor.visitLabel(label1);
methodVisitor.visitVarInsn(ILOAD, 7);
methodVisitor.visitVarInsn(ALOAD, 1);
methodVisitor.visitInsn(ARRAYLENGTH);
Label label2 = new Label();
methodVisitor.visitJumpInsn(IF_ICMPGE, label2);
methodVisitor.visitVarInsn(ALOAD, 1);
methodVisitor.visitVarInsn(ILOAD, 7);
methodVisitor.visitInsn(CALOAD);
methodVisitor.visitVarInsn(ISTORE, 8);
methodVisitor.visitVarInsn(ILOAD, 8);
methodVisitor.visitIntInsn(BIPUSH, 122);
Label label3 = new Label();
methodVisitor.visitJumpInsn(IF_ICMPGT, label3);
methodVisitor.visitVarInsn(ILOAD, 8);
methodVisitor.visitIntInsn(BIPUSH, 46);
methodVisitor.visitJumpInsn(IF_ICMPLT, label3);
methodVisitor.visitVarInsn(ILOAD, 8);
methodVisitor.visitIntInsn(BIPUSH, 57);
Label label4 = new Label();
methodVisitor.visitJumpInsn(IF_ICMPLE, label4);
methodVisitor.visitVarInsn(ILOAD, 8);
methodVisitor.visitIntInsn(BIPUSH, 65);
methodVisitor.visitJumpInsn(IF_ICMPGE, label4);
methodVisitor.visitLabel(label3);
methodVisitor.visitTypeInsn(NEW, "java/lang/IllegalArgumentException");
methodVisitor.visitInsn(DUP);
methodVisitor.visitTypeInsn(NEW, "java/lang/StringBuilder");
methodVisitor.visitInsn(DUP);
methodVisitor.visitMethodInsn(INVOKESPECIAL, "java/lang/StringBuilder", "<init>", "()V", false);
methodVisitor.visitLdcInsn("Salt string contains invalid character: ");
methodVisitor.visitMethodInsn(INVOKEVIRTUAL, "java/lang/StringBuilder", "append", "(Ljava/lang/String;)Ljava/lang/StringBuilder;", false);
methodVisitor.visitVarInsn(ILOAD, 8);
methodVisitor.visitMethodInsn(INVOKEVIRTUAL, "java/lang/StringBuilder", "append", "(I)Ljava/lang/StringBuilder;", false);
methodVisitor.visitMethodInsn(INVOKEVIRTUAL, "java/lang/StringBuilder", "toString", "()Ljava/lang/String;", false);
methodVisitor.visitMethodInsn(INVOKESPECIAL, "java/lang/IllegalArgumentException", "<init>", "(Ljava/lang/String;)V", false);
methodVisitor.visitInsn(ATHROW);
methodVisitor.visitLabel(label4);
methodVisitor.visitIincInsn(7, 1);
methodVisitor.visitJumpInsn(GOTO, label1);
methodVisitor.visitLabel(label2);
methodVisitor.visitIntInsn(BIPUSH, 24);
methodVisitor.visitIntInsn(NEWARRAY, T_CHAR);
methodVisitor.visitVarInsn(ASTORE, 7);
methodVisitor.visitVarInsn(ALOAD, 1);
methodVisitor.visitInsn(ICONST_0);
methodVisitor.visitVarInsn(ALOAD, 7);
methodVisitor.visitInsn(ICONST_0);
methodVisitor.visitVarInsn(ALOAD, 1);
methodVisitor.visitInsn(ARRAYLENGTH);
methodVisitor.visitMethodInsn(INVOKESTATIC, "java/lang/System", "arraycopy", "(Ljava/lang/Object;ILjava/lang/Object;II)V", false);
methodVisitor.visitVarInsn(ALOAD, 7);
methodVisitor.visitVarInsn(ASTORE, 1);
methodVisitor.visitVarInsn(ALOAD, 1);
methodVisitor.visitInsn(ARRAYLENGTH);
methodVisitor.visitVarInsn(ISTORE, 8);
methodVisitor.visitInsn(ICONST_0);
methodVisitor.visitVarInsn(ISTORE, 9);
Label label5 = new Label();
methodVisitor.visitLabel(label5);
methodVisitor.visitVarInsn(ILOAD, 9);
methodVisitor.visitVarInsn(ILOAD, 8);
Label label6 = new Label();
methodVisitor.visitJumpInsn(IF_ICMPGE, label6);
methodVisitor.visitFieldInsn(GETSTATIC, "org/bouncycastle/crypto/generators/OpenBSDBCrypt", "decodingTable", "[B");
methodVisitor.visitVarInsn(ALOAD, 1);
methodVisitor.visitVarInsn(ILOAD, 9);
methodVisitor.visitInsn(CALOAD);
methodVisitor.visitInsn(BALOAD);
methodVisitor.visitVarInsn(ISTORE, 3);
methodVisitor.visitFieldInsn(GETSTATIC, "org/bouncycastle/crypto/generators/OpenBSDBCrypt", "decodingTable", "[B");
methodVisitor.visitVarInsn(ALOAD, 1);
methodVisitor.visitVarInsn(ILOAD, 9);
methodVisitor.visitInsn(ICONST_1);
methodVisitor.visitInsn(IADD);
methodVisitor.visitInsn(CALOAD);
methodVisitor.visitInsn(BALOAD);
methodVisitor.visitVarInsn(ISTORE, 4);
methodVisitor.visitFieldInsn(GETSTATIC, "org/bouncycastle/crypto/generators/OpenBSDBCrypt", "decodingTable", "[B");
methodVisitor.visitVarInsn(ALOAD, 1);
methodVisitor.visitVarInsn(ILOAD, 9);
methodVisitor.visitInsn(ICONST_2);
methodVisitor.visitInsn(IADD);
methodVisitor.visitInsn(CALOAD);
methodVisitor.visitInsn(BALOAD);
methodVisitor.visitVarInsn(ISTORE, 5);
methodVisitor.visitFieldInsn(GETSTATIC, "org/bouncycastle/crypto/generators/OpenBSDBCrypt", "decodingTable", "[B");
methodVisitor.visitVarInsn(ALOAD, 1);
methodVisitor.visitVarInsn(ILOAD, 9);
methodVisitor.visitInsn(ICONST_3);
methodVisitor.visitInsn(IADD);
methodVisitor.visitInsn(CALOAD);
methodVisitor.visitInsn(BALOAD);
methodVisitor.visitVarInsn(ISTORE, 6);
methodVisitor.visitVarInsn(ALOAD, 2);
methodVisitor.visitVarInsn(ILOAD, 3);
methodVisitor.visitInsn(ICONST_2);
methodVisitor.visitInsn(ISHL);
methodVisitor.visitVarInsn(ILOAD, 4);
methodVisitor.visitInsn(ICONST_4);
methodVisitor.visitInsn(ISHR);
methodVisitor.visitInsn(IOR);
methodVisitor.visitMethodInsn(INVOKEVIRTUAL, "java/io/ByteArrayOutputStream", "write", "(I)V", false);
methodVisitor.visitVarInsn(ALOAD, 2);
methodVisitor.visitVarInsn(ILOAD, 4);
methodVisitor.visitInsn(ICONST_4);
methodVisitor.visitInsn(ISHL);
methodVisitor.visitVarInsn(ILOAD, 5);
methodVisitor.visitInsn(ICONST_2);
methodVisitor.visitInsn(ISHR);
methodVisitor.visitInsn(IOR);
methodVisitor.visitMethodInsn(INVOKEVIRTUAL, "java/io/ByteArrayOutputStream", "write", "(I)V", false);
methodVisitor.visitVarInsn(ALOAD, 2);
methodVisitor.visitVarInsn(ILOAD, 5);
methodVisitor.visitIntInsn(BIPUSH, 6);
methodVisitor.visitInsn(ISHL);
methodVisitor.visitVarInsn(ILOAD, 6);
methodVisitor.visitInsn(IOR);
methodVisitor.visitMethodInsn(INVOKEVIRTUAL, "java/io/ByteArrayOutputStream", "write", "(I)V", false);
methodVisitor.visitIincInsn(9, 4);
methodVisitor.visitJumpInsn(GOTO, label5);
methodVisitor.visitLabel(label6);
methodVisitor.visitVarInsn(ALOAD, 2);
methodVisitor.visitMethodInsn(INVOKEVIRTUAL, "java/io/ByteArrayOutputStream", "toByteArray", "()[B", false);
methodVisitor.visitVarInsn(ASTORE, 9);
methodVisitor.visitIntInsn(BIPUSH, 16);
methodVisitor.visitIntInsn(NEWARRAY, T_BYTE);
methodVisitor.visitVarInsn(ASTORE, 10);
methodVisitor.visitVarInsn(ALOAD, 9);
methodVisitor.visitInsn(ICONST_0);
methodVisitor.visitVarInsn(ALOAD, 10);
methodVisitor.visitInsn(ICONST_0);
methodVisitor.visitVarInsn(ALOAD, 10);
methodVisitor.visitInsn(ARRAYLENGTH);
methodVisitor.visitMethodInsn(INVOKESTATIC, "java/lang/System", "arraycopy", "(Ljava/lang/Object;ILjava/lang/Object;II)V", false);
methodVisitor.visitVarInsn(ALOAD, 10);
methodVisitor.visitVarInsn(ASTORE, 9);
methodVisitor.visitVarInsn(ALOAD, 9);
methodVisitor.visitInsn(ARETURN);
methodVisitor.visitMaxs(5, 11);
methodVisitor.visitEnd();
}
{
methodVisitor = classWriter.visitMethod(ACC_STATIC, "<clinit>", "()V", null, null);
methodVisitor.visitCode();
methodVisitor.visitIntInsn(BIPUSH, 64);
methodVisitor.visitIntInsn(NEWARRAY, T_BYTE);
methodVisitor.visitInsn(DUP);
methodVisitor.visitInsn(ICONST_0);
methodVisitor.visitIntInsn(BIPUSH, 46);
methodVisitor.visitInsn(BASTORE);
methodVisitor.visitInsn(DUP);
methodVisitor.visitInsn(ICONST_1);
methodVisitor.visitIntInsn(BIPUSH, 47);
methodVisitor.visitInsn(BASTORE);
methodVisitor.visitInsn(DUP);
methodVisitor.visitInsn(ICONST_2);
methodVisitor.visitIntInsn(BIPUSH, 65);
methodVisitor.visitInsn(BASTORE);
methodVisitor.visitInsn(DUP);
methodVisitor.visitInsn(ICONST_3);
methodVisitor.visitIntInsn(BIPUSH, 66);
methodVisitor.visitInsn(BASTORE);
methodVisitor.visitInsn(DUP);
methodVisitor.visitInsn(ICONST_4);
methodVisitor.visitIntInsn(BIPUSH, 67);
methodVisitor.visitInsn(BASTORE);
methodVisitor.visitInsn(DUP);
methodVisitor.visitInsn(ICONST_5);
methodVisitor.visitIntInsn(BIPUSH, 68);
methodVisitor.visitInsn(BASTORE);
methodVisitor.visitInsn(DUP);
methodVisitor.visitIntInsn(BIPUSH, 6);
methodVisitor.visitIntInsn(BIPUSH, 69);
methodVisitor.visitInsn(BASTORE);
methodVisitor.visitInsn(DUP);
methodVisitor.visitIntInsn(BIPUSH, 7);
methodVisitor.visitIntInsn(BIPUSH, 70);
methodVisitor.visitInsn(BASTORE);
methodVisitor.visitInsn(DUP);
methodVisitor.visitIntInsn(BIPUSH, 8);
methodVisitor.visitIntInsn(BIPUSH, 71);
methodVisitor.visitInsn(BASTORE);
methodVisitor.visitInsn(DUP);
methodVisitor.visitIntInsn(BIPUSH, 9);
methodVisitor.visitIntInsn(BIPUSH, 72);
methodVisitor.visitInsn(BASTORE);
methodVisitor.visitInsn(DUP);
methodVisitor.visitIntInsn(BIPUSH, 10);
methodVisitor.visitIntInsn(BIPUSH, 73);
methodVisitor.visitInsn(BASTORE);
methodVisitor.visitInsn(DUP);
methodVisitor.visitIntInsn(BIPUSH, 11);
methodVisitor.visitIntInsn(BIPUSH, 74);
methodVisitor.visitInsn(BASTORE);
methodVisitor.visitInsn(DUP);
methodVisitor.visitIntInsn(BIPUSH, 12);
methodVisitor.visitIntInsn(BIPUSH, 75);
methodVisitor.visitInsn(BASTORE);
methodVisitor.visitInsn(DUP);
methodVisitor.visitIntInsn(BIPUSH, 13);
methodVisitor.visitIntInsn(BIPUSH, 76);
methodVisitor.visitInsn(BASTORE);
methodVisitor.visitInsn(DUP);
methodVisitor.visitIntInsn(BIPUSH, 14);
methodVisitor.visitIntInsn(BIPUSH, 77);
methodVisitor.visitInsn(BASTORE);
methodVisitor.visitInsn(DUP);
methodVisitor.visitIntInsn(BIPUSH, 15);
methodVisitor.visitIntInsn(BIPUSH, 78);
methodVisitor.visitInsn(BASTORE);
methodVisitor.visitInsn(DUP);
methodVisitor.visitIntInsn(BIPUSH, 16);
methodVisitor.visitIntInsn(BIPUSH, 79);
methodVisitor.visitInsn(BASTORE);
methodVisitor.visitInsn(DUP);
methodVisitor.visitIntInsn(BIPUSH, 17);
methodVisitor.visitIntInsn(BIPUSH, 80);
methodVisitor.visitInsn(BASTORE);
methodVisitor.visitInsn(DUP);
methodVisitor.visitIntInsn(BIPUSH, 18);
methodVisitor.visitIntInsn(BIPUSH, 81);
methodVisitor.visitInsn(BASTORE);
methodVisitor.visitInsn(DUP);
methodVisitor.visitIntInsn(BIPUSH, 19);
methodVisitor.visitIntInsn(BIPUSH, 82);
methodVisitor.visitInsn(BASTORE);
methodVisitor.visitInsn(DUP);
methodVisitor.visitIntInsn(BIPUSH, 20);
methodVisitor.visitIntInsn(BIPUSH, 83);
methodVisitor.visitInsn(BASTORE);
methodVisitor.visitInsn(DUP);
methodVisitor.visitIntInsn(BIPUSH, 21);
methodVisitor.visitIntInsn(BIPUSH, 84);
methodVisitor.visitInsn(BASTORE);
methodVisitor.visitInsn(DUP);
methodVisitor.visitIntInsn(BIPUSH, 22);
methodVisitor.visitIntInsn(BIPUSH, 85);
methodVisitor.visitInsn(BASTORE);
methodVisitor.visitInsn(DUP);
methodVisitor.visitIntInsn(BIPUSH, 23);
methodVisitor.visitIntInsn(BIPUSH, 86);
methodVisitor.visitInsn(BASTORE);
methodVisitor.visitInsn(DUP);
methodVisitor.visitIntInsn(BIPUSH, 24);
methodVisitor.visitIntInsn(BIPUSH, 87);
methodVisitor.visitInsn(BASTORE);
methodVisitor.visitInsn(DUP);
methodVisitor.visitIntInsn(BIPUSH, 25);
methodVisitor.visitIntInsn(BIPUSH, 88);
methodVisitor.visitInsn(BASTORE);
methodVisitor.visitInsn(DUP);
methodVisitor.visitIntInsn(BIPUSH, 26);
methodVisitor.visitIntInsn(BIPUSH, 89);
methodVisitor.visitInsn(BASTORE);
methodVisitor.visitInsn(DUP);
methodVisitor.visitIntInsn(BIPUSH, 27);
methodVisitor.visitIntInsn(BIPUSH, 90);
methodVisitor.visitInsn(BASTORE);
methodVisitor.visitInsn(DUP);
methodVisitor.visitIntInsn(BIPUSH, 28);
methodVisitor.visitIntInsn(BIPUSH, 97);
methodVisitor.visitInsn(BASTORE);
methodVisitor.visitInsn(DUP);
methodVisitor.visitIntInsn(BIPUSH, 29);
methodVisitor.visitIntInsn(BIPUSH, 98);
methodVisitor.visitInsn(BASTORE);
methodVisitor.visitInsn(DUP);
methodVisitor.visitIntInsn(BIPUSH, 30);
methodVisitor.visitIntInsn(BIPUSH, 99);
methodVisitor.visitInsn(BASTORE);
methodVisitor.visitInsn(DUP);
methodVisitor.visitIntInsn(BIPUSH, 31);
methodVisitor.visitIntInsn(BIPUSH, 100);
methodVisitor.visitInsn(BASTORE);
methodVisitor.visitInsn(DUP);
methodVisitor.visitIntInsn(BIPUSH, 32);
methodVisitor.visitIntInsn(BIPUSH, 101);
methodVisitor.visitInsn(BASTORE);
methodVisitor.visitInsn(DUP);
methodVisitor.visitIntInsn(BIPUSH, 33);
methodVisitor.visitIntInsn(BIPUSH, 102);
methodVisitor.visitInsn(BASTORE);
methodVisitor.visitInsn(DUP);
methodVisitor.visitIntInsn(BIPUSH, 34);
methodVisitor.visitIntInsn(BIPUSH, 103);
methodVisitor.visitInsn(BASTORE);
methodVisitor.visitInsn(DUP);
methodVisitor.visitIntInsn(BIPUSH, 35);
methodVisitor.visitIntInsn(BIPUSH, 104);
methodVisitor.visitInsn(BASTORE);
methodVisitor.visitInsn(DUP);
methodVisitor.visitIntInsn(BIPUSH, 36);
methodVisitor.visitIntInsn(BIPUSH, 105);
methodVisitor.visitInsn(BASTORE);
methodVisitor.visitInsn(DUP);
methodVisitor.visitIntInsn(BIPUSH, 37);
methodVisitor.visitIntInsn(BIPUSH, 106);
methodVisitor.visitInsn(BASTORE);
methodVisitor.visitInsn(DUP);
methodVisitor.visitIntInsn(BIPUSH, 38);
methodVisitor.visitIntInsn(BIPUSH, 107);
methodVisitor.visitInsn(BASTORE);
methodVisitor.visitInsn(DUP);
methodVisitor.visitIntInsn(BIPUSH, 39);
methodVisitor.visitIntInsn(BIPUSH, 108);
methodVisitor.visitInsn(BASTORE);
methodVisitor.visitInsn(DUP);
methodVisitor.visitIntInsn(BIPUSH, 40);
methodVisitor.visitIntInsn(BIPUSH, 109);
methodVisitor.visitInsn(BASTORE);
methodVisitor.visitInsn(DUP);
methodVisitor.visitIntInsn(BIPUSH, 41);
methodVisitor.visitIntInsn(BIPUSH, 110);
methodVisitor.visitInsn(BASTORE);
methodVisitor.visitInsn(DUP);
methodVisitor.visitIntInsn(BIPUSH, 42);
methodVisitor.visitIntInsn(BIPUSH, 111);
methodVisitor.visitInsn(BASTORE);
methodVisitor.visitInsn(DUP);
methodVisitor.visitIntInsn(BIPUSH, 43);
methodVisitor.visitIntInsn(BIPUSH, 112);
methodVisitor.visitInsn(BASTORE);
methodVisitor.visitInsn(DUP);
methodVisitor.visitIntInsn(BIPUSH, 44);
methodVisitor.visitIntInsn(BIPUSH, 113);
methodVisitor.visitInsn(BASTORE);
methodVisitor.visitInsn(DUP);
methodVisitor.visitIntInsn(BIPUSH, 45);
methodVisitor.visitIntInsn(BIPUSH, 114);
methodVisitor.visitInsn(BASTORE);
methodVisitor.visitInsn(DUP);
methodVisitor.visitIntInsn(BIPUSH, 46);
methodVisitor.visitIntInsn(BIPUSH, 115);
methodVisitor.visitInsn(BASTORE);
methodVisitor.visitInsn(DUP);
methodVisitor.visitIntInsn(BIPUSH, 47);
methodVisitor.visitIntInsn(BIPUSH, 116);
methodVisitor.visitInsn(BASTORE);
methodVisitor.visitInsn(DUP);
methodVisitor.visitIntInsn(BIPUSH, 48);
methodVisitor.visitIntInsn(BIPUSH, 117);
methodVisitor.visitInsn(BASTORE);
methodVisitor.visitInsn(DUP);
methodVisitor.visitIntInsn(BIPUSH, 49);
methodVisitor.visitIntInsn(BIPUSH, 118);
methodVisitor.visitInsn(BASTORE);
methodVisitor.visitInsn(DUP);
methodVisitor.visitIntInsn(BIPUSH, 50);
methodVisitor.visitIntInsn(BIPUSH, 119);
methodVisitor.visitInsn(BASTORE);
methodVisitor.visitInsn(DUP);
methodVisitor.visitIntInsn(BIPUSH, 51);
methodVisitor.visitIntInsn(BIPUSH, 120);
methodVisitor.visitInsn(BASTORE);
methodVisitor.visitInsn(DUP);
methodVisitor.visitIntInsn(BIPUSH, 52);
methodVisitor.visitIntInsn(BIPUSH, 121);
methodVisitor.visitInsn(BASTORE);
methodVisitor.visitInsn(DUP);
methodVisitor.visitIntInsn(BIPUSH, 53);
methodVisitor.visitIntInsn(BIPUSH, 122);
methodVisitor.visitInsn(BASTORE);
methodVisitor.visitInsn(DUP);
methodVisitor.visitIntInsn(BIPUSH, 54);
methodVisitor.visitIntInsn(BIPUSH, 48);
methodVisitor.visitInsn(BASTORE);
methodVisitor.visitInsn(DUP);
methodVisitor.visitIntInsn(BIPUSH, 55);
methodVisitor.visitIntInsn(BIPUSH, 49);
methodVisitor.visitInsn(BASTORE);
methodVisitor.visitInsn(DUP);
methodVisitor.visitIntInsn(BIPUSH, 56);
methodVisitor.visitIntInsn(BIPUSH, 50);
methodVisitor.visitInsn(BASTORE);
methodVisitor.visitInsn(DUP);
methodVisitor.visitIntInsn(BIPUSH, 57);
methodVisitor.visitIntInsn(BIPUSH, 51);
methodVisitor.visitInsn(BASTORE);
methodVisitor.visitInsn(DUP);
methodVisitor.visitIntInsn(BIPUSH, 58);
methodVisitor.visitIntInsn(BIPUSH, 52);
methodVisitor.visitInsn(BASTORE);
methodVisitor.visitInsn(DUP);
methodVisitor.visitIntInsn(BIPUSH, 59);
methodVisitor.visitIntInsn(BIPUSH, 53);
methodVisitor.visitInsn(BASTORE);
methodVisitor.visitInsn(DUP);
methodVisitor.visitIntInsn(BIPUSH, 60);
methodVisitor.visitIntInsn(BIPUSH, 54);
methodVisitor.visitInsn(BASTORE);
methodVisitor.visitInsn(DUP);
methodVisitor.visitIntInsn(BIPUSH, 61);
methodVisitor.visitIntInsn(BIPUSH, 55);
methodVisitor.visitInsn(BASTORE);
methodVisitor.visitInsn(DUP);
methodVisitor.visitIntInsn(BIPUSH, 62);
methodVisitor.visitIntInsn(BIPUSH, 56);
methodVisitor.visitInsn(BASTORE);
methodVisitor.visitInsn(DUP);
methodVisitor.visitIntInsn(BIPUSH, 63);
methodVisitor.visitIntInsn(BIPUSH, 57);
methodVisitor.visitInsn(BASTORE);
methodVisitor.visitFieldInsn(PUTSTATIC, "org/bouncycastle/crypto/generators/OpenBSDBCrypt", "encodingTable", "[B");
methodVisitor.visitIntInsn(SIPUSH, 128);
methodVisitor.visitIntInsn(NEWARRAY, T_BYTE);
methodVisitor.visitFieldInsn(PUTSTATIC, "org/bouncycastle/crypto/generators/OpenBSDBCrypt", "decodingTable", "[B");
methodVisitor.visitTypeInsn(NEW, "java/util/HashSet");
methodVisitor.visitInsn(DUP);
methodVisitor.visitMethodInsn(INVOKESPECIAL, "java/util/HashSet", "<init>", "()V", false);
methodVisitor.visitFieldInsn(PUTSTATIC, "org/bouncycastle/crypto/generators/OpenBSDBCrypt", "allowedVersions", "Ljava/util/Set;");
methodVisitor.visitFieldInsn(GETSTATIC, "org/bouncycastle/crypto/generators/OpenBSDBCrypt", "allowedVersions", "Ljava/util/Set;");
methodVisitor.visitLdcInsn("2a");
methodVisitor.visitMethodInsn(INVOKEINTERFACE, "java/util/Set", "add", "(Ljava/lang/Object;)Z", true);
methodVisitor.visitInsn(POP);
methodVisitor.visitFieldInsn(GETSTATIC, "org/bouncycastle/crypto/generators/OpenBSDBCrypt", "allowedVersions", "Ljava/util/Set;");
methodVisitor.visitLdcInsn("2y");
methodVisitor.visitMethodInsn(INVOKEINTERFACE, "java/util/Set", "add", "(Ljava/lang/Object;)Z", true);
methodVisitor.visitInsn(POP);
methodVisitor.visitFieldInsn(GETSTATIC, "org/bouncycastle/crypto/generators/OpenBSDBCrypt", "allowedVersions", "Ljava/util/Set;");
methodVisitor.visitLdcInsn("2b");
methodVisitor.visitMethodInsn(INVOKEINTERFACE, "java/util/Set", "add", "(Ljava/lang/Object;)Z", true);
methodVisitor.visitInsn(POP);
methodVisitor.visitInsn(ICONST_0);
methodVisitor.visitVarInsn(ISTORE, 0);
Label label0 = new Label();
methodVisitor.visitLabel(label0);
methodVisitor.visitVarInsn(ILOAD, 0);
methodVisitor.visitFieldInsn(GETSTATIC, "org/bouncycastle/crypto/generators/OpenBSDBCrypt", "decodingTable", "[B");
methodVisitor.visitInsn(ARRAYLENGTH);
Label label1 = new Label();
methodVisitor.visitJumpInsn(IF_ICMPGE, label1);
methodVisitor.visitFieldInsn(GETSTATIC, "org/bouncycastle/crypto/generators/OpenBSDBCrypt", "decodingTable", "[B");
methodVisitor.visitVarInsn(ILOAD, 0);
methodVisitor.visitInsn(ICONST_M1);
methodVisitor.visitInsn(BASTORE);
methodVisitor.visitIincInsn(0, 1);
methodVisitor.visitJumpInsn(GOTO, label0);
methodVisitor.visitLabel(label1);
methodVisitor.visitInsn(ICONST_0);
methodVisitor.visitVarInsn(ISTORE, 0);
Label label2 = new Label();
methodVisitor.visitLabel(label2);
methodVisitor.visitVarInsn(ILOAD, 0);
methodVisitor.visitFieldInsn(GETSTATIC, "org/bouncycastle/crypto/generators/OpenBSDBCrypt", "encodingTable", "[B");
methodVisitor.visitInsn(ARRAYLENGTH);
Label label3 = new Label();
methodVisitor.visitJumpInsn(IF_ICMPGE, label3);
methodVisitor.visitFieldInsn(GETSTATIC, "org/bouncycastle/crypto/generators/OpenBSDBCrypt", "decodingTable", "[B");
methodVisitor.visitFieldInsn(GETSTATIC, "org/bouncycastle/crypto/generators/OpenBSDBCrypt", "encodingTable", "[B");
methodVisitor.visitVarInsn(ILOAD, 0);
methodVisitor.visitInsn(BALOAD);
methodVisitor.visitVarInsn(ILOAD, 0);
methodVisitor.visitInsn(I2B);
methodVisitor.visitInsn(BASTORE);
methodVisitor.visitIincInsn(0, 1);
methodVisitor.visitJumpInsn(GOTO, label2);
methodVisitor.visitLabel(label3);
methodVisitor.visitInsn(RETURN);
methodVisitor.visitMaxs(4, 1);
methodVisitor.visitEnd();
}
classWriter.visitEnd();

return classWriter.toByteArray();
}
}
