package asm.org.bouncycastle.pqc.math.linearalgebra;
import org.objectweb.asm.AnnotationVisitor;
import org.objectweb.asm.Attribute;
import org.objectweb.asm.ClassReader;
import org.objectweb.asm.ClassWriter;
import org.objectweb.asm.ConstantDynamic;
import org.objectweb.asm.FieldVisitor;
import org.objectweb.asm.Handle;
import org.objectweb.asm.Label;
import org.objectweb.asm.MethodVisitor;
import org.objectweb.asm.Opcodes;
import org.objectweb.asm.RecordComponentVisitor;
import org.objectweb.asm.Type;
import org.objectweb.asm.TypePath;
public class LittleEndianConversionsDump implements Opcodes {

public static byte[] dump () throws Exception {

ClassWriter classWriter = new ClassWriter(0);
FieldVisitor fieldVisitor;
RecordComponentVisitor recordComponentVisitor;
MethodVisitor methodVisitor;
AnnotationVisitor annotationVisitor0;

classWriter.visit(V1_5, ACC_PUBLIC | ACC_FINAL | ACC_SUPER, "org/bouncycastle/pqc/math/linearalgebra/LittleEndianConversions", null, "java/lang/Object", null);

{
methodVisitor = classWriter.visitMethod(ACC_PRIVATE, "<init>", "()V", null, null);
methodVisitor.visitCode();
methodVisitor.visitVarInsn(ALOAD, 0);
methodVisitor.visitMethodInsn(INVOKESPECIAL, "java/lang/Object", "<init>", "()V", false);
methodVisitor.visitInsn(RETURN);
methodVisitor.visitMaxs(1, 1);
methodVisitor.visitEnd();
}
{
methodVisitor = classWriter.visitMethod(ACC_PUBLIC | ACC_STATIC, "OS2IP", "([B)I", null, null);
methodVisitor.visitCode();
methodVisitor.visitVarInsn(ALOAD, 0);
methodVisitor.visitInsn(ICONST_0);
methodVisitor.visitInsn(BALOAD);
methodVisitor.visitIntInsn(SIPUSH, 255);
methodVisitor.visitInsn(IAND);
methodVisitor.visitVarInsn(ALOAD, 0);
methodVisitor.visitInsn(ICONST_1);
methodVisitor.visitInsn(BALOAD);
methodVisitor.visitIntInsn(SIPUSH, 255);
methodVisitor.visitInsn(IAND);
methodVisitor.visitIntInsn(BIPUSH, 8);
methodVisitor.visitInsn(ISHL);
methodVisitor.visitInsn(IOR);
methodVisitor.visitVarInsn(ALOAD, 0);
methodVisitor.visitInsn(ICONST_2);
methodVisitor.visitInsn(BALOAD);
methodVisitor.visitIntInsn(SIPUSH, 255);
methodVisitor.visitInsn(IAND);
methodVisitor.visitIntInsn(BIPUSH, 16);
methodVisitor.visitInsn(ISHL);
methodVisitor.visitInsn(IOR);
methodVisitor.visitVarInsn(ALOAD, 0);
methodVisitor.visitInsn(ICONST_3);
methodVisitor.visitInsn(BALOAD);
methodVisitor.visitIntInsn(SIPUSH, 255);
methodVisitor.visitInsn(IAND);
methodVisitor.visitIntInsn(BIPUSH, 24);
methodVisitor.visitInsn(ISHL);
methodVisitor.visitInsn(IOR);
methodVisitor.visitInsn(IRETURN);
methodVisitor.visitMaxs(3, 1);
methodVisitor.visitEnd();
}
{
methodVisitor = classWriter.visitMethod(ACC_PUBLIC | ACC_STATIC, "OS2IP", "([BI)I", null, null);
methodVisitor.visitCode();
methodVisitor.visitVarInsn(ALOAD, 0);
methodVisitor.visitVarInsn(ILOAD, 1);
methodVisitor.visitIincInsn(1, 1);
methodVisitor.visitInsn(BALOAD);
methodVisitor.visitIntInsn(SIPUSH, 255);
methodVisitor.visitInsn(IAND);
methodVisitor.visitVarInsn(ISTORE, 2);
methodVisitor.visitVarInsn(ILOAD, 2);
methodVisitor.visitVarInsn(ALOAD, 0);
methodVisitor.visitVarInsn(ILOAD, 1);
methodVisitor.visitIincInsn(1, 1);
methodVisitor.visitInsn(BALOAD);
methodVisitor.visitIntInsn(SIPUSH, 255);
methodVisitor.visitInsn(IAND);
methodVisitor.visitIntInsn(BIPUSH, 8);
methodVisitor.visitInsn(ISHL);
methodVisitor.visitInsn(IOR);
methodVisitor.visitVarInsn(ISTORE, 2);
methodVisitor.visitVarInsn(ILOAD, 2);
methodVisitor.visitVarInsn(ALOAD, 0);
methodVisitor.visitVarInsn(ILOAD, 1);
methodVisitor.visitIincInsn(1, 1);
methodVisitor.visitInsn(BALOAD);
methodVisitor.visitIntInsn(SIPUSH, 255);
methodVisitor.visitInsn(IAND);
methodVisitor.visitIntInsn(BIPUSH, 16);
methodVisitor.visitInsn(ISHL);
methodVisitor.visitInsn(IOR);
methodVisitor.visitVarInsn(ISTORE, 2);
methodVisitor.visitVarInsn(ILOAD, 2);
methodVisitor.visitVarInsn(ALOAD, 0);
methodVisitor.visitVarInsn(ILOAD, 1);
methodVisitor.visitInsn(BALOAD);
methodVisitor.visitIntInsn(SIPUSH, 255);
methodVisitor.visitInsn(IAND);
methodVisitor.visitIntInsn(BIPUSH, 24);
methodVisitor.visitInsn(ISHL);
methodVisitor.visitInsn(IOR);
methodVisitor.visitVarInsn(ISTORE, 2);
methodVisitor.visitVarInsn(ILOAD, 2);
methodVisitor.visitInsn(IRETURN);
methodVisitor.visitMaxs(3, 3);
methodVisitor.visitEnd();
}
{
methodVisitor = classWriter.visitMethod(ACC_PUBLIC | ACC_STATIC, "OS2IP", "([BII)I", null, null);
methodVisitor.visitCode();
methodVisitor.visitInsn(ICONST_0);
methodVisitor.visitVarInsn(ISTORE, 3);
methodVisitor.visitVarInsn(ILOAD, 2);
methodVisitor.visitInsn(ICONST_1);
methodVisitor.visitInsn(ISUB);
methodVisitor.visitVarInsn(ISTORE, 4);
Label label0 = new Label();
methodVisitor.visitLabel(label0);
methodVisitor.visitVarInsn(ILOAD, 4);
Label label1 = new Label();
methodVisitor.visitJumpInsn(IFLT, label1);
methodVisitor.visitVarInsn(ILOAD, 3);
methodVisitor.visitVarInsn(ALOAD, 0);
methodVisitor.visitVarInsn(ILOAD, 1);
methodVisitor.visitVarInsn(ILOAD, 4);
methodVisitor.visitInsn(IADD);
methodVisitor.visitInsn(BALOAD);
methodVisitor.visitIntInsn(SIPUSH, 255);
methodVisitor.visitInsn(IAND);
methodVisitor.visitIntInsn(BIPUSH, 8);
methodVisitor.visitVarInsn(ILOAD, 4);
methodVisitor.visitInsn(IMUL);
methodVisitor.visitInsn(ISHL);
methodVisitor.visitInsn(IOR);
methodVisitor.visitVarInsn(ISTORE, 3);
methodVisitor.visitIincInsn(4, -1);
methodVisitor.visitJumpInsn(GOTO, label0);
methodVisitor.visitLabel(label1);
methodVisitor.visitVarInsn(ILOAD, 3);
methodVisitor.visitInsn(IRETURN);
methodVisitor.visitMaxs(4, 5);
methodVisitor.visitEnd();
}
{
methodVisitor = classWriter.visitMethod(ACC_PUBLIC | ACC_STATIC, "OS2LIP", "([BI)J", null, null);
methodVisitor.visitCode();
methodVisitor.visitVarInsn(ALOAD, 0);
methodVisitor.visitVarInsn(ILOAD, 1);
methodVisitor.visitIincInsn(1, 1);
methodVisitor.visitInsn(BALOAD);
methodVisitor.visitIntInsn(SIPUSH, 255);
methodVisitor.visitInsn(IAND);
methodVisitor.visitInsn(I2L);
methodVisitor.visitVarInsn(LSTORE, 2);
methodVisitor.visitVarInsn(LLOAD, 2);
methodVisitor.visitVarInsn(ALOAD, 0);
methodVisitor.visitVarInsn(ILOAD, 1);
methodVisitor.visitIincInsn(1, 1);
methodVisitor.visitInsn(BALOAD);
methodVisitor.visitIntInsn(SIPUSH, 255);
methodVisitor.visitInsn(IAND);
methodVisitor.visitIntInsn(BIPUSH, 8);
methodVisitor.visitInsn(ISHL);
methodVisitor.visitInsn(I2L);
methodVisitor.visitInsn(LOR);
methodVisitor.visitVarInsn(LSTORE, 2);
methodVisitor.visitVarInsn(LLOAD, 2);
methodVisitor.visitVarInsn(ALOAD, 0);
methodVisitor.visitVarInsn(ILOAD, 1);
methodVisitor.visitIincInsn(1, 1);
methodVisitor.visitInsn(BALOAD);
methodVisitor.visitIntInsn(SIPUSH, 255);
methodVisitor.visitInsn(IAND);
methodVisitor.visitIntInsn(BIPUSH, 16);
methodVisitor.visitInsn(ISHL);
methodVisitor.visitInsn(I2L);
methodVisitor.visitInsn(LOR);
methodVisitor.visitVarInsn(LSTORE, 2);
methodVisitor.visitVarInsn(LLOAD, 2);
methodVisitor.visitVarInsn(ALOAD, 0);
methodVisitor.visitVarInsn(ILOAD, 1);
methodVisitor.visitIincInsn(1, 1);
methodVisitor.visitInsn(BALOAD);
methodVisitor.visitInsn(I2L);
methodVisitor.visitLdcInsn(new Long(255L));
methodVisitor.visitInsn(LAND);
methodVisitor.visitIntInsn(BIPUSH, 24);
methodVisitor.visitInsn(LSHL);
methodVisitor.visitInsn(LOR);
methodVisitor.visitVarInsn(LSTORE, 2);
methodVisitor.visitVarInsn(LLOAD, 2);
methodVisitor.visitVarInsn(ALOAD, 0);
methodVisitor.visitVarInsn(ILOAD, 1);
methodVisitor.visitIincInsn(1, 1);
methodVisitor.visitInsn(BALOAD);
methodVisitor.visitInsn(I2L);
methodVisitor.visitLdcInsn(new Long(255L));
methodVisitor.visitInsn(LAND);
methodVisitor.visitIntInsn(BIPUSH, 32);
methodVisitor.visitInsn(LSHL);
methodVisitor.visitInsn(LOR);
methodVisitor.visitVarInsn(LSTORE, 2);
methodVisitor.visitVarInsn(LLOAD, 2);
methodVisitor.visitVarInsn(ALOAD, 0);
methodVisitor.visitVarInsn(ILOAD, 1);
methodVisitor.visitIincInsn(1, 1);
methodVisitor.visitInsn(BALOAD);
methodVisitor.visitInsn(I2L);
methodVisitor.visitLdcInsn(new Long(255L));
methodVisitor.visitInsn(LAND);
methodVisitor.visitIntInsn(BIPUSH, 40);
methodVisitor.visitInsn(LSHL);
methodVisitor.visitInsn(LOR);
methodVisitor.visitVarInsn(LSTORE, 2);
methodVisitor.visitVarInsn(LLOAD, 2);
methodVisitor.visitVarInsn(ALOAD, 0);
methodVisitor.visitVarInsn(ILOAD, 1);
methodVisitor.visitIincInsn(1, 1);
methodVisitor.visitInsn(BALOAD);
methodVisitor.visitInsn(I2L);
methodVisitor.visitLdcInsn(new Long(255L));
methodVisitor.visitInsn(LAND);
methodVisitor.visitIntInsn(BIPUSH, 48);
methodVisitor.visitInsn(LSHL);
methodVisitor.visitInsn(LOR);
methodVisitor.visitVarInsn(LSTORE, 2);
methodVisitor.visitVarInsn(LLOAD, 2);
methodVisitor.visitVarInsn(ALOAD, 0);
methodVisitor.visitVarInsn(ILOAD, 1);
methodVisitor.visitIincInsn(1, 1);
methodVisitor.visitInsn(BALOAD);
methodVisitor.visitInsn(I2L);
methodVisitor.visitLdcInsn(new Long(255L));
methodVisitor.visitInsn(LAND);
methodVisitor.visitIntInsn(BIPUSH, 56);
methodVisitor.visitInsn(LSHL);
methodVisitor.visitInsn(LOR);
methodVisitor.visitVarInsn(LSTORE, 2);
methodVisitor.visitVarInsn(LLOAD, 2);
methodVisitor.visitInsn(LRETURN);
methodVisitor.visitMaxs(6, 4);
methodVisitor.visitEnd();
}
{
methodVisitor = classWriter.visitMethod(ACC_PUBLIC | ACC_STATIC, "I2OSP", "(I)[B", null, null);
methodVisitor.visitCode();
methodVisitor.visitInsn(ICONST_4);
methodVisitor.visitIntInsn(NEWARRAY, T_BYTE);
methodVisitor.visitVarInsn(ASTORE, 1);
methodVisitor.visitVarInsn(ALOAD, 1);
methodVisitor.visitInsn(ICONST_0);
methodVisitor.visitVarInsn(ILOAD, 0);
methodVisitor.visitInsn(I2B);
methodVisitor.visitInsn(BASTORE);
methodVisitor.visitVarInsn(ALOAD, 1);
methodVisitor.visitInsn(ICONST_1);
methodVisitor.visitVarInsn(ILOAD, 0);
methodVisitor.visitIntInsn(BIPUSH, 8);
methodVisitor.visitInsn(IUSHR);
methodVisitor.visitInsn(I2B);
methodVisitor.visitInsn(BASTORE);
methodVisitor.visitVarInsn(ALOAD, 1);
methodVisitor.visitInsn(ICONST_2);
methodVisitor.visitVarInsn(ILOAD, 0);
methodVisitor.visitIntInsn(BIPUSH, 16);
methodVisitor.visitInsn(IUSHR);
methodVisitor.visitInsn(I2B);
methodVisitor.visitInsn(BASTORE);
methodVisitor.visitVarInsn(ALOAD, 1);
methodVisitor.visitInsn(ICONST_3);
methodVisitor.visitVarInsn(ILOAD, 0);
methodVisitor.visitIntInsn(BIPUSH, 24);
methodVisitor.visitInsn(IUSHR);
methodVisitor.visitInsn(I2B);
methodVisitor.visitInsn(BASTORE);
methodVisitor.visitVarInsn(ALOAD, 1);
methodVisitor.visitInsn(ARETURN);
methodVisitor.visitMaxs(4, 2);
methodVisitor.visitEnd();
}
{
methodVisitor = classWriter.visitMethod(ACC_PUBLIC | ACC_STATIC, "I2OSP", "(I[BI)V", null, null);
methodVisitor.visitCode();
methodVisitor.visitVarInsn(ALOAD, 1);
methodVisitor.visitVarInsn(ILOAD, 2);
methodVisitor.visitIincInsn(2, 1);
methodVisitor.visitVarInsn(ILOAD, 0);
methodVisitor.visitInsn(I2B);
methodVisitor.visitInsn(BASTORE);
methodVisitor.visitVarInsn(ALOAD, 1);
methodVisitor.visitVarInsn(ILOAD, 2);
methodVisitor.visitIincInsn(2, 1);
methodVisitor.visitVarInsn(ILOAD, 0);
methodVisitor.visitIntInsn(BIPUSH, 8);
methodVisitor.visitInsn(IUSHR);
methodVisitor.visitInsn(I2B);
methodVisitor.visitInsn(BASTORE);
methodVisitor.visitVarInsn(ALOAD, 1);
methodVisitor.visitVarInsn(ILOAD, 2);
methodVisitor.visitIincInsn(2, 1);
methodVisitor.visitVarInsn(ILOAD, 0);
methodVisitor.visitIntInsn(BIPUSH, 16);
methodVisitor.visitInsn(IUSHR);
methodVisitor.visitInsn(I2B);
methodVisitor.visitInsn(BASTORE);
methodVisitor.visitVarInsn(ALOAD, 1);
methodVisitor.visitVarInsn(ILOAD, 2);
methodVisitor.visitIincInsn(2, 1);
methodVisitor.visitVarInsn(ILOAD, 0);
methodVisitor.visitIntInsn(BIPUSH, 24);
methodVisitor.visitInsn(IUSHR);
methodVisitor.visitInsn(I2B);
methodVisitor.visitInsn(BASTORE);
methodVisitor.visitInsn(RETURN);
methodVisitor.visitMaxs(4, 3);
methodVisitor.visitEnd();
}
{
methodVisitor = classWriter.visitMethod(ACC_PUBLIC | ACC_STATIC, "I2OSP", "(I[BII)V", null, null);
methodVisitor.visitCode();
methodVisitor.visitVarInsn(ILOAD, 3);
methodVisitor.visitInsn(ICONST_1);
methodVisitor.visitInsn(ISUB);
methodVisitor.visitVarInsn(ISTORE, 4);
Label label0 = new Label();
methodVisitor.visitLabel(label0);
methodVisitor.visitVarInsn(ILOAD, 4);
Label label1 = new Label();
methodVisitor.visitJumpInsn(IFLT, label1);
methodVisitor.visitVarInsn(ALOAD, 1);
methodVisitor.visitVarInsn(ILOAD, 2);
methodVisitor.visitVarInsn(ILOAD, 4);
methodVisitor.visitInsn(IADD);
methodVisitor.visitVarInsn(ILOAD, 0);
methodVisitor.visitIntInsn(BIPUSH, 8);
methodVisitor.visitVarInsn(ILOAD, 4);
methodVisitor.visitInsn(IMUL);
methodVisitor.visitInsn(IUSHR);
methodVisitor.visitInsn(I2B);
methodVisitor.visitInsn(BASTORE);
methodVisitor.visitIincInsn(4, -1);
methodVisitor.visitJumpInsn(GOTO, label0);
methodVisitor.visitLabel(label1);
methodVisitor.visitInsn(RETURN);
methodVisitor.visitMaxs(5, 5);
methodVisitor.visitEnd();
}
{
methodVisitor = classWriter.visitMethod(ACC_PUBLIC | ACC_STATIC, "I2OSP", "(J)[B", null, null);
methodVisitor.visitCode();
methodVisitor.visitIntInsn(BIPUSH, 8);
methodVisitor.visitIntInsn(NEWARRAY, T_BYTE);
methodVisitor.visitVarInsn(ASTORE, 2);
methodVisitor.visitVarInsn(ALOAD, 2);
methodVisitor.visitInsn(ICONST_0);
methodVisitor.visitVarInsn(LLOAD, 0);
methodVisitor.visitInsn(L2I);
methodVisitor.visitInsn(I2B);
methodVisitor.visitInsn(BASTORE);
methodVisitor.visitVarInsn(ALOAD, 2);
methodVisitor.visitInsn(ICONST_1);
methodVisitor.visitVarInsn(LLOAD, 0);
methodVisitor.visitIntInsn(BIPUSH, 8);
methodVisitor.visitInsn(LUSHR);
methodVisitor.visitInsn(L2I);
methodVisitor.visitInsn(I2B);
methodVisitor.visitInsn(BASTORE);
methodVisitor.visitVarInsn(ALOAD, 2);
methodVisitor.visitInsn(ICONST_2);
methodVisitor.visitVarInsn(LLOAD, 0);
methodVisitor.visitIntInsn(BIPUSH, 16);
methodVisitor.visitInsn(LUSHR);
methodVisitor.visitInsn(L2I);
methodVisitor.visitInsn(I2B);
methodVisitor.visitInsn(BASTORE);
methodVisitor.visitVarInsn(ALOAD, 2);
methodVisitor.visitInsn(ICONST_3);
methodVisitor.visitVarInsn(LLOAD, 0);
methodVisitor.visitIntInsn(BIPUSH, 24);
methodVisitor.visitInsn(LUSHR);
methodVisitor.visitInsn(L2I);
methodVisitor.visitInsn(I2B);
methodVisitor.visitInsn(BASTORE);
methodVisitor.visitVarInsn(ALOAD, 2);
methodVisitor.visitInsn(ICONST_4);
methodVisitor.visitVarInsn(LLOAD, 0);
methodVisitor.visitIntInsn(BIPUSH, 32);
methodVisitor.visitInsn(LUSHR);
methodVisitor.visitInsn(L2I);
methodVisitor.visitInsn(I2B);
methodVisitor.visitInsn(BASTORE);
methodVisitor.visitVarInsn(ALOAD, 2);
methodVisitor.visitInsn(ICONST_5);
methodVisitor.visitVarInsn(LLOAD, 0);
methodVisitor.visitIntInsn(BIPUSH, 40);
methodVisitor.visitInsn(LUSHR);
methodVisitor.visitInsn(L2I);
methodVisitor.visitInsn(I2B);
methodVisitor.visitInsn(BASTORE);
methodVisitor.visitVarInsn(ALOAD, 2);
methodVisitor.visitIntInsn(BIPUSH, 6);
methodVisitor.visitVarInsn(LLOAD, 0);
methodVisitor.visitIntInsn(BIPUSH, 48);
methodVisitor.visitInsn(LUSHR);
methodVisitor.visitInsn(L2I);
methodVisitor.visitInsn(I2B);
methodVisitor.visitInsn(BASTORE);
methodVisitor.visitVarInsn(ALOAD, 2);
methodVisitor.visitIntInsn(BIPUSH, 7);
methodVisitor.visitVarInsn(LLOAD, 0);
methodVisitor.visitIntInsn(BIPUSH, 56);
methodVisitor.visitInsn(LUSHR);
methodVisitor.visitInsn(L2I);
methodVisitor.visitInsn(I2B);
methodVisitor.visitInsn(BASTORE);
methodVisitor.visitVarInsn(ALOAD, 2);
methodVisitor.visitInsn(ARETURN);
methodVisitor.visitMaxs(5, 3);
methodVisitor.visitEnd();
}
{
methodVisitor = classWriter.visitMethod(ACC_PUBLIC | ACC_STATIC, "I2OSP", "(J[BI)V", null, null);
methodVisitor.visitCode();
methodVisitor.visitVarInsn(ALOAD, 2);
methodVisitor.visitVarInsn(ILOAD, 3);
methodVisitor.visitIincInsn(3, 1);
methodVisitor.visitVarInsn(LLOAD, 0);
methodVisitor.visitInsn(L2I);
methodVisitor.visitInsn(I2B);
methodVisitor.visitInsn(BASTORE);
methodVisitor.visitVarInsn(ALOAD, 2);
methodVisitor.visitVarInsn(ILOAD, 3);
methodVisitor.visitIincInsn(3, 1);
methodVisitor.visitVarInsn(LLOAD, 0);
methodVisitor.visitIntInsn(BIPUSH, 8);
methodVisitor.visitInsn(LUSHR);
methodVisitor.visitInsn(L2I);
methodVisitor.visitInsn(I2B);
methodVisitor.visitInsn(BASTORE);
methodVisitor.visitVarInsn(ALOAD, 2);
methodVisitor.visitVarInsn(ILOAD, 3);
methodVisitor.visitIincInsn(3, 1);
methodVisitor.visitVarInsn(LLOAD, 0);
methodVisitor.visitIntInsn(BIPUSH, 16);
methodVisitor.visitInsn(LUSHR);
methodVisitor.visitInsn(L2I);
methodVisitor.visitInsn(I2B);
methodVisitor.visitInsn(BASTORE);
methodVisitor.visitVarInsn(ALOAD, 2);
methodVisitor.visitVarInsn(ILOAD, 3);
methodVisitor.visitIincInsn(3, 1);
methodVisitor.visitVarInsn(LLOAD, 0);
methodVisitor.visitIntInsn(BIPUSH, 24);
methodVisitor.visitInsn(LUSHR);
methodVisitor.visitInsn(L2I);
methodVisitor.visitInsn(I2B);
methodVisitor.visitInsn(BASTORE);
methodVisitor.visitVarInsn(ALOAD, 2);
methodVisitor.visitVarInsn(ILOAD, 3);
methodVisitor.visitIincInsn(3, 1);
methodVisitor.visitVarInsn(LLOAD, 0);
methodVisitor.visitIntInsn(BIPUSH, 32);
methodVisitor.visitInsn(LUSHR);
methodVisitor.visitInsn(L2I);
methodVisitor.visitInsn(I2B);
methodVisitor.visitInsn(BASTORE);
methodVisitor.visitVarInsn(ALOAD, 2);
methodVisitor.visitVarInsn(ILOAD, 3);
methodVisitor.visitIincInsn(3, 1);
methodVisitor.visitVarInsn(LLOAD, 0);
methodVisitor.visitIntInsn(BIPUSH, 40);
methodVisitor.visitInsn(LUSHR);
methodVisitor.visitInsn(L2I);
methodVisitor.visitInsn(I2B);
methodVisitor.visitInsn(BASTORE);
methodVisitor.visitVarInsn(ALOAD, 2);
methodVisitor.visitVarInsn(ILOAD, 3);
methodVisitor.visitIincInsn(3, 1);
methodVisitor.visitVarInsn(LLOAD, 0);
methodVisitor.visitIntInsn(BIPUSH, 48);
methodVisitor.visitInsn(LUSHR);
methodVisitor.visitInsn(L2I);
methodVisitor.visitInsn(I2B);
methodVisitor.visitInsn(BASTORE);
methodVisitor.visitVarInsn(ALOAD, 2);
methodVisitor.visitVarInsn(ILOAD, 3);
methodVisitor.visitVarInsn(LLOAD, 0);
methodVisitor.visitIntInsn(BIPUSH, 56);
methodVisitor.visitInsn(LUSHR);
methodVisitor.visitInsn(L2I);
methodVisitor.visitInsn(I2B);
methodVisitor.visitInsn(BASTORE);
methodVisitor.visitInsn(RETURN);
methodVisitor.visitMaxs(5, 4);
methodVisitor.visitEnd();
}
{
methodVisitor = classWriter.visitMethod(ACC_PUBLIC | ACC_STATIC, "toByteArray", "([II)[B", null, null);
methodVisitor.visitCode();
methodVisitor.visitVarInsn(ALOAD, 0);
methodVisitor.visitInsn(ARRAYLENGTH);
methodVisitor.visitVarInsn(ISTORE, 2);
methodVisitor.visitVarInsn(ILOAD, 1);
methodVisitor.visitIntInsn(NEWARRAY, T_BYTE);
methodVisitor.visitVarInsn(ASTORE, 3);
methodVisitor.visitInsn(ICONST_0);
methodVisitor.visitVarInsn(ISTORE, 4);
methodVisitor.visitInsn(ICONST_0);
methodVisitor.visitVarInsn(ISTORE, 5);
Label label0 = new Label();
methodVisitor.visitLabel(label0);
methodVisitor.visitVarInsn(ILOAD, 5);
methodVisitor.visitVarInsn(ILOAD, 2);
methodVisitor.visitInsn(ICONST_2);
methodVisitor.visitInsn(ISUB);
Label label1 = new Label();
methodVisitor.visitJumpInsn(IF_ICMPGT, label1);
methodVisitor.visitVarInsn(ALOAD, 0);
methodVisitor.visitVarInsn(ILOAD, 5);
methodVisitor.visitInsn(IALOAD);
methodVisitor.visitVarInsn(ALOAD, 3);
methodVisitor.visitVarInsn(ILOAD, 4);
methodVisitor.visitMethodInsn(INVOKESTATIC, "org/bouncycastle/pqc/math/linearalgebra/LittleEndianConversions", "I2OSP", "(I[BI)V", false);
methodVisitor.visitIincInsn(5, 1);
methodVisitor.visitIincInsn(4, 4);
methodVisitor.visitJumpInsn(GOTO, label0);
methodVisitor.visitLabel(label1);
methodVisitor.visitVarInsn(ALOAD, 0);
methodVisitor.visitVarInsn(ILOAD, 2);
methodVisitor.visitInsn(ICONST_1);
methodVisitor.visitInsn(ISUB);
methodVisitor.visitInsn(IALOAD);
methodVisitor.visitVarInsn(ALOAD, 3);
methodVisitor.visitVarInsn(ILOAD, 4);
methodVisitor.visitVarInsn(ILOAD, 1);
methodVisitor.visitVarInsn(ILOAD, 4);
methodVisitor.visitInsn(ISUB);
methodVisitor.visitMethodInsn(INVOKESTATIC, "org/bouncycastle/pqc/math/linearalgebra/LittleEndianConversions", "I2OSP", "(I[BII)V", false);
methodVisitor.visitVarInsn(ALOAD, 3);
methodVisitor.visitInsn(ARETURN);
methodVisitor.visitMaxs(5, 6);
methodVisitor.visitEnd();
}
{
methodVisitor = classWriter.visitMethod(ACC_PUBLIC | ACC_STATIC, "toIntArray", "([B)[I", null, null);
methodVisitor.visitCode();
methodVisitor.visitVarInsn(ALOAD, 0);
methodVisitor.visitInsn(ARRAYLENGTH);
methodVisitor.visitInsn(ICONST_3);
methodVisitor.visitInsn(IADD);
methodVisitor.visitInsn(ICONST_4);
methodVisitor.visitInsn(IDIV);
methodVisitor.visitVarInsn(ISTORE, 1);
methodVisitor.visitVarInsn(ALOAD, 0);
methodVisitor.visitInsn(ARRAYLENGTH);
methodVisitor.visitInsn(ICONST_3);
methodVisitor.visitInsn(IAND);
methodVisitor.visitVarInsn(ISTORE, 2);
methodVisitor.visitVarInsn(ILOAD, 1);
methodVisitor.visitIntInsn(NEWARRAY, T_INT);
methodVisitor.visitVarInsn(ASTORE, 3);
methodVisitor.visitInsn(ICONST_0);
methodVisitor.visitVarInsn(ISTORE, 4);
methodVisitor.visitInsn(ICONST_0);
methodVisitor.visitVarInsn(ISTORE, 5);
Label label0 = new Label();
methodVisitor.visitLabel(label0);
methodVisitor.visitVarInsn(ILOAD, 5);
methodVisitor.visitVarInsn(ILOAD, 1);
methodVisitor.visitInsn(ICONST_2);
methodVisitor.visitInsn(ISUB);
Label label1 = new Label();
methodVisitor.visitJumpInsn(IF_ICMPGT, label1);
methodVisitor.visitVarInsn(ALOAD, 3);
methodVisitor.visitVarInsn(ILOAD, 5);
methodVisitor.visitVarInsn(ALOAD, 0);
methodVisitor.visitVarInsn(ILOAD, 4);
methodVisitor.visitMethodInsn(INVOKESTATIC, "org/bouncycastle/pqc/math/linearalgebra/LittleEndianConversions", "OS2IP", "([BI)I", false);
methodVisitor.visitInsn(IASTORE);
methodVisitor.visitIincInsn(5, 1);
methodVisitor.visitIincInsn(4, 4);
methodVisitor.visitJumpInsn(GOTO, label0);
methodVisitor.visitLabel(label1);
methodVisitor.visitVarInsn(ILOAD, 2);
Label label2 = new Label();
methodVisitor.visitJumpInsn(IFEQ, label2);
methodVisitor.visitVarInsn(ALOAD, 3);
methodVisitor.visitVarInsn(ILOAD, 1);
methodVisitor.visitInsn(ICONST_1);
methodVisitor.visitInsn(ISUB);
methodVisitor.visitVarInsn(ALOAD, 0);
methodVisitor.visitVarInsn(ILOAD, 4);
methodVisitor.visitVarInsn(ILOAD, 2);
methodVisitor.visitMethodInsn(INVOKESTATIC, "org/bouncycastle/pqc/math/linearalgebra/LittleEndianConversions", "OS2IP", "([BII)I", false);
methodVisitor.visitInsn(IASTORE);
Label label3 = new Label();
methodVisitor.visitJumpInsn(GOTO, label3);
methodVisitor.visitLabel(label2);
methodVisitor.visitVarInsn(ALOAD, 3);
methodVisitor.visitVarInsn(ILOAD, 1);
methodVisitor.visitInsn(ICONST_1);
methodVisitor.visitInsn(ISUB);
methodVisitor.visitVarInsn(ALOAD, 0);
methodVisitor.visitVarInsn(ILOAD, 4);
methodVisitor.visitMethodInsn(INVOKESTATIC, "org/bouncycastle/pqc/math/linearalgebra/LittleEndianConversions", "OS2IP", "([BI)I", false);
methodVisitor.visitInsn(IASTORE);
methodVisitor.visitLabel(label3);
methodVisitor.visitVarInsn(ALOAD, 3);
methodVisitor.visitInsn(ARETURN);
methodVisitor.visitMaxs(5, 6);
methodVisitor.visitEnd();
}
classWriter.visitEnd();

return classWriter.toByteArray();
}
}
