package asm.org.bouncycastle.asn1.x509;
import org.objectweb.asm.AnnotationVisitor;
import org.objectweb.asm.Attribute;
import org.objectweb.asm.ClassReader;
import org.objectweb.asm.ClassWriter;
import org.objectweb.asm.ConstantDynamic;
import org.objectweb.asm.FieldVisitor;
import org.objectweb.asm.Handle;
import org.objectweb.asm.Label;
import org.objectweb.asm.MethodVisitor;
import org.objectweb.asm.Opcodes;
import org.objectweb.asm.RecordComponentVisitor;
import org.objectweb.asm.Type;
import org.objectweb.asm.TypePath;
public class GeneralNameDump implements Opcodes {

public static byte[] dump () throws Exception {

ClassWriter classWriter = new ClassWriter(0);
FieldVisitor fieldVisitor;
RecordComponentVisitor recordComponentVisitor;
MethodVisitor methodVisitor;
AnnotationVisitor annotationVisitor0;

classWriter.visit(V1_5, ACC_PUBLIC | ACC_SUPER, "org/bouncycastle/asn1/x509/GeneralName", null, "org/bouncycastle/asn1/ASN1Object", new String[] { "org/bouncycastle/asn1/ASN1Choice" });

{
fieldVisitor = classWriter.visitField(ACC_PUBLIC | ACC_FINAL | ACC_STATIC, "otherName", "I", null, new Integer(0));
fieldVisitor.visitEnd();
}
{
fieldVisitor = classWriter.visitField(ACC_PUBLIC | ACC_FINAL | ACC_STATIC, "rfc822Name", "I", null, new Integer(1));
fieldVisitor.visitEnd();
}
{
fieldVisitor = classWriter.visitField(ACC_PUBLIC | ACC_FINAL | ACC_STATIC, "dNSName", "I", null, new Integer(2));
fieldVisitor.visitEnd();
}
{
fieldVisitor = classWriter.visitField(ACC_PUBLIC | ACC_FINAL | ACC_STATIC, "x400Address", "I", null, new Integer(3));
fieldVisitor.visitEnd();
}
{
fieldVisitor = classWriter.visitField(ACC_PUBLIC | ACC_FINAL | ACC_STATIC, "directoryName", "I", null, new Integer(4));
fieldVisitor.visitEnd();
}
{
fieldVisitor = classWriter.visitField(ACC_PUBLIC | ACC_FINAL | ACC_STATIC, "ediPartyName", "I", null, new Integer(5));
fieldVisitor.visitEnd();
}
{
fieldVisitor = classWriter.visitField(ACC_PUBLIC | ACC_FINAL | ACC_STATIC, "uniformResourceIdentifier", "I", null, new Integer(6));
fieldVisitor.visitEnd();
}
{
fieldVisitor = classWriter.visitField(ACC_PUBLIC | ACC_FINAL | ACC_STATIC, "iPAddress", "I", null, new Integer(7));
fieldVisitor.visitEnd();
}
{
fieldVisitor = classWriter.visitField(ACC_PUBLIC | ACC_FINAL | ACC_STATIC, "registeredID", "I", null, new Integer(8));
fieldVisitor.visitEnd();
}
{
fieldVisitor = classWriter.visitField(ACC_PRIVATE, "obj", "Lorg/bouncycastle/asn1/ASN1Encodable;", null, null);
fieldVisitor.visitEnd();
}
{
fieldVisitor = classWriter.visitField(ACC_PRIVATE, "tag", "I", null, null);
fieldVisitor.visitEnd();
}
{
methodVisitor = classWriter.visitMethod(ACC_PUBLIC | ACC_DEPRECATED, "<init>", "(Lorg/bouncycastle/asn1/x509/X509Name;)V", null, null);
methodVisitor.visitCode();
methodVisitor.visitVarInsn(ALOAD, 0);
methodVisitor.visitMethodInsn(INVOKESPECIAL, "org/bouncycastle/asn1/ASN1Object", "<init>", "()V", false);
methodVisitor.visitVarInsn(ALOAD, 0);
methodVisitor.visitVarInsn(ALOAD, 1);
methodVisitor.visitMethodInsn(INVOKESTATIC, "org/bouncycastle/asn1/x500/X500Name", "getInstance", "(Ljava/lang/Object;)Lorg/bouncycastle/asn1/x500/X500Name;", false);
methodVisitor.visitFieldInsn(PUTFIELD, "org/bouncycastle/asn1/x509/GeneralName", "obj", "Lorg/bouncycastle/asn1/ASN1Encodable;");
methodVisitor.visitVarInsn(ALOAD, 0);
methodVisitor.visitInsn(ICONST_4);
methodVisitor.visitFieldInsn(PUTFIELD, "org/bouncycastle/asn1/x509/GeneralName", "tag", "I");
methodVisitor.visitInsn(RETURN);
methodVisitor.visitMaxs(2, 2);
methodVisitor.visitEnd();
}
{
methodVisitor = classWriter.visitMethod(ACC_PUBLIC, "<init>", "(Lorg/bouncycastle/asn1/x500/X500Name;)V", null, null);
methodVisitor.visitCode();
methodVisitor.visitVarInsn(ALOAD, 0);
methodVisitor.visitMethodInsn(INVOKESPECIAL, "org/bouncycastle/asn1/ASN1Object", "<init>", "()V", false);
methodVisitor.visitVarInsn(ALOAD, 0);
methodVisitor.visitVarInsn(ALOAD, 1);
methodVisitor.visitFieldInsn(PUTFIELD, "org/bouncycastle/asn1/x509/GeneralName", "obj", "Lorg/bouncycastle/asn1/ASN1Encodable;");
methodVisitor.visitVarInsn(ALOAD, 0);
methodVisitor.visitInsn(ICONST_4);
methodVisitor.visitFieldInsn(PUTFIELD, "org/bouncycastle/asn1/x509/GeneralName", "tag", "I");
methodVisitor.visitInsn(RETURN);
methodVisitor.visitMaxs(2, 2);
methodVisitor.visitEnd();
}
{
methodVisitor = classWriter.visitMethod(ACC_PUBLIC, "<init>", "(ILorg/bouncycastle/asn1/ASN1Encodable;)V", null, null);
methodVisitor.visitCode();
methodVisitor.visitVarInsn(ALOAD, 0);
methodVisitor.visitMethodInsn(INVOKESPECIAL, "org/bouncycastle/asn1/ASN1Object", "<init>", "()V", false);
methodVisitor.visitVarInsn(ALOAD, 0);
methodVisitor.visitVarInsn(ALOAD, 2);
methodVisitor.visitFieldInsn(PUTFIELD, "org/bouncycastle/asn1/x509/GeneralName", "obj", "Lorg/bouncycastle/asn1/ASN1Encodable;");
methodVisitor.visitVarInsn(ALOAD, 0);
methodVisitor.visitVarInsn(ILOAD, 1);
methodVisitor.visitFieldInsn(PUTFIELD, "org/bouncycastle/asn1/x509/GeneralName", "tag", "I");
methodVisitor.visitInsn(RETURN);
methodVisitor.visitMaxs(2, 3);
methodVisitor.visitEnd();
}
{
methodVisitor = classWriter.visitMethod(ACC_PUBLIC, "<init>", "(ILjava/lang/String;)V", null, null);
methodVisitor.visitCode();
methodVisitor.visitVarInsn(ALOAD, 0);
methodVisitor.visitMethodInsn(INVOKESPECIAL, "org/bouncycastle/asn1/ASN1Object", "<init>", "()V", false);
methodVisitor.visitVarInsn(ALOAD, 0);
methodVisitor.visitVarInsn(ILOAD, 1);
methodVisitor.visitFieldInsn(PUTFIELD, "org/bouncycastle/asn1/x509/GeneralName", "tag", "I");
methodVisitor.visitVarInsn(ILOAD, 1);
methodVisitor.visitInsn(ICONST_1);
Label label0 = new Label();
methodVisitor.visitJumpInsn(IF_ICMPEQ, label0);
methodVisitor.visitVarInsn(ILOAD, 1);
methodVisitor.visitInsn(ICONST_2);
methodVisitor.visitJumpInsn(IF_ICMPEQ, label0);
methodVisitor.visitVarInsn(ILOAD, 1);
methodVisitor.visitIntInsn(BIPUSH, 6);
Label label1 = new Label();
methodVisitor.visitJumpInsn(IF_ICMPNE, label1);
methodVisitor.visitLabel(label0);
methodVisitor.visitVarInsn(ALOAD, 0);
methodVisitor.visitTypeInsn(NEW, "org/bouncycastle/asn1/DERIA5String");
methodVisitor.visitInsn(DUP);
methodVisitor.visitVarInsn(ALOAD, 2);
methodVisitor.visitMethodInsn(INVOKESPECIAL, "org/bouncycastle/asn1/DERIA5String", "<init>", "(Ljava/lang/String;)V", false);
methodVisitor.visitFieldInsn(PUTFIELD, "org/bouncycastle/asn1/x509/GeneralName", "obj", "Lorg/bouncycastle/asn1/ASN1Encodable;");
Label label2 = new Label();
methodVisitor.visitJumpInsn(GOTO, label2);
methodVisitor.visitLabel(label1);
methodVisitor.visitVarInsn(ILOAD, 1);
methodVisitor.visitIntInsn(BIPUSH, 8);
Label label3 = new Label();
methodVisitor.visitJumpInsn(IF_ICMPNE, label3);
methodVisitor.visitVarInsn(ALOAD, 0);
methodVisitor.visitTypeInsn(NEW, "org/bouncycastle/asn1/ASN1ObjectIdentifier");
methodVisitor.visitInsn(DUP);
methodVisitor.visitVarInsn(ALOAD, 2);
methodVisitor.visitMethodInsn(INVOKESPECIAL, "org/bouncycastle/asn1/ASN1ObjectIdentifier", "<init>", "(Ljava/lang/String;)V", false);
methodVisitor.visitFieldInsn(PUTFIELD, "org/bouncycastle/asn1/x509/GeneralName", "obj", "Lorg/bouncycastle/asn1/ASN1Encodable;");
methodVisitor.visitJumpInsn(GOTO, label2);
methodVisitor.visitLabel(label3);
methodVisitor.visitVarInsn(ILOAD, 1);
methodVisitor.visitInsn(ICONST_4);
Label label4 = new Label();
methodVisitor.visitJumpInsn(IF_ICMPNE, label4);
methodVisitor.visitVarInsn(ALOAD, 0);
methodVisitor.visitTypeInsn(NEW, "org/bouncycastle/asn1/x500/X500Name");
methodVisitor.visitInsn(DUP);
methodVisitor.visitVarInsn(ALOAD, 2);
methodVisitor.visitMethodInsn(INVOKESPECIAL, "org/bouncycastle/asn1/x500/X500Name", "<init>", "(Ljava/lang/String;)V", false);
methodVisitor.visitFieldInsn(PUTFIELD, "org/bouncycastle/asn1/x509/GeneralName", "obj", "Lorg/bouncycastle/asn1/ASN1Encodable;");
methodVisitor.visitJumpInsn(GOTO, label2);
methodVisitor.visitLabel(label4);
methodVisitor.visitVarInsn(ILOAD, 1);
methodVisitor.visitIntInsn(BIPUSH, 7);
Label label5 = new Label();
methodVisitor.visitJumpInsn(IF_ICMPNE, label5);
methodVisitor.visitVarInsn(ALOAD, 0);
methodVisitor.visitVarInsn(ALOAD, 2);
methodVisitor.visitMethodInsn(INVOKESPECIAL, "org/bouncycastle/asn1/x509/GeneralName", "toGeneralNameEncoding", "(Ljava/lang/String;)[B", false);
methodVisitor.visitVarInsn(ASTORE, 3);
methodVisitor.visitVarInsn(ALOAD, 3);
Label label6 = new Label();
methodVisitor.visitJumpInsn(IFNULL, label6);
methodVisitor.visitVarInsn(ALOAD, 0);
methodVisitor.visitTypeInsn(NEW, "org/bouncycastle/asn1/DEROctetString");
methodVisitor.visitInsn(DUP);
methodVisitor.visitVarInsn(ALOAD, 3);
methodVisitor.visitMethodInsn(INVOKESPECIAL, "org/bouncycastle/asn1/DEROctetString", "<init>", "([B)V", false);
methodVisitor.visitFieldInsn(PUTFIELD, "org/bouncycastle/asn1/x509/GeneralName", "obj", "Lorg/bouncycastle/asn1/ASN1Encodable;");
Label label7 = new Label();
methodVisitor.visitJumpInsn(GOTO, label7);
methodVisitor.visitLabel(label6);
methodVisitor.visitTypeInsn(NEW, "java/lang/IllegalArgumentException");
methodVisitor.visitInsn(DUP);
methodVisitor.visitLdcInsn("IP Address is invalid");
methodVisitor.visitMethodInsn(INVOKESPECIAL, "java/lang/IllegalArgumentException", "<init>", "(Ljava/lang/String;)V", false);
methodVisitor.visitInsn(ATHROW);
methodVisitor.visitLabel(label7);
methodVisitor.visitJumpInsn(GOTO, label2);
methodVisitor.visitLabel(label5);
methodVisitor.visitTypeInsn(NEW, "java/lang/IllegalArgumentException");
methodVisitor.visitInsn(DUP);
methodVisitor.visitTypeInsn(NEW, "java/lang/StringBuilder");
methodVisitor.visitInsn(DUP);
methodVisitor.visitMethodInsn(INVOKESPECIAL, "java/lang/StringBuilder", "<init>", "()V", false);
methodVisitor.visitLdcInsn("can't process String for tag: ");
methodVisitor.visitMethodInsn(INVOKEVIRTUAL, "java/lang/StringBuilder", "append", "(Ljava/lang/String;)Ljava/lang/StringBuilder;", false);
methodVisitor.visitVarInsn(ILOAD, 1);
methodVisitor.visitMethodInsn(INVOKEVIRTUAL, "java/lang/StringBuilder", "append", "(I)Ljava/lang/StringBuilder;", false);
methodVisitor.visitMethodInsn(INVOKEVIRTUAL, "java/lang/StringBuilder", "toString", "()Ljava/lang/String;", false);
methodVisitor.visitMethodInsn(INVOKESPECIAL, "java/lang/IllegalArgumentException", "<init>", "(Ljava/lang/String;)V", false);
methodVisitor.visitInsn(ATHROW);
methodVisitor.visitLabel(label2);
methodVisitor.visitInsn(RETURN);
methodVisitor.visitMaxs(4, 4);
methodVisitor.visitEnd();
}
{
methodVisitor = classWriter.visitMethod(ACC_PUBLIC | ACC_STATIC, "getInstance", "(Ljava/lang/Object;)Lorg/bouncycastle/asn1/x509/GeneralName;", null, null);
methodVisitor.visitCode();
Label label0 = new Label();
Label label1 = new Label();
Label label2 = new Label();
methodVisitor.visitTryCatchBlock(label0, label1, label2, "java/io/IOException");
methodVisitor.visitVarInsn(ALOAD, 0);
Label label3 = new Label();
methodVisitor.visitJumpInsn(IFNULL, label3);
methodVisitor.visitVarInsn(ALOAD, 0);
methodVisitor.visitTypeInsn(INSTANCEOF, "org/bouncycastle/asn1/x509/GeneralName");
Label label4 = new Label();
methodVisitor.visitJumpInsn(IFEQ, label4);
methodVisitor.visitLabel(label3);
methodVisitor.visitVarInsn(ALOAD, 0);
methodVisitor.visitTypeInsn(CHECKCAST, "org/bouncycastle/asn1/x509/GeneralName");
methodVisitor.visitInsn(ARETURN);
methodVisitor.visitLabel(label4);
methodVisitor.visitVarInsn(ALOAD, 0);
methodVisitor.visitTypeInsn(INSTANCEOF, "org/bouncycastle/asn1/ASN1TaggedObject");
Label label5 = new Label();
methodVisitor.visitJumpInsn(IFEQ, label5);
methodVisitor.visitVarInsn(ALOAD, 0);
methodVisitor.visitTypeInsn(CHECKCAST, "org/bouncycastle/asn1/ASN1TaggedObject");
methodVisitor.visitVarInsn(ASTORE, 1);
methodVisitor.visitVarInsn(ALOAD, 1);
methodVisitor.visitMethodInsn(INVOKEVIRTUAL, "org/bouncycastle/asn1/ASN1TaggedObject", "getTagNo", "()I", false);
methodVisitor.visitVarInsn(ISTORE, 2);
methodVisitor.visitVarInsn(ILOAD, 2);
Label label6 = new Label();
Label label7 = new Label();
Label label8 = new Label();
Label label9 = new Label();
Label label10 = new Label();
Label label11 = new Label();
methodVisitor.visitTableSwitchInsn(0, 8, label11, new Label[] { label6, label7, label7, label6, label8, label6, label7, label9, label10 });
methodVisitor.visitLabel(label6);
methodVisitor.visitTypeInsn(NEW, "org/bouncycastle/asn1/x509/GeneralName");
methodVisitor.visitInsn(DUP);
methodVisitor.visitVarInsn(ILOAD, 2);
methodVisitor.visitVarInsn(ALOAD, 1);
methodVisitor.visitInsn(ICONST_0);
methodVisitor.visitMethodInsn(INVOKESTATIC, "org/bouncycastle/asn1/ASN1Sequence", "getInstance", "(Lorg/bouncycastle/asn1/ASN1TaggedObject;Z)Lorg/bouncycastle/asn1/ASN1Sequence;", false);
methodVisitor.visitMethodInsn(INVOKESPECIAL, "org/bouncycastle/asn1/x509/GeneralName", "<init>", "(ILorg/bouncycastle/asn1/ASN1Encodable;)V", false);
methodVisitor.visitInsn(ARETURN);
methodVisitor.visitLabel(label7);
methodVisitor.visitTypeInsn(NEW, "org/bouncycastle/asn1/x509/GeneralName");
methodVisitor.visitInsn(DUP);
methodVisitor.visitVarInsn(ILOAD, 2);
methodVisitor.visitVarInsn(ALOAD, 1);
methodVisitor.visitInsn(ICONST_0);
methodVisitor.visitMethodInsn(INVOKESTATIC, "org/bouncycastle/asn1/DERIA5String", "getInstance", "(Lorg/bouncycastle/asn1/ASN1TaggedObject;Z)Lorg/bouncycastle/asn1/DERIA5String;", false);
methodVisitor.visitMethodInsn(INVOKESPECIAL, "org/bouncycastle/asn1/x509/GeneralName", "<init>", "(ILorg/bouncycastle/asn1/ASN1Encodable;)V", false);
methodVisitor.visitInsn(ARETURN);
methodVisitor.visitLabel(label8);
methodVisitor.visitTypeInsn(NEW, "org/bouncycastle/asn1/x509/GeneralName");
methodVisitor.visitInsn(DUP);
methodVisitor.visitVarInsn(ILOAD, 2);
methodVisitor.visitVarInsn(ALOAD, 1);
methodVisitor.visitInsn(ICONST_1);
methodVisitor.visitMethodInsn(INVOKESTATIC, "org/bouncycastle/asn1/x500/X500Name", "getInstance", "(Lorg/bouncycastle/asn1/ASN1TaggedObject;Z)Lorg/bouncycastle/asn1/x500/X500Name;", false);
methodVisitor.visitMethodInsn(INVOKESPECIAL, "org/bouncycastle/asn1/x509/GeneralName", "<init>", "(ILorg/bouncycastle/asn1/ASN1Encodable;)V", false);
methodVisitor.visitInsn(ARETURN);
methodVisitor.visitLabel(label9);
methodVisitor.visitTypeInsn(NEW, "org/bouncycastle/asn1/x509/GeneralName");
methodVisitor.visitInsn(DUP);
methodVisitor.visitVarInsn(ILOAD, 2);
methodVisitor.visitVarInsn(ALOAD, 1);
methodVisitor.visitInsn(ICONST_0);
methodVisitor.visitMethodInsn(INVOKESTATIC, "org/bouncycastle/asn1/ASN1OctetString", "getInstance", "(Lorg/bouncycastle/asn1/ASN1TaggedObject;Z)Lorg/bouncycastle/asn1/ASN1OctetString;", false);
methodVisitor.visitMethodInsn(INVOKESPECIAL, "org/bouncycastle/asn1/x509/GeneralName", "<init>", "(ILorg/bouncycastle/asn1/ASN1Encodable;)V", false);
methodVisitor.visitInsn(ARETURN);
methodVisitor.visitLabel(label10);
methodVisitor.visitTypeInsn(NEW, "org/bouncycastle/asn1/x509/GeneralName");
methodVisitor.visitInsn(DUP);
methodVisitor.visitVarInsn(ILOAD, 2);
methodVisitor.visitVarInsn(ALOAD, 1);
methodVisitor.visitInsn(ICONST_0);
methodVisitor.visitMethodInsn(INVOKESTATIC, "org/bouncycastle/asn1/ASN1ObjectIdentifier", "getInstance", "(Lorg/bouncycastle/asn1/ASN1TaggedObject;Z)Lorg/bouncycastle/asn1/ASN1ObjectIdentifier;", false);
methodVisitor.visitMethodInsn(INVOKESPECIAL, "org/bouncycastle/asn1/x509/GeneralName", "<init>", "(ILorg/bouncycastle/asn1/ASN1Encodable;)V", false);
methodVisitor.visitInsn(ARETURN);
methodVisitor.visitLabel(label11);
methodVisitor.visitTypeInsn(NEW, "java/lang/IllegalArgumentException");
methodVisitor.visitInsn(DUP);
methodVisitor.visitTypeInsn(NEW, "java/lang/StringBuilder");
methodVisitor.visitInsn(DUP);
methodVisitor.visitMethodInsn(INVOKESPECIAL, "java/lang/StringBuilder", "<init>", "()V", false);
methodVisitor.visitLdcInsn("unknown tag: ");
methodVisitor.visitMethodInsn(INVOKEVIRTUAL, "java/lang/StringBuilder", "append", "(Ljava/lang/String;)Ljava/lang/StringBuilder;", false);
methodVisitor.visitVarInsn(ILOAD, 2);
methodVisitor.visitMethodInsn(INVOKEVIRTUAL, "java/lang/StringBuilder", "append", "(I)Ljava/lang/StringBuilder;", false);
methodVisitor.visitMethodInsn(INVOKEVIRTUAL, "java/lang/StringBuilder", "toString", "()Ljava/lang/String;", false);
methodVisitor.visitMethodInsn(INVOKESPECIAL, "java/lang/IllegalArgumentException", "<init>", "(Ljava/lang/String;)V", false);
methodVisitor.visitInsn(ATHROW);
methodVisitor.visitLabel(label5);
methodVisitor.visitVarInsn(ALOAD, 0);
methodVisitor.visitTypeInsn(INSTANCEOF, "[B");
Label label12 = new Label();
methodVisitor.visitJumpInsn(IFEQ, label12);
methodVisitor.visitLabel(label0);
methodVisitor.visitVarInsn(ALOAD, 0);
methodVisitor.visitTypeInsn(CHECKCAST, "[B");
methodVisitor.visitTypeInsn(CHECKCAST, "[B");
methodVisitor.visitMethodInsn(INVOKESTATIC, "org/bouncycastle/asn1/ASN1Primitive", "fromByteArray", "([B)Lorg/bouncycastle/asn1/ASN1Primitive;", false);
methodVisitor.visitMethodInsn(INVOKESTATIC, "org/bouncycastle/asn1/x509/GeneralName", "getInstance", "(Ljava/lang/Object;)Lorg/bouncycastle/asn1/x509/GeneralName;", false);
methodVisitor.visitLabel(label1);
methodVisitor.visitInsn(ARETURN);
methodVisitor.visitLabel(label2);
methodVisitor.visitVarInsn(ASTORE, 1);
methodVisitor.visitTypeInsn(NEW, "java/lang/IllegalArgumentException");
methodVisitor.visitInsn(DUP);
methodVisitor.visitLdcInsn("unable to parse encoded general name");
methodVisitor.visitMethodInsn(INVOKESPECIAL, "java/lang/IllegalArgumentException", "<init>", "(Ljava/lang/String;)V", false);
methodVisitor.visitInsn(ATHROW);
methodVisitor.visitLabel(label12);
methodVisitor.visitTypeInsn(NEW, "java/lang/IllegalArgumentException");
methodVisitor.visitInsn(DUP);
methodVisitor.visitTypeInsn(NEW, "java/lang/StringBuilder");
methodVisitor.visitInsn(DUP);
methodVisitor.visitMethodInsn(INVOKESPECIAL, "java/lang/StringBuilder", "<init>", "()V", false);
methodVisitor.visitLdcInsn("unknown object in getInstance: ");
methodVisitor.visitMethodInsn(INVOKEVIRTUAL, "java/lang/StringBuilder", "append", "(Ljava/lang/String;)Ljava/lang/StringBuilder;", false);
methodVisitor.visitVarInsn(ALOAD, 0);
methodVisitor.visitMethodInsn(INVOKEVIRTUAL, "java/lang/Object", "getClass", "()Ljava/lang/Class;", false);
methodVisitor.visitMethodInsn(INVOKEVIRTUAL, "java/lang/Class", "getName", "()Ljava/lang/String;", false);
methodVisitor.visitMethodInsn(INVOKEVIRTUAL, "java/lang/StringBuilder", "append", "(Ljava/lang/String;)Ljava/lang/StringBuilder;", false);
methodVisitor.visitMethodInsn(INVOKEVIRTUAL, "java/lang/StringBuilder", "toString", "()Ljava/lang/String;", false);
methodVisitor.visitMethodInsn(INVOKESPECIAL, "java/lang/IllegalArgumentException", "<init>", "(Ljava/lang/String;)V", false);
methodVisitor.visitInsn(ATHROW);
methodVisitor.visitMaxs(5, 3);
methodVisitor.visitEnd();
}
{
methodVisitor = classWriter.visitMethod(ACC_PUBLIC | ACC_STATIC, "getInstance", "(Lorg/bouncycastle/asn1/ASN1TaggedObject;Z)Lorg/bouncycastle/asn1/x509/GeneralName;", null, null);
methodVisitor.visitCode();
methodVisitor.visitVarInsn(ALOAD, 0);
methodVisitor.visitInsn(ICONST_1);
methodVisitor.visitMethodInsn(INVOKESTATIC, "org/bouncycastle/asn1/ASN1TaggedObject", "getInstance", "(Lorg/bouncycastle/asn1/ASN1TaggedObject;Z)Lorg/bouncycastle/asn1/ASN1TaggedObject;", false);
methodVisitor.visitMethodInsn(INVOKESTATIC, "org/bouncycastle/asn1/x509/GeneralName", "getInstance", "(Ljava/lang/Object;)Lorg/bouncycastle/asn1/x509/GeneralName;", false);
methodVisitor.visitInsn(ARETURN);
methodVisitor.visitMaxs(2, 2);
methodVisitor.visitEnd();
}
{
methodVisitor = classWriter.visitMethod(ACC_PUBLIC, "getTagNo", "()I", null, null);
methodVisitor.visitCode();
methodVisitor.visitVarInsn(ALOAD, 0);
methodVisitor.visitFieldInsn(GETFIELD, "org/bouncycastle/asn1/x509/GeneralName", "tag", "I");
methodVisitor.visitInsn(IRETURN);
methodVisitor.visitMaxs(1, 1);
methodVisitor.visitEnd();
}
{
methodVisitor = classWriter.visitMethod(ACC_PUBLIC, "getName", "()Lorg/bouncycastle/asn1/ASN1Encodable;", null, null);
methodVisitor.visitCode();
methodVisitor.visitVarInsn(ALOAD, 0);
methodVisitor.visitFieldInsn(GETFIELD, "org/bouncycastle/asn1/x509/GeneralName", "obj", "Lorg/bouncycastle/asn1/ASN1Encodable;");
methodVisitor.visitInsn(ARETURN);
methodVisitor.visitMaxs(1, 1);
methodVisitor.visitEnd();
}
{
methodVisitor = classWriter.visitMethod(ACC_PUBLIC, "toString", "()Ljava/lang/String;", null, null);
methodVisitor.visitCode();
methodVisitor.visitTypeInsn(NEW, "java/lang/StringBuffer");
methodVisitor.visitInsn(DUP);
methodVisitor.visitMethodInsn(INVOKESPECIAL, "java/lang/StringBuffer", "<init>", "()V", false);
methodVisitor.visitVarInsn(ASTORE, 1);
methodVisitor.visitVarInsn(ALOAD, 1);
methodVisitor.visitVarInsn(ALOAD, 0);
methodVisitor.visitFieldInsn(GETFIELD, "org/bouncycastle/asn1/x509/GeneralName", "tag", "I");
methodVisitor.visitMethodInsn(INVOKEVIRTUAL, "java/lang/StringBuffer", "append", "(I)Ljava/lang/StringBuffer;", false);
methodVisitor.visitInsn(POP);
methodVisitor.visitVarInsn(ALOAD, 1);
methodVisitor.visitLdcInsn(": ");
methodVisitor.visitMethodInsn(INVOKEVIRTUAL, "java/lang/StringBuffer", "append", "(Ljava/lang/String;)Ljava/lang/StringBuffer;", false);
methodVisitor.visitInsn(POP);
methodVisitor.visitVarInsn(ALOAD, 0);
methodVisitor.visitFieldInsn(GETFIELD, "org/bouncycastle/asn1/x509/GeneralName", "tag", "I");
Label label0 = new Label();
Label label1 = new Label();
Label label2 = new Label();
methodVisitor.visitTableSwitchInsn(1, 6, label1, new Label[] { label0, label0, label1, label2, label1, label0 });
methodVisitor.visitLabel(label0);
methodVisitor.visitVarInsn(ALOAD, 1);
methodVisitor.visitVarInsn(ALOAD, 0);
methodVisitor.visitFieldInsn(GETFIELD, "org/bouncycastle/asn1/x509/GeneralName", "obj", "Lorg/bouncycastle/asn1/ASN1Encodable;");
methodVisitor.visitMethodInsn(INVOKESTATIC, "org/bouncycastle/asn1/DERIA5String", "getInstance", "(Ljava/lang/Object;)Lorg/bouncycastle/asn1/DERIA5String;", false);
methodVisitor.visitMethodInsn(INVOKEVIRTUAL, "org/bouncycastle/asn1/DERIA5String", "getString", "()Ljava/lang/String;", false);
methodVisitor.visitMethodInsn(INVOKEVIRTUAL, "java/lang/StringBuffer", "append", "(Ljava/lang/String;)Ljava/lang/StringBuffer;", false);
methodVisitor.visitInsn(POP);
Label label3 = new Label();
methodVisitor.visitJumpInsn(GOTO, label3);
methodVisitor.visitLabel(label2);
methodVisitor.visitVarInsn(ALOAD, 1);
methodVisitor.visitVarInsn(ALOAD, 0);
methodVisitor.visitFieldInsn(GETFIELD, "org/bouncycastle/asn1/x509/GeneralName", "obj", "Lorg/bouncycastle/asn1/ASN1Encodable;");
methodVisitor.visitMethodInsn(INVOKESTATIC, "org/bouncycastle/asn1/x500/X500Name", "getInstance", "(Ljava/lang/Object;)Lorg/bouncycastle/asn1/x500/X500Name;", false);
methodVisitor.visitMethodInsn(INVOKEVIRTUAL, "org/bouncycastle/asn1/x500/X500Name", "toString", "()Ljava/lang/String;", false);
methodVisitor.visitMethodInsn(INVOKEVIRTUAL, "java/lang/StringBuffer", "append", "(Ljava/lang/String;)Ljava/lang/StringBuffer;", false);
methodVisitor.visitInsn(POP);
methodVisitor.visitJumpInsn(GOTO, label3);
methodVisitor.visitLabel(label1);
methodVisitor.visitVarInsn(ALOAD, 1);
methodVisitor.visitVarInsn(ALOAD, 0);
methodVisitor.visitFieldInsn(GETFIELD, "org/bouncycastle/asn1/x509/GeneralName", "obj", "Lorg/bouncycastle/asn1/ASN1Encodable;");
methodVisitor.visitMethodInsn(INVOKEVIRTUAL, "java/lang/Object", "toString", "()Ljava/lang/String;", false);
methodVisitor.visitMethodInsn(INVOKEVIRTUAL, "java/lang/StringBuffer", "append", "(Ljava/lang/String;)Ljava/lang/StringBuffer;", false);
methodVisitor.visitInsn(POP);
methodVisitor.visitLabel(label3);
methodVisitor.visitVarInsn(ALOAD, 1);
methodVisitor.visitMethodInsn(INVOKEVIRTUAL, "java/lang/StringBuffer", "toString", "()Ljava/lang/String;", false);
methodVisitor.visitInsn(ARETURN);
methodVisitor.visitMaxs(2, 2);
methodVisitor.visitEnd();
}
{
methodVisitor = classWriter.visitMethod(ACC_PRIVATE, "toGeneralNameEncoding", "(Ljava/lang/String;)[B", null, null);
methodVisitor.visitCode();
methodVisitor.visitVarInsn(ALOAD, 1);
methodVisitor.visitMethodInsn(INVOKESTATIC, "org/bouncycastle/util/IPAddress", "isValidIPv6WithNetmask", "(Ljava/lang/String;)Z", false);
Label label0 = new Label();
methodVisitor.visitJumpInsn(IFNE, label0);
methodVisitor.visitVarInsn(ALOAD, 1);
methodVisitor.visitMethodInsn(INVOKESTATIC, "org/bouncycastle/util/IPAddress", "isValidIPv6", "(Ljava/lang/String;)Z", false);
Label label1 = new Label();
methodVisitor.visitJumpInsn(IFEQ, label1);
methodVisitor.visitLabel(label0);
methodVisitor.visitVarInsn(ALOAD, 1);
methodVisitor.visitIntInsn(BIPUSH, 47);
methodVisitor.visitMethodInsn(INVOKEVIRTUAL, "java/lang/String", "indexOf", "(I)I", false);
methodVisitor.visitVarInsn(ISTORE, 2);
methodVisitor.visitVarInsn(ILOAD, 2);
Label label2 = new Label();
methodVisitor.visitJumpInsn(IFGE, label2);
methodVisitor.visitIntInsn(BIPUSH, 16);
methodVisitor.visitIntInsn(NEWARRAY, T_BYTE);
methodVisitor.visitVarInsn(ASTORE, 3);
methodVisitor.visitVarInsn(ALOAD, 0);
methodVisitor.visitVarInsn(ALOAD, 1);
methodVisitor.visitMethodInsn(INVOKESPECIAL, "org/bouncycastle/asn1/x509/GeneralName", "parseIPv6", "(Ljava/lang/String;)[I", false);
methodVisitor.visitVarInsn(ASTORE, 4);
methodVisitor.visitVarInsn(ALOAD, 0);
methodVisitor.visitVarInsn(ALOAD, 4);
methodVisitor.visitVarInsn(ALOAD, 3);
methodVisitor.visitInsn(ICONST_0);
methodVisitor.visitMethodInsn(INVOKESPECIAL, "org/bouncycastle/asn1/x509/GeneralName", "copyInts", "([I[BI)V", false);
methodVisitor.visitVarInsn(ALOAD, 3);
methodVisitor.visitInsn(ARETURN);
methodVisitor.visitLabel(label2);
methodVisitor.visitIntInsn(BIPUSH, 32);
methodVisitor.visitIntInsn(NEWARRAY, T_BYTE);
methodVisitor.visitVarInsn(ASTORE, 3);
methodVisitor.visitVarInsn(ALOAD, 0);
methodVisitor.visitVarInsn(ALOAD, 1);
methodVisitor.visitInsn(ICONST_0);
methodVisitor.visitVarInsn(ILOAD, 2);
methodVisitor.visitMethodInsn(INVOKEVIRTUAL, "java/lang/String", "substring", "(II)Ljava/lang/String;", false);
methodVisitor.visitMethodInsn(INVOKESPECIAL, "org/bouncycastle/asn1/x509/GeneralName", "parseIPv6", "(Ljava/lang/String;)[I", false);
methodVisitor.visitVarInsn(ASTORE, 4);
methodVisitor.visitVarInsn(ALOAD, 0);
methodVisitor.visitVarInsn(ALOAD, 4);
methodVisitor.visitVarInsn(ALOAD, 3);
methodVisitor.visitInsn(ICONST_0);
methodVisitor.visitMethodInsn(INVOKESPECIAL, "org/bouncycastle/asn1/x509/GeneralName", "copyInts", "([I[BI)V", false);
methodVisitor.visitVarInsn(ALOAD, 1);
methodVisitor.visitVarInsn(ILOAD, 2);
methodVisitor.visitInsn(ICONST_1);
methodVisitor.visitInsn(IADD);
methodVisitor.visitMethodInsn(INVOKEVIRTUAL, "java/lang/String", "substring", "(I)Ljava/lang/String;", false);
methodVisitor.visitVarInsn(ASTORE, 5);
methodVisitor.visitVarInsn(ALOAD, 5);
methodVisitor.visitIntInsn(BIPUSH, 58);
methodVisitor.visitMethodInsn(INVOKEVIRTUAL, "java/lang/String", "indexOf", "(I)I", false);
Label label3 = new Label();
methodVisitor.visitJumpInsn(IFLE, label3);
methodVisitor.visitVarInsn(ALOAD, 0);
methodVisitor.visitVarInsn(ALOAD, 5);
methodVisitor.visitMethodInsn(INVOKESPECIAL, "org/bouncycastle/asn1/x509/GeneralName", "parseIPv6", "(Ljava/lang/String;)[I", false);
methodVisitor.visitVarInsn(ASTORE, 4);
Label label4 = new Label();
methodVisitor.visitJumpInsn(GOTO, label4);
methodVisitor.visitLabel(label3);
methodVisitor.visitVarInsn(ALOAD, 0);
methodVisitor.visitVarInsn(ALOAD, 5);
methodVisitor.visitMethodInsn(INVOKESPECIAL, "org/bouncycastle/asn1/x509/GeneralName", "parseMask", "(Ljava/lang/String;)[I", false);
methodVisitor.visitVarInsn(ASTORE, 4);
methodVisitor.visitLabel(label4);
methodVisitor.visitVarInsn(ALOAD, 0);
methodVisitor.visitVarInsn(ALOAD, 4);
methodVisitor.visitVarInsn(ALOAD, 3);
methodVisitor.visitIntInsn(BIPUSH, 16);
methodVisitor.visitMethodInsn(INVOKESPECIAL, "org/bouncycastle/asn1/x509/GeneralName", "copyInts", "([I[BI)V", false);
methodVisitor.visitVarInsn(ALOAD, 3);
methodVisitor.visitInsn(ARETURN);
methodVisitor.visitLabel(label1);
methodVisitor.visitVarInsn(ALOAD, 1);
methodVisitor.visitMethodInsn(INVOKESTATIC, "org/bouncycastle/util/IPAddress", "isValidIPv4WithNetmask", "(Ljava/lang/String;)Z", false);
Label label5 = new Label();
methodVisitor.visitJumpInsn(IFNE, label5);
methodVisitor.visitVarInsn(ALOAD, 1);
methodVisitor.visitMethodInsn(INVOKESTATIC, "org/bouncycastle/util/IPAddress", "isValidIPv4", "(Ljava/lang/String;)Z", false);
Label label6 = new Label();
methodVisitor.visitJumpInsn(IFEQ, label6);
methodVisitor.visitLabel(label5);
methodVisitor.visitVarInsn(ALOAD, 1);
methodVisitor.visitIntInsn(BIPUSH, 47);
methodVisitor.visitMethodInsn(INVOKEVIRTUAL, "java/lang/String", "indexOf", "(I)I", false);
methodVisitor.visitVarInsn(ISTORE, 2);
methodVisitor.visitVarInsn(ILOAD, 2);
Label label7 = new Label();
methodVisitor.visitJumpInsn(IFGE, label7);
methodVisitor.visitInsn(ICONST_4);
methodVisitor.visitIntInsn(NEWARRAY, T_BYTE);
methodVisitor.visitVarInsn(ASTORE, 3);
methodVisitor.visitVarInsn(ALOAD, 0);
methodVisitor.visitVarInsn(ALOAD, 1);
methodVisitor.visitVarInsn(ALOAD, 3);
methodVisitor.visitInsn(ICONST_0);
methodVisitor.visitMethodInsn(INVOKESPECIAL, "org/bouncycastle/asn1/x509/GeneralName", "parseIPv4", "(Ljava/lang/String;[BI)V", false);
methodVisitor.visitVarInsn(ALOAD, 3);
methodVisitor.visitInsn(ARETURN);
methodVisitor.visitLabel(label7);
methodVisitor.visitIntInsn(BIPUSH, 8);
methodVisitor.visitIntInsn(NEWARRAY, T_BYTE);
methodVisitor.visitVarInsn(ASTORE, 3);
methodVisitor.visitVarInsn(ALOAD, 0);
methodVisitor.visitVarInsn(ALOAD, 1);
methodVisitor.visitInsn(ICONST_0);
methodVisitor.visitVarInsn(ILOAD, 2);
methodVisitor.visitMethodInsn(INVOKEVIRTUAL, "java/lang/String", "substring", "(II)Ljava/lang/String;", false);
methodVisitor.visitVarInsn(ALOAD, 3);
methodVisitor.visitInsn(ICONST_0);
methodVisitor.visitMethodInsn(INVOKESPECIAL, "org/bouncycastle/asn1/x509/GeneralName", "parseIPv4", "(Ljava/lang/String;[BI)V", false);
methodVisitor.visitVarInsn(ALOAD, 1);
methodVisitor.visitVarInsn(ILOAD, 2);
methodVisitor.visitInsn(ICONST_1);
methodVisitor.visitInsn(IADD);
methodVisitor.visitMethodInsn(INVOKEVIRTUAL, "java/lang/String", "substring", "(I)Ljava/lang/String;", false);
methodVisitor.visitVarInsn(ASTORE, 4);
methodVisitor.visitVarInsn(ALOAD, 4);
methodVisitor.visitIntInsn(BIPUSH, 46);
methodVisitor.visitMethodInsn(INVOKEVIRTUAL, "java/lang/String", "indexOf", "(I)I", false);
Label label8 = new Label();
methodVisitor.visitJumpInsn(IFLE, label8);
methodVisitor.visitVarInsn(ALOAD, 0);
methodVisitor.visitVarInsn(ALOAD, 4);
methodVisitor.visitVarInsn(ALOAD, 3);
methodVisitor.visitInsn(ICONST_4);
methodVisitor.visitMethodInsn(INVOKESPECIAL, "org/bouncycastle/asn1/x509/GeneralName", "parseIPv4", "(Ljava/lang/String;[BI)V", false);
Label label9 = new Label();
methodVisitor.visitJumpInsn(GOTO, label9);
methodVisitor.visitLabel(label8);
methodVisitor.visitVarInsn(ALOAD, 0);
methodVisitor.visitVarInsn(ALOAD, 4);
methodVisitor.visitVarInsn(ALOAD, 3);
methodVisitor.visitInsn(ICONST_4);
methodVisitor.visitMethodInsn(INVOKESPECIAL, "org/bouncycastle/asn1/x509/GeneralName", "parseIPv4Mask", "(Ljava/lang/String;[BI)V", false);
methodVisitor.visitLabel(label9);
methodVisitor.visitVarInsn(ALOAD, 3);
methodVisitor.visitInsn(ARETURN);
methodVisitor.visitLabel(label6);
methodVisitor.visitInsn(ACONST_NULL);
methodVisitor.visitInsn(ARETURN);
methodVisitor.visitMaxs(4, 6);
methodVisitor.visitEnd();
}
{
methodVisitor = classWriter.visitMethod(ACC_PRIVATE, "parseIPv4Mask", "(Ljava/lang/String;[BI)V", null, null);
methodVisitor.visitCode();
methodVisitor.visitVarInsn(ALOAD, 1);
methodVisitor.visitMethodInsn(INVOKESTATIC, "java/lang/Integer", "parseInt", "(Ljava/lang/String;)I", false);
methodVisitor.visitVarInsn(ISTORE, 4);
methodVisitor.visitInsn(ICONST_0);
methodVisitor.visitVarInsn(ISTORE, 5);
Label label0 = new Label();
methodVisitor.visitLabel(label0);
methodVisitor.visitVarInsn(ILOAD, 5);
methodVisitor.visitVarInsn(ILOAD, 4);
Label label1 = new Label();
methodVisitor.visitJumpInsn(IF_ICMPEQ, label1);
methodVisitor.visitVarInsn(ALOAD, 2);
methodVisitor.visitVarInsn(ILOAD, 5);
methodVisitor.visitIntInsn(BIPUSH, 8);
methodVisitor.visitInsn(IDIV);
methodVisitor.visitVarInsn(ILOAD, 3);
methodVisitor.visitInsn(IADD);
methodVisitor.visitInsn(DUP2);
methodVisitor.visitInsn(BALOAD);
methodVisitor.visitInsn(ICONST_1);
methodVisitor.visitIntInsn(BIPUSH, 7);
methodVisitor.visitVarInsn(ILOAD, 5);
methodVisitor.visitIntInsn(BIPUSH, 8);
methodVisitor.visitInsn(IREM);
methodVisitor.visitInsn(ISUB);
methodVisitor.visitInsn(ISHL);
methodVisitor.visitInsn(IOR);
methodVisitor.visitInsn(I2B);
methodVisitor.visitInsn(BASTORE);
methodVisitor.visitIincInsn(5, 1);
methodVisitor.visitJumpInsn(GOTO, label0);
methodVisitor.visitLabel(label1);
methodVisitor.visitInsn(RETURN);
methodVisitor.visitMaxs(7, 6);
methodVisitor.visitEnd();
}
{
methodVisitor = classWriter.visitMethod(ACC_PRIVATE, "parseIPv4", "(Ljava/lang/String;[BI)V", null, null);
methodVisitor.visitCode();
methodVisitor.visitTypeInsn(NEW, "java/util/StringTokenizer");
methodVisitor.visitInsn(DUP);
methodVisitor.visitVarInsn(ALOAD, 1);
methodVisitor.visitLdcInsn("./");
methodVisitor.visitMethodInsn(INVOKESPECIAL, "java/util/StringTokenizer", "<init>", "(Ljava/lang/String;Ljava/lang/String;)V", false);
methodVisitor.visitVarInsn(ASTORE, 4);
methodVisitor.visitInsn(ICONST_0);
methodVisitor.visitVarInsn(ISTORE, 5);
Label label0 = new Label();
methodVisitor.visitLabel(label0);
methodVisitor.visitVarInsn(ALOAD, 4);
methodVisitor.visitMethodInsn(INVOKEVIRTUAL, "java/util/StringTokenizer", "hasMoreTokens", "()Z", false);
Label label1 = new Label();
methodVisitor.visitJumpInsn(IFEQ, label1);
methodVisitor.visitVarInsn(ALOAD, 2);
methodVisitor.visitVarInsn(ILOAD, 3);
methodVisitor.visitVarInsn(ILOAD, 5);
methodVisitor.visitIincInsn(5, 1);
methodVisitor.visitInsn(IADD);
methodVisitor.visitVarInsn(ALOAD, 4);
methodVisitor.visitMethodInsn(INVOKEVIRTUAL, "java/util/StringTokenizer", "nextToken", "()Ljava/lang/String;", false);
methodVisitor.visitMethodInsn(INVOKESTATIC, "java/lang/Integer", "parseInt", "(Ljava/lang/String;)I", false);
methodVisitor.visitInsn(I2B);
methodVisitor.visitInsn(BASTORE);
methodVisitor.visitJumpInsn(GOTO, label0);
methodVisitor.visitLabel(label1);
methodVisitor.visitInsn(RETURN);
methodVisitor.visitMaxs(4, 6);
methodVisitor.visitEnd();
}
{
methodVisitor = classWriter.visitMethod(ACC_PRIVATE, "parseMask", "(Ljava/lang/String;)[I", null, null);
methodVisitor.visitCode();
methodVisitor.visitIntInsn(BIPUSH, 8);
methodVisitor.visitIntInsn(NEWARRAY, T_INT);
methodVisitor.visitVarInsn(ASTORE, 2);
methodVisitor.visitVarInsn(ALOAD, 1);
methodVisitor.visitMethodInsn(INVOKESTATIC, "java/lang/Integer", "parseInt", "(Ljava/lang/String;)I", false);
methodVisitor.visitVarInsn(ISTORE, 3);
methodVisitor.visitInsn(ICONST_0);
methodVisitor.visitVarInsn(ISTORE, 4);
Label label0 = new Label();
methodVisitor.visitLabel(label0);
methodVisitor.visitVarInsn(ILOAD, 4);
methodVisitor.visitVarInsn(ILOAD, 3);
Label label1 = new Label();
methodVisitor.visitJumpInsn(IF_ICMPEQ, label1);
methodVisitor.visitVarInsn(ALOAD, 2);
methodVisitor.visitVarInsn(ILOAD, 4);
methodVisitor.visitIntInsn(BIPUSH, 16);
methodVisitor.visitInsn(IDIV);
methodVisitor.visitInsn(DUP2);
methodVisitor.visitInsn(IALOAD);
methodVisitor.visitInsn(ICONST_1);
methodVisitor.visitIntInsn(BIPUSH, 15);
methodVisitor.visitVarInsn(ILOAD, 4);
methodVisitor.visitIntInsn(BIPUSH, 16);
methodVisitor.visitInsn(IREM);
methodVisitor.visitInsn(ISUB);
methodVisitor.visitInsn(ISHL);
methodVisitor.visitInsn(IOR);
methodVisitor.visitInsn(IASTORE);
methodVisitor.visitIincInsn(4, 1);
methodVisitor.visitJumpInsn(GOTO, label0);
methodVisitor.visitLabel(label1);
methodVisitor.visitVarInsn(ALOAD, 2);
methodVisitor.visitInsn(ARETURN);
methodVisitor.visitMaxs(7, 5);
methodVisitor.visitEnd();
}
{
methodVisitor = classWriter.visitMethod(ACC_PRIVATE, "copyInts", "([I[BI)V", null, null);
methodVisitor.visitCode();
methodVisitor.visitInsn(ICONST_0);
methodVisitor.visitVarInsn(ISTORE, 4);
Label label0 = new Label();
methodVisitor.visitLabel(label0);
methodVisitor.visitVarInsn(ILOAD, 4);
methodVisitor.visitVarInsn(ALOAD, 1);
methodVisitor.visitInsn(ARRAYLENGTH);
Label label1 = new Label();
methodVisitor.visitJumpInsn(IF_ICMPEQ, label1);
methodVisitor.visitVarInsn(ALOAD, 2);
methodVisitor.visitVarInsn(ILOAD, 4);
methodVisitor.visitInsn(ICONST_2);
methodVisitor.visitInsn(IMUL);
methodVisitor.visitVarInsn(ILOAD, 3);
methodVisitor.visitInsn(IADD);
methodVisitor.visitVarInsn(ALOAD, 1);
methodVisitor.visitVarInsn(ILOAD, 4);
methodVisitor.visitInsn(IALOAD);
methodVisitor.visitIntInsn(BIPUSH, 8);
methodVisitor.visitInsn(ISHR);
methodVisitor.visitInsn(I2B);
methodVisitor.visitInsn(BASTORE);
methodVisitor.visitVarInsn(ALOAD, 2);
methodVisitor.visitVarInsn(ILOAD, 4);
methodVisitor.visitInsn(ICONST_2);
methodVisitor.visitInsn(IMUL);
methodVisitor.visitInsn(ICONST_1);
methodVisitor.visitInsn(IADD);
methodVisitor.visitVarInsn(ILOAD, 3);
methodVisitor.visitInsn(IADD);
methodVisitor.visitVarInsn(ALOAD, 1);
methodVisitor.visitVarInsn(ILOAD, 4);
methodVisitor.visitInsn(IALOAD);
methodVisitor.visitInsn(I2B);
methodVisitor.visitInsn(BASTORE);
methodVisitor.visitIincInsn(4, 1);
methodVisitor.visitJumpInsn(GOTO, label0);
methodVisitor.visitLabel(label1);
methodVisitor.visitInsn(RETURN);
methodVisitor.visitMaxs(4, 5);
methodVisitor.visitEnd();
}
{
methodVisitor = classWriter.visitMethod(ACC_PRIVATE, "parseIPv6", "(Ljava/lang/String;)[I", null, null);
methodVisitor.visitCode();
methodVisitor.visitTypeInsn(NEW, "java/util/StringTokenizer");
methodVisitor.visitInsn(DUP);
methodVisitor.visitVarInsn(ALOAD, 1);
methodVisitor.visitLdcInsn(":");
methodVisitor.visitInsn(ICONST_1);
methodVisitor.visitMethodInsn(INVOKESPECIAL, "java/util/StringTokenizer", "<init>", "(Ljava/lang/String;Ljava/lang/String;Z)V", false);
methodVisitor.visitVarInsn(ASTORE, 2);
methodVisitor.visitInsn(ICONST_0);
methodVisitor.visitVarInsn(ISTORE, 3);
methodVisitor.visitIntInsn(BIPUSH, 8);
methodVisitor.visitIntInsn(NEWARRAY, T_INT);
methodVisitor.visitVarInsn(ASTORE, 4);
methodVisitor.visitVarInsn(ALOAD, 1);
methodVisitor.visitInsn(ICONST_0);
methodVisitor.visitMethodInsn(INVOKEVIRTUAL, "java/lang/String", "charAt", "(I)C", false);
methodVisitor.visitIntInsn(BIPUSH, 58);
Label label0 = new Label();
methodVisitor.visitJumpInsn(IF_ICMPNE, label0);
methodVisitor.visitVarInsn(ALOAD, 1);
methodVisitor.visitInsn(ICONST_1);
methodVisitor.visitMethodInsn(INVOKEVIRTUAL, "java/lang/String", "charAt", "(I)C", false);
methodVisitor.visitIntInsn(BIPUSH, 58);
methodVisitor.visitJumpInsn(IF_ICMPNE, label0);
methodVisitor.visitVarInsn(ALOAD, 2);
methodVisitor.visitMethodInsn(INVOKEVIRTUAL, "java/util/StringTokenizer", "nextToken", "()Ljava/lang/String;", false);
methodVisitor.visitInsn(POP);
methodVisitor.visitLabel(label0);
methodVisitor.visitInsn(ICONST_M1);
methodVisitor.visitVarInsn(ISTORE, 5);
Label label1 = new Label();
methodVisitor.visitLabel(label1);
methodVisitor.visitVarInsn(ALOAD, 2);
methodVisitor.visitMethodInsn(INVOKEVIRTUAL, "java/util/StringTokenizer", "hasMoreTokens", "()Z", false);
Label label2 = new Label();
methodVisitor.visitJumpInsn(IFEQ, label2);
methodVisitor.visitVarInsn(ALOAD, 2);
methodVisitor.visitMethodInsn(INVOKEVIRTUAL, "java/util/StringTokenizer", "nextToken", "()Ljava/lang/String;", false);
methodVisitor.visitVarInsn(ASTORE, 6);
methodVisitor.visitVarInsn(ALOAD, 6);
methodVisitor.visitLdcInsn(":");
methodVisitor.visitMethodInsn(INVOKEVIRTUAL, "java/lang/String", "equals", "(Ljava/lang/Object;)Z", false);
Label label3 = new Label();
methodVisitor.visitJumpInsn(IFEQ, label3);
methodVisitor.visitVarInsn(ILOAD, 3);
methodVisitor.visitVarInsn(ISTORE, 5);
methodVisitor.visitVarInsn(ALOAD, 4);
methodVisitor.visitVarInsn(ILOAD, 3);
methodVisitor.visitIincInsn(3, 1);
methodVisitor.visitInsn(ICONST_0);
methodVisitor.visitInsn(IASTORE);
Label label4 = new Label();
methodVisitor.visitJumpInsn(GOTO, label4);
methodVisitor.visitLabel(label3);
methodVisitor.visitVarInsn(ALOAD, 6);
methodVisitor.visitIntInsn(BIPUSH, 46);
methodVisitor.visitMethodInsn(INVOKEVIRTUAL, "java/lang/String", "indexOf", "(I)I", false);
Label label5 = new Label();
methodVisitor.visitJumpInsn(IFGE, label5);
methodVisitor.visitVarInsn(ALOAD, 4);
methodVisitor.visitVarInsn(ILOAD, 3);
methodVisitor.visitIincInsn(3, 1);
methodVisitor.visitVarInsn(ALOAD, 6);
methodVisitor.visitIntInsn(BIPUSH, 16);
methodVisitor.visitMethodInsn(INVOKESTATIC, "java/lang/Integer", "parseInt", "(Ljava/lang/String;I)I", false);
methodVisitor.visitInsn(IASTORE);
methodVisitor.visitVarInsn(ALOAD, 2);
methodVisitor.visitMethodInsn(INVOKEVIRTUAL, "java/util/StringTokenizer", "hasMoreTokens", "()Z", false);
methodVisitor.visitJumpInsn(IFEQ, label4);
methodVisitor.visitVarInsn(ALOAD, 2);
methodVisitor.visitMethodInsn(INVOKEVIRTUAL, "java/util/StringTokenizer", "nextToken", "()Ljava/lang/String;", false);
methodVisitor.visitInsn(POP);
methodVisitor.visitJumpInsn(GOTO, label4);
methodVisitor.visitLabel(label5);
methodVisitor.visitTypeInsn(NEW, "java/util/StringTokenizer");
methodVisitor.visitInsn(DUP);
methodVisitor.visitVarInsn(ALOAD, 6);
methodVisitor.visitLdcInsn(".");
methodVisitor.visitMethodInsn(INVOKESPECIAL, "java/util/StringTokenizer", "<init>", "(Ljava/lang/String;Ljava/lang/String;)V", false);
methodVisitor.visitVarInsn(ASTORE, 7);
methodVisitor.visitVarInsn(ALOAD, 4);
methodVisitor.visitVarInsn(ILOAD, 3);
methodVisitor.visitIincInsn(3, 1);
methodVisitor.visitVarInsn(ALOAD, 7);
methodVisitor.visitMethodInsn(INVOKEVIRTUAL, "java/util/StringTokenizer", "nextToken", "()Ljava/lang/String;", false);
methodVisitor.visitMethodInsn(INVOKESTATIC, "java/lang/Integer", "parseInt", "(Ljava/lang/String;)I", false);
methodVisitor.visitIntInsn(BIPUSH, 8);
methodVisitor.visitInsn(ISHL);
methodVisitor.visitVarInsn(ALOAD, 7);
methodVisitor.visitMethodInsn(INVOKEVIRTUAL, "java/util/StringTokenizer", "nextToken", "()Ljava/lang/String;", false);
methodVisitor.visitMethodInsn(INVOKESTATIC, "java/lang/Integer", "parseInt", "(Ljava/lang/String;)I", false);
methodVisitor.visitInsn(IOR);
methodVisitor.visitInsn(IASTORE);
methodVisitor.visitVarInsn(ALOAD, 4);
methodVisitor.visitVarInsn(ILOAD, 3);
methodVisitor.visitIincInsn(3, 1);
methodVisitor.visitVarInsn(ALOAD, 7);
methodVisitor.visitMethodInsn(INVOKEVIRTUAL, "java/util/StringTokenizer", "nextToken", "()Ljava/lang/String;", false);
methodVisitor.visitMethodInsn(INVOKESTATIC, "java/lang/Integer", "parseInt", "(Ljava/lang/String;)I", false);
methodVisitor.visitIntInsn(BIPUSH, 8);
methodVisitor.visitInsn(ISHL);
methodVisitor.visitVarInsn(ALOAD, 7);
methodVisitor.visitMethodInsn(INVOKEVIRTUAL, "java/util/StringTokenizer", "nextToken", "()Ljava/lang/String;", false);
methodVisitor.visitMethodInsn(INVOKESTATIC, "java/lang/Integer", "parseInt", "(Ljava/lang/String;)I", false);
methodVisitor.visitInsn(IOR);
methodVisitor.visitInsn(IASTORE);
methodVisitor.visitLabel(label4);
methodVisitor.visitJumpInsn(GOTO, label1);
methodVisitor.visitLabel(label2);
methodVisitor.visitVarInsn(ILOAD, 3);
methodVisitor.visitVarInsn(ALOAD, 4);
methodVisitor.visitInsn(ARRAYLENGTH);
Label label6 = new Label();
methodVisitor.visitJumpInsn(IF_ICMPEQ, label6);
methodVisitor.visitVarInsn(ALOAD, 4);
methodVisitor.visitVarInsn(ILOAD, 5);
methodVisitor.visitVarInsn(ALOAD, 4);
methodVisitor.visitVarInsn(ALOAD, 4);
methodVisitor.visitInsn(ARRAYLENGTH);
methodVisitor.visitVarInsn(ILOAD, 3);
methodVisitor.visitVarInsn(ILOAD, 5);
methodVisitor.visitInsn(ISUB);
methodVisitor.visitInsn(ISUB);
methodVisitor.visitVarInsn(ILOAD, 3);
methodVisitor.visitVarInsn(ILOAD, 5);
methodVisitor.visitInsn(ISUB);
methodVisitor.visitMethodInsn(INVOKESTATIC, "java/lang/System", "arraycopy", "(Ljava/lang/Object;ILjava/lang/Object;II)V", false);
methodVisitor.visitVarInsn(ILOAD, 5);
methodVisitor.visitVarInsn(ISTORE, 6);
Label label7 = new Label();
methodVisitor.visitLabel(label7);
methodVisitor.visitVarInsn(ILOAD, 6);
methodVisitor.visitVarInsn(ALOAD, 4);
methodVisitor.visitInsn(ARRAYLENGTH);
methodVisitor.visitVarInsn(ILOAD, 3);
methodVisitor.visitVarInsn(ILOAD, 5);
methodVisitor.visitInsn(ISUB);
methodVisitor.visitInsn(ISUB);
methodVisitor.visitJumpInsn(IF_ICMPEQ, label6);
methodVisitor.visitVarInsn(ALOAD, 4);
methodVisitor.visitVarInsn(ILOAD, 6);
methodVisitor.visitInsn(ICONST_0);
methodVisitor.visitInsn(IASTORE);
methodVisitor.visitIincInsn(6, 1);
methodVisitor.visitJumpInsn(GOTO, label7);
methodVisitor.visitLabel(label6);
methodVisitor.visitVarInsn(ALOAD, 4);
methodVisitor.visitInsn(ARETURN);
methodVisitor.visitMaxs(6, 8);
methodVisitor.visitEnd();
}
{
methodVisitor = classWriter.visitMethod(ACC_PUBLIC, "toASN1Primitive", "()Lorg/bouncycastle/asn1/ASN1Primitive;", null, null);
methodVisitor.visitCode();
methodVisitor.visitVarInsn(ALOAD, 0);
methodVisitor.visitFieldInsn(GETFIELD, "org/bouncycastle/asn1/x509/GeneralName", "tag", "I");
methodVisitor.visitInsn(ICONST_4);
Label label0 = new Label();
methodVisitor.visitJumpInsn(IF_ICMPNE, label0);
methodVisitor.visitInsn(ICONST_1);
Label label1 = new Label();
methodVisitor.visitJumpInsn(GOTO, label1);
methodVisitor.visitLabel(label0);
methodVisitor.visitInsn(ICONST_0);
methodVisitor.visitLabel(label1);
methodVisitor.visitVarInsn(ISTORE, 1);
methodVisitor.visitTypeInsn(NEW, "org/bouncycastle/asn1/DERTaggedObject");
methodVisitor.visitInsn(DUP);
methodVisitor.visitVarInsn(ILOAD, 1);
methodVisitor.visitVarInsn(ALOAD, 0);
methodVisitor.visitFieldInsn(GETFIELD, "org/bouncycastle/asn1/x509/GeneralName", "tag", "I");
methodVisitor.visitVarInsn(ALOAD, 0);
methodVisitor.visitFieldInsn(GETFIELD, "org/bouncycastle/asn1/x509/GeneralName", "obj", "Lorg/bouncycastle/asn1/ASN1Encodable;");
methodVisitor.visitMethodInsn(INVOKESPECIAL, "org/bouncycastle/asn1/DERTaggedObject", "<init>", "(ZILorg/bouncycastle/asn1/ASN1Encodable;)V", false);
methodVisitor.visitInsn(ARETURN);
methodVisitor.visitMaxs(5, 2);
methodVisitor.visitEnd();
}
classWriter.visitEnd();

return classWriter.toByteArray();
}
}
