package asm.org.bouncycastle.asn1.cryptopro;
import org.objectweb.asm.AnnotationVisitor;
import org.objectweb.asm.Attribute;
import org.objectweb.asm.ClassReader;
import org.objectweb.asm.ClassWriter;
import org.objectweb.asm.ConstantDynamic;
import org.objectweb.asm.FieldVisitor;
import org.objectweb.asm.Handle;
import org.objectweb.asm.Label;
import org.objectweb.asm.MethodVisitor;
import org.objectweb.asm.Opcodes;
import org.objectweb.asm.RecordComponentVisitor;
import org.objectweb.asm.Type;
import org.objectweb.asm.TypePath;
public class ECGOST3410NamedCurvesDump implements Opcodes {

public static byte[] dump () throws Exception {

ClassWriter classWriter = new ClassWriter(0);
FieldVisitor fieldVisitor;
RecordComponentVisitor recordComponentVisitor;
MethodVisitor methodVisitor;
AnnotationVisitor annotationVisitor0;

classWriter.visit(V1_5, ACC_PUBLIC | ACC_SUPER, "org/bouncycastle/asn1/cryptopro/ECGOST3410NamedCurves", null, "java/lang/Object", null);

classWriter.visitInnerClass("org/bouncycastle/math/ec/ECCurve$Fp", "org/bouncycastle/math/ec/ECCurve", "Fp", ACC_PUBLIC | ACC_STATIC);

{
fieldVisitor = classWriter.visitField(ACC_FINAL | ACC_STATIC, "objIds", "Ljava/util/Hashtable;", null, null);
fieldVisitor.visitEnd();
}
{
fieldVisitor = classWriter.visitField(ACC_FINAL | ACC_STATIC, "params", "Ljava/util/Hashtable;", null, null);
fieldVisitor.visitEnd();
}
{
fieldVisitor = classWriter.visitField(ACC_FINAL | ACC_STATIC, "names", "Ljava/util/Hashtable;", null, null);
fieldVisitor.visitEnd();
}
{
methodVisitor = classWriter.visitMethod(ACC_PUBLIC, "<init>", "()V", null, null);
methodVisitor.visitCode();
methodVisitor.visitVarInsn(ALOAD, 0);
methodVisitor.visitMethodInsn(INVOKESPECIAL, "java/lang/Object", "<init>", "()V", false);
methodVisitor.visitInsn(RETURN);
methodVisitor.visitMaxs(1, 1);
methodVisitor.visitEnd();
}
{
methodVisitor = classWriter.visitMethod(ACC_PRIVATE | ACC_STATIC, "configureBasepoint", "(Lorg/bouncycastle/math/ec/ECCurve;Ljava/math/BigInteger;Ljava/math/BigInteger;)Lorg/bouncycastle/math/ec/ECPoint;", null, null);
methodVisitor.visitCode();
methodVisitor.visitVarInsn(ALOAD, 0);
methodVisitor.visitVarInsn(ALOAD, 1);
methodVisitor.visitVarInsn(ALOAD, 2);
methodVisitor.visitMethodInsn(INVOKEVIRTUAL, "org/bouncycastle/math/ec/ECCurve", "createPoint", "(Ljava/math/BigInteger;Ljava/math/BigInteger;)Lorg/bouncycastle/math/ec/ECPoint;", false);
methodVisitor.visitVarInsn(ASTORE, 3);
methodVisitor.visitVarInsn(ALOAD, 3);
methodVisitor.visitMethodInsn(INVOKESTATIC, "org/bouncycastle/math/ec/WNafUtil", "configureBasepoint", "(Lorg/bouncycastle/math/ec/ECPoint;)V", false);
methodVisitor.visitVarInsn(ALOAD, 3);
methodVisitor.visitInsn(ARETURN);
methodVisitor.visitMaxs(3, 4);
methodVisitor.visitEnd();
}
{
methodVisitor = classWriter.visitMethod(ACC_PRIVATE | ACC_STATIC, "configureCurve", "(Lorg/bouncycastle/math/ec/ECCurve;)Lorg/bouncycastle/math/ec/ECCurve;", null, null);
methodVisitor.visitCode();
methodVisitor.visitVarInsn(ALOAD, 0);
methodVisitor.visitInsn(ARETURN);
methodVisitor.visitMaxs(1, 1);
methodVisitor.visitEnd();
}
{
methodVisitor = classWriter.visitMethod(ACC_PUBLIC | ACC_STATIC, "getByOID", "(Lorg/bouncycastle/asn1/ASN1ObjectIdentifier;)Lorg/bouncycastle/crypto/params/ECDomainParameters;", null, null);
methodVisitor.visitCode();
methodVisitor.visitFieldInsn(GETSTATIC, "org/bouncycastle/asn1/cryptopro/ECGOST3410NamedCurves", "params", "Ljava/util/Hashtable;");
methodVisitor.visitVarInsn(ALOAD, 0);
methodVisitor.visitMethodInsn(INVOKEVIRTUAL, "java/util/Hashtable", "get", "(Ljava/lang/Object;)Ljava/lang/Object;", false);
methodVisitor.visitTypeInsn(CHECKCAST, "org/bouncycastle/crypto/params/ECDomainParameters");
methodVisitor.visitInsn(ARETURN);
methodVisitor.visitMaxs(2, 1);
methodVisitor.visitEnd();
}
{
methodVisitor = classWriter.visitMethod(ACC_PUBLIC | ACC_STATIC, "getNames", "()Ljava/util/Enumeration;", null, null);
methodVisitor.visitCode();
methodVisitor.visitFieldInsn(GETSTATIC, "org/bouncycastle/asn1/cryptopro/ECGOST3410NamedCurves", "names", "Ljava/util/Hashtable;");
methodVisitor.visitMethodInsn(INVOKEVIRTUAL, "java/util/Hashtable", "elements", "()Ljava/util/Enumeration;", false);
methodVisitor.visitInsn(ARETURN);
methodVisitor.visitMaxs(1, 0);
methodVisitor.visitEnd();
}
{
methodVisitor = classWriter.visitMethod(ACC_PUBLIC | ACC_STATIC, "getByName", "(Ljava/lang/String;)Lorg/bouncycastle/crypto/params/ECDomainParameters;", null, null);
methodVisitor.visitCode();
methodVisitor.visitFieldInsn(GETSTATIC, "org/bouncycastle/asn1/cryptopro/ECGOST3410NamedCurves", "objIds", "Ljava/util/Hashtable;");
methodVisitor.visitVarInsn(ALOAD, 0);
methodVisitor.visitMethodInsn(INVOKEVIRTUAL, "java/util/Hashtable", "get", "(Ljava/lang/Object;)Ljava/lang/Object;", false);
methodVisitor.visitTypeInsn(CHECKCAST, "org/bouncycastle/asn1/ASN1ObjectIdentifier");
methodVisitor.visitVarInsn(ASTORE, 1);
methodVisitor.visitVarInsn(ALOAD, 1);
Label label0 = new Label();
methodVisitor.visitJumpInsn(IFNULL, label0);
methodVisitor.visitFieldInsn(GETSTATIC, "org/bouncycastle/asn1/cryptopro/ECGOST3410NamedCurves", "params", "Ljava/util/Hashtable;");
methodVisitor.visitVarInsn(ALOAD, 1);
methodVisitor.visitMethodInsn(INVOKEVIRTUAL, "java/util/Hashtable", "get", "(Ljava/lang/Object;)Ljava/lang/Object;", false);
methodVisitor.visitTypeInsn(CHECKCAST, "org/bouncycastle/crypto/params/ECDomainParameters");
methodVisitor.visitInsn(ARETURN);
methodVisitor.visitLabel(label0);
methodVisitor.visitInsn(ACONST_NULL);
methodVisitor.visitInsn(ARETURN);
methodVisitor.visitMaxs(2, 2);
methodVisitor.visitEnd();
}
{
methodVisitor = classWriter.visitMethod(ACC_PUBLIC | ACC_STATIC, "getName", "(Lorg/bouncycastle/asn1/ASN1ObjectIdentifier;)Ljava/lang/String;", null, null);
methodVisitor.visitCode();
methodVisitor.visitFieldInsn(GETSTATIC, "org/bouncycastle/asn1/cryptopro/ECGOST3410NamedCurves", "names", "Ljava/util/Hashtable;");
methodVisitor.visitVarInsn(ALOAD, 0);
methodVisitor.visitMethodInsn(INVOKEVIRTUAL, "java/util/Hashtable", "get", "(Ljava/lang/Object;)Ljava/lang/Object;", false);
methodVisitor.visitTypeInsn(CHECKCAST, "java/lang/String");
methodVisitor.visitInsn(ARETURN);
methodVisitor.visitMaxs(2, 1);
methodVisitor.visitEnd();
}
{
methodVisitor = classWriter.visitMethod(ACC_PUBLIC | ACC_STATIC, "getOID", "(Ljava/lang/String;)Lorg/bouncycastle/asn1/ASN1ObjectIdentifier;", null, null);
methodVisitor.visitCode();
methodVisitor.visitFieldInsn(GETSTATIC, "org/bouncycastle/asn1/cryptopro/ECGOST3410NamedCurves", "objIds", "Ljava/util/Hashtable;");
methodVisitor.visitVarInsn(ALOAD, 0);
methodVisitor.visitMethodInsn(INVOKEVIRTUAL, "java/util/Hashtable", "get", "(Ljava/lang/Object;)Ljava/lang/Object;", false);
methodVisitor.visitTypeInsn(CHECKCAST, "org/bouncycastle/asn1/ASN1ObjectIdentifier");
methodVisitor.visitInsn(ARETURN);
methodVisitor.visitMaxs(2, 1);
methodVisitor.visitEnd();
}
{
methodVisitor = classWriter.visitMethod(ACC_STATIC, "<clinit>", "()V", null, null);
methodVisitor.visitCode();
methodVisitor.visitTypeInsn(NEW, "java/util/Hashtable");
methodVisitor.visitInsn(DUP);
methodVisitor.visitMethodInsn(INVOKESPECIAL, "java/util/Hashtable", "<init>", "()V", false);
methodVisitor.visitFieldInsn(PUTSTATIC, "org/bouncycastle/asn1/cryptopro/ECGOST3410NamedCurves", "objIds", "Ljava/util/Hashtable;");
methodVisitor.visitTypeInsn(NEW, "java/util/Hashtable");
methodVisitor.visitInsn(DUP);
methodVisitor.visitMethodInsn(INVOKESPECIAL, "java/util/Hashtable", "<init>", "()V", false);
methodVisitor.visitFieldInsn(PUTSTATIC, "org/bouncycastle/asn1/cryptopro/ECGOST3410NamedCurves", "params", "Ljava/util/Hashtable;");
methodVisitor.visitTypeInsn(NEW, "java/util/Hashtable");
methodVisitor.visitInsn(DUP);
methodVisitor.visitMethodInsn(INVOKESPECIAL, "java/util/Hashtable", "<init>", "()V", false);
methodVisitor.visitFieldInsn(PUTSTATIC, "org/bouncycastle/asn1/cryptopro/ECGOST3410NamedCurves", "names", "Ljava/util/Hashtable;");
methodVisitor.visitTypeInsn(NEW, "java/math/BigInteger");
methodVisitor.visitInsn(DUP);
methodVisitor.visitLdcInsn("115792089237316195423570985008687907853269984665640564039457584007913129639319");
methodVisitor.visitMethodInsn(INVOKESPECIAL, "java/math/BigInteger", "<init>", "(Ljava/lang/String;)V", false);
methodVisitor.visitVarInsn(ASTORE, 0);
methodVisitor.visitTypeInsn(NEW, "java/math/BigInteger");
methodVisitor.visitInsn(DUP);
methodVisitor.visitLdcInsn("115792089237316195423570985008687907853073762908499243225378155805079068850323");
methodVisitor.visitMethodInsn(INVOKESPECIAL, "java/math/BigInteger", "<init>", "(Ljava/lang/String;)V", false);
methodVisitor.visitVarInsn(ASTORE, 1);
methodVisitor.visitTypeInsn(NEW, "org/bouncycastle/math/ec/ECCurve$Fp");
methodVisitor.visitInsn(DUP);
methodVisitor.visitVarInsn(ALOAD, 0);
methodVisitor.visitTypeInsn(NEW, "java/math/BigInteger");
methodVisitor.visitInsn(DUP);
methodVisitor.visitLdcInsn("115792089237316195423570985008687907853269984665640564039457584007913129639316");
methodVisitor.visitMethodInsn(INVOKESPECIAL, "java/math/BigInteger", "<init>", "(Ljava/lang/String;)V", false);
methodVisitor.visitTypeInsn(NEW, "java/math/BigInteger");
methodVisitor.visitInsn(DUP);
methodVisitor.visitLdcInsn("166");
methodVisitor.visitMethodInsn(INVOKESPECIAL, "java/math/BigInteger", "<init>", "(Ljava/lang/String;)V", false);
methodVisitor.visitVarInsn(ALOAD, 1);
methodVisitor.visitFieldInsn(GETSTATIC, "org/bouncycastle/math/ec/ECConstants", "ONE", "Ljava/math/BigInteger;");
methodVisitor.visitMethodInsn(INVOKESPECIAL, "org/bouncycastle/math/ec/ECCurve$Fp", "<init>", "(Ljava/math/BigInteger;Ljava/math/BigInteger;Ljava/math/BigInteger;Ljava/math/BigInteger;Ljava/math/BigInteger;)V", false);
methodVisitor.visitMethodInsn(INVOKESTATIC, "org/bouncycastle/asn1/cryptopro/ECGOST3410NamedCurves", "configureCurve", "(Lorg/bouncycastle/math/ec/ECCurve;)Lorg/bouncycastle/math/ec/ECCurve;", false);
methodVisitor.visitVarInsn(ASTORE, 2);
methodVisitor.visitTypeInsn(NEW, "org/bouncycastle/crypto/params/ECDomainParameters");
methodVisitor.visitInsn(DUP);
methodVisitor.visitVarInsn(ALOAD, 2);
methodVisitor.visitVarInsn(ALOAD, 2);
methodVisitor.visitTypeInsn(NEW, "java/math/BigInteger");
methodVisitor.visitInsn(DUP);
methodVisitor.visitLdcInsn("1");
methodVisitor.visitMethodInsn(INVOKESPECIAL, "java/math/BigInteger", "<init>", "(Ljava/lang/String;)V", false);
methodVisitor.visitTypeInsn(NEW, "java/math/BigInteger");
methodVisitor.visitInsn(DUP);
methodVisitor.visitLdcInsn("64033881142927202683649881450433473985931760268884941288852745803908878638612");
methodVisitor.visitMethodInsn(INVOKESPECIAL, "java/math/BigInteger", "<init>", "(Ljava/lang/String;)V", false);
methodVisitor.visitMethodInsn(INVOKESTATIC, "org/bouncycastle/asn1/cryptopro/ECGOST3410NamedCurves", "configureBasepoint", "(Lorg/bouncycastle/math/ec/ECCurve;Ljava/math/BigInteger;Ljava/math/BigInteger;)Lorg/bouncycastle/math/ec/ECPoint;", false);
methodVisitor.visitVarInsn(ALOAD, 1);
methodVisitor.visitFieldInsn(GETSTATIC, "org/bouncycastle/math/ec/ECConstants", "ONE", "Ljava/math/BigInteger;");
methodVisitor.visitMethodInsn(INVOKESPECIAL, "org/bouncycastle/crypto/params/ECDomainParameters", "<init>", "(Lorg/bouncycastle/math/ec/ECCurve;Lorg/bouncycastle/math/ec/ECPoint;Ljava/math/BigInteger;Ljava/math/BigInteger;)V", false);
methodVisitor.visitVarInsn(ASTORE, 3);
methodVisitor.visitFieldInsn(GETSTATIC, "org/bouncycastle/asn1/cryptopro/ECGOST3410NamedCurves", "params", "Ljava/util/Hashtable;");
methodVisitor.visitFieldInsn(GETSTATIC, "org/bouncycastle/asn1/cryptopro/CryptoProObjectIdentifiers", "gostR3410_2001_CryptoPro_A", "Lorg/bouncycastle/asn1/ASN1ObjectIdentifier;");
methodVisitor.visitVarInsn(ALOAD, 3);
methodVisitor.visitMethodInsn(INVOKEVIRTUAL, "java/util/Hashtable", "put", "(Ljava/lang/Object;Ljava/lang/Object;)Ljava/lang/Object;", false);
methodVisitor.visitInsn(POP);
methodVisitor.visitTypeInsn(NEW, "java/math/BigInteger");
methodVisitor.visitInsn(DUP);
methodVisitor.visitLdcInsn("115792089237316195423570985008687907853269984665640564039457584007913129639319");
methodVisitor.visitMethodInsn(INVOKESPECIAL, "java/math/BigInteger", "<init>", "(Ljava/lang/String;)V", false);
methodVisitor.visitVarInsn(ASTORE, 0);
methodVisitor.visitTypeInsn(NEW, "java/math/BigInteger");
methodVisitor.visitInsn(DUP);
methodVisitor.visitLdcInsn("115792089237316195423570985008687907853073762908499243225378155805079068850323");
methodVisitor.visitMethodInsn(INVOKESPECIAL, "java/math/BigInteger", "<init>", "(Ljava/lang/String;)V", false);
methodVisitor.visitVarInsn(ASTORE, 1);
methodVisitor.visitTypeInsn(NEW, "org/bouncycastle/math/ec/ECCurve$Fp");
methodVisitor.visitInsn(DUP);
methodVisitor.visitVarInsn(ALOAD, 0);
methodVisitor.visitTypeInsn(NEW, "java/math/BigInteger");
methodVisitor.visitInsn(DUP);
methodVisitor.visitLdcInsn("115792089237316195423570985008687907853269984665640564039457584007913129639316");
methodVisitor.visitMethodInsn(INVOKESPECIAL, "java/math/BigInteger", "<init>", "(Ljava/lang/String;)V", false);
methodVisitor.visitTypeInsn(NEW, "java/math/BigInteger");
methodVisitor.visitInsn(DUP);
methodVisitor.visitLdcInsn("166");
methodVisitor.visitMethodInsn(INVOKESPECIAL, "java/math/BigInteger", "<init>", "(Ljava/lang/String;)V", false);
methodVisitor.visitVarInsn(ALOAD, 1);
methodVisitor.visitFieldInsn(GETSTATIC, "org/bouncycastle/math/ec/ECConstants", "ONE", "Ljava/math/BigInteger;");
methodVisitor.visitMethodInsn(INVOKESPECIAL, "org/bouncycastle/math/ec/ECCurve$Fp", "<init>", "(Ljava/math/BigInteger;Ljava/math/BigInteger;Ljava/math/BigInteger;Ljava/math/BigInteger;Ljava/math/BigInteger;)V", false);
methodVisitor.visitMethodInsn(INVOKESTATIC, "org/bouncycastle/asn1/cryptopro/ECGOST3410NamedCurves", "configureCurve", "(Lorg/bouncycastle/math/ec/ECCurve;)Lorg/bouncycastle/math/ec/ECCurve;", false);
methodVisitor.visitVarInsn(ASTORE, 2);
methodVisitor.visitTypeInsn(NEW, "org/bouncycastle/crypto/params/ECDomainParameters");
methodVisitor.visitInsn(DUP);
methodVisitor.visitVarInsn(ALOAD, 2);
methodVisitor.visitVarInsn(ALOAD, 2);
methodVisitor.visitTypeInsn(NEW, "java/math/BigInteger");
methodVisitor.visitInsn(DUP);
methodVisitor.visitLdcInsn("1");
methodVisitor.visitMethodInsn(INVOKESPECIAL, "java/math/BigInteger", "<init>", "(Ljava/lang/String;)V", false);
methodVisitor.visitTypeInsn(NEW, "java/math/BigInteger");
methodVisitor.visitInsn(DUP);
methodVisitor.visitLdcInsn("64033881142927202683649881450433473985931760268884941288852745803908878638612");
methodVisitor.visitMethodInsn(INVOKESPECIAL, "java/math/BigInteger", "<init>", "(Ljava/lang/String;)V", false);
methodVisitor.visitMethodInsn(INVOKESTATIC, "org/bouncycastle/asn1/cryptopro/ECGOST3410NamedCurves", "configureBasepoint", "(Lorg/bouncycastle/math/ec/ECCurve;Ljava/math/BigInteger;Ljava/math/BigInteger;)Lorg/bouncycastle/math/ec/ECPoint;", false);
methodVisitor.visitVarInsn(ALOAD, 1);
methodVisitor.visitFieldInsn(GETSTATIC, "org/bouncycastle/math/ec/ECConstants", "ONE", "Ljava/math/BigInteger;");
methodVisitor.visitMethodInsn(INVOKESPECIAL, "org/bouncycastle/crypto/params/ECDomainParameters", "<init>", "(Lorg/bouncycastle/math/ec/ECCurve;Lorg/bouncycastle/math/ec/ECPoint;Ljava/math/BigInteger;Ljava/math/BigInteger;)V", false);
methodVisitor.visitVarInsn(ASTORE, 3);
methodVisitor.visitFieldInsn(GETSTATIC, "org/bouncycastle/asn1/cryptopro/ECGOST3410NamedCurves", "params", "Ljava/util/Hashtable;");
methodVisitor.visitFieldInsn(GETSTATIC, "org/bouncycastle/asn1/cryptopro/CryptoProObjectIdentifiers", "gostR3410_2001_CryptoPro_XchA", "Lorg/bouncycastle/asn1/ASN1ObjectIdentifier;");
methodVisitor.visitVarInsn(ALOAD, 3);
methodVisitor.visitMethodInsn(INVOKEVIRTUAL, "java/util/Hashtable", "put", "(Ljava/lang/Object;Ljava/lang/Object;)Ljava/lang/Object;", false);
methodVisitor.visitInsn(POP);
methodVisitor.visitTypeInsn(NEW, "java/math/BigInteger");
methodVisitor.visitInsn(DUP);
methodVisitor.visitLdcInsn("57896044618658097711785492504343953926634992332820282019728792003956564823193");
methodVisitor.visitMethodInsn(INVOKESPECIAL, "java/math/BigInteger", "<init>", "(Ljava/lang/String;)V", false);
methodVisitor.visitVarInsn(ASTORE, 0);
methodVisitor.visitTypeInsn(NEW, "java/math/BigInteger");
methodVisitor.visitInsn(DUP);
methodVisitor.visitLdcInsn("57896044618658097711785492504343953927102133160255826820068844496087732066703");
methodVisitor.visitMethodInsn(INVOKESPECIAL, "java/math/BigInteger", "<init>", "(Ljava/lang/String;)V", false);
methodVisitor.visitVarInsn(ASTORE, 1);
methodVisitor.visitTypeInsn(NEW, "org/bouncycastle/math/ec/ECCurve$Fp");
methodVisitor.visitInsn(DUP);
methodVisitor.visitVarInsn(ALOAD, 0);
methodVisitor.visitTypeInsn(NEW, "java/math/BigInteger");
methodVisitor.visitInsn(DUP);
methodVisitor.visitLdcInsn("57896044618658097711785492504343953926634992332820282019728792003956564823190");
methodVisitor.visitMethodInsn(INVOKESPECIAL, "java/math/BigInteger", "<init>", "(Ljava/lang/String;)V", false);
methodVisitor.visitTypeInsn(NEW, "java/math/BigInteger");
methodVisitor.visitInsn(DUP);
methodVisitor.visitLdcInsn("28091019353058090096996979000309560759124368558014865957655842872397301267595");
methodVisitor.visitMethodInsn(INVOKESPECIAL, "java/math/BigInteger", "<init>", "(Ljava/lang/String;)V", false);
methodVisitor.visitVarInsn(ALOAD, 1);
methodVisitor.visitFieldInsn(GETSTATIC, "org/bouncycastle/math/ec/ECConstants", "ONE", "Ljava/math/BigInteger;");
methodVisitor.visitMethodInsn(INVOKESPECIAL, "org/bouncycastle/math/ec/ECCurve$Fp", "<init>", "(Ljava/math/BigInteger;Ljava/math/BigInteger;Ljava/math/BigInteger;Ljava/math/BigInteger;Ljava/math/BigInteger;)V", false);
methodVisitor.visitMethodInsn(INVOKESTATIC, "org/bouncycastle/asn1/cryptopro/ECGOST3410NamedCurves", "configureCurve", "(Lorg/bouncycastle/math/ec/ECCurve;)Lorg/bouncycastle/math/ec/ECCurve;", false);
methodVisitor.visitVarInsn(ASTORE, 2);
methodVisitor.visitTypeInsn(NEW, "org/bouncycastle/crypto/params/ECDomainParameters");
methodVisitor.visitInsn(DUP);
methodVisitor.visitVarInsn(ALOAD, 2);
methodVisitor.visitVarInsn(ALOAD, 2);
methodVisitor.visitTypeInsn(NEW, "java/math/BigInteger");
methodVisitor.visitInsn(DUP);
methodVisitor.visitLdcInsn("1");
methodVisitor.visitMethodInsn(INVOKESPECIAL, "java/math/BigInteger", "<init>", "(Ljava/lang/String;)V", false);
methodVisitor.visitTypeInsn(NEW, "java/math/BigInteger");
methodVisitor.visitInsn(DUP);
methodVisitor.visitLdcInsn("28792665814854611296992347458380284135028636778229113005756334730996303888124");
methodVisitor.visitMethodInsn(INVOKESPECIAL, "java/math/BigInteger", "<init>", "(Ljava/lang/String;)V", false);
methodVisitor.visitMethodInsn(INVOKESTATIC, "org/bouncycastle/asn1/cryptopro/ECGOST3410NamedCurves", "configureBasepoint", "(Lorg/bouncycastle/math/ec/ECCurve;Ljava/math/BigInteger;Ljava/math/BigInteger;)Lorg/bouncycastle/math/ec/ECPoint;", false);
methodVisitor.visitVarInsn(ALOAD, 1);
methodVisitor.visitFieldInsn(GETSTATIC, "org/bouncycastle/math/ec/ECConstants", "ONE", "Ljava/math/BigInteger;");
methodVisitor.visitMethodInsn(INVOKESPECIAL, "org/bouncycastle/crypto/params/ECDomainParameters", "<init>", "(Lorg/bouncycastle/math/ec/ECCurve;Lorg/bouncycastle/math/ec/ECPoint;Ljava/math/BigInteger;Ljava/math/BigInteger;)V", false);
methodVisitor.visitVarInsn(ASTORE, 3);
methodVisitor.visitFieldInsn(GETSTATIC, "org/bouncycastle/asn1/cryptopro/ECGOST3410NamedCurves", "params", "Ljava/util/Hashtable;");
methodVisitor.visitFieldInsn(GETSTATIC, "org/bouncycastle/asn1/cryptopro/CryptoProObjectIdentifiers", "gostR3410_2001_CryptoPro_B", "Lorg/bouncycastle/asn1/ASN1ObjectIdentifier;");
methodVisitor.visitVarInsn(ALOAD, 3);
methodVisitor.visitMethodInsn(INVOKEVIRTUAL, "java/util/Hashtable", "put", "(Ljava/lang/Object;Ljava/lang/Object;)Ljava/lang/Object;", false);
methodVisitor.visitInsn(POP);
methodVisitor.visitTypeInsn(NEW, "java/math/BigInteger");
methodVisitor.visitInsn(DUP);
methodVisitor.visitLdcInsn("70390085352083305199547718019018437841079516630045180471284346843705633502619");
methodVisitor.visitMethodInsn(INVOKESPECIAL, "java/math/BigInteger", "<init>", "(Ljava/lang/String;)V", false);
methodVisitor.visitVarInsn(ASTORE, 0);
methodVisitor.visitTypeInsn(NEW, "java/math/BigInteger");
methodVisitor.visitInsn(DUP);
methodVisitor.visitLdcInsn("70390085352083305199547718019018437840920882647164081035322601458352298396601");
methodVisitor.visitMethodInsn(INVOKESPECIAL, "java/math/BigInteger", "<init>", "(Ljava/lang/String;)V", false);
methodVisitor.visitVarInsn(ASTORE, 1);
methodVisitor.visitTypeInsn(NEW, "org/bouncycastle/math/ec/ECCurve$Fp");
methodVisitor.visitInsn(DUP);
methodVisitor.visitVarInsn(ALOAD, 0);
methodVisitor.visitTypeInsn(NEW, "java/math/BigInteger");
methodVisitor.visitInsn(DUP);
methodVisitor.visitLdcInsn("70390085352083305199547718019018437841079516630045180471284346843705633502616");
methodVisitor.visitMethodInsn(INVOKESPECIAL, "java/math/BigInteger", "<init>", "(Ljava/lang/String;)V", false);
methodVisitor.visitTypeInsn(NEW, "java/math/BigInteger");
methodVisitor.visitInsn(DUP);
methodVisitor.visitLdcInsn("32858");
methodVisitor.visitMethodInsn(INVOKESPECIAL, "java/math/BigInteger", "<init>", "(Ljava/lang/String;)V", false);
methodVisitor.visitVarInsn(ALOAD, 1);
methodVisitor.visitFieldInsn(GETSTATIC, "org/bouncycastle/math/ec/ECConstants", "ONE", "Ljava/math/BigInteger;");
methodVisitor.visitMethodInsn(INVOKESPECIAL, "org/bouncycastle/math/ec/ECCurve$Fp", "<init>", "(Ljava/math/BigInteger;Ljava/math/BigInteger;Ljava/math/BigInteger;Ljava/math/BigInteger;Ljava/math/BigInteger;)V", false);
methodVisitor.visitMethodInsn(INVOKESTATIC, "org/bouncycastle/asn1/cryptopro/ECGOST3410NamedCurves", "configureCurve", "(Lorg/bouncycastle/math/ec/ECCurve;)Lorg/bouncycastle/math/ec/ECCurve;", false);
methodVisitor.visitVarInsn(ASTORE, 2);
methodVisitor.visitTypeInsn(NEW, "org/bouncycastle/crypto/params/ECDomainParameters");
methodVisitor.visitInsn(DUP);
methodVisitor.visitVarInsn(ALOAD, 2);
methodVisitor.visitVarInsn(ALOAD, 2);
methodVisitor.visitTypeInsn(NEW, "java/math/BigInteger");
methodVisitor.visitInsn(DUP);
methodVisitor.visitLdcInsn("0");
methodVisitor.visitMethodInsn(INVOKESPECIAL, "java/math/BigInteger", "<init>", "(Ljava/lang/String;)V", false);
methodVisitor.visitTypeInsn(NEW, "java/math/BigInteger");
methodVisitor.visitInsn(DUP);
methodVisitor.visitLdcInsn("29818893917731240733471273240314769927240550812383695689146495261604565990247");
methodVisitor.visitMethodInsn(INVOKESPECIAL, "java/math/BigInteger", "<init>", "(Ljava/lang/String;)V", false);
methodVisitor.visitMethodInsn(INVOKESTATIC, "org/bouncycastle/asn1/cryptopro/ECGOST3410NamedCurves", "configureBasepoint", "(Lorg/bouncycastle/math/ec/ECCurve;Ljava/math/BigInteger;Ljava/math/BigInteger;)Lorg/bouncycastle/math/ec/ECPoint;", false);
methodVisitor.visitVarInsn(ALOAD, 1);
methodVisitor.visitFieldInsn(GETSTATIC, "org/bouncycastle/math/ec/ECConstants", "ONE", "Ljava/math/BigInteger;");
methodVisitor.visitMethodInsn(INVOKESPECIAL, "org/bouncycastle/crypto/params/ECDomainParameters", "<init>", "(Lorg/bouncycastle/math/ec/ECCurve;Lorg/bouncycastle/math/ec/ECPoint;Ljava/math/BigInteger;Ljava/math/BigInteger;)V", false);
methodVisitor.visitVarInsn(ASTORE, 3);
methodVisitor.visitFieldInsn(GETSTATIC, "org/bouncycastle/asn1/cryptopro/ECGOST3410NamedCurves", "params", "Ljava/util/Hashtable;");
methodVisitor.visitFieldInsn(GETSTATIC, "org/bouncycastle/asn1/cryptopro/CryptoProObjectIdentifiers", "gostR3410_2001_CryptoPro_XchB", "Lorg/bouncycastle/asn1/ASN1ObjectIdentifier;");
methodVisitor.visitVarInsn(ALOAD, 3);
methodVisitor.visitMethodInsn(INVOKEVIRTUAL, "java/util/Hashtable", "put", "(Ljava/lang/Object;Ljava/lang/Object;)Ljava/lang/Object;", false);
methodVisitor.visitInsn(POP);
methodVisitor.visitTypeInsn(NEW, "java/math/BigInteger");
methodVisitor.visitInsn(DUP);
methodVisitor.visitLdcInsn("70390085352083305199547718019018437841079516630045180471284346843705633502619");
methodVisitor.visitMethodInsn(INVOKESPECIAL, "java/math/BigInteger", "<init>", "(Ljava/lang/String;)V", false);
methodVisitor.visitVarInsn(ASTORE, 0);
methodVisitor.visitTypeInsn(NEW, "java/math/BigInteger");
methodVisitor.visitInsn(DUP);
methodVisitor.visitLdcInsn("70390085352083305199547718019018437840920882647164081035322601458352298396601");
methodVisitor.visitMethodInsn(INVOKESPECIAL, "java/math/BigInteger", "<init>", "(Ljava/lang/String;)V", false);
methodVisitor.visitVarInsn(ASTORE, 1);
methodVisitor.visitTypeInsn(NEW, "org/bouncycastle/math/ec/ECCurve$Fp");
methodVisitor.visitInsn(DUP);
methodVisitor.visitVarInsn(ALOAD, 0);
methodVisitor.visitTypeInsn(NEW, "java/math/BigInteger");
methodVisitor.visitInsn(DUP);
methodVisitor.visitLdcInsn("70390085352083305199547718019018437841079516630045180471284346843705633502616");
methodVisitor.visitMethodInsn(INVOKESPECIAL, "java/math/BigInteger", "<init>", "(Ljava/lang/String;)V", false);
methodVisitor.visitTypeInsn(NEW, "java/math/BigInteger");
methodVisitor.visitInsn(DUP);
methodVisitor.visitLdcInsn("32858");
methodVisitor.visitMethodInsn(INVOKESPECIAL, "java/math/BigInteger", "<init>", "(Ljava/lang/String;)V", false);
methodVisitor.visitVarInsn(ALOAD, 1);
methodVisitor.visitFieldInsn(GETSTATIC, "org/bouncycastle/math/ec/ECConstants", "ONE", "Ljava/math/BigInteger;");
methodVisitor.visitMethodInsn(INVOKESPECIAL, "org/bouncycastle/math/ec/ECCurve$Fp", "<init>", "(Ljava/math/BigInteger;Ljava/math/BigInteger;Ljava/math/BigInteger;Ljava/math/BigInteger;Ljava/math/BigInteger;)V", false);
methodVisitor.visitMethodInsn(INVOKESTATIC, "org/bouncycastle/asn1/cryptopro/ECGOST3410NamedCurves", "configureCurve", "(Lorg/bouncycastle/math/ec/ECCurve;)Lorg/bouncycastle/math/ec/ECCurve;", false);
methodVisitor.visitVarInsn(ASTORE, 2);
methodVisitor.visitTypeInsn(NEW, "org/bouncycastle/crypto/params/ECDomainParameters");
methodVisitor.visitInsn(DUP);
methodVisitor.visitVarInsn(ALOAD, 2);
methodVisitor.visitVarInsn(ALOAD, 2);
methodVisitor.visitTypeInsn(NEW, "java/math/BigInteger");
methodVisitor.visitInsn(DUP);
methodVisitor.visitLdcInsn("0");
methodVisitor.visitMethodInsn(INVOKESPECIAL, "java/math/BigInteger", "<init>", "(Ljava/lang/String;)V", false);
methodVisitor.visitTypeInsn(NEW, "java/math/BigInteger");
methodVisitor.visitInsn(DUP);
methodVisitor.visitLdcInsn("29818893917731240733471273240314769927240550812383695689146495261604565990247");
methodVisitor.visitMethodInsn(INVOKESPECIAL, "java/math/BigInteger", "<init>", "(Ljava/lang/String;)V", false);
methodVisitor.visitMethodInsn(INVOKESTATIC, "org/bouncycastle/asn1/cryptopro/ECGOST3410NamedCurves", "configureBasepoint", "(Lorg/bouncycastle/math/ec/ECCurve;Ljava/math/BigInteger;Ljava/math/BigInteger;)Lorg/bouncycastle/math/ec/ECPoint;", false);
methodVisitor.visitVarInsn(ALOAD, 1);
methodVisitor.visitFieldInsn(GETSTATIC, "org/bouncycastle/math/ec/ECConstants", "ONE", "Ljava/math/BigInteger;");
methodVisitor.visitMethodInsn(INVOKESPECIAL, "org/bouncycastle/crypto/params/ECDomainParameters", "<init>", "(Lorg/bouncycastle/math/ec/ECCurve;Lorg/bouncycastle/math/ec/ECPoint;Ljava/math/BigInteger;Ljava/math/BigInteger;)V", false);
methodVisitor.visitVarInsn(ASTORE, 3);
methodVisitor.visitFieldInsn(GETSTATIC, "org/bouncycastle/asn1/cryptopro/ECGOST3410NamedCurves", "params", "Ljava/util/Hashtable;");
methodVisitor.visitFieldInsn(GETSTATIC, "org/bouncycastle/asn1/cryptopro/CryptoProObjectIdentifiers", "gostR3410_2001_CryptoPro_C", "Lorg/bouncycastle/asn1/ASN1ObjectIdentifier;");
methodVisitor.visitVarInsn(ALOAD, 3);
methodVisitor.visitMethodInsn(INVOKEVIRTUAL, "java/util/Hashtable", "put", "(Ljava/lang/Object;Ljava/lang/Object;)Ljava/lang/Object;", false);
methodVisitor.visitInsn(POP);
methodVisitor.visitTypeInsn(NEW, "java/math/BigInteger");
methodVisitor.visitInsn(DUP);
methodVisitor.visitLdcInsn("FFFFFFFFFFFFFFFFFFFFFFFFFFFFFFFFFFFFFFFFFFFFFFFFFFFFFFFFFFFFFD97");
methodVisitor.visitIntInsn(BIPUSH, 16);
methodVisitor.visitMethodInsn(INVOKESPECIAL, "java/math/BigInteger", "<init>", "(Ljava/lang/String;I)V", false);
methodVisitor.visitVarInsn(ASTORE, 0);
methodVisitor.visitTypeInsn(NEW, "java/math/BigInteger");
methodVisitor.visitInsn(DUP);
methodVisitor.visitLdcInsn("400000000000000000000000000000000FD8CDDFC87B6635C115AF556C360C67");
methodVisitor.visitIntInsn(BIPUSH, 16);
methodVisitor.visitMethodInsn(INVOKESPECIAL, "java/math/BigInteger", "<init>", "(Ljava/lang/String;I)V", false);
methodVisitor.visitVarInsn(ASTORE, 1);
methodVisitor.visitTypeInsn(NEW, "org/bouncycastle/math/ec/ECCurve$Fp");
methodVisitor.visitInsn(DUP);
methodVisitor.visitVarInsn(ALOAD, 0);
methodVisitor.visitTypeInsn(NEW, "java/math/BigInteger");
methodVisitor.visitInsn(DUP);
methodVisitor.visitLdcInsn("C2173F1513981673AF4892C23035A27CE25E2013BF95AA33B22C656F277E7335");
methodVisitor.visitIntInsn(BIPUSH, 16);
methodVisitor.visitMethodInsn(INVOKESPECIAL, "java/math/BigInteger", "<init>", "(Ljava/lang/String;I)V", false);
methodVisitor.visitTypeInsn(NEW, "java/math/BigInteger");
methodVisitor.visitInsn(DUP);
methodVisitor.visitLdcInsn("295F9BAE7428ED9CCC20E7C359A9D41A22FCCD9108E17BF7BA9337A6F8AE9513");
methodVisitor.visitIntInsn(BIPUSH, 16);
methodVisitor.visitMethodInsn(INVOKESPECIAL, "java/math/BigInteger", "<init>", "(Ljava/lang/String;I)V", false);
methodVisitor.visitVarInsn(ALOAD, 1);
methodVisitor.visitFieldInsn(GETSTATIC, "org/bouncycastle/math/ec/ECConstants", "FOUR", "Ljava/math/BigInteger;");
methodVisitor.visitMethodInsn(INVOKESPECIAL, "org/bouncycastle/math/ec/ECCurve$Fp", "<init>", "(Ljava/math/BigInteger;Ljava/math/BigInteger;Ljava/math/BigInteger;Ljava/math/BigInteger;Ljava/math/BigInteger;)V", false);
methodVisitor.visitMethodInsn(INVOKESTATIC, "org/bouncycastle/asn1/cryptopro/ECGOST3410NamedCurves", "configureCurve", "(Lorg/bouncycastle/math/ec/ECCurve;)Lorg/bouncycastle/math/ec/ECCurve;", false);
methodVisitor.visitVarInsn(ASTORE, 2);
methodVisitor.visitTypeInsn(NEW, "org/bouncycastle/crypto/params/ECDomainParameters");
methodVisitor.visitInsn(DUP);
methodVisitor.visitVarInsn(ALOAD, 2);
methodVisitor.visitVarInsn(ALOAD, 2);
methodVisitor.visitTypeInsn(NEW, "java/math/BigInteger");
methodVisitor.visitInsn(DUP);
methodVisitor.visitLdcInsn("91E38443A5E82C0D880923425712B2BB658B9196932E02C78B2582FE742DAA28");
methodVisitor.visitIntInsn(BIPUSH, 16);
methodVisitor.visitMethodInsn(INVOKESPECIAL, "java/math/BigInteger", "<init>", "(Ljava/lang/String;I)V", false);
methodVisitor.visitTypeInsn(NEW, "java/math/BigInteger");
methodVisitor.visitInsn(DUP);
methodVisitor.visitLdcInsn("32879423AB1A0375895786C4BB46E9565FDE0B5344766740AF268ADB32322E5C");
methodVisitor.visitIntInsn(BIPUSH, 16);
methodVisitor.visitMethodInsn(INVOKESPECIAL, "java/math/BigInteger", "<init>", "(Ljava/lang/String;I)V", false);
methodVisitor.visitMethodInsn(INVOKESTATIC, "org/bouncycastle/asn1/cryptopro/ECGOST3410NamedCurves", "configureBasepoint", "(Lorg/bouncycastle/math/ec/ECCurve;Ljava/math/BigInteger;Ljava/math/BigInteger;)Lorg/bouncycastle/math/ec/ECPoint;", false);
methodVisitor.visitVarInsn(ALOAD, 1);
methodVisitor.visitFieldInsn(GETSTATIC, "org/bouncycastle/math/ec/ECConstants", "FOUR", "Ljava/math/BigInteger;");
methodVisitor.visitMethodInsn(INVOKESPECIAL, "org/bouncycastle/crypto/params/ECDomainParameters", "<init>", "(Lorg/bouncycastle/math/ec/ECCurve;Lorg/bouncycastle/math/ec/ECPoint;Ljava/math/BigInteger;Ljava/math/BigInteger;)V", false);
methodVisitor.visitVarInsn(ASTORE, 3);
methodVisitor.visitFieldInsn(GETSTATIC, "org/bouncycastle/asn1/cryptopro/ECGOST3410NamedCurves", "params", "Ljava/util/Hashtable;");
methodVisitor.visitFieldInsn(GETSTATIC, "org/bouncycastle/asn1/rosstandart/RosstandartObjectIdentifiers", "id_tc26_gost_3410_12_256_paramSetA", "Lorg/bouncycastle/asn1/ASN1ObjectIdentifier;");
methodVisitor.visitVarInsn(ALOAD, 3);
methodVisitor.visitMethodInsn(INVOKEVIRTUAL, "java/util/Hashtable", "put", "(Ljava/lang/Object;Ljava/lang/Object;)Ljava/lang/Object;", false);
methodVisitor.visitInsn(POP);
methodVisitor.visitTypeInsn(NEW, "java/math/BigInteger");
methodVisitor.visitInsn(DUP);
methodVisitor.visitLdcInsn("FFFFFFFFFFFFFFFFFFFFFFFFFFFFFFFFFFFFFFFFFFFFFFFFFFFFFFFFFFFFFFFFFFFFFFFFFFFFFFFFFFFFFFFFFFFFFFFFFFFFFFFFFFFFFFFFFFFFFFFFFFFFFDC7");
methodVisitor.visitIntInsn(BIPUSH, 16);
methodVisitor.visitMethodInsn(INVOKESPECIAL, "java/math/BigInteger", "<init>", "(Ljava/lang/String;I)V", false);
methodVisitor.visitVarInsn(ASTORE, 0);
methodVisitor.visitTypeInsn(NEW, "java/math/BigInteger");
methodVisitor.visitInsn(DUP);
methodVisitor.visitLdcInsn("FFFFFFFFFFFFFFFFFFFFFFFFFFFFFFFFFFFFFFFFFFFFFFFFFFFFFFFFFFFFFFFF27E69532F48D89116FF22B8D4E0560609B4B38ABFAD2B85DCACDB1411F10B275");
methodVisitor.visitIntInsn(BIPUSH, 16);
methodVisitor.visitMethodInsn(INVOKESPECIAL, "java/math/BigInteger", "<init>", "(Ljava/lang/String;I)V", false);
methodVisitor.visitVarInsn(ASTORE, 1);
methodVisitor.visitTypeInsn(NEW, "org/bouncycastle/math/ec/ECCurve$Fp");
methodVisitor.visitInsn(DUP);
methodVisitor.visitVarInsn(ALOAD, 0);
methodVisitor.visitTypeInsn(NEW, "java/math/BigInteger");
methodVisitor.visitInsn(DUP);
methodVisitor.visitLdcInsn("FFFFFFFFFFFFFFFFFFFFFFFFFFFFFFFFFFFFFFFFFFFFFFFFFFFFFFFFFFFFFFFFFFFFFFFFFFFFFFFFFFFFFFFFFFFFFFFFFFFFFFFFFFFFFFFFFFFFFFFFFFFFFDC4");
methodVisitor.visitIntInsn(BIPUSH, 16);
methodVisitor.visitMethodInsn(INVOKESPECIAL, "java/math/BigInteger", "<init>", "(Ljava/lang/String;I)V", false);
methodVisitor.visitTypeInsn(NEW, "java/math/BigInteger");
methodVisitor.visitInsn(DUP);
methodVisitor.visitLdcInsn("E8C2505DEDFC86DDC1BD0B2B6667F1DA34B82574761CB0E879BD081CFD0B6265EE3CB090F30D27614CB4574010DA90DD862EF9D4EBEE4761503190785A71C760");
methodVisitor.visitIntInsn(BIPUSH, 16);
methodVisitor.visitMethodInsn(INVOKESPECIAL, "java/math/BigInteger", "<init>", "(Ljava/lang/String;I)V", false);
methodVisitor.visitVarInsn(ALOAD, 1);
methodVisitor.visitFieldInsn(GETSTATIC, "org/bouncycastle/math/ec/ECConstants", "ONE", "Ljava/math/BigInteger;");
methodVisitor.visitMethodInsn(INVOKESPECIAL, "org/bouncycastle/math/ec/ECCurve$Fp", "<init>", "(Ljava/math/BigInteger;Ljava/math/BigInteger;Ljava/math/BigInteger;Ljava/math/BigInteger;Ljava/math/BigInteger;)V", false);
methodVisitor.visitMethodInsn(INVOKESTATIC, "org/bouncycastle/asn1/cryptopro/ECGOST3410NamedCurves", "configureCurve", "(Lorg/bouncycastle/math/ec/ECCurve;)Lorg/bouncycastle/math/ec/ECCurve;", false);
methodVisitor.visitVarInsn(ASTORE, 2);
methodVisitor.visitTypeInsn(NEW, "org/bouncycastle/crypto/params/ECDomainParameters");
methodVisitor.visitInsn(DUP);
methodVisitor.visitVarInsn(ALOAD, 2);
methodVisitor.visitVarInsn(ALOAD, 2);
methodVisitor.visitTypeInsn(NEW, "java/math/BigInteger");
methodVisitor.visitInsn(DUP);
methodVisitor.visitLdcInsn("00000000000000000000000000000000000000000000000000000000000000000000000000000000000000000000000000000000000000000000000000000003");
methodVisitor.visitMethodInsn(INVOKESPECIAL, "java/math/BigInteger", "<init>", "(Ljava/lang/String;)V", false);
methodVisitor.visitTypeInsn(NEW, "java/math/BigInteger");
methodVisitor.visitInsn(DUP);
methodVisitor.visitLdcInsn("7503CFE87A836AE3A61B8816E25450E6CE5E1C93ACF1ABC1778064FDCBEFA921DF1626BE4FD036E93D75E6A50E3A41E98028FE5FC235F5B889A589CB5215F2A4");
methodVisitor.visitIntInsn(BIPUSH, 16);
methodVisitor.visitMethodInsn(INVOKESPECIAL, "java/math/BigInteger", "<init>", "(Ljava/lang/String;I)V", false);
methodVisitor.visitMethodInsn(INVOKESTATIC, "org/bouncycastle/asn1/cryptopro/ECGOST3410NamedCurves", "configureBasepoint", "(Lorg/bouncycastle/math/ec/ECCurve;Ljava/math/BigInteger;Ljava/math/BigInteger;)Lorg/bouncycastle/math/ec/ECPoint;", false);
methodVisitor.visitVarInsn(ALOAD, 1);
methodVisitor.visitFieldInsn(GETSTATIC, "org/bouncycastle/math/ec/ECConstants", "ONE", "Ljava/math/BigInteger;");
methodVisitor.visitMethodInsn(INVOKESPECIAL, "org/bouncycastle/crypto/params/ECDomainParameters", "<init>", "(Lorg/bouncycastle/math/ec/ECCurve;Lorg/bouncycastle/math/ec/ECPoint;Ljava/math/BigInteger;Ljava/math/BigInteger;)V", false);
methodVisitor.visitVarInsn(ASTORE, 3);
methodVisitor.visitFieldInsn(GETSTATIC, "org/bouncycastle/asn1/cryptopro/ECGOST3410NamedCurves", "params", "Ljava/util/Hashtable;");
methodVisitor.visitFieldInsn(GETSTATIC, "org/bouncycastle/asn1/rosstandart/RosstandartObjectIdentifiers", "id_tc26_gost_3410_12_512_paramSetA", "Lorg/bouncycastle/asn1/ASN1ObjectIdentifier;");
methodVisitor.visitVarInsn(ALOAD, 3);
methodVisitor.visitMethodInsn(INVOKEVIRTUAL, "java/util/Hashtable", "put", "(Ljava/lang/Object;Ljava/lang/Object;)Ljava/lang/Object;", false);
methodVisitor.visitInsn(POP);
methodVisitor.visitTypeInsn(NEW, "java/math/BigInteger");
methodVisitor.visitInsn(DUP);
methodVisitor.visitLdcInsn("8000000000000000000000000000000000000000000000000000000000000000000000000000000000000000000000000000000000000000000000000000006F");
methodVisitor.visitIntInsn(BIPUSH, 16);
methodVisitor.visitMethodInsn(INVOKESPECIAL, "java/math/BigInteger", "<init>", "(Ljava/lang/String;I)V", false);
methodVisitor.visitVarInsn(ASTORE, 0);
methodVisitor.visitTypeInsn(NEW, "java/math/BigInteger");
methodVisitor.visitInsn(DUP);
methodVisitor.visitLdcInsn("800000000000000000000000000000000000000000000000000000000000000149A1EC142565A545ACFDB77BD9D40CFA8B996712101BEA0EC6346C54374F25BD");
methodVisitor.visitIntInsn(BIPUSH, 16);
methodVisitor.visitMethodInsn(INVOKESPECIAL, "java/math/BigInteger", "<init>", "(Ljava/lang/String;I)V", false);
methodVisitor.visitVarInsn(ASTORE, 1);
methodVisitor.visitTypeInsn(NEW, "org/bouncycastle/math/ec/ECCurve$Fp");
methodVisitor.visitInsn(DUP);
methodVisitor.visitVarInsn(ALOAD, 0);
methodVisitor.visitTypeInsn(NEW, "java/math/BigInteger");
methodVisitor.visitInsn(DUP);
methodVisitor.visitLdcInsn("8000000000000000000000000000000000000000000000000000000000000000000000000000000000000000000000000000000000000000000000000000006C");
methodVisitor.visitIntInsn(BIPUSH, 16);
methodVisitor.visitMethodInsn(INVOKESPECIAL, "java/math/BigInteger", "<init>", "(Ljava/lang/String;I)V", false);
methodVisitor.visitTypeInsn(NEW, "java/math/BigInteger");
methodVisitor.visitInsn(DUP);
methodVisitor.visitLdcInsn("687D1B459DC841457E3E06CF6F5E2517B97C7D614AF138BCBF85DC806C4B289F3E965D2DB1416D217F8B276FAD1AB69C50F78BEE1FA3106EFB8CCBC7C5140116");
methodVisitor.visitIntInsn(BIPUSH, 16);
methodVisitor.visitMethodInsn(INVOKESPECIAL, "java/math/BigInteger", "<init>", "(Ljava/lang/String;I)V", false);
methodVisitor.visitVarInsn(ALOAD, 1);
methodVisitor.visitFieldInsn(GETSTATIC, "org/bouncycastle/math/ec/ECConstants", "ONE", "Ljava/math/BigInteger;");
methodVisitor.visitMethodInsn(INVOKESPECIAL, "org/bouncycastle/math/ec/ECCurve$Fp", "<init>", "(Ljava/math/BigInteger;Ljava/math/BigInteger;Ljava/math/BigInteger;Ljava/math/BigInteger;Ljava/math/BigInteger;)V", false);
methodVisitor.visitMethodInsn(INVOKESTATIC, "org/bouncycastle/asn1/cryptopro/ECGOST3410NamedCurves", "configureCurve", "(Lorg/bouncycastle/math/ec/ECCurve;)Lorg/bouncycastle/math/ec/ECCurve;", false);
methodVisitor.visitVarInsn(ASTORE, 2);
methodVisitor.visitTypeInsn(NEW, "org/bouncycastle/crypto/params/ECDomainParameters");
methodVisitor.visitInsn(DUP);
methodVisitor.visitVarInsn(ALOAD, 2);
methodVisitor.visitVarInsn(ALOAD, 2);
methodVisitor.visitTypeInsn(NEW, "java/math/BigInteger");
methodVisitor.visitInsn(DUP);
methodVisitor.visitLdcInsn("00000000000000000000000000000000000000000000000000000000000000000000000000000000000000000000000000000000000000000000000000000002");
methodVisitor.visitMethodInsn(INVOKESPECIAL, "java/math/BigInteger", "<init>", "(Ljava/lang/String;)V", false);
methodVisitor.visitTypeInsn(NEW, "java/math/BigInteger");
methodVisitor.visitInsn(DUP);
methodVisitor.visitLdcInsn("1A8F7EDA389B094C2C071E3647A8940F3C123B697578C213BE6DD9E6C8EC7335DCB228FD1EDF4A39152CBCAAF8C0398828041055F94CEEEC7E21340780FE41BD");
methodVisitor.visitIntInsn(BIPUSH, 16);
methodVisitor.visitMethodInsn(INVOKESPECIAL, "java/math/BigInteger", "<init>", "(Ljava/lang/String;I)V", false);
methodVisitor.visitMethodInsn(INVOKESTATIC, "org/bouncycastle/asn1/cryptopro/ECGOST3410NamedCurves", "configureBasepoint", "(Lorg/bouncycastle/math/ec/ECCurve;Ljava/math/BigInteger;Ljava/math/BigInteger;)Lorg/bouncycastle/math/ec/ECPoint;", false);
methodVisitor.visitVarInsn(ALOAD, 1);
methodVisitor.visitFieldInsn(GETSTATIC, "org/bouncycastle/math/ec/ECConstants", "ONE", "Ljava/math/BigInteger;");
methodVisitor.visitMethodInsn(INVOKESPECIAL, "org/bouncycastle/crypto/params/ECDomainParameters", "<init>", "(Lorg/bouncycastle/math/ec/ECCurve;Lorg/bouncycastle/math/ec/ECPoint;Ljava/math/BigInteger;Ljava/math/BigInteger;)V", false);
methodVisitor.visitVarInsn(ASTORE, 3);
methodVisitor.visitFieldInsn(GETSTATIC, "org/bouncycastle/asn1/cryptopro/ECGOST3410NamedCurves", "params", "Ljava/util/Hashtable;");
methodVisitor.visitFieldInsn(GETSTATIC, "org/bouncycastle/asn1/rosstandart/RosstandartObjectIdentifiers", "id_tc26_gost_3410_12_512_paramSetB", "Lorg/bouncycastle/asn1/ASN1ObjectIdentifier;");
methodVisitor.visitVarInsn(ALOAD, 3);
methodVisitor.visitMethodInsn(INVOKEVIRTUAL, "java/util/Hashtable", "put", "(Ljava/lang/Object;Ljava/lang/Object;)Ljava/lang/Object;", false);
methodVisitor.visitInsn(POP);
methodVisitor.visitTypeInsn(NEW, "java/math/BigInteger");
methodVisitor.visitInsn(DUP);
methodVisitor.visitLdcInsn("FFFFFFFFFFFFFFFFFFFFFFFFFFFFFFFFFFFFFFFFFFFFFFFFFFFFFFFFFFFFFFFFFFFFFFFFFFFFFFFFFFFFFFFFFFFFFFFFFFFFFFFFFFFFFFFFFFFFFFFFFFFFFDC7");
methodVisitor.visitIntInsn(BIPUSH, 16);
methodVisitor.visitMethodInsn(INVOKESPECIAL, "java/math/BigInteger", "<init>", "(Ljava/lang/String;I)V", false);
methodVisitor.visitVarInsn(ASTORE, 0);
methodVisitor.visitTypeInsn(NEW, "java/math/BigInteger");
methodVisitor.visitInsn(DUP);
methodVisitor.visitLdcInsn("3FFFFFFFFFFFFFFFFFFFFFFFFFFFFFFFFFFFFFFFFFFFFFFFFFFFFFFFFFFFFFFFC98CDBA46506AB004C33A9FF5147502CC8EDA9E7A769A12694623CEF47F023ED");
methodVisitor.visitIntInsn(BIPUSH, 16);
methodVisitor.visitMethodInsn(INVOKESPECIAL, "java/math/BigInteger", "<init>", "(Ljava/lang/String;I)V", false);
methodVisitor.visitVarInsn(ASTORE, 1);
methodVisitor.visitTypeInsn(NEW, "org/bouncycastle/math/ec/ECCurve$Fp");
methodVisitor.visitInsn(DUP);
methodVisitor.visitVarInsn(ALOAD, 0);
methodVisitor.visitTypeInsn(NEW, "java/math/BigInteger");
methodVisitor.visitInsn(DUP);
methodVisitor.visitLdcInsn("DC9203E514A721875485A529D2C722FB187BC8980EB866644DE41C68E143064546E861C0E2C9EDD92ADE71F46FCF50FF2AD97F951FDA9F2A2EB6546F39689BD3");
methodVisitor.visitIntInsn(BIPUSH, 16);
methodVisitor.visitMethodInsn(INVOKESPECIAL, "java/math/BigInteger", "<init>", "(Ljava/lang/String;I)V", false);
methodVisitor.visitTypeInsn(NEW, "java/math/BigInteger");
methodVisitor.visitInsn(DUP);
methodVisitor.visitLdcInsn("B4C4EE28CEBC6C2C8AC12952CF37F16AC7EFB6A9F69F4B57FFDA2E4F0DE5ADE038CBC2FFF719D2C18DE0284B8BFEF3B52B8CC7A5F5BF0A3C8D2319A5312557E1");
methodVisitor.visitIntInsn(BIPUSH, 16);
methodVisitor.visitMethodInsn(INVOKESPECIAL, "java/math/BigInteger", "<init>", "(Ljava/lang/String;I)V", false);
methodVisitor.visitVarInsn(ALOAD, 1);
methodVisitor.visitFieldInsn(GETSTATIC, "org/bouncycastle/math/ec/ECConstants", "FOUR", "Ljava/math/BigInteger;");
methodVisitor.visitMethodInsn(INVOKESPECIAL, "org/bouncycastle/math/ec/ECCurve$Fp", "<init>", "(Ljava/math/BigInteger;Ljava/math/BigInteger;Ljava/math/BigInteger;Ljava/math/BigInteger;Ljava/math/BigInteger;)V", false);
methodVisitor.visitMethodInsn(INVOKESTATIC, "org/bouncycastle/asn1/cryptopro/ECGOST3410NamedCurves", "configureCurve", "(Lorg/bouncycastle/math/ec/ECCurve;)Lorg/bouncycastle/math/ec/ECCurve;", false);
methodVisitor.visitVarInsn(ASTORE, 2);
methodVisitor.visitTypeInsn(NEW, "org/bouncycastle/crypto/params/ECDomainParameters");
methodVisitor.visitInsn(DUP);
methodVisitor.visitVarInsn(ALOAD, 2);
methodVisitor.visitVarInsn(ALOAD, 2);
methodVisitor.visitTypeInsn(NEW, "java/math/BigInteger");
methodVisitor.visitInsn(DUP);
methodVisitor.visitLdcInsn("E2E31EDFC23DE7BDEBE241CE593EF5DE2295B7A9CBAEF021D385F7074CEA043AA27272A7AE602BF2A7B9033DB9ED3610C6FB85487EAE97AAC5BC7928C1950148");
methodVisitor.visitIntInsn(BIPUSH, 16);
methodVisitor.visitMethodInsn(INVOKESPECIAL, "java/math/BigInteger", "<init>", "(Ljava/lang/String;I)V", false);
methodVisitor.visitTypeInsn(NEW, "java/math/BigInteger");
methodVisitor.visitInsn(DUP);
methodVisitor.visitLdcInsn("F5CE40D95B5EB899ABBCCFF5911CB8577939804D6527378B8C108C3D2090FF9BE18E2D33E3021ED2EF32D85822423B6304F726AA854BAE07D0396E9A9ADDC40F");
methodVisitor.visitIntInsn(BIPUSH, 16);
methodVisitor.visitMethodInsn(INVOKESPECIAL, "java/math/BigInteger", "<init>", "(Ljava/lang/String;I)V", false);
methodVisitor.visitMethodInsn(INVOKESTATIC, "org/bouncycastle/asn1/cryptopro/ECGOST3410NamedCurves", "configureBasepoint", "(Lorg/bouncycastle/math/ec/ECCurve;Ljava/math/BigInteger;Ljava/math/BigInteger;)Lorg/bouncycastle/math/ec/ECPoint;", false);
methodVisitor.visitVarInsn(ALOAD, 1);
methodVisitor.visitFieldInsn(GETSTATIC, "org/bouncycastle/math/ec/ECConstants", "FOUR", "Ljava/math/BigInteger;");
methodVisitor.visitMethodInsn(INVOKESPECIAL, "org/bouncycastle/crypto/params/ECDomainParameters", "<init>", "(Lorg/bouncycastle/math/ec/ECCurve;Lorg/bouncycastle/math/ec/ECPoint;Ljava/math/BigInteger;Ljava/math/BigInteger;)V", false);
methodVisitor.visitVarInsn(ASTORE, 3);
methodVisitor.visitFieldInsn(GETSTATIC, "org/bouncycastle/asn1/cryptopro/ECGOST3410NamedCurves", "params", "Ljava/util/Hashtable;");
methodVisitor.visitFieldInsn(GETSTATIC, "org/bouncycastle/asn1/rosstandart/RosstandartObjectIdentifiers", "id_tc26_gost_3410_12_512_paramSetC", "Lorg/bouncycastle/asn1/ASN1ObjectIdentifier;");
methodVisitor.visitVarInsn(ALOAD, 3);
methodVisitor.visitMethodInsn(INVOKEVIRTUAL, "java/util/Hashtable", "put", "(Ljava/lang/Object;Ljava/lang/Object;)Ljava/lang/Object;", false);
methodVisitor.visitInsn(POP);
methodVisitor.visitFieldInsn(GETSTATIC, "org/bouncycastle/asn1/cryptopro/ECGOST3410NamedCurves", "objIds", "Ljava/util/Hashtable;");
methodVisitor.visitLdcInsn("GostR3410-2001-CryptoPro-A");
methodVisitor.visitFieldInsn(GETSTATIC, "org/bouncycastle/asn1/cryptopro/CryptoProObjectIdentifiers", "gostR3410_2001_CryptoPro_A", "Lorg/bouncycastle/asn1/ASN1ObjectIdentifier;");
methodVisitor.visitMethodInsn(INVOKEVIRTUAL, "java/util/Hashtable", "put", "(Ljava/lang/Object;Ljava/lang/Object;)Ljava/lang/Object;", false);
methodVisitor.visitInsn(POP);
methodVisitor.visitFieldInsn(GETSTATIC, "org/bouncycastle/asn1/cryptopro/ECGOST3410NamedCurves", "objIds", "Ljava/util/Hashtable;");
methodVisitor.visitLdcInsn("GostR3410-2001-CryptoPro-B");
methodVisitor.visitFieldInsn(GETSTATIC, "org/bouncycastle/asn1/cryptopro/CryptoProObjectIdentifiers", "gostR3410_2001_CryptoPro_B", "Lorg/bouncycastle/asn1/ASN1ObjectIdentifier;");
methodVisitor.visitMethodInsn(INVOKEVIRTUAL, "java/util/Hashtable", "put", "(Ljava/lang/Object;Ljava/lang/Object;)Ljava/lang/Object;", false);
methodVisitor.visitInsn(POP);
methodVisitor.visitFieldInsn(GETSTATIC, "org/bouncycastle/asn1/cryptopro/ECGOST3410NamedCurves", "objIds", "Ljava/util/Hashtable;");
methodVisitor.visitLdcInsn("GostR3410-2001-CryptoPro-C");
methodVisitor.visitFieldInsn(GETSTATIC, "org/bouncycastle/asn1/cryptopro/CryptoProObjectIdentifiers", "gostR3410_2001_CryptoPro_C", "Lorg/bouncycastle/asn1/ASN1ObjectIdentifier;");
methodVisitor.visitMethodInsn(INVOKEVIRTUAL, "java/util/Hashtable", "put", "(Ljava/lang/Object;Ljava/lang/Object;)Ljava/lang/Object;", false);
methodVisitor.visitInsn(POP);
methodVisitor.visitFieldInsn(GETSTATIC, "org/bouncycastle/asn1/cryptopro/ECGOST3410NamedCurves", "objIds", "Ljava/util/Hashtable;");
methodVisitor.visitLdcInsn("GostR3410-2001-CryptoPro-XchA");
methodVisitor.visitFieldInsn(GETSTATIC, "org/bouncycastle/asn1/cryptopro/CryptoProObjectIdentifiers", "gostR3410_2001_CryptoPro_XchA", "Lorg/bouncycastle/asn1/ASN1ObjectIdentifier;");
methodVisitor.visitMethodInsn(INVOKEVIRTUAL, "java/util/Hashtable", "put", "(Ljava/lang/Object;Ljava/lang/Object;)Ljava/lang/Object;", false);
methodVisitor.visitInsn(POP);
methodVisitor.visitFieldInsn(GETSTATIC, "org/bouncycastle/asn1/cryptopro/ECGOST3410NamedCurves", "objIds", "Ljava/util/Hashtable;");
methodVisitor.visitLdcInsn("GostR3410-2001-CryptoPro-XchB");
methodVisitor.visitFieldInsn(GETSTATIC, "org/bouncycastle/asn1/cryptopro/CryptoProObjectIdentifiers", "gostR3410_2001_CryptoPro_XchB", "Lorg/bouncycastle/asn1/ASN1ObjectIdentifier;");
methodVisitor.visitMethodInsn(INVOKEVIRTUAL, "java/util/Hashtable", "put", "(Ljava/lang/Object;Ljava/lang/Object;)Ljava/lang/Object;", false);
methodVisitor.visitInsn(POP);
methodVisitor.visitFieldInsn(GETSTATIC, "org/bouncycastle/asn1/cryptopro/ECGOST3410NamedCurves", "objIds", "Ljava/util/Hashtable;");
methodVisitor.visitLdcInsn("Tc26-Gost-3410-12-256-paramSetA");
methodVisitor.visitFieldInsn(GETSTATIC, "org/bouncycastle/asn1/rosstandart/RosstandartObjectIdentifiers", "id_tc26_gost_3410_12_256_paramSetA", "Lorg/bouncycastle/asn1/ASN1ObjectIdentifier;");
methodVisitor.visitMethodInsn(INVOKEVIRTUAL, "java/util/Hashtable", "put", "(Ljava/lang/Object;Ljava/lang/Object;)Ljava/lang/Object;", false);
methodVisitor.visitInsn(POP);
methodVisitor.visitFieldInsn(GETSTATIC, "org/bouncycastle/asn1/cryptopro/ECGOST3410NamedCurves", "objIds", "Ljava/util/Hashtable;");
methodVisitor.visitLdcInsn("Tc26-Gost-3410-12-512-paramSetA");
methodVisitor.visitFieldInsn(GETSTATIC, "org/bouncycastle/asn1/rosstandart/RosstandartObjectIdentifiers", "id_tc26_gost_3410_12_512_paramSetA", "Lorg/bouncycastle/asn1/ASN1ObjectIdentifier;");
methodVisitor.visitMethodInsn(INVOKEVIRTUAL, "java/util/Hashtable", "put", "(Ljava/lang/Object;Ljava/lang/Object;)Ljava/lang/Object;", false);
methodVisitor.visitInsn(POP);
methodVisitor.visitFieldInsn(GETSTATIC, "org/bouncycastle/asn1/cryptopro/ECGOST3410NamedCurves", "objIds", "Ljava/util/Hashtable;");
methodVisitor.visitLdcInsn("Tc26-Gost-3410-12-512-paramSetB");
methodVisitor.visitFieldInsn(GETSTATIC, "org/bouncycastle/asn1/rosstandart/RosstandartObjectIdentifiers", "id_tc26_gost_3410_12_512_paramSetB", "Lorg/bouncycastle/asn1/ASN1ObjectIdentifier;");
methodVisitor.visitMethodInsn(INVOKEVIRTUAL, "java/util/Hashtable", "put", "(Ljava/lang/Object;Ljava/lang/Object;)Ljava/lang/Object;", false);
methodVisitor.visitInsn(POP);
methodVisitor.visitFieldInsn(GETSTATIC, "org/bouncycastle/asn1/cryptopro/ECGOST3410NamedCurves", "objIds", "Ljava/util/Hashtable;");
methodVisitor.visitLdcInsn("Tc26-Gost-3410-12-512-paramSetC");
methodVisitor.visitFieldInsn(GETSTATIC, "org/bouncycastle/asn1/rosstandart/RosstandartObjectIdentifiers", "id_tc26_gost_3410_12_512_paramSetC", "Lorg/bouncycastle/asn1/ASN1ObjectIdentifier;");
methodVisitor.visitMethodInsn(INVOKEVIRTUAL, "java/util/Hashtable", "put", "(Ljava/lang/Object;Ljava/lang/Object;)Ljava/lang/Object;", false);
methodVisitor.visitInsn(POP);
methodVisitor.visitFieldInsn(GETSTATIC, "org/bouncycastle/asn1/cryptopro/ECGOST3410NamedCurves", "names", "Ljava/util/Hashtable;");
methodVisitor.visitFieldInsn(GETSTATIC, "org/bouncycastle/asn1/cryptopro/CryptoProObjectIdentifiers", "gostR3410_2001_CryptoPro_A", "Lorg/bouncycastle/asn1/ASN1ObjectIdentifier;");
methodVisitor.visitLdcInsn("GostR3410-2001-CryptoPro-A");
methodVisitor.visitMethodInsn(INVOKEVIRTUAL, "java/util/Hashtable", "put", "(Ljava/lang/Object;Ljava/lang/Object;)Ljava/lang/Object;", false);
methodVisitor.visitInsn(POP);
methodVisitor.visitFieldInsn(GETSTATIC, "org/bouncycastle/asn1/cryptopro/ECGOST3410NamedCurves", "names", "Ljava/util/Hashtable;");
methodVisitor.visitFieldInsn(GETSTATIC, "org/bouncycastle/asn1/cryptopro/CryptoProObjectIdentifiers", "gostR3410_2001_CryptoPro_B", "Lorg/bouncycastle/asn1/ASN1ObjectIdentifier;");
methodVisitor.visitLdcInsn("GostR3410-2001-CryptoPro-B");
methodVisitor.visitMethodInsn(INVOKEVIRTUAL, "java/util/Hashtable", "put", "(Ljava/lang/Object;Ljava/lang/Object;)Ljava/lang/Object;", false);
methodVisitor.visitInsn(POP);
methodVisitor.visitFieldInsn(GETSTATIC, "org/bouncycastle/asn1/cryptopro/ECGOST3410NamedCurves", "names", "Ljava/util/Hashtable;");
methodVisitor.visitFieldInsn(GETSTATIC, "org/bouncycastle/asn1/cryptopro/CryptoProObjectIdentifiers", "gostR3410_2001_CryptoPro_C", "Lorg/bouncycastle/asn1/ASN1ObjectIdentifier;");
methodVisitor.visitLdcInsn("GostR3410-2001-CryptoPro-C");
methodVisitor.visitMethodInsn(INVOKEVIRTUAL, "java/util/Hashtable", "put", "(Ljava/lang/Object;Ljava/lang/Object;)Ljava/lang/Object;", false);
methodVisitor.visitInsn(POP);
methodVisitor.visitFieldInsn(GETSTATIC, "org/bouncycastle/asn1/cryptopro/ECGOST3410NamedCurves", "names", "Ljava/util/Hashtable;");
methodVisitor.visitFieldInsn(GETSTATIC, "org/bouncycastle/asn1/cryptopro/CryptoProObjectIdentifiers", "gostR3410_2001_CryptoPro_XchA", "Lorg/bouncycastle/asn1/ASN1ObjectIdentifier;");
methodVisitor.visitLdcInsn("GostR3410-2001-CryptoPro-XchA");
methodVisitor.visitMethodInsn(INVOKEVIRTUAL, "java/util/Hashtable", "put", "(Ljava/lang/Object;Ljava/lang/Object;)Ljava/lang/Object;", false);
methodVisitor.visitInsn(POP);
methodVisitor.visitFieldInsn(GETSTATIC, "org/bouncycastle/asn1/cryptopro/ECGOST3410NamedCurves", "names", "Ljava/util/Hashtable;");
methodVisitor.visitFieldInsn(GETSTATIC, "org/bouncycastle/asn1/cryptopro/CryptoProObjectIdentifiers", "gostR3410_2001_CryptoPro_XchB", "Lorg/bouncycastle/asn1/ASN1ObjectIdentifier;");
methodVisitor.visitLdcInsn("GostR3410-2001-CryptoPro-XchB");
methodVisitor.visitMethodInsn(INVOKEVIRTUAL, "java/util/Hashtable", "put", "(Ljava/lang/Object;Ljava/lang/Object;)Ljava/lang/Object;", false);
methodVisitor.visitInsn(POP);
methodVisitor.visitFieldInsn(GETSTATIC, "org/bouncycastle/asn1/cryptopro/ECGOST3410NamedCurves", "names", "Ljava/util/Hashtable;");
methodVisitor.visitFieldInsn(GETSTATIC, "org/bouncycastle/asn1/rosstandart/RosstandartObjectIdentifiers", "id_tc26_gost_3410_12_256_paramSetA", "Lorg/bouncycastle/asn1/ASN1ObjectIdentifier;");
methodVisitor.visitLdcInsn("Tc26-Gost-3410-12-256-paramSetA");
methodVisitor.visitMethodInsn(INVOKEVIRTUAL, "java/util/Hashtable", "put", "(Ljava/lang/Object;Ljava/lang/Object;)Ljava/lang/Object;", false);
methodVisitor.visitInsn(POP);
methodVisitor.visitFieldInsn(GETSTATIC, "org/bouncycastle/asn1/cryptopro/ECGOST3410NamedCurves", "names", "Ljava/util/Hashtable;");
methodVisitor.visitFieldInsn(GETSTATIC, "org/bouncycastle/asn1/rosstandart/RosstandartObjectIdentifiers", "id_tc26_gost_3410_12_512_paramSetA", "Lorg/bouncycastle/asn1/ASN1ObjectIdentifier;");
methodVisitor.visitLdcInsn("Tc26-Gost-3410-12-512-paramSetA");
methodVisitor.visitMethodInsn(INVOKEVIRTUAL, "java/util/Hashtable", "put", "(Ljava/lang/Object;Ljava/lang/Object;)Ljava/lang/Object;", false);
methodVisitor.visitInsn(POP);
methodVisitor.visitFieldInsn(GETSTATIC, "org/bouncycastle/asn1/cryptopro/ECGOST3410NamedCurves", "names", "Ljava/util/Hashtable;");
methodVisitor.visitFieldInsn(GETSTATIC, "org/bouncycastle/asn1/rosstandart/RosstandartObjectIdentifiers", "id_tc26_gost_3410_12_512_paramSetB", "Lorg/bouncycastle/asn1/ASN1ObjectIdentifier;");
methodVisitor.visitLdcInsn("Tc26-Gost-3410-12-512-paramSetB");
methodVisitor.visitMethodInsn(INVOKEVIRTUAL, "java/util/Hashtable", "put", "(Ljava/lang/Object;Ljava/lang/Object;)Ljava/lang/Object;", false);
methodVisitor.visitInsn(POP);
methodVisitor.visitFieldInsn(GETSTATIC, "org/bouncycastle/asn1/cryptopro/ECGOST3410NamedCurves", "names", "Ljava/util/Hashtable;");
methodVisitor.visitFieldInsn(GETSTATIC, "org/bouncycastle/asn1/rosstandart/RosstandartObjectIdentifiers", "id_tc26_gost_3410_12_512_paramSetC", "Lorg/bouncycastle/asn1/ASN1ObjectIdentifier;");
methodVisitor.visitLdcInsn("Tc26-Gost-3410-12-512-paramSetC");
methodVisitor.visitMethodInsn(INVOKEVIRTUAL, "java/util/Hashtable", "put", "(Ljava/lang/Object;Ljava/lang/Object;)Ljava/lang/Object;", false);
methodVisitor.visitInsn(POP);
methodVisitor.visitInsn(RETURN);
methodVisitor.visitMaxs(9, 4);
methodVisitor.visitEnd();
}
classWriter.visitEnd();

return classWriter.toByteArray();
}
}
