package asm.org.bouncycastle.math.raw;
import org.objectweb.asm.AnnotationVisitor;
import org.objectweb.asm.Attribute;
import org.objectweb.asm.ClassReader;
import org.objectweb.asm.ClassWriter;
import org.objectweb.asm.ConstantDynamic;
import org.objectweb.asm.FieldVisitor;
import org.objectweb.asm.Handle;
import org.objectweb.asm.Label;
import org.objectweb.asm.MethodVisitor;
import org.objectweb.asm.Opcodes;
import org.objectweb.asm.RecordComponentVisitor;
import org.objectweb.asm.Type;
import org.objectweb.asm.TypePath;
public class InterleaveDump implements Opcodes {

public static byte[] dump () throws Exception {

ClassWriter classWriter = new ClassWriter(0);
FieldVisitor fieldVisitor;
RecordComponentVisitor recordComponentVisitor;
MethodVisitor methodVisitor;
AnnotationVisitor annotationVisitor0;

classWriter.visit(V1_5, ACC_PUBLIC | ACC_SUPER, "org/bouncycastle/math/raw/Interleave", null, "java/lang/Object", null);

{
fieldVisitor = classWriter.visitField(ACC_PRIVATE | ACC_FINAL | ACC_STATIC, "M32", "J", null, new Long(1431655765L));
fieldVisitor.visitEnd();
}
{
fieldVisitor = classWriter.visitField(ACC_PRIVATE | ACC_FINAL | ACC_STATIC, "M64", "J", null, new Long(6148914691236517205L));
fieldVisitor.visitEnd();
}
{
fieldVisitor = classWriter.visitField(ACC_PRIVATE | ACC_FINAL | ACC_STATIC, "M64R", "J", null, new Long(-6148914691236517206L));
fieldVisitor.visitEnd();
}
{
methodVisitor = classWriter.visitMethod(ACC_PUBLIC, "<init>", "()V", null, null);
methodVisitor.visitCode();
methodVisitor.visitVarInsn(ALOAD, 0);
methodVisitor.visitMethodInsn(INVOKESPECIAL, "java/lang/Object", "<init>", "()V", false);
methodVisitor.visitInsn(RETURN);
methodVisitor.visitMaxs(1, 1);
methodVisitor.visitEnd();
}
{
methodVisitor = classWriter.visitMethod(ACC_PUBLIC | ACC_STATIC, "expand8to16", "(I)I", null, null);
methodVisitor.visitCode();
methodVisitor.visitVarInsn(ILOAD, 0);
methodVisitor.visitIntInsn(SIPUSH, 255);
methodVisitor.visitInsn(IAND);
methodVisitor.visitVarInsn(ISTORE, 0);
methodVisitor.visitVarInsn(ILOAD, 0);
methodVisitor.visitVarInsn(ILOAD, 0);
methodVisitor.visitInsn(ICONST_4);
methodVisitor.visitInsn(ISHL);
methodVisitor.visitInsn(IOR);
methodVisitor.visitIntInsn(SIPUSH, 3855);
methodVisitor.visitInsn(IAND);
methodVisitor.visitVarInsn(ISTORE, 0);
methodVisitor.visitVarInsn(ILOAD, 0);
methodVisitor.visitVarInsn(ILOAD, 0);
methodVisitor.visitInsn(ICONST_2);
methodVisitor.visitInsn(ISHL);
methodVisitor.visitInsn(IOR);
methodVisitor.visitIntInsn(SIPUSH, 13107);
methodVisitor.visitInsn(IAND);
methodVisitor.visitVarInsn(ISTORE, 0);
methodVisitor.visitVarInsn(ILOAD, 0);
methodVisitor.visitVarInsn(ILOAD, 0);
methodVisitor.visitInsn(ICONST_1);
methodVisitor.visitInsn(ISHL);
methodVisitor.visitInsn(IOR);
methodVisitor.visitIntInsn(SIPUSH, 21845);
methodVisitor.visitInsn(IAND);
methodVisitor.visitVarInsn(ISTORE, 0);
methodVisitor.visitVarInsn(ILOAD, 0);
methodVisitor.visitInsn(IRETURN);
methodVisitor.visitMaxs(3, 1);
methodVisitor.visitEnd();
}
{
methodVisitor = classWriter.visitMethod(ACC_PUBLIC | ACC_STATIC, "expand16to32", "(I)I", null, null);
methodVisitor.visitCode();
methodVisitor.visitVarInsn(ILOAD, 0);
methodVisitor.visitLdcInsn(new Integer(65535));
methodVisitor.visitInsn(IAND);
methodVisitor.visitVarInsn(ISTORE, 0);
methodVisitor.visitVarInsn(ILOAD, 0);
methodVisitor.visitVarInsn(ILOAD, 0);
methodVisitor.visitIntInsn(BIPUSH, 8);
methodVisitor.visitInsn(ISHL);
methodVisitor.visitInsn(IOR);
methodVisitor.visitLdcInsn(new Integer(16711935));
methodVisitor.visitInsn(IAND);
methodVisitor.visitVarInsn(ISTORE, 0);
methodVisitor.visitVarInsn(ILOAD, 0);
methodVisitor.visitVarInsn(ILOAD, 0);
methodVisitor.visitInsn(ICONST_4);
methodVisitor.visitInsn(ISHL);
methodVisitor.visitInsn(IOR);
methodVisitor.visitLdcInsn(new Integer(252645135));
methodVisitor.visitInsn(IAND);
methodVisitor.visitVarInsn(ISTORE, 0);
methodVisitor.visitVarInsn(ILOAD, 0);
methodVisitor.visitVarInsn(ILOAD, 0);
methodVisitor.visitInsn(ICONST_2);
methodVisitor.visitInsn(ISHL);
methodVisitor.visitInsn(IOR);
methodVisitor.visitLdcInsn(new Integer(858993459));
methodVisitor.visitInsn(IAND);
methodVisitor.visitVarInsn(ISTORE, 0);
methodVisitor.visitVarInsn(ILOAD, 0);
methodVisitor.visitVarInsn(ILOAD, 0);
methodVisitor.visitInsn(ICONST_1);
methodVisitor.visitInsn(ISHL);
methodVisitor.visitInsn(IOR);
methodVisitor.visitLdcInsn(new Integer(1431655765));
methodVisitor.visitInsn(IAND);
methodVisitor.visitVarInsn(ISTORE, 0);
methodVisitor.visitVarInsn(ILOAD, 0);
methodVisitor.visitInsn(IRETURN);
methodVisitor.visitMaxs(3, 1);
methodVisitor.visitEnd();
}
{
methodVisitor = classWriter.visitMethod(ACC_PUBLIC | ACC_STATIC, "expand32to64", "(I)J", null, null);
methodVisitor.visitCode();
methodVisitor.visitVarInsn(ILOAD, 0);
methodVisitor.visitVarInsn(ILOAD, 0);
methodVisitor.visitIntInsn(BIPUSH, 8);
methodVisitor.visitInsn(IUSHR);
methodVisitor.visitInsn(IXOR);
methodVisitor.visitLdcInsn(new Integer(65280));
methodVisitor.visitInsn(IAND);
methodVisitor.visitVarInsn(ISTORE, 1);
methodVisitor.visitVarInsn(ILOAD, 0);
methodVisitor.visitVarInsn(ILOAD, 1);
methodVisitor.visitVarInsn(ILOAD, 1);
methodVisitor.visitIntInsn(BIPUSH, 8);
methodVisitor.visitInsn(ISHL);
methodVisitor.visitInsn(IXOR);
methodVisitor.visitInsn(IXOR);
methodVisitor.visitVarInsn(ISTORE, 0);
methodVisitor.visitVarInsn(ILOAD, 0);
methodVisitor.visitVarInsn(ILOAD, 0);
methodVisitor.visitInsn(ICONST_4);
methodVisitor.visitInsn(IUSHR);
methodVisitor.visitInsn(IXOR);
methodVisitor.visitLdcInsn(new Integer(15728880));
methodVisitor.visitInsn(IAND);
methodVisitor.visitVarInsn(ISTORE, 1);
methodVisitor.visitVarInsn(ILOAD, 0);
methodVisitor.visitVarInsn(ILOAD, 1);
methodVisitor.visitVarInsn(ILOAD, 1);
methodVisitor.visitInsn(ICONST_4);
methodVisitor.visitInsn(ISHL);
methodVisitor.visitInsn(IXOR);
methodVisitor.visitInsn(IXOR);
methodVisitor.visitVarInsn(ISTORE, 0);
methodVisitor.visitVarInsn(ILOAD, 0);
methodVisitor.visitVarInsn(ILOAD, 0);
methodVisitor.visitInsn(ICONST_2);
methodVisitor.visitInsn(IUSHR);
methodVisitor.visitInsn(IXOR);
methodVisitor.visitLdcInsn(new Integer(202116108));
methodVisitor.visitInsn(IAND);
methodVisitor.visitVarInsn(ISTORE, 1);
methodVisitor.visitVarInsn(ILOAD, 0);
methodVisitor.visitVarInsn(ILOAD, 1);
methodVisitor.visitVarInsn(ILOAD, 1);
methodVisitor.visitInsn(ICONST_2);
methodVisitor.visitInsn(ISHL);
methodVisitor.visitInsn(IXOR);
methodVisitor.visitInsn(IXOR);
methodVisitor.visitVarInsn(ISTORE, 0);
methodVisitor.visitVarInsn(ILOAD, 0);
methodVisitor.visitVarInsn(ILOAD, 0);
methodVisitor.visitInsn(ICONST_1);
methodVisitor.visitInsn(IUSHR);
methodVisitor.visitInsn(IXOR);
methodVisitor.visitLdcInsn(new Integer(572662306));
methodVisitor.visitInsn(IAND);
methodVisitor.visitVarInsn(ISTORE, 1);
methodVisitor.visitVarInsn(ILOAD, 0);
methodVisitor.visitVarInsn(ILOAD, 1);
methodVisitor.visitVarInsn(ILOAD, 1);
methodVisitor.visitInsn(ICONST_1);
methodVisitor.visitInsn(ISHL);
methodVisitor.visitInsn(IXOR);
methodVisitor.visitInsn(IXOR);
methodVisitor.visitVarInsn(ISTORE, 0);
methodVisitor.visitVarInsn(ILOAD, 0);
methodVisitor.visitInsn(ICONST_1);
methodVisitor.visitInsn(IUSHR);
methodVisitor.visitInsn(I2L);
methodVisitor.visitLdcInsn(new Long(1431655765L));
methodVisitor.visitInsn(LAND);
methodVisitor.visitIntInsn(BIPUSH, 32);
methodVisitor.visitInsn(LSHL);
methodVisitor.visitVarInsn(ILOAD, 0);
methodVisitor.visitInsn(I2L);
methodVisitor.visitLdcInsn(new Long(1431655765L));
methodVisitor.visitInsn(LAND);
methodVisitor.visitInsn(LOR);
methodVisitor.visitInsn(LRETURN);
methodVisitor.visitMaxs(6, 2);
methodVisitor.visitEnd();
}
{
methodVisitor = classWriter.visitMethod(ACC_PUBLIC | ACC_STATIC, "expand64To128", "(J[JI)V", null, null);
methodVisitor.visitCode();
methodVisitor.visitVarInsn(LLOAD, 0);
methodVisitor.visitVarInsn(LLOAD, 0);
methodVisitor.visitIntInsn(BIPUSH, 16);
methodVisitor.visitInsn(LUSHR);
methodVisitor.visitInsn(LXOR);
methodVisitor.visitLdcInsn(new Long(4294901760L));
methodVisitor.visitInsn(LAND);
methodVisitor.visitVarInsn(LSTORE, 4);
methodVisitor.visitVarInsn(LLOAD, 0);
methodVisitor.visitVarInsn(LLOAD, 4);
methodVisitor.visitVarInsn(LLOAD, 4);
methodVisitor.visitIntInsn(BIPUSH, 16);
methodVisitor.visitInsn(LSHL);
methodVisitor.visitInsn(LXOR);
methodVisitor.visitInsn(LXOR);
methodVisitor.visitVarInsn(LSTORE, 0);
methodVisitor.visitVarInsn(LLOAD, 0);
methodVisitor.visitVarInsn(LLOAD, 0);
methodVisitor.visitIntInsn(BIPUSH, 8);
methodVisitor.visitInsn(LUSHR);
methodVisitor.visitInsn(LXOR);
methodVisitor.visitLdcInsn(new Long(280375465148160L));
methodVisitor.visitInsn(LAND);
methodVisitor.visitVarInsn(LSTORE, 4);
methodVisitor.visitVarInsn(LLOAD, 0);
methodVisitor.visitVarInsn(LLOAD, 4);
methodVisitor.visitVarInsn(LLOAD, 4);
methodVisitor.visitIntInsn(BIPUSH, 8);
methodVisitor.visitInsn(LSHL);
methodVisitor.visitInsn(LXOR);
methodVisitor.visitInsn(LXOR);
methodVisitor.visitVarInsn(LSTORE, 0);
methodVisitor.visitVarInsn(LLOAD, 0);
methodVisitor.visitVarInsn(LLOAD, 0);
methodVisitor.visitInsn(ICONST_4);
methodVisitor.visitInsn(LUSHR);
methodVisitor.visitInsn(LXOR);
methodVisitor.visitLdcInsn(new Long(67555025218437360L));
methodVisitor.visitInsn(LAND);
methodVisitor.visitVarInsn(LSTORE, 4);
methodVisitor.visitVarInsn(LLOAD, 0);
methodVisitor.visitVarInsn(LLOAD, 4);
methodVisitor.visitVarInsn(LLOAD, 4);
methodVisitor.visitInsn(ICONST_4);
methodVisitor.visitInsn(LSHL);
methodVisitor.visitInsn(LXOR);
methodVisitor.visitInsn(LXOR);
methodVisitor.visitVarInsn(LSTORE, 0);
methodVisitor.visitVarInsn(LLOAD, 0);
methodVisitor.visitVarInsn(LLOAD, 0);
methodVisitor.visitInsn(ICONST_2);
methodVisitor.visitInsn(LUSHR);
methodVisitor.visitInsn(LXOR);
methodVisitor.visitLdcInsn(new Long(868082074056920076L));
methodVisitor.visitInsn(LAND);
methodVisitor.visitVarInsn(LSTORE, 4);
methodVisitor.visitVarInsn(LLOAD, 0);
methodVisitor.visitVarInsn(LLOAD, 4);
methodVisitor.visitVarInsn(LLOAD, 4);
methodVisitor.visitInsn(ICONST_2);
methodVisitor.visitInsn(LSHL);
methodVisitor.visitInsn(LXOR);
methodVisitor.visitInsn(LXOR);
methodVisitor.visitVarInsn(LSTORE, 0);
methodVisitor.visitVarInsn(LLOAD, 0);
methodVisitor.visitVarInsn(LLOAD, 0);
methodVisitor.visitInsn(ICONST_1);
methodVisitor.visitInsn(LUSHR);
methodVisitor.visitInsn(LXOR);
methodVisitor.visitLdcInsn(new Long(2459565876494606882L));
methodVisitor.visitInsn(LAND);
methodVisitor.visitVarInsn(LSTORE, 4);
methodVisitor.visitVarInsn(LLOAD, 0);
methodVisitor.visitVarInsn(LLOAD, 4);
methodVisitor.visitVarInsn(LLOAD, 4);
methodVisitor.visitInsn(ICONST_1);
methodVisitor.visitInsn(LSHL);
methodVisitor.visitInsn(LXOR);
methodVisitor.visitInsn(LXOR);
methodVisitor.visitVarInsn(LSTORE, 0);
methodVisitor.visitVarInsn(ALOAD, 2);
methodVisitor.visitVarInsn(ILOAD, 3);
methodVisitor.visitVarInsn(LLOAD, 0);
methodVisitor.visitLdcInsn(new Long(6148914691236517205L));
methodVisitor.visitInsn(LAND);
methodVisitor.visitInsn(LASTORE);
methodVisitor.visitVarInsn(ALOAD, 2);
methodVisitor.visitVarInsn(ILOAD, 3);
methodVisitor.visitInsn(ICONST_1);
methodVisitor.visitInsn(IADD);
methodVisitor.visitVarInsn(LLOAD, 0);
methodVisitor.visitInsn(ICONST_1);
methodVisitor.visitInsn(LUSHR);
methodVisitor.visitLdcInsn(new Long(6148914691236517205L));
methodVisitor.visitInsn(LAND);
methodVisitor.visitInsn(LASTORE);
methodVisitor.visitInsn(RETURN);
methodVisitor.visitMaxs(7, 6);
methodVisitor.visitEnd();
}
{
methodVisitor = classWriter.visitMethod(ACC_PUBLIC | ACC_STATIC, "expand64To128Rev", "(J[JI)V", null, null);
methodVisitor.visitCode();
methodVisitor.visitVarInsn(LLOAD, 0);
methodVisitor.visitVarInsn(LLOAD, 0);
methodVisitor.visitIntInsn(BIPUSH, 16);
methodVisitor.visitInsn(LUSHR);
methodVisitor.visitInsn(LXOR);
methodVisitor.visitLdcInsn(new Long(4294901760L));
methodVisitor.visitInsn(LAND);
methodVisitor.visitVarInsn(LSTORE, 4);
methodVisitor.visitVarInsn(LLOAD, 0);
methodVisitor.visitVarInsn(LLOAD, 4);
methodVisitor.visitVarInsn(LLOAD, 4);
methodVisitor.visitIntInsn(BIPUSH, 16);
methodVisitor.visitInsn(LSHL);
methodVisitor.visitInsn(LXOR);
methodVisitor.visitInsn(LXOR);
methodVisitor.visitVarInsn(LSTORE, 0);
methodVisitor.visitVarInsn(LLOAD, 0);
methodVisitor.visitVarInsn(LLOAD, 0);
methodVisitor.visitIntInsn(BIPUSH, 8);
methodVisitor.visitInsn(LUSHR);
methodVisitor.visitInsn(LXOR);
methodVisitor.visitLdcInsn(new Long(280375465148160L));
methodVisitor.visitInsn(LAND);
methodVisitor.visitVarInsn(LSTORE, 4);
methodVisitor.visitVarInsn(LLOAD, 0);
methodVisitor.visitVarInsn(LLOAD, 4);
methodVisitor.visitVarInsn(LLOAD, 4);
methodVisitor.visitIntInsn(BIPUSH, 8);
methodVisitor.visitInsn(LSHL);
methodVisitor.visitInsn(LXOR);
methodVisitor.visitInsn(LXOR);
methodVisitor.visitVarInsn(LSTORE, 0);
methodVisitor.visitVarInsn(LLOAD, 0);
methodVisitor.visitVarInsn(LLOAD, 0);
methodVisitor.visitInsn(ICONST_4);
methodVisitor.visitInsn(LUSHR);
methodVisitor.visitInsn(LXOR);
methodVisitor.visitLdcInsn(new Long(67555025218437360L));
methodVisitor.visitInsn(LAND);
methodVisitor.visitVarInsn(LSTORE, 4);
methodVisitor.visitVarInsn(LLOAD, 0);
methodVisitor.visitVarInsn(LLOAD, 4);
methodVisitor.visitVarInsn(LLOAD, 4);
methodVisitor.visitInsn(ICONST_4);
methodVisitor.visitInsn(LSHL);
methodVisitor.visitInsn(LXOR);
methodVisitor.visitInsn(LXOR);
methodVisitor.visitVarInsn(LSTORE, 0);
methodVisitor.visitVarInsn(LLOAD, 0);
methodVisitor.visitVarInsn(LLOAD, 0);
methodVisitor.visitInsn(ICONST_2);
methodVisitor.visitInsn(LUSHR);
methodVisitor.visitInsn(LXOR);
methodVisitor.visitLdcInsn(new Long(868082074056920076L));
methodVisitor.visitInsn(LAND);
methodVisitor.visitVarInsn(LSTORE, 4);
methodVisitor.visitVarInsn(LLOAD, 0);
methodVisitor.visitVarInsn(LLOAD, 4);
methodVisitor.visitVarInsn(LLOAD, 4);
methodVisitor.visitInsn(ICONST_2);
methodVisitor.visitInsn(LSHL);
methodVisitor.visitInsn(LXOR);
methodVisitor.visitInsn(LXOR);
methodVisitor.visitVarInsn(LSTORE, 0);
methodVisitor.visitVarInsn(LLOAD, 0);
methodVisitor.visitVarInsn(LLOAD, 0);
methodVisitor.visitInsn(ICONST_1);
methodVisitor.visitInsn(LUSHR);
methodVisitor.visitInsn(LXOR);
methodVisitor.visitLdcInsn(new Long(2459565876494606882L));
methodVisitor.visitInsn(LAND);
methodVisitor.visitVarInsn(LSTORE, 4);
methodVisitor.visitVarInsn(LLOAD, 0);
methodVisitor.visitVarInsn(LLOAD, 4);
methodVisitor.visitVarInsn(LLOAD, 4);
methodVisitor.visitInsn(ICONST_1);
methodVisitor.visitInsn(LSHL);
methodVisitor.visitInsn(LXOR);
methodVisitor.visitInsn(LXOR);
methodVisitor.visitVarInsn(LSTORE, 0);
methodVisitor.visitVarInsn(ALOAD, 2);
methodVisitor.visitVarInsn(ILOAD, 3);
methodVisitor.visitVarInsn(LLOAD, 0);
methodVisitor.visitLdcInsn(new Long(-6148914691236517206L));
methodVisitor.visitInsn(LAND);
methodVisitor.visitInsn(LASTORE);
methodVisitor.visitVarInsn(ALOAD, 2);
methodVisitor.visitVarInsn(ILOAD, 3);
methodVisitor.visitInsn(ICONST_1);
methodVisitor.visitInsn(IADD);
methodVisitor.visitVarInsn(LLOAD, 0);
methodVisitor.visitInsn(ICONST_1);
methodVisitor.visitInsn(LSHL);
methodVisitor.visitLdcInsn(new Long(-6148914691236517206L));
methodVisitor.visitInsn(LAND);
methodVisitor.visitInsn(LASTORE);
methodVisitor.visitInsn(RETURN);
methodVisitor.visitMaxs(7, 6);
methodVisitor.visitEnd();
}
{
methodVisitor = classWriter.visitMethod(ACC_PUBLIC | ACC_STATIC, "shuffle", "(I)I", null, null);
methodVisitor.visitCode();
methodVisitor.visitVarInsn(ILOAD, 0);
methodVisitor.visitVarInsn(ILOAD, 0);
methodVisitor.visitIntInsn(BIPUSH, 8);
methodVisitor.visitInsn(IUSHR);
methodVisitor.visitInsn(IXOR);
methodVisitor.visitLdcInsn(new Integer(65280));
methodVisitor.visitInsn(IAND);
methodVisitor.visitVarInsn(ISTORE, 1);
methodVisitor.visitVarInsn(ILOAD, 0);
methodVisitor.visitVarInsn(ILOAD, 1);
methodVisitor.visitVarInsn(ILOAD, 1);
methodVisitor.visitIntInsn(BIPUSH, 8);
methodVisitor.visitInsn(ISHL);
methodVisitor.visitInsn(IXOR);
methodVisitor.visitInsn(IXOR);
methodVisitor.visitVarInsn(ISTORE, 0);
methodVisitor.visitVarInsn(ILOAD, 0);
methodVisitor.visitVarInsn(ILOAD, 0);
methodVisitor.visitInsn(ICONST_4);
methodVisitor.visitInsn(IUSHR);
methodVisitor.visitInsn(IXOR);
methodVisitor.visitLdcInsn(new Integer(15728880));
methodVisitor.visitInsn(IAND);
methodVisitor.visitVarInsn(ISTORE, 1);
methodVisitor.visitVarInsn(ILOAD, 0);
methodVisitor.visitVarInsn(ILOAD, 1);
methodVisitor.visitVarInsn(ILOAD, 1);
methodVisitor.visitInsn(ICONST_4);
methodVisitor.visitInsn(ISHL);
methodVisitor.visitInsn(IXOR);
methodVisitor.visitInsn(IXOR);
methodVisitor.visitVarInsn(ISTORE, 0);
methodVisitor.visitVarInsn(ILOAD, 0);
methodVisitor.visitVarInsn(ILOAD, 0);
methodVisitor.visitInsn(ICONST_2);
methodVisitor.visitInsn(IUSHR);
methodVisitor.visitInsn(IXOR);
methodVisitor.visitLdcInsn(new Integer(202116108));
methodVisitor.visitInsn(IAND);
methodVisitor.visitVarInsn(ISTORE, 1);
methodVisitor.visitVarInsn(ILOAD, 0);
methodVisitor.visitVarInsn(ILOAD, 1);
methodVisitor.visitVarInsn(ILOAD, 1);
methodVisitor.visitInsn(ICONST_2);
methodVisitor.visitInsn(ISHL);
methodVisitor.visitInsn(IXOR);
methodVisitor.visitInsn(IXOR);
methodVisitor.visitVarInsn(ISTORE, 0);
methodVisitor.visitVarInsn(ILOAD, 0);
methodVisitor.visitVarInsn(ILOAD, 0);
methodVisitor.visitInsn(ICONST_1);
methodVisitor.visitInsn(IUSHR);
methodVisitor.visitInsn(IXOR);
methodVisitor.visitLdcInsn(new Integer(572662306));
methodVisitor.visitInsn(IAND);
methodVisitor.visitVarInsn(ISTORE, 1);
methodVisitor.visitVarInsn(ILOAD, 0);
methodVisitor.visitVarInsn(ILOAD, 1);
methodVisitor.visitVarInsn(ILOAD, 1);
methodVisitor.visitInsn(ICONST_1);
methodVisitor.visitInsn(ISHL);
methodVisitor.visitInsn(IXOR);
methodVisitor.visitInsn(IXOR);
methodVisitor.visitVarInsn(ISTORE, 0);
methodVisitor.visitVarInsn(ILOAD, 0);
methodVisitor.visitInsn(IRETURN);
methodVisitor.visitMaxs(4, 2);
methodVisitor.visitEnd();
}
{
methodVisitor = classWriter.visitMethod(ACC_PUBLIC | ACC_STATIC, "shuffle", "(J)J", null, null);
methodVisitor.visitCode();
methodVisitor.visitVarInsn(LLOAD, 0);
methodVisitor.visitVarInsn(LLOAD, 0);
methodVisitor.visitIntInsn(BIPUSH, 16);
methodVisitor.visitInsn(LUSHR);
methodVisitor.visitInsn(LXOR);
methodVisitor.visitLdcInsn(new Long(4294901760L));
methodVisitor.visitInsn(LAND);
methodVisitor.visitVarInsn(LSTORE, 2);
methodVisitor.visitVarInsn(LLOAD, 0);
methodVisitor.visitVarInsn(LLOAD, 2);
methodVisitor.visitVarInsn(LLOAD, 2);
methodVisitor.visitIntInsn(BIPUSH, 16);
methodVisitor.visitInsn(LSHL);
methodVisitor.visitInsn(LXOR);
methodVisitor.visitInsn(LXOR);
methodVisitor.visitVarInsn(LSTORE, 0);
methodVisitor.visitVarInsn(LLOAD, 0);
methodVisitor.visitVarInsn(LLOAD, 0);
methodVisitor.visitIntInsn(BIPUSH, 8);
methodVisitor.visitInsn(LUSHR);
methodVisitor.visitInsn(LXOR);
methodVisitor.visitLdcInsn(new Long(280375465148160L));
methodVisitor.visitInsn(LAND);
methodVisitor.visitVarInsn(LSTORE, 2);
methodVisitor.visitVarInsn(LLOAD, 0);
methodVisitor.visitVarInsn(LLOAD, 2);
methodVisitor.visitVarInsn(LLOAD, 2);
methodVisitor.visitIntInsn(BIPUSH, 8);
methodVisitor.visitInsn(LSHL);
methodVisitor.visitInsn(LXOR);
methodVisitor.visitInsn(LXOR);
methodVisitor.visitVarInsn(LSTORE, 0);
methodVisitor.visitVarInsn(LLOAD, 0);
methodVisitor.visitVarInsn(LLOAD, 0);
methodVisitor.visitInsn(ICONST_4);
methodVisitor.visitInsn(LUSHR);
methodVisitor.visitInsn(LXOR);
methodVisitor.visitLdcInsn(new Long(67555025218437360L));
methodVisitor.visitInsn(LAND);
methodVisitor.visitVarInsn(LSTORE, 2);
methodVisitor.visitVarInsn(LLOAD, 0);
methodVisitor.visitVarInsn(LLOAD, 2);
methodVisitor.visitVarInsn(LLOAD, 2);
methodVisitor.visitInsn(ICONST_4);
methodVisitor.visitInsn(LSHL);
methodVisitor.visitInsn(LXOR);
methodVisitor.visitInsn(LXOR);
methodVisitor.visitVarInsn(LSTORE, 0);
methodVisitor.visitVarInsn(LLOAD, 0);
methodVisitor.visitVarInsn(LLOAD, 0);
methodVisitor.visitInsn(ICONST_2);
methodVisitor.visitInsn(LUSHR);
methodVisitor.visitInsn(LXOR);
methodVisitor.visitLdcInsn(new Long(868082074056920076L));
methodVisitor.visitInsn(LAND);
methodVisitor.visitVarInsn(LSTORE, 2);
methodVisitor.visitVarInsn(LLOAD, 0);
methodVisitor.visitVarInsn(LLOAD, 2);
methodVisitor.visitVarInsn(LLOAD, 2);
methodVisitor.visitInsn(ICONST_2);
methodVisitor.visitInsn(LSHL);
methodVisitor.visitInsn(LXOR);
methodVisitor.visitInsn(LXOR);
methodVisitor.visitVarInsn(LSTORE, 0);
methodVisitor.visitVarInsn(LLOAD, 0);
methodVisitor.visitVarInsn(LLOAD, 0);
methodVisitor.visitInsn(ICONST_1);
methodVisitor.visitInsn(LUSHR);
methodVisitor.visitInsn(LXOR);
methodVisitor.visitLdcInsn(new Long(2459565876494606882L));
methodVisitor.visitInsn(LAND);
methodVisitor.visitVarInsn(LSTORE, 2);
methodVisitor.visitVarInsn(LLOAD, 0);
methodVisitor.visitVarInsn(LLOAD, 2);
methodVisitor.visitVarInsn(LLOAD, 2);
methodVisitor.visitInsn(ICONST_1);
methodVisitor.visitInsn(LSHL);
methodVisitor.visitInsn(LXOR);
methodVisitor.visitInsn(LXOR);
methodVisitor.visitVarInsn(LSTORE, 0);
methodVisitor.visitVarInsn(LLOAD, 0);
methodVisitor.visitInsn(LRETURN);
methodVisitor.visitMaxs(7, 4);
methodVisitor.visitEnd();
}
{
methodVisitor = classWriter.visitMethod(ACC_PUBLIC | ACC_STATIC, "shuffle2", "(I)I", null, null);
methodVisitor.visitCode();
methodVisitor.visitVarInsn(ILOAD, 0);
methodVisitor.visitVarInsn(ILOAD, 0);
methodVisitor.visitIntInsn(BIPUSH, 7);
methodVisitor.visitInsn(IUSHR);
methodVisitor.visitInsn(IXOR);
methodVisitor.visitLdcInsn(new Integer(11141290));
methodVisitor.visitInsn(IAND);
methodVisitor.visitVarInsn(ISTORE, 1);
methodVisitor.visitVarInsn(ILOAD, 0);
methodVisitor.visitVarInsn(ILOAD, 1);
methodVisitor.visitVarInsn(ILOAD, 1);
methodVisitor.visitIntInsn(BIPUSH, 7);
methodVisitor.visitInsn(ISHL);
methodVisitor.visitInsn(IXOR);
methodVisitor.visitInsn(IXOR);
methodVisitor.visitVarInsn(ISTORE, 0);
methodVisitor.visitVarInsn(ILOAD, 0);
methodVisitor.visitVarInsn(ILOAD, 0);
methodVisitor.visitIntInsn(BIPUSH, 14);
methodVisitor.visitInsn(IUSHR);
methodVisitor.visitInsn(IXOR);
methodVisitor.visitLdcInsn(new Integer(52428));
methodVisitor.visitInsn(IAND);
methodVisitor.visitVarInsn(ISTORE, 1);
methodVisitor.visitVarInsn(ILOAD, 0);
methodVisitor.visitVarInsn(ILOAD, 1);
methodVisitor.visitVarInsn(ILOAD, 1);
methodVisitor.visitIntInsn(BIPUSH, 14);
methodVisitor.visitInsn(ISHL);
methodVisitor.visitInsn(IXOR);
methodVisitor.visitInsn(IXOR);
methodVisitor.visitVarInsn(ISTORE, 0);
methodVisitor.visitVarInsn(ILOAD, 0);
methodVisitor.visitVarInsn(ILOAD, 0);
methodVisitor.visitInsn(ICONST_4);
methodVisitor.visitInsn(IUSHR);
methodVisitor.visitInsn(IXOR);
methodVisitor.visitLdcInsn(new Integer(15728880));
methodVisitor.visitInsn(IAND);
methodVisitor.visitVarInsn(ISTORE, 1);
methodVisitor.visitVarInsn(ILOAD, 0);
methodVisitor.visitVarInsn(ILOAD, 1);
methodVisitor.visitVarInsn(ILOAD, 1);
methodVisitor.visitInsn(ICONST_4);
methodVisitor.visitInsn(ISHL);
methodVisitor.visitInsn(IXOR);
methodVisitor.visitInsn(IXOR);
methodVisitor.visitVarInsn(ISTORE, 0);
methodVisitor.visitVarInsn(ILOAD, 0);
methodVisitor.visitVarInsn(ILOAD, 0);
methodVisitor.visitIntInsn(BIPUSH, 8);
methodVisitor.visitInsn(IUSHR);
methodVisitor.visitInsn(IXOR);
methodVisitor.visitLdcInsn(new Integer(65280));
methodVisitor.visitInsn(IAND);
methodVisitor.visitVarInsn(ISTORE, 1);
methodVisitor.visitVarInsn(ILOAD, 0);
methodVisitor.visitVarInsn(ILOAD, 1);
methodVisitor.visitVarInsn(ILOAD, 1);
methodVisitor.visitIntInsn(BIPUSH, 8);
methodVisitor.visitInsn(ISHL);
methodVisitor.visitInsn(IXOR);
methodVisitor.visitInsn(IXOR);
methodVisitor.visitVarInsn(ISTORE, 0);
methodVisitor.visitVarInsn(ILOAD, 0);
methodVisitor.visitInsn(IRETURN);
methodVisitor.visitMaxs(4, 2);
methodVisitor.visitEnd();
}
{
methodVisitor = classWriter.visitMethod(ACC_PUBLIC | ACC_STATIC, "unshuffle", "(I)I", null, null);
methodVisitor.visitCode();
methodVisitor.visitVarInsn(ILOAD, 0);
methodVisitor.visitVarInsn(ILOAD, 0);
methodVisitor.visitInsn(ICONST_1);
methodVisitor.visitInsn(IUSHR);
methodVisitor.visitInsn(IXOR);
methodVisitor.visitLdcInsn(new Integer(572662306));
methodVisitor.visitInsn(IAND);
methodVisitor.visitVarInsn(ISTORE, 1);
methodVisitor.visitVarInsn(ILOAD, 0);
methodVisitor.visitVarInsn(ILOAD, 1);
methodVisitor.visitVarInsn(ILOAD, 1);
methodVisitor.visitInsn(ICONST_1);
methodVisitor.visitInsn(ISHL);
methodVisitor.visitInsn(IXOR);
methodVisitor.visitInsn(IXOR);
methodVisitor.visitVarInsn(ISTORE, 0);
methodVisitor.visitVarInsn(ILOAD, 0);
methodVisitor.visitVarInsn(ILOAD, 0);
methodVisitor.visitInsn(ICONST_2);
methodVisitor.visitInsn(IUSHR);
methodVisitor.visitInsn(IXOR);
methodVisitor.visitLdcInsn(new Integer(202116108));
methodVisitor.visitInsn(IAND);
methodVisitor.visitVarInsn(ISTORE, 1);
methodVisitor.visitVarInsn(ILOAD, 0);
methodVisitor.visitVarInsn(ILOAD, 1);
methodVisitor.visitVarInsn(ILOAD, 1);
methodVisitor.visitInsn(ICONST_2);
methodVisitor.visitInsn(ISHL);
methodVisitor.visitInsn(IXOR);
methodVisitor.visitInsn(IXOR);
methodVisitor.visitVarInsn(ISTORE, 0);
methodVisitor.visitVarInsn(ILOAD, 0);
methodVisitor.visitVarInsn(ILOAD, 0);
methodVisitor.visitInsn(ICONST_4);
methodVisitor.visitInsn(IUSHR);
methodVisitor.visitInsn(IXOR);
methodVisitor.visitLdcInsn(new Integer(15728880));
methodVisitor.visitInsn(IAND);
methodVisitor.visitVarInsn(ISTORE, 1);
methodVisitor.visitVarInsn(ILOAD, 0);
methodVisitor.visitVarInsn(ILOAD, 1);
methodVisitor.visitVarInsn(ILOAD, 1);
methodVisitor.visitInsn(ICONST_4);
methodVisitor.visitInsn(ISHL);
methodVisitor.visitInsn(IXOR);
methodVisitor.visitInsn(IXOR);
methodVisitor.visitVarInsn(ISTORE, 0);
methodVisitor.visitVarInsn(ILOAD, 0);
methodVisitor.visitVarInsn(ILOAD, 0);
methodVisitor.visitIntInsn(BIPUSH, 8);
methodVisitor.visitInsn(IUSHR);
methodVisitor.visitInsn(IXOR);
methodVisitor.visitLdcInsn(new Integer(65280));
methodVisitor.visitInsn(IAND);
methodVisitor.visitVarInsn(ISTORE, 1);
methodVisitor.visitVarInsn(ILOAD, 0);
methodVisitor.visitVarInsn(ILOAD, 1);
methodVisitor.visitVarInsn(ILOAD, 1);
methodVisitor.visitIntInsn(BIPUSH, 8);
methodVisitor.visitInsn(ISHL);
methodVisitor.visitInsn(IXOR);
methodVisitor.visitInsn(IXOR);
methodVisitor.visitVarInsn(ISTORE, 0);
methodVisitor.visitVarInsn(ILOAD, 0);
methodVisitor.visitInsn(IRETURN);
methodVisitor.visitMaxs(4, 2);
methodVisitor.visitEnd();
}
{
methodVisitor = classWriter.visitMethod(ACC_PUBLIC | ACC_STATIC, "unshuffle", "(J)J", null, null);
methodVisitor.visitCode();
methodVisitor.visitVarInsn(LLOAD, 0);
methodVisitor.visitVarInsn(LLOAD, 0);
methodVisitor.visitInsn(ICONST_1);
methodVisitor.visitInsn(LUSHR);
methodVisitor.visitInsn(LXOR);
methodVisitor.visitLdcInsn(new Long(2459565876494606882L));
methodVisitor.visitInsn(LAND);
methodVisitor.visitVarInsn(LSTORE, 2);
methodVisitor.visitVarInsn(LLOAD, 0);
methodVisitor.visitVarInsn(LLOAD, 2);
methodVisitor.visitVarInsn(LLOAD, 2);
methodVisitor.visitInsn(ICONST_1);
methodVisitor.visitInsn(LSHL);
methodVisitor.visitInsn(LXOR);
methodVisitor.visitInsn(LXOR);
methodVisitor.visitVarInsn(LSTORE, 0);
methodVisitor.visitVarInsn(LLOAD, 0);
methodVisitor.visitVarInsn(LLOAD, 0);
methodVisitor.visitInsn(ICONST_2);
methodVisitor.visitInsn(LUSHR);
methodVisitor.visitInsn(LXOR);
methodVisitor.visitLdcInsn(new Long(868082074056920076L));
methodVisitor.visitInsn(LAND);
methodVisitor.visitVarInsn(LSTORE, 2);
methodVisitor.visitVarInsn(LLOAD, 0);
methodVisitor.visitVarInsn(LLOAD, 2);
methodVisitor.visitVarInsn(LLOAD, 2);
methodVisitor.visitInsn(ICONST_2);
methodVisitor.visitInsn(LSHL);
methodVisitor.visitInsn(LXOR);
methodVisitor.visitInsn(LXOR);
methodVisitor.visitVarInsn(LSTORE, 0);
methodVisitor.visitVarInsn(LLOAD, 0);
methodVisitor.visitVarInsn(LLOAD, 0);
methodVisitor.visitInsn(ICONST_4);
methodVisitor.visitInsn(LUSHR);
methodVisitor.visitInsn(LXOR);
methodVisitor.visitLdcInsn(new Long(67555025218437360L));
methodVisitor.visitInsn(LAND);
methodVisitor.visitVarInsn(LSTORE, 2);
methodVisitor.visitVarInsn(LLOAD, 0);
methodVisitor.visitVarInsn(LLOAD, 2);
methodVisitor.visitVarInsn(LLOAD, 2);
methodVisitor.visitInsn(ICONST_4);
methodVisitor.visitInsn(LSHL);
methodVisitor.visitInsn(LXOR);
methodVisitor.visitInsn(LXOR);
methodVisitor.visitVarInsn(LSTORE, 0);
methodVisitor.visitVarInsn(LLOAD, 0);
methodVisitor.visitVarInsn(LLOAD, 0);
methodVisitor.visitIntInsn(BIPUSH, 8);
methodVisitor.visitInsn(LUSHR);
methodVisitor.visitInsn(LXOR);
methodVisitor.visitLdcInsn(new Long(280375465148160L));
methodVisitor.visitInsn(LAND);
methodVisitor.visitVarInsn(LSTORE, 2);
methodVisitor.visitVarInsn(LLOAD, 0);
methodVisitor.visitVarInsn(LLOAD, 2);
methodVisitor.visitVarInsn(LLOAD, 2);
methodVisitor.visitIntInsn(BIPUSH, 8);
methodVisitor.visitInsn(LSHL);
methodVisitor.visitInsn(LXOR);
methodVisitor.visitInsn(LXOR);
methodVisitor.visitVarInsn(LSTORE, 0);
methodVisitor.visitVarInsn(LLOAD, 0);
methodVisitor.visitVarInsn(LLOAD, 0);
methodVisitor.visitIntInsn(BIPUSH, 16);
methodVisitor.visitInsn(LUSHR);
methodVisitor.visitInsn(LXOR);
methodVisitor.visitLdcInsn(new Long(4294901760L));
methodVisitor.visitInsn(LAND);
methodVisitor.visitVarInsn(LSTORE, 2);
methodVisitor.visitVarInsn(LLOAD, 0);
methodVisitor.visitVarInsn(LLOAD, 2);
methodVisitor.visitVarInsn(LLOAD, 2);
methodVisitor.visitIntInsn(BIPUSH, 16);
methodVisitor.visitInsn(LSHL);
methodVisitor.visitInsn(LXOR);
methodVisitor.visitInsn(LXOR);
methodVisitor.visitVarInsn(LSTORE, 0);
methodVisitor.visitVarInsn(LLOAD, 0);
methodVisitor.visitInsn(LRETURN);
methodVisitor.visitMaxs(7, 4);
methodVisitor.visitEnd();
}
{
methodVisitor = classWriter.visitMethod(ACC_PUBLIC | ACC_STATIC, "unshuffle2", "(I)I", null, null);
methodVisitor.visitCode();
methodVisitor.visitVarInsn(ILOAD, 0);
methodVisitor.visitVarInsn(ILOAD, 0);
methodVisitor.visitIntInsn(BIPUSH, 8);
methodVisitor.visitInsn(IUSHR);
methodVisitor.visitInsn(IXOR);
methodVisitor.visitLdcInsn(new Integer(65280));
methodVisitor.visitInsn(IAND);
methodVisitor.visitVarInsn(ISTORE, 1);
methodVisitor.visitVarInsn(ILOAD, 0);
methodVisitor.visitVarInsn(ILOAD, 1);
methodVisitor.visitVarInsn(ILOAD, 1);
methodVisitor.visitIntInsn(BIPUSH, 8);
methodVisitor.visitInsn(ISHL);
methodVisitor.visitInsn(IXOR);
methodVisitor.visitInsn(IXOR);
methodVisitor.visitVarInsn(ISTORE, 0);
methodVisitor.visitVarInsn(ILOAD, 0);
methodVisitor.visitVarInsn(ILOAD, 0);
methodVisitor.visitInsn(ICONST_4);
methodVisitor.visitInsn(IUSHR);
methodVisitor.visitInsn(IXOR);
methodVisitor.visitLdcInsn(new Integer(15728880));
methodVisitor.visitInsn(IAND);
methodVisitor.visitVarInsn(ISTORE, 1);
methodVisitor.visitVarInsn(ILOAD, 0);
methodVisitor.visitVarInsn(ILOAD, 1);
methodVisitor.visitVarInsn(ILOAD, 1);
methodVisitor.visitInsn(ICONST_4);
methodVisitor.visitInsn(ISHL);
methodVisitor.visitInsn(IXOR);
methodVisitor.visitInsn(IXOR);
methodVisitor.visitVarInsn(ISTORE, 0);
methodVisitor.visitVarInsn(ILOAD, 0);
methodVisitor.visitVarInsn(ILOAD, 0);
methodVisitor.visitIntInsn(BIPUSH, 14);
methodVisitor.visitInsn(IUSHR);
methodVisitor.visitInsn(IXOR);
methodVisitor.visitLdcInsn(new Integer(52428));
methodVisitor.visitInsn(IAND);
methodVisitor.visitVarInsn(ISTORE, 1);
methodVisitor.visitVarInsn(ILOAD, 0);
methodVisitor.visitVarInsn(ILOAD, 1);
methodVisitor.visitVarInsn(ILOAD, 1);
methodVisitor.visitIntInsn(BIPUSH, 14);
methodVisitor.visitInsn(ISHL);
methodVisitor.visitInsn(IXOR);
methodVisitor.visitInsn(IXOR);
methodVisitor.visitVarInsn(ISTORE, 0);
methodVisitor.visitVarInsn(ILOAD, 0);
methodVisitor.visitVarInsn(ILOAD, 0);
methodVisitor.visitIntInsn(BIPUSH, 7);
methodVisitor.visitInsn(IUSHR);
methodVisitor.visitInsn(IXOR);
methodVisitor.visitLdcInsn(new Integer(11141290));
methodVisitor.visitInsn(IAND);
methodVisitor.visitVarInsn(ISTORE, 1);
methodVisitor.visitVarInsn(ILOAD, 0);
methodVisitor.visitVarInsn(ILOAD, 1);
methodVisitor.visitVarInsn(ILOAD, 1);
methodVisitor.visitIntInsn(BIPUSH, 7);
methodVisitor.visitInsn(ISHL);
methodVisitor.visitInsn(IXOR);
methodVisitor.visitInsn(IXOR);
methodVisitor.visitVarInsn(ISTORE, 0);
methodVisitor.visitVarInsn(ILOAD, 0);
methodVisitor.visitInsn(IRETURN);
methodVisitor.visitMaxs(4, 2);
methodVisitor.visitEnd();
}
classWriter.visitEnd();

return classWriter.toByteArray();
}
}
