package asm.org.bouncycastle.crypto.modes;
import org.objectweb.asm.AnnotationVisitor;
import org.objectweb.asm.Attribute;
import org.objectweb.asm.ClassReader;
import org.objectweb.asm.ClassWriter;
import org.objectweb.asm.ConstantDynamic;
import org.objectweb.asm.FieldVisitor;
import org.objectweb.asm.Handle;
import org.objectweb.asm.Label;
import org.objectweb.asm.MethodVisitor;
import org.objectweb.asm.Opcodes;
import org.objectweb.asm.RecordComponentVisitor;
import org.objectweb.asm.Type;
import org.objectweb.asm.TypePath;
public class CCMBlockCipherDump implements Opcodes {

public static byte[] dump () throws Exception {

ClassWriter classWriter = new ClassWriter(0);
FieldVisitor fieldVisitor;
RecordComponentVisitor recordComponentVisitor;
MethodVisitor methodVisitor;
AnnotationVisitor annotationVisitor0;

classWriter.visit(V1_5, ACC_PUBLIC | ACC_SUPER, "org/bouncycastle/crypto/modes/CCMBlockCipher", null, "java/lang/Object", new String[] { "org/bouncycastle/crypto/modes/AEADBlockCipher" });

classWriter.visitInnerClass("org/bouncycastle/crypto/modes/CCMBlockCipher$ExposedByteArrayOutputStream", "org/bouncycastle/crypto/modes/CCMBlockCipher", "ExposedByteArrayOutputStream", ACC_PRIVATE);

{
fieldVisitor = classWriter.visitField(ACC_PRIVATE, "cipher", "Lorg/bouncycastle/crypto/BlockCipher;", null, null);
fieldVisitor.visitEnd();
}
{
fieldVisitor = classWriter.visitField(ACC_PRIVATE, "blockSize", "I", null, null);
fieldVisitor.visitEnd();
}
{
fieldVisitor = classWriter.visitField(ACC_PRIVATE, "forEncryption", "Z", null, null);
fieldVisitor.visitEnd();
}
{
fieldVisitor = classWriter.visitField(ACC_PRIVATE, "nonce", "[B", null, null);
fieldVisitor.visitEnd();
}
{
fieldVisitor = classWriter.visitField(ACC_PRIVATE, "initialAssociatedText", "[B", null, null);
fieldVisitor.visitEnd();
}
{
fieldVisitor = classWriter.visitField(ACC_PRIVATE, "macSize", "I", null, null);
fieldVisitor.visitEnd();
}
{
fieldVisitor = classWriter.visitField(ACC_PRIVATE, "keyParam", "Lorg/bouncycastle/crypto/CipherParameters;", null, null);
fieldVisitor.visitEnd();
}
{
fieldVisitor = classWriter.visitField(ACC_PRIVATE, "macBlock", "[B", null, null);
fieldVisitor.visitEnd();
}
{
fieldVisitor = classWriter.visitField(ACC_PRIVATE, "associatedText", "Lorg/bouncycastle/crypto/modes/CCMBlockCipher$ExposedByteArrayOutputStream;", null, null);
fieldVisitor.visitEnd();
}
{
fieldVisitor = classWriter.visitField(ACC_PRIVATE, "data", "Lorg/bouncycastle/crypto/modes/CCMBlockCipher$ExposedByteArrayOutputStream;", null, null);
fieldVisitor.visitEnd();
}
{
methodVisitor = classWriter.visitMethod(ACC_PUBLIC, "<init>", "(Lorg/bouncycastle/crypto/BlockCipher;)V", null, null);
methodVisitor.visitCode();
methodVisitor.visitVarInsn(ALOAD, 0);
methodVisitor.visitMethodInsn(INVOKESPECIAL, "java/lang/Object", "<init>", "()V", false);
methodVisitor.visitVarInsn(ALOAD, 0);
methodVisitor.visitTypeInsn(NEW, "org/bouncycastle/crypto/modes/CCMBlockCipher$ExposedByteArrayOutputStream");
methodVisitor.visitInsn(DUP);
methodVisitor.visitVarInsn(ALOAD, 0);
methodVisitor.visitMethodInsn(INVOKESPECIAL, "org/bouncycastle/crypto/modes/CCMBlockCipher$ExposedByteArrayOutputStream", "<init>", "(Lorg/bouncycastle/crypto/modes/CCMBlockCipher;)V", false);
methodVisitor.visitFieldInsn(PUTFIELD, "org/bouncycastle/crypto/modes/CCMBlockCipher", "associatedText", "Lorg/bouncycastle/crypto/modes/CCMBlockCipher$ExposedByteArrayOutputStream;");
methodVisitor.visitVarInsn(ALOAD, 0);
methodVisitor.visitTypeInsn(NEW, "org/bouncycastle/crypto/modes/CCMBlockCipher$ExposedByteArrayOutputStream");
methodVisitor.visitInsn(DUP);
methodVisitor.visitVarInsn(ALOAD, 0);
methodVisitor.visitMethodInsn(INVOKESPECIAL, "org/bouncycastle/crypto/modes/CCMBlockCipher$ExposedByteArrayOutputStream", "<init>", "(Lorg/bouncycastle/crypto/modes/CCMBlockCipher;)V", false);
methodVisitor.visitFieldInsn(PUTFIELD, "org/bouncycastle/crypto/modes/CCMBlockCipher", "data", "Lorg/bouncycastle/crypto/modes/CCMBlockCipher$ExposedByteArrayOutputStream;");
methodVisitor.visitVarInsn(ALOAD, 0);
methodVisitor.visitVarInsn(ALOAD, 1);
methodVisitor.visitFieldInsn(PUTFIELD, "org/bouncycastle/crypto/modes/CCMBlockCipher", "cipher", "Lorg/bouncycastle/crypto/BlockCipher;");
methodVisitor.visitVarInsn(ALOAD, 0);
methodVisitor.visitVarInsn(ALOAD, 1);
methodVisitor.visitMethodInsn(INVOKEINTERFACE, "org/bouncycastle/crypto/BlockCipher", "getBlockSize", "()I", true);
methodVisitor.visitFieldInsn(PUTFIELD, "org/bouncycastle/crypto/modes/CCMBlockCipher", "blockSize", "I");
methodVisitor.visitVarInsn(ALOAD, 0);
methodVisitor.visitVarInsn(ALOAD, 0);
methodVisitor.visitFieldInsn(GETFIELD, "org/bouncycastle/crypto/modes/CCMBlockCipher", "blockSize", "I");
methodVisitor.visitIntInsn(NEWARRAY, T_BYTE);
methodVisitor.visitFieldInsn(PUTFIELD, "org/bouncycastle/crypto/modes/CCMBlockCipher", "macBlock", "[B");
methodVisitor.visitVarInsn(ALOAD, 0);
methodVisitor.visitFieldInsn(GETFIELD, "org/bouncycastle/crypto/modes/CCMBlockCipher", "blockSize", "I");
methodVisitor.visitIntInsn(BIPUSH, 16);
Label label0 = new Label();
methodVisitor.visitJumpInsn(IF_ICMPEQ, label0);
methodVisitor.visitTypeInsn(NEW, "java/lang/IllegalArgumentException");
methodVisitor.visitInsn(DUP);
methodVisitor.visitLdcInsn("cipher required with a block size of 16.");
methodVisitor.visitMethodInsn(INVOKESPECIAL, "java/lang/IllegalArgumentException", "<init>", "(Ljava/lang/String;)V", false);
methodVisitor.visitInsn(ATHROW);
methodVisitor.visitLabel(label0);
methodVisitor.visitInsn(RETURN);
methodVisitor.visitMaxs(4, 2);
methodVisitor.visitEnd();
}
{
methodVisitor = classWriter.visitMethod(ACC_PUBLIC, "getUnderlyingCipher", "()Lorg/bouncycastle/crypto/BlockCipher;", null, null);
methodVisitor.visitCode();
methodVisitor.visitVarInsn(ALOAD, 0);
methodVisitor.visitFieldInsn(GETFIELD, "org/bouncycastle/crypto/modes/CCMBlockCipher", "cipher", "Lorg/bouncycastle/crypto/BlockCipher;");
methodVisitor.visitInsn(ARETURN);
methodVisitor.visitMaxs(1, 1);
methodVisitor.visitEnd();
}
{
methodVisitor = classWriter.visitMethod(ACC_PUBLIC, "init", "(ZLorg/bouncycastle/crypto/CipherParameters;)V", null, new String[] { "java/lang/IllegalArgumentException" });
methodVisitor.visitCode();
methodVisitor.visitVarInsn(ALOAD, 0);
methodVisitor.visitVarInsn(ILOAD, 1);
methodVisitor.visitFieldInsn(PUTFIELD, "org/bouncycastle/crypto/modes/CCMBlockCipher", "forEncryption", "Z");
methodVisitor.visitVarInsn(ALOAD, 2);
methodVisitor.visitTypeInsn(INSTANCEOF, "org/bouncycastle/crypto/params/AEADParameters");
Label label0 = new Label();
methodVisitor.visitJumpInsn(IFEQ, label0);
methodVisitor.visitVarInsn(ALOAD, 2);
methodVisitor.visitTypeInsn(CHECKCAST, "org/bouncycastle/crypto/params/AEADParameters");
methodVisitor.visitVarInsn(ASTORE, 4);
methodVisitor.visitVarInsn(ALOAD, 0);
methodVisitor.visitVarInsn(ALOAD, 4);
methodVisitor.visitMethodInsn(INVOKEVIRTUAL, "org/bouncycastle/crypto/params/AEADParameters", "getNonce", "()[B", false);
methodVisitor.visitFieldInsn(PUTFIELD, "org/bouncycastle/crypto/modes/CCMBlockCipher", "nonce", "[B");
methodVisitor.visitVarInsn(ALOAD, 0);
methodVisitor.visitVarInsn(ALOAD, 4);
methodVisitor.visitMethodInsn(INVOKEVIRTUAL, "org/bouncycastle/crypto/params/AEADParameters", "getAssociatedText", "()[B", false);
methodVisitor.visitFieldInsn(PUTFIELD, "org/bouncycastle/crypto/modes/CCMBlockCipher", "initialAssociatedText", "[B");
methodVisitor.visitVarInsn(ALOAD, 0);
methodVisitor.visitVarInsn(ALOAD, 0);
methodVisitor.visitVarInsn(ILOAD, 1);
methodVisitor.visitVarInsn(ALOAD, 4);
methodVisitor.visitMethodInsn(INVOKEVIRTUAL, "org/bouncycastle/crypto/params/AEADParameters", "getMacSize", "()I", false);
methodVisitor.visitMethodInsn(INVOKESPECIAL, "org/bouncycastle/crypto/modes/CCMBlockCipher", "getMacSize", "(ZI)I", false);
methodVisitor.visitFieldInsn(PUTFIELD, "org/bouncycastle/crypto/modes/CCMBlockCipher", "macSize", "I");
methodVisitor.visitVarInsn(ALOAD, 4);
methodVisitor.visitMethodInsn(INVOKEVIRTUAL, "org/bouncycastle/crypto/params/AEADParameters", "getKey", "()Lorg/bouncycastle/crypto/params/KeyParameter;", false);
methodVisitor.visitVarInsn(ASTORE, 3);
Label label1 = new Label();
methodVisitor.visitJumpInsn(GOTO, label1);
methodVisitor.visitLabel(label0);
methodVisitor.visitVarInsn(ALOAD, 2);
methodVisitor.visitTypeInsn(INSTANCEOF, "org/bouncycastle/crypto/params/ParametersWithIV");
Label label2 = new Label();
methodVisitor.visitJumpInsn(IFEQ, label2);
methodVisitor.visitVarInsn(ALOAD, 2);
methodVisitor.visitTypeInsn(CHECKCAST, "org/bouncycastle/crypto/params/ParametersWithIV");
methodVisitor.visitVarInsn(ASTORE, 4);
methodVisitor.visitVarInsn(ALOAD, 0);
methodVisitor.visitVarInsn(ALOAD, 4);
methodVisitor.visitMethodInsn(INVOKEVIRTUAL, "org/bouncycastle/crypto/params/ParametersWithIV", "getIV", "()[B", false);
methodVisitor.visitFieldInsn(PUTFIELD, "org/bouncycastle/crypto/modes/CCMBlockCipher", "nonce", "[B");
methodVisitor.visitVarInsn(ALOAD, 0);
methodVisitor.visitInsn(ACONST_NULL);
methodVisitor.visitFieldInsn(PUTFIELD, "org/bouncycastle/crypto/modes/CCMBlockCipher", "initialAssociatedText", "[B");
methodVisitor.visitVarInsn(ALOAD, 0);
methodVisitor.visitVarInsn(ALOAD, 0);
methodVisitor.visitVarInsn(ILOAD, 1);
methodVisitor.visitIntInsn(BIPUSH, 64);
methodVisitor.visitMethodInsn(INVOKESPECIAL, "org/bouncycastle/crypto/modes/CCMBlockCipher", "getMacSize", "(ZI)I", false);
methodVisitor.visitFieldInsn(PUTFIELD, "org/bouncycastle/crypto/modes/CCMBlockCipher", "macSize", "I");
methodVisitor.visitVarInsn(ALOAD, 4);
methodVisitor.visitMethodInsn(INVOKEVIRTUAL, "org/bouncycastle/crypto/params/ParametersWithIV", "getParameters", "()Lorg/bouncycastle/crypto/CipherParameters;", false);
methodVisitor.visitVarInsn(ASTORE, 3);
methodVisitor.visitJumpInsn(GOTO, label1);
methodVisitor.visitLabel(label2);
methodVisitor.visitTypeInsn(NEW, "java/lang/IllegalArgumentException");
methodVisitor.visitInsn(DUP);
methodVisitor.visitTypeInsn(NEW, "java/lang/StringBuilder");
methodVisitor.visitInsn(DUP);
methodVisitor.visitMethodInsn(INVOKESPECIAL, "java/lang/StringBuilder", "<init>", "()V", false);
methodVisitor.visitLdcInsn("invalid parameters passed to CCM: ");
methodVisitor.visitMethodInsn(INVOKEVIRTUAL, "java/lang/StringBuilder", "append", "(Ljava/lang/String;)Ljava/lang/StringBuilder;", false);
methodVisitor.visitVarInsn(ALOAD, 2);
methodVisitor.visitMethodInsn(INVOKEVIRTUAL, "java/lang/Object", "getClass", "()Ljava/lang/Class;", false);
methodVisitor.visitMethodInsn(INVOKEVIRTUAL, "java/lang/Class", "getName", "()Ljava/lang/String;", false);
methodVisitor.visitMethodInsn(INVOKEVIRTUAL, "java/lang/StringBuilder", "append", "(Ljava/lang/String;)Ljava/lang/StringBuilder;", false);
methodVisitor.visitMethodInsn(INVOKEVIRTUAL, "java/lang/StringBuilder", "toString", "()Ljava/lang/String;", false);
methodVisitor.visitMethodInsn(INVOKESPECIAL, "java/lang/IllegalArgumentException", "<init>", "(Ljava/lang/String;)V", false);
methodVisitor.visitInsn(ATHROW);
methodVisitor.visitLabel(label1);
methodVisitor.visitVarInsn(ALOAD, 3);
Label label3 = new Label();
methodVisitor.visitJumpInsn(IFNULL, label3);
methodVisitor.visitVarInsn(ALOAD, 0);
methodVisitor.visitVarInsn(ALOAD, 3);
methodVisitor.visitFieldInsn(PUTFIELD, "org/bouncycastle/crypto/modes/CCMBlockCipher", "keyParam", "Lorg/bouncycastle/crypto/CipherParameters;");
methodVisitor.visitLabel(label3);
methodVisitor.visitVarInsn(ALOAD, 0);
methodVisitor.visitFieldInsn(GETFIELD, "org/bouncycastle/crypto/modes/CCMBlockCipher", "nonce", "[B");
Label label4 = new Label();
methodVisitor.visitJumpInsn(IFNULL, label4);
methodVisitor.visitVarInsn(ALOAD, 0);
methodVisitor.visitFieldInsn(GETFIELD, "org/bouncycastle/crypto/modes/CCMBlockCipher", "nonce", "[B");
methodVisitor.visitInsn(ARRAYLENGTH);
methodVisitor.visitIntInsn(BIPUSH, 7);
methodVisitor.visitJumpInsn(IF_ICMPLT, label4);
methodVisitor.visitVarInsn(ALOAD, 0);
methodVisitor.visitFieldInsn(GETFIELD, "org/bouncycastle/crypto/modes/CCMBlockCipher", "nonce", "[B");
methodVisitor.visitInsn(ARRAYLENGTH);
methodVisitor.visitIntInsn(BIPUSH, 13);
Label label5 = new Label();
methodVisitor.visitJumpInsn(IF_ICMPLE, label5);
methodVisitor.visitLabel(label4);
methodVisitor.visitTypeInsn(NEW, "java/lang/IllegalArgumentException");
methodVisitor.visitInsn(DUP);
methodVisitor.visitLdcInsn("nonce must have length from 7 to 13 octets");
methodVisitor.visitMethodInsn(INVOKESPECIAL, "java/lang/IllegalArgumentException", "<init>", "(Ljava/lang/String;)V", false);
methodVisitor.visitInsn(ATHROW);
methodVisitor.visitLabel(label5);
methodVisitor.visitVarInsn(ALOAD, 0);
methodVisitor.visitMethodInsn(INVOKEVIRTUAL, "org/bouncycastle/crypto/modes/CCMBlockCipher", "reset", "()V", false);
methodVisitor.visitInsn(RETURN);
methodVisitor.visitMaxs(4, 5);
methodVisitor.visitEnd();
}
{
methodVisitor = classWriter.visitMethod(ACC_PUBLIC, "getAlgorithmName", "()Ljava/lang/String;", null, null);
methodVisitor.visitCode();
methodVisitor.visitTypeInsn(NEW, "java/lang/StringBuilder");
methodVisitor.visitInsn(DUP);
methodVisitor.visitMethodInsn(INVOKESPECIAL, "java/lang/StringBuilder", "<init>", "()V", false);
methodVisitor.visitVarInsn(ALOAD, 0);
methodVisitor.visitFieldInsn(GETFIELD, "org/bouncycastle/crypto/modes/CCMBlockCipher", "cipher", "Lorg/bouncycastle/crypto/BlockCipher;");
methodVisitor.visitMethodInsn(INVOKEINTERFACE, "org/bouncycastle/crypto/BlockCipher", "getAlgorithmName", "()Ljava/lang/String;", true);
methodVisitor.visitMethodInsn(INVOKEVIRTUAL, "java/lang/StringBuilder", "append", "(Ljava/lang/String;)Ljava/lang/StringBuilder;", false);
methodVisitor.visitLdcInsn("/CCM");
methodVisitor.visitMethodInsn(INVOKEVIRTUAL, "java/lang/StringBuilder", "append", "(Ljava/lang/String;)Ljava/lang/StringBuilder;", false);
methodVisitor.visitMethodInsn(INVOKEVIRTUAL, "java/lang/StringBuilder", "toString", "()Ljava/lang/String;", false);
methodVisitor.visitInsn(ARETURN);
methodVisitor.visitMaxs(2, 1);
methodVisitor.visitEnd();
}
{
methodVisitor = classWriter.visitMethod(ACC_PUBLIC, "processAADByte", "(B)V", null, null);
methodVisitor.visitCode();
methodVisitor.visitVarInsn(ALOAD, 0);
methodVisitor.visitFieldInsn(GETFIELD, "org/bouncycastle/crypto/modes/CCMBlockCipher", "associatedText", "Lorg/bouncycastle/crypto/modes/CCMBlockCipher$ExposedByteArrayOutputStream;");
methodVisitor.visitVarInsn(ILOAD, 1);
methodVisitor.visitMethodInsn(INVOKEVIRTUAL, "org/bouncycastle/crypto/modes/CCMBlockCipher$ExposedByteArrayOutputStream", "write", "(I)V", false);
methodVisitor.visitInsn(RETURN);
methodVisitor.visitMaxs(2, 2);
methodVisitor.visitEnd();
}
{
methodVisitor = classWriter.visitMethod(ACC_PUBLIC, "processAADBytes", "([BII)V", null, null);
methodVisitor.visitCode();
methodVisitor.visitVarInsn(ALOAD, 0);
methodVisitor.visitFieldInsn(GETFIELD, "org/bouncycastle/crypto/modes/CCMBlockCipher", "associatedText", "Lorg/bouncycastle/crypto/modes/CCMBlockCipher$ExposedByteArrayOutputStream;");
methodVisitor.visitVarInsn(ALOAD, 1);
methodVisitor.visitVarInsn(ILOAD, 2);
methodVisitor.visitVarInsn(ILOAD, 3);
methodVisitor.visitMethodInsn(INVOKEVIRTUAL, "org/bouncycastle/crypto/modes/CCMBlockCipher$ExposedByteArrayOutputStream", "write", "([BII)V", false);
methodVisitor.visitInsn(RETURN);
methodVisitor.visitMaxs(4, 4);
methodVisitor.visitEnd();
}
{
methodVisitor = classWriter.visitMethod(ACC_PUBLIC, "processByte", "(B[BI)I", null, new String[] { "org/bouncycastle/crypto/DataLengthException", "java/lang/IllegalStateException" });
methodVisitor.visitCode();
methodVisitor.visitVarInsn(ALOAD, 0);
methodVisitor.visitFieldInsn(GETFIELD, "org/bouncycastle/crypto/modes/CCMBlockCipher", "data", "Lorg/bouncycastle/crypto/modes/CCMBlockCipher$ExposedByteArrayOutputStream;");
methodVisitor.visitVarInsn(ILOAD, 1);
methodVisitor.visitMethodInsn(INVOKEVIRTUAL, "org/bouncycastle/crypto/modes/CCMBlockCipher$ExposedByteArrayOutputStream", "write", "(I)V", false);
methodVisitor.visitInsn(ICONST_0);
methodVisitor.visitInsn(IRETURN);
methodVisitor.visitMaxs(2, 4);
methodVisitor.visitEnd();
}
{
methodVisitor = classWriter.visitMethod(ACC_PUBLIC, "processBytes", "([BII[BI)I", null, new String[] { "org/bouncycastle/crypto/DataLengthException", "java/lang/IllegalStateException" });
methodVisitor.visitCode();
methodVisitor.visitVarInsn(ALOAD, 1);
methodVisitor.visitInsn(ARRAYLENGTH);
methodVisitor.visitVarInsn(ILOAD, 2);
methodVisitor.visitVarInsn(ILOAD, 3);
methodVisitor.visitInsn(IADD);
Label label0 = new Label();
methodVisitor.visitJumpInsn(IF_ICMPGE, label0);
methodVisitor.visitTypeInsn(NEW, "org/bouncycastle/crypto/DataLengthException");
methodVisitor.visitInsn(DUP);
methodVisitor.visitLdcInsn("Input buffer too short");
methodVisitor.visitMethodInsn(INVOKESPECIAL, "org/bouncycastle/crypto/DataLengthException", "<init>", "(Ljava/lang/String;)V", false);
methodVisitor.visitInsn(ATHROW);
methodVisitor.visitLabel(label0);
methodVisitor.visitVarInsn(ALOAD, 0);
methodVisitor.visitFieldInsn(GETFIELD, "org/bouncycastle/crypto/modes/CCMBlockCipher", "data", "Lorg/bouncycastle/crypto/modes/CCMBlockCipher$ExposedByteArrayOutputStream;");
methodVisitor.visitVarInsn(ALOAD, 1);
methodVisitor.visitVarInsn(ILOAD, 2);
methodVisitor.visitVarInsn(ILOAD, 3);
methodVisitor.visitMethodInsn(INVOKEVIRTUAL, "org/bouncycastle/crypto/modes/CCMBlockCipher$ExposedByteArrayOutputStream", "write", "([BII)V", false);
methodVisitor.visitInsn(ICONST_0);
methodVisitor.visitInsn(IRETURN);
methodVisitor.visitMaxs(4, 6);
methodVisitor.visitEnd();
}
{
methodVisitor = classWriter.visitMethod(ACC_PUBLIC, "doFinal", "([BI)I", null, new String[] { "java/lang/IllegalStateException", "org/bouncycastle/crypto/InvalidCipherTextException" });
methodVisitor.visitCode();
methodVisitor.visitVarInsn(ALOAD, 0);
methodVisitor.visitVarInsn(ALOAD, 0);
methodVisitor.visitFieldInsn(GETFIELD, "org/bouncycastle/crypto/modes/CCMBlockCipher", "data", "Lorg/bouncycastle/crypto/modes/CCMBlockCipher$ExposedByteArrayOutputStream;");
methodVisitor.visitMethodInsn(INVOKEVIRTUAL, "org/bouncycastle/crypto/modes/CCMBlockCipher$ExposedByteArrayOutputStream", "getBuffer", "()[B", false);
methodVisitor.visitInsn(ICONST_0);
methodVisitor.visitVarInsn(ALOAD, 0);
methodVisitor.visitFieldInsn(GETFIELD, "org/bouncycastle/crypto/modes/CCMBlockCipher", "data", "Lorg/bouncycastle/crypto/modes/CCMBlockCipher$ExposedByteArrayOutputStream;");
methodVisitor.visitMethodInsn(INVOKEVIRTUAL, "org/bouncycastle/crypto/modes/CCMBlockCipher$ExposedByteArrayOutputStream", "size", "()I", false);
methodVisitor.visitVarInsn(ALOAD, 1);
methodVisitor.visitVarInsn(ILOAD, 2);
methodVisitor.visitMethodInsn(INVOKEVIRTUAL, "org/bouncycastle/crypto/modes/CCMBlockCipher", "processPacket", "([BII[BI)I", false);
methodVisitor.visitVarInsn(ISTORE, 3);
methodVisitor.visitVarInsn(ALOAD, 0);
methodVisitor.visitMethodInsn(INVOKEVIRTUAL, "org/bouncycastle/crypto/modes/CCMBlockCipher", "reset", "()V", false);
methodVisitor.visitVarInsn(ILOAD, 3);
methodVisitor.visitInsn(IRETURN);
methodVisitor.visitMaxs(6, 4);
methodVisitor.visitEnd();
}
{
methodVisitor = classWriter.visitMethod(ACC_PUBLIC, "reset", "()V", null, null);
methodVisitor.visitCode();
methodVisitor.visitVarInsn(ALOAD, 0);
methodVisitor.visitFieldInsn(GETFIELD, "org/bouncycastle/crypto/modes/CCMBlockCipher", "cipher", "Lorg/bouncycastle/crypto/BlockCipher;");
methodVisitor.visitMethodInsn(INVOKEINTERFACE, "org/bouncycastle/crypto/BlockCipher", "reset", "()V", true);
methodVisitor.visitVarInsn(ALOAD, 0);
methodVisitor.visitFieldInsn(GETFIELD, "org/bouncycastle/crypto/modes/CCMBlockCipher", "associatedText", "Lorg/bouncycastle/crypto/modes/CCMBlockCipher$ExposedByteArrayOutputStream;");
methodVisitor.visitMethodInsn(INVOKEVIRTUAL, "org/bouncycastle/crypto/modes/CCMBlockCipher$ExposedByteArrayOutputStream", "reset", "()V", false);
methodVisitor.visitVarInsn(ALOAD, 0);
methodVisitor.visitFieldInsn(GETFIELD, "org/bouncycastle/crypto/modes/CCMBlockCipher", "data", "Lorg/bouncycastle/crypto/modes/CCMBlockCipher$ExposedByteArrayOutputStream;");
methodVisitor.visitMethodInsn(INVOKEVIRTUAL, "org/bouncycastle/crypto/modes/CCMBlockCipher$ExposedByteArrayOutputStream", "reset", "()V", false);
methodVisitor.visitInsn(RETURN);
methodVisitor.visitMaxs(1, 1);
methodVisitor.visitEnd();
}
{
methodVisitor = classWriter.visitMethod(ACC_PUBLIC, "getMac", "()[B", null, null);
methodVisitor.visitCode();
methodVisitor.visitVarInsn(ALOAD, 0);
methodVisitor.visitFieldInsn(GETFIELD, "org/bouncycastle/crypto/modes/CCMBlockCipher", "macSize", "I");
methodVisitor.visitIntInsn(NEWARRAY, T_BYTE);
methodVisitor.visitVarInsn(ASTORE, 1);
methodVisitor.visitVarInsn(ALOAD, 0);
methodVisitor.visitFieldInsn(GETFIELD, "org/bouncycastle/crypto/modes/CCMBlockCipher", "macBlock", "[B");
methodVisitor.visitInsn(ICONST_0);
methodVisitor.visitVarInsn(ALOAD, 1);
methodVisitor.visitInsn(ICONST_0);
methodVisitor.visitVarInsn(ALOAD, 1);
methodVisitor.visitInsn(ARRAYLENGTH);
methodVisitor.visitMethodInsn(INVOKESTATIC, "java/lang/System", "arraycopy", "(Ljava/lang/Object;ILjava/lang/Object;II)V", false);
methodVisitor.visitVarInsn(ALOAD, 1);
methodVisitor.visitInsn(ARETURN);
methodVisitor.visitMaxs(5, 2);
methodVisitor.visitEnd();
}
{
methodVisitor = classWriter.visitMethod(ACC_PUBLIC, "getUpdateOutputSize", "(I)I", null, null);
methodVisitor.visitCode();
methodVisitor.visitInsn(ICONST_0);
methodVisitor.visitInsn(IRETURN);
methodVisitor.visitMaxs(1, 2);
methodVisitor.visitEnd();
}
{
methodVisitor = classWriter.visitMethod(ACC_PUBLIC, "getOutputSize", "(I)I", null, null);
methodVisitor.visitCode();
methodVisitor.visitVarInsn(ILOAD, 1);
methodVisitor.visitVarInsn(ALOAD, 0);
methodVisitor.visitFieldInsn(GETFIELD, "org/bouncycastle/crypto/modes/CCMBlockCipher", "data", "Lorg/bouncycastle/crypto/modes/CCMBlockCipher$ExposedByteArrayOutputStream;");
methodVisitor.visitMethodInsn(INVOKEVIRTUAL, "org/bouncycastle/crypto/modes/CCMBlockCipher$ExposedByteArrayOutputStream", "size", "()I", false);
methodVisitor.visitInsn(IADD);
methodVisitor.visitVarInsn(ISTORE, 2);
methodVisitor.visitVarInsn(ALOAD, 0);
methodVisitor.visitFieldInsn(GETFIELD, "org/bouncycastle/crypto/modes/CCMBlockCipher", "forEncryption", "Z");
Label label0 = new Label();
methodVisitor.visitJumpInsn(IFEQ, label0);
methodVisitor.visitVarInsn(ILOAD, 2);
methodVisitor.visitVarInsn(ALOAD, 0);
methodVisitor.visitFieldInsn(GETFIELD, "org/bouncycastle/crypto/modes/CCMBlockCipher", "macSize", "I");
methodVisitor.visitInsn(IADD);
methodVisitor.visitInsn(IRETURN);
methodVisitor.visitLabel(label0);
methodVisitor.visitVarInsn(ILOAD, 2);
methodVisitor.visitVarInsn(ALOAD, 0);
methodVisitor.visitFieldInsn(GETFIELD, "org/bouncycastle/crypto/modes/CCMBlockCipher", "macSize", "I");
Label label1 = new Label();
methodVisitor.visitJumpInsn(IF_ICMPGE, label1);
methodVisitor.visitInsn(ICONST_0);
Label label2 = new Label();
methodVisitor.visitJumpInsn(GOTO, label2);
methodVisitor.visitLabel(label1);
methodVisitor.visitVarInsn(ILOAD, 2);
methodVisitor.visitVarInsn(ALOAD, 0);
methodVisitor.visitFieldInsn(GETFIELD, "org/bouncycastle/crypto/modes/CCMBlockCipher", "macSize", "I");
methodVisitor.visitInsn(ISUB);
methodVisitor.visitLabel(label2);
methodVisitor.visitInsn(IRETURN);
methodVisitor.visitMaxs(2, 3);
methodVisitor.visitEnd();
}
{
methodVisitor = classWriter.visitMethod(ACC_PUBLIC, "processPacket", "([BII)[B", null, new String[] { "java/lang/IllegalStateException", "org/bouncycastle/crypto/InvalidCipherTextException" });
methodVisitor.visitCode();
methodVisitor.visitVarInsn(ALOAD, 0);
methodVisitor.visitFieldInsn(GETFIELD, "org/bouncycastle/crypto/modes/CCMBlockCipher", "forEncryption", "Z");
Label label0 = new Label();
methodVisitor.visitJumpInsn(IFEQ, label0);
methodVisitor.visitVarInsn(ILOAD, 3);
methodVisitor.visitVarInsn(ALOAD, 0);
methodVisitor.visitFieldInsn(GETFIELD, "org/bouncycastle/crypto/modes/CCMBlockCipher", "macSize", "I");
methodVisitor.visitInsn(IADD);
methodVisitor.visitIntInsn(NEWARRAY, T_BYTE);
methodVisitor.visitVarInsn(ASTORE, 4);
Label label1 = new Label();
methodVisitor.visitJumpInsn(GOTO, label1);
methodVisitor.visitLabel(label0);
methodVisitor.visitVarInsn(ILOAD, 3);
methodVisitor.visitVarInsn(ALOAD, 0);
methodVisitor.visitFieldInsn(GETFIELD, "org/bouncycastle/crypto/modes/CCMBlockCipher", "macSize", "I");
Label label2 = new Label();
methodVisitor.visitJumpInsn(IF_ICMPGE, label2);
methodVisitor.visitTypeInsn(NEW, "org/bouncycastle/crypto/InvalidCipherTextException");
methodVisitor.visitInsn(DUP);
methodVisitor.visitLdcInsn("data too short");
methodVisitor.visitMethodInsn(INVOKESPECIAL, "org/bouncycastle/crypto/InvalidCipherTextException", "<init>", "(Ljava/lang/String;)V", false);
methodVisitor.visitInsn(ATHROW);
methodVisitor.visitLabel(label2);
methodVisitor.visitVarInsn(ILOAD, 3);
methodVisitor.visitVarInsn(ALOAD, 0);
methodVisitor.visitFieldInsn(GETFIELD, "org/bouncycastle/crypto/modes/CCMBlockCipher", "macSize", "I");
methodVisitor.visitInsn(ISUB);
methodVisitor.visitIntInsn(NEWARRAY, T_BYTE);
methodVisitor.visitVarInsn(ASTORE, 4);
methodVisitor.visitLabel(label1);
methodVisitor.visitVarInsn(ALOAD, 0);
methodVisitor.visitVarInsn(ALOAD, 1);
methodVisitor.visitVarInsn(ILOAD, 2);
methodVisitor.visitVarInsn(ILOAD, 3);
methodVisitor.visitVarInsn(ALOAD, 4);
methodVisitor.visitInsn(ICONST_0);
methodVisitor.visitMethodInsn(INVOKEVIRTUAL, "org/bouncycastle/crypto/modes/CCMBlockCipher", "processPacket", "([BII[BI)I", false);
methodVisitor.visitInsn(POP);
methodVisitor.visitVarInsn(ALOAD, 4);
methodVisitor.visitInsn(ARETURN);
methodVisitor.visitMaxs(6, 5);
methodVisitor.visitEnd();
}
{
methodVisitor = classWriter.visitMethod(ACC_PUBLIC, "processPacket", "([BII[BI)I", null, new String[] { "java/lang/IllegalStateException", "org/bouncycastle/crypto/InvalidCipherTextException", "org/bouncycastle/crypto/DataLengthException" });
methodVisitor.visitCode();
methodVisitor.visitVarInsn(ALOAD, 0);
methodVisitor.visitFieldInsn(GETFIELD, "org/bouncycastle/crypto/modes/CCMBlockCipher", "keyParam", "Lorg/bouncycastle/crypto/CipherParameters;");
Label label0 = new Label();
methodVisitor.visitJumpInsn(IFNONNULL, label0);
methodVisitor.visitTypeInsn(NEW, "java/lang/IllegalStateException");
methodVisitor.visitInsn(DUP);
methodVisitor.visitLdcInsn("CCM cipher unitialized.");
methodVisitor.visitMethodInsn(INVOKESPECIAL, "java/lang/IllegalStateException", "<init>", "(Ljava/lang/String;)V", false);
methodVisitor.visitInsn(ATHROW);
methodVisitor.visitLabel(label0);
methodVisitor.visitVarInsn(ALOAD, 0);
methodVisitor.visitFieldInsn(GETFIELD, "org/bouncycastle/crypto/modes/CCMBlockCipher", "nonce", "[B");
methodVisitor.visitInsn(ARRAYLENGTH);
methodVisitor.visitVarInsn(ISTORE, 6);
methodVisitor.visitIntInsn(BIPUSH, 15);
methodVisitor.visitVarInsn(ILOAD, 6);
methodVisitor.visitInsn(ISUB);
methodVisitor.visitVarInsn(ISTORE, 7);
methodVisitor.visitVarInsn(ILOAD, 7);
methodVisitor.visitInsn(ICONST_4);
Label label1 = new Label();
methodVisitor.visitJumpInsn(IF_ICMPGE, label1);
methodVisitor.visitInsn(ICONST_1);
methodVisitor.visitIntInsn(BIPUSH, 8);
methodVisitor.visitVarInsn(ILOAD, 7);
methodVisitor.visitInsn(IMUL);
methodVisitor.visitInsn(ISHL);
methodVisitor.visitVarInsn(ISTORE, 8);
methodVisitor.visitVarInsn(ILOAD, 3);
methodVisitor.visitVarInsn(ILOAD, 8);
methodVisitor.visitJumpInsn(IF_ICMPLT, label1);
methodVisitor.visitTypeInsn(NEW, "java/lang/IllegalStateException");
methodVisitor.visitInsn(DUP);
methodVisitor.visitLdcInsn("CCM packet too large for choice of q.");
methodVisitor.visitMethodInsn(INVOKESPECIAL, "java/lang/IllegalStateException", "<init>", "(Ljava/lang/String;)V", false);
methodVisitor.visitInsn(ATHROW);
methodVisitor.visitLabel(label1);
methodVisitor.visitVarInsn(ALOAD, 0);
methodVisitor.visitFieldInsn(GETFIELD, "org/bouncycastle/crypto/modes/CCMBlockCipher", "blockSize", "I");
methodVisitor.visitIntInsn(NEWARRAY, T_BYTE);
methodVisitor.visitVarInsn(ASTORE, 8);
methodVisitor.visitVarInsn(ALOAD, 8);
methodVisitor.visitInsn(ICONST_0);
methodVisitor.visitVarInsn(ILOAD, 7);
methodVisitor.visitInsn(ICONST_1);
methodVisitor.visitInsn(ISUB);
methodVisitor.visitIntInsn(BIPUSH, 7);
methodVisitor.visitInsn(IAND);
methodVisitor.visitInsn(I2B);
methodVisitor.visitInsn(BASTORE);
methodVisitor.visitVarInsn(ALOAD, 0);
methodVisitor.visitFieldInsn(GETFIELD, "org/bouncycastle/crypto/modes/CCMBlockCipher", "nonce", "[B");
methodVisitor.visitInsn(ICONST_0);
methodVisitor.visitVarInsn(ALOAD, 8);
methodVisitor.visitInsn(ICONST_1);
methodVisitor.visitVarInsn(ALOAD, 0);
methodVisitor.visitFieldInsn(GETFIELD, "org/bouncycastle/crypto/modes/CCMBlockCipher", "nonce", "[B");
methodVisitor.visitInsn(ARRAYLENGTH);
methodVisitor.visitMethodInsn(INVOKESTATIC, "java/lang/System", "arraycopy", "(Ljava/lang/Object;ILjava/lang/Object;II)V", false);
methodVisitor.visitTypeInsn(NEW, "org/bouncycastle/crypto/modes/SICBlockCipher");
methodVisitor.visitInsn(DUP);
methodVisitor.visitVarInsn(ALOAD, 0);
methodVisitor.visitFieldInsn(GETFIELD, "org/bouncycastle/crypto/modes/CCMBlockCipher", "cipher", "Lorg/bouncycastle/crypto/BlockCipher;");
methodVisitor.visitMethodInsn(INVOKESPECIAL, "org/bouncycastle/crypto/modes/SICBlockCipher", "<init>", "(Lorg/bouncycastle/crypto/BlockCipher;)V", false);
methodVisitor.visitVarInsn(ASTORE, 9);
methodVisitor.visitVarInsn(ALOAD, 9);
methodVisitor.visitVarInsn(ALOAD, 0);
methodVisitor.visitFieldInsn(GETFIELD, "org/bouncycastle/crypto/modes/CCMBlockCipher", "forEncryption", "Z");
methodVisitor.visitTypeInsn(NEW, "org/bouncycastle/crypto/params/ParametersWithIV");
methodVisitor.visitInsn(DUP);
methodVisitor.visitVarInsn(ALOAD, 0);
methodVisitor.visitFieldInsn(GETFIELD, "org/bouncycastle/crypto/modes/CCMBlockCipher", "keyParam", "Lorg/bouncycastle/crypto/CipherParameters;");
methodVisitor.visitVarInsn(ALOAD, 8);
methodVisitor.visitMethodInsn(INVOKESPECIAL, "org/bouncycastle/crypto/params/ParametersWithIV", "<init>", "(Lorg/bouncycastle/crypto/CipherParameters;[B)V", false);
methodVisitor.visitMethodInsn(INVOKEINTERFACE, "org/bouncycastle/crypto/BlockCipher", "init", "(ZLorg/bouncycastle/crypto/CipherParameters;)V", true);
methodVisitor.visitVarInsn(ILOAD, 2);
methodVisitor.visitVarInsn(ISTORE, 11);
methodVisitor.visitVarInsn(ILOAD, 5);
methodVisitor.visitVarInsn(ISTORE, 12);
methodVisitor.visitVarInsn(ALOAD, 0);
methodVisitor.visitFieldInsn(GETFIELD, "org/bouncycastle/crypto/modes/CCMBlockCipher", "forEncryption", "Z");
Label label2 = new Label();
methodVisitor.visitJumpInsn(IFEQ, label2);
methodVisitor.visitVarInsn(ILOAD, 3);
methodVisitor.visitVarInsn(ALOAD, 0);
methodVisitor.visitFieldInsn(GETFIELD, "org/bouncycastle/crypto/modes/CCMBlockCipher", "macSize", "I");
methodVisitor.visitInsn(IADD);
methodVisitor.visitVarInsn(ISTORE, 10);
methodVisitor.visitVarInsn(ALOAD, 4);
methodVisitor.visitInsn(ARRAYLENGTH);
methodVisitor.visitVarInsn(ILOAD, 10);
methodVisitor.visitVarInsn(ILOAD, 5);
methodVisitor.visitInsn(IADD);
Label label3 = new Label();
methodVisitor.visitJumpInsn(IF_ICMPGE, label3);
methodVisitor.visitTypeInsn(NEW, "org/bouncycastle/crypto/OutputLengthException");
methodVisitor.visitInsn(DUP);
methodVisitor.visitLdcInsn("Output buffer too short.");
methodVisitor.visitMethodInsn(INVOKESPECIAL, "org/bouncycastle/crypto/OutputLengthException", "<init>", "(Ljava/lang/String;)V", false);
methodVisitor.visitInsn(ATHROW);
methodVisitor.visitLabel(label3);
methodVisitor.visitVarInsn(ALOAD, 0);
methodVisitor.visitVarInsn(ALOAD, 1);
methodVisitor.visitVarInsn(ILOAD, 2);
methodVisitor.visitVarInsn(ILOAD, 3);
methodVisitor.visitVarInsn(ALOAD, 0);
methodVisitor.visitFieldInsn(GETFIELD, "org/bouncycastle/crypto/modes/CCMBlockCipher", "macBlock", "[B");
methodVisitor.visitMethodInsn(INVOKESPECIAL, "org/bouncycastle/crypto/modes/CCMBlockCipher", "calculateMac", "([BII[B)I", false);
methodVisitor.visitInsn(POP);
methodVisitor.visitVarInsn(ALOAD, 0);
methodVisitor.visitFieldInsn(GETFIELD, "org/bouncycastle/crypto/modes/CCMBlockCipher", "blockSize", "I");
methodVisitor.visitIntInsn(NEWARRAY, T_BYTE);
methodVisitor.visitVarInsn(ASTORE, 13);
methodVisitor.visitVarInsn(ALOAD, 9);
methodVisitor.visitVarInsn(ALOAD, 0);
methodVisitor.visitFieldInsn(GETFIELD, "org/bouncycastle/crypto/modes/CCMBlockCipher", "macBlock", "[B");
methodVisitor.visitInsn(ICONST_0);
methodVisitor.visitVarInsn(ALOAD, 13);
methodVisitor.visitInsn(ICONST_0);
methodVisitor.visitMethodInsn(INVOKEINTERFACE, "org/bouncycastle/crypto/BlockCipher", "processBlock", "([BI[BI)I", true);
methodVisitor.visitInsn(POP);
Label label4 = new Label();
methodVisitor.visitLabel(label4);
methodVisitor.visitVarInsn(ILOAD, 11);
methodVisitor.visitVarInsn(ILOAD, 2);
methodVisitor.visitVarInsn(ILOAD, 3);
methodVisitor.visitInsn(IADD);
methodVisitor.visitVarInsn(ALOAD, 0);
methodVisitor.visitFieldInsn(GETFIELD, "org/bouncycastle/crypto/modes/CCMBlockCipher", "blockSize", "I");
methodVisitor.visitInsn(ISUB);
Label label5 = new Label();
methodVisitor.visitJumpInsn(IF_ICMPGE, label5);
methodVisitor.visitVarInsn(ALOAD, 9);
methodVisitor.visitVarInsn(ALOAD, 1);
methodVisitor.visitVarInsn(ILOAD, 11);
methodVisitor.visitVarInsn(ALOAD, 4);
methodVisitor.visitVarInsn(ILOAD, 12);
methodVisitor.visitMethodInsn(INVOKEINTERFACE, "org/bouncycastle/crypto/BlockCipher", "processBlock", "([BI[BI)I", true);
methodVisitor.visitInsn(POP);
methodVisitor.visitVarInsn(ILOAD, 12);
methodVisitor.visitVarInsn(ALOAD, 0);
methodVisitor.visitFieldInsn(GETFIELD, "org/bouncycastle/crypto/modes/CCMBlockCipher", "blockSize", "I");
methodVisitor.visitInsn(IADD);
methodVisitor.visitVarInsn(ISTORE, 12);
methodVisitor.visitVarInsn(ILOAD, 11);
methodVisitor.visitVarInsn(ALOAD, 0);
methodVisitor.visitFieldInsn(GETFIELD, "org/bouncycastle/crypto/modes/CCMBlockCipher", "blockSize", "I");
methodVisitor.visitInsn(IADD);
methodVisitor.visitVarInsn(ISTORE, 11);
methodVisitor.visitJumpInsn(GOTO, label4);
methodVisitor.visitLabel(label5);
methodVisitor.visitVarInsn(ALOAD, 0);
methodVisitor.visitFieldInsn(GETFIELD, "org/bouncycastle/crypto/modes/CCMBlockCipher", "blockSize", "I");
methodVisitor.visitIntInsn(NEWARRAY, T_BYTE);
methodVisitor.visitVarInsn(ASTORE, 14);
methodVisitor.visitVarInsn(ALOAD, 1);
methodVisitor.visitVarInsn(ILOAD, 11);
methodVisitor.visitVarInsn(ALOAD, 14);
methodVisitor.visitInsn(ICONST_0);
methodVisitor.visitVarInsn(ILOAD, 3);
methodVisitor.visitVarInsn(ILOAD, 2);
methodVisitor.visitInsn(IADD);
methodVisitor.visitVarInsn(ILOAD, 11);
methodVisitor.visitInsn(ISUB);
methodVisitor.visitMethodInsn(INVOKESTATIC, "java/lang/System", "arraycopy", "(Ljava/lang/Object;ILjava/lang/Object;II)V", false);
methodVisitor.visitVarInsn(ALOAD, 9);
methodVisitor.visitVarInsn(ALOAD, 14);
methodVisitor.visitInsn(ICONST_0);
methodVisitor.visitVarInsn(ALOAD, 14);
methodVisitor.visitInsn(ICONST_0);
methodVisitor.visitMethodInsn(INVOKEINTERFACE, "org/bouncycastle/crypto/BlockCipher", "processBlock", "([BI[BI)I", true);
methodVisitor.visitInsn(POP);
methodVisitor.visitVarInsn(ALOAD, 14);
methodVisitor.visitInsn(ICONST_0);
methodVisitor.visitVarInsn(ALOAD, 4);
methodVisitor.visitVarInsn(ILOAD, 12);
methodVisitor.visitVarInsn(ILOAD, 3);
methodVisitor.visitVarInsn(ILOAD, 2);
methodVisitor.visitInsn(IADD);
methodVisitor.visitVarInsn(ILOAD, 11);
methodVisitor.visitInsn(ISUB);
methodVisitor.visitMethodInsn(INVOKESTATIC, "java/lang/System", "arraycopy", "(Ljava/lang/Object;ILjava/lang/Object;II)V", false);
methodVisitor.visitVarInsn(ALOAD, 13);
methodVisitor.visitInsn(ICONST_0);
methodVisitor.visitVarInsn(ALOAD, 4);
methodVisitor.visitVarInsn(ILOAD, 5);
methodVisitor.visitVarInsn(ILOAD, 3);
methodVisitor.visitInsn(IADD);
methodVisitor.visitVarInsn(ALOAD, 0);
methodVisitor.visitFieldInsn(GETFIELD, "org/bouncycastle/crypto/modes/CCMBlockCipher", "macSize", "I");
methodVisitor.visitMethodInsn(INVOKESTATIC, "java/lang/System", "arraycopy", "(Ljava/lang/Object;ILjava/lang/Object;II)V", false);
Label label6 = new Label();
methodVisitor.visitJumpInsn(GOTO, label6);
methodVisitor.visitLabel(label2);
methodVisitor.visitVarInsn(ILOAD, 3);
methodVisitor.visitVarInsn(ALOAD, 0);
methodVisitor.visitFieldInsn(GETFIELD, "org/bouncycastle/crypto/modes/CCMBlockCipher", "macSize", "I");
Label label7 = new Label();
methodVisitor.visitJumpInsn(IF_ICMPGE, label7);
methodVisitor.visitTypeInsn(NEW, "org/bouncycastle/crypto/InvalidCipherTextException");
methodVisitor.visitInsn(DUP);
methodVisitor.visitLdcInsn("data too short");
methodVisitor.visitMethodInsn(INVOKESPECIAL, "org/bouncycastle/crypto/InvalidCipherTextException", "<init>", "(Ljava/lang/String;)V", false);
methodVisitor.visitInsn(ATHROW);
methodVisitor.visitLabel(label7);
methodVisitor.visitVarInsn(ILOAD, 3);
methodVisitor.visitVarInsn(ALOAD, 0);
methodVisitor.visitFieldInsn(GETFIELD, "org/bouncycastle/crypto/modes/CCMBlockCipher", "macSize", "I");
methodVisitor.visitInsn(ISUB);
methodVisitor.visitVarInsn(ISTORE, 10);
methodVisitor.visitVarInsn(ALOAD, 4);
methodVisitor.visitInsn(ARRAYLENGTH);
methodVisitor.visitVarInsn(ILOAD, 10);
methodVisitor.visitVarInsn(ILOAD, 5);
methodVisitor.visitInsn(IADD);
Label label8 = new Label();
methodVisitor.visitJumpInsn(IF_ICMPGE, label8);
methodVisitor.visitTypeInsn(NEW, "org/bouncycastle/crypto/OutputLengthException");
methodVisitor.visitInsn(DUP);
methodVisitor.visitLdcInsn("Output buffer too short.");
methodVisitor.visitMethodInsn(INVOKESPECIAL, "org/bouncycastle/crypto/OutputLengthException", "<init>", "(Ljava/lang/String;)V", false);
methodVisitor.visitInsn(ATHROW);
methodVisitor.visitLabel(label8);
methodVisitor.visitVarInsn(ALOAD, 1);
methodVisitor.visitVarInsn(ILOAD, 2);
methodVisitor.visitVarInsn(ILOAD, 10);
methodVisitor.visitInsn(IADD);
methodVisitor.visitVarInsn(ALOAD, 0);
methodVisitor.visitFieldInsn(GETFIELD, "org/bouncycastle/crypto/modes/CCMBlockCipher", "macBlock", "[B");
methodVisitor.visitInsn(ICONST_0);
methodVisitor.visitVarInsn(ALOAD, 0);
methodVisitor.visitFieldInsn(GETFIELD, "org/bouncycastle/crypto/modes/CCMBlockCipher", "macSize", "I");
methodVisitor.visitMethodInsn(INVOKESTATIC, "java/lang/System", "arraycopy", "(Ljava/lang/Object;ILjava/lang/Object;II)V", false);
methodVisitor.visitVarInsn(ALOAD, 9);
methodVisitor.visitVarInsn(ALOAD, 0);
methodVisitor.visitFieldInsn(GETFIELD, "org/bouncycastle/crypto/modes/CCMBlockCipher", "macBlock", "[B");
methodVisitor.visitInsn(ICONST_0);
methodVisitor.visitVarInsn(ALOAD, 0);
methodVisitor.visitFieldInsn(GETFIELD, "org/bouncycastle/crypto/modes/CCMBlockCipher", "macBlock", "[B");
methodVisitor.visitInsn(ICONST_0);
methodVisitor.visitMethodInsn(INVOKEINTERFACE, "org/bouncycastle/crypto/BlockCipher", "processBlock", "([BI[BI)I", true);
methodVisitor.visitInsn(POP);
methodVisitor.visitVarInsn(ALOAD, 0);
methodVisitor.visitFieldInsn(GETFIELD, "org/bouncycastle/crypto/modes/CCMBlockCipher", "macSize", "I");
methodVisitor.visitVarInsn(ISTORE, 13);
Label label9 = new Label();
methodVisitor.visitLabel(label9);
methodVisitor.visitVarInsn(ILOAD, 13);
methodVisitor.visitVarInsn(ALOAD, 0);
methodVisitor.visitFieldInsn(GETFIELD, "org/bouncycastle/crypto/modes/CCMBlockCipher", "macBlock", "[B");
methodVisitor.visitInsn(ARRAYLENGTH);
Label label10 = new Label();
methodVisitor.visitJumpInsn(IF_ICMPEQ, label10);
methodVisitor.visitVarInsn(ALOAD, 0);
methodVisitor.visitFieldInsn(GETFIELD, "org/bouncycastle/crypto/modes/CCMBlockCipher", "macBlock", "[B");
methodVisitor.visitVarInsn(ILOAD, 13);
methodVisitor.visitInsn(ICONST_0);
methodVisitor.visitInsn(BASTORE);
methodVisitor.visitIincInsn(13, 1);
methodVisitor.visitJumpInsn(GOTO, label9);
methodVisitor.visitLabel(label10);
methodVisitor.visitVarInsn(ILOAD, 11);
methodVisitor.visitVarInsn(ILOAD, 2);
methodVisitor.visitVarInsn(ILOAD, 10);
methodVisitor.visitInsn(IADD);
methodVisitor.visitVarInsn(ALOAD, 0);
methodVisitor.visitFieldInsn(GETFIELD, "org/bouncycastle/crypto/modes/CCMBlockCipher", "blockSize", "I");
methodVisitor.visitInsn(ISUB);
Label label11 = new Label();
methodVisitor.visitJumpInsn(IF_ICMPGE, label11);
methodVisitor.visitVarInsn(ALOAD, 9);
methodVisitor.visitVarInsn(ALOAD, 1);
methodVisitor.visitVarInsn(ILOAD, 11);
methodVisitor.visitVarInsn(ALOAD, 4);
methodVisitor.visitVarInsn(ILOAD, 12);
methodVisitor.visitMethodInsn(INVOKEINTERFACE, "org/bouncycastle/crypto/BlockCipher", "processBlock", "([BI[BI)I", true);
methodVisitor.visitInsn(POP);
methodVisitor.visitVarInsn(ILOAD, 12);
methodVisitor.visitVarInsn(ALOAD, 0);
methodVisitor.visitFieldInsn(GETFIELD, "org/bouncycastle/crypto/modes/CCMBlockCipher", "blockSize", "I");
methodVisitor.visitInsn(IADD);
methodVisitor.visitVarInsn(ISTORE, 12);
methodVisitor.visitVarInsn(ILOAD, 11);
methodVisitor.visitVarInsn(ALOAD, 0);
methodVisitor.visitFieldInsn(GETFIELD, "org/bouncycastle/crypto/modes/CCMBlockCipher", "blockSize", "I");
methodVisitor.visitInsn(IADD);
methodVisitor.visitVarInsn(ISTORE, 11);
methodVisitor.visitJumpInsn(GOTO, label10);
methodVisitor.visitLabel(label11);
methodVisitor.visitVarInsn(ALOAD, 0);
methodVisitor.visitFieldInsn(GETFIELD, "org/bouncycastle/crypto/modes/CCMBlockCipher", "blockSize", "I");
methodVisitor.visitIntInsn(NEWARRAY, T_BYTE);
methodVisitor.visitVarInsn(ASTORE, 13);
methodVisitor.visitVarInsn(ALOAD, 1);
methodVisitor.visitVarInsn(ILOAD, 11);
methodVisitor.visitVarInsn(ALOAD, 13);
methodVisitor.visitInsn(ICONST_0);
methodVisitor.visitVarInsn(ILOAD, 10);
methodVisitor.visitVarInsn(ILOAD, 11);
methodVisitor.visitVarInsn(ILOAD, 2);
methodVisitor.visitInsn(ISUB);
methodVisitor.visitInsn(ISUB);
methodVisitor.visitMethodInsn(INVOKESTATIC, "java/lang/System", "arraycopy", "(Ljava/lang/Object;ILjava/lang/Object;II)V", false);
methodVisitor.visitVarInsn(ALOAD, 9);
methodVisitor.visitVarInsn(ALOAD, 13);
methodVisitor.visitInsn(ICONST_0);
methodVisitor.visitVarInsn(ALOAD, 13);
methodVisitor.visitInsn(ICONST_0);
methodVisitor.visitMethodInsn(INVOKEINTERFACE, "org/bouncycastle/crypto/BlockCipher", "processBlock", "([BI[BI)I", true);
methodVisitor.visitInsn(POP);
methodVisitor.visitVarInsn(ALOAD, 13);
methodVisitor.visitInsn(ICONST_0);
methodVisitor.visitVarInsn(ALOAD, 4);
methodVisitor.visitVarInsn(ILOAD, 12);
methodVisitor.visitVarInsn(ILOAD, 10);
methodVisitor.visitVarInsn(ILOAD, 11);
methodVisitor.visitVarInsn(ILOAD, 2);
methodVisitor.visitInsn(ISUB);
methodVisitor.visitInsn(ISUB);
methodVisitor.visitMethodInsn(INVOKESTATIC, "java/lang/System", "arraycopy", "(Ljava/lang/Object;ILjava/lang/Object;II)V", false);
methodVisitor.visitVarInsn(ALOAD, 0);
methodVisitor.visitFieldInsn(GETFIELD, "org/bouncycastle/crypto/modes/CCMBlockCipher", "blockSize", "I");
methodVisitor.visitIntInsn(NEWARRAY, T_BYTE);
methodVisitor.visitVarInsn(ASTORE, 14);
methodVisitor.visitVarInsn(ALOAD, 0);
methodVisitor.visitVarInsn(ALOAD, 4);
methodVisitor.visitVarInsn(ILOAD, 5);
methodVisitor.visitVarInsn(ILOAD, 10);
methodVisitor.visitVarInsn(ALOAD, 14);
methodVisitor.visitMethodInsn(INVOKESPECIAL, "org/bouncycastle/crypto/modes/CCMBlockCipher", "calculateMac", "([BII[B)I", false);
methodVisitor.visitInsn(POP);
methodVisitor.visitVarInsn(ALOAD, 0);
methodVisitor.visitFieldInsn(GETFIELD, "org/bouncycastle/crypto/modes/CCMBlockCipher", "macBlock", "[B");
methodVisitor.visitVarInsn(ALOAD, 14);
methodVisitor.visitMethodInsn(INVOKESTATIC, "org/bouncycastle/util/Arrays", "constantTimeAreEqual", "([B[B)Z", false);
methodVisitor.visitJumpInsn(IFNE, label6);
methodVisitor.visitTypeInsn(NEW, "org/bouncycastle/crypto/InvalidCipherTextException");
methodVisitor.visitInsn(DUP);
methodVisitor.visitLdcInsn("mac check in CCM failed");
methodVisitor.visitMethodInsn(INVOKESPECIAL, "org/bouncycastle/crypto/InvalidCipherTextException", "<init>", "(Ljava/lang/String;)V", false);
methodVisitor.visitInsn(ATHROW);
methodVisitor.visitLabel(label6);
methodVisitor.visitVarInsn(ILOAD, 10);
methodVisitor.visitInsn(IRETURN);
methodVisitor.visitMaxs(7, 15);
methodVisitor.visitEnd();
}
{
methodVisitor = classWriter.visitMethod(ACC_PRIVATE, "calculateMac", "([BII[B)I", null, null);
methodVisitor.visitCode();
methodVisitor.visitTypeInsn(NEW, "org/bouncycastle/crypto/macs/CBCBlockCipherMac");
methodVisitor.visitInsn(DUP);
methodVisitor.visitVarInsn(ALOAD, 0);
methodVisitor.visitFieldInsn(GETFIELD, "org/bouncycastle/crypto/modes/CCMBlockCipher", "cipher", "Lorg/bouncycastle/crypto/BlockCipher;");
methodVisitor.visitVarInsn(ALOAD, 0);
methodVisitor.visitFieldInsn(GETFIELD, "org/bouncycastle/crypto/modes/CCMBlockCipher", "macSize", "I");
methodVisitor.visitIntInsn(BIPUSH, 8);
methodVisitor.visitInsn(IMUL);
methodVisitor.visitMethodInsn(INVOKESPECIAL, "org/bouncycastle/crypto/macs/CBCBlockCipherMac", "<init>", "(Lorg/bouncycastle/crypto/BlockCipher;I)V", false);
methodVisitor.visitVarInsn(ASTORE, 5);
methodVisitor.visitVarInsn(ALOAD, 5);
methodVisitor.visitVarInsn(ALOAD, 0);
methodVisitor.visitFieldInsn(GETFIELD, "org/bouncycastle/crypto/modes/CCMBlockCipher", "keyParam", "Lorg/bouncycastle/crypto/CipherParameters;");
methodVisitor.visitMethodInsn(INVOKEINTERFACE, "org/bouncycastle/crypto/Mac", "init", "(Lorg/bouncycastle/crypto/CipherParameters;)V", true);
methodVisitor.visitIntInsn(BIPUSH, 16);
methodVisitor.visitIntInsn(NEWARRAY, T_BYTE);
methodVisitor.visitVarInsn(ASTORE, 6);
methodVisitor.visitVarInsn(ALOAD, 0);
methodVisitor.visitMethodInsn(INVOKESPECIAL, "org/bouncycastle/crypto/modes/CCMBlockCipher", "hasAssociatedText", "()Z", false);
Label label0 = new Label();
methodVisitor.visitJumpInsn(IFEQ, label0);
methodVisitor.visitVarInsn(ALOAD, 6);
methodVisitor.visitInsn(ICONST_0);
methodVisitor.visitInsn(DUP2);
methodVisitor.visitInsn(BALOAD);
methodVisitor.visitIntInsn(BIPUSH, 64);
methodVisitor.visitInsn(IOR);
methodVisitor.visitInsn(I2B);
methodVisitor.visitInsn(BASTORE);
methodVisitor.visitLabel(label0);
methodVisitor.visitVarInsn(ALOAD, 6);
methodVisitor.visitInsn(ICONST_0);
methodVisitor.visitInsn(DUP2);
methodVisitor.visitInsn(BALOAD);
methodVisitor.visitVarInsn(ALOAD, 5);
methodVisitor.visitMethodInsn(INVOKEINTERFACE, "org/bouncycastle/crypto/Mac", "getMacSize", "()I", true);
methodVisitor.visitInsn(ICONST_2);
methodVisitor.visitInsn(ISUB);
methodVisitor.visitInsn(ICONST_2);
methodVisitor.visitInsn(IDIV);
methodVisitor.visitIntInsn(BIPUSH, 7);
methodVisitor.visitInsn(IAND);
methodVisitor.visitInsn(ICONST_3);
methodVisitor.visitInsn(ISHL);
methodVisitor.visitInsn(IOR);
methodVisitor.visitInsn(I2B);
methodVisitor.visitInsn(BASTORE);
methodVisitor.visitVarInsn(ALOAD, 6);
methodVisitor.visitInsn(ICONST_0);
methodVisitor.visitInsn(DUP2);
methodVisitor.visitInsn(BALOAD);
methodVisitor.visitIntInsn(BIPUSH, 15);
methodVisitor.visitVarInsn(ALOAD, 0);
methodVisitor.visitFieldInsn(GETFIELD, "org/bouncycastle/crypto/modes/CCMBlockCipher", "nonce", "[B");
methodVisitor.visitInsn(ARRAYLENGTH);
methodVisitor.visitInsn(ISUB);
methodVisitor.visitInsn(ICONST_1);
methodVisitor.visitInsn(ISUB);
methodVisitor.visitIntInsn(BIPUSH, 7);
methodVisitor.visitInsn(IAND);
methodVisitor.visitInsn(IOR);
methodVisitor.visitInsn(I2B);
methodVisitor.visitInsn(BASTORE);
methodVisitor.visitVarInsn(ALOAD, 0);
methodVisitor.visitFieldInsn(GETFIELD, "org/bouncycastle/crypto/modes/CCMBlockCipher", "nonce", "[B");
methodVisitor.visitInsn(ICONST_0);
methodVisitor.visitVarInsn(ALOAD, 6);
methodVisitor.visitInsn(ICONST_1);
methodVisitor.visitVarInsn(ALOAD, 0);
methodVisitor.visitFieldInsn(GETFIELD, "org/bouncycastle/crypto/modes/CCMBlockCipher", "nonce", "[B");
methodVisitor.visitInsn(ARRAYLENGTH);
methodVisitor.visitMethodInsn(INVOKESTATIC, "java/lang/System", "arraycopy", "(Ljava/lang/Object;ILjava/lang/Object;II)V", false);
methodVisitor.visitVarInsn(ILOAD, 3);
methodVisitor.visitVarInsn(ISTORE, 7);
methodVisitor.visitInsn(ICONST_1);
methodVisitor.visitVarInsn(ISTORE, 8);
Label label1 = new Label();
methodVisitor.visitLabel(label1);
methodVisitor.visitVarInsn(ILOAD, 7);
Label label2 = new Label();
methodVisitor.visitJumpInsn(IFLE, label2);
methodVisitor.visitVarInsn(ALOAD, 6);
methodVisitor.visitVarInsn(ALOAD, 6);
methodVisitor.visitInsn(ARRAYLENGTH);
methodVisitor.visitVarInsn(ILOAD, 8);
methodVisitor.visitInsn(ISUB);
methodVisitor.visitVarInsn(ILOAD, 7);
methodVisitor.visitIntInsn(SIPUSH, 255);
methodVisitor.visitInsn(IAND);
methodVisitor.visitInsn(I2B);
methodVisitor.visitInsn(BASTORE);
methodVisitor.visitVarInsn(ILOAD, 7);
methodVisitor.visitIntInsn(BIPUSH, 8);
methodVisitor.visitInsn(IUSHR);
methodVisitor.visitVarInsn(ISTORE, 7);
methodVisitor.visitIincInsn(8, 1);
methodVisitor.visitJumpInsn(GOTO, label1);
methodVisitor.visitLabel(label2);
methodVisitor.visitVarInsn(ALOAD, 5);
methodVisitor.visitVarInsn(ALOAD, 6);
methodVisitor.visitInsn(ICONST_0);
methodVisitor.visitVarInsn(ALOAD, 6);
methodVisitor.visitInsn(ARRAYLENGTH);
methodVisitor.visitMethodInsn(INVOKEINTERFACE, "org/bouncycastle/crypto/Mac", "update", "([BII)V", true);
methodVisitor.visitVarInsn(ALOAD, 0);
methodVisitor.visitMethodInsn(INVOKESPECIAL, "org/bouncycastle/crypto/modes/CCMBlockCipher", "hasAssociatedText", "()Z", false);
Label label3 = new Label();
methodVisitor.visitJumpInsn(IFEQ, label3);
methodVisitor.visitVarInsn(ALOAD, 0);
methodVisitor.visitMethodInsn(INVOKESPECIAL, "org/bouncycastle/crypto/modes/CCMBlockCipher", "getAssociatedTextLength", "()I", false);
methodVisitor.visitVarInsn(ISTORE, 10);
methodVisitor.visitVarInsn(ILOAD, 10);
methodVisitor.visitLdcInsn(new Integer(65280));
Label label4 = new Label();
methodVisitor.visitJumpInsn(IF_ICMPGE, label4);
methodVisitor.visitVarInsn(ALOAD, 5);
methodVisitor.visitVarInsn(ILOAD, 10);
methodVisitor.visitIntInsn(BIPUSH, 8);
methodVisitor.visitInsn(ISHR);
methodVisitor.visitInsn(I2B);
methodVisitor.visitMethodInsn(INVOKEINTERFACE, "org/bouncycastle/crypto/Mac", "update", "(B)V", true);
methodVisitor.visitVarInsn(ALOAD, 5);
methodVisitor.visitVarInsn(ILOAD, 10);
methodVisitor.visitInsn(I2B);
methodVisitor.visitMethodInsn(INVOKEINTERFACE, "org/bouncycastle/crypto/Mac", "update", "(B)V", true);
methodVisitor.visitInsn(ICONST_2);
methodVisitor.visitVarInsn(ISTORE, 9);
Label label5 = new Label();
methodVisitor.visitJumpInsn(GOTO, label5);
methodVisitor.visitLabel(label4);
methodVisitor.visitVarInsn(ALOAD, 5);
methodVisitor.visitInsn(ICONST_M1);
methodVisitor.visitMethodInsn(INVOKEINTERFACE, "org/bouncycastle/crypto/Mac", "update", "(B)V", true);
methodVisitor.visitVarInsn(ALOAD, 5);
methodVisitor.visitIntInsn(BIPUSH, -2);
methodVisitor.visitMethodInsn(INVOKEINTERFACE, "org/bouncycastle/crypto/Mac", "update", "(B)V", true);
methodVisitor.visitVarInsn(ALOAD, 5);
methodVisitor.visitVarInsn(ILOAD, 10);
methodVisitor.visitIntInsn(BIPUSH, 24);
methodVisitor.visitInsn(ISHR);
methodVisitor.visitInsn(I2B);
methodVisitor.visitMethodInsn(INVOKEINTERFACE, "org/bouncycastle/crypto/Mac", "update", "(B)V", true);
methodVisitor.visitVarInsn(ALOAD, 5);
methodVisitor.visitVarInsn(ILOAD, 10);
methodVisitor.visitIntInsn(BIPUSH, 16);
methodVisitor.visitInsn(ISHR);
methodVisitor.visitInsn(I2B);
methodVisitor.visitMethodInsn(INVOKEINTERFACE, "org/bouncycastle/crypto/Mac", "update", "(B)V", true);
methodVisitor.visitVarInsn(ALOAD, 5);
methodVisitor.visitVarInsn(ILOAD, 10);
methodVisitor.visitIntInsn(BIPUSH, 8);
methodVisitor.visitInsn(ISHR);
methodVisitor.visitInsn(I2B);
methodVisitor.visitMethodInsn(INVOKEINTERFACE, "org/bouncycastle/crypto/Mac", "update", "(B)V", true);
methodVisitor.visitVarInsn(ALOAD, 5);
methodVisitor.visitVarInsn(ILOAD, 10);
methodVisitor.visitInsn(I2B);
methodVisitor.visitMethodInsn(INVOKEINTERFACE, "org/bouncycastle/crypto/Mac", "update", "(B)V", true);
methodVisitor.visitIntInsn(BIPUSH, 6);
methodVisitor.visitVarInsn(ISTORE, 9);
methodVisitor.visitLabel(label5);
methodVisitor.visitVarInsn(ALOAD, 0);
methodVisitor.visitFieldInsn(GETFIELD, "org/bouncycastle/crypto/modes/CCMBlockCipher", "initialAssociatedText", "[B");
Label label6 = new Label();
methodVisitor.visitJumpInsn(IFNULL, label6);
methodVisitor.visitVarInsn(ALOAD, 5);
methodVisitor.visitVarInsn(ALOAD, 0);
methodVisitor.visitFieldInsn(GETFIELD, "org/bouncycastle/crypto/modes/CCMBlockCipher", "initialAssociatedText", "[B");
methodVisitor.visitInsn(ICONST_0);
methodVisitor.visitVarInsn(ALOAD, 0);
methodVisitor.visitFieldInsn(GETFIELD, "org/bouncycastle/crypto/modes/CCMBlockCipher", "initialAssociatedText", "[B");
methodVisitor.visitInsn(ARRAYLENGTH);
methodVisitor.visitMethodInsn(INVOKEINTERFACE, "org/bouncycastle/crypto/Mac", "update", "([BII)V", true);
methodVisitor.visitLabel(label6);
methodVisitor.visitVarInsn(ALOAD, 0);
methodVisitor.visitFieldInsn(GETFIELD, "org/bouncycastle/crypto/modes/CCMBlockCipher", "associatedText", "Lorg/bouncycastle/crypto/modes/CCMBlockCipher$ExposedByteArrayOutputStream;");
methodVisitor.visitMethodInsn(INVOKEVIRTUAL, "org/bouncycastle/crypto/modes/CCMBlockCipher$ExposedByteArrayOutputStream", "size", "()I", false);
Label label7 = new Label();
methodVisitor.visitJumpInsn(IFLE, label7);
methodVisitor.visitVarInsn(ALOAD, 5);
methodVisitor.visitVarInsn(ALOAD, 0);
methodVisitor.visitFieldInsn(GETFIELD, "org/bouncycastle/crypto/modes/CCMBlockCipher", "associatedText", "Lorg/bouncycastle/crypto/modes/CCMBlockCipher$ExposedByteArrayOutputStream;");
methodVisitor.visitMethodInsn(INVOKEVIRTUAL, "org/bouncycastle/crypto/modes/CCMBlockCipher$ExposedByteArrayOutputStream", "getBuffer", "()[B", false);
methodVisitor.visitInsn(ICONST_0);
methodVisitor.visitVarInsn(ALOAD, 0);
methodVisitor.visitFieldInsn(GETFIELD, "org/bouncycastle/crypto/modes/CCMBlockCipher", "associatedText", "Lorg/bouncycastle/crypto/modes/CCMBlockCipher$ExposedByteArrayOutputStream;");
methodVisitor.visitMethodInsn(INVOKEVIRTUAL, "org/bouncycastle/crypto/modes/CCMBlockCipher$ExposedByteArrayOutputStream", "size", "()I", false);
methodVisitor.visitMethodInsn(INVOKEINTERFACE, "org/bouncycastle/crypto/Mac", "update", "([BII)V", true);
methodVisitor.visitLabel(label7);
methodVisitor.visitVarInsn(ILOAD, 9);
methodVisitor.visitVarInsn(ILOAD, 10);
methodVisitor.visitInsn(IADD);
methodVisitor.visitIntInsn(BIPUSH, 16);
methodVisitor.visitInsn(IREM);
methodVisitor.visitVarInsn(ISTORE, 9);
methodVisitor.visitVarInsn(ILOAD, 9);
methodVisitor.visitJumpInsn(IFEQ, label3);
methodVisitor.visitVarInsn(ILOAD, 9);
methodVisitor.visitVarInsn(ISTORE, 11);
Label label8 = new Label();
methodVisitor.visitLabel(label8);
methodVisitor.visitVarInsn(ILOAD, 11);
methodVisitor.visitIntInsn(BIPUSH, 16);
methodVisitor.visitJumpInsn(IF_ICMPEQ, label3);
methodVisitor.visitVarInsn(ALOAD, 5);
methodVisitor.visitInsn(ICONST_0);
methodVisitor.visitMethodInsn(INVOKEINTERFACE, "org/bouncycastle/crypto/Mac", "update", "(B)V", true);
methodVisitor.visitIincInsn(11, 1);
methodVisitor.visitJumpInsn(GOTO, label8);
methodVisitor.visitLabel(label3);
methodVisitor.visitVarInsn(ALOAD, 5);
methodVisitor.visitVarInsn(ALOAD, 1);
methodVisitor.visitVarInsn(ILOAD, 2);
methodVisitor.visitVarInsn(ILOAD, 3);
methodVisitor.visitMethodInsn(INVOKEINTERFACE, "org/bouncycastle/crypto/Mac", "update", "([BII)V", true);
methodVisitor.visitVarInsn(ALOAD, 5);
methodVisitor.visitVarInsn(ALOAD, 4);
methodVisitor.visitInsn(ICONST_0);
methodVisitor.visitMethodInsn(INVOKEINTERFACE, "org/bouncycastle/crypto/Mac", "doFinal", "([BI)I", true);
methodVisitor.visitInsn(IRETURN);
methodVisitor.visitMaxs(5, 12);
methodVisitor.visitEnd();
}
{
methodVisitor = classWriter.visitMethod(ACC_PRIVATE, "getMacSize", "(ZI)I", null, null);
methodVisitor.visitCode();
methodVisitor.visitVarInsn(ILOAD, 1);
Label label0 = new Label();
methodVisitor.visitJumpInsn(IFEQ, label0);
methodVisitor.visitVarInsn(ILOAD, 2);
methodVisitor.visitIntInsn(BIPUSH, 32);
Label label1 = new Label();
methodVisitor.visitJumpInsn(IF_ICMPLT, label1);
methodVisitor.visitVarInsn(ILOAD, 2);
methodVisitor.visitIntInsn(SIPUSH, 128);
methodVisitor.visitJumpInsn(IF_ICMPGT, label1);
methodVisitor.visitInsn(ICONST_0);
methodVisitor.visitVarInsn(ILOAD, 2);
methodVisitor.visitIntInsn(BIPUSH, 15);
methodVisitor.visitInsn(IAND);
methodVisitor.visitJumpInsn(IF_ICMPEQ, label0);
methodVisitor.visitLabel(label1);
methodVisitor.visitTypeInsn(NEW, "java/lang/IllegalArgumentException");
methodVisitor.visitInsn(DUP);
methodVisitor.visitLdcInsn("tag length in octets must be one of {4,6,8,10,12,14,16}");
methodVisitor.visitMethodInsn(INVOKESPECIAL, "java/lang/IllegalArgumentException", "<init>", "(Ljava/lang/String;)V", false);
methodVisitor.visitInsn(ATHROW);
methodVisitor.visitLabel(label0);
methodVisitor.visitVarInsn(ILOAD, 2);
methodVisitor.visitInsn(ICONST_3);
methodVisitor.visitInsn(IUSHR);
methodVisitor.visitInsn(IRETURN);
methodVisitor.visitMaxs(3, 3);
methodVisitor.visitEnd();
}
{
methodVisitor = classWriter.visitMethod(ACC_PRIVATE, "getAssociatedTextLength", "()I", null, null);
methodVisitor.visitCode();
methodVisitor.visitVarInsn(ALOAD, 0);
methodVisitor.visitFieldInsn(GETFIELD, "org/bouncycastle/crypto/modes/CCMBlockCipher", "associatedText", "Lorg/bouncycastle/crypto/modes/CCMBlockCipher$ExposedByteArrayOutputStream;");
methodVisitor.visitMethodInsn(INVOKEVIRTUAL, "org/bouncycastle/crypto/modes/CCMBlockCipher$ExposedByteArrayOutputStream", "size", "()I", false);
methodVisitor.visitVarInsn(ALOAD, 0);
methodVisitor.visitFieldInsn(GETFIELD, "org/bouncycastle/crypto/modes/CCMBlockCipher", "initialAssociatedText", "[B");
Label label0 = new Label();
methodVisitor.visitJumpInsn(IFNONNULL, label0);
methodVisitor.visitInsn(ICONST_0);
Label label1 = new Label();
methodVisitor.visitJumpInsn(GOTO, label1);
methodVisitor.visitLabel(label0);
methodVisitor.visitVarInsn(ALOAD, 0);
methodVisitor.visitFieldInsn(GETFIELD, "org/bouncycastle/crypto/modes/CCMBlockCipher", "initialAssociatedText", "[B");
methodVisitor.visitInsn(ARRAYLENGTH);
methodVisitor.visitLabel(label1);
methodVisitor.visitInsn(IADD);
methodVisitor.visitInsn(IRETURN);
methodVisitor.visitMaxs(2, 1);
methodVisitor.visitEnd();
}
{
methodVisitor = classWriter.visitMethod(ACC_PRIVATE, "hasAssociatedText", "()Z", null, null);
methodVisitor.visitCode();
methodVisitor.visitVarInsn(ALOAD, 0);
methodVisitor.visitMethodInsn(INVOKESPECIAL, "org/bouncycastle/crypto/modes/CCMBlockCipher", "getAssociatedTextLength", "()I", false);
Label label0 = new Label();
methodVisitor.visitJumpInsn(IFLE, label0);
methodVisitor.visitInsn(ICONST_1);
Label label1 = new Label();
methodVisitor.visitJumpInsn(GOTO, label1);
methodVisitor.visitLabel(label0);
methodVisitor.visitInsn(ICONST_0);
methodVisitor.visitLabel(label1);
methodVisitor.visitInsn(IRETURN);
methodVisitor.visitMaxs(1, 1);
methodVisitor.visitEnd();
}
classWriter.visitEnd();

return classWriter.toByteArray();
}
}
