package asm.org.apache.cxf.rs.security.jose.jwe;
import org.objectweb.asm.AnnotationVisitor;
import org.objectweb.asm.Attribute;
import org.objectweb.asm.ClassReader;
import org.objectweb.asm.ClassWriter;
import org.objectweb.asm.ConstantDynamic;
import org.objectweb.asm.FieldVisitor;
import org.objectweb.asm.Handle;
import org.objectweb.asm.Label;
import org.objectweb.asm.MethodVisitor;
import org.objectweb.asm.Opcodes;
import org.objectweb.asm.RecordComponentVisitor;
import org.objectweb.asm.Type;
import org.objectweb.asm.TypePath;
public class JweOutputStreamDump implements Opcodes {

public static byte[] dump () throws Exception {

ClassWriter classWriter = new ClassWriter(0);
FieldVisitor fieldVisitor;
RecordComponentVisitor recordComponentVisitor;
MethodVisitor methodVisitor;
AnnotationVisitor annotationVisitor0;

classWriter.visit(V1_8, ACC_PUBLIC | ACC_SUPER, "org/apache/cxf/rs/security/jose/jwe/JweOutputStream", null, "java/io/FilterOutputStream", null);

classWriter.visitInnerClass("org/apache/cxf/rs/security/jose/jwe/JweException$Error", "org/apache/cxf/rs/security/jose/jwe/JweException", "Error", ACC_PUBLIC | ACC_FINAL | ACC_STATIC | ACC_ENUM);

{
fieldVisitor = classWriter.visitField(ACC_PROTECTED | ACC_FINAL | ACC_STATIC, "LOG", "Ljava/util/logging/Logger;", null, null);
fieldVisitor.visitEnd();
}
{
fieldVisitor = classWriter.visitField(ACC_PRIVATE | ACC_FINAL, "encryptingCipher", "Ljavax/crypto/Cipher;", null, null);
fieldVisitor.visitEnd();
}
{
fieldVisitor = classWriter.visitField(ACC_PRIVATE | ACC_FINAL, "blockSize", "I", null, null);
fieldVisitor.visitEnd();
}
{
fieldVisitor = classWriter.visitField(ACC_PRIVATE | ACC_FINAL, "authTagProducer", "Lorg/apache/cxf/rs/security/jose/jwe/AuthenticationTagProducer;", null, null);
fieldVisitor.visitEnd();
}
{
fieldVisitor = classWriter.visitField(ACC_PRIVATE, "lastRawDataChunk", "[B", null, null);
fieldVisitor.visitEnd();
}
{
fieldVisitor = classWriter.visitField(ACC_PRIVATE, "lastEncryptedDataChunk", "[B", null, null);
fieldVisitor.visitEnd();
}
{
fieldVisitor = classWriter.visitField(ACC_PRIVATE, "flushed", "Z", null, null);
fieldVisitor.visitEnd();
}
{
methodVisitor = classWriter.visitMethod(ACC_PUBLIC, "<init>", "(Ljava/io/OutputStream;Ljavax/crypto/Cipher;Lorg/apache/cxf/rs/security/jose/jwe/AuthenticationTagProducer;)V", null, null);
methodVisitor.visitCode();
methodVisitor.visitVarInsn(ALOAD, 0);
methodVisitor.visitVarInsn(ALOAD, 1);
methodVisitor.visitMethodInsn(INVOKESPECIAL, "java/io/FilterOutputStream", "<init>", "(Ljava/io/OutputStream;)V", false);
methodVisitor.visitVarInsn(ALOAD, 0);
methodVisitor.visitVarInsn(ALOAD, 2);
methodVisitor.visitFieldInsn(PUTFIELD, "org/apache/cxf/rs/security/jose/jwe/JweOutputStream", "encryptingCipher", "Ljavax/crypto/Cipher;");
methodVisitor.visitVarInsn(ALOAD, 0);
methodVisitor.visitVarInsn(ALOAD, 2);
methodVisitor.visitMethodInsn(INVOKEVIRTUAL, "javax/crypto/Cipher", "getBlockSize", "()I", false);
methodVisitor.visitFieldInsn(PUTFIELD, "org/apache/cxf/rs/security/jose/jwe/JweOutputStream", "blockSize", "I");
methodVisitor.visitVarInsn(ALOAD, 0);
methodVisitor.visitVarInsn(ALOAD, 3);
methodVisitor.visitFieldInsn(PUTFIELD, "org/apache/cxf/rs/security/jose/jwe/JweOutputStream", "authTagProducer", "Lorg/apache/cxf/rs/security/jose/jwe/AuthenticationTagProducer;");
methodVisitor.visitInsn(RETURN);
methodVisitor.visitMaxs(2, 4);
methodVisitor.visitEnd();
}
{
methodVisitor = classWriter.visitMethod(ACC_PUBLIC, "write", "(I)V", null, new String[] { "java/io/IOException" });
methodVisitor.visitCode();
methodVisitor.visitInsn(ICONST_4);
methodVisitor.visitMethodInsn(INVOKESTATIC, "java/nio/ByteBuffer", "allocate", "(I)Ljava/nio/ByteBuffer;", false);
methodVisitor.visitVarInsn(ILOAD, 1);
methodVisitor.visitMethodInsn(INVOKEVIRTUAL, "java/nio/ByteBuffer", "putInt", "(I)Ljava/nio/ByteBuffer;", false);
methodVisitor.visitMethodInsn(INVOKEVIRTUAL, "java/nio/ByteBuffer", "array", "()[B", false);
methodVisitor.visitVarInsn(ASTORE, 2);
methodVisitor.visitVarInsn(ALOAD, 0);
methodVisitor.visitVarInsn(ALOAD, 2);
methodVisitor.visitInsn(ICONST_0);
methodVisitor.visitVarInsn(ALOAD, 2);
methodVisitor.visitInsn(ARRAYLENGTH);
methodVisitor.visitMethodInsn(INVOKEVIRTUAL, "org/apache/cxf/rs/security/jose/jwe/JweOutputStream", "write", "([BII)V", false);
methodVisitor.visitInsn(RETURN);
methodVisitor.visitMaxs(4, 3);
methodVisitor.visitEnd();
}
{
methodVisitor = classWriter.visitMethod(ACC_PUBLIC, "write", "([BII)V", null, new String[] { "java/io/IOException" });
methodVisitor.visitCode();
methodVisitor.visitVarInsn(ALOAD, 0);
methodVisitor.visitFieldInsn(GETFIELD, "org/apache/cxf/rs/security/jose/jwe/JweOutputStream", "lastRawDataChunk", "[B");
Label label0 = new Label();
methodVisitor.visitJumpInsn(IFNULL, label0);
methodVisitor.visitVarInsn(ALOAD, 0);
methodVisitor.visitFieldInsn(GETFIELD, "org/apache/cxf/rs/security/jose/jwe/JweOutputStream", "blockSize", "I");
methodVisitor.visitVarInsn(ALOAD, 0);
methodVisitor.visitFieldInsn(GETFIELD, "org/apache/cxf/rs/security/jose/jwe/JweOutputStream", "lastRawDataChunk", "[B");
methodVisitor.visitInsn(ARRAYLENGTH);
methodVisitor.visitInsn(ISUB);
methodVisitor.visitVarInsn(ISTORE, 4);
methodVisitor.visitVarInsn(ILOAD, 4);
methodVisitor.visitVarInsn(ILOAD, 3);
Label label1 = new Label();
methodVisitor.visitJumpInsn(IF_ICMPGE, label1);
methodVisitor.visitVarInsn(ILOAD, 4);
Label label2 = new Label();
methodVisitor.visitJumpInsn(GOTO, label2);
methodVisitor.visitLabel(label1);
methodVisitor.visitFrame(Opcodes.F_APPEND,1, new Object[] {Opcodes.INTEGER}, 0, null);
methodVisitor.visitVarInsn(ILOAD, 3);
methodVisitor.visitLabel(label2);
methodVisitor.visitFrame(Opcodes.F_SAME1, 0, null, 1, new Object[] {Opcodes.INTEGER});
methodVisitor.visitVarInsn(ISTORE, 5);
methodVisitor.visitVarInsn(ALOAD, 0);
methodVisitor.visitVarInsn(ALOAD, 0);
methodVisitor.visitVarInsn(ALOAD, 0);
methodVisitor.visitFieldInsn(GETFIELD, "org/apache/cxf/rs/security/jose/jwe/JweOutputStream", "lastRawDataChunk", "[B");
methodVisitor.visitInsn(ICONST_0);
methodVisitor.visitVarInsn(ALOAD, 0);
methodVisitor.visitFieldInsn(GETFIELD, "org/apache/cxf/rs/security/jose/jwe/JweOutputStream", "lastRawDataChunk", "[B");
methodVisitor.visitInsn(ARRAYLENGTH);
methodVisitor.visitVarInsn(ALOAD, 1);
methodVisitor.visitVarInsn(ILOAD, 2);
methodVisitor.visitVarInsn(ILOAD, 5);
methodVisitor.visitMethodInsn(INVOKESPECIAL, "org/apache/cxf/rs/security/jose/jwe/JweOutputStream", "newArray", "([BII[BII)[B", false);
methodVisitor.visitFieldInsn(PUTFIELD, "org/apache/cxf/rs/security/jose/jwe/JweOutputStream", "lastRawDataChunk", "[B");
methodVisitor.visitVarInsn(ILOAD, 2);
methodVisitor.visitVarInsn(ILOAD, 5);
methodVisitor.visitInsn(IADD);
methodVisitor.visitVarInsn(ISTORE, 2);
methodVisitor.visitVarInsn(ILOAD, 3);
methodVisitor.visitVarInsn(ILOAD, 5);
methodVisitor.visitInsn(ISUB);
methodVisitor.visitVarInsn(ISTORE, 3);
methodVisitor.visitVarInsn(ALOAD, 0);
methodVisitor.visitFieldInsn(GETFIELD, "org/apache/cxf/rs/security/jose/jwe/JweOutputStream", "lastRawDataChunk", "[B");
methodVisitor.visitInsn(ARRAYLENGTH);
methodVisitor.visitVarInsn(ALOAD, 0);
methodVisitor.visitFieldInsn(GETFIELD, "org/apache/cxf/rs/security/jose/jwe/JweOutputStream", "blockSize", "I");
Label label3 = new Label();
methodVisitor.visitJumpInsn(IF_ICMPGE, label3);
methodVisitor.visitInsn(RETURN);
methodVisitor.visitLabel(label3);
methodVisitor.visitFrame(Opcodes.F_APPEND,1, new Object[] {Opcodes.INTEGER}, 0, null);
methodVisitor.visitVarInsn(ALOAD, 0);
methodVisitor.visitVarInsn(ALOAD, 0);
methodVisitor.visitFieldInsn(GETFIELD, "org/apache/cxf/rs/security/jose/jwe/JweOutputStream", "lastRawDataChunk", "[B");
methodVisitor.visitInsn(ICONST_0);
methodVisitor.visitVarInsn(ALOAD, 0);
methodVisitor.visitFieldInsn(GETFIELD, "org/apache/cxf/rs/security/jose/jwe/JweOutputStream", "lastRawDataChunk", "[B");
methodVisitor.visitInsn(ARRAYLENGTH);
methodVisitor.visitMethodInsn(INVOKESPECIAL, "org/apache/cxf/rs/security/jose/jwe/JweOutputStream", "encryptAndWrite", "([BII)V", false);
methodVisitor.visitVarInsn(ALOAD, 0);
methodVisitor.visitInsn(ACONST_NULL);
methodVisitor.visitFieldInsn(PUTFIELD, "org/apache/cxf/rs/security/jose/jwe/JweOutputStream", "lastRawDataChunk", "[B");
methodVisitor.visitLabel(label0);
methodVisitor.visitFrame(Opcodes.F_CHOP,2, null, 0, null);
methodVisitor.visitInsn(ICONST_0);
methodVisitor.visitVarInsn(ISTORE, 4);
methodVisitor.visitVarInsn(ALOAD, 0);
methodVisitor.visitFieldInsn(GETFIELD, "org/apache/cxf/rs/security/jose/jwe/JweOutputStream", "blockSize", "I");
methodVisitor.visitVarInsn(ILOAD, 3);
Label label4 = new Label();
methodVisitor.visitJumpInsn(IF_ICMPLE, label4);
methodVisitor.visitVarInsn(ALOAD, 0);
methodVisitor.visitFieldInsn(GETFIELD, "org/apache/cxf/rs/security/jose/jwe/JweOutputStream", "blockSize", "I");
Label label5 = new Label();
methodVisitor.visitJumpInsn(GOTO, label5);
methodVisitor.visitLabel(label4);
methodVisitor.visitFrame(Opcodes.F_APPEND,1, new Object[] {Opcodes.INTEGER}, 0, null);
methodVisitor.visitVarInsn(ALOAD, 0);
methodVisitor.visitFieldInsn(GETFIELD, "org/apache/cxf/rs/security/jose/jwe/JweOutputStream", "blockSize", "I");
methodVisitor.visitVarInsn(ILOAD, 3);
methodVisitor.visitVarInsn(ALOAD, 0);
methodVisitor.visitFieldInsn(GETFIELD, "org/apache/cxf/rs/security/jose/jwe/JweOutputStream", "blockSize", "I");
methodVisitor.visitInsn(IDIV);
methodVisitor.visitInsn(IMUL);
methodVisitor.visitLabel(label5);
methodVisitor.visitFrame(Opcodes.F_SAME1, 0, null, 1, new Object[] {Opcodes.INTEGER});
methodVisitor.visitVarInsn(ISTORE, 5);
Label label6 = new Label();
methodVisitor.visitLabel(label6);
methodVisitor.visitFrame(Opcodes.F_APPEND,1, new Object[] {Opcodes.INTEGER}, 0, null);
methodVisitor.visitVarInsn(ILOAD, 4);
methodVisitor.visitVarInsn(ILOAD, 5);
methodVisitor.visitInsn(IADD);
methodVisitor.visitVarInsn(ILOAD, 3);
Label label7 = new Label();
methodVisitor.visitJumpInsn(IF_ICMPGT, label7);
methodVisitor.visitVarInsn(ALOAD, 0);
methodVisitor.visitVarInsn(ALOAD, 1);
methodVisitor.visitVarInsn(ILOAD, 2);
methodVisitor.visitVarInsn(ILOAD, 5);
methodVisitor.visitMethodInsn(INVOKESPECIAL, "org/apache/cxf/rs/security/jose/jwe/JweOutputStream", "encryptAndWrite", "([BII)V", false);
methodVisitor.visitVarInsn(ILOAD, 4);
methodVisitor.visitVarInsn(ILOAD, 5);
methodVisitor.visitInsn(IADD);
methodVisitor.visitVarInsn(ISTORE, 4);
methodVisitor.visitVarInsn(ILOAD, 2);
methodVisitor.visitVarInsn(ILOAD, 5);
methodVisitor.visitInsn(IADD);
methodVisitor.visitVarInsn(ISTORE, 2);
methodVisitor.visitJumpInsn(GOTO, label6);
methodVisitor.visitLabel(label7);
methodVisitor.visitFrame(Opcodes.F_SAME, 0, null, 0, null);
methodVisitor.visitVarInsn(ILOAD, 4);
methodVisitor.visitVarInsn(ILOAD, 3);
Label label8 = new Label();
methodVisitor.visitJumpInsn(IF_ICMPGE, label8);
methodVisitor.visitVarInsn(ALOAD, 0);
methodVisitor.visitVarInsn(ALOAD, 0);
methodVisitor.visitVarInsn(ALOAD, 1);
methodVisitor.visitVarInsn(ILOAD, 2);
methodVisitor.visitVarInsn(ILOAD, 3);
methodVisitor.visitVarInsn(ILOAD, 4);
methodVisitor.visitInsn(ISUB);
methodVisitor.visitMethodInsn(INVOKESPECIAL, "org/apache/cxf/rs/security/jose/jwe/JweOutputStream", "newArray", "([BII)[B", false);
methodVisitor.visitFieldInsn(PUTFIELD, "org/apache/cxf/rs/security/jose/jwe/JweOutputStream", "lastRawDataChunk", "[B");
methodVisitor.visitLabel(label8);
methodVisitor.visitFrame(Opcodes.F_SAME, 0, null, 0, null);
methodVisitor.visitInsn(RETURN);
methodVisitor.visitMaxs(8, 6);
methodVisitor.visitEnd();
}
{
methodVisitor = classWriter.visitMethod(ACC_PRIVATE, "encryptAndWrite", "([BII)V", null, new String[] { "java/io/IOException" });
methodVisitor.visitCode();
methodVisitor.visitVarInsn(ALOAD, 0);
methodVisitor.visitFieldInsn(GETFIELD, "org/apache/cxf/rs/security/jose/jwe/JweOutputStream", "encryptingCipher", "Ljavax/crypto/Cipher;");
methodVisitor.visitVarInsn(ALOAD, 1);
methodVisitor.visitVarInsn(ILOAD, 2);
methodVisitor.visitVarInsn(ILOAD, 3);
methodVisitor.visitMethodInsn(INVOKEVIRTUAL, "javax/crypto/Cipher", "update", "([BII)[B", false);
methodVisitor.visitVarInsn(ASTORE, 4);
methodVisitor.visitVarInsn(ALOAD, 4);
Label label0 = new Label();
methodVisitor.visitJumpInsn(IFNULL, label0);
methodVisitor.visitVarInsn(ALOAD, 0);
methodVisitor.visitFieldInsn(GETFIELD, "org/apache/cxf/rs/security/jose/jwe/JweOutputStream", "authTagProducer", "Lorg/apache/cxf/rs/security/jose/jwe/AuthenticationTagProducer;");
Label label1 = new Label();
methodVisitor.visitJumpInsn(IFNULL, label1);
methodVisitor.visitVarInsn(ALOAD, 0);
methodVisitor.visitFieldInsn(GETFIELD, "org/apache/cxf/rs/security/jose/jwe/JweOutputStream", "authTagProducer", "Lorg/apache/cxf/rs/security/jose/jwe/AuthenticationTagProducer;");
methodVisitor.visitVarInsn(ALOAD, 4);
methodVisitor.visitInsn(ICONST_0);
methodVisitor.visitVarInsn(ALOAD, 4);
methodVisitor.visitInsn(ARRAYLENGTH);
methodVisitor.visitMethodInsn(INVOKEINTERFACE, "org/apache/cxf/rs/security/jose/jwe/AuthenticationTagProducer", "update", "([BII)V", true);
methodVisitor.visitLabel(label1);
methodVisitor.visitFrame(Opcodes.F_APPEND,1, new Object[] {"[B"}, 0, null);
methodVisitor.visitVarInsn(ALOAD, 0);
methodVisitor.visitVarInsn(ALOAD, 4);
methodVisitor.visitInsn(ICONST_0);
methodVisitor.visitVarInsn(ALOAD, 4);
methodVisitor.visitInsn(ARRAYLENGTH);
methodVisitor.visitInsn(ICONST_0);
methodVisitor.visitMethodInsn(INVOKESPECIAL, "org/apache/cxf/rs/security/jose/jwe/JweOutputStream", "encodeAndWrite", "([BIIZ)V", false);
methodVisitor.visitLabel(label0);
methodVisitor.visitFrame(Opcodes.F_SAME, 0, null, 0, null);
methodVisitor.visitInsn(RETURN);
methodVisitor.visitMaxs(5, 5);
methodVisitor.visitEnd();
}
{
methodVisitor = classWriter.visitMethod(ACC_PRIVATE, "encodeAndWrite", "([BIIZ)V", null, new String[] { "java/io/IOException" });
methodVisitor.visitCode();
methodVisitor.visitVarInsn(ALOAD, 0);
methodVisitor.visitFieldInsn(GETFIELD, "org/apache/cxf/rs/security/jose/jwe/JweOutputStream", "lastEncryptedDataChunk", "[B");
methodVisitor.visitVarInsn(ASTORE, 5);
methodVisitor.visitVarInsn(ILOAD, 3);
methodVisitor.visitVarInsn(ISTORE, 6);
methodVisitor.visitVarInsn(ALOAD, 5);
Label label0 = new Label();
methodVisitor.visitJumpInsn(IFNULL, label0);
methodVisitor.visitVarInsn(ALOAD, 0);
methodVisitor.visitVarInsn(ALOAD, 5);
methodVisitor.visitInsn(ICONST_0);
methodVisitor.visitVarInsn(ALOAD, 5);
methodVisitor.visitInsn(ARRAYLENGTH);
methodVisitor.visitVarInsn(ALOAD, 1);
methodVisitor.visitVarInsn(ILOAD, 2);
methodVisitor.visitVarInsn(ILOAD, 3);
methodVisitor.visitMethodInsn(INVOKESPECIAL, "org/apache/cxf/rs/security/jose/jwe/JweOutputStream", "newArray", "([BII[BII)[B", false);
methodVisitor.visitVarInsn(ASTORE, 5);
methodVisitor.visitVarInsn(ALOAD, 5);
methodVisitor.visitInsn(ARRAYLENGTH);
methodVisitor.visitVarInsn(ISTORE, 6);
methodVisitor.visitInsn(ICONST_0);
methodVisitor.visitVarInsn(ISTORE, 2);
Label label1 = new Label();
methodVisitor.visitJumpInsn(GOTO, label1);
methodVisitor.visitLabel(label0);
methodVisitor.visitFrame(Opcodes.F_APPEND,2, new Object[] {"[B", Opcodes.INTEGER}, 0, null);
methodVisitor.visitVarInsn(ALOAD, 1);
methodVisitor.visitVarInsn(ASTORE, 5);
methodVisitor.visitLabel(label1);
methodVisitor.visitFrame(Opcodes.F_SAME, 0, null, 0, null);
methodVisitor.visitVarInsn(ILOAD, 4);
Label label2 = new Label();
methodVisitor.visitJumpInsn(IFEQ, label2);
methodVisitor.visitInsn(ICONST_0);
Label label3 = new Label();
methodVisitor.visitJumpInsn(GOTO, label3);
methodVisitor.visitLabel(label2);
methodVisitor.visitFrame(Opcodes.F_SAME, 0, null, 0, null);
methodVisitor.visitVarInsn(ILOAD, 6);
methodVisitor.visitInsn(ICONST_3);
methodVisitor.visitInsn(IREM);
methodVisitor.visitLabel(label3);
methodVisitor.visitFrame(Opcodes.F_SAME1, 0, null, 1, new Object[] {Opcodes.INTEGER});
methodVisitor.visitVarInsn(ISTORE, 7);
methodVisitor.visitVarInsn(ALOAD, 5);
methodVisitor.visitVarInsn(ILOAD, 2);
methodVisitor.visitVarInsn(ILOAD, 6);
methodVisitor.visitVarInsn(ILOAD, 7);
methodVisitor.visitInsn(ISUB);
methodVisitor.visitVarInsn(ALOAD, 0);
methodVisitor.visitFieldInsn(GETFIELD, "org/apache/cxf/rs/security/jose/jwe/JweOutputStream", "out", "Ljava/io/OutputStream;");
methodVisitor.visitMethodInsn(INVOKESTATIC, "org/apache/cxf/common/util/Base64UrlUtility", "encodeAndStream", "([BIILjava/io/OutputStream;)V", false);
methodVisitor.visitVarInsn(ALOAD, 0);
methodVisitor.visitFieldInsn(GETFIELD, "org/apache/cxf/rs/security/jose/jwe/JweOutputStream", "out", "Ljava/io/OutputStream;");
methodVisitor.visitMethodInsn(INVOKEVIRTUAL, "java/io/OutputStream", "flush", "()V", false);
methodVisitor.visitVarInsn(ILOAD, 7);
Label label4 = new Label();
methodVisitor.visitJumpInsn(IFLE, label4);
methodVisitor.visitVarInsn(ALOAD, 0);
methodVisitor.visitVarInsn(ALOAD, 0);
methodVisitor.visitVarInsn(ALOAD, 5);
methodVisitor.visitVarInsn(ILOAD, 6);
methodVisitor.visitVarInsn(ILOAD, 7);
methodVisitor.visitInsn(ISUB);
methodVisitor.visitVarInsn(ILOAD, 7);
methodVisitor.visitMethodInsn(INVOKESPECIAL, "org/apache/cxf/rs/security/jose/jwe/JweOutputStream", "newArray", "([BII)[B", false);
methodVisitor.visitFieldInsn(PUTFIELD, "org/apache/cxf/rs/security/jose/jwe/JweOutputStream", "lastEncryptedDataChunk", "[B");
Label label5 = new Label();
methodVisitor.visitJumpInsn(GOTO, label5);
methodVisitor.visitLabel(label4);
methodVisitor.visitFrame(Opcodes.F_APPEND,1, new Object[] {Opcodes.INTEGER}, 0, null);
methodVisitor.visitVarInsn(ALOAD, 0);
methodVisitor.visitInsn(ACONST_NULL);
methodVisitor.visitFieldInsn(PUTFIELD, "org/apache/cxf/rs/security/jose/jwe/JweOutputStream", "lastEncryptedDataChunk", "[B");
methodVisitor.visitLabel(label5);
methodVisitor.visitFrame(Opcodes.F_SAME, 0, null, 0, null);
methodVisitor.visitInsn(RETURN);
methodVisitor.visitMaxs(7, 8);
methodVisitor.visitEnd();
}
{
methodVisitor = classWriter.visitMethod(ACC_PUBLIC, "finalFlush", "()V", null, new String[] { "java/io/IOException" });
methodVisitor.visitCode();
Label label0 = new Label();
Label label1 = new Label();
Label label2 = new Label();
methodVisitor.visitTryCatchBlock(label0, label1, label2, "java/lang/Exception");
methodVisitor.visitVarInsn(ALOAD, 0);
methodVisitor.visitFieldInsn(GETFIELD, "org/apache/cxf/rs/security/jose/jwe/JweOutputStream", "flushed", "Z");
methodVisitor.visitJumpInsn(IFEQ, label0);
methodVisitor.visitInsn(RETURN);
methodVisitor.visitLabel(label0);
methodVisitor.visitFrame(Opcodes.F_SAME, 0, null, 0, null);
methodVisitor.visitVarInsn(ALOAD, 0);
methodVisitor.visitFieldInsn(GETFIELD, "org/apache/cxf/rs/security/jose/jwe/JweOutputStream", "lastRawDataChunk", "[B");
Label label3 = new Label();
methodVisitor.visitJumpInsn(IFNONNULL, label3);
methodVisitor.visitVarInsn(ALOAD, 0);
methodVisitor.visitFieldInsn(GETFIELD, "org/apache/cxf/rs/security/jose/jwe/JweOutputStream", "encryptingCipher", "Ljavax/crypto/Cipher;");
methodVisitor.visitMethodInsn(INVOKEVIRTUAL, "javax/crypto/Cipher", "doFinal", "()[B", false);
Label label4 = new Label();
methodVisitor.visitJumpInsn(GOTO, label4);
methodVisitor.visitLabel(label3);
methodVisitor.visitFrame(Opcodes.F_SAME, 0, null, 0, null);
methodVisitor.visitVarInsn(ALOAD, 0);
methodVisitor.visitFieldInsn(GETFIELD, "org/apache/cxf/rs/security/jose/jwe/JweOutputStream", "encryptingCipher", "Ljavax/crypto/Cipher;");
methodVisitor.visitVarInsn(ALOAD, 0);
methodVisitor.visitFieldInsn(GETFIELD, "org/apache/cxf/rs/security/jose/jwe/JweOutputStream", "lastRawDataChunk", "[B");
methodVisitor.visitInsn(ICONST_0);
methodVisitor.visitVarInsn(ALOAD, 0);
methodVisitor.visitFieldInsn(GETFIELD, "org/apache/cxf/rs/security/jose/jwe/JweOutputStream", "lastRawDataChunk", "[B");
methodVisitor.visitInsn(ARRAYLENGTH);
methodVisitor.visitMethodInsn(INVOKEVIRTUAL, "javax/crypto/Cipher", "doFinal", "([BII)[B", false);
methodVisitor.visitLabel(label4);
methodVisitor.visitFrame(Opcodes.F_SAME1, 0, null, 1, new Object[] {"[B"});
methodVisitor.visitVarInsn(ASTORE, 1);
methodVisitor.visitIntInsn(SIPUSH, 128);
methodVisitor.visitVarInsn(ISTORE, 2);
methodVisitor.visitVarInsn(ALOAD, 0);
methodVisitor.visitFieldInsn(GETFIELD, "org/apache/cxf/rs/security/jose/jwe/JweOutputStream", "authTagProducer", "Lorg/apache/cxf/rs/security/jose/jwe/AuthenticationTagProducer;");
Label label5 = new Label();
methodVisitor.visitJumpInsn(IFNULL, label5);
methodVisitor.visitVarInsn(ALOAD, 0);
methodVisitor.visitFieldInsn(GETFIELD, "org/apache/cxf/rs/security/jose/jwe/JweOutputStream", "authTagProducer", "Lorg/apache/cxf/rs/security/jose/jwe/AuthenticationTagProducer;");
methodVisitor.visitVarInsn(ALOAD, 1);
methodVisitor.visitInsn(ICONST_0);
methodVisitor.visitVarInsn(ALOAD, 1);
methodVisitor.visitInsn(ARRAYLENGTH);
methodVisitor.visitMethodInsn(INVOKEINTERFACE, "org/apache/cxf/rs/security/jose/jwe/AuthenticationTagProducer", "update", "([BII)V", true);
methodVisitor.visitVarInsn(ALOAD, 0);
methodVisitor.visitVarInsn(ALOAD, 1);
methodVisitor.visitInsn(ICONST_0);
methodVisitor.visitVarInsn(ALOAD, 1);
methodVisitor.visitInsn(ARRAYLENGTH);
methodVisitor.visitInsn(ICONST_1);
methodVisitor.visitMethodInsn(INVOKESPECIAL, "org/apache/cxf/rs/security/jose/jwe/JweOutputStream", "encodeAndWrite", "([BIIZ)V", false);
Label label6 = new Label();
methodVisitor.visitJumpInsn(GOTO, label6);
methodVisitor.visitLabel(label5);
methodVisitor.visitFrame(Opcodes.F_APPEND,2, new Object[] {"[B", Opcodes.INTEGER}, 0, null);
methodVisitor.visitVarInsn(ALOAD, 0);
methodVisitor.visitVarInsn(ALOAD, 1);
methodVisitor.visitInsn(ICONST_0);
methodVisitor.visitVarInsn(ALOAD, 1);
methodVisitor.visitInsn(ARRAYLENGTH);
methodVisitor.visitIntInsn(BIPUSH, 16);
methodVisitor.visitInsn(ISUB);
methodVisitor.visitInsn(ICONST_1);
methodVisitor.visitMethodInsn(INVOKESPECIAL, "org/apache/cxf/rs/security/jose/jwe/JweOutputStream", "encodeAndWrite", "([BIIZ)V", false);
methodVisitor.visitLabel(label6);
methodVisitor.visitFrame(Opcodes.F_SAME, 0, null, 0, null);
methodVisitor.visitVarInsn(ALOAD, 0);
methodVisitor.visitFieldInsn(GETFIELD, "org/apache/cxf/rs/security/jose/jwe/JweOutputStream", "out", "Ljava/io/OutputStream;");
methodVisitor.visitInsn(ICONST_1);
methodVisitor.visitIntInsn(NEWARRAY, T_BYTE);
methodVisitor.visitInsn(DUP);
methodVisitor.visitInsn(ICONST_0);
methodVisitor.visitIntInsn(BIPUSH, 46);
methodVisitor.visitInsn(BASTORE);
methodVisitor.visitMethodInsn(INVOKEVIRTUAL, "java/io/OutputStream", "write", "([B)V", false);
methodVisitor.visitVarInsn(ALOAD, 0);
methodVisitor.visitFieldInsn(GETFIELD, "org/apache/cxf/rs/security/jose/jwe/JweOutputStream", "authTagProducer", "Lorg/apache/cxf/rs/security/jose/jwe/AuthenticationTagProducer;");
Label label7 = new Label();
methodVisitor.visitJumpInsn(IFNONNULL, label7);
methodVisitor.visitVarInsn(ALOAD, 0);
methodVisitor.visitVarInsn(ALOAD, 1);
methodVisitor.visitVarInsn(ALOAD, 1);
methodVisitor.visitInsn(ARRAYLENGTH);
methodVisitor.visitIntInsn(BIPUSH, 16);
methodVisitor.visitInsn(ISUB);
methodVisitor.visitIntInsn(BIPUSH, 16);
methodVisitor.visitInsn(ICONST_1);
methodVisitor.visitMethodInsn(INVOKESPECIAL, "org/apache/cxf/rs/security/jose/jwe/JweOutputStream", "encodeAndWrite", "([BIIZ)V", false);
methodVisitor.visitJumpInsn(GOTO, label1);
methodVisitor.visitLabel(label7);
methodVisitor.visitFrame(Opcodes.F_SAME, 0, null, 0, null);
methodVisitor.visitVarInsn(ALOAD, 0);
methodVisitor.visitFieldInsn(GETFIELD, "org/apache/cxf/rs/security/jose/jwe/JweOutputStream", "authTagProducer", "Lorg/apache/cxf/rs/security/jose/jwe/AuthenticationTagProducer;");
methodVisitor.visitMethodInsn(INVOKEINTERFACE, "org/apache/cxf/rs/security/jose/jwe/AuthenticationTagProducer", "getTag", "()[B", true);
methodVisitor.visitVarInsn(ASTORE, 3);
methodVisitor.visitVarInsn(ALOAD, 0);
methodVisitor.visitVarInsn(ALOAD, 3);
methodVisitor.visitInsn(ICONST_0);
methodVisitor.visitIntInsn(BIPUSH, 16);
methodVisitor.visitInsn(ICONST_1);
methodVisitor.visitMethodInsn(INVOKESPECIAL, "org/apache/cxf/rs/security/jose/jwe/JweOutputStream", "encodeAndWrite", "([BIIZ)V", false);
methodVisitor.visitLabel(label1);
methodVisitor.visitFrame(Opcodes.F_CHOP,2, null, 0, null);
Label label8 = new Label();
methodVisitor.visitJumpInsn(GOTO, label8);
methodVisitor.visitLabel(label2);
methodVisitor.visitFrame(Opcodes.F_SAME1, 0, null, 1, new Object[] {"java/lang/Exception"});
methodVisitor.visitVarInsn(ASTORE, 1);
methodVisitor.visitFieldInsn(GETSTATIC, "org/apache/cxf/rs/security/jose/jwe/JweOutputStream", "LOG", "Ljava/util/logging/Logger;");
methodVisitor.visitLdcInsn("Content encryption failure");
methodVisitor.visitMethodInsn(INVOKEVIRTUAL, "java/util/logging/Logger", "warning", "(Ljava/lang/String;)V", false);
methodVisitor.visitTypeInsn(NEW, "org/apache/cxf/rs/security/jose/jwe/JweException");
methodVisitor.visitInsn(DUP);
methodVisitor.visitFieldInsn(GETSTATIC, "org/apache/cxf/rs/security/jose/jwe/JweException$Error", "CONTENT_ENCRYPTION_FAILURE", "Lorg/apache/cxf/rs/security/jose/jwe/JweException$Error;");
methodVisitor.visitVarInsn(ALOAD, 1);
methodVisitor.visitMethodInsn(INVOKESPECIAL, "org/apache/cxf/rs/security/jose/jwe/JweException", "<init>", "(Lorg/apache/cxf/rs/security/jose/jwe/JweException$Error;Ljava/lang/Throwable;)V", false);
methodVisitor.visitInsn(ATHROW);
methodVisitor.visitLabel(label8);
methodVisitor.visitFrame(Opcodes.F_SAME, 0, null, 0, null);
methodVisitor.visitVarInsn(ALOAD, 0);
methodVisitor.visitInsn(ICONST_1);
methodVisitor.visitFieldInsn(PUTFIELD, "org/apache/cxf/rs/security/jose/jwe/JweOutputStream", "flushed", "Z");
methodVisitor.visitInsn(RETURN);
methodVisitor.visitMaxs(5, 4);
methodVisitor.visitEnd();
}
{
methodVisitor = classWriter.visitMethod(ACC_PRIVATE, "newArray", "([BII)[B", null, null);
methodVisitor.visitCode();
methodVisitor.visitVarInsn(ILOAD, 3);
methodVisitor.visitIntInsn(NEWARRAY, T_BYTE);
methodVisitor.visitVarInsn(ASTORE, 4);
methodVisitor.visitVarInsn(ALOAD, 1);
methodVisitor.visitVarInsn(ILOAD, 2);
methodVisitor.visitVarInsn(ALOAD, 4);
methodVisitor.visitInsn(ICONST_0);
methodVisitor.visitVarInsn(ILOAD, 3);
methodVisitor.visitMethodInsn(INVOKESTATIC, "java/lang/System", "arraycopy", "(Ljava/lang/Object;ILjava/lang/Object;II)V", false);
methodVisitor.visitVarInsn(ALOAD, 4);
methodVisitor.visitInsn(ARETURN);
methodVisitor.visitMaxs(5, 5);
methodVisitor.visitEnd();
}
{
methodVisitor = classWriter.visitMethod(ACC_PRIVATE, "newArray", "([BII[BII)[B", null, null);
methodVisitor.visitCode();
methodVisitor.visitVarInsn(ILOAD, 3);
methodVisitor.visitVarInsn(ILOAD, 6);
methodVisitor.visitInsn(IADD);
methodVisitor.visitIntInsn(NEWARRAY, T_BYTE);
methodVisitor.visitVarInsn(ASTORE, 7);
methodVisitor.visitVarInsn(ALOAD, 1);
methodVisitor.visitVarInsn(ILOAD, 2);
methodVisitor.visitVarInsn(ALOAD, 7);
methodVisitor.visitInsn(ICONST_0);
methodVisitor.visitVarInsn(ILOAD, 3);
methodVisitor.visitMethodInsn(INVOKESTATIC, "java/lang/System", "arraycopy", "(Ljava/lang/Object;ILjava/lang/Object;II)V", false);
methodVisitor.visitVarInsn(ALOAD, 4);
methodVisitor.visitVarInsn(ILOAD, 5);
methodVisitor.visitVarInsn(ALOAD, 7);
methodVisitor.visitVarInsn(ILOAD, 3);
methodVisitor.visitVarInsn(ILOAD, 6);
methodVisitor.visitMethodInsn(INVOKESTATIC, "java/lang/System", "arraycopy", "(Ljava/lang/Object;ILjava/lang/Object;II)V", false);
methodVisitor.visitVarInsn(ALOAD, 7);
methodVisitor.visitInsn(ARETURN);
methodVisitor.visitMaxs(5, 8);
methodVisitor.visitEnd();
}
{
methodVisitor = classWriter.visitMethod(ACC_STATIC, "<clinit>", "()V", null, null);
methodVisitor.visitCode();
methodVisitor.visitLdcInsn(Type.getType("Lorg/apache/cxf/rs/security/jose/jwe/JweOutputStream;"));
methodVisitor.visitMethodInsn(INVOKESTATIC, "org/apache/cxf/common/logging/LogUtils", "getL7dLogger", "(Ljava/lang/Class;)Ljava/util/logging/Logger;", false);
methodVisitor.visitFieldInsn(PUTSTATIC, "org/apache/cxf/rs/security/jose/jwe/JweOutputStream", "LOG", "Ljava/util/logging/Logger;");
methodVisitor.visitInsn(RETURN);
methodVisitor.visitMaxs(1, 0);
methodVisitor.visitEnd();
}
classWriter.visitEnd();

return classWriter.toByteArray();
}
}
