package asm.org.bouncycastle.crypto.examples;
import org.objectweb.asm.AnnotationVisitor;
import org.objectweb.asm.Attribute;
import org.objectweb.asm.ClassReader;
import org.objectweb.asm.ClassWriter;
import org.objectweb.asm.ConstantDynamic;
import org.objectweb.asm.FieldVisitor;
import org.objectweb.asm.Handle;
import org.objectweb.asm.Label;
import org.objectweb.asm.MethodVisitor;
import org.objectweb.asm.Opcodes;
import org.objectweb.asm.RecordComponentVisitor;
import org.objectweb.asm.Type;
import org.objectweb.asm.TypePath;
public class JPAKEExampleDump implements Opcodes {

public static byte[] dump () throws Exception {

ClassWriter classWriter = new ClassWriter(0);
FieldVisitor fieldVisitor;
RecordComponentVisitor recordComponentVisitor;
MethodVisitor methodVisitor;
AnnotationVisitor annotationVisitor0;

classWriter.visit(V1_5, ACC_PUBLIC | ACC_SUPER, "org/bouncycastle/crypto/examples/JPAKEExample", null, "java/lang/Object", null);

{
methodVisitor = classWriter.visitMethod(ACC_PUBLIC, "<init>", "()V", null, null);
methodVisitor.visitCode();
methodVisitor.visitVarInsn(ALOAD, 0);
methodVisitor.visitMethodInsn(INVOKESPECIAL, "java/lang/Object", "<init>", "()V", false);
methodVisitor.visitInsn(RETURN);
methodVisitor.visitMaxs(1, 1);
methodVisitor.visitEnd();
}
{
methodVisitor = classWriter.visitMethod(ACC_PUBLIC | ACC_STATIC, "main", "([Ljava/lang/String;)V", null, new String[] { "org/bouncycastle/crypto/CryptoException" });
methodVisitor.visitCode();
methodVisitor.visitFieldInsn(GETSTATIC, "org/bouncycastle/crypto/agreement/jpake/JPAKEPrimeOrderGroups", "NIST_3072", "Lorg/bouncycastle/crypto/agreement/jpake/JPAKEPrimeOrderGroup;");
methodVisitor.visitVarInsn(ASTORE, 1);
methodVisitor.visitVarInsn(ALOAD, 1);
methodVisitor.visitMethodInsn(INVOKEVIRTUAL, "org/bouncycastle/crypto/agreement/jpake/JPAKEPrimeOrderGroup", "getP", "()Ljava/math/BigInteger;", false);
methodVisitor.visitVarInsn(ASTORE, 2);
methodVisitor.visitVarInsn(ALOAD, 1);
methodVisitor.visitMethodInsn(INVOKEVIRTUAL, "org/bouncycastle/crypto/agreement/jpake/JPAKEPrimeOrderGroup", "getQ", "()Ljava/math/BigInteger;", false);
methodVisitor.visitVarInsn(ASTORE, 3);
methodVisitor.visitVarInsn(ALOAD, 1);
methodVisitor.visitMethodInsn(INVOKEVIRTUAL, "org/bouncycastle/crypto/agreement/jpake/JPAKEPrimeOrderGroup", "getG", "()Ljava/math/BigInteger;", false);
methodVisitor.visitVarInsn(ASTORE, 4);
methodVisitor.visitLdcInsn("password");
methodVisitor.visitVarInsn(ASTORE, 5);
methodVisitor.visitLdcInsn("password");
methodVisitor.visitVarInsn(ASTORE, 6);
methodVisitor.visitFieldInsn(GETSTATIC, "java/lang/System", "out", "Ljava/io/PrintStream;");
methodVisitor.visitLdcInsn("********* Initialization **********");
methodVisitor.visitMethodInsn(INVOKEVIRTUAL, "java/io/PrintStream", "println", "(Ljava/lang/String;)V", false);
methodVisitor.visitFieldInsn(GETSTATIC, "java/lang/System", "out", "Ljava/io/PrintStream;");
methodVisitor.visitLdcInsn("Public parameters for the cyclic group:");
methodVisitor.visitMethodInsn(INVOKEVIRTUAL, "java/io/PrintStream", "println", "(Ljava/lang/String;)V", false);
methodVisitor.visitFieldInsn(GETSTATIC, "java/lang/System", "out", "Ljava/io/PrintStream;");
methodVisitor.visitTypeInsn(NEW, "java/lang/StringBuilder");
methodVisitor.visitInsn(DUP);
methodVisitor.visitMethodInsn(INVOKESPECIAL, "java/lang/StringBuilder", "<init>", "()V", false);
methodVisitor.visitLdcInsn("p (");
methodVisitor.visitMethodInsn(INVOKEVIRTUAL, "java/lang/StringBuilder", "append", "(Ljava/lang/String;)Ljava/lang/StringBuilder;", false);
methodVisitor.visitVarInsn(ALOAD, 2);
methodVisitor.visitMethodInsn(INVOKEVIRTUAL, "java/math/BigInteger", "bitLength", "()I", false);
methodVisitor.visitMethodInsn(INVOKEVIRTUAL, "java/lang/StringBuilder", "append", "(I)Ljava/lang/StringBuilder;", false);
methodVisitor.visitLdcInsn(" bits): ");
methodVisitor.visitMethodInsn(INVOKEVIRTUAL, "java/lang/StringBuilder", "append", "(Ljava/lang/String;)Ljava/lang/StringBuilder;", false);
methodVisitor.visitVarInsn(ALOAD, 2);
methodVisitor.visitIntInsn(BIPUSH, 16);
methodVisitor.visitMethodInsn(INVOKEVIRTUAL, "java/math/BigInteger", "toString", "(I)Ljava/lang/String;", false);
methodVisitor.visitMethodInsn(INVOKEVIRTUAL, "java/lang/StringBuilder", "append", "(Ljava/lang/String;)Ljava/lang/StringBuilder;", false);
methodVisitor.visitMethodInsn(INVOKEVIRTUAL, "java/lang/StringBuilder", "toString", "()Ljava/lang/String;", false);
methodVisitor.visitMethodInsn(INVOKEVIRTUAL, "java/io/PrintStream", "println", "(Ljava/lang/String;)V", false);
methodVisitor.visitFieldInsn(GETSTATIC, "java/lang/System", "out", "Ljava/io/PrintStream;");
methodVisitor.visitTypeInsn(NEW, "java/lang/StringBuilder");
methodVisitor.visitInsn(DUP);
methodVisitor.visitMethodInsn(INVOKESPECIAL, "java/lang/StringBuilder", "<init>", "()V", false);
methodVisitor.visitLdcInsn("q (");
methodVisitor.visitMethodInsn(INVOKEVIRTUAL, "java/lang/StringBuilder", "append", "(Ljava/lang/String;)Ljava/lang/StringBuilder;", false);
methodVisitor.visitVarInsn(ALOAD, 3);
methodVisitor.visitMethodInsn(INVOKEVIRTUAL, "java/math/BigInteger", "bitLength", "()I", false);
methodVisitor.visitMethodInsn(INVOKEVIRTUAL, "java/lang/StringBuilder", "append", "(I)Ljava/lang/StringBuilder;", false);
methodVisitor.visitLdcInsn(" bits): ");
methodVisitor.visitMethodInsn(INVOKEVIRTUAL, "java/lang/StringBuilder", "append", "(Ljava/lang/String;)Ljava/lang/StringBuilder;", false);
methodVisitor.visitVarInsn(ALOAD, 3);
methodVisitor.visitIntInsn(BIPUSH, 16);
methodVisitor.visitMethodInsn(INVOKEVIRTUAL, "java/math/BigInteger", "toString", "(I)Ljava/lang/String;", false);
methodVisitor.visitMethodInsn(INVOKEVIRTUAL, "java/lang/StringBuilder", "append", "(Ljava/lang/String;)Ljava/lang/StringBuilder;", false);
methodVisitor.visitMethodInsn(INVOKEVIRTUAL, "java/lang/StringBuilder", "toString", "()Ljava/lang/String;", false);
methodVisitor.visitMethodInsn(INVOKEVIRTUAL, "java/io/PrintStream", "println", "(Ljava/lang/String;)V", false);
methodVisitor.visitFieldInsn(GETSTATIC, "java/lang/System", "out", "Ljava/io/PrintStream;");
methodVisitor.visitTypeInsn(NEW, "java/lang/StringBuilder");
methodVisitor.visitInsn(DUP);
methodVisitor.visitMethodInsn(INVOKESPECIAL, "java/lang/StringBuilder", "<init>", "()V", false);
methodVisitor.visitLdcInsn("g (");
methodVisitor.visitMethodInsn(INVOKEVIRTUAL, "java/lang/StringBuilder", "append", "(Ljava/lang/String;)Ljava/lang/StringBuilder;", false);
methodVisitor.visitVarInsn(ALOAD, 2);
methodVisitor.visitMethodInsn(INVOKEVIRTUAL, "java/math/BigInteger", "bitLength", "()I", false);
methodVisitor.visitMethodInsn(INVOKEVIRTUAL, "java/lang/StringBuilder", "append", "(I)Ljava/lang/StringBuilder;", false);
methodVisitor.visitLdcInsn(" bits): ");
methodVisitor.visitMethodInsn(INVOKEVIRTUAL, "java/lang/StringBuilder", "append", "(Ljava/lang/String;)Ljava/lang/StringBuilder;", false);
methodVisitor.visitVarInsn(ALOAD, 4);
methodVisitor.visitIntInsn(BIPUSH, 16);
methodVisitor.visitMethodInsn(INVOKEVIRTUAL, "java/math/BigInteger", "toString", "(I)Ljava/lang/String;", false);
methodVisitor.visitMethodInsn(INVOKEVIRTUAL, "java/lang/StringBuilder", "append", "(Ljava/lang/String;)Ljava/lang/StringBuilder;", false);
methodVisitor.visitMethodInsn(INVOKEVIRTUAL, "java/lang/StringBuilder", "toString", "()Ljava/lang/String;", false);
methodVisitor.visitMethodInsn(INVOKEVIRTUAL, "java/io/PrintStream", "println", "(Ljava/lang/String;)V", false);
methodVisitor.visitFieldInsn(GETSTATIC, "java/lang/System", "out", "Ljava/io/PrintStream;");
methodVisitor.visitTypeInsn(NEW, "java/lang/StringBuilder");
methodVisitor.visitInsn(DUP);
methodVisitor.visitMethodInsn(INVOKESPECIAL, "java/lang/StringBuilder", "<init>", "()V", false);
methodVisitor.visitLdcInsn("p mod q = ");
methodVisitor.visitMethodInsn(INVOKEVIRTUAL, "java/lang/StringBuilder", "append", "(Ljava/lang/String;)Ljava/lang/StringBuilder;", false);
methodVisitor.visitVarInsn(ALOAD, 2);
methodVisitor.visitVarInsn(ALOAD, 3);
methodVisitor.visitMethodInsn(INVOKEVIRTUAL, "java/math/BigInteger", "mod", "(Ljava/math/BigInteger;)Ljava/math/BigInteger;", false);
methodVisitor.visitIntInsn(BIPUSH, 16);
methodVisitor.visitMethodInsn(INVOKEVIRTUAL, "java/math/BigInteger", "toString", "(I)Ljava/lang/String;", false);
methodVisitor.visitMethodInsn(INVOKEVIRTUAL, "java/lang/StringBuilder", "append", "(Ljava/lang/String;)Ljava/lang/StringBuilder;", false);
methodVisitor.visitMethodInsn(INVOKEVIRTUAL, "java/lang/StringBuilder", "toString", "()Ljava/lang/String;", false);
methodVisitor.visitMethodInsn(INVOKEVIRTUAL, "java/io/PrintStream", "println", "(Ljava/lang/String;)V", false);
methodVisitor.visitFieldInsn(GETSTATIC, "java/lang/System", "out", "Ljava/io/PrintStream;");
methodVisitor.visitTypeInsn(NEW, "java/lang/StringBuilder");
methodVisitor.visitInsn(DUP);
methodVisitor.visitMethodInsn(INVOKESPECIAL, "java/lang/StringBuilder", "<init>", "()V", false);
methodVisitor.visitLdcInsn("g^{q} mod p = ");
methodVisitor.visitMethodInsn(INVOKEVIRTUAL, "java/lang/StringBuilder", "append", "(Ljava/lang/String;)Ljava/lang/StringBuilder;", false);
methodVisitor.visitVarInsn(ALOAD, 4);
methodVisitor.visitVarInsn(ALOAD, 3);
methodVisitor.visitVarInsn(ALOAD, 2);
methodVisitor.visitMethodInsn(INVOKEVIRTUAL, "java/math/BigInteger", "modPow", "(Ljava/math/BigInteger;Ljava/math/BigInteger;)Ljava/math/BigInteger;", false);
methodVisitor.visitIntInsn(BIPUSH, 16);
methodVisitor.visitMethodInsn(INVOKEVIRTUAL, "java/math/BigInteger", "toString", "(I)Ljava/lang/String;", false);
methodVisitor.visitMethodInsn(INVOKEVIRTUAL, "java/lang/StringBuilder", "append", "(Ljava/lang/String;)Ljava/lang/StringBuilder;", false);
methodVisitor.visitMethodInsn(INVOKEVIRTUAL, "java/lang/StringBuilder", "toString", "()Ljava/lang/String;", false);
methodVisitor.visitMethodInsn(INVOKEVIRTUAL, "java/io/PrintStream", "println", "(Ljava/lang/String;)V", false);
methodVisitor.visitFieldInsn(GETSTATIC, "java/lang/System", "out", "Ljava/io/PrintStream;");
methodVisitor.visitLdcInsn("");
methodVisitor.visitMethodInsn(INVOKEVIRTUAL, "java/io/PrintStream", "println", "(Ljava/lang/String;)V", false);
methodVisitor.visitFieldInsn(GETSTATIC, "java/lang/System", "out", "Ljava/io/PrintStream;");
methodVisitor.visitTypeInsn(NEW, "java/lang/StringBuilder");
methodVisitor.visitInsn(DUP);
methodVisitor.visitMethodInsn(INVOKESPECIAL, "java/lang/StringBuilder", "<init>", "()V", false);
methodVisitor.visitLdcInsn("(Secret passwords used by Alice and Bob: \"");
methodVisitor.visitMethodInsn(INVOKEVIRTUAL, "java/lang/StringBuilder", "append", "(Ljava/lang/String;)Ljava/lang/StringBuilder;", false);
methodVisitor.visitVarInsn(ALOAD, 5);
methodVisitor.visitMethodInsn(INVOKEVIRTUAL, "java/lang/StringBuilder", "append", "(Ljava/lang/String;)Ljava/lang/StringBuilder;", false);
methodVisitor.visitLdcInsn("\" and \"");
methodVisitor.visitMethodInsn(INVOKEVIRTUAL, "java/lang/StringBuilder", "append", "(Ljava/lang/String;)Ljava/lang/StringBuilder;", false);
methodVisitor.visitVarInsn(ALOAD, 6);
methodVisitor.visitMethodInsn(INVOKEVIRTUAL, "java/lang/StringBuilder", "append", "(Ljava/lang/String;)Ljava/lang/StringBuilder;", false);
methodVisitor.visitLdcInsn("\")\n");
methodVisitor.visitMethodInsn(INVOKEVIRTUAL, "java/lang/StringBuilder", "append", "(Ljava/lang/String;)Ljava/lang/StringBuilder;", false);
methodVisitor.visitMethodInsn(INVOKEVIRTUAL, "java/lang/StringBuilder", "toString", "()Ljava/lang/String;", false);
methodVisitor.visitMethodInsn(INVOKEVIRTUAL, "java/io/PrintStream", "println", "(Ljava/lang/String;)V", false);
methodVisitor.visitTypeInsn(NEW, "org/bouncycastle/crypto/digests/SHA256Digest");
methodVisitor.visitInsn(DUP);
methodVisitor.visitMethodInsn(INVOKESPECIAL, "org/bouncycastle/crypto/digests/SHA256Digest", "<init>", "()V", false);
methodVisitor.visitVarInsn(ASTORE, 7);
methodVisitor.visitTypeInsn(NEW, "java/security/SecureRandom");
methodVisitor.visitInsn(DUP);
methodVisitor.visitMethodInsn(INVOKESPECIAL, "java/security/SecureRandom", "<init>", "()V", false);
methodVisitor.visitVarInsn(ASTORE, 8);
methodVisitor.visitTypeInsn(NEW, "org/bouncycastle/crypto/agreement/jpake/JPAKEParticipant");
methodVisitor.visitInsn(DUP);
methodVisitor.visitLdcInsn("alice");
methodVisitor.visitVarInsn(ALOAD, 5);
methodVisitor.visitMethodInsn(INVOKEVIRTUAL, "java/lang/String", "toCharArray", "()[C", false);
methodVisitor.visitVarInsn(ALOAD, 1);
methodVisitor.visitVarInsn(ALOAD, 7);
methodVisitor.visitVarInsn(ALOAD, 8);
methodVisitor.visitMethodInsn(INVOKESPECIAL, "org/bouncycastle/crypto/agreement/jpake/JPAKEParticipant", "<init>", "(Ljava/lang/String;[CLorg/bouncycastle/crypto/agreement/jpake/JPAKEPrimeOrderGroup;Lorg/bouncycastle/crypto/Digest;Ljava/security/SecureRandom;)V", false);
methodVisitor.visitVarInsn(ASTORE, 9);
methodVisitor.visitTypeInsn(NEW, "org/bouncycastle/crypto/agreement/jpake/JPAKEParticipant");
methodVisitor.visitInsn(DUP);
methodVisitor.visitLdcInsn("bob");
methodVisitor.visitVarInsn(ALOAD, 6);
methodVisitor.visitMethodInsn(INVOKEVIRTUAL, "java/lang/String", "toCharArray", "()[C", false);
methodVisitor.visitVarInsn(ALOAD, 1);
methodVisitor.visitVarInsn(ALOAD, 7);
methodVisitor.visitVarInsn(ALOAD, 8);
methodVisitor.visitMethodInsn(INVOKESPECIAL, "org/bouncycastle/crypto/agreement/jpake/JPAKEParticipant", "<init>", "(Ljava/lang/String;[CLorg/bouncycastle/crypto/agreement/jpake/JPAKEPrimeOrderGroup;Lorg/bouncycastle/crypto/Digest;Ljava/security/SecureRandom;)V", false);
methodVisitor.visitVarInsn(ASTORE, 10);
methodVisitor.visitVarInsn(ALOAD, 9);
methodVisitor.visitMethodInsn(INVOKEVIRTUAL, "org/bouncycastle/crypto/agreement/jpake/JPAKEParticipant", "createRound1PayloadToSend", "()Lorg/bouncycastle/crypto/agreement/jpake/JPAKERound1Payload;", false);
methodVisitor.visitVarInsn(ASTORE, 11);
methodVisitor.visitVarInsn(ALOAD, 10);
methodVisitor.visitMethodInsn(INVOKEVIRTUAL, "org/bouncycastle/crypto/agreement/jpake/JPAKEParticipant", "createRound1PayloadToSend", "()Lorg/bouncycastle/crypto/agreement/jpake/JPAKERound1Payload;", false);
methodVisitor.visitVarInsn(ASTORE, 12);
methodVisitor.visitFieldInsn(GETSTATIC, "java/lang/System", "out", "Ljava/io/PrintStream;");
methodVisitor.visitLdcInsn("************ Round 1 **************");
methodVisitor.visitMethodInsn(INVOKEVIRTUAL, "java/io/PrintStream", "println", "(Ljava/lang/String;)V", false);
methodVisitor.visitFieldInsn(GETSTATIC, "java/lang/System", "out", "Ljava/io/PrintStream;");
methodVisitor.visitLdcInsn("Alice sends to Bob: ");
methodVisitor.visitMethodInsn(INVOKEVIRTUAL, "java/io/PrintStream", "println", "(Ljava/lang/String;)V", false);
methodVisitor.visitFieldInsn(GETSTATIC, "java/lang/System", "out", "Ljava/io/PrintStream;");
methodVisitor.visitTypeInsn(NEW, "java/lang/StringBuilder");
methodVisitor.visitInsn(DUP);
methodVisitor.visitMethodInsn(INVOKESPECIAL, "java/lang/StringBuilder", "<init>", "()V", false);
methodVisitor.visitLdcInsn("g^{x1}=");
methodVisitor.visitMethodInsn(INVOKEVIRTUAL, "java/lang/StringBuilder", "append", "(Ljava/lang/String;)Ljava/lang/StringBuilder;", false);
methodVisitor.visitVarInsn(ALOAD, 11);
methodVisitor.visitMethodInsn(INVOKEVIRTUAL, "org/bouncycastle/crypto/agreement/jpake/JPAKERound1Payload", "getGx1", "()Ljava/math/BigInteger;", false);
methodVisitor.visitIntInsn(BIPUSH, 16);
methodVisitor.visitMethodInsn(INVOKEVIRTUAL, "java/math/BigInteger", "toString", "(I)Ljava/lang/String;", false);
methodVisitor.visitMethodInsn(INVOKEVIRTUAL, "java/lang/StringBuilder", "append", "(Ljava/lang/String;)Ljava/lang/StringBuilder;", false);
methodVisitor.visitMethodInsn(INVOKEVIRTUAL, "java/lang/StringBuilder", "toString", "()Ljava/lang/String;", false);
methodVisitor.visitMethodInsn(INVOKEVIRTUAL, "java/io/PrintStream", "println", "(Ljava/lang/String;)V", false);
methodVisitor.visitFieldInsn(GETSTATIC, "java/lang/System", "out", "Ljava/io/PrintStream;");
methodVisitor.visitTypeInsn(NEW, "java/lang/StringBuilder");
methodVisitor.visitInsn(DUP);
methodVisitor.visitMethodInsn(INVOKESPECIAL, "java/lang/StringBuilder", "<init>", "()V", false);
methodVisitor.visitLdcInsn("g^{x2}=");
methodVisitor.visitMethodInsn(INVOKEVIRTUAL, "java/lang/StringBuilder", "append", "(Ljava/lang/String;)Ljava/lang/StringBuilder;", false);
methodVisitor.visitVarInsn(ALOAD, 11);
methodVisitor.visitMethodInsn(INVOKEVIRTUAL, "org/bouncycastle/crypto/agreement/jpake/JPAKERound1Payload", "getGx2", "()Ljava/math/BigInteger;", false);
methodVisitor.visitIntInsn(BIPUSH, 16);
methodVisitor.visitMethodInsn(INVOKEVIRTUAL, "java/math/BigInteger", "toString", "(I)Ljava/lang/String;", false);
methodVisitor.visitMethodInsn(INVOKEVIRTUAL, "java/lang/StringBuilder", "append", "(Ljava/lang/String;)Ljava/lang/StringBuilder;", false);
methodVisitor.visitMethodInsn(INVOKEVIRTUAL, "java/lang/StringBuilder", "toString", "()Ljava/lang/String;", false);
methodVisitor.visitMethodInsn(INVOKEVIRTUAL, "java/io/PrintStream", "println", "(Ljava/lang/String;)V", false);
methodVisitor.visitFieldInsn(GETSTATIC, "java/lang/System", "out", "Ljava/io/PrintStream;");
methodVisitor.visitTypeInsn(NEW, "java/lang/StringBuilder");
methodVisitor.visitInsn(DUP);
methodVisitor.visitMethodInsn(INVOKESPECIAL, "java/lang/StringBuilder", "<init>", "()V", false);
methodVisitor.visitLdcInsn("KP{x1}={");
methodVisitor.visitMethodInsn(INVOKEVIRTUAL, "java/lang/StringBuilder", "append", "(Ljava/lang/String;)Ljava/lang/StringBuilder;", false);
methodVisitor.visitVarInsn(ALOAD, 11);
methodVisitor.visitMethodInsn(INVOKEVIRTUAL, "org/bouncycastle/crypto/agreement/jpake/JPAKERound1Payload", "getKnowledgeProofForX1", "()[Ljava/math/BigInteger;", false);
methodVisitor.visitInsn(ICONST_0);
methodVisitor.visitInsn(AALOAD);
methodVisitor.visitIntInsn(BIPUSH, 16);
methodVisitor.visitMethodInsn(INVOKEVIRTUAL, "java/math/BigInteger", "toString", "(I)Ljava/lang/String;", false);
methodVisitor.visitMethodInsn(INVOKEVIRTUAL, "java/lang/StringBuilder", "append", "(Ljava/lang/String;)Ljava/lang/StringBuilder;", false);
methodVisitor.visitLdcInsn("};{");
methodVisitor.visitMethodInsn(INVOKEVIRTUAL, "java/lang/StringBuilder", "append", "(Ljava/lang/String;)Ljava/lang/StringBuilder;", false);
methodVisitor.visitVarInsn(ALOAD, 11);
methodVisitor.visitMethodInsn(INVOKEVIRTUAL, "org/bouncycastle/crypto/agreement/jpake/JPAKERound1Payload", "getKnowledgeProofForX1", "()[Ljava/math/BigInteger;", false);
methodVisitor.visitInsn(ICONST_1);
methodVisitor.visitInsn(AALOAD);
methodVisitor.visitIntInsn(BIPUSH, 16);
methodVisitor.visitMethodInsn(INVOKEVIRTUAL, "java/math/BigInteger", "toString", "(I)Ljava/lang/String;", false);
methodVisitor.visitMethodInsn(INVOKEVIRTUAL, "java/lang/StringBuilder", "append", "(Ljava/lang/String;)Ljava/lang/StringBuilder;", false);
methodVisitor.visitLdcInsn("}");
methodVisitor.visitMethodInsn(INVOKEVIRTUAL, "java/lang/StringBuilder", "append", "(Ljava/lang/String;)Ljava/lang/StringBuilder;", false);
methodVisitor.visitMethodInsn(INVOKEVIRTUAL, "java/lang/StringBuilder", "toString", "()Ljava/lang/String;", false);
methodVisitor.visitMethodInsn(INVOKEVIRTUAL, "java/io/PrintStream", "println", "(Ljava/lang/String;)V", false);
methodVisitor.visitFieldInsn(GETSTATIC, "java/lang/System", "out", "Ljava/io/PrintStream;");
methodVisitor.visitTypeInsn(NEW, "java/lang/StringBuilder");
methodVisitor.visitInsn(DUP);
methodVisitor.visitMethodInsn(INVOKESPECIAL, "java/lang/StringBuilder", "<init>", "()V", false);
methodVisitor.visitLdcInsn("KP{x2}={");
methodVisitor.visitMethodInsn(INVOKEVIRTUAL, "java/lang/StringBuilder", "append", "(Ljava/lang/String;)Ljava/lang/StringBuilder;", false);
methodVisitor.visitVarInsn(ALOAD, 11);
methodVisitor.visitMethodInsn(INVOKEVIRTUAL, "org/bouncycastle/crypto/agreement/jpake/JPAKERound1Payload", "getKnowledgeProofForX2", "()[Ljava/math/BigInteger;", false);
methodVisitor.visitInsn(ICONST_0);
methodVisitor.visitInsn(AALOAD);
methodVisitor.visitIntInsn(BIPUSH, 16);
methodVisitor.visitMethodInsn(INVOKEVIRTUAL, "java/math/BigInteger", "toString", "(I)Ljava/lang/String;", false);
methodVisitor.visitMethodInsn(INVOKEVIRTUAL, "java/lang/StringBuilder", "append", "(Ljava/lang/String;)Ljava/lang/StringBuilder;", false);
methodVisitor.visitLdcInsn("};{");
methodVisitor.visitMethodInsn(INVOKEVIRTUAL, "java/lang/StringBuilder", "append", "(Ljava/lang/String;)Ljava/lang/StringBuilder;", false);
methodVisitor.visitVarInsn(ALOAD, 11);
methodVisitor.visitMethodInsn(INVOKEVIRTUAL, "org/bouncycastle/crypto/agreement/jpake/JPAKERound1Payload", "getKnowledgeProofForX2", "()[Ljava/math/BigInteger;", false);
methodVisitor.visitInsn(ICONST_1);
methodVisitor.visitInsn(AALOAD);
methodVisitor.visitIntInsn(BIPUSH, 16);
methodVisitor.visitMethodInsn(INVOKEVIRTUAL, "java/math/BigInteger", "toString", "(I)Ljava/lang/String;", false);
methodVisitor.visitMethodInsn(INVOKEVIRTUAL, "java/lang/StringBuilder", "append", "(Ljava/lang/String;)Ljava/lang/StringBuilder;", false);
methodVisitor.visitLdcInsn("}");
methodVisitor.visitMethodInsn(INVOKEVIRTUAL, "java/lang/StringBuilder", "append", "(Ljava/lang/String;)Ljava/lang/StringBuilder;", false);
methodVisitor.visitMethodInsn(INVOKEVIRTUAL, "java/lang/StringBuilder", "toString", "()Ljava/lang/String;", false);
methodVisitor.visitMethodInsn(INVOKEVIRTUAL, "java/io/PrintStream", "println", "(Ljava/lang/String;)V", false);
methodVisitor.visitFieldInsn(GETSTATIC, "java/lang/System", "out", "Ljava/io/PrintStream;");
methodVisitor.visitLdcInsn("");
methodVisitor.visitMethodInsn(INVOKEVIRTUAL, "java/io/PrintStream", "println", "(Ljava/lang/String;)V", false);
methodVisitor.visitFieldInsn(GETSTATIC, "java/lang/System", "out", "Ljava/io/PrintStream;");
methodVisitor.visitLdcInsn("Bob sends to Alice: ");
methodVisitor.visitMethodInsn(INVOKEVIRTUAL, "java/io/PrintStream", "println", "(Ljava/lang/String;)V", false);
methodVisitor.visitFieldInsn(GETSTATIC, "java/lang/System", "out", "Ljava/io/PrintStream;");
methodVisitor.visitTypeInsn(NEW, "java/lang/StringBuilder");
methodVisitor.visitInsn(DUP);
methodVisitor.visitMethodInsn(INVOKESPECIAL, "java/lang/StringBuilder", "<init>", "()V", false);
methodVisitor.visitLdcInsn("g^{x3}=");
methodVisitor.visitMethodInsn(INVOKEVIRTUAL, "java/lang/StringBuilder", "append", "(Ljava/lang/String;)Ljava/lang/StringBuilder;", false);
methodVisitor.visitVarInsn(ALOAD, 12);
methodVisitor.visitMethodInsn(INVOKEVIRTUAL, "org/bouncycastle/crypto/agreement/jpake/JPAKERound1Payload", "getGx1", "()Ljava/math/BigInteger;", false);
methodVisitor.visitIntInsn(BIPUSH, 16);
methodVisitor.visitMethodInsn(INVOKEVIRTUAL, "java/math/BigInteger", "toString", "(I)Ljava/lang/String;", false);
methodVisitor.visitMethodInsn(INVOKEVIRTUAL, "java/lang/StringBuilder", "append", "(Ljava/lang/String;)Ljava/lang/StringBuilder;", false);
methodVisitor.visitMethodInsn(INVOKEVIRTUAL, "java/lang/StringBuilder", "toString", "()Ljava/lang/String;", false);
methodVisitor.visitMethodInsn(INVOKEVIRTUAL, "java/io/PrintStream", "println", "(Ljava/lang/String;)V", false);
methodVisitor.visitFieldInsn(GETSTATIC, "java/lang/System", "out", "Ljava/io/PrintStream;");
methodVisitor.visitTypeInsn(NEW, "java/lang/StringBuilder");
methodVisitor.visitInsn(DUP);
methodVisitor.visitMethodInsn(INVOKESPECIAL, "java/lang/StringBuilder", "<init>", "()V", false);
methodVisitor.visitLdcInsn("g^{x4}=");
methodVisitor.visitMethodInsn(INVOKEVIRTUAL, "java/lang/StringBuilder", "append", "(Ljava/lang/String;)Ljava/lang/StringBuilder;", false);
methodVisitor.visitVarInsn(ALOAD, 12);
methodVisitor.visitMethodInsn(INVOKEVIRTUAL, "org/bouncycastle/crypto/agreement/jpake/JPAKERound1Payload", "getGx2", "()Ljava/math/BigInteger;", false);
methodVisitor.visitIntInsn(BIPUSH, 16);
methodVisitor.visitMethodInsn(INVOKEVIRTUAL, "java/math/BigInteger", "toString", "(I)Ljava/lang/String;", false);
methodVisitor.visitMethodInsn(INVOKEVIRTUAL, "java/lang/StringBuilder", "append", "(Ljava/lang/String;)Ljava/lang/StringBuilder;", false);
methodVisitor.visitMethodInsn(INVOKEVIRTUAL, "java/lang/StringBuilder", "toString", "()Ljava/lang/String;", false);
methodVisitor.visitMethodInsn(INVOKEVIRTUAL, "java/io/PrintStream", "println", "(Ljava/lang/String;)V", false);
methodVisitor.visitFieldInsn(GETSTATIC, "java/lang/System", "out", "Ljava/io/PrintStream;");
methodVisitor.visitTypeInsn(NEW, "java/lang/StringBuilder");
methodVisitor.visitInsn(DUP);
methodVisitor.visitMethodInsn(INVOKESPECIAL, "java/lang/StringBuilder", "<init>", "()V", false);
methodVisitor.visitLdcInsn("KP{x3}={");
methodVisitor.visitMethodInsn(INVOKEVIRTUAL, "java/lang/StringBuilder", "append", "(Ljava/lang/String;)Ljava/lang/StringBuilder;", false);
methodVisitor.visitVarInsn(ALOAD, 12);
methodVisitor.visitMethodInsn(INVOKEVIRTUAL, "org/bouncycastle/crypto/agreement/jpake/JPAKERound1Payload", "getKnowledgeProofForX1", "()[Ljava/math/BigInteger;", false);
methodVisitor.visitInsn(ICONST_0);
methodVisitor.visitInsn(AALOAD);
methodVisitor.visitIntInsn(BIPUSH, 16);
methodVisitor.visitMethodInsn(INVOKEVIRTUAL, "java/math/BigInteger", "toString", "(I)Ljava/lang/String;", false);
methodVisitor.visitMethodInsn(INVOKEVIRTUAL, "java/lang/StringBuilder", "append", "(Ljava/lang/String;)Ljava/lang/StringBuilder;", false);
methodVisitor.visitLdcInsn("};{");
methodVisitor.visitMethodInsn(INVOKEVIRTUAL, "java/lang/StringBuilder", "append", "(Ljava/lang/String;)Ljava/lang/StringBuilder;", false);
methodVisitor.visitVarInsn(ALOAD, 12);
methodVisitor.visitMethodInsn(INVOKEVIRTUAL, "org/bouncycastle/crypto/agreement/jpake/JPAKERound1Payload", "getKnowledgeProofForX1", "()[Ljava/math/BigInteger;", false);
methodVisitor.visitInsn(ICONST_1);
methodVisitor.visitInsn(AALOAD);
methodVisitor.visitIntInsn(BIPUSH, 16);
methodVisitor.visitMethodInsn(INVOKEVIRTUAL, "java/math/BigInteger", "toString", "(I)Ljava/lang/String;", false);
methodVisitor.visitMethodInsn(INVOKEVIRTUAL, "java/lang/StringBuilder", "append", "(Ljava/lang/String;)Ljava/lang/StringBuilder;", false);
methodVisitor.visitLdcInsn("}");
methodVisitor.visitMethodInsn(INVOKEVIRTUAL, "java/lang/StringBuilder", "append", "(Ljava/lang/String;)Ljava/lang/StringBuilder;", false);
methodVisitor.visitMethodInsn(INVOKEVIRTUAL, "java/lang/StringBuilder", "toString", "()Ljava/lang/String;", false);
methodVisitor.visitMethodInsn(INVOKEVIRTUAL, "java/io/PrintStream", "println", "(Ljava/lang/String;)V", false);
methodVisitor.visitFieldInsn(GETSTATIC, "java/lang/System", "out", "Ljava/io/PrintStream;");
methodVisitor.visitTypeInsn(NEW, "java/lang/StringBuilder");
methodVisitor.visitInsn(DUP);
methodVisitor.visitMethodInsn(INVOKESPECIAL, "java/lang/StringBuilder", "<init>", "()V", false);
methodVisitor.visitLdcInsn("KP{x4}={");
methodVisitor.visitMethodInsn(INVOKEVIRTUAL, "java/lang/StringBuilder", "append", "(Ljava/lang/String;)Ljava/lang/StringBuilder;", false);
methodVisitor.visitVarInsn(ALOAD, 12);
methodVisitor.visitMethodInsn(INVOKEVIRTUAL, "org/bouncycastle/crypto/agreement/jpake/JPAKERound1Payload", "getKnowledgeProofForX2", "()[Ljava/math/BigInteger;", false);
methodVisitor.visitInsn(ICONST_0);
methodVisitor.visitInsn(AALOAD);
methodVisitor.visitIntInsn(BIPUSH, 16);
methodVisitor.visitMethodInsn(INVOKEVIRTUAL, "java/math/BigInteger", "toString", "(I)Ljava/lang/String;", false);
methodVisitor.visitMethodInsn(INVOKEVIRTUAL, "java/lang/StringBuilder", "append", "(Ljava/lang/String;)Ljava/lang/StringBuilder;", false);
methodVisitor.visitLdcInsn("};{");
methodVisitor.visitMethodInsn(INVOKEVIRTUAL, "java/lang/StringBuilder", "append", "(Ljava/lang/String;)Ljava/lang/StringBuilder;", false);
methodVisitor.visitVarInsn(ALOAD, 12);
methodVisitor.visitMethodInsn(INVOKEVIRTUAL, "org/bouncycastle/crypto/agreement/jpake/JPAKERound1Payload", "getKnowledgeProofForX2", "()[Ljava/math/BigInteger;", false);
methodVisitor.visitInsn(ICONST_1);
methodVisitor.visitInsn(AALOAD);
methodVisitor.visitIntInsn(BIPUSH, 16);
methodVisitor.visitMethodInsn(INVOKEVIRTUAL, "java/math/BigInteger", "toString", "(I)Ljava/lang/String;", false);
methodVisitor.visitMethodInsn(INVOKEVIRTUAL, "java/lang/StringBuilder", "append", "(Ljava/lang/String;)Ljava/lang/StringBuilder;", false);
methodVisitor.visitLdcInsn("}");
methodVisitor.visitMethodInsn(INVOKEVIRTUAL, "java/lang/StringBuilder", "append", "(Ljava/lang/String;)Ljava/lang/StringBuilder;", false);
methodVisitor.visitMethodInsn(INVOKEVIRTUAL, "java/lang/StringBuilder", "toString", "()Ljava/lang/String;", false);
methodVisitor.visitMethodInsn(INVOKEVIRTUAL, "java/io/PrintStream", "println", "(Ljava/lang/String;)V", false);
methodVisitor.visitFieldInsn(GETSTATIC, "java/lang/System", "out", "Ljava/io/PrintStream;");
methodVisitor.visitLdcInsn("");
methodVisitor.visitMethodInsn(INVOKEVIRTUAL, "java/io/PrintStream", "println", "(Ljava/lang/String;)V", false);
methodVisitor.visitVarInsn(ALOAD, 9);
methodVisitor.visitVarInsn(ALOAD, 12);
methodVisitor.visitMethodInsn(INVOKEVIRTUAL, "org/bouncycastle/crypto/agreement/jpake/JPAKEParticipant", "validateRound1PayloadReceived", "(Lorg/bouncycastle/crypto/agreement/jpake/JPAKERound1Payload;)V", false);
methodVisitor.visitFieldInsn(GETSTATIC, "java/lang/System", "out", "Ljava/io/PrintStream;");
methodVisitor.visitLdcInsn("Alice checks g^{x4}!=1: OK");
methodVisitor.visitMethodInsn(INVOKEVIRTUAL, "java/io/PrintStream", "println", "(Ljava/lang/String;)V", false);
methodVisitor.visitFieldInsn(GETSTATIC, "java/lang/System", "out", "Ljava/io/PrintStream;");
methodVisitor.visitLdcInsn("Alice checks KP{x3}: OK");
methodVisitor.visitMethodInsn(INVOKEVIRTUAL, "java/io/PrintStream", "println", "(Ljava/lang/String;)V", false);
methodVisitor.visitFieldInsn(GETSTATIC, "java/lang/System", "out", "Ljava/io/PrintStream;");
methodVisitor.visitLdcInsn("Alice checks KP{x4}: OK");
methodVisitor.visitMethodInsn(INVOKEVIRTUAL, "java/io/PrintStream", "println", "(Ljava/lang/String;)V", false);
methodVisitor.visitFieldInsn(GETSTATIC, "java/lang/System", "out", "Ljava/io/PrintStream;");
methodVisitor.visitLdcInsn("");
methodVisitor.visitMethodInsn(INVOKEVIRTUAL, "java/io/PrintStream", "println", "(Ljava/lang/String;)V", false);
methodVisitor.visitVarInsn(ALOAD, 10);
methodVisitor.visitVarInsn(ALOAD, 11);
methodVisitor.visitMethodInsn(INVOKEVIRTUAL, "org/bouncycastle/crypto/agreement/jpake/JPAKEParticipant", "validateRound1PayloadReceived", "(Lorg/bouncycastle/crypto/agreement/jpake/JPAKERound1Payload;)V", false);
methodVisitor.visitFieldInsn(GETSTATIC, "java/lang/System", "out", "Ljava/io/PrintStream;");
methodVisitor.visitLdcInsn("Bob checks g^{x2}!=1: OK");
methodVisitor.visitMethodInsn(INVOKEVIRTUAL, "java/io/PrintStream", "println", "(Ljava/lang/String;)V", false);
methodVisitor.visitFieldInsn(GETSTATIC, "java/lang/System", "out", "Ljava/io/PrintStream;");
methodVisitor.visitLdcInsn("Bob checks KP{x1},: OK");
methodVisitor.visitMethodInsn(INVOKEVIRTUAL, "java/io/PrintStream", "println", "(Ljava/lang/String;)V", false);
methodVisitor.visitFieldInsn(GETSTATIC, "java/lang/System", "out", "Ljava/io/PrintStream;");
methodVisitor.visitLdcInsn("Bob checks KP{x2},: OK");
methodVisitor.visitMethodInsn(INVOKEVIRTUAL, "java/io/PrintStream", "println", "(Ljava/lang/String;)V", false);
methodVisitor.visitFieldInsn(GETSTATIC, "java/lang/System", "out", "Ljava/io/PrintStream;");
methodVisitor.visitLdcInsn("");
methodVisitor.visitMethodInsn(INVOKEVIRTUAL, "java/io/PrintStream", "println", "(Ljava/lang/String;)V", false);
methodVisitor.visitVarInsn(ALOAD, 9);
methodVisitor.visitMethodInsn(INVOKEVIRTUAL, "org/bouncycastle/crypto/agreement/jpake/JPAKEParticipant", "createRound2PayloadToSend", "()Lorg/bouncycastle/crypto/agreement/jpake/JPAKERound2Payload;", false);
methodVisitor.visitVarInsn(ASTORE, 13);
methodVisitor.visitVarInsn(ALOAD, 10);
methodVisitor.visitMethodInsn(INVOKEVIRTUAL, "org/bouncycastle/crypto/agreement/jpake/JPAKEParticipant", "createRound2PayloadToSend", "()Lorg/bouncycastle/crypto/agreement/jpake/JPAKERound2Payload;", false);
methodVisitor.visitVarInsn(ASTORE, 14);
methodVisitor.visitFieldInsn(GETSTATIC, "java/lang/System", "out", "Ljava/io/PrintStream;");
methodVisitor.visitLdcInsn("************ Round 2 **************");
methodVisitor.visitMethodInsn(INVOKEVIRTUAL, "java/io/PrintStream", "println", "(Ljava/lang/String;)V", false);
methodVisitor.visitFieldInsn(GETSTATIC, "java/lang/System", "out", "Ljava/io/PrintStream;");
methodVisitor.visitLdcInsn("Alice sends to Bob: ");
methodVisitor.visitMethodInsn(INVOKEVIRTUAL, "java/io/PrintStream", "println", "(Ljava/lang/String;)V", false);
methodVisitor.visitFieldInsn(GETSTATIC, "java/lang/System", "out", "Ljava/io/PrintStream;");
methodVisitor.visitTypeInsn(NEW, "java/lang/StringBuilder");
methodVisitor.visitInsn(DUP);
methodVisitor.visitMethodInsn(INVOKESPECIAL, "java/lang/StringBuilder", "<init>", "()V", false);
methodVisitor.visitLdcInsn("A=");
methodVisitor.visitMethodInsn(INVOKEVIRTUAL, "java/lang/StringBuilder", "append", "(Ljava/lang/String;)Ljava/lang/StringBuilder;", false);
methodVisitor.visitVarInsn(ALOAD, 13);
methodVisitor.visitMethodInsn(INVOKEVIRTUAL, "org/bouncycastle/crypto/agreement/jpake/JPAKERound2Payload", "getA", "()Ljava/math/BigInteger;", false);
methodVisitor.visitIntInsn(BIPUSH, 16);
methodVisitor.visitMethodInsn(INVOKEVIRTUAL, "java/math/BigInteger", "toString", "(I)Ljava/lang/String;", false);
methodVisitor.visitMethodInsn(INVOKEVIRTUAL, "java/lang/StringBuilder", "append", "(Ljava/lang/String;)Ljava/lang/StringBuilder;", false);
methodVisitor.visitMethodInsn(INVOKEVIRTUAL, "java/lang/StringBuilder", "toString", "()Ljava/lang/String;", false);
methodVisitor.visitMethodInsn(INVOKEVIRTUAL, "java/io/PrintStream", "println", "(Ljava/lang/String;)V", false);
methodVisitor.visitFieldInsn(GETSTATIC, "java/lang/System", "out", "Ljava/io/PrintStream;");
methodVisitor.visitTypeInsn(NEW, "java/lang/StringBuilder");
methodVisitor.visitInsn(DUP);
methodVisitor.visitMethodInsn(INVOKESPECIAL, "java/lang/StringBuilder", "<init>", "()V", false);
methodVisitor.visitLdcInsn("KP{x2*s}={");
methodVisitor.visitMethodInsn(INVOKEVIRTUAL, "java/lang/StringBuilder", "append", "(Ljava/lang/String;)Ljava/lang/StringBuilder;", false);
methodVisitor.visitVarInsn(ALOAD, 13);
methodVisitor.visitMethodInsn(INVOKEVIRTUAL, "org/bouncycastle/crypto/agreement/jpake/JPAKERound2Payload", "getKnowledgeProofForX2s", "()[Ljava/math/BigInteger;", false);
methodVisitor.visitInsn(ICONST_0);
methodVisitor.visitInsn(AALOAD);
methodVisitor.visitIntInsn(BIPUSH, 16);
methodVisitor.visitMethodInsn(INVOKEVIRTUAL, "java/math/BigInteger", "toString", "(I)Ljava/lang/String;", false);
methodVisitor.visitMethodInsn(INVOKEVIRTUAL, "java/lang/StringBuilder", "append", "(Ljava/lang/String;)Ljava/lang/StringBuilder;", false);
methodVisitor.visitLdcInsn("},{");
methodVisitor.visitMethodInsn(INVOKEVIRTUAL, "java/lang/StringBuilder", "append", "(Ljava/lang/String;)Ljava/lang/StringBuilder;", false);
methodVisitor.visitVarInsn(ALOAD, 13);
methodVisitor.visitMethodInsn(INVOKEVIRTUAL, "org/bouncycastle/crypto/agreement/jpake/JPAKERound2Payload", "getKnowledgeProofForX2s", "()[Ljava/math/BigInteger;", false);
methodVisitor.visitInsn(ICONST_1);
methodVisitor.visitInsn(AALOAD);
methodVisitor.visitIntInsn(BIPUSH, 16);
methodVisitor.visitMethodInsn(INVOKEVIRTUAL, "java/math/BigInteger", "toString", "(I)Ljava/lang/String;", false);
methodVisitor.visitMethodInsn(INVOKEVIRTUAL, "java/lang/StringBuilder", "append", "(Ljava/lang/String;)Ljava/lang/StringBuilder;", false);
methodVisitor.visitLdcInsn("}");
methodVisitor.visitMethodInsn(INVOKEVIRTUAL, "java/lang/StringBuilder", "append", "(Ljava/lang/String;)Ljava/lang/StringBuilder;", false);
methodVisitor.visitMethodInsn(INVOKEVIRTUAL, "java/lang/StringBuilder", "toString", "()Ljava/lang/String;", false);
methodVisitor.visitMethodInsn(INVOKEVIRTUAL, "java/io/PrintStream", "println", "(Ljava/lang/String;)V", false);
methodVisitor.visitFieldInsn(GETSTATIC, "java/lang/System", "out", "Ljava/io/PrintStream;");
methodVisitor.visitLdcInsn("");
methodVisitor.visitMethodInsn(INVOKEVIRTUAL, "java/io/PrintStream", "println", "(Ljava/lang/String;)V", false);
methodVisitor.visitFieldInsn(GETSTATIC, "java/lang/System", "out", "Ljava/io/PrintStream;");
methodVisitor.visitLdcInsn("Bob sends to Alice");
methodVisitor.visitMethodInsn(INVOKEVIRTUAL, "java/io/PrintStream", "println", "(Ljava/lang/String;)V", false);
methodVisitor.visitFieldInsn(GETSTATIC, "java/lang/System", "out", "Ljava/io/PrintStream;");
methodVisitor.visitTypeInsn(NEW, "java/lang/StringBuilder");
methodVisitor.visitInsn(DUP);
methodVisitor.visitMethodInsn(INVOKESPECIAL, "java/lang/StringBuilder", "<init>", "()V", false);
methodVisitor.visitLdcInsn("B=");
methodVisitor.visitMethodInsn(INVOKEVIRTUAL, "java/lang/StringBuilder", "append", "(Ljava/lang/String;)Ljava/lang/StringBuilder;", false);
methodVisitor.visitVarInsn(ALOAD, 14);
methodVisitor.visitMethodInsn(INVOKEVIRTUAL, "org/bouncycastle/crypto/agreement/jpake/JPAKERound2Payload", "getA", "()Ljava/math/BigInteger;", false);
methodVisitor.visitIntInsn(BIPUSH, 16);
methodVisitor.visitMethodInsn(INVOKEVIRTUAL, "java/math/BigInteger", "toString", "(I)Ljava/lang/String;", false);
methodVisitor.visitMethodInsn(INVOKEVIRTUAL, "java/lang/StringBuilder", "append", "(Ljava/lang/String;)Ljava/lang/StringBuilder;", false);
methodVisitor.visitMethodInsn(INVOKEVIRTUAL, "java/lang/StringBuilder", "toString", "()Ljava/lang/String;", false);
methodVisitor.visitMethodInsn(INVOKEVIRTUAL, "java/io/PrintStream", "println", "(Ljava/lang/String;)V", false);
methodVisitor.visitFieldInsn(GETSTATIC, "java/lang/System", "out", "Ljava/io/PrintStream;");
methodVisitor.visitTypeInsn(NEW, "java/lang/StringBuilder");
methodVisitor.visitInsn(DUP);
methodVisitor.visitMethodInsn(INVOKESPECIAL, "java/lang/StringBuilder", "<init>", "()V", false);
methodVisitor.visitLdcInsn("KP{x4*s}={");
methodVisitor.visitMethodInsn(INVOKEVIRTUAL, "java/lang/StringBuilder", "append", "(Ljava/lang/String;)Ljava/lang/StringBuilder;", false);
methodVisitor.visitVarInsn(ALOAD, 14);
methodVisitor.visitMethodInsn(INVOKEVIRTUAL, "org/bouncycastle/crypto/agreement/jpake/JPAKERound2Payload", "getKnowledgeProofForX2s", "()[Ljava/math/BigInteger;", false);
methodVisitor.visitInsn(ICONST_0);
methodVisitor.visitInsn(AALOAD);
methodVisitor.visitIntInsn(BIPUSH, 16);
methodVisitor.visitMethodInsn(INVOKEVIRTUAL, "java/math/BigInteger", "toString", "(I)Ljava/lang/String;", false);
methodVisitor.visitMethodInsn(INVOKEVIRTUAL, "java/lang/StringBuilder", "append", "(Ljava/lang/String;)Ljava/lang/StringBuilder;", false);
methodVisitor.visitLdcInsn("},{");
methodVisitor.visitMethodInsn(INVOKEVIRTUAL, "java/lang/StringBuilder", "append", "(Ljava/lang/String;)Ljava/lang/StringBuilder;", false);
methodVisitor.visitVarInsn(ALOAD, 14);
methodVisitor.visitMethodInsn(INVOKEVIRTUAL, "org/bouncycastle/crypto/agreement/jpake/JPAKERound2Payload", "getKnowledgeProofForX2s", "()[Ljava/math/BigInteger;", false);
methodVisitor.visitInsn(ICONST_1);
methodVisitor.visitInsn(AALOAD);
methodVisitor.visitIntInsn(BIPUSH, 16);
methodVisitor.visitMethodInsn(INVOKEVIRTUAL, "java/math/BigInteger", "toString", "(I)Ljava/lang/String;", false);
methodVisitor.visitMethodInsn(INVOKEVIRTUAL, "java/lang/StringBuilder", "append", "(Ljava/lang/String;)Ljava/lang/StringBuilder;", false);
methodVisitor.visitLdcInsn("}");
methodVisitor.visitMethodInsn(INVOKEVIRTUAL, "java/lang/StringBuilder", "append", "(Ljava/lang/String;)Ljava/lang/StringBuilder;", false);
methodVisitor.visitMethodInsn(INVOKEVIRTUAL, "java/lang/StringBuilder", "toString", "()Ljava/lang/String;", false);
methodVisitor.visitMethodInsn(INVOKEVIRTUAL, "java/io/PrintStream", "println", "(Ljava/lang/String;)V", false);
methodVisitor.visitFieldInsn(GETSTATIC, "java/lang/System", "out", "Ljava/io/PrintStream;");
methodVisitor.visitLdcInsn("");
methodVisitor.visitMethodInsn(INVOKEVIRTUAL, "java/io/PrintStream", "println", "(Ljava/lang/String;)V", false);
methodVisitor.visitVarInsn(ALOAD, 9);
methodVisitor.visitVarInsn(ALOAD, 14);
methodVisitor.visitMethodInsn(INVOKEVIRTUAL, "org/bouncycastle/crypto/agreement/jpake/JPAKEParticipant", "validateRound2PayloadReceived", "(Lorg/bouncycastle/crypto/agreement/jpake/JPAKERound2Payload;)V", false);
methodVisitor.visitFieldInsn(GETSTATIC, "java/lang/System", "out", "Ljava/io/PrintStream;");
methodVisitor.visitLdcInsn("Alice checks KP{x4*s}: OK\n");
methodVisitor.visitMethodInsn(INVOKEVIRTUAL, "java/io/PrintStream", "println", "(Ljava/lang/String;)V", false);
methodVisitor.visitVarInsn(ALOAD, 10);
methodVisitor.visitVarInsn(ALOAD, 13);
methodVisitor.visitMethodInsn(INVOKEVIRTUAL, "org/bouncycastle/crypto/agreement/jpake/JPAKEParticipant", "validateRound2PayloadReceived", "(Lorg/bouncycastle/crypto/agreement/jpake/JPAKERound2Payload;)V", false);
methodVisitor.visitFieldInsn(GETSTATIC, "java/lang/System", "out", "Ljava/io/PrintStream;");
methodVisitor.visitLdcInsn("Bob checks KP{x2*s}: OK\n");
methodVisitor.visitMethodInsn(INVOKEVIRTUAL, "java/io/PrintStream", "println", "(Ljava/lang/String;)V", false);
methodVisitor.visitVarInsn(ALOAD, 9);
methodVisitor.visitMethodInsn(INVOKEVIRTUAL, "org/bouncycastle/crypto/agreement/jpake/JPAKEParticipant", "calculateKeyingMaterial", "()Ljava/math/BigInteger;", false);
methodVisitor.visitVarInsn(ASTORE, 15);
methodVisitor.visitVarInsn(ALOAD, 10);
methodVisitor.visitMethodInsn(INVOKEVIRTUAL, "org/bouncycastle/crypto/agreement/jpake/JPAKEParticipant", "calculateKeyingMaterial", "()Ljava/math/BigInteger;", false);
methodVisitor.visitVarInsn(ASTORE, 16);
methodVisitor.visitFieldInsn(GETSTATIC, "java/lang/System", "out", "Ljava/io/PrintStream;");
methodVisitor.visitLdcInsn("********* After round 2 ***********");
methodVisitor.visitMethodInsn(INVOKEVIRTUAL, "java/io/PrintStream", "println", "(Ljava/lang/String;)V", false);
methodVisitor.visitFieldInsn(GETSTATIC, "java/lang/System", "out", "Ljava/io/PrintStream;");
methodVisitor.visitTypeInsn(NEW, "java/lang/StringBuilder");
methodVisitor.visitInsn(DUP);
methodVisitor.visitMethodInsn(INVOKESPECIAL, "java/lang/StringBuilder", "<init>", "()V", false);
methodVisitor.visitLdcInsn("Alice computes key material \u0009 K=");
methodVisitor.visitMethodInsn(INVOKEVIRTUAL, "java/lang/StringBuilder", "append", "(Ljava/lang/String;)Ljava/lang/StringBuilder;", false);
methodVisitor.visitVarInsn(ALOAD, 15);
methodVisitor.visitIntInsn(BIPUSH, 16);
methodVisitor.visitMethodInsn(INVOKEVIRTUAL, "java/math/BigInteger", "toString", "(I)Ljava/lang/String;", false);
methodVisitor.visitMethodInsn(INVOKEVIRTUAL, "java/lang/StringBuilder", "append", "(Ljava/lang/String;)Ljava/lang/StringBuilder;", false);
methodVisitor.visitMethodInsn(INVOKEVIRTUAL, "java/lang/StringBuilder", "toString", "()Ljava/lang/String;", false);
methodVisitor.visitMethodInsn(INVOKEVIRTUAL, "java/io/PrintStream", "println", "(Ljava/lang/String;)V", false);
methodVisitor.visitFieldInsn(GETSTATIC, "java/lang/System", "out", "Ljava/io/PrintStream;");
methodVisitor.visitTypeInsn(NEW, "java/lang/StringBuilder");
methodVisitor.visitInsn(DUP);
methodVisitor.visitMethodInsn(INVOKESPECIAL, "java/lang/StringBuilder", "<init>", "()V", false);
methodVisitor.visitLdcInsn("Bob computes key material \u0009 K=");
methodVisitor.visitMethodInsn(INVOKEVIRTUAL, "java/lang/StringBuilder", "append", "(Ljava/lang/String;)Ljava/lang/StringBuilder;", false);
methodVisitor.visitVarInsn(ALOAD, 16);
methodVisitor.visitIntInsn(BIPUSH, 16);
methodVisitor.visitMethodInsn(INVOKEVIRTUAL, "java/math/BigInteger", "toString", "(I)Ljava/lang/String;", false);
methodVisitor.visitMethodInsn(INVOKEVIRTUAL, "java/lang/StringBuilder", "append", "(Ljava/lang/String;)Ljava/lang/StringBuilder;", false);
methodVisitor.visitMethodInsn(INVOKEVIRTUAL, "java/lang/StringBuilder", "toString", "()Ljava/lang/String;", false);
methodVisitor.visitMethodInsn(INVOKEVIRTUAL, "java/io/PrintStream", "println", "(Ljava/lang/String;)V", false);
methodVisitor.visitFieldInsn(GETSTATIC, "java/lang/System", "out", "Ljava/io/PrintStream;");
methodVisitor.visitMethodInsn(INVOKEVIRTUAL, "java/io/PrintStream", "println", "()V", false);
methodVisitor.visitVarInsn(ALOAD, 15);
methodVisitor.visitMethodInsn(INVOKESTATIC, "org/bouncycastle/crypto/examples/JPAKEExample", "deriveSessionKey", "(Ljava/math/BigInteger;)Ljava/math/BigInteger;", false);
methodVisitor.visitVarInsn(ASTORE, 17);
methodVisitor.visitVarInsn(ALOAD, 16);
methodVisitor.visitMethodInsn(INVOKESTATIC, "org/bouncycastle/crypto/examples/JPAKEExample", "deriveSessionKey", "(Ljava/math/BigInteger;)Ljava/math/BigInteger;", false);
methodVisitor.visitVarInsn(ASTORE, 18);
methodVisitor.visitVarInsn(ALOAD, 9);
methodVisitor.visitVarInsn(ALOAD, 15);
methodVisitor.visitMethodInsn(INVOKEVIRTUAL, "org/bouncycastle/crypto/agreement/jpake/JPAKEParticipant", "createRound3PayloadToSend", "(Ljava/math/BigInteger;)Lorg/bouncycastle/crypto/agreement/jpake/JPAKERound3Payload;", false);
methodVisitor.visitVarInsn(ASTORE, 19);
methodVisitor.visitVarInsn(ALOAD, 10);
methodVisitor.visitVarInsn(ALOAD, 16);
methodVisitor.visitMethodInsn(INVOKEVIRTUAL, "org/bouncycastle/crypto/agreement/jpake/JPAKEParticipant", "createRound3PayloadToSend", "(Ljava/math/BigInteger;)Lorg/bouncycastle/crypto/agreement/jpake/JPAKERound3Payload;", false);
methodVisitor.visitVarInsn(ASTORE, 20);
methodVisitor.visitFieldInsn(GETSTATIC, "java/lang/System", "out", "Ljava/io/PrintStream;");
methodVisitor.visitLdcInsn("************ Round 3 **************");
methodVisitor.visitMethodInsn(INVOKEVIRTUAL, "java/io/PrintStream", "println", "(Ljava/lang/String;)V", false);
methodVisitor.visitFieldInsn(GETSTATIC, "java/lang/System", "out", "Ljava/io/PrintStream;");
methodVisitor.visitLdcInsn("Alice sends to Bob: ");
methodVisitor.visitMethodInsn(INVOKEVIRTUAL, "java/io/PrintStream", "println", "(Ljava/lang/String;)V", false);
methodVisitor.visitFieldInsn(GETSTATIC, "java/lang/System", "out", "Ljava/io/PrintStream;");
methodVisitor.visitTypeInsn(NEW, "java/lang/StringBuilder");
methodVisitor.visitInsn(DUP);
methodVisitor.visitMethodInsn(INVOKESPECIAL, "java/lang/StringBuilder", "<init>", "()V", false);
methodVisitor.visitLdcInsn("MacTag=");
methodVisitor.visitMethodInsn(INVOKEVIRTUAL, "java/lang/StringBuilder", "append", "(Ljava/lang/String;)Ljava/lang/StringBuilder;", false);
methodVisitor.visitVarInsn(ALOAD, 19);
methodVisitor.visitMethodInsn(INVOKEVIRTUAL, "org/bouncycastle/crypto/agreement/jpake/JPAKERound3Payload", "getMacTag", "()Ljava/math/BigInteger;", false);
methodVisitor.visitIntInsn(BIPUSH, 16);
methodVisitor.visitMethodInsn(INVOKEVIRTUAL, "java/math/BigInteger", "toString", "(I)Ljava/lang/String;", false);
methodVisitor.visitMethodInsn(INVOKEVIRTUAL, "java/lang/StringBuilder", "append", "(Ljava/lang/String;)Ljava/lang/StringBuilder;", false);
methodVisitor.visitMethodInsn(INVOKEVIRTUAL, "java/lang/StringBuilder", "toString", "()Ljava/lang/String;", false);
methodVisitor.visitMethodInsn(INVOKEVIRTUAL, "java/io/PrintStream", "println", "(Ljava/lang/String;)V", false);
methodVisitor.visitFieldInsn(GETSTATIC, "java/lang/System", "out", "Ljava/io/PrintStream;");
methodVisitor.visitLdcInsn("");
methodVisitor.visitMethodInsn(INVOKEVIRTUAL, "java/io/PrintStream", "println", "(Ljava/lang/String;)V", false);
methodVisitor.visitFieldInsn(GETSTATIC, "java/lang/System", "out", "Ljava/io/PrintStream;");
methodVisitor.visitLdcInsn("Bob sends to Alice: ");
methodVisitor.visitMethodInsn(INVOKEVIRTUAL, "java/io/PrintStream", "println", "(Ljava/lang/String;)V", false);
methodVisitor.visitFieldInsn(GETSTATIC, "java/lang/System", "out", "Ljava/io/PrintStream;");
methodVisitor.visitTypeInsn(NEW, "java/lang/StringBuilder");
methodVisitor.visitInsn(DUP);
methodVisitor.visitMethodInsn(INVOKESPECIAL, "java/lang/StringBuilder", "<init>", "()V", false);
methodVisitor.visitLdcInsn("MacTag=");
methodVisitor.visitMethodInsn(INVOKEVIRTUAL, "java/lang/StringBuilder", "append", "(Ljava/lang/String;)Ljava/lang/StringBuilder;", false);
methodVisitor.visitVarInsn(ALOAD, 20);
methodVisitor.visitMethodInsn(INVOKEVIRTUAL, "org/bouncycastle/crypto/agreement/jpake/JPAKERound3Payload", "getMacTag", "()Ljava/math/BigInteger;", false);
methodVisitor.visitIntInsn(BIPUSH, 16);
methodVisitor.visitMethodInsn(INVOKEVIRTUAL, "java/math/BigInteger", "toString", "(I)Ljava/lang/String;", false);
methodVisitor.visitMethodInsn(INVOKEVIRTUAL, "java/lang/StringBuilder", "append", "(Ljava/lang/String;)Ljava/lang/StringBuilder;", false);
methodVisitor.visitMethodInsn(INVOKEVIRTUAL, "java/lang/StringBuilder", "toString", "()Ljava/lang/String;", false);
methodVisitor.visitMethodInsn(INVOKEVIRTUAL, "java/io/PrintStream", "println", "(Ljava/lang/String;)V", false);
methodVisitor.visitFieldInsn(GETSTATIC, "java/lang/System", "out", "Ljava/io/PrintStream;");
methodVisitor.visitLdcInsn("");
methodVisitor.visitMethodInsn(INVOKEVIRTUAL, "java/io/PrintStream", "println", "(Ljava/lang/String;)V", false);
methodVisitor.visitVarInsn(ALOAD, 9);
methodVisitor.visitVarInsn(ALOAD, 20);
methodVisitor.visitVarInsn(ALOAD, 15);
methodVisitor.visitMethodInsn(INVOKEVIRTUAL, "org/bouncycastle/crypto/agreement/jpake/JPAKEParticipant", "validateRound3PayloadReceived", "(Lorg/bouncycastle/crypto/agreement/jpake/JPAKERound3Payload;Ljava/math/BigInteger;)V", false);
methodVisitor.visitFieldInsn(GETSTATIC, "java/lang/System", "out", "Ljava/io/PrintStream;");
methodVisitor.visitLdcInsn("Alice checks MacTag: OK\n");
methodVisitor.visitMethodInsn(INVOKEVIRTUAL, "java/io/PrintStream", "println", "(Ljava/lang/String;)V", false);
methodVisitor.visitVarInsn(ALOAD, 10);
methodVisitor.visitVarInsn(ALOAD, 19);
methodVisitor.visitVarInsn(ALOAD, 16);
methodVisitor.visitMethodInsn(INVOKEVIRTUAL, "org/bouncycastle/crypto/agreement/jpake/JPAKEParticipant", "validateRound3PayloadReceived", "(Lorg/bouncycastle/crypto/agreement/jpake/JPAKERound3Payload;Ljava/math/BigInteger;)V", false);
methodVisitor.visitFieldInsn(GETSTATIC, "java/lang/System", "out", "Ljava/io/PrintStream;");
methodVisitor.visitLdcInsn("Bob checks MacTag: OK\n");
methodVisitor.visitMethodInsn(INVOKEVIRTUAL, "java/io/PrintStream", "println", "(Ljava/lang/String;)V", false);
methodVisitor.visitFieldInsn(GETSTATIC, "java/lang/System", "out", "Ljava/io/PrintStream;");
methodVisitor.visitMethodInsn(INVOKEVIRTUAL, "java/io/PrintStream", "println", "()V", false);
methodVisitor.visitFieldInsn(GETSTATIC, "java/lang/System", "out", "Ljava/io/PrintStream;");
methodVisitor.visitLdcInsn("MacTags validated, therefore the keying material matches.");
methodVisitor.visitMethodInsn(INVOKEVIRTUAL, "java/io/PrintStream", "println", "(Ljava/lang/String;)V", false);
methodVisitor.visitInsn(RETURN);
methodVisitor.visitMaxs(7, 21);
methodVisitor.visitEnd();
}
{
methodVisitor = classWriter.visitMethod(ACC_PRIVATE | ACC_STATIC, "deriveSessionKey", "(Ljava/math/BigInteger;)Ljava/math/BigInteger;", null, null);
methodVisitor.visitCode();
methodVisitor.visitTypeInsn(NEW, "org/bouncycastle/crypto/digests/SHA256Digest");
methodVisitor.visitInsn(DUP);
methodVisitor.visitMethodInsn(INVOKESPECIAL, "org/bouncycastle/crypto/digests/SHA256Digest", "<init>", "()V", false);
methodVisitor.visitVarInsn(ASTORE, 1);
methodVisitor.visitVarInsn(ALOAD, 0);
methodVisitor.visitMethodInsn(INVOKEVIRTUAL, "java/math/BigInteger", "toByteArray", "()[B", false);
methodVisitor.visitVarInsn(ASTORE, 2);
methodVisitor.visitVarInsn(ALOAD, 1);
methodVisitor.visitMethodInsn(INVOKEVIRTUAL, "org/bouncycastle/crypto/digests/SHA256Digest", "getDigestSize", "()I", false);
methodVisitor.visitIntInsn(NEWARRAY, T_BYTE);
methodVisitor.visitVarInsn(ASTORE, 3);
methodVisitor.visitVarInsn(ALOAD, 1);
methodVisitor.visitVarInsn(ALOAD, 2);
methodVisitor.visitInsn(ICONST_0);
methodVisitor.visitVarInsn(ALOAD, 2);
methodVisitor.visitInsn(ARRAYLENGTH);
methodVisitor.visitMethodInsn(INVOKEVIRTUAL, "org/bouncycastle/crypto/digests/SHA256Digest", "update", "([BII)V", false);
methodVisitor.visitVarInsn(ALOAD, 1);
methodVisitor.visitVarInsn(ALOAD, 3);
methodVisitor.visitInsn(ICONST_0);
methodVisitor.visitMethodInsn(INVOKEVIRTUAL, "org/bouncycastle/crypto/digests/SHA256Digest", "doFinal", "([BI)I", false);
methodVisitor.visitInsn(POP);
methodVisitor.visitTypeInsn(NEW, "java/math/BigInteger");
methodVisitor.visitInsn(DUP);
methodVisitor.visitVarInsn(ALOAD, 3);
methodVisitor.visitMethodInsn(INVOKESPECIAL, "java/math/BigInteger", "<init>", "([B)V", false);
methodVisitor.visitInsn(ARETURN);
methodVisitor.visitMaxs(4, 4);
methodVisitor.visitEnd();
}
classWriter.visitEnd();

return classWriter.toByteArray();
}
}
