package asm.org.bouncycastle.math.ec.custom.djb;
import org.objectweb.asm.AnnotationVisitor;
import org.objectweb.asm.Attribute;
import org.objectweb.asm.ClassReader;
import org.objectweb.asm.ClassWriter;
import org.objectweb.asm.ConstantDynamic;
import org.objectweb.asm.FieldVisitor;
import org.objectweb.asm.Handle;
import org.objectweb.asm.Label;
import org.objectweb.asm.MethodVisitor;
import org.objectweb.asm.Opcodes;
import org.objectweb.asm.RecordComponentVisitor;
import org.objectweb.asm.Type;
import org.objectweb.asm.TypePath;
public class Curve25519FieldDump implements Opcodes {

public static byte[] dump () throws Exception {

ClassWriter classWriter = new ClassWriter(0);
FieldVisitor fieldVisitor;
RecordComponentVisitor recordComponentVisitor;
MethodVisitor methodVisitor;
AnnotationVisitor annotationVisitor0;

classWriter.visit(V1_5, ACC_PUBLIC | ACC_SUPER, "org/bouncycastle/math/ec/custom/djb/Curve25519Field", null, "java/lang/Object", null);

{
fieldVisitor = classWriter.visitField(ACC_PRIVATE | ACC_FINAL | ACC_STATIC, "M", "J", null, new Long(4294967295L));
fieldVisitor.visitEnd();
}
{
fieldVisitor = classWriter.visitField(ACC_FINAL | ACC_STATIC, "P", "[I", null, null);
fieldVisitor.visitEnd();
}
{
fieldVisitor = classWriter.visitField(ACC_PRIVATE | ACC_FINAL | ACC_STATIC, "P7", "I", null, new Integer(2147483647));
fieldVisitor.visitEnd();
}
{
fieldVisitor = classWriter.visitField(ACC_PRIVATE | ACC_FINAL | ACC_STATIC, "PExt", "[I", null, null);
fieldVisitor.visitEnd();
}
{
fieldVisitor = classWriter.visitField(ACC_PRIVATE | ACC_FINAL | ACC_STATIC, "PInv", "I", null, new Integer(19));
fieldVisitor.visitEnd();
}
{
methodVisitor = classWriter.visitMethod(ACC_PUBLIC, "<init>", "()V", null, null);
methodVisitor.visitCode();
methodVisitor.visitVarInsn(ALOAD, 0);
methodVisitor.visitMethodInsn(INVOKESPECIAL, "java/lang/Object", "<init>", "()V", false);
methodVisitor.visitInsn(RETURN);
methodVisitor.visitMaxs(1, 1);
methodVisitor.visitEnd();
}
{
methodVisitor = classWriter.visitMethod(ACC_PUBLIC | ACC_STATIC, "add", "([I[I[I)V", null, null);
methodVisitor.visitCode();
methodVisitor.visitVarInsn(ALOAD, 0);
methodVisitor.visitVarInsn(ALOAD, 1);
methodVisitor.visitVarInsn(ALOAD, 2);
methodVisitor.visitMethodInsn(INVOKESTATIC, "org/bouncycastle/math/raw/Nat256", "add", "([I[I[I)I", false);
methodVisitor.visitInsn(POP);
methodVisitor.visitVarInsn(ALOAD, 2);
methodVisitor.visitFieldInsn(GETSTATIC, "org/bouncycastle/math/ec/custom/djb/Curve25519Field", "P", "[I");
methodVisitor.visitMethodInsn(INVOKESTATIC, "org/bouncycastle/math/raw/Nat256", "gte", "([I[I)Z", false);
Label label0 = new Label();
methodVisitor.visitJumpInsn(IFEQ, label0);
methodVisitor.visitVarInsn(ALOAD, 2);
methodVisitor.visitMethodInsn(INVOKESTATIC, "org/bouncycastle/math/ec/custom/djb/Curve25519Field", "subPFrom", "([I)I", false);
methodVisitor.visitInsn(POP);
methodVisitor.visitLabel(label0);
methodVisitor.visitInsn(RETURN);
methodVisitor.visitMaxs(3, 3);
methodVisitor.visitEnd();
}
{
methodVisitor = classWriter.visitMethod(ACC_PUBLIC | ACC_STATIC, "addExt", "([I[I[I)V", null, null);
methodVisitor.visitCode();
methodVisitor.visitIntInsn(BIPUSH, 16);
methodVisitor.visitVarInsn(ALOAD, 0);
methodVisitor.visitVarInsn(ALOAD, 1);
methodVisitor.visitVarInsn(ALOAD, 2);
methodVisitor.visitMethodInsn(INVOKESTATIC, "org/bouncycastle/math/raw/Nat", "add", "(I[I[I[I)I", false);
methodVisitor.visitInsn(POP);
methodVisitor.visitIntInsn(BIPUSH, 16);
methodVisitor.visitVarInsn(ALOAD, 2);
methodVisitor.visitFieldInsn(GETSTATIC, "org/bouncycastle/math/ec/custom/djb/Curve25519Field", "PExt", "[I");
methodVisitor.visitMethodInsn(INVOKESTATIC, "org/bouncycastle/math/raw/Nat", "gte", "(I[I[I)Z", false);
Label label0 = new Label();
methodVisitor.visitJumpInsn(IFEQ, label0);
methodVisitor.visitVarInsn(ALOAD, 2);
methodVisitor.visitMethodInsn(INVOKESTATIC, "org/bouncycastle/math/ec/custom/djb/Curve25519Field", "subPExtFrom", "([I)I", false);
methodVisitor.visitInsn(POP);
methodVisitor.visitLabel(label0);
methodVisitor.visitInsn(RETURN);
methodVisitor.visitMaxs(4, 3);
methodVisitor.visitEnd();
}
{
methodVisitor = classWriter.visitMethod(ACC_PUBLIC | ACC_STATIC, "addOne", "([I[I)V", null, null);
methodVisitor.visitCode();
methodVisitor.visitIntInsn(BIPUSH, 8);
methodVisitor.visitVarInsn(ALOAD, 0);
methodVisitor.visitVarInsn(ALOAD, 1);
methodVisitor.visitMethodInsn(INVOKESTATIC, "org/bouncycastle/math/raw/Nat", "inc", "(I[I[I)I", false);
methodVisitor.visitInsn(POP);
methodVisitor.visitVarInsn(ALOAD, 1);
methodVisitor.visitFieldInsn(GETSTATIC, "org/bouncycastle/math/ec/custom/djb/Curve25519Field", "P", "[I");
methodVisitor.visitMethodInsn(INVOKESTATIC, "org/bouncycastle/math/raw/Nat256", "gte", "([I[I)Z", false);
Label label0 = new Label();
methodVisitor.visitJumpInsn(IFEQ, label0);
methodVisitor.visitVarInsn(ALOAD, 1);
methodVisitor.visitMethodInsn(INVOKESTATIC, "org/bouncycastle/math/ec/custom/djb/Curve25519Field", "subPFrom", "([I)I", false);
methodVisitor.visitInsn(POP);
methodVisitor.visitLabel(label0);
methodVisitor.visitInsn(RETURN);
methodVisitor.visitMaxs(3, 2);
methodVisitor.visitEnd();
}
{
methodVisitor = classWriter.visitMethod(ACC_PUBLIC | ACC_STATIC, "fromBigInteger", "(Ljava/math/BigInteger;)[I", null, null);
methodVisitor.visitCode();
methodVisitor.visitVarInsn(ALOAD, 0);
methodVisitor.visitMethodInsn(INVOKESTATIC, "org/bouncycastle/math/raw/Nat256", "fromBigInteger", "(Ljava/math/BigInteger;)[I", false);
methodVisitor.visitVarInsn(ASTORE, 1);
Label label0 = new Label();
methodVisitor.visitLabel(label0);
methodVisitor.visitVarInsn(ALOAD, 1);
methodVisitor.visitFieldInsn(GETSTATIC, "org/bouncycastle/math/ec/custom/djb/Curve25519Field", "P", "[I");
methodVisitor.visitMethodInsn(INVOKESTATIC, "org/bouncycastle/math/raw/Nat256", "gte", "([I[I)Z", false);
Label label1 = new Label();
methodVisitor.visitJumpInsn(IFEQ, label1);
methodVisitor.visitFieldInsn(GETSTATIC, "org/bouncycastle/math/ec/custom/djb/Curve25519Field", "P", "[I");
methodVisitor.visitVarInsn(ALOAD, 1);
methodVisitor.visitMethodInsn(INVOKESTATIC, "org/bouncycastle/math/raw/Nat256", "subFrom", "([I[I)I", false);
methodVisitor.visitInsn(POP);
methodVisitor.visitJumpInsn(GOTO, label0);
methodVisitor.visitLabel(label1);
methodVisitor.visitVarInsn(ALOAD, 1);
methodVisitor.visitInsn(ARETURN);
methodVisitor.visitMaxs(2, 2);
methodVisitor.visitEnd();
}
{
methodVisitor = classWriter.visitMethod(ACC_PUBLIC | ACC_STATIC, "half", "([I[I)V", null, null);
methodVisitor.visitCode();
methodVisitor.visitVarInsn(ALOAD, 0);
methodVisitor.visitInsn(ICONST_0);
methodVisitor.visitInsn(IALOAD);
methodVisitor.visitInsn(ICONST_1);
methodVisitor.visitInsn(IAND);
Label label0 = new Label();
methodVisitor.visitJumpInsn(IFNE, label0);
methodVisitor.visitIntInsn(BIPUSH, 8);
methodVisitor.visitVarInsn(ALOAD, 0);
methodVisitor.visitInsn(ICONST_0);
methodVisitor.visitVarInsn(ALOAD, 1);
methodVisitor.visitMethodInsn(INVOKESTATIC, "org/bouncycastle/math/raw/Nat", "shiftDownBit", "(I[II[I)I", false);
methodVisitor.visitInsn(POP);
Label label1 = new Label();
methodVisitor.visitJumpInsn(GOTO, label1);
methodVisitor.visitLabel(label0);
methodVisitor.visitVarInsn(ALOAD, 0);
methodVisitor.visitFieldInsn(GETSTATIC, "org/bouncycastle/math/ec/custom/djb/Curve25519Field", "P", "[I");
methodVisitor.visitVarInsn(ALOAD, 1);
methodVisitor.visitMethodInsn(INVOKESTATIC, "org/bouncycastle/math/raw/Nat256", "add", "([I[I[I)I", false);
methodVisitor.visitInsn(POP);
methodVisitor.visitIntInsn(BIPUSH, 8);
methodVisitor.visitVarInsn(ALOAD, 1);
methodVisitor.visitInsn(ICONST_0);
methodVisitor.visitMethodInsn(INVOKESTATIC, "org/bouncycastle/math/raw/Nat", "shiftDownBit", "(I[II)I", false);
methodVisitor.visitInsn(POP);
methodVisitor.visitLabel(label1);
methodVisitor.visitInsn(RETURN);
methodVisitor.visitMaxs(4, 2);
methodVisitor.visitEnd();
}
{
methodVisitor = classWriter.visitMethod(ACC_PUBLIC | ACC_STATIC, "multiply", "([I[I[I)V", null, null);
methodVisitor.visitCode();
methodVisitor.visitMethodInsn(INVOKESTATIC, "org/bouncycastle/math/raw/Nat256", "createExt", "()[I", false);
methodVisitor.visitVarInsn(ASTORE, 3);
methodVisitor.visitVarInsn(ALOAD, 0);
methodVisitor.visitVarInsn(ALOAD, 1);
methodVisitor.visitVarInsn(ALOAD, 3);
methodVisitor.visitMethodInsn(INVOKESTATIC, "org/bouncycastle/math/raw/Nat256", "mul", "([I[I[I)V", false);
methodVisitor.visitVarInsn(ALOAD, 3);
methodVisitor.visitVarInsn(ALOAD, 2);
methodVisitor.visitMethodInsn(INVOKESTATIC, "org/bouncycastle/math/ec/custom/djb/Curve25519Field", "reduce", "([I[I)V", false);
methodVisitor.visitInsn(RETURN);
methodVisitor.visitMaxs(3, 4);
methodVisitor.visitEnd();
}
{
methodVisitor = classWriter.visitMethod(ACC_PUBLIC | ACC_STATIC, "multiplyAddToExt", "([I[I[I)V", null, null);
methodVisitor.visitCode();
methodVisitor.visitVarInsn(ALOAD, 0);
methodVisitor.visitVarInsn(ALOAD, 1);
methodVisitor.visitVarInsn(ALOAD, 2);
methodVisitor.visitMethodInsn(INVOKESTATIC, "org/bouncycastle/math/raw/Nat256", "mulAddTo", "([I[I[I)I", false);
methodVisitor.visitInsn(POP);
methodVisitor.visitIntInsn(BIPUSH, 16);
methodVisitor.visitVarInsn(ALOAD, 2);
methodVisitor.visitFieldInsn(GETSTATIC, "org/bouncycastle/math/ec/custom/djb/Curve25519Field", "PExt", "[I");
methodVisitor.visitMethodInsn(INVOKESTATIC, "org/bouncycastle/math/raw/Nat", "gte", "(I[I[I)Z", false);
Label label0 = new Label();
methodVisitor.visitJumpInsn(IFEQ, label0);
methodVisitor.visitVarInsn(ALOAD, 2);
methodVisitor.visitMethodInsn(INVOKESTATIC, "org/bouncycastle/math/ec/custom/djb/Curve25519Field", "subPExtFrom", "([I)I", false);
methodVisitor.visitInsn(POP);
methodVisitor.visitLabel(label0);
methodVisitor.visitInsn(RETURN);
methodVisitor.visitMaxs(3, 3);
methodVisitor.visitEnd();
}
{
methodVisitor = classWriter.visitMethod(ACC_PUBLIC | ACC_STATIC, "negate", "([I[I)V", null, null);
methodVisitor.visitCode();
methodVisitor.visitVarInsn(ALOAD, 0);
methodVisitor.visitMethodInsn(INVOKESTATIC, "org/bouncycastle/math/raw/Nat256", "isZero", "([I)Z", false);
Label label0 = new Label();
methodVisitor.visitJumpInsn(IFEQ, label0);
methodVisitor.visitVarInsn(ALOAD, 1);
methodVisitor.visitMethodInsn(INVOKESTATIC, "org/bouncycastle/math/raw/Nat256", "zero", "([I)V", false);
Label label1 = new Label();
methodVisitor.visitJumpInsn(GOTO, label1);
methodVisitor.visitLabel(label0);
methodVisitor.visitFieldInsn(GETSTATIC, "org/bouncycastle/math/ec/custom/djb/Curve25519Field", "P", "[I");
methodVisitor.visitVarInsn(ALOAD, 0);
methodVisitor.visitVarInsn(ALOAD, 1);
methodVisitor.visitMethodInsn(INVOKESTATIC, "org/bouncycastle/math/raw/Nat256", "sub", "([I[I[I)I", false);
methodVisitor.visitInsn(POP);
methodVisitor.visitLabel(label1);
methodVisitor.visitInsn(RETURN);
methodVisitor.visitMaxs(3, 2);
methodVisitor.visitEnd();
}
{
methodVisitor = classWriter.visitMethod(ACC_PUBLIC | ACC_STATIC, "reduce", "([I[I)V", null, null);
methodVisitor.visitCode();
methodVisitor.visitVarInsn(ALOAD, 0);
methodVisitor.visitIntInsn(BIPUSH, 7);
methodVisitor.visitInsn(IALOAD);
methodVisitor.visitVarInsn(ISTORE, 2);
methodVisitor.visitIntInsn(BIPUSH, 8);
methodVisitor.visitVarInsn(ALOAD, 0);
methodVisitor.visitIntInsn(BIPUSH, 8);
methodVisitor.visitVarInsn(ILOAD, 2);
methodVisitor.visitVarInsn(ALOAD, 1);
methodVisitor.visitInsn(ICONST_0);
methodVisitor.visitMethodInsn(INVOKESTATIC, "org/bouncycastle/math/raw/Nat", "shiftUpBit", "(I[III[II)I", false);
methodVisitor.visitInsn(POP);
methodVisitor.visitIntInsn(BIPUSH, 19);
methodVisitor.visitVarInsn(ALOAD, 0);
methodVisitor.visitVarInsn(ALOAD, 1);
methodVisitor.visitMethodInsn(INVOKESTATIC, "org/bouncycastle/math/raw/Nat256", "mulByWordAddTo", "(I[I[I)I", false);
methodVisitor.visitInsn(ICONST_1);
methodVisitor.visitInsn(ISHL);
methodVisitor.visitVarInsn(ISTORE, 3);
methodVisitor.visitVarInsn(ALOAD, 1);
methodVisitor.visitIntInsn(BIPUSH, 7);
methodVisitor.visitInsn(IALOAD);
methodVisitor.visitVarInsn(ISTORE, 4);
methodVisitor.visitVarInsn(ILOAD, 3);
methodVisitor.visitVarInsn(ILOAD, 4);
methodVisitor.visitIntInsn(BIPUSH, 31);
methodVisitor.visitInsn(IUSHR);
methodVisitor.visitVarInsn(ILOAD, 2);
methodVisitor.visitIntInsn(BIPUSH, 31);
methodVisitor.visitInsn(IUSHR);
methodVisitor.visitInsn(ISUB);
methodVisitor.visitInsn(IADD);
methodVisitor.visitVarInsn(ISTORE, 3);
methodVisitor.visitVarInsn(ILOAD, 4);
methodVisitor.visitLdcInsn(new Integer(2147483647));
methodVisitor.visitInsn(IAND);
methodVisitor.visitVarInsn(ISTORE, 4);
methodVisitor.visitVarInsn(ILOAD, 4);
methodVisitor.visitIntInsn(BIPUSH, 7);
methodVisitor.visitVarInsn(ILOAD, 3);
methodVisitor.visitIntInsn(BIPUSH, 19);
methodVisitor.visitInsn(IMUL);
methodVisitor.visitVarInsn(ALOAD, 1);
methodVisitor.visitMethodInsn(INVOKESTATIC, "org/bouncycastle/math/raw/Nat", "addWordTo", "(II[I)I", false);
methodVisitor.visitInsn(IADD);
methodVisitor.visitVarInsn(ISTORE, 4);
methodVisitor.visitVarInsn(ALOAD, 1);
methodVisitor.visitIntInsn(BIPUSH, 7);
methodVisitor.visitVarInsn(ILOAD, 4);
methodVisitor.visitInsn(IASTORE);
methodVisitor.visitVarInsn(ALOAD, 1);
methodVisitor.visitFieldInsn(GETSTATIC, "org/bouncycastle/math/ec/custom/djb/Curve25519Field", "P", "[I");
methodVisitor.visitMethodInsn(INVOKESTATIC, "org/bouncycastle/math/raw/Nat256", "gte", "([I[I)Z", false);
Label label0 = new Label();
methodVisitor.visitJumpInsn(IFEQ, label0);
methodVisitor.visitVarInsn(ALOAD, 1);
methodVisitor.visitMethodInsn(INVOKESTATIC, "org/bouncycastle/math/ec/custom/djb/Curve25519Field", "subPFrom", "([I)I", false);
methodVisitor.visitInsn(POP);
methodVisitor.visitLabel(label0);
methodVisitor.visitInsn(RETURN);
methodVisitor.visitMaxs(6, 5);
methodVisitor.visitEnd();
}
{
methodVisitor = classWriter.visitMethod(ACC_PUBLIC | ACC_STATIC, "reduce27", "(I[I)V", null, null);
methodVisitor.visitCode();
methodVisitor.visitVarInsn(ALOAD, 1);
methodVisitor.visitIntInsn(BIPUSH, 7);
methodVisitor.visitInsn(IALOAD);
methodVisitor.visitVarInsn(ISTORE, 2);
methodVisitor.visitVarInsn(ILOAD, 0);
methodVisitor.visitInsn(ICONST_1);
methodVisitor.visitInsn(ISHL);
methodVisitor.visitVarInsn(ILOAD, 2);
methodVisitor.visitIntInsn(BIPUSH, 31);
methodVisitor.visitInsn(IUSHR);
methodVisitor.visitInsn(IOR);
methodVisitor.visitVarInsn(ISTORE, 3);
methodVisitor.visitVarInsn(ILOAD, 2);
methodVisitor.visitLdcInsn(new Integer(2147483647));
methodVisitor.visitInsn(IAND);
methodVisitor.visitVarInsn(ISTORE, 2);
methodVisitor.visitVarInsn(ILOAD, 2);
methodVisitor.visitIntInsn(BIPUSH, 7);
methodVisitor.visitVarInsn(ILOAD, 3);
methodVisitor.visitIntInsn(BIPUSH, 19);
methodVisitor.visitInsn(IMUL);
methodVisitor.visitVarInsn(ALOAD, 1);
methodVisitor.visitMethodInsn(INVOKESTATIC, "org/bouncycastle/math/raw/Nat", "addWordTo", "(II[I)I", false);
methodVisitor.visitInsn(IADD);
methodVisitor.visitVarInsn(ISTORE, 2);
methodVisitor.visitVarInsn(ALOAD, 1);
methodVisitor.visitIntInsn(BIPUSH, 7);
methodVisitor.visitVarInsn(ILOAD, 2);
methodVisitor.visitInsn(IASTORE);
methodVisitor.visitVarInsn(ALOAD, 1);
methodVisitor.visitFieldInsn(GETSTATIC, "org/bouncycastle/math/ec/custom/djb/Curve25519Field", "P", "[I");
methodVisitor.visitMethodInsn(INVOKESTATIC, "org/bouncycastle/math/raw/Nat256", "gte", "([I[I)Z", false);
Label label0 = new Label();
methodVisitor.visitJumpInsn(IFEQ, label0);
methodVisitor.visitVarInsn(ALOAD, 1);
methodVisitor.visitMethodInsn(INVOKESTATIC, "org/bouncycastle/math/ec/custom/djb/Curve25519Field", "subPFrom", "([I)I", false);
methodVisitor.visitInsn(POP);
methodVisitor.visitLabel(label0);
methodVisitor.visitInsn(RETURN);
methodVisitor.visitMaxs(4, 4);
methodVisitor.visitEnd();
}
{
methodVisitor = classWriter.visitMethod(ACC_PUBLIC | ACC_STATIC, "square", "([I[I)V", null, null);
methodVisitor.visitCode();
methodVisitor.visitMethodInsn(INVOKESTATIC, "org/bouncycastle/math/raw/Nat256", "createExt", "()[I", false);
methodVisitor.visitVarInsn(ASTORE, 2);
methodVisitor.visitVarInsn(ALOAD, 0);
methodVisitor.visitVarInsn(ALOAD, 2);
methodVisitor.visitMethodInsn(INVOKESTATIC, "org/bouncycastle/math/raw/Nat256", "square", "([I[I)V", false);
methodVisitor.visitVarInsn(ALOAD, 2);
methodVisitor.visitVarInsn(ALOAD, 1);
methodVisitor.visitMethodInsn(INVOKESTATIC, "org/bouncycastle/math/ec/custom/djb/Curve25519Field", "reduce", "([I[I)V", false);
methodVisitor.visitInsn(RETURN);
methodVisitor.visitMaxs(2, 3);
methodVisitor.visitEnd();
}
{
methodVisitor = classWriter.visitMethod(ACC_PUBLIC | ACC_STATIC, "squareN", "([II[I)V", null, null);
methodVisitor.visitCode();
methodVisitor.visitMethodInsn(INVOKESTATIC, "org/bouncycastle/math/raw/Nat256", "createExt", "()[I", false);
methodVisitor.visitVarInsn(ASTORE, 3);
methodVisitor.visitVarInsn(ALOAD, 0);
methodVisitor.visitVarInsn(ALOAD, 3);
methodVisitor.visitMethodInsn(INVOKESTATIC, "org/bouncycastle/math/raw/Nat256", "square", "([I[I)V", false);
methodVisitor.visitVarInsn(ALOAD, 3);
methodVisitor.visitVarInsn(ALOAD, 2);
methodVisitor.visitMethodInsn(INVOKESTATIC, "org/bouncycastle/math/ec/custom/djb/Curve25519Field", "reduce", "([I[I)V", false);
Label label0 = new Label();
methodVisitor.visitLabel(label0);
methodVisitor.visitIincInsn(1, -1);
methodVisitor.visitVarInsn(ILOAD, 1);
Label label1 = new Label();
methodVisitor.visitJumpInsn(IFLE, label1);
methodVisitor.visitVarInsn(ALOAD, 2);
methodVisitor.visitVarInsn(ALOAD, 3);
methodVisitor.visitMethodInsn(INVOKESTATIC, "org/bouncycastle/math/raw/Nat256", "square", "([I[I)V", false);
methodVisitor.visitVarInsn(ALOAD, 3);
methodVisitor.visitVarInsn(ALOAD, 2);
methodVisitor.visitMethodInsn(INVOKESTATIC, "org/bouncycastle/math/ec/custom/djb/Curve25519Field", "reduce", "([I[I)V", false);
methodVisitor.visitJumpInsn(GOTO, label0);
methodVisitor.visitLabel(label1);
methodVisitor.visitInsn(RETURN);
methodVisitor.visitMaxs(2, 4);
methodVisitor.visitEnd();
}
{
methodVisitor = classWriter.visitMethod(ACC_PUBLIC | ACC_STATIC, "subtract", "([I[I[I)V", null, null);
methodVisitor.visitCode();
methodVisitor.visitVarInsn(ALOAD, 0);
methodVisitor.visitVarInsn(ALOAD, 1);
methodVisitor.visitVarInsn(ALOAD, 2);
methodVisitor.visitMethodInsn(INVOKESTATIC, "org/bouncycastle/math/raw/Nat256", "sub", "([I[I[I)I", false);
methodVisitor.visitVarInsn(ISTORE, 3);
methodVisitor.visitVarInsn(ILOAD, 3);
Label label0 = new Label();
methodVisitor.visitJumpInsn(IFEQ, label0);
methodVisitor.visitVarInsn(ALOAD, 2);
methodVisitor.visitMethodInsn(INVOKESTATIC, "org/bouncycastle/math/ec/custom/djb/Curve25519Field", "addPTo", "([I)I", false);
methodVisitor.visitInsn(POP);
methodVisitor.visitLabel(label0);
methodVisitor.visitInsn(RETURN);
methodVisitor.visitMaxs(3, 4);
methodVisitor.visitEnd();
}
{
methodVisitor = classWriter.visitMethod(ACC_PUBLIC | ACC_STATIC, "subtractExt", "([I[I[I)V", null, null);
methodVisitor.visitCode();
methodVisitor.visitIntInsn(BIPUSH, 16);
methodVisitor.visitVarInsn(ALOAD, 0);
methodVisitor.visitVarInsn(ALOAD, 1);
methodVisitor.visitVarInsn(ALOAD, 2);
methodVisitor.visitMethodInsn(INVOKESTATIC, "org/bouncycastle/math/raw/Nat", "sub", "(I[I[I[I)I", false);
methodVisitor.visitVarInsn(ISTORE, 3);
methodVisitor.visitVarInsn(ILOAD, 3);
Label label0 = new Label();
methodVisitor.visitJumpInsn(IFEQ, label0);
methodVisitor.visitVarInsn(ALOAD, 2);
methodVisitor.visitMethodInsn(INVOKESTATIC, "org/bouncycastle/math/ec/custom/djb/Curve25519Field", "addPExtTo", "([I)I", false);
methodVisitor.visitInsn(POP);
methodVisitor.visitLabel(label0);
methodVisitor.visitInsn(RETURN);
methodVisitor.visitMaxs(4, 4);
methodVisitor.visitEnd();
}
{
methodVisitor = classWriter.visitMethod(ACC_PUBLIC | ACC_STATIC, "twice", "([I[I)V", null, null);
methodVisitor.visitCode();
methodVisitor.visitIntInsn(BIPUSH, 8);
methodVisitor.visitVarInsn(ALOAD, 0);
methodVisitor.visitInsn(ICONST_0);
methodVisitor.visitVarInsn(ALOAD, 1);
methodVisitor.visitMethodInsn(INVOKESTATIC, "org/bouncycastle/math/raw/Nat", "shiftUpBit", "(I[II[I)I", false);
methodVisitor.visitInsn(POP);
methodVisitor.visitVarInsn(ALOAD, 1);
methodVisitor.visitFieldInsn(GETSTATIC, "org/bouncycastle/math/ec/custom/djb/Curve25519Field", "P", "[I");
methodVisitor.visitMethodInsn(INVOKESTATIC, "org/bouncycastle/math/raw/Nat256", "gte", "([I[I)Z", false);
Label label0 = new Label();
methodVisitor.visitJumpInsn(IFEQ, label0);
methodVisitor.visitVarInsn(ALOAD, 1);
methodVisitor.visitMethodInsn(INVOKESTATIC, "org/bouncycastle/math/ec/custom/djb/Curve25519Field", "subPFrom", "([I)I", false);
methodVisitor.visitInsn(POP);
methodVisitor.visitLabel(label0);
methodVisitor.visitInsn(RETURN);
methodVisitor.visitMaxs(4, 2);
methodVisitor.visitEnd();
}
{
methodVisitor = classWriter.visitMethod(ACC_PRIVATE | ACC_STATIC, "addPTo", "([I)I", null, null);
methodVisitor.visitCode();
methodVisitor.visitVarInsn(ALOAD, 0);
methodVisitor.visitInsn(ICONST_0);
methodVisitor.visitInsn(IALOAD);
methodVisitor.visitInsn(I2L);
methodVisitor.visitLdcInsn(new Long(4294967295L));
methodVisitor.visitInsn(LAND);
methodVisitor.visitLdcInsn(new Long(19L));
methodVisitor.visitInsn(LSUB);
methodVisitor.visitVarInsn(LSTORE, 1);
methodVisitor.visitVarInsn(ALOAD, 0);
methodVisitor.visitInsn(ICONST_0);
methodVisitor.visitVarInsn(LLOAD, 1);
methodVisitor.visitInsn(L2I);
methodVisitor.visitInsn(IASTORE);
methodVisitor.visitVarInsn(LLOAD, 1);
methodVisitor.visitIntInsn(BIPUSH, 32);
methodVisitor.visitInsn(LSHR);
methodVisitor.visitVarInsn(LSTORE, 1);
methodVisitor.visitVarInsn(LLOAD, 1);
methodVisitor.visitInsn(LCONST_0);
methodVisitor.visitInsn(LCMP);
Label label0 = new Label();
methodVisitor.visitJumpInsn(IFEQ, label0);
methodVisitor.visitIntInsn(BIPUSH, 7);
methodVisitor.visitVarInsn(ALOAD, 0);
methodVisitor.visitInsn(ICONST_1);
methodVisitor.visitMethodInsn(INVOKESTATIC, "org/bouncycastle/math/raw/Nat", "decAt", "(I[II)I", false);
methodVisitor.visitInsn(I2L);
methodVisitor.visitVarInsn(LSTORE, 1);
methodVisitor.visitLabel(label0);
methodVisitor.visitVarInsn(LLOAD, 1);
methodVisitor.visitVarInsn(ALOAD, 0);
methodVisitor.visitIntInsn(BIPUSH, 7);
methodVisitor.visitInsn(IALOAD);
methodVisitor.visitInsn(I2L);
methodVisitor.visitLdcInsn(new Long(4294967295L));
methodVisitor.visitInsn(LAND);
methodVisitor.visitLdcInsn(new Long(2147483648L));
methodVisitor.visitInsn(LADD);
methodVisitor.visitInsn(LADD);
methodVisitor.visitVarInsn(LSTORE, 1);
methodVisitor.visitVarInsn(ALOAD, 0);
methodVisitor.visitIntInsn(BIPUSH, 7);
methodVisitor.visitVarInsn(LLOAD, 1);
methodVisitor.visitInsn(L2I);
methodVisitor.visitInsn(IASTORE);
methodVisitor.visitVarInsn(LLOAD, 1);
methodVisitor.visitIntInsn(BIPUSH, 32);
methodVisitor.visitInsn(LSHR);
methodVisitor.visitVarInsn(LSTORE, 1);
methodVisitor.visitVarInsn(LLOAD, 1);
methodVisitor.visitInsn(L2I);
methodVisitor.visitInsn(IRETURN);
methodVisitor.visitMaxs(6, 3);
methodVisitor.visitEnd();
}
{
methodVisitor = classWriter.visitMethod(ACC_PRIVATE | ACC_STATIC, "addPExtTo", "([I)I", null, null);
methodVisitor.visitCode();
methodVisitor.visitVarInsn(ALOAD, 0);
methodVisitor.visitInsn(ICONST_0);
methodVisitor.visitInsn(IALOAD);
methodVisitor.visitInsn(I2L);
methodVisitor.visitLdcInsn(new Long(4294967295L));
methodVisitor.visitInsn(LAND);
methodVisitor.visitFieldInsn(GETSTATIC, "org/bouncycastle/math/ec/custom/djb/Curve25519Field", "PExt", "[I");
methodVisitor.visitInsn(ICONST_0);
methodVisitor.visitInsn(IALOAD);
methodVisitor.visitInsn(I2L);
methodVisitor.visitLdcInsn(new Long(4294967295L));
methodVisitor.visitInsn(LAND);
methodVisitor.visitInsn(LADD);
methodVisitor.visitVarInsn(LSTORE, 1);
methodVisitor.visitVarInsn(ALOAD, 0);
methodVisitor.visitInsn(ICONST_0);
methodVisitor.visitVarInsn(LLOAD, 1);
methodVisitor.visitInsn(L2I);
methodVisitor.visitInsn(IASTORE);
methodVisitor.visitVarInsn(LLOAD, 1);
methodVisitor.visitIntInsn(BIPUSH, 32);
methodVisitor.visitInsn(LSHR);
methodVisitor.visitVarInsn(LSTORE, 1);
methodVisitor.visitVarInsn(LLOAD, 1);
methodVisitor.visitInsn(LCONST_0);
methodVisitor.visitInsn(LCMP);
Label label0 = new Label();
methodVisitor.visitJumpInsn(IFEQ, label0);
methodVisitor.visitIntInsn(BIPUSH, 8);
methodVisitor.visitVarInsn(ALOAD, 0);
methodVisitor.visitInsn(ICONST_1);
methodVisitor.visitMethodInsn(INVOKESTATIC, "org/bouncycastle/math/raw/Nat", "incAt", "(I[II)I", false);
methodVisitor.visitInsn(I2L);
methodVisitor.visitVarInsn(LSTORE, 1);
methodVisitor.visitLabel(label0);
methodVisitor.visitVarInsn(LLOAD, 1);
methodVisitor.visitVarInsn(ALOAD, 0);
methodVisitor.visitIntInsn(BIPUSH, 8);
methodVisitor.visitInsn(IALOAD);
methodVisitor.visitInsn(I2L);
methodVisitor.visitLdcInsn(new Long(4294967295L));
methodVisitor.visitInsn(LAND);
methodVisitor.visitLdcInsn(new Long(19L));
methodVisitor.visitInsn(LSUB);
methodVisitor.visitInsn(LADD);
methodVisitor.visitVarInsn(LSTORE, 1);
methodVisitor.visitVarInsn(ALOAD, 0);
methodVisitor.visitIntInsn(BIPUSH, 8);
methodVisitor.visitVarInsn(LLOAD, 1);
methodVisitor.visitInsn(L2I);
methodVisitor.visitInsn(IASTORE);
methodVisitor.visitVarInsn(LLOAD, 1);
methodVisitor.visitIntInsn(BIPUSH, 32);
methodVisitor.visitInsn(LSHR);
methodVisitor.visitVarInsn(LSTORE, 1);
methodVisitor.visitVarInsn(LLOAD, 1);
methodVisitor.visitInsn(LCONST_0);
methodVisitor.visitInsn(LCMP);
Label label1 = new Label();
methodVisitor.visitJumpInsn(IFEQ, label1);
methodVisitor.visitIntInsn(BIPUSH, 15);
methodVisitor.visitVarInsn(ALOAD, 0);
methodVisitor.visitIntInsn(BIPUSH, 9);
methodVisitor.visitMethodInsn(INVOKESTATIC, "org/bouncycastle/math/raw/Nat", "decAt", "(I[II)I", false);
methodVisitor.visitInsn(I2L);
methodVisitor.visitVarInsn(LSTORE, 1);
methodVisitor.visitLabel(label1);
methodVisitor.visitVarInsn(LLOAD, 1);
methodVisitor.visitVarInsn(ALOAD, 0);
methodVisitor.visitIntInsn(BIPUSH, 15);
methodVisitor.visitInsn(IALOAD);
methodVisitor.visitInsn(I2L);
methodVisitor.visitLdcInsn(new Long(4294967295L));
methodVisitor.visitInsn(LAND);
methodVisitor.visitFieldInsn(GETSTATIC, "org/bouncycastle/math/ec/custom/djb/Curve25519Field", "PExt", "[I");
methodVisitor.visitIntInsn(BIPUSH, 15);
methodVisitor.visitInsn(IALOAD);
methodVisitor.visitInsn(ICONST_1);
methodVisitor.visitInsn(IADD);
methodVisitor.visitInsn(I2L);
methodVisitor.visitLdcInsn(new Long(4294967295L));
methodVisitor.visitInsn(LAND);
methodVisitor.visitInsn(LADD);
methodVisitor.visitInsn(LADD);
methodVisitor.visitVarInsn(LSTORE, 1);
methodVisitor.visitVarInsn(ALOAD, 0);
methodVisitor.visitIntInsn(BIPUSH, 15);
methodVisitor.visitVarInsn(LLOAD, 1);
methodVisitor.visitInsn(L2I);
methodVisitor.visitInsn(IASTORE);
methodVisitor.visitVarInsn(LLOAD, 1);
methodVisitor.visitIntInsn(BIPUSH, 32);
methodVisitor.visitInsn(LSHR);
methodVisitor.visitVarInsn(LSTORE, 1);
methodVisitor.visitVarInsn(LLOAD, 1);
methodVisitor.visitInsn(L2I);
methodVisitor.visitInsn(IRETURN);
methodVisitor.visitMaxs(8, 3);
methodVisitor.visitEnd();
}
{
methodVisitor = classWriter.visitMethod(ACC_PRIVATE | ACC_STATIC, "subPFrom", "([I)I", null, null);
methodVisitor.visitCode();
methodVisitor.visitVarInsn(ALOAD, 0);
methodVisitor.visitInsn(ICONST_0);
methodVisitor.visitInsn(IALOAD);
methodVisitor.visitInsn(I2L);
methodVisitor.visitLdcInsn(new Long(4294967295L));
methodVisitor.visitInsn(LAND);
methodVisitor.visitLdcInsn(new Long(19L));
methodVisitor.visitInsn(LADD);
methodVisitor.visitVarInsn(LSTORE, 1);
methodVisitor.visitVarInsn(ALOAD, 0);
methodVisitor.visitInsn(ICONST_0);
methodVisitor.visitVarInsn(LLOAD, 1);
methodVisitor.visitInsn(L2I);
methodVisitor.visitInsn(IASTORE);
methodVisitor.visitVarInsn(LLOAD, 1);
methodVisitor.visitIntInsn(BIPUSH, 32);
methodVisitor.visitInsn(LSHR);
methodVisitor.visitVarInsn(LSTORE, 1);
methodVisitor.visitVarInsn(LLOAD, 1);
methodVisitor.visitInsn(LCONST_0);
methodVisitor.visitInsn(LCMP);
Label label0 = new Label();
methodVisitor.visitJumpInsn(IFEQ, label0);
methodVisitor.visitIntInsn(BIPUSH, 7);
methodVisitor.visitVarInsn(ALOAD, 0);
methodVisitor.visitInsn(ICONST_1);
methodVisitor.visitMethodInsn(INVOKESTATIC, "org/bouncycastle/math/raw/Nat", "incAt", "(I[II)I", false);
methodVisitor.visitInsn(I2L);
methodVisitor.visitVarInsn(LSTORE, 1);
methodVisitor.visitLabel(label0);
methodVisitor.visitVarInsn(LLOAD, 1);
methodVisitor.visitVarInsn(ALOAD, 0);
methodVisitor.visitIntInsn(BIPUSH, 7);
methodVisitor.visitInsn(IALOAD);
methodVisitor.visitInsn(I2L);
methodVisitor.visitLdcInsn(new Long(4294967295L));
methodVisitor.visitInsn(LAND);
methodVisitor.visitLdcInsn(new Long(2147483648L));
methodVisitor.visitInsn(LSUB);
methodVisitor.visitInsn(LADD);
methodVisitor.visitVarInsn(LSTORE, 1);
methodVisitor.visitVarInsn(ALOAD, 0);
methodVisitor.visitIntInsn(BIPUSH, 7);
methodVisitor.visitVarInsn(LLOAD, 1);
methodVisitor.visitInsn(L2I);
methodVisitor.visitInsn(IASTORE);
methodVisitor.visitVarInsn(LLOAD, 1);
methodVisitor.visitIntInsn(BIPUSH, 32);
methodVisitor.visitInsn(LSHR);
methodVisitor.visitVarInsn(LSTORE, 1);
methodVisitor.visitVarInsn(LLOAD, 1);
methodVisitor.visitInsn(L2I);
methodVisitor.visitInsn(IRETURN);
methodVisitor.visitMaxs(6, 3);
methodVisitor.visitEnd();
}
{
methodVisitor = classWriter.visitMethod(ACC_PRIVATE | ACC_STATIC, "subPExtFrom", "([I)I", null, null);
methodVisitor.visitCode();
methodVisitor.visitVarInsn(ALOAD, 0);
methodVisitor.visitInsn(ICONST_0);
methodVisitor.visitInsn(IALOAD);
methodVisitor.visitInsn(I2L);
methodVisitor.visitLdcInsn(new Long(4294967295L));
methodVisitor.visitInsn(LAND);
methodVisitor.visitFieldInsn(GETSTATIC, "org/bouncycastle/math/ec/custom/djb/Curve25519Field", "PExt", "[I");
methodVisitor.visitInsn(ICONST_0);
methodVisitor.visitInsn(IALOAD);
methodVisitor.visitInsn(I2L);
methodVisitor.visitLdcInsn(new Long(4294967295L));
methodVisitor.visitInsn(LAND);
methodVisitor.visitInsn(LSUB);
methodVisitor.visitVarInsn(LSTORE, 1);
methodVisitor.visitVarInsn(ALOAD, 0);
methodVisitor.visitInsn(ICONST_0);
methodVisitor.visitVarInsn(LLOAD, 1);
methodVisitor.visitInsn(L2I);
methodVisitor.visitInsn(IASTORE);
methodVisitor.visitVarInsn(LLOAD, 1);
methodVisitor.visitIntInsn(BIPUSH, 32);
methodVisitor.visitInsn(LSHR);
methodVisitor.visitVarInsn(LSTORE, 1);
methodVisitor.visitVarInsn(LLOAD, 1);
methodVisitor.visitInsn(LCONST_0);
methodVisitor.visitInsn(LCMP);
Label label0 = new Label();
methodVisitor.visitJumpInsn(IFEQ, label0);
methodVisitor.visitIntInsn(BIPUSH, 8);
methodVisitor.visitVarInsn(ALOAD, 0);
methodVisitor.visitInsn(ICONST_1);
methodVisitor.visitMethodInsn(INVOKESTATIC, "org/bouncycastle/math/raw/Nat", "decAt", "(I[II)I", false);
methodVisitor.visitInsn(I2L);
methodVisitor.visitVarInsn(LSTORE, 1);
methodVisitor.visitLabel(label0);
methodVisitor.visitVarInsn(LLOAD, 1);
methodVisitor.visitVarInsn(ALOAD, 0);
methodVisitor.visitIntInsn(BIPUSH, 8);
methodVisitor.visitInsn(IALOAD);
methodVisitor.visitInsn(I2L);
methodVisitor.visitLdcInsn(new Long(4294967295L));
methodVisitor.visitInsn(LAND);
methodVisitor.visitLdcInsn(new Long(19L));
methodVisitor.visitInsn(LADD);
methodVisitor.visitInsn(LADD);
methodVisitor.visitVarInsn(LSTORE, 1);
methodVisitor.visitVarInsn(ALOAD, 0);
methodVisitor.visitIntInsn(BIPUSH, 8);
methodVisitor.visitVarInsn(LLOAD, 1);
methodVisitor.visitInsn(L2I);
methodVisitor.visitInsn(IASTORE);
methodVisitor.visitVarInsn(LLOAD, 1);
methodVisitor.visitIntInsn(BIPUSH, 32);
methodVisitor.visitInsn(LSHR);
methodVisitor.visitVarInsn(LSTORE, 1);
methodVisitor.visitVarInsn(LLOAD, 1);
methodVisitor.visitInsn(LCONST_0);
methodVisitor.visitInsn(LCMP);
Label label1 = new Label();
methodVisitor.visitJumpInsn(IFEQ, label1);
methodVisitor.visitIntInsn(BIPUSH, 15);
methodVisitor.visitVarInsn(ALOAD, 0);
methodVisitor.visitIntInsn(BIPUSH, 9);
methodVisitor.visitMethodInsn(INVOKESTATIC, "org/bouncycastle/math/raw/Nat", "incAt", "(I[II)I", false);
methodVisitor.visitInsn(I2L);
methodVisitor.visitVarInsn(LSTORE, 1);
methodVisitor.visitLabel(label1);
methodVisitor.visitVarInsn(LLOAD, 1);
methodVisitor.visitVarInsn(ALOAD, 0);
methodVisitor.visitIntInsn(BIPUSH, 15);
methodVisitor.visitInsn(IALOAD);
methodVisitor.visitInsn(I2L);
methodVisitor.visitLdcInsn(new Long(4294967295L));
methodVisitor.visitInsn(LAND);
methodVisitor.visitFieldInsn(GETSTATIC, "org/bouncycastle/math/ec/custom/djb/Curve25519Field", "PExt", "[I");
methodVisitor.visitIntInsn(BIPUSH, 15);
methodVisitor.visitInsn(IALOAD);
methodVisitor.visitInsn(ICONST_1);
methodVisitor.visitInsn(IADD);
methodVisitor.visitInsn(I2L);
methodVisitor.visitLdcInsn(new Long(4294967295L));
methodVisitor.visitInsn(LAND);
methodVisitor.visitInsn(LSUB);
methodVisitor.visitInsn(LADD);
methodVisitor.visitVarInsn(LSTORE, 1);
methodVisitor.visitVarInsn(ALOAD, 0);
methodVisitor.visitIntInsn(BIPUSH, 15);
methodVisitor.visitVarInsn(LLOAD, 1);
methodVisitor.visitInsn(L2I);
methodVisitor.visitInsn(IASTORE);
methodVisitor.visitVarInsn(LLOAD, 1);
methodVisitor.visitIntInsn(BIPUSH, 32);
methodVisitor.visitInsn(LSHR);
methodVisitor.visitVarInsn(LSTORE, 1);
methodVisitor.visitVarInsn(LLOAD, 1);
methodVisitor.visitInsn(L2I);
methodVisitor.visitInsn(IRETURN);
methodVisitor.visitMaxs(8, 3);
methodVisitor.visitEnd();
}
{
methodVisitor = classWriter.visitMethod(ACC_STATIC, "<clinit>", "()V", null, null);
methodVisitor.visitCode();
methodVisitor.visitIntInsn(BIPUSH, 8);
methodVisitor.visitIntInsn(NEWARRAY, T_INT);
methodVisitor.visitInsn(DUP);
methodVisitor.visitInsn(ICONST_0);
methodVisitor.visitIntInsn(BIPUSH, -19);
methodVisitor.visitInsn(IASTORE);
methodVisitor.visitInsn(DUP);
methodVisitor.visitInsn(ICONST_1);
methodVisitor.visitInsn(ICONST_M1);
methodVisitor.visitInsn(IASTORE);
methodVisitor.visitInsn(DUP);
methodVisitor.visitInsn(ICONST_2);
methodVisitor.visitInsn(ICONST_M1);
methodVisitor.visitInsn(IASTORE);
methodVisitor.visitInsn(DUP);
methodVisitor.visitInsn(ICONST_3);
methodVisitor.visitInsn(ICONST_M1);
methodVisitor.visitInsn(IASTORE);
methodVisitor.visitInsn(DUP);
methodVisitor.visitInsn(ICONST_4);
methodVisitor.visitInsn(ICONST_M1);
methodVisitor.visitInsn(IASTORE);
methodVisitor.visitInsn(DUP);
methodVisitor.visitInsn(ICONST_5);
methodVisitor.visitInsn(ICONST_M1);
methodVisitor.visitInsn(IASTORE);
methodVisitor.visitInsn(DUP);
methodVisitor.visitIntInsn(BIPUSH, 6);
methodVisitor.visitInsn(ICONST_M1);
methodVisitor.visitInsn(IASTORE);
methodVisitor.visitInsn(DUP);
methodVisitor.visitIntInsn(BIPUSH, 7);
methodVisitor.visitLdcInsn(new Integer(2147483647));
methodVisitor.visitInsn(IASTORE);
methodVisitor.visitFieldInsn(PUTSTATIC, "org/bouncycastle/math/ec/custom/djb/Curve25519Field", "P", "[I");
methodVisitor.visitIntInsn(BIPUSH, 16);
methodVisitor.visitIntInsn(NEWARRAY, T_INT);
methodVisitor.visitInsn(DUP);
methodVisitor.visitInsn(ICONST_0);
methodVisitor.visitIntInsn(SIPUSH, 361);
methodVisitor.visitInsn(IASTORE);
methodVisitor.visitInsn(DUP);
methodVisitor.visitInsn(ICONST_1);
methodVisitor.visitInsn(ICONST_0);
methodVisitor.visitInsn(IASTORE);
methodVisitor.visitInsn(DUP);
methodVisitor.visitInsn(ICONST_2);
methodVisitor.visitInsn(ICONST_0);
methodVisitor.visitInsn(IASTORE);
methodVisitor.visitInsn(DUP);
methodVisitor.visitInsn(ICONST_3);
methodVisitor.visitInsn(ICONST_0);
methodVisitor.visitInsn(IASTORE);
methodVisitor.visitInsn(DUP);
methodVisitor.visitInsn(ICONST_4);
methodVisitor.visitInsn(ICONST_0);
methodVisitor.visitInsn(IASTORE);
methodVisitor.visitInsn(DUP);
methodVisitor.visitInsn(ICONST_5);
methodVisitor.visitInsn(ICONST_0);
methodVisitor.visitInsn(IASTORE);
methodVisitor.visitInsn(DUP);
methodVisitor.visitIntInsn(BIPUSH, 6);
methodVisitor.visitInsn(ICONST_0);
methodVisitor.visitInsn(IASTORE);
methodVisitor.visitInsn(DUP);
methodVisitor.visitIntInsn(BIPUSH, 7);
methodVisitor.visitInsn(ICONST_0);
methodVisitor.visitInsn(IASTORE);
methodVisitor.visitInsn(DUP);
methodVisitor.visitIntInsn(BIPUSH, 8);
methodVisitor.visitIntInsn(BIPUSH, -19);
methodVisitor.visitInsn(IASTORE);
methodVisitor.visitInsn(DUP);
methodVisitor.visitIntInsn(BIPUSH, 9);
methodVisitor.visitInsn(ICONST_M1);
methodVisitor.visitInsn(IASTORE);
methodVisitor.visitInsn(DUP);
methodVisitor.visitIntInsn(BIPUSH, 10);
methodVisitor.visitInsn(ICONST_M1);
methodVisitor.visitInsn(IASTORE);
methodVisitor.visitInsn(DUP);
methodVisitor.visitIntInsn(BIPUSH, 11);
methodVisitor.visitInsn(ICONST_M1);
methodVisitor.visitInsn(IASTORE);
methodVisitor.visitInsn(DUP);
methodVisitor.visitIntInsn(BIPUSH, 12);
methodVisitor.visitInsn(ICONST_M1);
methodVisitor.visitInsn(IASTORE);
methodVisitor.visitInsn(DUP);
methodVisitor.visitIntInsn(BIPUSH, 13);
methodVisitor.visitInsn(ICONST_M1);
methodVisitor.visitInsn(IASTORE);
methodVisitor.visitInsn(DUP);
methodVisitor.visitIntInsn(BIPUSH, 14);
methodVisitor.visitInsn(ICONST_M1);
methodVisitor.visitInsn(IASTORE);
methodVisitor.visitInsn(DUP);
methodVisitor.visitIntInsn(BIPUSH, 15);
methodVisitor.visitLdcInsn(new Integer(1073741823));
methodVisitor.visitInsn(IASTORE);
methodVisitor.visitFieldInsn(PUTSTATIC, "org/bouncycastle/math/ec/custom/djb/Curve25519Field", "PExt", "[I");
methodVisitor.visitInsn(RETURN);
methodVisitor.visitMaxs(4, 0);
methodVisitor.visitEnd();
}
classWriter.visitEnd();

return classWriter.toByteArray();
}
}
