package asm.org.bouncycastle.crypto.engines;
import org.objectweb.asm.AnnotationVisitor;
import org.objectweb.asm.Attribute;
import org.objectweb.asm.ClassReader;
import org.objectweb.asm.ClassWriter;
import org.objectweb.asm.ConstantDynamic;
import org.objectweb.asm.FieldVisitor;
import org.objectweb.asm.Handle;
import org.objectweb.asm.Label;
import org.objectweb.asm.MethodVisitor;
import org.objectweb.asm.Opcodes;
import org.objectweb.asm.RecordComponentVisitor;
import org.objectweb.asm.Type;
import org.objectweb.asm.TypePath;
public class ChaChaEngineDump implements Opcodes {

public static byte[] dump () throws Exception {

ClassWriter classWriter = new ClassWriter(0);
FieldVisitor fieldVisitor;
RecordComponentVisitor recordComponentVisitor;
MethodVisitor methodVisitor;
AnnotationVisitor annotationVisitor0;

classWriter.visit(V1_5, ACC_PUBLIC | ACC_SUPER, "org/bouncycastle/crypto/engines/ChaChaEngine", null, "org/bouncycastle/crypto/engines/Salsa20Engine", null);

{
methodVisitor = classWriter.visitMethod(ACC_PUBLIC, "<init>", "()V", null, null);
methodVisitor.visitCode();
methodVisitor.visitVarInsn(ALOAD, 0);
methodVisitor.visitMethodInsn(INVOKESPECIAL, "org/bouncycastle/crypto/engines/Salsa20Engine", "<init>", "()V", false);
methodVisitor.visitInsn(RETURN);
methodVisitor.visitMaxs(1, 1);
methodVisitor.visitEnd();
}
{
methodVisitor = classWriter.visitMethod(ACC_PUBLIC, "<init>", "(I)V", null, null);
methodVisitor.visitCode();
methodVisitor.visitVarInsn(ALOAD, 0);
methodVisitor.visitVarInsn(ILOAD, 1);
methodVisitor.visitMethodInsn(INVOKESPECIAL, "org/bouncycastle/crypto/engines/Salsa20Engine", "<init>", "(I)V", false);
methodVisitor.visitInsn(RETURN);
methodVisitor.visitMaxs(2, 2);
methodVisitor.visitEnd();
}
{
methodVisitor = classWriter.visitMethod(ACC_PUBLIC, "getAlgorithmName", "()Ljava/lang/String;", null, null);
methodVisitor.visitCode();
methodVisitor.visitTypeInsn(NEW, "java/lang/StringBuilder");
methodVisitor.visitInsn(DUP);
methodVisitor.visitMethodInsn(INVOKESPECIAL, "java/lang/StringBuilder", "<init>", "()V", false);
methodVisitor.visitLdcInsn("ChaCha");
methodVisitor.visitMethodInsn(INVOKEVIRTUAL, "java/lang/StringBuilder", "append", "(Ljava/lang/String;)Ljava/lang/StringBuilder;", false);
methodVisitor.visitVarInsn(ALOAD, 0);
methodVisitor.visitFieldInsn(GETFIELD, "org/bouncycastle/crypto/engines/ChaChaEngine", "rounds", "I");
methodVisitor.visitMethodInsn(INVOKEVIRTUAL, "java/lang/StringBuilder", "append", "(I)Ljava/lang/StringBuilder;", false);
methodVisitor.visitMethodInsn(INVOKEVIRTUAL, "java/lang/StringBuilder", "toString", "()Ljava/lang/String;", false);
methodVisitor.visitInsn(ARETURN);
methodVisitor.visitMaxs(2, 1);
methodVisitor.visitEnd();
}
{
methodVisitor = classWriter.visitMethod(ACC_PROTECTED, "advanceCounter", "(J)V", null, null);
methodVisitor.visitCode();
methodVisitor.visitVarInsn(LLOAD, 1);
methodVisitor.visitIntInsn(BIPUSH, 32);
methodVisitor.visitInsn(LUSHR);
methodVisitor.visitInsn(L2I);
methodVisitor.visitVarInsn(ISTORE, 3);
methodVisitor.visitVarInsn(LLOAD, 1);
methodVisitor.visitInsn(L2I);
methodVisitor.visitVarInsn(ISTORE, 4);
methodVisitor.visitVarInsn(ILOAD, 3);
Label label0 = new Label();
methodVisitor.visitJumpInsn(IFLE, label0);
methodVisitor.visitVarInsn(ALOAD, 0);
methodVisitor.visitFieldInsn(GETFIELD, "org/bouncycastle/crypto/engines/ChaChaEngine", "engineState", "[I");
methodVisitor.visitIntInsn(BIPUSH, 13);
methodVisitor.visitInsn(DUP2);
methodVisitor.visitInsn(IALOAD);
methodVisitor.visitVarInsn(ILOAD, 3);
methodVisitor.visitInsn(IADD);
methodVisitor.visitInsn(IASTORE);
methodVisitor.visitLabel(label0);
methodVisitor.visitVarInsn(ALOAD, 0);
methodVisitor.visitFieldInsn(GETFIELD, "org/bouncycastle/crypto/engines/ChaChaEngine", "engineState", "[I");
methodVisitor.visitIntInsn(BIPUSH, 12);
methodVisitor.visitInsn(IALOAD);
methodVisitor.visitVarInsn(ISTORE, 5);
methodVisitor.visitVarInsn(ALOAD, 0);
methodVisitor.visitFieldInsn(GETFIELD, "org/bouncycastle/crypto/engines/ChaChaEngine", "engineState", "[I");
methodVisitor.visitIntInsn(BIPUSH, 12);
methodVisitor.visitInsn(DUP2);
methodVisitor.visitInsn(IALOAD);
methodVisitor.visitVarInsn(ILOAD, 4);
methodVisitor.visitInsn(IADD);
methodVisitor.visitInsn(IASTORE);
methodVisitor.visitVarInsn(ILOAD, 5);
Label label1 = new Label();
methodVisitor.visitJumpInsn(IFEQ, label1);
methodVisitor.visitVarInsn(ALOAD, 0);
methodVisitor.visitFieldInsn(GETFIELD, "org/bouncycastle/crypto/engines/ChaChaEngine", "engineState", "[I");
methodVisitor.visitIntInsn(BIPUSH, 12);
methodVisitor.visitInsn(IALOAD);
methodVisitor.visitVarInsn(ILOAD, 5);
methodVisitor.visitJumpInsn(IF_ICMPGE, label1);
methodVisitor.visitVarInsn(ALOAD, 0);
methodVisitor.visitFieldInsn(GETFIELD, "org/bouncycastle/crypto/engines/ChaChaEngine", "engineState", "[I");
methodVisitor.visitIntInsn(BIPUSH, 13);
methodVisitor.visitInsn(DUP2);
methodVisitor.visitInsn(IALOAD);
methodVisitor.visitInsn(ICONST_1);
methodVisitor.visitInsn(IADD);
methodVisitor.visitInsn(IASTORE);
methodVisitor.visitLabel(label1);
methodVisitor.visitInsn(RETURN);
methodVisitor.visitMaxs(4, 6);
methodVisitor.visitEnd();
}
{
methodVisitor = classWriter.visitMethod(ACC_PROTECTED, "advanceCounter", "()V", null, null);
methodVisitor.visitCode();
methodVisitor.visitVarInsn(ALOAD, 0);
methodVisitor.visitFieldInsn(GETFIELD, "org/bouncycastle/crypto/engines/ChaChaEngine", "engineState", "[I");
methodVisitor.visitIntInsn(BIPUSH, 12);
methodVisitor.visitInsn(DUP2);
methodVisitor.visitInsn(IALOAD);
methodVisitor.visitInsn(ICONST_1);
methodVisitor.visitInsn(IADD);
methodVisitor.visitInsn(DUP_X2);
methodVisitor.visitInsn(IASTORE);
Label label0 = new Label();
methodVisitor.visitJumpInsn(IFNE, label0);
methodVisitor.visitVarInsn(ALOAD, 0);
methodVisitor.visitFieldInsn(GETFIELD, "org/bouncycastle/crypto/engines/ChaChaEngine", "engineState", "[I");
methodVisitor.visitIntInsn(BIPUSH, 13);
methodVisitor.visitInsn(DUP2);
methodVisitor.visitInsn(IALOAD);
methodVisitor.visitInsn(ICONST_1);
methodVisitor.visitInsn(IADD);
methodVisitor.visitInsn(IASTORE);
methodVisitor.visitLabel(label0);
methodVisitor.visitInsn(RETURN);
methodVisitor.visitMaxs(4, 1);
methodVisitor.visitEnd();
}
{
methodVisitor = classWriter.visitMethod(ACC_PROTECTED, "retreatCounter", "(J)V", null, null);
methodVisitor.visitCode();
methodVisitor.visitVarInsn(LLOAD, 1);
methodVisitor.visitIntInsn(BIPUSH, 32);
methodVisitor.visitInsn(LUSHR);
methodVisitor.visitInsn(L2I);
methodVisitor.visitVarInsn(ISTORE, 3);
methodVisitor.visitVarInsn(LLOAD, 1);
methodVisitor.visitInsn(L2I);
methodVisitor.visitVarInsn(ISTORE, 4);
methodVisitor.visitVarInsn(ILOAD, 3);
Label label0 = new Label();
methodVisitor.visitJumpInsn(IFEQ, label0);
methodVisitor.visitVarInsn(ALOAD, 0);
methodVisitor.visitFieldInsn(GETFIELD, "org/bouncycastle/crypto/engines/ChaChaEngine", "engineState", "[I");
methodVisitor.visitIntInsn(BIPUSH, 13);
methodVisitor.visitInsn(IALOAD);
methodVisitor.visitInsn(I2L);
methodVisitor.visitLdcInsn(new Long(4294967295L));
methodVisitor.visitInsn(LAND);
methodVisitor.visitVarInsn(ILOAD, 3);
methodVisitor.visitInsn(I2L);
methodVisitor.visitLdcInsn(new Long(4294967295L));
methodVisitor.visitInsn(LAND);
methodVisitor.visitInsn(LCMP);
Label label1 = new Label();
methodVisitor.visitJumpInsn(IFLT, label1);
methodVisitor.visitVarInsn(ALOAD, 0);
methodVisitor.visitFieldInsn(GETFIELD, "org/bouncycastle/crypto/engines/ChaChaEngine", "engineState", "[I");
methodVisitor.visitIntInsn(BIPUSH, 13);
methodVisitor.visitInsn(DUP2);
methodVisitor.visitInsn(IALOAD);
methodVisitor.visitVarInsn(ILOAD, 3);
methodVisitor.visitInsn(ISUB);
methodVisitor.visitInsn(IASTORE);
methodVisitor.visitJumpInsn(GOTO, label0);
methodVisitor.visitLabel(label1);
methodVisitor.visitTypeInsn(NEW, "java/lang/IllegalStateException");
methodVisitor.visitInsn(DUP);
methodVisitor.visitLdcInsn("attempt to reduce counter past zero.");
methodVisitor.visitMethodInsn(INVOKESPECIAL, "java/lang/IllegalStateException", "<init>", "(Ljava/lang/String;)V", false);
methodVisitor.visitInsn(ATHROW);
methodVisitor.visitLabel(label0);
methodVisitor.visitVarInsn(ALOAD, 0);
methodVisitor.visitFieldInsn(GETFIELD, "org/bouncycastle/crypto/engines/ChaChaEngine", "engineState", "[I");
methodVisitor.visitIntInsn(BIPUSH, 12);
methodVisitor.visitInsn(IALOAD);
methodVisitor.visitInsn(I2L);
methodVisitor.visitLdcInsn(new Long(4294967295L));
methodVisitor.visitInsn(LAND);
methodVisitor.visitVarInsn(ILOAD, 4);
methodVisitor.visitInsn(I2L);
methodVisitor.visitLdcInsn(new Long(4294967295L));
methodVisitor.visitInsn(LAND);
methodVisitor.visitInsn(LCMP);
Label label2 = new Label();
methodVisitor.visitJumpInsn(IFLT, label2);
methodVisitor.visitVarInsn(ALOAD, 0);
methodVisitor.visitFieldInsn(GETFIELD, "org/bouncycastle/crypto/engines/ChaChaEngine", "engineState", "[I");
methodVisitor.visitIntInsn(BIPUSH, 12);
methodVisitor.visitInsn(DUP2);
methodVisitor.visitInsn(IALOAD);
methodVisitor.visitVarInsn(ILOAD, 4);
methodVisitor.visitInsn(ISUB);
methodVisitor.visitInsn(IASTORE);
Label label3 = new Label();
methodVisitor.visitJumpInsn(GOTO, label3);
methodVisitor.visitLabel(label2);
methodVisitor.visitVarInsn(ALOAD, 0);
methodVisitor.visitFieldInsn(GETFIELD, "org/bouncycastle/crypto/engines/ChaChaEngine", "engineState", "[I");
methodVisitor.visitIntInsn(BIPUSH, 13);
methodVisitor.visitInsn(IALOAD);
Label label4 = new Label();
methodVisitor.visitJumpInsn(IFEQ, label4);
methodVisitor.visitVarInsn(ALOAD, 0);
methodVisitor.visitFieldInsn(GETFIELD, "org/bouncycastle/crypto/engines/ChaChaEngine", "engineState", "[I");
methodVisitor.visitIntInsn(BIPUSH, 13);
methodVisitor.visitInsn(DUP2);
methodVisitor.visitInsn(IALOAD);
methodVisitor.visitInsn(ICONST_1);
methodVisitor.visitInsn(ISUB);
methodVisitor.visitInsn(IASTORE);
methodVisitor.visitVarInsn(ALOAD, 0);
methodVisitor.visitFieldInsn(GETFIELD, "org/bouncycastle/crypto/engines/ChaChaEngine", "engineState", "[I");
methodVisitor.visitIntInsn(BIPUSH, 12);
methodVisitor.visitInsn(DUP2);
methodVisitor.visitInsn(IALOAD);
methodVisitor.visitVarInsn(ILOAD, 4);
methodVisitor.visitInsn(ISUB);
methodVisitor.visitInsn(IASTORE);
methodVisitor.visitJumpInsn(GOTO, label3);
methodVisitor.visitLabel(label4);
methodVisitor.visitTypeInsn(NEW, "java/lang/IllegalStateException");
methodVisitor.visitInsn(DUP);
methodVisitor.visitLdcInsn("attempt to reduce counter past zero.");
methodVisitor.visitMethodInsn(INVOKESPECIAL, "java/lang/IllegalStateException", "<init>", "(Ljava/lang/String;)V", false);
methodVisitor.visitInsn(ATHROW);
methodVisitor.visitLabel(label3);
methodVisitor.visitInsn(RETURN);
methodVisitor.visitMaxs(6, 5);
methodVisitor.visitEnd();
}
{
methodVisitor = classWriter.visitMethod(ACC_PROTECTED, "retreatCounter", "()V", null, null);
methodVisitor.visitCode();
methodVisitor.visitVarInsn(ALOAD, 0);
methodVisitor.visitFieldInsn(GETFIELD, "org/bouncycastle/crypto/engines/ChaChaEngine", "engineState", "[I");
methodVisitor.visitIntInsn(BIPUSH, 12);
methodVisitor.visitInsn(IALOAD);
Label label0 = new Label();
methodVisitor.visitJumpInsn(IFNE, label0);
methodVisitor.visitVarInsn(ALOAD, 0);
methodVisitor.visitFieldInsn(GETFIELD, "org/bouncycastle/crypto/engines/ChaChaEngine", "engineState", "[I");
methodVisitor.visitIntInsn(BIPUSH, 13);
methodVisitor.visitInsn(IALOAD);
methodVisitor.visitJumpInsn(IFNE, label0);
methodVisitor.visitTypeInsn(NEW, "java/lang/IllegalStateException");
methodVisitor.visitInsn(DUP);
methodVisitor.visitLdcInsn("attempt to reduce counter past zero.");
methodVisitor.visitMethodInsn(INVOKESPECIAL, "java/lang/IllegalStateException", "<init>", "(Ljava/lang/String;)V", false);
methodVisitor.visitInsn(ATHROW);
methodVisitor.visitLabel(label0);
methodVisitor.visitVarInsn(ALOAD, 0);
methodVisitor.visitFieldInsn(GETFIELD, "org/bouncycastle/crypto/engines/ChaChaEngine", "engineState", "[I");
methodVisitor.visitIntInsn(BIPUSH, 12);
methodVisitor.visitInsn(DUP2);
methodVisitor.visitInsn(IALOAD);
methodVisitor.visitInsn(ICONST_1);
methodVisitor.visitInsn(ISUB);
methodVisitor.visitInsn(DUP_X2);
methodVisitor.visitInsn(IASTORE);
methodVisitor.visitInsn(ICONST_M1);
Label label1 = new Label();
methodVisitor.visitJumpInsn(IF_ICMPNE, label1);
methodVisitor.visitVarInsn(ALOAD, 0);
methodVisitor.visitFieldInsn(GETFIELD, "org/bouncycastle/crypto/engines/ChaChaEngine", "engineState", "[I");
methodVisitor.visitIntInsn(BIPUSH, 13);
methodVisitor.visitInsn(DUP2);
methodVisitor.visitInsn(IALOAD);
methodVisitor.visitInsn(ICONST_1);
methodVisitor.visitInsn(ISUB);
methodVisitor.visitInsn(IASTORE);
methodVisitor.visitLabel(label1);
methodVisitor.visitInsn(RETURN);
methodVisitor.visitMaxs(4, 1);
methodVisitor.visitEnd();
}
{
methodVisitor = classWriter.visitMethod(ACC_PROTECTED, "getCounter", "()J", null, null);
methodVisitor.visitCode();
methodVisitor.visitVarInsn(ALOAD, 0);
methodVisitor.visitFieldInsn(GETFIELD, "org/bouncycastle/crypto/engines/ChaChaEngine", "engineState", "[I");
methodVisitor.visitIntInsn(BIPUSH, 13);
methodVisitor.visitInsn(IALOAD);
methodVisitor.visitInsn(I2L);
methodVisitor.visitIntInsn(BIPUSH, 32);
methodVisitor.visitInsn(LSHL);
methodVisitor.visitVarInsn(ALOAD, 0);
methodVisitor.visitFieldInsn(GETFIELD, "org/bouncycastle/crypto/engines/ChaChaEngine", "engineState", "[I");
methodVisitor.visitIntInsn(BIPUSH, 12);
methodVisitor.visitInsn(IALOAD);
methodVisitor.visitInsn(I2L);
methodVisitor.visitLdcInsn(new Long(4294967295L));
methodVisitor.visitInsn(LAND);
methodVisitor.visitInsn(LOR);
methodVisitor.visitInsn(LRETURN);
methodVisitor.visitMaxs(6, 1);
methodVisitor.visitEnd();
}
{
methodVisitor = classWriter.visitMethod(ACC_PROTECTED, "resetCounter", "()V", null, null);
methodVisitor.visitCode();
methodVisitor.visitVarInsn(ALOAD, 0);
methodVisitor.visitFieldInsn(GETFIELD, "org/bouncycastle/crypto/engines/ChaChaEngine", "engineState", "[I");
methodVisitor.visitIntInsn(BIPUSH, 12);
methodVisitor.visitVarInsn(ALOAD, 0);
methodVisitor.visitFieldInsn(GETFIELD, "org/bouncycastle/crypto/engines/ChaChaEngine", "engineState", "[I");
methodVisitor.visitIntInsn(BIPUSH, 13);
methodVisitor.visitInsn(ICONST_0);
methodVisitor.visitInsn(DUP_X2);
methodVisitor.visitInsn(IASTORE);
methodVisitor.visitInsn(IASTORE);
methodVisitor.visitInsn(RETURN);
methodVisitor.visitMaxs(6, 1);
methodVisitor.visitEnd();
}
{
methodVisitor = classWriter.visitMethod(ACC_PROTECTED, "setKey", "([B[B)V", null, null);
methodVisitor.visitCode();
methodVisitor.visitVarInsn(ALOAD, 1);
Label label0 = new Label();
methodVisitor.visitJumpInsn(IFNULL, label0);
methodVisitor.visitVarInsn(ALOAD, 1);
methodVisitor.visitInsn(ARRAYLENGTH);
methodVisitor.visitIntInsn(BIPUSH, 16);
Label label1 = new Label();
methodVisitor.visitJumpInsn(IF_ICMPEQ, label1);
methodVisitor.visitVarInsn(ALOAD, 1);
methodVisitor.visitInsn(ARRAYLENGTH);
methodVisitor.visitIntInsn(BIPUSH, 32);
methodVisitor.visitJumpInsn(IF_ICMPEQ, label1);
methodVisitor.visitTypeInsn(NEW, "java/lang/IllegalArgumentException");
methodVisitor.visitInsn(DUP);
methodVisitor.visitTypeInsn(NEW, "java/lang/StringBuilder");
methodVisitor.visitInsn(DUP);
methodVisitor.visitMethodInsn(INVOKESPECIAL, "java/lang/StringBuilder", "<init>", "()V", false);
methodVisitor.visitVarInsn(ALOAD, 0);
methodVisitor.visitMethodInsn(INVOKEVIRTUAL, "org/bouncycastle/crypto/engines/ChaChaEngine", "getAlgorithmName", "()Ljava/lang/String;", false);
methodVisitor.visitMethodInsn(INVOKEVIRTUAL, "java/lang/StringBuilder", "append", "(Ljava/lang/String;)Ljava/lang/StringBuilder;", false);
methodVisitor.visitLdcInsn(" requires 128 bit or 256 bit key");
methodVisitor.visitMethodInsn(INVOKEVIRTUAL, "java/lang/StringBuilder", "append", "(Ljava/lang/String;)Ljava/lang/StringBuilder;", false);
methodVisitor.visitMethodInsn(INVOKEVIRTUAL, "java/lang/StringBuilder", "toString", "()Ljava/lang/String;", false);
methodVisitor.visitMethodInsn(INVOKESPECIAL, "java/lang/IllegalArgumentException", "<init>", "(Ljava/lang/String;)V", false);
methodVisitor.visitInsn(ATHROW);
methodVisitor.visitLabel(label1);
methodVisitor.visitVarInsn(ALOAD, 0);
methodVisitor.visitVarInsn(ALOAD, 1);
methodVisitor.visitInsn(ARRAYLENGTH);
methodVisitor.visitVarInsn(ALOAD, 0);
methodVisitor.visitFieldInsn(GETFIELD, "org/bouncycastle/crypto/engines/ChaChaEngine", "engineState", "[I");
methodVisitor.visitInsn(ICONST_0);
methodVisitor.visitMethodInsn(INVOKEVIRTUAL, "org/bouncycastle/crypto/engines/ChaChaEngine", "packTauOrSigma", "(I[II)V", false);
methodVisitor.visitVarInsn(ALOAD, 1);
methodVisitor.visitInsn(ICONST_0);
methodVisitor.visitVarInsn(ALOAD, 0);
methodVisitor.visitFieldInsn(GETFIELD, "org/bouncycastle/crypto/engines/ChaChaEngine", "engineState", "[I");
methodVisitor.visitInsn(ICONST_4);
methodVisitor.visitInsn(ICONST_4);
methodVisitor.visitMethodInsn(INVOKESTATIC, "org/bouncycastle/util/Pack", "littleEndianToInt", "([BI[III)V", false);
methodVisitor.visitVarInsn(ALOAD, 1);
methodVisitor.visitVarInsn(ALOAD, 1);
methodVisitor.visitInsn(ARRAYLENGTH);
methodVisitor.visitIntInsn(BIPUSH, 16);
methodVisitor.visitInsn(ISUB);
methodVisitor.visitVarInsn(ALOAD, 0);
methodVisitor.visitFieldInsn(GETFIELD, "org/bouncycastle/crypto/engines/ChaChaEngine", "engineState", "[I");
methodVisitor.visitIntInsn(BIPUSH, 8);
methodVisitor.visitInsn(ICONST_4);
methodVisitor.visitMethodInsn(INVOKESTATIC, "org/bouncycastle/util/Pack", "littleEndianToInt", "([BI[III)V", false);
methodVisitor.visitLabel(label0);
methodVisitor.visitVarInsn(ALOAD, 2);
methodVisitor.visitInsn(ICONST_0);
methodVisitor.visitVarInsn(ALOAD, 0);
methodVisitor.visitFieldInsn(GETFIELD, "org/bouncycastle/crypto/engines/ChaChaEngine", "engineState", "[I");
methodVisitor.visitIntInsn(BIPUSH, 14);
methodVisitor.visitInsn(ICONST_2);
methodVisitor.visitMethodInsn(INVOKESTATIC, "org/bouncycastle/util/Pack", "littleEndianToInt", "([BI[III)V", false);
methodVisitor.visitInsn(RETURN);
methodVisitor.visitMaxs(5, 3);
methodVisitor.visitEnd();
}
{
methodVisitor = classWriter.visitMethod(ACC_PROTECTED, "generateKeyStream", "([B)V", null, null);
methodVisitor.visitCode();
methodVisitor.visitVarInsn(ALOAD, 0);
methodVisitor.visitFieldInsn(GETFIELD, "org/bouncycastle/crypto/engines/ChaChaEngine", "rounds", "I");
methodVisitor.visitVarInsn(ALOAD, 0);
methodVisitor.visitFieldInsn(GETFIELD, "org/bouncycastle/crypto/engines/ChaChaEngine", "engineState", "[I");
methodVisitor.visitVarInsn(ALOAD, 0);
methodVisitor.visitFieldInsn(GETFIELD, "org/bouncycastle/crypto/engines/ChaChaEngine", "x", "[I");
methodVisitor.visitMethodInsn(INVOKESTATIC, "org/bouncycastle/crypto/engines/ChaChaEngine", "chachaCore", "(I[I[I)V", false);
methodVisitor.visitVarInsn(ALOAD, 0);
methodVisitor.visitFieldInsn(GETFIELD, "org/bouncycastle/crypto/engines/ChaChaEngine", "x", "[I");
methodVisitor.visitVarInsn(ALOAD, 1);
methodVisitor.visitInsn(ICONST_0);
methodVisitor.visitMethodInsn(INVOKESTATIC, "org/bouncycastle/util/Pack", "intToLittleEndian", "([I[BI)V", false);
methodVisitor.visitInsn(RETURN);
methodVisitor.visitMaxs(3, 2);
methodVisitor.visitEnd();
}
{
methodVisitor = classWriter.visitMethod(ACC_PUBLIC | ACC_STATIC, "chachaCore", "(I[I[I)V", null, null);
methodVisitor.visitCode();
methodVisitor.visitVarInsn(ALOAD, 1);
methodVisitor.visitInsn(ARRAYLENGTH);
methodVisitor.visitIntInsn(BIPUSH, 16);
Label label0 = new Label();
methodVisitor.visitJumpInsn(IF_ICMPEQ, label0);
methodVisitor.visitTypeInsn(NEW, "java/lang/IllegalArgumentException");
methodVisitor.visitInsn(DUP);
methodVisitor.visitMethodInsn(INVOKESPECIAL, "java/lang/IllegalArgumentException", "<init>", "()V", false);
methodVisitor.visitInsn(ATHROW);
methodVisitor.visitLabel(label0);
methodVisitor.visitVarInsn(ALOAD, 2);
methodVisitor.visitInsn(ARRAYLENGTH);
methodVisitor.visitIntInsn(BIPUSH, 16);
Label label1 = new Label();
methodVisitor.visitJumpInsn(IF_ICMPEQ, label1);
methodVisitor.visitTypeInsn(NEW, "java/lang/IllegalArgumentException");
methodVisitor.visitInsn(DUP);
methodVisitor.visitMethodInsn(INVOKESPECIAL, "java/lang/IllegalArgumentException", "<init>", "()V", false);
methodVisitor.visitInsn(ATHROW);
methodVisitor.visitLabel(label1);
methodVisitor.visitVarInsn(ILOAD, 0);
methodVisitor.visitInsn(ICONST_2);
methodVisitor.visitInsn(IREM);
Label label2 = new Label();
methodVisitor.visitJumpInsn(IFEQ, label2);
methodVisitor.visitTypeInsn(NEW, "java/lang/IllegalArgumentException");
methodVisitor.visitInsn(DUP);
methodVisitor.visitLdcInsn("Number of rounds must be even");
methodVisitor.visitMethodInsn(INVOKESPECIAL, "java/lang/IllegalArgumentException", "<init>", "(Ljava/lang/String;)V", false);
methodVisitor.visitInsn(ATHROW);
methodVisitor.visitLabel(label2);
methodVisitor.visitVarInsn(ALOAD, 1);
methodVisitor.visitInsn(ICONST_0);
methodVisitor.visitInsn(IALOAD);
methodVisitor.visitVarInsn(ISTORE, 3);
methodVisitor.visitVarInsn(ALOAD, 1);
methodVisitor.visitInsn(ICONST_1);
methodVisitor.visitInsn(IALOAD);
methodVisitor.visitVarInsn(ISTORE, 4);
methodVisitor.visitVarInsn(ALOAD, 1);
methodVisitor.visitInsn(ICONST_2);
methodVisitor.visitInsn(IALOAD);
methodVisitor.visitVarInsn(ISTORE, 5);
methodVisitor.visitVarInsn(ALOAD, 1);
methodVisitor.visitInsn(ICONST_3);
methodVisitor.visitInsn(IALOAD);
methodVisitor.visitVarInsn(ISTORE, 6);
methodVisitor.visitVarInsn(ALOAD, 1);
methodVisitor.visitInsn(ICONST_4);
methodVisitor.visitInsn(IALOAD);
methodVisitor.visitVarInsn(ISTORE, 7);
methodVisitor.visitVarInsn(ALOAD, 1);
methodVisitor.visitInsn(ICONST_5);
methodVisitor.visitInsn(IALOAD);
methodVisitor.visitVarInsn(ISTORE, 8);
methodVisitor.visitVarInsn(ALOAD, 1);
methodVisitor.visitIntInsn(BIPUSH, 6);
methodVisitor.visitInsn(IALOAD);
methodVisitor.visitVarInsn(ISTORE, 9);
methodVisitor.visitVarInsn(ALOAD, 1);
methodVisitor.visitIntInsn(BIPUSH, 7);
methodVisitor.visitInsn(IALOAD);
methodVisitor.visitVarInsn(ISTORE, 10);
methodVisitor.visitVarInsn(ALOAD, 1);
methodVisitor.visitIntInsn(BIPUSH, 8);
methodVisitor.visitInsn(IALOAD);
methodVisitor.visitVarInsn(ISTORE, 11);
methodVisitor.visitVarInsn(ALOAD, 1);
methodVisitor.visitIntInsn(BIPUSH, 9);
methodVisitor.visitInsn(IALOAD);
methodVisitor.visitVarInsn(ISTORE, 12);
methodVisitor.visitVarInsn(ALOAD, 1);
methodVisitor.visitIntInsn(BIPUSH, 10);
methodVisitor.visitInsn(IALOAD);
methodVisitor.visitVarInsn(ISTORE, 13);
methodVisitor.visitVarInsn(ALOAD, 1);
methodVisitor.visitIntInsn(BIPUSH, 11);
methodVisitor.visitInsn(IALOAD);
methodVisitor.visitVarInsn(ISTORE, 14);
methodVisitor.visitVarInsn(ALOAD, 1);
methodVisitor.visitIntInsn(BIPUSH, 12);
methodVisitor.visitInsn(IALOAD);
methodVisitor.visitVarInsn(ISTORE, 15);
methodVisitor.visitVarInsn(ALOAD, 1);
methodVisitor.visitIntInsn(BIPUSH, 13);
methodVisitor.visitInsn(IALOAD);
methodVisitor.visitVarInsn(ISTORE, 16);
methodVisitor.visitVarInsn(ALOAD, 1);
methodVisitor.visitIntInsn(BIPUSH, 14);
methodVisitor.visitInsn(IALOAD);
methodVisitor.visitVarInsn(ISTORE, 17);
methodVisitor.visitVarInsn(ALOAD, 1);
methodVisitor.visitIntInsn(BIPUSH, 15);
methodVisitor.visitInsn(IALOAD);
methodVisitor.visitVarInsn(ISTORE, 18);
methodVisitor.visitVarInsn(ILOAD, 0);
methodVisitor.visitVarInsn(ISTORE, 19);
Label label3 = new Label();
methodVisitor.visitLabel(label3);
methodVisitor.visitVarInsn(ILOAD, 19);
Label label4 = new Label();
methodVisitor.visitJumpInsn(IFLE, label4);
methodVisitor.visitVarInsn(ILOAD, 3);
methodVisitor.visitVarInsn(ILOAD, 7);
methodVisitor.visitInsn(IADD);
methodVisitor.visitVarInsn(ISTORE, 3);
methodVisitor.visitVarInsn(ILOAD, 15);
methodVisitor.visitVarInsn(ILOAD, 3);
methodVisitor.visitInsn(IXOR);
methodVisitor.visitIntInsn(BIPUSH, 16);
methodVisitor.visitMethodInsn(INVOKESTATIC, "org/bouncycastle/crypto/engines/ChaChaEngine", "rotl", "(II)I", false);
methodVisitor.visitVarInsn(ISTORE, 15);
methodVisitor.visitVarInsn(ILOAD, 11);
methodVisitor.visitVarInsn(ILOAD, 15);
methodVisitor.visitInsn(IADD);
methodVisitor.visitVarInsn(ISTORE, 11);
methodVisitor.visitVarInsn(ILOAD, 7);
methodVisitor.visitVarInsn(ILOAD, 11);
methodVisitor.visitInsn(IXOR);
methodVisitor.visitIntInsn(BIPUSH, 12);
methodVisitor.visitMethodInsn(INVOKESTATIC, "org/bouncycastle/crypto/engines/ChaChaEngine", "rotl", "(II)I", false);
methodVisitor.visitVarInsn(ISTORE, 7);
methodVisitor.visitVarInsn(ILOAD, 3);
methodVisitor.visitVarInsn(ILOAD, 7);
methodVisitor.visitInsn(IADD);
methodVisitor.visitVarInsn(ISTORE, 3);
methodVisitor.visitVarInsn(ILOAD, 15);
methodVisitor.visitVarInsn(ILOAD, 3);
methodVisitor.visitInsn(IXOR);
methodVisitor.visitIntInsn(BIPUSH, 8);
methodVisitor.visitMethodInsn(INVOKESTATIC, "org/bouncycastle/crypto/engines/ChaChaEngine", "rotl", "(II)I", false);
methodVisitor.visitVarInsn(ISTORE, 15);
methodVisitor.visitVarInsn(ILOAD, 11);
methodVisitor.visitVarInsn(ILOAD, 15);
methodVisitor.visitInsn(IADD);
methodVisitor.visitVarInsn(ISTORE, 11);
methodVisitor.visitVarInsn(ILOAD, 7);
methodVisitor.visitVarInsn(ILOAD, 11);
methodVisitor.visitInsn(IXOR);
methodVisitor.visitIntInsn(BIPUSH, 7);
methodVisitor.visitMethodInsn(INVOKESTATIC, "org/bouncycastle/crypto/engines/ChaChaEngine", "rotl", "(II)I", false);
methodVisitor.visitVarInsn(ISTORE, 7);
methodVisitor.visitVarInsn(ILOAD, 4);
methodVisitor.visitVarInsn(ILOAD, 8);
methodVisitor.visitInsn(IADD);
methodVisitor.visitVarInsn(ISTORE, 4);
methodVisitor.visitVarInsn(ILOAD, 16);
methodVisitor.visitVarInsn(ILOAD, 4);
methodVisitor.visitInsn(IXOR);
methodVisitor.visitIntInsn(BIPUSH, 16);
methodVisitor.visitMethodInsn(INVOKESTATIC, "org/bouncycastle/crypto/engines/ChaChaEngine", "rotl", "(II)I", false);
methodVisitor.visitVarInsn(ISTORE, 16);
methodVisitor.visitVarInsn(ILOAD, 12);
methodVisitor.visitVarInsn(ILOAD, 16);
methodVisitor.visitInsn(IADD);
methodVisitor.visitVarInsn(ISTORE, 12);
methodVisitor.visitVarInsn(ILOAD, 8);
methodVisitor.visitVarInsn(ILOAD, 12);
methodVisitor.visitInsn(IXOR);
methodVisitor.visitIntInsn(BIPUSH, 12);
methodVisitor.visitMethodInsn(INVOKESTATIC, "org/bouncycastle/crypto/engines/ChaChaEngine", "rotl", "(II)I", false);
methodVisitor.visitVarInsn(ISTORE, 8);
methodVisitor.visitVarInsn(ILOAD, 4);
methodVisitor.visitVarInsn(ILOAD, 8);
methodVisitor.visitInsn(IADD);
methodVisitor.visitVarInsn(ISTORE, 4);
methodVisitor.visitVarInsn(ILOAD, 16);
methodVisitor.visitVarInsn(ILOAD, 4);
methodVisitor.visitInsn(IXOR);
methodVisitor.visitIntInsn(BIPUSH, 8);
methodVisitor.visitMethodInsn(INVOKESTATIC, "org/bouncycastle/crypto/engines/ChaChaEngine", "rotl", "(II)I", false);
methodVisitor.visitVarInsn(ISTORE, 16);
methodVisitor.visitVarInsn(ILOAD, 12);
methodVisitor.visitVarInsn(ILOAD, 16);
methodVisitor.visitInsn(IADD);
methodVisitor.visitVarInsn(ISTORE, 12);
methodVisitor.visitVarInsn(ILOAD, 8);
methodVisitor.visitVarInsn(ILOAD, 12);
methodVisitor.visitInsn(IXOR);
methodVisitor.visitIntInsn(BIPUSH, 7);
methodVisitor.visitMethodInsn(INVOKESTATIC, "org/bouncycastle/crypto/engines/ChaChaEngine", "rotl", "(II)I", false);
methodVisitor.visitVarInsn(ISTORE, 8);
methodVisitor.visitVarInsn(ILOAD, 5);
methodVisitor.visitVarInsn(ILOAD, 9);
methodVisitor.visitInsn(IADD);
methodVisitor.visitVarInsn(ISTORE, 5);
methodVisitor.visitVarInsn(ILOAD, 17);
methodVisitor.visitVarInsn(ILOAD, 5);
methodVisitor.visitInsn(IXOR);
methodVisitor.visitIntInsn(BIPUSH, 16);
methodVisitor.visitMethodInsn(INVOKESTATIC, "org/bouncycastle/crypto/engines/ChaChaEngine", "rotl", "(II)I", false);
methodVisitor.visitVarInsn(ISTORE, 17);
methodVisitor.visitVarInsn(ILOAD, 13);
methodVisitor.visitVarInsn(ILOAD, 17);
methodVisitor.visitInsn(IADD);
methodVisitor.visitVarInsn(ISTORE, 13);
methodVisitor.visitVarInsn(ILOAD, 9);
methodVisitor.visitVarInsn(ILOAD, 13);
methodVisitor.visitInsn(IXOR);
methodVisitor.visitIntInsn(BIPUSH, 12);
methodVisitor.visitMethodInsn(INVOKESTATIC, "org/bouncycastle/crypto/engines/ChaChaEngine", "rotl", "(II)I", false);
methodVisitor.visitVarInsn(ISTORE, 9);
methodVisitor.visitVarInsn(ILOAD, 5);
methodVisitor.visitVarInsn(ILOAD, 9);
methodVisitor.visitInsn(IADD);
methodVisitor.visitVarInsn(ISTORE, 5);
methodVisitor.visitVarInsn(ILOAD, 17);
methodVisitor.visitVarInsn(ILOAD, 5);
methodVisitor.visitInsn(IXOR);
methodVisitor.visitIntInsn(BIPUSH, 8);
methodVisitor.visitMethodInsn(INVOKESTATIC, "org/bouncycastle/crypto/engines/ChaChaEngine", "rotl", "(II)I", false);
methodVisitor.visitVarInsn(ISTORE, 17);
methodVisitor.visitVarInsn(ILOAD, 13);
methodVisitor.visitVarInsn(ILOAD, 17);
methodVisitor.visitInsn(IADD);
methodVisitor.visitVarInsn(ISTORE, 13);
methodVisitor.visitVarInsn(ILOAD, 9);
methodVisitor.visitVarInsn(ILOAD, 13);
methodVisitor.visitInsn(IXOR);
methodVisitor.visitIntInsn(BIPUSH, 7);
methodVisitor.visitMethodInsn(INVOKESTATIC, "org/bouncycastle/crypto/engines/ChaChaEngine", "rotl", "(II)I", false);
methodVisitor.visitVarInsn(ISTORE, 9);
methodVisitor.visitVarInsn(ILOAD, 6);
methodVisitor.visitVarInsn(ILOAD, 10);
methodVisitor.visitInsn(IADD);
methodVisitor.visitVarInsn(ISTORE, 6);
methodVisitor.visitVarInsn(ILOAD, 18);
methodVisitor.visitVarInsn(ILOAD, 6);
methodVisitor.visitInsn(IXOR);
methodVisitor.visitIntInsn(BIPUSH, 16);
methodVisitor.visitMethodInsn(INVOKESTATIC, "org/bouncycastle/crypto/engines/ChaChaEngine", "rotl", "(II)I", false);
methodVisitor.visitVarInsn(ISTORE, 18);
methodVisitor.visitVarInsn(ILOAD, 14);
methodVisitor.visitVarInsn(ILOAD, 18);
methodVisitor.visitInsn(IADD);
methodVisitor.visitVarInsn(ISTORE, 14);
methodVisitor.visitVarInsn(ILOAD, 10);
methodVisitor.visitVarInsn(ILOAD, 14);
methodVisitor.visitInsn(IXOR);
methodVisitor.visitIntInsn(BIPUSH, 12);
methodVisitor.visitMethodInsn(INVOKESTATIC, "org/bouncycastle/crypto/engines/ChaChaEngine", "rotl", "(II)I", false);
methodVisitor.visitVarInsn(ISTORE, 10);
methodVisitor.visitVarInsn(ILOAD, 6);
methodVisitor.visitVarInsn(ILOAD, 10);
methodVisitor.visitInsn(IADD);
methodVisitor.visitVarInsn(ISTORE, 6);
methodVisitor.visitVarInsn(ILOAD, 18);
methodVisitor.visitVarInsn(ILOAD, 6);
methodVisitor.visitInsn(IXOR);
methodVisitor.visitIntInsn(BIPUSH, 8);
methodVisitor.visitMethodInsn(INVOKESTATIC, "org/bouncycastle/crypto/engines/ChaChaEngine", "rotl", "(II)I", false);
methodVisitor.visitVarInsn(ISTORE, 18);
methodVisitor.visitVarInsn(ILOAD, 14);
methodVisitor.visitVarInsn(ILOAD, 18);
methodVisitor.visitInsn(IADD);
methodVisitor.visitVarInsn(ISTORE, 14);
methodVisitor.visitVarInsn(ILOAD, 10);
methodVisitor.visitVarInsn(ILOAD, 14);
methodVisitor.visitInsn(IXOR);
methodVisitor.visitIntInsn(BIPUSH, 7);
methodVisitor.visitMethodInsn(INVOKESTATIC, "org/bouncycastle/crypto/engines/ChaChaEngine", "rotl", "(II)I", false);
methodVisitor.visitVarInsn(ISTORE, 10);
methodVisitor.visitVarInsn(ILOAD, 3);
methodVisitor.visitVarInsn(ILOAD, 8);
methodVisitor.visitInsn(IADD);
methodVisitor.visitVarInsn(ISTORE, 3);
methodVisitor.visitVarInsn(ILOAD, 18);
methodVisitor.visitVarInsn(ILOAD, 3);
methodVisitor.visitInsn(IXOR);
methodVisitor.visitIntInsn(BIPUSH, 16);
methodVisitor.visitMethodInsn(INVOKESTATIC, "org/bouncycastle/crypto/engines/ChaChaEngine", "rotl", "(II)I", false);
methodVisitor.visitVarInsn(ISTORE, 18);
methodVisitor.visitVarInsn(ILOAD, 13);
methodVisitor.visitVarInsn(ILOAD, 18);
methodVisitor.visitInsn(IADD);
methodVisitor.visitVarInsn(ISTORE, 13);
methodVisitor.visitVarInsn(ILOAD, 8);
methodVisitor.visitVarInsn(ILOAD, 13);
methodVisitor.visitInsn(IXOR);
methodVisitor.visitIntInsn(BIPUSH, 12);
methodVisitor.visitMethodInsn(INVOKESTATIC, "org/bouncycastle/crypto/engines/ChaChaEngine", "rotl", "(II)I", false);
methodVisitor.visitVarInsn(ISTORE, 8);
methodVisitor.visitVarInsn(ILOAD, 3);
methodVisitor.visitVarInsn(ILOAD, 8);
methodVisitor.visitInsn(IADD);
methodVisitor.visitVarInsn(ISTORE, 3);
methodVisitor.visitVarInsn(ILOAD, 18);
methodVisitor.visitVarInsn(ILOAD, 3);
methodVisitor.visitInsn(IXOR);
methodVisitor.visitIntInsn(BIPUSH, 8);
methodVisitor.visitMethodInsn(INVOKESTATIC, "org/bouncycastle/crypto/engines/ChaChaEngine", "rotl", "(II)I", false);
methodVisitor.visitVarInsn(ISTORE, 18);
methodVisitor.visitVarInsn(ILOAD, 13);
methodVisitor.visitVarInsn(ILOAD, 18);
methodVisitor.visitInsn(IADD);
methodVisitor.visitVarInsn(ISTORE, 13);
methodVisitor.visitVarInsn(ILOAD, 8);
methodVisitor.visitVarInsn(ILOAD, 13);
methodVisitor.visitInsn(IXOR);
methodVisitor.visitIntInsn(BIPUSH, 7);
methodVisitor.visitMethodInsn(INVOKESTATIC, "org/bouncycastle/crypto/engines/ChaChaEngine", "rotl", "(II)I", false);
methodVisitor.visitVarInsn(ISTORE, 8);
methodVisitor.visitVarInsn(ILOAD, 4);
methodVisitor.visitVarInsn(ILOAD, 9);
methodVisitor.visitInsn(IADD);
methodVisitor.visitVarInsn(ISTORE, 4);
methodVisitor.visitVarInsn(ILOAD, 15);
methodVisitor.visitVarInsn(ILOAD, 4);
methodVisitor.visitInsn(IXOR);
methodVisitor.visitIntInsn(BIPUSH, 16);
methodVisitor.visitMethodInsn(INVOKESTATIC, "org/bouncycastle/crypto/engines/ChaChaEngine", "rotl", "(II)I", false);
methodVisitor.visitVarInsn(ISTORE, 15);
methodVisitor.visitVarInsn(ILOAD, 14);
methodVisitor.visitVarInsn(ILOAD, 15);
methodVisitor.visitInsn(IADD);
methodVisitor.visitVarInsn(ISTORE, 14);
methodVisitor.visitVarInsn(ILOAD, 9);
methodVisitor.visitVarInsn(ILOAD, 14);
methodVisitor.visitInsn(IXOR);
methodVisitor.visitIntInsn(BIPUSH, 12);
methodVisitor.visitMethodInsn(INVOKESTATIC, "org/bouncycastle/crypto/engines/ChaChaEngine", "rotl", "(II)I", false);
methodVisitor.visitVarInsn(ISTORE, 9);
methodVisitor.visitVarInsn(ILOAD, 4);
methodVisitor.visitVarInsn(ILOAD, 9);
methodVisitor.visitInsn(IADD);
methodVisitor.visitVarInsn(ISTORE, 4);
methodVisitor.visitVarInsn(ILOAD, 15);
methodVisitor.visitVarInsn(ILOAD, 4);
methodVisitor.visitInsn(IXOR);
methodVisitor.visitIntInsn(BIPUSH, 8);
methodVisitor.visitMethodInsn(INVOKESTATIC, "org/bouncycastle/crypto/engines/ChaChaEngine", "rotl", "(II)I", false);
methodVisitor.visitVarInsn(ISTORE, 15);
methodVisitor.visitVarInsn(ILOAD, 14);
methodVisitor.visitVarInsn(ILOAD, 15);
methodVisitor.visitInsn(IADD);
methodVisitor.visitVarInsn(ISTORE, 14);
methodVisitor.visitVarInsn(ILOAD, 9);
methodVisitor.visitVarInsn(ILOAD, 14);
methodVisitor.visitInsn(IXOR);
methodVisitor.visitIntInsn(BIPUSH, 7);
methodVisitor.visitMethodInsn(INVOKESTATIC, "org/bouncycastle/crypto/engines/ChaChaEngine", "rotl", "(II)I", false);
methodVisitor.visitVarInsn(ISTORE, 9);
methodVisitor.visitVarInsn(ILOAD, 5);
methodVisitor.visitVarInsn(ILOAD, 10);
methodVisitor.visitInsn(IADD);
methodVisitor.visitVarInsn(ISTORE, 5);
methodVisitor.visitVarInsn(ILOAD, 16);
methodVisitor.visitVarInsn(ILOAD, 5);
methodVisitor.visitInsn(IXOR);
methodVisitor.visitIntInsn(BIPUSH, 16);
methodVisitor.visitMethodInsn(INVOKESTATIC, "org/bouncycastle/crypto/engines/ChaChaEngine", "rotl", "(II)I", false);
methodVisitor.visitVarInsn(ISTORE, 16);
methodVisitor.visitVarInsn(ILOAD, 11);
methodVisitor.visitVarInsn(ILOAD, 16);
methodVisitor.visitInsn(IADD);
methodVisitor.visitVarInsn(ISTORE, 11);
methodVisitor.visitVarInsn(ILOAD, 10);
methodVisitor.visitVarInsn(ILOAD, 11);
methodVisitor.visitInsn(IXOR);
methodVisitor.visitIntInsn(BIPUSH, 12);
methodVisitor.visitMethodInsn(INVOKESTATIC, "org/bouncycastle/crypto/engines/ChaChaEngine", "rotl", "(II)I", false);
methodVisitor.visitVarInsn(ISTORE, 10);
methodVisitor.visitVarInsn(ILOAD, 5);
methodVisitor.visitVarInsn(ILOAD, 10);
methodVisitor.visitInsn(IADD);
methodVisitor.visitVarInsn(ISTORE, 5);
methodVisitor.visitVarInsn(ILOAD, 16);
methodVisitor.visitVarInsn(ILOAD, 5);
methodVisitor.visitInsn(IXOR);
methodVisitor.visitIntInsn(BIPUSH, 8);
methodVisitor.visitMethodInsn(INVOKESTATIC, "org/bouncycastle/crypto/engines/ChaChaEngine", "rotl", "(II)I", false);
methodVisitor.visitVarInsn(ISTORE, 16);
methodVisitor.visitVarInsn(ILOAD, 11);
methodVisitor.visitVarInsn(ILOAD, 16);
methodVisitor.visitInsn(IADD);
methodVisitor.visitVarInsn(ISTORE, 11);
methodVisitor.visitVarInsn(ILOAD, 10);
methodVisitor.visitVarInsn(ILOAD, 11);
methodVisitor.visitInsn(IXOR);
methodVisitor.visitIntInsn(BIPUSH, 7);
methodVisitor.visitMethodInsn(INVOKESTATIC, "org/bouncycastle/crypto/engines/ChaChaEngine", "rotl", "(II)I", false);
methodVisitor.visitVarInsn(ISTORE, 10);
methodVisitor.visitVarInsn(ILOAD, 6);
methodVisitor.visitVarInsn(ILOAD, 7);
methodVisitor.visitInsn(IADD);
methodVisitor.visitVarInsn(ISTORE, 6);
methodVisitor.visitVarInsn(ILOAD, 17);
methodVisitor.visitVarInsn(ILOAD, 6);
methodVisitor.visitInsn(IXOR);
methodVisitor.visitIntInsn(BIPUSH, 16);
methodVisitor.visitMethodInsn(INVOKESTATIC, "org/bouncycastle/crypto/engines/ChaChaEngine", "rotl", "(II)I", false);
methodVisitor.visitVarInsn(ISTORE, 17);
methodVisitor.visitVarInsn(ILOAD, 12);
methodVisitor.visitVarInsn(ILOAD, 17);
methodVisitor.visitInsn(IADD);
methodVisitor.visitVarInsn(ISTORE, 12);
methodVisitor.visitVarInsn(ILOAD, 7);
methodVisitor.visitVarInsn(ILOAD, 12);
methodVisitor.visitInsn(IXOR);
methodVisitor.visitIntInsn(BIPUSH, 12);
methodVisitor.visitMethodInsn(INVOKESTATIC, "org/bouncycastle/crypto/engines/ChaChaEngine", "rotl", "(II)I", false);
methodVisitor.visitVarInsn(ISTORE, 7);
methodVisitor.visitVarInsn(ILOAD, 6);
methodVisitor.visitVarInsn(ILOAD, 7);
methodVisitor.visitInsn(IADD);
methodVisitor.visitVarInsn(ISTORE, 6);
methodVisitor.visitVarInsn(ILOAD, 17);
methodVisitor.visitVarInsn(ILOAD, 6);
methodVisitor.visitInsn(IXOR);
methodVisitor.visitIntInsn(BIPUSH, 8);
methodVisitor.visitMethodInsn(INVOKESTATIC, "org/bouncycastle/crypto/engines/ChaChaEngine", "rotl", "(II)I", false);
methodVisitor.visitVarInsn(ISTORE, 17);
methodVisitor.visitVarInsn(ILOAD, 12);
methodVisitor.visitVarInsn(ILOAD, 17);
methodVisitor.visitInsn(IADD);
methodVisitor.visitVarInsn(ISTORE, 12);
methodVisitor.visitVarInsn(ILOAD, 7);
methodVisitor.visitVarInsn(ILOAD, 12);
methodVisitor.visitInsn(IXOR);
methodVisitor.visitIntInsn(BIPUSH, 7);
methodVisitor.visitMethodInsn(INVOKESTATIC, "org/bouncycastle/crypto/engines/ChaChaEngine", "rotl", "(II)I", false);
methodVisitor.visitVarInsn(ISTORE, 7);
methodVisitor.visitIincInsn(19, -2);
methodVisitor.visitJumpInsn(GOTO, label3);
methodVisitor.visitLabel(label4);
methodVisitor.visitVarInsn(ALOAD, 2);
methodVisitor.visitInsn(ICONST_0);
methodVisitor.visitVarInsn(ILOAD, 3);
methodVisitor.visitVarInsn(ALOAD, 1);
methodVisitor.visitInsn(ICONST_0);
methodVisitor.visitInsn(IALOAD);
methodVisitor.visitInsn(IADD);
methodVisitor.visitInsn(IASTORE);
methodVisitor.visitVarInsn(ALOAD, 2);
methodVisitor.visitInsn(ICONST_1);
methodVisitor.visitVarInsn(ILOAD, 4);
methodVisitor.visitVarInsn(ALOAD, 1);
methodVisitor.visitInsn(ICONST_1);
methodVisitor.visitInsn(IALOAD);
methodVisitor.visitInsn(IADD);
methodVisitor.visitInsn(IASTORE);
methodVisitor.visitVarInsn(ALOAD, 2);
methodVisitor.visitInsn(ICONST_2);
methodVisitor.visitVarInsn(ILOAD, 5);
methodVisitor.visitVarInsn(ALOAD, 1);
methodVisitor.visitInsn(ICONST_2);
methodVisitor.visitInsn(IALOAD);
methodVisitor.visitInsn(IADD);
methodVisitor.visitInsn(IASTORE);
methodVisitor.visitVarInsn(ALOAD, 2);
methodVisitor.visitInsn(ICONST_3);
methodVisitor.visitVarInsn(ILOAD, 6);
methodVisitor.visitVarInsn(ALOAD, 1);
methodVisitor.visitInsn(ICONST_3);
methodVisitor.visitInsn(IALOAD);
methodVisitor.visitInsn(IADD);
methodVisitor.visitInsn(IASTORE);
methodVisitor.visitVarInsn(ALOAD, 2);
methodVisitor.visitInsn(ICONST_4);
methodVisitor.visitVarInsn(ILOAD, 7);
methodVisitor.visitVarInsn(ALOAD, 1);
methodVisitor.visitInsn(ICONST_4);
methodVisitor.visitInsn(IALOAD);
methodVisitor.visitInsn(IADD);
methodVisitor.visitInsn(IASTORE);
methodVisitor.visitVarInsn(ALOAD, 2);
methodVisitor.visitInsn(ICONST_5);
methodVisitor.visitVarInsn(ILOAD, 8);
methodVisitor.visitVarInsn(ALOAD, 1);
methodVisitor.visitInsn(ICONST_5);
methodVisitor.visitInsn(IALOAD);
methodVisitor.visitInsn(IADD);
methodVisitor.visitInsn(IASTORE);
methodVisitor.visitVarInsn(ALOAD, 2);
methodVisitor.visitIntInsn(BIPUSH, 6);
methodVisitor.visitVarInsn(ILOAD, 9);
methodVisitor.visitVarInsn(ALOAD, 1);
methodVisitor.visitIntInsn(BIPUSH, 6);
methodVisitor.visitInsn(IALOAD);
methodVisitor.visitInsn(IADD);
methodVisitor.visitInsn(IASTORE);
methodVisitor.visitVarInsn(ALOAD, 2);
methodVisitor.visitIntInsn(BIPUSH, 7);
methodVisitor.visitVarInsn(ILOAD, 10);
methodVisitor.visitVarInsn(ALOAD, 1);
methodVisitor.visitIntInsn(BIPUSH, 7);
methodVisitor.visitInsn(IALOAD);
methodVisitor.visitInsn(IADD);
methodVisitor.visitInsn(IASTORE);
methodVisitor.visitVarInsn(ALOAD, 2);
methodVisitor.visitIntInsn(BIPUSH, 8);
methodVisitor.visitVarInsn(ILOAD, 11);
methodVisitor.visitVarInsn(ALOAD, 1);
methodVisitor.visitIntInsn(BIPUSH, 8);
methodVisitor.visitInsn(IALOAD);
methodVisitor.visitInsn(IADD);
methodVisitor.visitInsn(IASTORE);
methodVisitor.visitVarInsn(ALOAD, 2);
methodVisitor.visitIntInsn(BIPUSH, 9);
methodVisitor.visitVarInsn(ILOAD, 12);
methodVisitor.visitVarInsn(ALOAD, 1);
methodVisitor.visitIntInsn(BIPUSH, 9);
methodVisitor.visitInsn(IALOAD);
methodVisitor.visitInsn(IADD);
methodVisitor.visitInsn(IASTORE);
methodVisitor.visitVarInsn(ALOAD, 2);
methodVisitor.visitIntInsn(BIPUSH, 10);
methodVisitor.visitVarInsn(ILOAD, 13);
methodVisitor.visitVarInsn(ALOAD, 1);
methodVisitor.visitIntInsn(BIPUSH, 10);
methodVisitor.visitInsn(IALOAD);
methodVisitor.visitInsn(IADD);
methodVisitor.visitInsn(IASTORE);
methodVisitor.visitVarInsn(ALOAD, 2);
methodVisitor.visitIntInsn(BIPUSH, 11);
methodVisitor.visitVarInsn(ILOAD, 14);
methodVisitor.visitVarInsn(ALOAD, 1);
methodVisitor.visitIntInsn(BIPUSH, 11);
methodVisitor.visitInsn(IALOAD);
methodVisitor.visitInsn(IADD);
methodVisitor.visitInsn(IASTORE);
methodVisitor.visitVarInsn(ALOAD, 2);
methodVisitor.visitIntInsn(BIPUSH, 12);
methodVisitor.visitVarInsn(ILOAD, 15);
methodVisitor.visitVarInsn(ALOAD, 1);
methodVisitor.visitIntInsn(BIPUSH, 12);
methodVisitor.visitInsn(IALOAD);
methodVisitor.visitInsn(IADD);
methodVisitor.visitInsn(IASTORE);
methodVisitor.visitVarInsn(ALOAD, 2);
methodVisitor.visitIntInsn(BIPUSH, 13);
methodVisitor.visitVarInsn(ILOAD, 16);
methodVisitor.visitVarInsn(ALOAD, 1);
methodVisitor.visitIntInsn(BIPUSH, 13);
methodVisitor.visitInsn(IALOAD);
methodVisitor.visitInsn(IADD);
methodVisitor.visitInsn(IASTORE);
methodVisitor.visitVarInsn(ALOAD, 2);
methodVisitor.visitIntInsn(BIPUSH, 14);
methodVisitor.visitVarInsn(ILOAD, 17);
methodVisitor.visitVarInsn(ALOAD, 1);
methodVisitor.visitIntInsn(BIPUSH, 14);
methodVisitor.visitInsn(IALOAD);
methodVisitor.visitInsn(IADD);
methodVisitor.visitInsn(IASTORE);
methodVisitor.visitVarInsn(ALOAD, 2);
methodVisitor.visitIntInsn(BIPUSH, 15);
methodVisitor.visitVarInsn(ILOAD, 18);
methodVisitor.visitVarInsn(ALOAD, 1);
methodVisitor.visitIntInsn(BIPUSH, 15);
methodVisitor.visitInsn(IALOAD);
methodVisitor.visitInsn(IADD);
methodVisitor.visitInsn(IASTORE);
methodVisitor.visitInsn(RETURN);
methodVisitor.visitMaxs(5, 20);
methodVisitor.visitEnd();
}
classWriter.visitEnd();

return classWriter.toByteArray();
}
}
