package asm.org.bouncycastle.crypto.engines;
import org.objectweb.asm.AnnotationVisitor;
import org.objectweb.asm.Attribute;
import org.objectweb.asm.ClassReader;
import org.objectweb.asm.ClassWriter;
import org.objectweb.asm.ConstantDynamic;
import org.objectweb.asm.FieldVisitor;
import org.objectweb.asm.Handle;
import org.objectweb.asm.Label;
import org.objectweb.asm.MethodVisitor;
import org.objectweb.asm.Opcodes;
import org.objectweb.asm.RecordComponentVisitor;
import org.objectweb.asm.Type;
import org.objectweb.asm.TypePath;
public class NoekeonEngineDump implements Opcodes {

public static byte[] dump () throws Exception {

ClassWriter classWriter = new ClassWriter(0);
FieldVisitor fieldVisitor;
RecordComponentVisitor recordComponentVisitor;
MethodVisitor methodVisitor;
AnnotationVisitor annotationVisitor0;

classWriter.visit(V1_5, ACC_PUBLIC | ACC_SUPER, "org/bouncycastle/crypto/engines/NoekeonEngine", null, "java/lang/Object", new String[] { "org/bouncycastle/crypto/BlockCipher" });

{
fieldVisitor = classWriter.visitField(ACC_PRIVATE | ACC_FINAL | ACC_STATIC, "genericSize", "I", null, new Integer(16));
fieldVisitor.visitEnd();
}
{
fieldVisitor = classWriter.visitField(ACC_PRIVATE | ACC_FINAL | ACC_STATIC, "nullVector", "[I", null, null);
fieldVisitor.visitEnd();
}
{
fieldVisitor = classWriter.visitField(ACC_PRIVATE | ACC_FINAL | ACC_STATIC, "roundConstants", "[I", null, null);
fieldVisitor.visitEnd();
}
{
fieldVisitor = classWriter.visitField(ACC_PRIVATE, "state", "[I", null, null);
fieldVisitor.visitEnd();
}
{
fieldVisitor = classWriter.visitField(ACC_PRIVATE, "subKeys", "[I", null, null);
fieldVisitor.visitEnd();
}
{
fieldVisitor = classWriter.visitField(ACC_PRIVATE, "decryptKeys", "[I", null, null);
fieldVisitor.visitEnd();
}
{
fieldVisitor = classWriter.visitField(ACC_PRIVATE, "_initialised", "Z", null, null);
fieldVisitor.visitEnd();
}
{
fieldVisitor = classWriter.visitField(ACC_PRIVATE, "_forEncryption", "Z", null, null);
fieldVisitor.visitEnd();
}
{
methodVisitor = classWriter.visitMethod(ACC_PUBLIC, "<init>", "()V", null, null);
methodVisitor.visitCode();
methodVisitor.visitVarInsn(ALOAD, 0);
methodVisitor.visitMethodInsn(INVOKESPECIAL, "java/lang/Object", "<init>", "()V", false);
methodVisitor.visitVarInsn(ALOAD, 0);
methodVisitor.visitInsn(ICONST_4);
methodVisitor.visitIntInsn(NEWARRAY, T_INT);
methodVisitor.visitFieldInsn(PUTFIELD, "org/bouncycastle/crypto/engines/NoekeonEngine", "state", "[I");
methodVisitor.visitVarInsn(ALOAD, 0);
methodVisitor.visitInsn(ICONST_4);
methodVisitor.visitIntInsn(NEWARRAY, T_INT);
methodVisitor.visitFieldInsn(PUTFIELD, "org/bouncycastle/crypto/engines/NoekeonEngine", "subKeys", "[I");
methodVisitor.visitVarInsn(ALOAD, 0);
methodVisitor.visitInsn(ICONST_4);
methodVisitor.visitIntInsn(NEWARRAY, T_INT);
methodVisitor.visitFieldInsn(PUTFIELD, "org/bouncycastle/crypto/engines/NoekeonEngine", "decryptKeys", "[I");
methodVisitor.visitVarInsn(ALOAD, 0);
methodVisitor.visitInsn(ICONST_0);
methodVisitor.visitFieldInsn(PUTFIELD, "org/bouncycastle/crypto/engines/NoekeonEngine", "_initialised", "Z");
methodVisitor.visitInsn(RETURN);
methodVisitor.visitMaxs(2, 1);
methodVisitor.visitEnd();
}
{
methodVisitor = classWriter.visitMethod(ACC_PUBLIC, "getAlgorithmName", "()Ljava/lang/String;", null, null);
methodVisitor.visitCode();
methodVisitor.visitLdcInsn("Noekeon");
methodVisitor.visitInsn(ARETURN);
methodVisitor.visitMaxs(1, 1);
methodVisitor.visitEnd();
}
{
methodVisitor = classWriter.visitMethod(ACC_PUBLIC, "getBlockSize", "()I", null, null);
methodVisitor.visitCode();
methodVisitor.visitIntInsn(BIPUSH, 16);
methodVisitor.visitInsn(IRETURN);
methodVisitor.visitMaxs(1, 1);
methodVisitor.visitEnd();
}
{
methodVisitor = classWriter.visitMethod(ACC_PUBLIC, "init", "(ZLorg/bouncycastle/crypto/CipherParameters;)V", null, null);
methodVisitor.visitCode();
methodVisitor.visitVarInsn(ALOAD, 2);
methodVisitor.visitTypeInsn(INSTANCEOF, "org/bouncycastle/crypto/params/KeyParameter");
Label label0 = new Label();
methodVisitor.visitJumpInsn(IFNE, label0);
methodVisitor.visitTypeInsn(NEW, "java/lang/IllegalArgumentException");
methodVisitor.visitInsn(DUP);
methodVisitor.visitTypeInsn(NEW, "java/lang/StringBuilder");
methodVisitor.visitInsn(DUP);
methodVisitor.visitMethodInsn(INVOKESPECIAL, "java/lang/StringBuilder", "<init>", "()V", false);
methodVisitor.visitLdcInsn("invalid parameter passed to Noekeon init - ");
methodVisitor.visitMethodInsn(INVOKEVIRTUAL, "java/lang/StringBuilder", "append", "(Ljava/lang/String;)Ljava/lang/StringBuilder;", false);
methodVisitor.visitVarInsn(ALOAD, 2);
methodVisitor.visitMethodInsn(INVOKEVIRTUAL, "java/lang/Object", "getClass", "()Ljava/lang/Class;", false);
methodVisitor.visitMethodInsn(INVOKEVIRTUAL, "java/lang/Class", "getName", "()Ljava/lang/String;", false);
methodVisitor.visitMethodInsn(INVOKEVIRTUAL, "java/lang/StringBuilder", "append", "(Ljava/lang/String;)Ljava/lang/StringBuilder;", false);
methodVisitor.visitMethodInsn(INVOKEVIRTUAL, "java/lang/StringBuilder", "toString", "()Ljava/lang/String;", false);
methodVisitor.visitMethodInsn(INVOKESPECIAL, "java/lang/IllegalArgumentException", "<init>", "(Ljava/lang/String;)V", false);
methodVisitor.visitInsn(ATHROW);
methodVisitor.visitLabel(label0);
methodVisitor.visitVarInsn(ALOAD, 0);
methodVisitor.visitVarInsn(ILOAD, 1);
methodVisitor.visitFieldInsn(PUTFIELD, "org/bouncycastle/crypto/engines/NoekeonEngine", "_forEncryption", "Z");
methodVisitor.visitVarInsn(ALOAD, 0);
methodVisitor.visitInsn(ICONST_1);
methodVisitor.visitFieldInsn(PUTFIELD, "org/bouncycastle/crypto/engines/NoekeonEngine", "_initialised", "Z");
methodVisitor.visitVarInsn(ALOAD, 2);
methodVisitor.visitTypeInsn(CHECKCAST, "org/bouncycastle/crypto/params/KeyParameter");
methodVisitor.visitVarInsn(ASTORE, 3);
methodVisitor.visitVarInsn(ALOAD, 0);
methodVisitor.visitVarInsn(ALOAD, 3);
methodVisitor.visitMethodInsn(INVOKEVIRTUAL, "org/bouncycastle/crypto/params/KeyParameter", "getKey", "()[B", false);
methodVisitor.visitMethodInsn(INVOKESPECIAL, "org/bouncycastle/crypto/engines/NoekeonEngine", "setKey", "([B)V", false);
methodVisitor.visitInsn(RETURN);
methodVisitor.visitMaxs(4, 4);
methodVisitor.visitEnd();
}
{
methodVisitor = classWriter.visitMethod(ACC_PUBLIC, "processBlock", "([BI[BI)I", null, null);
methodVisitor.visitCode();
methodVisitor.visitVarInsn(ALOAD, 0);
methodVisitor.visitFieldInsn(GETFIELD, "org/bouncycastle/crypto/engines/NoekeonEngine", "_initialised", "Z");
Label label0 = new Label();
methodVisitor.visitJumpInsn(IFNE, label0);
methodVisitor.visitTypeInsn(NEW, "java/lang/IllegalStateException");
methodVisitor.visitInsn(DUP);
methodVisitor.visitTypeInsn(NEW, "java/lang/StringBuilder");
methodVisitor.visitInsn(DUP);
methodVisitor.visitMethodInsn(INVOKESPECIAL, "java/lang/StringBuilder", "<init>", "()V", false);
methodVisitor.visitVarInsn(ALOAD, 0);
methodVisitor.visitMethodInsn(INVOKEVIRTUAL, "org/bouncycastle/crypto/engines/NoekeonEngine", "getAlgorithmName", "()Ljava/lang/String;", false);
methodVisitor.visitMethodInsn(INVOKEVIRTUAL, "java/lang/StringBuilder", "append", "(Ljava/lang/String;)Ljava/lang/StringBuilder;", false);
methodVisitor.visitLdcInsn(" not initialised");
methodVisitor.visitMethodInsn(INVOKEVIRTUAL, "java/lang/StringBuilder", "append", "(Ljava/lang/String;)Ljava/lang/StringBuilder;", false);
methodVisitor.visitMethodInsn(INVOKEVIRTUAL, "java/lang/StringBuilder", "toString", "()Ljava/lang/String;", false);
methodVisitor.visitMethodInsn(INVOKESPECIAL, "java/lang/IllegalStateException", "<init>", "(Ljava/lang/String;)V", false);
methodVisitor.visitInsn(ATHROW);
methodVisitor.visitLabel(label0);
methodVisitor.visitVarInsn(ILOAD, 2);
methodVisitor.visitIntInsn(BIPUSH, 16);
methodVisitor.visitInsn(IADD);
methodVisitor.visitVarInsn(ALOAD, 1);
methodVisitor.visitInsn(ARRAYLENGTH);
Label label1 = new Label();
methodVisitor.visitJumpInsn(IF_ICMPLE, label1);
methodVisitor.visitTypeInsn(NEW, "org/bouncycastle/crypto/DataLengthException");
methodVisitor.visitInsn(DUP);
methodVisitor.visitLdcInsn("input buffer too short");
methodVisitor.visitMethodInsn(INVOKESPECIAL, "org/bouncycastle/crypto/DataLengthException", "<init>", "(Ljava/lang/String;)V", false);
methodVisitor.visitInsn(ATHROW);
methodVisitor.visitLabel(label1);
methodVisitor.visitVarInsn(ILOAD, 4);
methodVisitor.visitIntInsn(BIPUSH, 16);
methodVisitor.visitInsn(IADD);
methodVisitor.visitVarInsn(ALOAD, 3);
methodVisitor.visitInsn(ARRAYLENGTH);
Label label2 = new Label();
methodVisitor.visitJumpInsn(IF_ICMPLE, label2);
methodVisitor.visitTypeInsn(NEW, "org/bouncycastle/crypto/OutputLengthException");
methodVisitor.visitInsn(DUP);
methodVisitor.visitLdcInsn("output buffer too short");
methodVisitor.visitMethodInsn(INVOKESPECIAL, "org/bouncycastle/crypto/OutputLengthException", "<init>", "(Ljava/lang/String;)V", false);
methodVisitor.visitInsn(ATHROW);
methodVisitor.visitLabel(label2);
methodVisitor.visitVarInsn(ALOAD, 0);
methodVisitor.visitFieldInsn(GETFIELD, "org/bouncycastle/crypto/engines/NoekeonEngine", "_forEncryption", "Z");
Label label3 = new Label();
methodVisitor.visitJumpInsn(IFEQ, label3);
methodVisitor.visitVarInsn(ALOAD, 0);
methodVisitor.visitVarInsn(ALOAD, 1);
methodVisitor.visitVarInsn(ILOAD, 2);
methodVisitor.visitVarInsn(ALOAD, 3);
methodVisitor.visitVarInsn(ILOAD, 4);
methodVisitor.visitMethodInsn(INVOKESPECIAL, "org/bouncycastle/crypto/engines/NoekeonEngine", "encryptBlock", "([BI[BI)I", false);
Label label4 = new Label();
methodVisitor.visitJumpInsn(GOTO, label4);
methodVisitor.visitLabel(label3);
methodVisitor.visitVarInsn(ALOAD, 0);
methodVisitor.visitVarInsn(ALOAD, 1);
methodVisitor.visitVarInsn(ILOAD, 2);
methodVisitor.visitVarInsn(ALOAD, 3);
methodVisitor.visitVarInsn(ILOAD, 4);
methodVisitor.visitMethodInsn(INVOKESPECIAL, "org/bouncycastle/crypto/engines/NoekeonEngine", "decryptBlock", "([BI[BI)I", false);
methodVisitor.visitLabel(label4);
methodVisitor.visitInsn(IRETURN);
methodVisitor.visitMaxs(5, 5);
methodVisitor.visitEnd();
}
{
methodVisitor = classWriter.visitMethod(ACC_PUBLIC, "reset", "()V", null, null);
methodVisitor.visitCode();
methodVisitor.visitInsn(RETURN);
methodVisitor.visitMaxs(0, 1);
methodVisitor.visitEnd();
}
{
methodVisitor = classWriter.visitMethod(ACC_PRIVATE, "setKey", "([B)V", null, null);
methodVisitor.visitCode();
methodVisitor.visitVarInsn(ALOAD, 0);
methodVisitor.visitFieldInsn(GETFIELD, "org/bouncycastle/crypto/engines/NoekeonEngine", "subKeys", "[I");
methodVisitor.visitInsn(ICONST_0);
methodVisitor.visitVarInsn(ALOAD, 0);
methodVisitor.visitVarInsn(ALOAD, 1);
methodVisitor.visitInsn(ICONST_0);
methodVisitor.visitMethodInsn(INVOKESPECIAL, "org/bouncycastle/crypto/engines/NoekeonEngine", "bytesToIntBig", "([BI)I", false);
methodVisitor.visitInsn(IASTORE);
methodVisitor.visitVarInsn(ALOAD, 0);
methodVisitor.visitFieldInsn(GETFIELD, "org/bouncycastle/crypto/engines/NoekeonEngine", "subKeys", "[I");
methodVisitor.visitInsn(ICONST_1);
methodVisitor.visitVarInsn(ALOAD, 0);
methodVisitor.visitVarInsn(ALOAD, 1);
methodVisitor.visitInsn(ICONST_4);
methodVisitor.visitMethodInsn(INVOKESPECIAL, "org/bouncycastle/crypto/engines/NoekeonEngine", "bytesToIntBig", "([BI)I", false);
methodVisitor.visitInsn(IASTORE);
methodVisitor.visitVarInsn(ALOAD, 0);
methodVisitor.visitFieldInsn(GETFIELD, "org/bouncycastle/crypto/engines/NoekeonEngine", "subKeys", "[I");
methodVisitor.visitInsn(ICONST_2);
methodVisitor.visitVarInsn(ALOAD, 0);
methodVisitor.visitVarInsn(ALOAD, 1);
methodVisitor.visitIntInsn(BIPUSH, 8);
methodVisitor.visitMethodInsn(INVOKESPECIAL, "org/bouncycastle/crypto/engines/NoekeonEngine", "bytesToIntBig", "([BI)I", false);
methodVisitor.visitInsn(IASTORE);
methodVisitor.visitVarInsn(ALOAD, 0);
methodVisitor.visitFieldInsn(GETFIELD, "org/bouncycastle/crypto/engines/NoekeonEngine", "subKeys", "[I");
methodVisitor.visitInsn(ICONST_3);
methodVisitor.visitVarInsn(ALOAD, 0);
methodVisitor.visitVarInsn(ALOAD, 1);
methodVisitor.visitIntInsn(BIPUSH, 12);
methodVisitor.visitMethodInsn(INVOKESPECIAL, "org/bouncycastle/crypto/engines/NoekeonEngine", "bytesToIntBig", "([BI)I", false);
methodVisitor.visitInsn(IASTORE);
methodVisitor.visitInsn(RETURN);
methodVisitor.visitMaxs(5, 2);
methodVisitor.visitEnd();
}
{
methodVisitor = classWriter.visitMethod(ACC_PRIVATE, "encryptBlock", "([BI[BI)I", null, null);
methodVisitor.visitCode();
methodVisitor.visitVarInsn(ALOAD, 0);
methodVisitor.visitFieldInsn(GETFIELD, "org/bouncycastle/crypto/engines/NoekeonEngine", "state", "[I");
methodVisitor.visitInsn(ICONST_0);
methodVisitor.visitVarInsn(ALOAD, 0);
methodVisitor.visitVarInsn(ALOAD, 1);
methodVisitor.visitVarInsn(ILOAD, 2);
methodVisitor.visitMethodInsn(INVOKESPECIAL, "org/bouncycastle/crypto/engines/NoekeonEngine", "bytesToIntBig", "([BI)I", false);
methodVisitor.visitInsn(IASTORE);
methodVisitor.visitVarInsn(ALOAD, 0);
methodVisitor.visitFieldInsn(GETFIELD, "org/bouncycastle/crypto/engines/NoekeonEngine", "state", "[I");
methodVisitor.visitInsn(ICONST_1);
methodVisitor.visitVarInsn(ALOAD, 0);
methodVisitor.visitVarInsn(ALOAD, 1);
methodVisitor.visitVarInsn(ILOAD, 2);
methodVisitor.visitInsn(ICONST_4);
methodVisitor.visitInsn(IADD);
methodVisitor.visitMethodInsn(INVOKESPECIAL, "org/bouncycastle/crypto/engines/NoekeonEngine", "bytesToIntBig", "([BI)I", false);
methodVisitor.visitInsn(IASTORE);
methodVisitor.visitVarInsn(ALOAD, 0);
methodVisitor.visitFieldInsn(GETFIELD, "org/bouncycastle/crypto/engines/NoekeonEngine", "state", "[I");
methodVisitor.visitInsn(ICONST_2);
methodVisitor.visitVarInsn(ALOAD, 0);
methodVisitor.visitVarInsn(ALOAD, 1);
methodVisitor.visitVarInsn(ILOAD, 2);
methodVisitor.visitIntInsn(BIPUSH, 8);
methodVisitor.visitInsn(IADD);
methodVisitor.visitMethodInsn(INVOKESPECIAL, "org/bouncycastle/crypto/engines/NoekeonEngine", "bytesToIntBig", "([BI)I", false);
methodVisitor.visitInsn(IASTORE);
methodVisitor.visitVarInsn(ALOAD, 0);
methodVisitor.visitFieldInsn(GETFIELD, "org/bouncycastle/crypto/engines/NoekeonEngine", "state", "[I");
methodVisitor.visitInsn(ICONST_3);
methodVisitor.visitVarInsn(ALOAD, 0);
methodVisitor.visitVarInsn(ALOAD, 1);
methodVisitor.visitVarInsn(ILOAD, 2);
methodVisitor.visitIntInsn(BIPUSH, 12);
methodVisitor.visitInsn(IADD);
methodVisitor.visitMethodInsn(INVOKESPECIAL, "org/bouncycastle/crypto/engines/NoekeonEngine", "bytesToIntBig", "([BI)I", false);
methodVisitor.visitInsn(IASTORE);
methodVisitor.visitInsn(ICONST_0);
methodVisitor.visitVarInsn(ISTORE, 5);
Label label0 = new Label();
methodVisitor.visitLabel(label0);
methodVisitor.visitVarInsn(ILOAD, 5);
methodVisitor.visitIntInsn(BIPUSH, 16);
Label label1 = new Label();
methodVisitor.visitJumpInsn(IF_ICMPGE, label1);
methodVisitor.visitVarInsn(ALOAD, 0);
methodVisitor.visitFieldInsn(GETFIELD, "org/bouncycastle/crypto/engines/NoekeonEngine", "state", "[I");
methodVisitor.visitInsn(ICONST_0);
methodVisitor.visitInsn(DUP2);
methodVisitor.visitInsn(IALOAD);
methodVisitor.visitFieldInsn(GETSTATIC, "org/bouncycastle/crypto/engines/NoekeonEngine", "roundConstants", "[I");
methodVisitor.visitVarInsn(ILOAD, 5);
methodVisitor.visitInsn(IALOAD);
methodVisitor.visitInsn(IXOR);
methodVisitor.visitInsn(IASTORE);
methodVisitor.visitVarInsn(ALOAD, 0);
methodVisitor.visitVarInsn(ALOAD, 0);
methodVisitor.visitFieldInsn(GETFIELD, "org/bouncycastle/crypto/engines/NoekeonEngine", "state", "[I");
methodVisitor.visitVarInsn(ALOAD, 0);
methodVisitor.visitFieldInsn(GETFIELD, "org/bouncycastle/crypto/engines/NoekeonEngine", "subKeys", "[I");
methodVisitor.visitMethodInsn(INVOKESPECIAL, "org/bouncycastle/crypto/engines/NoekeonEngine", "theta", "([I[I)V", false);
methodVisitor.visitVarInsn(ALOAD, 0);
methodVisitor.visitVarInsn(ALOAD, 0);
methodVisitor.visitFieldInsn(GETFIELD, "org/bouncycastle/crypto/engines/NoekeonEngine", "state", "[I");
methodVisitor.visitMethodInsn(INVOKESPECIAL, "org/bouncycastle/crypto/engines/NoekeonEngine", "pi1", "([I)V", false);
methodVisitor.visitVarInsn(ALOAD, 0);
methodVisitor.visitVarInsn(ALOAD, 0);
methodVisitor.visitFieldInsn(GETFIELD, "org/bouncycastle/crypto/engines/NoekeonEngine", "state", "[I");
methodVisitor.visitMethodInsn(INVOKESPECIAL, "org/bouncycastle/crypto/engines/NoekeonEngine", "gamma", "([I)V", false);
methodVisitor.visitVarInsn(ALOAD, 0);
methodVisitor.visitVarInsn(ALOAD, 0);
methodVisitor.visitFieldInsn(GETFIELD, "org/bouncycastle/crypto/engines/NoekeonEngine", "state", "[I");
methodVisitor.visitMethodInsn(INVOKESPECIAL, "org/bouncycastle/crypto/engines/NoekeonEngine", "pi2", "([I)V", false);
methodVisitor.visitIincInsn(5, 1);
methodVisitor.visitJumpInsn(GOTO, label0);
methodVisitor.visitLabel(label1);
methodVisitor.visitVarInsn(ALOAD, 0);
methodVisitor.visitFieldInsn(GETFIELD, "org/bouncycastle/crypto/engines/NoekeonEngine", "state", "[I");
methodVisitor.visitInsn(ICONST_0);
methodVisitor.visitInsn(DUP2);
methodVisitor.visitInsn(IALOAD);
methodVisitor.visitFieldInsn(GETSTATIC, "org/bouncycastle/crypto/engines/NoekeonEngine", "roundConstants", "[I");
methodVisitor.visitVarInsn(ILOAD, 5);
methodVisitor.visitInsn(IALOAD);
methodVisitor.visitInsn(IXOR);
methodVisitor.visitInsn(IASTORE);
methodVisitor.visitVarInsn(ALOAD, 0);
methodVisitor.visitVarInsn(ALOAD, 0);
methodVisitor.visitFieldInsn(GETFIELD, "org/bouncycastle/crypto/engines/NoekeonEngine", "state", "[I");
methodVisitor.visitVarInsn(ALOAD, 0);
methodVisitor.visitFieldInsn(GETFIELD, "org/bouncycastle/crypto/engines/NoekeonEngine", "subKeys", "[I");
methodVisitor.visitMethodInsn(INVOKESPECIAL, "org/bouncycastle/crypto/engines/NoekeonEngine", "theta", "([I[I)V", false);
methodVisitor.visitVarInsn(ALOAD, 0);
methodVisitor.visitVarInsn(ALOAD, 0);
methodVisitor.visitFieldInsn(GETFIELD, "org/bouncycastle/crypto/engines/NoekeonEngine", "state", "[I");
methodVisitor.visitInsn(ICONST_0);
methodVisitor.visitInsn(IALOAD);
methodVisitor.visitVarInsn(ALOAD, 3);
methodVisitor.visitVarInsn(ILOAD, 4);
methodVisitor.visitMethodInsn(INVOKESPECIAL, "org/bouncycastle/crypto/engines/NoekeonEngine", "intToBytesBig", "(I[BI)V", false);
methodVisitor.visitVarInsn(ALOAD, 0);
methodVisitor.visitVarInsn(ALOAD, 0);
methodVisitor.visitFieldInsn(GETFIELD, "org/bouncycastle/crypto/engines/NoekeonEngine", "state", "[I");
methodVisitor.visitInsn(ICONST_1);
methodVisitor.visitInsn(IALOAD);
methodVisitor.visitVarInsn(ALOAD, 3);
methodVisitor.visitVarInsn(ILOAD, 4);
methodVisitor.visitInsn(ICONST_4);
methodVisitor.visitInsn(IADD);
methodVisitor.visitMethodInsn(INVOKESPECIAL, "org/bouncycastle/crypto/engines/NoekeonEngine", "intToBytesBig", "(I[BI)V", false);
methodVisitor.visitVarInsn(ALOAD, 0);
methodVisitor.visitVarInsn(ALOAD, 0);
methodVisitor.visitFieldInsn(GETFIELD, "org/bouncycastle/crypto/engines/NoekeonEngine", "state", "[I");
methodVisitor.visitInsn(ICONST_2);
methodVisitor.visitInsn(IALOAD);
methodVisitor.visitVarInsn(ALOAD, 3);
methodVisitor.visitVarInsn(ILOAD, 4);
methodVisitor.visitIntInsn(BIPUSH, 8);
methodVisitor.visitInsn(IADD);
methodVisitor.visitMethodInsn(INVOKESPECIAL, "org/bouncycastle/crypto/engines/NoekeonEngine", "intToBytesBig", "(I[BI)V", false);
methodVisitor.visitVarInsn(ALOAD, 0);
methodVisitor.visitVarInsn(ALOAD, 0);
methodVisitor.visitFieldInsn(GETFIELD, "org/bouncycastle/crypto/engines/NoekeonEngine", "state", "[I");
methodVisitor.visitInsn(ICONST_3);
methodVisitor.visitInsn(IALOAD);
methodVisitor.visitVarInsn(ALOAD, 3);
methodVisitor.visitVarInsn(ILOAD, 4);
methodVisitor.visitIntInsn(BIPUSH, 12);
methodVisitor.visitInsn(IADD);
methodVisitor.visitMethodInsn(INVOKESPECIAL, "org/bouncycastle/crypto/engines/NoekeonEngine", "intToBytesBig", "(I[BI)V", false);
methodVisitor.visitIntInsn(BIPUSH, 16);
methodVisitor.visitInsn(IRETURN);
methodVisitor.visitMaxs(6, 6);
methodVisitor.visitEnd();
}
{
methodVisitor = classWriter.visitMethod(ACC_PRIVATE, "decryptBlock", "([BI[BI)I", null, null);
methodVisitor.visitCode();
methodVisitor.visitVarInsn(ALOAD, 0);
methodVisitor.visitFieldInsn(GETFIELD, "org/bouncycastle/crypto/engines/NoekeonEngine", "state", "[I");
methodVisitor.visitInsn(ICONST_0);
methodVisitor.visitVarInsn(ALOAD, 0);
methodVisitor.visitVarInsn(ALOAD, 1);
methodVisitor.visitVarInsn(ILOAD, 2);
methodVisitor.visitMethodInsn(INVOKESPECIAL, "org/bouncycastle/crypto/engines/NoekeonEngine", "bytesToIntBig", "([BI)I", false);
methodVisitor.visitInsn(IASTORE);
methodVisitor.visitVarInsn(ALOAD, 0);
methodVisitor.visitFieldInsn(GETFIELD, "org/bouncycastle/crypto/engines/NoekeonEngine", "state", "[I");
methodVisitor.visitInsn(ICONST_1);
methodVisitor.visitVarInsn(ALOAD, 0);
methodVisitor.visitVarInsn(ALOAD, 1);
methodVisitor.visitVarInsn(ILOAD, 2);
methodVisitor.visitInsn(ICONST_4);
methodVisitor.visitInsn(IADD);
methodVisitor.visitMethodInsn(INVOKESPECIAL, "org/bouncycastle/crypto/engines/NoekeonEngine", "bytesToIntBig", "([BI)I", false);
methodVisitor.visitInsn(IASTORE);
methodVisitor.visitVarInsn(ALOAD, 0);
methodVisitor.visitFieldInsn(GETFIELD, "org/bouncycastle/crypto/engines/NoekeonEngine", "state", "[I");
methodVisitor.visitInsn(ICONST_2);
methodVisitor.visitVarInsn(ALOAD, 0);
methodVisitor.visitVarInsn(ALOAD, 1);
methodVisitor.visitVarInsn(ILOAD, 2);
methodVisitor.visitIntInsn(BIPUSH, 8);
methodVisitor.visitInsn(IADD);
methodVisitor.visitMethodInsn(INVOKESPECIAL, "org/bouncycastle/crypto/engines/NoekeonEngine", "bytesToIntBig", "([BI)I", false);
methodVisitor.visitInsn(IASTORE);
methodVisitor.visitVarInsn(ALOAD, 0);
methodVisitor.visitFieldInsn(GETFIELD, "org/bouncycastle/crypto/engines/NoekeonEngine", "state", "[I");
methodVisitor.visitInsn(ICONST_3);
methodVisitor.visitVarInsn(ALOAD, 0);
methodVisitor.visitVarInsn(ALOAD, 1);
methodVisitor.visitVarInsn(ILOAD, 2);
methodVisitor.visitIntInsn(BIPUSH, 12);
methodVisitor.visitInsn(IADD);
methodVisitor.visitMethodInsn(INVOKESPECIAL, "org/bouncycastle/crypto/engines/NoekeonEngine", "bytesToIntBig", "([BI)I", false);
methodVisitor.visitInsn(IASTORE);
methodVisitor.visitVarInsn(ALOAD, 0);
methodVisitor.visitFieldInsn(GETFIELD, "org/bouncycastle/crypto/engines/NoekeonEngine", "subKeys", "[I");
methodVisitor.visitInsn(ICONST_0);
methodVisitor.visitVarInsn(ALOAD, 0);
methodVisitor.visitFieldInsn(GETFIELD, "org/bouncycastle/crypto/engines/NoekeonEngine", "decryptKeys", "[I");
methodVisitor.visitInsn(ICONST_0);
methodVisitor.visitVarInsn(ALOAD, 0);
methodVisitor.visitFieldInsn(GETFIELD, "org/bouncycastle/crypto/engines/NoekeonEngine", "subKeys", "[I");
methodVisitor.visitInsn(ARRAYLENGTH);
methodVisitor.visitMethodInsn(INVOKESTATIC, "java/lang/System", "arraycopy", "(Ljava/lang/Object;ILjava/lang/Object;II)V", false);
methodVisitor.visitVarInsn(ALOAD, 0);
methodVisitor.visitVarInsn(ALOAD, 0);
methodVisitor.visitFieldInsn(GETFIELD, "org/bouncycastle/crypto/engines/NoekeonEngine", "decryptKeys", "[I");
methodVisitor.visitFieldInsn(GETSTATIC, "org/bouncycastle/crypto/engines/NoekeonEngine", "nullVector", "[I");
methodVisitor.visitMethodInsn(INVOKESPECIAL, "org/bouncycastle/crypto/engines/NoekeonEngine", "theta", "([I[I)V", false);
methodVisitor.visitIntInsn(BIPUSH, 16);
methodVisitor.visitVarInsn(ISTORE, 5);
Label label0 = new Label();
methodVisitor.visitLabel(label0);
methodVisitor.visitVarInsn(ILOAD, 5);
Label label1 = new Label();
methodVisitor.visitJumpInsn(IFLE, label1);
methodVisitor.visitVarInsn(ALOAD, 0);
methodVisitor.visitVarInsn(ALOAD, 0);
methodVisitor.visitFieldInsn(GETFIELD, "org/bouncycastle/crypto/engines/NoekeonEngine", "state", "[I");
methodVisitor.visitVarInsn(ALOAD, 0);
methodVisitor.visitFieldInsn(GETFIELD, "org/bouncycastle/crypto/engines/NoekeonEngine", "decryptKeys", "[I");
methodVisitor.visitMethodInsn(INVOKESPECIAL, "org/bouncycastle/crypto/engines/NoekeonEngine", "theta", "([I[I)V", false);
methodVisitor.visitVarInsn(ALOAD, 0);
methodVisitor.visitFieldInsn(GETFIELD, "org/bouncycastle/crypto/engines/NoekeonEngine", "state", "[I");
methodVisitor.visitInsn(ICONST_0);
methodVisitor.visitInsn(DUP2);
methodVisitor.visitInsn(IALOAD);
methodVisitor.visitFieldInsn(GETSTATIC, "org/bouncycastle/crypto/engines/NoekeonEngine", "roundConstants", "[I");
methodVisitor.visitVarInsn(ILOAD, 5);
methodVisitor.visitInsn(IALOAD);
methodVisitor.visitInsn(IXOR);
methodVisitor.visitInsn(IASTORE);
methodVisitor.visitVarInsn(ALOAD, 0);
methodVisitor.visitVarInsn(ALOAD, 0);
methodVisitor.visitFieldInsn(GETFIELD, "org/bouncycastle/crypto/engines/NoekeonEngine", "state", "[I");
methodVisitor.visitMethodInsn(INVOKESPECIAL, "org/bouncycastle/crypto/engines/NoekeonEngine", "pi1", "([I)V", false);
methodVisitor.visitVarInsn(ALOAD, 0);
methodVisitor.visitVarInsn(ALOAD, 0);
methodVisitor.visitFieldInsn(GETFIELD, "org/bouncycastle/crypto/engines/NoekeonEngine", "state", "[I");
methodVisitor.visitMethodInsn(INVOKESPECIAL, "org/bouncycastle/crypto/engines/NoekeonEngine", "gamma", "([I)V", false);
methodVisitor.visitVarInsn(ALOAD, 0);
methodVisitor.visitVarInsn(ALOAD, 0);
methodVisitor.visitFieldInsn(GETFIELD, "org/bouncycastle/crypto/engines/NoekeonEngine", "state", "[I");
methodVisitor.visitMethodInsn(INVOKESPECIAL, "org/bouncycastle/crypto/engines/NoekeonEngine", "pi2", "([I)V", false);
methodVisitor.visitIincInsn(5, -1);
methodVisitor.visitJumpInsn(GOTO, label0);
methodVisitor.visitLabel(label1);
methodVisitor.visitVarInsn(ALOAD, 0);
methodVisitor.visitVarInsn(ALOAD, 0);
methodVisitor.visitFieldInsn(GETFIELD, "org/bouncycastle/crypto/engines/NoekeonEngine", "state", "[I");
methodVisitor.visitVarInsn(ALOAD, 0);
methodVisitor.visitFieldInsn(GETFIELD, "org/bouncycastle/crypto/engines/NoekeonEngine", "decryptKeys", "[I");
methodVisitor.visitMethodInsn(INVOKESPECIAL, "org/bouncycastle/crypto/engines/NoekeonEngine", "theta", "([I[I)V", false);
methodVisitor.visitVarInsn(ALOAD, 0);
methodVisitor.visitFieldInsn(GETFIELD, "org/bouncycastle/crypto/engines/NoekeonEngine", "state", "[I");
methodVisitor.visitInsn(ICONST_0);
methodVisitor.visitInsn(DUP2);
methodVisitor.visitInsn(IALOAD);
methodVisitor.visitFieldInsn(GETSTATIC, "org/bouncycastle/crypto/engines/NoekeonEngine", "roundConstants", "[I");
methodVisitor.visitVarInsn(ILOAD, 5);
methodVisitor.visitInsn(IALOAD);
methodVisitor.visitInsn(IXOR);
methodVisitor.visitInsn(IASTORE);
methodVisitor.visitVarInsn(ALOAD, 0);
methodVisitor.visitVarInsn(ALOAD, 0);
methodVisitor.visitFieldInsn(GETFIELD, "org/bouncycastle/crypto/engines/NoekeonEngine", "state", "[I");
methodVisitor.visitInsn(ICONST_0);
methodVisitor.visitInsn(IALOAD);
methodVisitor.visitVarInsn(ALOAD, 3);
methodVisitor.visitVarInsn(ILOAD, 4);
methodVisitor.visitMethodInsn(INVOKESPECIAL, "org/bouncycastle/crypto/engines/NoekeonEngine", "intToBytesBig", "(I[BI)V", false);
methodVisitor.visitVarInsn(ALOAD, 0);
methodVisitor.visitVarInsn(ALOAD, 0);
methodVisitor.visitFieldInsn(GETFIELD, "org/bouncycastle/crypto/engines/NoekeonEngine", "state", "[I");
methodVisitor.visitInsn(ICONST_1);
methodVisitor.visitInsn(IALOAD);
methodVisitor.visitVarInsn(ALOAD, 3);
methodVisitor.visitVarInsn(ILOAD, 4);
methodVisitor.visitInsn(ICONST_4);
methodVisitor.visitInsn(IADD);
methodVisitor.visitMethodInsn(INVOKESPECIAL, "org/bouncycastle/crypto/engines/NoekeonEngine", "intToBytesBig", "(I[BI)V", false);
methodVisitor.visitVarInsn(ALOAD, 0);
methodVisitor.visitVarInsn(ALOAD, 0);
methodVisitor.visitFieldInsn(GETFIELD, "org/bouncycastle/crypto/engines/NoekeonEngine", "state", "[I");
methodVisitor.visitInsn(ICONST_2);
methodVisitor.visitInsn(IALOAD);
methodVisitor.visitVarInsn(ALOAD, 3);
methodVisitor.visitVarInsn(ILOAD, 4);
methodVisitor.visitIntInsn(BIPUSH, 8);
methodVisitor.visitInsn(IADD);
methodVisitor.visitMethodInsn(INVOKESPECIAL, "org/bouncycastle/crypto/engines/NoekeonEngine", "intToBytesBig", "(I[BI)V", false);
methodVisitor.visitVarInsn(ALOAD, 0);
methodVisitor.visitVarInsn(ALOAD, 0);
methodVisitor.visitFieldInsn(GETFIELD, "org/bouncycastle/crypto/engines/NoekeonEngine", "state", "[I");
methodVisitor.visitInsn(ICONST_3);
methodVisitor.visitInsn(IALOAD);
methodVisitor.visitVarInsn(ALOAD, 3);
methodVisitor.visitVarInsn(ILOAD, 4);
methodVisitor.visitIntInsn(BIPUSH, 12);
methodVisitor.visitInsn(IADD);
methodVisitor.visitMethodInsn(INVOKESPECIAL, "org/bouncycastle/crypto/engines/NoekeonEngine", "intToBytesBig", "(I[BI)V", false);
methodVisitor.visitIntInsn(BIPUSH, 16);
methodVisitor.visitInsn(IRETURN);
methodVisitor.visitMaxs(6, 6);
methodVisitor.visitEnd();
}
{
methodVisitor = classWriter.visitMethod(ACC_PRIVATE, "gamma", "([I)V", null, null);
methodVisitor.visitCode();
methodVisitor.visitVarInsn(ALOAD, 1);
methodVisitor.visitInsn(ICONST_1);
methodVisitor.visitInsn(DUP2);
methodVisitor.visitInsn(IALOAD);
methodVisitor.visitVarInsn(ALOAD, 1);
methodVisitor.visitInsn(ICONST_3);
methodVisitor.visitInsn(IALOAD);
methodVisitor.visitInsn(ICONST_M1);
methodVisitor.visitInsn(IXOR);
methodVisitor.visitVarInsn(ALOAD, 1);
methodVisitor.visitInsn(ICONST_2);
methodVisitor.visitInsn(IALOAD);
methodVisitor.visitInsn(ICONST_M1);
methodVisitor.visitInsn(IXOR);
methodVisitor.visitInsn(IAND);
methodVisitor.visitInsn(IXOR);
methodVisitor.visitInsn(IASTORE);
methodVisitor.visitVarInsn(ALOAD, 1);
methodVisitor.visitInsn(ICONST_0);
methodVisitor.visitInsn(DUP2);
methodVisitor.visitInsn(IALOAD);
methodVisitor.visitVarInsn(ALOAD, 1);
methodVisitor.visitInsn(ICONST_2);
methodVisitor.visitInsn(IALOAD);
methodVisitor.visitVarInsn(ALOAD, 1);
methodVisitor.visitInsn(ICONST_1);
methodVisitor.visitInsn(IALOAD);
methodVisitor.visitInsn(IAND);
methodVisitor.visitInsn(IXOR);
methodVisitor.visitInsn(IASTORE);
methodVisitor.visitVarInsn(ALOAD, 1);
methodVisitor.visitInsn(ICONST_3);
methodVisitor.visitInsn(IALOAD);
methodVisitor.visitVarInsn(ISTORE, 2);
methodVisitor.visitVarInsn(ALOAD, 1);
methodVisitor.visitInsn(ICONST_3);
methodVisitor.visitVarInsn(ALOAD, 1);
methodVisitor.visitInsn(ICONST_0);
methodVisitor.visitInsn(IALOAD);
methodVisitor.visitInsn(IASTORE);
methodVisitor.visitVarInsn(ALOAD, 1);
methodVisitor.visitInsn(ICONST_0);
methodVisitor.visitVarInsn(ILOAD, 2);
methodVisitor.visitInsn(IASTORE);
methodVisitor.visitVarInsn(ALOAD, 1);
methodVisitor.visitInsn(ICONST_2);
methodVisitor.visitInsn(DUP2);
methodVisitor.visitInsn(IALOAD);
methodVisitor.visitVarInsn(ALOAD, 1);
methodVisitor.visitInsn(ICONST_0);
methodVisitor.visitInsn(IALOAD);
methodVisitor.visitVarInsn(ALOAD, 1);
methodVisitor.visitInsn(ICONST_1);
methodVisitor.visitInsn(IALOAD);
methodVisitor.visitInsn(IXOR);
methodVisitor.visitVarInsn(ALOAD, 1);
methodVisitor.visitInsn(ICONST_3);
methodVisitor.visitInsn(IALOAD);
methodVisitor.visitInsn(IXOR);
methodVisitor.visitInsn(IXOR);
methodVisitor.visitInsn(IASTORE);
methodVisitor.visitVarInsn(ALOAD, 1);
methodVisitor.visitInsn(ICONST_1);
methodVisitor.visitInsn(DUP2);
methodVisitor.visitInsn(IALOAD);
methodVisitor.visitVarInsn(ALOAD, 1);
methodVisitor.visitInsn(ICONST_3);
methodVisitor.visitInsn(IALOAD);
methodVisitor.visitInsn(ICONST_M1);
methodVisitor.visitInsn(IXOR);
methodVisitor.visitVarInsn(ALOAD, 1);
methodVisitor.visitInsn(ICONST_2);
methodVisitor.visitInsn(IALOAD);
methodVisitor.visitInsn(ICONST_M1);
methodVisitor.visitInsn(IXOR);
methodVisitor.visitInsn(IAND);
methodVisitor.visitInsn(IXOR);
methodVisitor.visitInsn(IASTORE);
methodVisitor.visitVarInsn(ALOAD, 1);
methodVisitor.visitInsn(ICONST_0);
methodVisitor.visitInsn(DUP2);
methodVisitor.visitInsn(IALOAD);
methodVisitor.visitVarInsn(ALOAD, 1);
methodVisitor.visitInsn(ICONST_2);
methodVisitor.visitInsn(IALOAD);
methodVisitor.visitVarInsn(ALOAD, 1);
methodVisitor.visitInsn(ICONST_1);
methodVisitor.visitInsn(IALOAD);
methodVisitor.visitInsn(IAND);
methodVisitor.visitInsn(IXOR);
methodVisitor.visitInsn(IASTORE);
methodVisitor.visitInsn(RETURN);
methodVisitor.visitMaxs(6, 3);
methodVisitor.visitEnd();
}
{
methodVisitor = classWriter.visitMethod(ACC_PRIVATE, "theta", "([I[I)V", null, null);
methodVisitor.visitCode();
methodVisitor.visitVarInsn(ALOAD, 1);
methodVisitor.visitInsn(ICONST_0);
methodVisitor.visitInsn(IALOAD);
methodVisitor.visitVarInsn(ALOAD, 1);
methodVisitor.visitInsn(ICONST_2);
methodVisitor.visitInsn(IALOAD);
methodVisitor.visitInsn(IXOR);
methodVisitor.visitVarInsn(ISTORE, 3);
methodVisitor.visitVarInsn(ILOAD, 3);
methodVisitor.visitVarInsn(ALOAD, 0);
methodVisitor.visitVarInsn(ILOAD, 3);
methodVisitor.visitIntInsn(BIPUSH, 8);
methodVisitor.visitMethodInsn(INVOKESPECIAL, "org/bouncycastle/crypto/engines/NoekeonEngine", "rotl", "(II)I", false);
methodVisitor.visitVarInsn(ALOAD, 0);
methodVisitor.visitVarInsn(ILOAD, 3);
methodVisitor.visitIntInsn(BIPUSH, 24);
methodVisitor.visitMethodInsn(INVOKESPECIAL, "org/bouncycastle/crypto/engines/NoekeonEngine", "rotl", "(II)I", false);
methodVisitor.visitInsn(IXOR);
methodVisitor.visitInsn(IXOR);
methodVisitor.visitVarInsn(ISTORE, 3);
methodVisitor.visitVarInsn(ALOAD, 1);
methodVisitor.visitInsn(ICONST_1);
methodVisitor.visitInsn(DUP2);
methodVisitor.visitInsn(IALOAD);
methodVisitor.visitVarInsn(ILOAD, 3);
methodVisitor.visitInsn(IXOR);
methodVisitor.visitInsn(IASTORE);
methodVisitor.visitVarInsn(ALOAD, 1);
methodVisitor.visitInsn(ICONST_3);
methodVisitor.visitInsn(DUP2);
methodVisitor.visitInsn(IALOAD);
methodVisitor.visitVarInsn(ILOAD, 3);
methodVisitor.visitInsn(IXOR);
methodVisitor.visitInsn(IASTORE);
methodVisitor.visitInsn(ICONST_0);
methodVisitor.visitVarInsn(ISTORE, 4);
Label label0 = new Label();
methodVisitor.visitLabel(label0);
methodVisitor.visitVarInsn(ILOAD, 4);
methodVisitor.visitInsn(ICONST_4);
Label label1 = new Label();
methodVisitor.visitJumpInsn(IF_ICMPGE, label1);
methodVisitor.visitVarInsn(ALOAD, 1);
methodVisitor.visitVarInsn(ILOAD, 4);
methodVisitor.visitInsn(DUP2);
methodVisitor.visitInsn(IALOAD);
methodVisitor.visitVarInsn(ALOAD, 2);
methodVisitor.visitVarInsn(ILOAD, 4);
methodVisitor.visitInsn(IALOAD);
methodVisitor.visitInsn(IXOR);
methodVisitor.visitInsn(IASTORE);
methodVisitor.visitIincInsn(4, 1);
methodVisitor.visitJumpInsn(GOTO, label0);
methodVisitor.visitLabel(label1);
methodVisitor.visitVarInsn(ALOAD, 1);
methodVisitor.visitInsn(ICONST_1);
methodVisitor.visitInsn(IALOAD);
methodVisitor.visitVarInsn(ALOAD, 1);
methodVisitor.visitInsn(ICONST_3);
methodVisitor.visitInsn(IALOAD);
methodVisitor.visitInsn(IXOR);
methodVisitor.visitVarInsn(ISTORE, 3);
methodVisitor.visitVarInsn(ILOAD, 3);
methodVisitor.visitVarInsn(ALOAD, 0);
methodVisitor.visitVarInsn(ILOAD, 3);
methodVisitor.visitIntInsn(BIPUSH, 8);
methodVisitor.visitMethodInsn(INVOKESPECIAL, "org/bouncycastle/crypto/engines/NoekeonEngine", "rotl", "(II)I", false);
methodVisitor.visitVarInsn(ALOAD, 0);
methodVisitor.visitVarInsn(ILOAD, 3);
methodVisitor.visitIntInsn(BIPUSH, 24);
methodVisitor.visitMethodInsn(INVOKESPECIAL, "org/bouncycastle/crypto/engines/NoekeonEngine", "rotl", "(II)I", false);
methodVisitor.visitInsn(IXOR);
methodVisitor.visitInsn(IXOR);
methodVisitor.visitVarInsn(ISTORE, 3);
methodVisitor.visitVarInsn(ALOAD, 1);
methodVisitor.visitInsn(ICONST_0);
methodVisitor.visitInsn(DUP2);
methodVisitor.visitInsn(IALOAD);
methodVisitor.visitVarInsn(ILOAD, 3);
methodVisitor.visitInsn(IXOR);
methodVisitor.visitInsn(IASTORE);
methodVisitor.visitVarInsn(ALOAD, 1);
methodVisitor.visitInsn(ICONST_2);
methodVisitor.visitInsn(DUP2);
methodVisitor.visitInsn(IALOAD);
methodVisitor.visitVarInsn(ILOAD, 3);
methodVisitor.visitInsn(IXOR);
methodVisitor.visitInsn(IASTORE);
methodVisitor.visitInsn(RETURN);
methodVisitor.visitMaxs(5, 5);
methodVisitor.visitEnd();
}
{
methodVisitor = classWriter.visitMethod(ACC_PRIVATE, "pi1", "([I)V", null, null);
methodVisitor.visitCode();
methodVisitor.visitVarInsn(ALOAD, 1);
methodVisitor.visitInsn(ICONST_1);
methodVisitor.visitVarInsn(ALOAD, 0);
methodVisitor.visitVarInsn(ALOAD, 1);
methodVisitor.visitInsn(ICONST_1);
methodVisitor.visitInsn(IALOAD);
methodVisitor.visitInsn(ICONST_1);
methodVisitor.visitMethodInsn(INVOKESPECIAL, "org/bouncycastle/crypto/engines/NoekeonEngine", "rotl", "(II)I", false);
methodVisitor.visitInsn(IASTORE);
methodVisitor.visitVarInsn(ALOAD, 1);
methodVisitor.visitInsn(ICONST_2);
methodVisitor.visitVarInsn(ALOAD, 0);
methodVisitor.visitVarInsn(ALOAD, 1);
methodVisitor.visitInsn(ICONST_2);
methodVisitor.visitInsn(IALOAD);
methodVisitor.visitInsn(ICONST_5);
methodVisitor.visitMethodInsn(INVOKESPECIAL, "org/bouncycastle/crypto/engines/NoekeonEngine", "rotl", "(II)I", false);
methodVisitor.visitInsn(IASTORE);
methodVisitor.visitVarInsn(ALOAD, 1);
methodVisitor.visitInsn(ICONST_3);
methodVisitor.visitVarInsn(ALOAD, 0);
methodVisitor.visitVarInsn(ALOAD, 1);
methodVisitor.visitInsn(ICONST_3);
methodVisitor.visitInsn(IALOAD);
methodVisitor.visitInsn(ICONST_2);
methodVisitor.visitMethodInsn(INVOKESPECIAL, "org/bouncycastle/crypto/engines/NoekeonEngine", "rotl", "(II)I", false);
methodVisitor.visitInsn(IASTORE);
methodVisitor.visitInsn(RETURN);
methodVisitor.visitMaxs(5, 2);
methodVisitor.visitEnd();
}
{
methodVisitor = classWriter.visitMethod(ACC_PRIVATE, "pi2", "([I)V", null, null);
methodVisitor.visitCode();
methodVisitor.visitVarInsn(ALOAD, 1);
methodVisitor.visitInsn(ICONST_1);
methodVisitor.visitVarInsn(ALOAD, 0);
methodVisitor.visitVarInsn(ALOAD, 1);
methodVisitor.visitInsn(ICONST_1);
methodVisitor.visitInsn(IALOAD);
methodVisitor.visitIntInsn(BIPUSH, 31);
methodVisitor.visitMethodInsn(INVOKESPECIAL, "org/bouncycastle/crypto/engines/NoekeonEngine", "rotl", "(II)I", false);
methodVisitor.visitInsn(IASTORE);
methodVisitor.visitVarInsn(ALOAD, 1);
methodVisitor.visitInsn(ICONST_2);
methodVisitor.visitVarInsn(ALOAD, 0);
methodVisitor.visitVarInsn(ALOAD, 1);
methodVisitor.visitInsn(ICONST_2);
methodVisitor.visitInsn(IALOAD);
methodVisitor.visitIntInsn(BIPUSH, 27);
methodVisitor.visitMethodInsn(INVOKESPECIAL, "org/bouncycastle/crypto/engines/NoekeonEngine", "rotl", "(II)I", false);
methodVisitor.visitInsn(IASTORE);
methodVisitor.visitVarInsn(ALOAD, 1);
methodVisitor.visitInsn(ICONST_3);
methodVisitor.visitVarInsn(ALOAD, 0);
methodVisitor.visitVarInsn(ALOAD, 1);
methodVisitor.visitInsn(ICONST_3);
methodVisitor.visitInsn(IALOAD);
methodVisitor.visitIntInsn(BIPUSH, 30);
methodVisitor.visitMethodInsn(INVOKESPECIAL, "org/bouncycastle/crypto/engines/NoekeonEngine", "rotl", "(II)I", false);
methodVisitor.visitInsn(IASTORE);
methodVisitor.visitInsn(RETURN);
methodVisitor.visitMaxs(5, 2);
methodVisitor.visitEnd();
}
{
methodVisitor = classWriter.visitMethod(ACC_PRIVATE, "bytesToIntBig", "([BI)I", null, null);
methodVisitor.visitCode();
methodVisitor.visitVarInsn(ALOAD, 1);
methodVisitor.visitVarInsn(ILOAD, 2);
methodVisitor.visitIincInsn(2, 1);
methodVisitor.visitInsn(BALOAD);
methodVisitor.visitIntInsn(BIPUSH, 24);
methodVisitor.visitInsn(ISHL);
methodVisitor.visitVarInsn(ALOAD, 1);
methodVisitor.visitVarInsn(ILOAD, 2);
methodVisitor.visitIincInsn(2, 1);
methodVisitor.visitInsn(BALOAD);
methodVisitor.visitIntInsn(SIPUSH, 255);
methodVisitor.visitInsn(IAND);
methodVisitor.visitIntInsn(BIPUSH, 16);
methodVisitor.visitInsn(ISHL);
methodVisitor.visitInsn(IOR);
methodVisitor.visitVarInsn(ALOAD, 1);
methodVisitor.visitVarInsn(ILOAD, 2);
methodVisitor.visitIincInsn(2, 1);
methodVisitor.visitInsn(BALOAD);
methodVisitor.visitIntInsn(SIPUSH, 255);
methodVisitor.visitInsn(IAND);
methodVisitor.visitIntInsn(BIPUSH, 8);
methodVisitor.visitInsn(ISHL);
methodVisitor.visitInsn(IOR);
methodVisitor.visitVarInsn(ALOAD, 1);
methodVisitor.visitVarInsn(ILOAD, 2);
methodVisitor.visitInsn(BALOAD);
methodVisitor.visitIntInsn(SIPUSH, 255);
methodVisitor.visitInsn(IAND);
methodVisitor.visitInsn(IOR);
methodVisitor.visitInsn(IRETURN);
methodVisitor.visitMaxs(3, 3);
methodVisitor.visitEnd();
}
{
methodVisitor = classWriter.visitMethod(ACC_PRIVATE, "intToBytesBig", "(I[BI)V", null, null);
methodVisitor.visitCode();
methodVisitor.visitVarInsn(ALOAD, 2);
methodVisitor.visitVarInsn(ILOAD, 3);
methodVisitor.visitIincInsn(3, 1);
methodVisitor.visitVarInsn(ILOAD, 1);
methodVisitor.visitIntInsn(BIPUSH, 24);
methodVisitor.visitInsn(IUSHR);
methodVisitor.visitInsn(I2B);
methodVisitor.visitInsn(BASTORE);
methodVisitor.visitVarInsn(ALOAD, 2);
methodVisitor.visitVarInsn(ILOAD, 3);
methodVisitor.visitIincInsn(3, 1);
methodVisitor.visitVarInsn(ILOAD, 1);
methodVisitor.visitIntInsn(BIPUSH, 16);
methodVisitor.visitInsn(IUSHR);
methodVisitor.visitInsn(I2B);
methodVisitor.visitInsn(BASTORE);
methodVisitor.visitVarInsn(ALOAD, 2);
methodVisitor.visitVarInsn(ILOAD, 3);
methodVisitor.visitIincInsn(3, 1);
methodVisitor.visitVarInsn(ILOAD, 1);
methodVisitor.visitIntInsn(BIPUSH, 8);
methodVisitor.visitInsn(IUSHR);
methodVisitor.visitInsn(I2B);
methodVisitor.visitInsn(BASTORE);
methodVisitor.visitVarInsn(ALOAD, 2);
methodVisitor.visitVarInsn(ILOAD, 3);
methodVisitor.visitVarInsn(ILOAD, 1);
methodVisitor.visitInsn(I2B);
methodVisitor.visitInsn(BASTORE);
methodVisitor.visitInsn(RETURN);
methodVisitor.visitMaxs(4, 4);
methodVisitor.visitEnd();
}
{
methodVisitor = classWriter.visitMethod(ACC_PRIVATE, "rotl", "(II)I", null, null);
methodVisitor.visitCode();
methodVisitor.visitVarInsn(ILOAD, 1);
methodVisitor.visitVarInsn(ILOAD, 2);
methodVisitor.visitInsn(ISHL);
methodVisitor.visitVarInsn(ILOAD, 1);
methodVisitor.visitIntInsn(BIPUSH, 32);
methodVisitor.visitVarInsn(ILOAD, 2);
methodVisitor.visitInsn(ISUB);
methodVisitor.visitInsn(IUSHR);
methodVisitor.visitInsn(IOR);
methodVisitor.visitInsn(IRETURN);
methodVisitor.visitMaxs(4, 3);
methodVisitor.visitEnd();
}
{
methodVisitor = classWriter.visitMethod(ACC_STATIC, "<clinit>", "()V", null, null);
methodVisitor.visitCode();
methodVisitor.visitInsn(ICONST_4);
methodVisitor.visitIntInsn(NEWARRAY, T_INT);
methodVisitor.visitInsn(DUP);
methodVisitor.visitInsn(ICONST_0);
methodVisitor.visitInsn(ICONST_0);
methodVisitor.visitInsn(IASTORE);
methodVisitor.visitInsn(DUP);
methodVisitor.visitInsn(ICONST_1);
methodVisitor.visitInsn(ICONST_0);
methodVisitor.visitInsn(IASTORE);
methodVisitor.visitInsn(DUP);
methodVisitor.visitInsn(ICONST_2);
methodVisitor.visitInsn(ICONST_0);
methodVisitor.visitInsn(IASTORE);
methodVisitor.visitInsn(DUP);
methodVisitor.visitInsn(ICONST_3);
methodVisitor.visitInsn(ICONST_0);
methodVisitor.visitInsn(IASTORE);
methodVisitor.visitFieldInsn(PUTSTATIC, "org/bouncycastle/crypto/engines/NoekeonEngine", "nullVector", "[I");
methodVisitor.visitIntInsn(BIPUSH, 17);
methodVisitor.visitIntInsn(NEWARRAY, T_INT);
methodVisitor.visitInsn(DUP);
methodVisitor.visitInsn(ICONST_0);
methodVisitor.visitIntInsn(SIPUSH, 128);
methodVisitor.visitInsn(IASTORE);
methodVisitor.visitInsn(DUP);
methodVisitor.visitInsn(ICONST_1);
methodVisitor.visitIntInsn(BIPUSH, 27);
methodVisitor.visitInsn(IASTORE);
methodVisitor.visitInsn(DUP);
methodVisitor.visitInsn(ICONST_2);
methodVisitor.visitIntInsn(BIPUSH, 54);
methodVisitor.visitInsn(IASTORE);
methodVisitor.visitInsn(DUP);
methodVisitor.visitInsn(ICONST_3);
methodVisitor.visitIntInsn(BIPUSH, 108);
methodVisitor.visitInsn(IASTORE);
methodVisitor.visitInsn(DUP);
methodVisitor.visitInsn(ICONST_4);
methodVisitor.visitIntInsn(SIPUSH, 216);
methodVisitor.visitInsn(IASTORE);
methodVisitor.visitInsn(DUP);
methodVisitor.visitInsn(ICONST_5);
methodVisitor.visitIntInsn(SIPUSH, 171);
methodVisitor.visitInsn(IASTORE);
methodVisitor.visitInsn(DUP);
methodVisitor.visitIntInsn(BIPUSH, 6);
methodVisitor.visitIntInsn(BIPUSH, 77);
methodVisitor.visitInsn(IASTORE);
methodVisitor.visitInsn(DUP);
methodVisitor.visitIntInsn(BIPUSH, 7);
methodVisitor.visitIntInsn(SIPUSH, 154);
methodVisitor.visitInsn(IASTORE);
methodVisitor.visitInsn(DUP);
methodVisitor.visitIntInsn(BIPUSH, 8);
methodVisitor.visitIntInsn(BIPUSH, 47);
methodVisitor.visitInsn(IASTORE);
methodVisitor.visitInsn(DUP);
methodVisitor.visitIntInsn(BIPUSH, 9);
methodVisitor.visitIntInsn(BIPUSH, 94);
methodVisitor.visitInsn(IASTORE);
methodVisitor.visitInsn(DUP);
methodVisitor.visitIntInsn(BIPUSH, 10);
methodVisitor.visitIntInsn(SIPUSH, 188);
methodVisitor.visitInsn(IASTORE);
methodVisitor.visitInsn(DUP);
methodVisitor.visitIntInsn(BIPUSH, 11);
methodVisitor.visitIntInsn(BIPUSH, 99);
methodVisitor.visitInsn(IASTORE);
methodVisitor.visitInsn(DUP);
methodVisitor.visitIntInsn(BIPUSH, 12);
methodVisitor.visitIntInsn(SIPUSH, 198);
methodVisitor.visitInsn(IASTORE);
methodVisitor.visitInsn(DUP);
methodVisitor.visitIntInsn(BIPUSH, 13);
methodVisitor.visitIntInsn(SIPUSH, 151);
methodVisitor.visitInsn(IASTORE);
methodVisitor.visitInsn(DUP);
methodVisitor.visitIntInsn(BIPUSH, 14);
methodVisitor.visitIntInsn(BIPUSH, 53);
methodVisitor.visitInsn(IASTORE);
methodVisitor.visitInsn(DUP);
methodVisitor.visitIntInsn(BIPUSH, 15);
methodVisitor.visitIntInsn(BIPUSH, 106);
methodVisitor.visitInsn(IASTORE);
methodVisitor.visitInsn(DUP);
methodVisitor.visitIntInsn(BIPUSH, 16);
methodVisitor.visitIntInsn(SIPUSH, 212);
methodVisitor.visitInsn(IASTORE);
methodVisitor.visitFieldInsn(PUTSTATIC, "org/bouncycastle/crypto/engines/NoekeonEngine", "roundConstants", "[I");
methodVisitor.visitInsn(RETURN);
methodVisitor.visitMaxs(4, 0);
methodVisitor.visitEnd();
}
classWriter.visitEnd();

return classWriter.toByteArray();
}
}
