package asm.org.apache.activemq.util;
import org.objectweb.asm.AnnotationVisitor;
import org.objectweb.asm.Attribute;
import org.objectweb.asm.ClassReader;
import org.objectweb.asm.ClassWriter;
import org.objectweb.asm.ConstantDynamic;
import org.objectweb.asm.FieldVisitor;
import org.objectweb.asm.Handle;
import org.objectweb.asm.Label;
import org.objectweb.asm.MethodVisitor;
import org.objectweb.asm.Opcodes;
import org.objectweb.asm.RecordComponentVisitor;
import org.objectweb.asm.Type;
import org.objectweb.asm.TypePath;
public class JenkinsHashDump implements Opcodes {

public static byte[] dump () throws Exception {

ClassWriter classWriter = new ClassWriter(0);
FieldVisitor fieldVisitor;
RecordComponentVisitor recordComponentVisitor;
MethodVisitor methodVisitor;
AnnotationVisitor annotationVisitor0;

classWriter.visit(V1_8, ACC_PUBLIC | ACC_SUPER, "org/apache/activemq/util/JenkinsHash", null, "java/lang/Object", null);

{
fieldVisitor = classWriter.visitField(ACC_PRIVATE | ACC_FINAL | ACC_STATIC, "INT_MASK", "J", null, new Long(4294967295L));
fieldVisitor.visitEnd();
}
{
fieldVisitor = classWriter.visitField(ACC_PRIVATE | ACC_FINAL | ACC_STATIC, "BYTE_MASK", "J", null, new Long(255L));
fieldVisitor.visitEnd();
}
{
fieldVisitor = classWriter.visitField(ACC_PRIVATE | ACC_FINAL | ACC_STATIC, "_instance", "Lorg/apache/activemq/util/JenkinsHash;", null, null);
fieldVisitor.visitEnd();
}
{
methodVisitor = classWriter.visitMethod(ACC_PUBLIC, "<init>", "()V", null, null);
methodVisitor.visitCode();
methodVisitor.visitVarInsn(ALOAD, 0);
methodVisitor.visitMethodInsn(INVOKESPECIAL, "java/lang/Object", "<init>", "()V", false);
methodVisitor.visitInsn(RETURN);
methodVisitor.visitMaxs(1, 1);
methodVisitor.visitEnd();
}
{
methodVisitor = classWriter.visitMethod(ACC_PUBLIC | ACC_STATIC, "getInstance", "()Lorg/apache/activemq/util/JenkinsHash;", null, null);
methodVisitor.visitCode();
methodVisitor.visitFieldInsn(GETSTATIC, "org/apache/activemq/util/JenkinsHash", "_instance", "Lorg/apache/activemq/util/JenkinsHash;");
methodVisitor.visitInsn(ARETURN);
methodVisitor.visitMaxs(1, 0);
methodVisitor.visitEnd();
}
{
methodVisitor = classWriter.visitMethod(ACC_PRIVATE | ACC_STATIC, "rot", "(JI)J", null, null);
methodVisitor.visitCode();
methodVisitor.visitVarInsn(LLOAD, 0);
methodVisitor.visitLdcInsn(new Long(4294967295L));
methodVisitor.visitInsn(LAND);
methodVisitor.visitInsn(L2I);
methodVisitor.visitVarInsn(ILOAD, 2);
methodVisitor.visitMethodInsn(INVOKESTATIC, "java/lang/Integer", "rotateLeft", "(II)I", false);
methodVisitor.visitInsn(I2L);
methodVisitor.visitLdcInsn(new Long(4294967295L));
methodVisitor.visitInsn(LAND);
methodVisitor.visitInsn(LRETURN);
methodVisitor.visitMaxs(4, 3);
methodVisitor.visitEnd();
}
{
methodVisitor = classWriter.visitMethod(ACC_PUBLIC, "hash", "([B)I", null, null);
methodVisitor.visitCode();
methodVisitor.visitVarInsn(ALOAD, 0);
methodVisitor.visitVarInsn(ALOAD, 1);
methodVisitor.visitVarInsn(ALOAD, 1);
methodVisitor.visitInsn(ARRAYLENGTH);
methodVisitor.visitInsn(ICONST_M1);
methodVisitor.visitMethodInsn(INVOKEVIRTUAL, "org/apache/activemq/util/JenkinsHash", "hash", "([BII)I", false);
methodVisitor.visitInsn(IRETURN);
methodVisitor.visitMaxs(4, 2);
methodVisitor.visitEnd();
}
{
methodVisitor = classWriter.visitMethod(ACC_PUBLIC, "hash", "([BI)I", null, null);
methodVisitor.visitCode();
methodVisitor.visitVarInsn(ALOAD, 0);
methodVisitor.visitVarInsn(ALOAD, 1);
methodVisitor.visitVarInsn(ALOAD, 1);
methodVisitor.visitInsn(ARRAYLENGTH);
methodVisitor.visitVarInsn(ILOAD, 2);
methodVisitor.visitMethodInsn(INVOKEVIRTUAL, "org/apache/activemq/util/JenkinsHash", "hash", "([BII)I", false);
methodVisitor.visitInsn(IRETURN);
methodVisitor.visitMaxs(4, 3);
methodVisitor.visitEnd();
}
{
methodVisitor = classWriter.visitMethod(ACC_PUBLIC, "hash", "([BII)I", null, null);
methodVisitor.visitCode();
methodVisitor.visitVarInsn(ILOAD, 2);
methodVisitor.visitVarInsn(ISTORE, 4);
methodVisitor.visitLdcInsn(new Long(3735928559L));
methodVisitor.visitVarInsn(ILOAD, 4);
methodVisitor.visitInsn(I2L);
methodVisitor.visitInsn(LADD);
methodVisitor.visitVarInsn(ILOAD, 3);
methodVisitor.visitInsn(I2L);
methodVisitor.visitInsn(LADD);
methodVisitor.visitLdcInsn(new Long(4294967295L));
methodVisitor.visitInsn(LAND);
methodVisitor.visitInsn(DUP2);
methodVisitor.visitVarInsn(LSTORE, 9);
methodVisitor.visitInsn(DUP2);
methodVisitor.visitVarInsn(LSTORE, 7);
methodVisitor.visitVarInsn(LSTORE, 5);
methodVisitor.visitInsn(ICONST_0);
methodVisitor.visitVarInsn(ISTORE, 11);
Label label0 = new Label();
methodVisitor.visitLabel(label0);
methodVisitor.visitFrame(Opcodes.F_FULL, 9, new Object[] {"org/apache/activemq/util/JenkinsHash", "[B", Opcodes.INTEGER, Opcodes.INTEGER, Opcodes.INTEGER, Opcodes.LONG, Opcodes.LONG, Opcodes.LONG, Opcodes.INTEGER}, 0, new Object[] {});
methodVisitor.visitVarInsn(ILOAD, 4);
methodVisitor.visitIntInsn(BIPUSH, 12);
Label label1 = new Label();
methodVisitor.visitJumpInsn(IF_ICMPLE, label1);
methodVisitor.visitVarInsn(LLOAD, 5);
methodVisitor.visitVarInsn(ALOAD, 1);
methodVisitor.visitVarInsn(ILOAD, 11);
methodVisitor.visitInsn(ICONST_0);
methodVisitor.visitInsn(IADD);
methodVisitor.visitInsn(BALOAD);
methodVisitor.visitInsn(I2L);
methodVisitor.visitLdcInsn(new Long(255L));
methodVisitor.visitInsn(LAND);
methodVisitor.visitInsn(LADD);
methodVisitor.visitLdcInsn(new Long(4294967295L));
methodVisitor.visitInsn(LAND);
methodVisitor.visitVarInsn(LSTORE, 5);
methodVisitor.visitVarInsn(LLOAD, 5);
methodVisitor.visitVarInsn(ALOAD, 1);
methodVisitor.visitVarInsn(ILOAD, 11);
methodVisitor.visitInsn(ICONST_1);
methodVisitor.visitInsn(IADD);
methodVisitor.visitInsn(BALOAD);
methodVisitor.visitInsn(I2L);
methodVisitor.visitLdcInsn(new Long(255L));
methodVisitor.visitInsn(LAND);
methodVisitor.visitIntInsn(BIPUSH, 8);
methodVisitor.visitInsn(LSHL);
methodVisitor.visitLdcInsn(new Long(4294967295L));
methodVisitor.visitInsn(LAND);
methodVisitor.visitInsn(LADD);
methodVisitor.visitLdcInsn(new Long(4294967295L));
methodVisitor.visitInsn(LAND);
methodVisitor.visitVarInsn(LSTORE, 5);
methodVisitor.visitVarInsn(LLOAD, 5);
methodVisitor.visitVarInsn(ALOAD, 1);
methodVisitor.visitVarInsn(ILOAD, 11);
methodVisitor.visitInsn(ICONST_2);
methodVisitor.visitInsn(IADD);
methodVisitor.visitInsn(BALOAD);
methodVisitor.visitInsn(I2L);
methodVisitor.visitLdcInsn(new Long(255L));
methodVisitor.visitInsn(LAND);
methodVisitor.visitIntInsn(BIPUSH, 16);
methodVisitor.visitInsn(LSHL);
methodVisitor.visitLdcInsn(new Long(4294967295L));
methodVisitor.visitInsn(LAND);
methodVisitor.visitInsn(LADD);
methodVisitor.visitLdcInsn(new Long(4294967295L));
methodVisitor.visitInsn(LAND);
methodVisitor.visitVarInsn(LSTORE, 5);
methodVisitor.visitVarInsn(LLOAD, 5);
methodVisitor.visitVarInsn(ALOAD, 1);
methodVisitor.visitVarInsn(ILOAD, 11);
methodVisitor.visitInsn(ICONST_3);
methodVisitor.visitInsn(IADD);
methodVisitor.visitInsn(BALOAD);
methodVisitor.visitInsn(I2L);
methodVisitor.visitLdcInsn(new Long(255L));
methodVisitor.visitInsn(LAND);
methodVisitor.visitIntInsn(BIPUSH, 24);
methodVisitor.visitInsn(LSHL);
methodVisitor.visitLdcInsn(new Long(4294967295L));
methodVisitor.visitInsn(LAND);
methodVisitor.visitInsn(LADD);
methodVisitor.visitLdcInsn(new Long(4294967295L));
methodVisitor.visitInsn(LAND);
methodVisitor.visitVarInsn(LSTORE, 5);
methodVisitor.visitVarInsn(LLOAD, 7);
methodVisitor.visitVarInsn(ALOAD, 1);
methodVisitor.visitVarInsn(ILOAD, 11);
methodVisitor.visitInsn(ICONST_4);
methodVisitor.visitInsn(IADD);
methodVisitor.visitInsn(BALOAD);
methodVisitor.visitInsn(I2L);
methodVisitor.visitLdcInsn(new Long(255L));
methodVisitor.visitInsn(LAND);
methodVisitor.visitInsn(LADD);
methodVisitor.visitLdcInsn(new Long(4294967295L));
methodVisitor.visitInsn(LAND);
methodVisitor.visitVarInsn(LSTORE, 7);
methodVisitor.visitVarInsn(LLOAD, 7);
methodVisitor.visitVarInsn(ALOAD, 1);
methodVisitor.visitVarInsn(ILOAD, 11);
methodVisitor.visitInsn(ICONST_5);
methodVisitor.visitInsn(IADD);
methodVisitor.visitInsn(BALOAD);
methodVisitor.visitInsn(I2L);
methodVisitor.visitLdcInsn(new Long(255L));
methodVisitor.visitInsn(LAND);
methodVisitor.visitIntInsn(BIPUSH, 8);
methodVisitor.visitInsn(LSHL);
methodVisitor.visitLdcInsn(new Long(4294967295L));
methodVisitor.visitInsn(LAND);
methodVisitor.visitInsn(LADD);
methodVisitor.visitLdcInsn(new Long(4294967295L));
methodVisitor.visitInsn(LAND);
methodVisitor.visitVarInsn(LSTORE, 7);
methodVisitor.visitVarInsn(LLOAD, 7);
methodVisitor.visitVarInsn(ALOAD, 1);
methodVisitor.visitVarInsn(ILOAD, 11);
methodVisitor.visitIntInsn(BIPUSH, 6);
methodVisitor.visitInsn(IADD);
methodVisitor.visitInsn(BALOAD);
methodVisitor.visitInsn(I2L);
methodVisitor.visitLdcInsn(new Long(255L));
methodVisitor.visitInsn(LAND);
methodVisitor.visitIntInsn(BIPUSH, 16);
methodVisitor.visitInsn(LSHL);
methodVisitor.visitLdcInsn(new Long(4294967295L));
methodVisitor.visitInsn(LAND);
methodVisitor.visitInsn(LADD);
methodVisitor.visitLdcInsn(new Long(4294967295L));
methodVisitor.visitInsn(LAND);
methodVisitor.visitVarInsn(LSTORE, 7);
methodVisitor.visitVarInsn(LLOAD, 7);
methodVisitor.visitVarInsn(ALOAD, 1);
methodVisitor.visitVarInsn(ILOAD, 11);
methodVisitor.visitIntInsn(BIPUSH, 7);
methodVisitor.visitInsn(IADD);
methodVisitor.visitInsn(BALOAD);
methodVisitor.visitInsn(I2L);
methodVisitor.visitLdcInsn(new Long(255L));
methodVisitor.visitInsn(LAND);
methodVisitor.visitIntInsn(BIPUSH, 24);
methodVisitor.visitInsn(LSHL);
methodVisitor.visitLdcInsn(new Long(4294967295L));
methodVisitor.visitInsn(LAND);
methodVisitor.visitInsn(LADD);
methodVisitor.visitLdcInsn(new Long(4294967295L));
methodVisitor.visitInsn(LAND);
methodVisitor.visitVarInsn(LSTORE, 7);
methodVisitor.visitVarInsn(LLOAD, 9);
methodVisitor.visitVarInsn(ALOAD, 1);
methodVisitor.visitVarInsn(ILOAD, 11);
methodVisitor.visitIntInsn(BIPUSH, 8);
methodVisitor.visitInsn(IADD);
methodVisitor.visitInsn(BALOAD);
methodVisitor.visitInsn(I2L);
methodVisitor.visitLdcInsn(new Long(255L));
methodVisitor.visitInsn(LAND);
methodVisitor.visitInsn(LADD);
methodVisitor.visitLdcInsn(new Long(4294967295L));
methodVisitor.visitInsn(LAND);
methodVisitor.visitVarInsn(LSTORE, 9);
methodVisitor.visitVarInsn(LLOAD, 9);
methodVisitor.visitVarInsn(ALOAD, 1);
methodVisitor.visitVarInsn(ILOAD, 11);
methodVisitor.visitIntInsn(BIPUSH, 9);
methodVisitor.visitInsn(IADD);
methodVisitor.visitInsn(BALOAD);
methodVisitor.visitInsn(I2L);
methodVisitor.visitLdcInsn(new Long(255L));
methodVisitor.visitInsn(LAND);
methodVisitor.visitIntInsn(BIPUSH, 8);
methodVisitor.visitInsn(LSHL);
methodVisitor.visitLdcInsn(new Long(4294967295L));
methodVisitor.visitInsn(LAND);
methodVisitor.visitInsn(LADD);
methodVisitor.visitLdcInsn(new Long(4294967295L));
methodVisitor.visitInsn(LAND);
methodVisitor.visitVarInsn(LSTORE, 9);
methodVisitor.visitVarInsn(LLOAD, 9);
methodVisitor.visitVarInsn(ALOAD, 1);
methodVisitor.visitVarInsn(ILOAD, 11);
methodVisitor.visitIntInsn(BIPUSH, 10);
methodVisitor.visitInsn(IADD);
methodVisitor.visitInsn(BALOAD);
methodVisitor.visitInsn(I2L);
methodVisitor.visitLdcInsn(new Long(255L));
methodVisitor.visitInsn(LAND);
methodVisitor.visitIntInsn(BIPUSH, 16);
methodVisitor.visitInsn(LSHL);
methodVisitor.visitLdcInsn(new Long(4294967295L));
methodVisitor.visitInsn(LAND);
methodVisitor.visitInsn(LADD);
methodVisitor.visitLdcInsn(new Long(4294967295L));
methodVisitor.visitInsn(LAND);
methodVisitor.visitVarInsn(LSTORE, 9);
methodVisitor.visitVarInsn(LLOAD, 9);
methodVisitor.visitVarInsn(ALOAD, 1);
methodVisitor.visitVarInsn(ILOAD, 11);
methodVisitor.visitIntInsn(BIPUSH, 11);
methodVisitor.visitInsn(IADD);
methodVisitor.visitInsn(BALOAD);
methodVisitor.visitInsn(I2L);
methodVisitor.visitLdcInsn(new Long(255L));
methodVisitor.visitInsn(LAND);
methodVisitor.visitIntInsn(BIPUSH, 24);
methodVisitor.visitInsn(LSHL);
methodVisitor.visitLdcInsn(new Long(4294967295L));
methodVisitor.visitInsn(LAND);
methodVisitor.visitInsn(LADD);
methodVisitor.visitLdcInsn(new Long(4294967295L));
methodVisitor.visitInsn(LAND);
methodVisitor.visitVarInsn(LSTORE, 9);
methodVisitor.visitVarInsn(LLOAD, 5);
methodVisitor.visitVarInsn(LLOAD, 9);
methodVisitor.visitInsn(LSUB);
methodVisitor.visitLdcInsn(new Long(4294967295L));
methodVisitor.visitInsn(LAND);
methodVisitor.visitVarInsn(LSTORE, 5);
methodVisitor.visitVarInsn(LLOAD, 5);
methodVisitor.visitVarInsn(LLOAD, 9);
methodVisitor.visitInsn(ICONST_4);
methodVisitor.visitMethodInsn(INVOKESTATIC, "org/apache/activemq/util/JenkinsHash", "rot", "(JI)J", false);
methodVisitor.visitInsn(LXOR);
methodVisitor.visitVarInsn(LSTORE, 5);
methodVisitor.visitVarInsn(LLOAD, 9);
methodVisitor.visitVarInsn(LLOAD, 7);
methodVisitor.visitInsn(LADD);
methodVisitor.visitLdcInsn(new Long(4294967295L));
methodVisitor.visitInsn(LAND);
methodVisitor.visitVarInsn(LSTORE, 9);
methodVisitor.visitVarInsn(LLOAD, 7);
methodVisitor.visitVarInsn(LLOAD, 5);
methodVisitor.visitInsn(LSUB);
methodVisitor.visitLdcInsn(new Long(4294967295L));
methodVisitor.visitInsn(LAND);
methodVisitor.visitVarInsn(LSTORE, 7);
methodVisitor.visitVarInsn(LLOAD, 7);
methodVisitor.visitVarInsn(LLOAD, 5);
methodVisitor.visitIntInsn(BIPUSH, 6);
methodVisitor.visitMethodInsn(INVOKESTATIC, "org/apache/activemq/util/JenkinsHash", "rot", "(JI)J", false);
methodVisitor.visitInsn(LXOR);
methodVisitor.visitVarInsn(LSTORE, 7);
methodVisitor.visitVarInsn(LLOAD, 5);
methodVisitor.visitVarInsn(LLOAD, 9);
methodVisitor.visitInsn(LADD);
methodVisitor.visitLdcInsn(new Long(4294967295L));
methodVisitor.visitInsn(LAND);
methodVisitor.visitVarInsn(LSTORE, 5);
methodVisitor.visitVarInsn(LLOAD, 9);
methodVisitor.visitVarInsn(LLOAD, 7);
methodVisitor.visitInsn(LSUB);
methodVisitor.visitLdcInsn(new Long(4294967295L));
methodVisitor.visitInsn(LAND);
methodVisitor.visitVarInsn(LSTORE, 9);
methodVisitor.visitVarInsn(LLOAD, 9);
methodVisitor.visitVarInsn(LLOAD, 7);
methodVisitor.visitIntInsn(BIPUSH, 8);
methodVisitor.visitMethodInsn(INVOKESTATIC, "org/apache/activemq/util/JenkinsHash", "rot", "(JI)J", false);
methodVisitor.visitInsn(LXOR);
methodVisitor.visitVarInsn(LSTORE, 9);
methodVisitor.visitVarInsn(LLOAD, 7);
methodVisitor.visitVarInsn(LLOAD, 5);
methodVisitor.visitInsn(LADD);
methodVisitor.visitLdcInsn(new Long(4294967295L));
methodVisitor.visitInsn(LAND);
methodVisitor.visitVarInsn(LSTORE, 7);
methodVisitor.visitVarInsn(LLOAD, 5);
methodVisitor.visitVarInsn(LLOAD, 9);
methodVisitor.visitInsn(LSUB);
methodVisitor.visitLdcInsn(new Long(4294967295L));
methodVisitor.visitInsn(LAND);
methodVisitor.visitVarInsn(LSTORE, 5);
methodVisitor.visitVarInsn(LLOAD, 5);
methodVisitor.visitVarInsn(LLOAD, 9);
methodVisitor.visitIntInsn(BIPUSH, 16);
methodVisitor.visitMethodInsn(INVOKESTATIC, "org/apache/activemq/util/JenkinsHash", "rot", "(JI)J", false);
methodVisitor.visitInsn(LXOR);
methodVisitor.visitVarInsn(LSTORE, 5);
methodVisitor.visitVarInsn(LLOAD, 9);
methodVisitor.visitVarInsn(LLOAD, 7);
methodVisitor.visitInsn(LADD);
methodVisitor.visitLdcInsn(new Long(4294967295L));
methodVisitor.visitInsn(LAND);
methodVisitor.visitVarInsn(LSTORE, 9);
methodVisitor.visitVarInsn(LLOAD, 7);
methodVisitor.visitVarInsn(LLOAD, 5);
methodVisitor.visitInsn(LSUB);
methodVisitor.visitLdcInsn(new Long(4294967295L));
methodVisitor.visitInsn(LAND);
methodVisitor.visitVarInsn(LSTORE, 7);
methodVisitor.visitVarInsn(LLOAD, 7);
methodVisitor.visitVarInsn(LLOAD, 5);
methodVisitor.visitIntInsn(BIPUSH, 19);
methodVisitor.visitMethodInsn(INVOKESTATIC, "org/apache/activemq/util/JenkinsHash", "rot", "(JI)J", false);
methodVisitor.visitInsn(LXOR);
methodVisitor.visitVarInsn(LSTORE, 7);
methodVisitor.visitVarInsn(LLOAD, 5);
methodVisitor.visitVarInsn(LLOAD, 9);
methodVisitor.visitInsn(LADD);
methodVisitor.visitLdcInsn(new Long(4294967295L));
methodVisitor.visitInsn(LAND);
methodVisitor.visitVarInsn(LSTORE, 5);
methodVisitor.visitVarInsn(LLOAD, 9);
methodVisitor.visitVarInsn(LLOAD, 7);
methodVisitor.visitInsn(LSUB);
methodVisitor.visitLdcInsn(new Long(4294967295L));
methodVisitor.visitInsn(LAND);
methodVisitor.visitVarInsn(LSTORE, 9);
methodVisitor.visitVarInsn(LLOAD, 9);
methodVisitor.visitVarInsn(LLOAD, 7);
methodVisitor.visitInsn(ICONST_4);
methodVisitor.visitMethodInsn(INVOKESTATIC, "org/apache/activemq/util/JenkinsHash", "rot", "(JI)J", false);
methodVisitor.visitInsn(LXOR);
methodVisitor.visitVarInsn(LSTORE, 9);
methodVisitor.visitVarInsn(LLOAD, 7);
methodVisitor.visitVarInsn(LLOAD, 5);
methodVisitor.visitInsn(LADD);
methodVisitor.visitLdcInsn(new Long(4294967295L));
methodVisitor.visitInsn(LAND);
methodVisitor.visitVarInsn(LSTORE, 7);
methodVisitor.visitIincInsn(11, 12);
methodVisitor.visitIincInsn(4, -12);
methodVisitor.visitJumpInsn(GOTO, label0);
methodVisitor.visitLabel(label1);
methodVisitor.visitFrame(Opcodes.F_SAME, 0, null, 0, null);
methodVisitor.visitVarInsn(ILOAD, 4);
Label label2 = new Label();
Label label3 = new Label();
Label label4 = new Label();
Label label5 = new Label();
Label label6 = new Label();
Label label7 = new Label();
Label label8 = new Label();
Label label9 = new Label();
Label label10 = new Label();
Label label11 = new Label();
Label label12 = new Label();
Label label13 = new Label();
Label label14 = new Label();
Label label15 = new Label();
methodVisitor.visitTableSwitchInsn(0, 12, label15, new Label[] { label2, label3, label4, label5, label6, label7, label8, label9, label10, label11, label12, label13, label14 });
methodVisitor.visitLabel(label14);
methodVisitor.visitFrame(Opcodes.F_SAME, 0, null, 0, null);
methodVisitor.visitVarInsn(LLOAD, 9);
methodVisitor.visitVarInsn(ALOAD, 1);
methodVisitor.visitVarInsn(ILOAD, 11);
methodVisitor.visitIntInsn(BIPUSH, 11);
methodVisitor.visitInsn(IADD);
methodVisitor.visitInsn(BALOAD);
methodVisitor.visitInsn(I2L);
methodVisitor.visitLdcInsn(new Long(255L));
methodVisitor.visitInsn(LAND);
methodVisitor.visitIntInsn(BIPUSH, 24);
methodVisitor.visitInsn(LSHL);
methodVisitor.visitLdcInsn(new Long(4294967295L));
methodVisitor.visitInsn(LAND);
methodVisitor.visitInsn(LADD);
methodVisitor.visitLdcInsn(new Long(4294967295L));
methodVisitor.visitInsn(LAND);
methodVisitor.visitVarInsn(LSTORE, 9);
methodVisitor.visitLabel(label13);
methodVisitor.visitFrame(Opcodes.F_SAME, 0, null, 0, null);
methodVisitor.visitVarInsn(LLOAD, 9);
methodVisitor.visitVarInsn(ALOAD, 1);
methodVisitor.visitVarInsn(ILOAD, 11);
methodVisitor.visitIntInsn(BIPUSH, 10);
methodVisitor.visitInsn(IADD);
methodVisitor.visitInsn(BALOAD);
methodVisitor.visitInsn(I2L);
methodVisitor.visitLdcInsn(new Long(255L));
methodVisitor.visitInsn(LAND);
methodVisitor.visitIntInsn(BIPUSH, 16);
methodVisitor.visitInsn(LSHL);
methodVisitor.visitLdcInsn(new Long(4294967295L));
methodVisitor.visitInsn(LAND);
methodVisitor.visitInsn(LADD);
methodVisitor.visitLdcInsn(new Long(4294967295L));
methodVisitor.visitInsn(LAND);
methodVisitor.visitVarInsn(LSTORE, 9);
methodVisitor.visitLabel(label12);
methodVisitor.visitFrame(Opcodes.F_SAME, 0, null, 0, null);
methodVisitor.visitVarInsn(LLOAD, 9);
methodVisitor.visitVarInsn(ALOAD, 1);
methodVisitor.visitVarInsn(ILOAD, 11);
methodVisitor.visitIntInsn(BIPUSH, 9);
methodVisitor.visitInsn(IADD);
methodVisitor.visitInsn(BALOAD);
methodVisitor.visitInsn(I2L);
methodVisitor.visitLdcInsn(new Long(255L));
methodVisitor.visitInsn(LAND);
methodVisitor.visitIntInsn(BIPUSH, 8);
methodVisitor.visitInsn(LSHL);
methodVisitor.visitLdcInsn(new Long(4294967295L));
methodVisitor.visitInsn(LAND);
methodVisitor.visitInsn(LADD);
methodVisitor.visitLdcInsn(new Long(4294967295L));
methodVisitor.visitInsn(LAND);
methodVisitor.visitVarInsn(LSTORE, 9);
methodVisitor.visitLabel(label11);
methodVisitor.visitFrame(Opcodes.F_SAME, 0, null, 0, null);
methodVisitor.visitVarInsn(LLOAD, 9);
methodVisitor.visitVarInsn(ALOAD, 1);
methodVisitor.visitVarInsn(ILOAD, 11);
methodVisitor.visitIntInsn(BIPUSH, 8);
methodVisitor.visitInsn(IADD);
methodVisitor.visitInsn(BALOAD);
methodVisitor.visitInsn(I2L);
methodVisitor.visitLdcInsn(new Long(255L));
methodVisitor.visitInsn(LAND);
methodVisitor.visitInsn(LADD);
methodVisitor.visitLdcInsn(new Long(4294967295L));
methodVisitor.visitInsn(LAND);
methodVisitor.visitVarInsn(LSTORE, 9);
methodVisitor.visitLabel(label10);
methodVisitor.visitFrame(Opcodes.F_SAME, 0, null, 0, null);
methodVisitor.visitVarInsn(LLOAD, 7);
methodVisitor.visitVarInsn(ALOAD, 1);
methodVisitor.visitVarInsn(ILOAD, 11);
methodVisitor.visitIntInsn(BIPUSH, 7);
methodVisitor.visitInsn(IADD);
methodVisitor.visitInsn(BALOAD);
methodVisitor.visitInsn(I2L);
methodVisitor.visitLdcInsn(new Long(255L));
methodVisitor.visitInsn(LAND);
methodVisitor.visitIntInsn(BIPUSH, 24);
methodVisitor.visitInsn(LSHL);
methodVisitor.visitLdcInsn(new Long(4294967295L));
methodVisitor.visitInsn(LAND);
methodVisitor.visitInsn(LADD);
methodVisitor.visitLdcInsn(new Long(4294967295L));
methodVisitor.visitInsn(LAND);
methodVisitor.visitVarInsn(LSTORE, 7);
methodVisitor.visitLabel(label9);
methodVisitor.visitFrame(Opcodes.F_SAME, 0, null, 0, null);
methodVisitor.visitVarInsn(LLOAD, 7);
methodVisitor.visitVarInsn(ALOAD, 1);
methodVisitor.visitVarInsn(ILOAD, 11);
methodVisitor.visitIntInsn(BIPUSH, 6);
methodVisitor.visitInsn(IADD);
methodVisitor.visitInsn(BALOAD);
methodVisitor.visitInsn(I2L);
methodVisitor.visitLdcInsn(new Long(255L));
methodVisitor.visitInsn(LAND);
methodVisitor.visitIntInsn(BIPUSH, 16);
methodVisitor.visitInsn(LSHL);
methodVisitor.visitLdcInsn(new Long(4294967295L));
methodVisitor.visitInsn(LAND);
methodVisitor.visitInsn(LADD);
methodVisitor.visitLdcInsn(new Long(4294967295L));
methodVisitor.visitInsn(LAND);
methodVisitor.visitVarInsn(LSTORE, 7);
methodVisitor.visitLabel(label8);
methodVisitor.visitFrame(Opcodes.F_SAME, 0, null, 0, null);
methodVisitor.visitVarInsn(LLOAD, 7);
methodVisitor.visitVarInsn(ALOAD, 1);
methodVisitor.visitVarInsn(ILOAD, 11);
methodVisitor.visitInsn(ICONST_5);
methodVisitor.visitInsn(IADD);
methodVisitor.visitInsn(BALOAD);
methodVisitor.visitInsn(I2L);
methodVisitor.visitLdcInsn(new Long(255L));
methodVisitor.visitInsn(LAND);
methodVisitor.visitIntInsn(BIPUSH, 8);
methodVisitor.visitInsn(LSHL);
methodVisitor.visitLdcInsn(new Long(4294967295L));
methodVisitor.visitInsn(LAND);
methodVisitor.visitInsn(LADD);
methodVisitor.visitLdcInsn(new Long(4294967295L));
methodVisitor.visitInsn(LAND);
methodVisitor.visitVarInsn(LSTORE, 7);
methodVisitor.visitLabel(label7);
methodVisitor.visitFrame(Opcodes.F_SAME, 0, null, 0, null);
methodVisitor.visitVarInsn(LLOAD, 7);
methodVisitor.visitVarInsn(ALOAD, 1);
methodVisitor.visitVarInsn(ILOAD, 11);
methodVisitor.visitInsn(ICONST_4);
methodVisitor.visitInsn(IADD);
methodVisitor.visitInsn(BALOAD);
methodVisitor.visitInsn(I2L);
methodVisitor.visitLdcInsn(new Long(255L));
methodVisitor.visitInsn(LAND);
methodVisitor.visitInsn(LADD);
methodVisitor.visitLdcInsn(new Long(4294967295L));
methodVisitor.visitInsn(LAND);
methodVisitor.visitVarInsn(LSTORE, 7);
methodVisitor.visitLabel(label6);
methodVisitor.visitFrame(Opcodes.F_SAME, 0, null, 0, null);
methodVisitor.visitVarInsn(LLOAD, 5);
methodVisitor.visitVarInsn(ALOAD, 1);
methodVisitor.visitVarInsn(ILOAD, 11);
methodVisitor.visitInsn(ICONST_3);
methodVisitor.visitInsn(IADD);
methodVisitor.visitInsn(BALOAD);
methodVisitor.visitInsn(I2L);
methodVisitor.visitLdcInsn(new Long(255L));
methodVisitor.visitInsn(LAND);
methodVisitor.visitIntInsn(BIPUSH, 24);
methodVisitor.visitInsn(LSHL);
methodVisitor.visitLdcInsn(new Long(4294967295L));
methodVisitor.visitInsn(LAND);
methodVisitor.visitInsn(LADD);
methodVisitor.visitLdcInsn(new Long(4294967295L));
methodVisitor.visitInsn(LAND);
methodVisitor.visitVarInsn(LSTORE, 5);
methodVisitor.visitLabel(label5);
methodVisitor.visitFrame(Opcodes.F_SAME, 0, null, 0, null);
methodVisitor.visitVarInsn(LLOAD, 5);
methodVisitor.visitVarInsn(ALOAD, 1);
methodVisitor.visitVarInsn(ILOAD, 11);
methodVisitor.visitInsn(ICONST_2);
methodVisitor.visitInsn(IADD);
methodVisitor.visitInsn(BALOAD);
methodVisitor.visitInsn(I2L);
methodVisitor.visitLdcInsn(new Long(255L));
methodVisitor.visitInsn(LAND);
methodVisitor.visitIntInsn(BIPUSH, 16);
methodVisitor.visitInsn(LSHL);
methodVisitor.visitLdcInsn(new Long(4294967295L));
methodVisitor.visitInsn(LAND);
methodVisitor.visitInsn(LADD);
methodVisitor.visitLdcInsn(new Long(4294967295L));
methodVisitor.visitInsn(LAND);
methodVisitor.visitVarInsn(LSTORE, 5);
methodVisitor.visitLabel(label4);
methodVisitor.visitFrame(Opcodes.F_SAME, 0, null, 0, null);
methodVisitor.visitVarInsn(LLOAD, 5);
methodVisitor.visitVarInsn(ALOAD, 1);
methodVisitor.visitVarInsn(ILOAD, 11);
methodVisitor.visitInsn(ICONST_1);
methodVisitor.visitInsn(IADD);
methodVisitor.visitInsn(BALOAD);
methodVisitor.visitInsn(I2L);
methodVisitor.visitLdcInsn(new Long(255L));
methodVisitor.visitInsn(LAND);
methodVisitor.visitIntInsn(BIPUSH, 8);
methodVisitor.visitInsn(LSHL);
methodVisitor.visitLdcInsn(new Long(4294967295L));
methodVisitor.visitInsn(LAND);
methodVisitor.visitInsn(LADD);
methodVisitor.visitLdcInsn(new Long(4294967295L));
methodVisitor.visitInsn(LAND);
methodVisitor.visitVarInsn(LSTORE, 5);
methodVisitor.visitLabel(label3);
methodVisitor.visitFrame(Opcodes.F_SAME, 0, null, 0, null);
methodVisitor.visitVarInsn(LLOAD, 5);
methodVisitor.visitVarInsn(ALOAD, 1);
methodVisitor.visitVarInsn(ILOAD, 11);
methodVisitor.visitInsn(ICONST_0);
methodVisitor.visitInsn(IADD);
methodVisitor.visitInsn(BALOAD);
methodVisitor.visitInsn(I2L);
methodVisitor.visitLdcInsn(new Long(255L));
methodVisitor.visitInsn(LAND);
methodVisitor.visitInsn(LADD);
methodVisitor.visitLdcInsn(new Long(4294967295L));
methodVisitor.visitInsn(LAND);
methodVisitor.visitVarInsn(LSTORE, 5);
methodVisitor.visitJumpInsn(GOTO, label15);
methodVisitor.visitLabel(label2);
methodVisitor.visitFrame(Opcodes.F_SAME, 0, null, 0, null);
methodVisitor.visitVarInsn(LLOAD, 9);
methodVisitor.visitLdcInsn(new Long(4294967295L));
methodVisitor.visitInsn(LAND);
methodVisitor.visitInsn(L2I);
methodVisitor.visitInsn(IRETURN);
methodVisitor.visitLabel(label15);
methodVisitor.visitFrame(Opcodes.F_SAME, 0, null, 0, null);
methodVisitor.visitVarInsn(LLOAD, 9);
methodVisitor.visitVarInsn(LLOAD, 7);
methodVisitor.visitInsn(LXOR);
methodVisitor.visitVarInsn(LSTORE, 9);
methodVisitor.visitVarInsn(LLOAD, 9);
methodVisitor.visitVarInsn(LLOAD, 7);
methodVisitor.visitIntInsn(BIPUSH, 14);
methodVisitor.visitMethodInsn(INVOKESTATIC, "org/apache/activemq/util/JenkinsHash", "rot", "(JI)J", false);
methodVisitor.visitInsn(LSUB);
methodVisitor.visitLdcInsn(new Long(4294967295L));
methodVisitor.visitInsn(LAND);
methodVisitor.visitVarInsn(LSTORE, 9);
methodVisitor.visitVarInsn(LLOAD, 5);
methodVisitor.visitVarInsn(LLOAD, 9);
methodVisitor.visitInsn(LXOR);
methodVisitor.visitVarInsn(LSTORE, 5);
methodVisitor.visitVarInsn(LLOAD, 5);
methodVisitor.visitVarInsn(LLOAD, 9);
methodVisitor.visitIntInsn(BIPUSH, 11);
methodVisitor.visitMethodInsn(INVOKESTATIC, "org/apache/activemq/util/JenkinsHash", "rot", "(JI)J", false);
methodVisitor.visitInsn(LSUB);
methodVisitor.visitLdcInsn(new Long(4294967295L));
methodVisitor.visitInsn(LAND);
methodVisitor.visitVarInsn(LSTORE, 5);
methodVisitor.visitVarInsn(LLOAD, 7);
methodVisitor.visitVarInsn(LLOAD, 5);
methodVisitor.visitInsn(LXOR);
methodVisitor.visitVarInsn(LSTORE, 7);
methodVisitor.visitVarInsn(LLOAD, 7);
methodVisitor.visitVarInsn(LLOAD, 5);
methodVisitor.visitIntInsn(BIPUSH, 25);
methodVisitor.visitMethodInsn(INVOKESTATIC, "org/apache/activemq/util/JenkinsHash", "rot", "(JI)J", false);
methodVisitor.visitInsn(LSUB);
methodVisitor.visitLdcInsn(new Long(4294967295L));
methodVisitor.visitInsn(LAND);
methodVisitor.visitVarInsn(LSTORE, 7);
methodVisitor.visitVarInsn(LLOAD, 9);
methodVisitor.visitVarInsn(LLOAD, 7);
methodVisitor.visitInsn(LXOR);
methodVisitor.visitVarInsn(LSTORE, 9);
methodVisitor.visitVarInsn(LLOAD, 9);
methodVisitor.visitVarInsn(LLOAD, 7);
methodVisitor.visitIntInsn(BIPUSH, 16);
methodVisitor.visitMethodInsn(INVOKESTATIC, "org/apache/activemq/util/JenkinsHash", "rot", "(JI)J", false);
methodVisitor.visitInsn(LSUB);
methodVisitor.visitLdcInsn(new Long(4294967295L));
methodVisitor.visitInsn(LAND);
methodVisitor.visitVarInsn(LSTORE, 9);
methodVisitor.visitVarInsn(LLOAD, 5);
methodVisitor.visitVarInsn(LLOAD, 9);
methodVisitor.visitInsn(LXOR);
methodVisitor.visitVarInsn(LSTORE, 5);
methodVisitor.visitVarInsn(LLOAD, 5);
methodVisitor.visitVarInsn(LLOAD, 9);
methodVisitor.visitInsn(ICONST_4);
methodVisitor.visitMethodInsn(INVOKESTATIC, "org/apache/activemq/util/JenkinsHash", "rot", "(JI)J", false);
methodVisitor.visitInsn(LSUB);
methodVisitor.visitLdcInsn(new Long(4294967295L));
methodVisitor.visitInsn(LAND);
methodVisitor.visitVarInsn(LSTORE, 5);
methodVisitor.visitVarInsn(LLOAD, 7);
methodVisitor.visitVarInsn(LLOAD, 5);
methodVisitor.visitInsn(LXOR);
methodVisitor.visitVarInsn(LSTORE, 7);
methodVisitor.visitVarInsn(LLOAD, 7);
methodVisitor.visitVarInsn(LLOAD, 5);
methodVisitor.visitIntInsn(BIPUSH, 14);
methodVisitor.visitMethodInsn(INVOKESTATIC, "org/apache/activemq/util/JenkinsHash", "rot", "(JI)J", false);
methodVisitor.visitInsn(LSUB);
methodVisitor.visitLdcInsn(new Long(4294967295L));
methodVisitor.visitInsn(LAND);
methodVisitor.visitVarInsn(LSTORE, 7);
methodVisitor.visitVarInsn(LLOAD, 9);
methodVisitor.visitVarInsn(LLOAD, 7);
methodVisitor.visitInsn(LXOR);
methodVisitor.visitVarInsn(LSTORE, 9);
methodVisitor.visitVarInsn(LLOAD, 9);
methodVisitor.visitVarInsn(LLOAD, 7);
methodVisitor.visitIntInsn(BIPUSH, 24);
methodVisitor.visitMethodInsn(INVOKESTATIC, "org/apache/activemq/util/JenkinsHash", "rot", "(JI)J", false);
methodVisitor.visitInsn(LSUB);
methodVisitor.visitLdcInsn(new Long(4294967295L));
methodVisitor.visitInsn(LAND);
methodVisitor.visitVarInsn(LSTORE, 9);
methodVisitor.visitVarInsn(LLOAD, 9);
methodVisitor.visitLdcInsn(new Long(4294967295L));
methodVisitor.visitInsn(LAND);
methodVisitor.visitInsn(L2I);
methodVisitor.visitInsn(IRETURN);
methodVisitor.visitMaxs(6, 12);
methodVisitor.visitEnd();
}
{
methodVisitor = classWriter.visitMethod(ACC_STATIC, "<clinit>", "()V", null, null);
methodVisitor.visitCode();
methodVisitor.visitTypeInsn(NEW, "org/apache/activemq/util/JenkinsHash");
methodVisitor.visitInsn(DUP);
methodVisitor.visitMethodInsn(INVOKESPECIAL, "org/apache/activemq/util/JenkinsHash", "<init>", "()V", false);
methodVisitor.visitFieldInsn(PUTSTATIC, "org/apache/activemq/util/JenkinsHash", "_instance", "Lorg/apache/activemq/util/JenkinsHash;");
methodVisitor.visitInsn(RETURN);
methodVisitor.visitMaxs(2, 0);
methodVisitor.visitEnd();
}
classWriter.visitEnd();

return classWriter.toByteArray();
}
}
