package asm.org.apache.coyote.http2;
import org.objectweb.asm.AnnotationVisitor;
import org.objectweb.asm.Attribute;
import org.objectweb.asm.ClassReader;
import org.objectweb.asm.ClassWriter;
import org.objectweb.asm.ConstantDynamic;
import org.objectweb.asm.FieldVisitor;
import org.objectweb.asm.Handle;
import org.objectweb.asm.Label;
import org.objectweb.asm.MethodVisitor;
import org.objectweb.asm.Opcodes;
import org.objectweb.asm.RecordComponentVisitor;
import org.objectweb.asm.Type;
import org.objectweb.asm.TypePath;
public class ByteUtilDump implements Opcodes {

public static byte[] dump () throws Exception {

ClassWriter classWriter = new ClassWriter(0);
FieldVisitor fieldVisitor;
RecordComponentVisitor recordComponentVisitor;
MethodVisitor methodVisitor;
AnnotationVisitor annotationVisitor0;

classWriter.visit(V1_8, ACC_SUPER, "org/apache/coyote/http2/ByteUtil", null, "java/lang/Object", null);

{
methodVisitor = classWriter.visitMethod(ACC_PRIVATE, "<init>", "()V", null, null);
methodVisitor.visitCode();
methodVisitor.visitVarInsn(ALOAD, 0);
methodVisitor.visitMethodInsn(INVOKESPECIAL, "java/lang/Object", "<init>", "()V", false);
methodVisitor.visitInsn(RETURN);
methodVisitor.visitMaxs(1, 1);
methodVisitor.visitEnd();
}
{
methodVisitor = classWriter.visitMethod(ACC_STATIC, "isBit7Set", "(B)Z", null, null);
methodVisitor.visitCode();
methodVisitor.visitVarInsn(ILOAD, 0);
methodVisitor.visitIntInsn(SIPUSH, 128);
methodVisitor.visitInsn(IAND);
Label label0 = new Label();
methodVisitor.visitJumpInsn(IFEQ, label0);
methodVisitor.visitInsn(ICONST_1);
Label label1 = new Label();
methodVisitor.visitJumpInsn(GOTO, label1);
methodVisitor.visitLabel(label0);
methodVisitor.visitFrame(Opcodes.F_SAME, 0, null, 0, null);
methodVisitor.visitInsn(ICONST_0);
methodVisitor.visitLabel(label1);
methodVisitor.visitFrame(Opcodes.F_SAME1, 0, null, 1, new Object[] {Opcodes.INTEGER});
methodVisitor.visitInsn(IRETURN);
methodVisitor.visitMaxs(2, 1);
methodVisitor.visitEnd();
}
{
methodVisitor = classWriter.visitMethod(ACC_STATIC, "get31Bits", "([BI)I", null, null);
methodVisitor.visitCode();
methodVisitor.visitVarInsn(ALOAD, 0);
methodVisitor.visitVarInsn(ILOAD, 1);
methodVisitor.visitInsn(BALOAD);
methodVisitor.visitIntInsn(BIPUSH, 127);
methodVisitor.visitInsn(IAND);
methodVisitor.visitIntInsn(BIPUSH, 24);
methodVisitor.visitInsn(ISHL);
methodVisitor.visitVarInsn(ALOAD, 0);
methodVisitor.visitVarInsn(ILOAD, 1);
methodVisitor.visitInsn(ICONST_1);
methodVisitor.visitInsn(IADD);
methodVisitor.visitInsn(BALOAD);
methodVisitor.visitIntInsn(SIPUSH, 255);
methodVisitor.visitInsn(IAND);
methodVisitor.visitIntInsn(BIPUSH, 16);
methodVisitor.visitInsn(ISHL);
methodVisitor.visitInsn(IADD);
methodVisitor.visitVarInsn(ALOAD, 0);
methodVisitor.visitVarInsn(ILOAD, 1);
methodVisitor.visitInsn(ICONST_2);
methodVisitor.visitInsn(IADD);
methodVisitor.visitInsn(BALOAD);
methodVisitor.visitIntInsn(SIPUSH, 255);
methodVisitor.visitInsn(IAND);
methodVisitor.visitIntInsn(BIPUSH, 8);
methodVisitor.visitInsn(ISHL);
methodVisitor.visitInsn(IADD);
methodVisitor.visitVarInsn(ALOAD, 0);
methodVisitor.visitVarInsn(ILOAD, 1);
methodVisitor.visitInsn(ICONST_3);
methodVisitor.visitInsn(IADD);
methodVisitor.visitInsn(BALOAD);
methodVisitor.visitIntInsn(SIPUSH, 255);
methodVisitor.visitInsn(IAND);
methodVisitor.visitInsn(IADD);
methodVisitor.visitInsn(IRETURN);
methodVisitor.visitMaxs(4, 2);
methodVisitor.visitEnd();
}
{
methodVisitor = classWriter.visitMethod(ACC_STATIC, "get31Bits", "(Ljava/nio/ByteBuffer;I)I", null, null);
methodVisitor.visitCode();
methodVisitor.visitVarInsn(ALOAD, 0);
methodVisitor.visitVarInsn(ILOAD, 1);
methodVisitor.visitMethodInsn(INVOKEVIRTUAL, "java/nio/ByteBuffer", "get", "(I)B", false);
methodVisitor.visitIntInsn(BIPUSH, 127);
methodVisitor.visitInsn(IAND);
methodVisitor.visitIntInsn(BIPUSH, 24);
methodVisitor.visitInsn(ISHL);
methodVisitor.visitVarInsn(ALOAD, 0);
methodVisitor.visitVarInsn(ILOAD, 1);
methodVisitor.visitInsn(ICONST_1);
methodVisitor.visitInsn(IADD);
methodVisitor.visitMethodInsn(INVOKEVIRTUAL, "java/nio/ByteBuffer", "get", "(I)B", false);
methodVisitor.visitIntInsn(SIPUSH, 255);
methodVisitor.visitInsn(IAND);
methodVisitor.visitIntInsn(BIPUSH, 16);
methodVisitor.visitInsn(ISHL);
methodVisitor.visitInsn(IADD);
methodVisitor.visitVarInsn(ALOAD, 0);
methodVisitor.visitVarInsn(ILOAD, 1);
methodVisitor.visitInsn(ICONST_2);
methodVisitor.visitInsn(IADD);
methodVisitor.visitMethodInsn(INVOKEVIRTUAL, "java/nio/ByteBuffer", "get", "(I)B", false);
methodVisitor.visitIntInsn(SIPUSH, 255);
methodVisitor.visitInsn(IAND);
methodVisitor.visitIntInsn(BIPUSH, 8);
methodVisitor.visitInsn(ISHL);
methodVisitor.visitInsn(IADD);
methodVisitor.visitVarInsn(ALOAD, 0);
methodVisitor.visitVarInsn(ILOAD, 1);
methodVisitor.visitInsn(ICONST_3);
methodVisitor.visitInsn(IADD);
methodVisitor.visitMethodInsn(INVOKEVIRTUAL, "java/nio/ByteBuffer", "get", "(I)B", false);
methodVisitor.visitIntInsn(SIPUSH, 255);
methodVisitor.visitInsn(IAND);
methodVisitor.visitInsn(IADD);
methodVisitor.visitInsn(IRETURN);
methodVisitor.visitMaxs(4, 2);
methodVisitor.visitEnd();
}
{
methodVisitor = classWriter.visitMethod(ACC_STATIC, "set31Bits", "([BII)V", null, null);
methodVisitor.visitCode();
methodVisitor.visitVarInsn(ALOAD, 0);
methodVisitor.visitVarInsn(ILOAD, 1);
methodVisitor.visitVarInsn(ILOAD, 2);
methodVisitor.visitLdcInsn(new Integer(2130706432));
methodVisitor.visitInsn(IAND);
methodVisitor.visitIntInsn(BIPUSH, 24);
methodVisitor.visitInsn(ISHR);
methodVisitor.visitInsn(I2B);
methodVisitor.visitInsn(BASTORE);
methodVisitor.visitVarInsn(ALOAD, 0);
methodVisitor.visitVarInsn(ILOAD, 1);
methodVisitor.visitInsn(ICONST_1);
methodVisitor.visitInsn(IADD);
methodVisitor.visitVarInsn(ILOAD, 2);
methodVisitor.visitLdcInsn(new Integer(16711680));
methodVisitor.visitInsn(IAND);
methodVisitor.visitIntInsn(BIPUSH, 16);
methodVisitor.visitInsn(ISHR);
methodVisitor.visitInsn(I2B);
methodVisitor.visitInsn(BASTORE);
methodVisitor.visitVarInsn(ALOAD, 0);
methodVisitor.visitVarInsn(ILOAD, 1);
methodVisitor.visitInsn(ICONST_2);
methodVisitor.visitInsn(IADD);
methodVisitor.visitVarInsn(ILOAD, 2);
methodVisitor.visitLdcInsn(new Integer(65280));
methodVisitor.visitInsn(IAND);
methodVisitor.visitIntInsn(BIPUSH, 8);
methodVisitor.visitInsn(ISHR);
methodVisitor.visitInsn(I2B);
methodVisitor.visitInsn(BASTORE);
methodVisitor.visitVarInsn(ALOAD, 0);
methodVisitor.visitVarInsn(ILOAD, 1);
methodVisitor.visitInsn(ICONST_3);
methodVisitor.visitInsn(IADD);
methodVisitor.visitVarInsn(ILOAD, 2);
methodVisitor.visitIntInsn(SIPUSH, 255);
methodVisitor.visitInsn(IAND);
methodVisitor.visitInsn(I2B);
methodVisitor.visitInsn(BASTORE);
methodVisitor.visitInsn(RETURN);
methodVisitor.visitMaxs(4, 3);
methodVisitor.visitEnd();
}
{
methodVisitor = classWriter.visitMethod(ACC_STATIC, "getOneByte", "([BI)I", null, null);
methodVisitor.visitCode();
methodVisitor.visitVarInsn(ALOAD, 0);
methodVisitor.visitVarInsn(ILOAD, 1);
methodVisitor.visitInsn(BALOAD);
methodVisitor.visitIntInsn(SIPUSH, 255);
methodVisitor.visitInsn(IAND);
methodVisitor.visitInsn(IRETURN);
methodVisitor.visitMaxs(2, 2);
methodVisitor.visitEnd();
}
{
methodVisitor = classWriter.visitMethod(ACC_STATIC, "getOneByte", "(Ljava/nio/ByteBuffer;I)I", null, null);
methodVisitor.visitCode();
methodVisitor.visitVarInsn(ALOAD, 0);
methodVisitor.visitVarInsn(ILOAD, 1);
methodVisitor.visitMethodInsn(INVOKEVIRTUAL, "java/nio/ByteBuffer", "get", "(I)B", false);
methodVisitor.visitIntInsn(SIPUSH, 255);
methodVisitor.visitInsn(IAND);
methodVisitor.visitInsn(IRETURN);
methodVisitor.visitMaxs(2, 2);
methodVisitor.visitEnd();
}
{
methodVisitor = classWriter.visitMethod(ACC_STATIC, "getTwoBytes", "([BI)I", null, null);
methodVisitor.visitCode();
methodVisitor.visitVarInsn(ALOAD, 0);
methodVisitor.visitVarInsn(ILOAD, 1);
methodVisitor.visitInsn(BALOAD);
methodVisitor.visitIntInsn(SIPUSH, 255);
methodVisitor.visitInsn(IAND);
methodVisitor.visitIntInsn(BIPUSH, 8);
methodVisitor.visitInsn(ISHL);
methodVisitor.visitVarInsn(ALOAD, 0);
methodVisitor.visitVarInsn(ILOAD, 1);
methodVisitor.visitInsn(ICONST_1);
methodVisitor.visitInsn(IADD);
methodVisitor.visitInsn(BALOAD);
methodVisitor.visitIntInsn(SIPUSH, 255);
methodVisitor.visitInsn(IAND);
methodVisitor.visitInsn(IADD);
methodVisitor.visitInsn(IRETURN);
methodVisitor.visitMaxs(4, 2);
methodVisitor.visitEnd();
}
{
methodVisitor = classWriter.visitMethod(ACC_STATIC, "getThreeBytes", "([BI)I", null, null);
methodVisitor.visitCode();
methodVisitor.visitVarInsn(ALOAD, 0);
methodVisitor.visitVarInsn(ILOAD, 1);
methodVisitor.visitInsn(BALOAD);
methodVisitor.visitIntInsn(SIPUSH, 255);
methodVisitor.visitInsn(IAND);
methodVisitor.visitIntInsn(BIPUSH, 16);
methodVisitor.visitInsn(ISHL);
methodVisitor.visitVarInsn(ALOAD, 0);
methodVisitor.visitVarInsn(ILOAD, 1);
methodVisitor.visitInsn(ICONST_1);
methodVisitor.visitInsn(IADD);
methodVisitor.visitInsn(BALOAD);
methodVisitor.visitIntInsn(SIPUSH, 255);
methodVisitor.visitInsn(IAND);
methodVisitor.visitIntInsn(BIPUSH, 8);
methodVisitor.visitInsn(ISHL);
methodVisitor.visitInsn(IADD);
methodVisitor.visitVarInsn(ALOAD, 0);
methodVisitor.visitVarInsn(ILOAD, 1);
methodVisitor.visitInsn(ICONST_2);
methodVisitor.visitInsn(IADD);
methodVisitor.visitInsn(BALOAD);
methodVisitor.visitIntInsn(SIPUSH, 255);
methodVisitor.visitInsn(IAND);
methodVisitor.visitInsn(IADD);
methodVisitor.visitInsn(IRETURN);
methodVisitor.visitMaxs(4, 2);
methodVisitor.visitEnd();
}
{
methodVisitor = classWriter.visitMethod(ACC_STATIC, "getThreeBytes", "(Ljava/nio/ByteBuffer;I)I", null, null);
methodVisitor.visitCode();
methodVisitor.visitVarInsn(ALOAD, 0);
methodVisitor.visitVarInsn(ILOAD, 1);
methodVisitor.visitMethodInsn(INVOKEVIRTUAL, "java/nio/ByteBuffer", "get", "(I)B", false);
methodVisitor.visitIntInsn(SIPUSH, 255);
methodVisitor.visitInsn(IAND);
methodVisitor.visitIntInsn(BIPUSH, 16);
methodVisitor.visitInsn(ISHL);
methodVisitor.visitVarInsn(ALOAD, 0);
methodVisitor.visitVarInsn(ILOAD, 1);
methodVisitor.visitInsn(ICONST_1);
methodVisitor.visitInsn(IADD);
methodVisitor.visitMethodInsn(INVOKEVIRTUAL, "java/nio/ByteBuffer", "get", "(I)B", false);
methodVisitor.visitIntInsn(SIPUSH, 255);
methodVisitor.visitInsn(IAND);
methodVisitor.visitIntInsn(BIPUSH, 8);
methodVisitor.visitInsn(ISHL);
methodVisitor.visitInsn(IADD);
methodVisitor.visitVarInsn(ALOAD, 0);
methodVisitor.visitVarInsn(ILOAD, 1);
methodVisitor.visitInsn(ICONST_2);
methodVisitor.visitInsn(IADD);
methodVisitor.visitMethodInsn(INVOKEVIRTUAL, "java/nio/ByteBuffer", "get", "(I)B", false);
methodVisitor.visitIntInsn(SIPUSH, 255);
methodVisitor.visitInsn(IAND);
methodVisitor.visitInsn(IADD);
methodVisitor.visitInsn(IRETURN);
methodVisitor.visitMaxs(4, 2);
methodVisitor.visitEnd();
}
{
methodVisitor = classWriter.visitMethod(ACC_STATIC, "setTwoBytes", "([BII)V", null, null);
methodVisitor.visitCode();
methodVisitor.visitVarInsn(ALOAD, 0);
methodVisitor.visitVarInsn(ILOAD, 1);
methodVisitor.visitVarInsn(ILOAD, 2);
methodVisitor.visitLdcInsn(new Integer(65280));
methodVisitor.visitInsn(IAND);
methodVisitor.visitIntInsn(BIPUSH, 8);
methodVisitor.visitInsn(ISHR);
methodVisitor.visitInsn(I2B);
methodVisitor.visitInsn(BASTORE);
methodVisitor.visitVarInsn(ALOAD, 0);
methodVisitor.visitVarInsn(ILOAD, 1);
methodVisitor.visitInsn(ICONST_1);
methodVisitor.visitInsn(IADD);
methodVisitor.visitVarInsn(ILOAD, 2);
methodVisitor.visitIntInsn(SIPUSH, 255);
methodVisitor.visitInsn(IAND);
methodVisitor.visitInsn(I2B);
methodVisitor.visitInsn(BASTORE);
methodVisitor.visitInsn(RETURN);
methodVisitor.visitMaxs(4, 3);
methodVisitor.visitEnd();
}
{
methodVisitor = classWriter.visitMethod(ACC_STATIC, "setThreeBytes", "([BII)V", null, null);
methodVisitor.visitCode();
methodVisitor.visitVarInsn(ALOAD, 0);
methodVisitor.visitVarInsn(ILOAD, 1);
methodVisitor.visitVarInsn(ILOAD, 2);
methodVisitor.visitLdcInsn(new Integer(16711680));
methodVisitor.visitInsn(IAND);
methodVisitor.visitIntInsn(BIPUSH, 16);
methodVisitor.visitInsn(ISHR);
methodVisitor.visitInsn(I2B);
methodVisitor.visitInsn(BASTORE);
methodVisitor.visitVarInsn(ALOAD, 0);
methodVisitor.visitVarInsn(ILOAD, 1);
methodVisitor.visitInsn(ICONST_1);
methodVisitor.visitInsn(IADD);
methodVisitor.visitVarInsn(ILOAD, 2);
methodVisitor.visitLdcInsn(new Integer(65280));
methodVisitor.visitInsn(IAND);
methodVisitor.visitIntInsn(BIPUSH, 8);
methodVisitor.visitInsn(ISHR);
methodVisitor.visitInsn(I2B);
methodVisitor.visitInsn(BASTORE);
methodVisitor.visitVarInsn(ALOAD, 0);
methodVisitor.visitVarInsn(ILOAD, 1);
methodVisitor.visitInsn(ICONST_2);
methodVisitor.visitInsn(IADD);
methodVisitor.visitVarInsn(ILOAD, 2);
methodVisitor.visitIntInsn(SIPUSH, 255);
methodVisitor.visitInsn(IAND);
methodVisitor.visitInsn(I2B);
methodVisitor.visitInsn(BASTORE);
methodVisitor.visitInsn(RETURN);
methodVisitor.visitMaxs(4, 3);
methodVisitor.visitEnd();
}
{
methodVisitor = classWriter.visitMethod(ACC_STATIC, "getFourBytes", "([BI)J", null, null);
methodVisitor.visitCode();
methodVisitor.visitVarInsn(ALOAD, 0);
methodVisitor.visitVarInsn(ILOAD, 1);
methodVisitor.visitInsn(BALOAD);
methodVisitor.visitIntInsn(SIPUSH, 255);
methodVisitor.visitInsn(IAND);
methodVisitor.visitInsn(I2L);
methodVisitor.visitIntInsn(BIPUSH, 24);
methodVisitor.visitInsn(LSHL);
methodVisitor.visitVarInsn(ALOAD, 0);
methodVisitor.visitVarInsn(ILOAD, 1);
methodVisitor.visitInsn(ICONST_1);
methodVisitor.visitInsn(IADD);
methodVisitor.visitInsn(BALOAD);
methodVisitor.visitIntInsn(SIPUSH, 255);
methodVisitor.visitInsn(IAND);
methodVisitor.visitIntInsn(BIPUSH, 16);
methodVisitor.visitInsn(ISHL);
methodVisitor.visitInsn(I2L);
methodVisitor.visitInsn(LADD);
methodVisitor.visitVarInsn(ALOAD, 0);
methodVisitor.visitVarInsn(ILOAD, 1);
methodVisitor.visitInsn(ICONST_2);
methodVisitor.visitInsn(IADD);
methodVisitor.visitInsn(BALOAD);
methodVisitor.visitIntInsn(SIPUSH, 255);
methodVisitor.visitInsn(IAND);
methodVisitor.visitIntInsn(BIPUSH, 8);
methodVisitor.visitInsn(ISHL);
methodVisitor.visitInsn(I2L);
methodVisitor.visitInsn(LADD);
methodVisitor.visitVarInsn(ALOAD, 0);
methodVisitor.visitVarInsn(ILOAD, 1);
methodVisitor.visitInsn(ICONST_3);
methodVisitor.visitInsn(IADD);
methodVisitor.visitInsn(BALOAD);
methodVisitor.visitIntInsn(SIPUSH, 255);
methodVisitor.visitInsn(IAND);
methodVisitor.visitInsn(I2L);
methodVisitor.visitInsn(LADD);
methodVisitor.visitInsn(LRETURN);
methodVisitor.visitMaxs(5, 2);
methodVisitor.visitEnd();
}
{
methodVisitor = classWriter.visitMethod(ACC_STATIC, "setFourBytes", "([BIJ)V", null, null);
methodVisitor.visitCode();
methodVisitor.visitVarInsn(ALOAD, 0);
methodVisitor.visitVarInsn(ILOAD, 1);
methodVisitor.visitVarInsn(LLOAD, 2);
methodVisitor.visitLdcInsn(new Long(-16777216L));
methodVisitor.visitInsn(LAND);
methodVisitor.visitIntInsn(BIPUSH, 24);
methodVisitor.visitInsn(LSHR);
methodVisitor.visitInsn(L2I);
methodVisitor.visitInsn(I2B);
methodVisitor.visitInsn(BASTORE);
methodVisitor.visitVarInsn(ALOAD, 0);
methodVisitor.visitVarInsn(ILOAD, 1);
methodVisitor.visitInsn(ICONST_1);
methodVisitor.visitInsn(IADD);
methodVisitor.visitVarInsn(LLOAD, 2);
methodVisitor.visitLdcInsn(new Long(16711680L));
methodVisitor.visitInsn(LAND);
methodVisitor.visitIntInsn(BIPUSH, 16);
methodVisitor.visitInsn(LSHR);
methodVisitor.visitInsn(L2I);
methodVisitor.visitInsn(I2B);
methodVisitor.visitInsn(BASTORE);
methodVisitor.visitVarInsn(ALOAD, 0);
methodVisitor.visitVarInsn(ILOAD, 1);
methodVisitor.visitInsn(ICONST_2);
methodVisitor.visitInsn(IADD);
methodVisitor.visitVarInsn(LLOAD, 2);
methodVisitor.visitLdcInsn(new Long(65280L));
methodVisitor.visitInsn(LAND);
methodVisitor.visitIntInsn(BIPUSH, 8);
methodVisitor.visitInsn(LSHR);
methodVisitor.visitInsn(L2I);
methodVisitor.visitInsn(I2B);
methodVisitor.visitInsn(BASTORE);
methodVisitor.visitVarInsn(ALOAD, 0);
methodVisitor.visitVarInsn(ILOAD, 1);
methodVisitor.visitInsn(ICONST_3);
methodVisitor.visitInsn(IADD);
methodVisitor.visitVarInsn(LLOAD, 2);
methodVisitor.visitLdcInsn(new Long(255L));
methodVisitor.visitInsn(LAND);
methodVisitor.visitInsn(L2I);
methodVisitor.visitInsn(I2B);
methodVisitor.visitInsn(BASTORE);
methodVisitor.visitInsn(RETURN);
methodVisitor.visitMaxs(6, 4);
methodVisitor.visitEnd();
}
classWriter.visitEnd();

return classWriter.toByteArray();
}
}
