package asm.com.sun.xml.fastinfoset.algorithm;
import org.objectweb.asm.AnnotationVisitor;
import org.objectweb.asm.Attribute;
import org.objectweb.asm.ClassReader;
import org.objectweb.asm.ClassWriter;
import org.objectweb.asm.ConstantDynamic;
import org.objectweb.asm.FieldVisitor;
import org.objectweb.asm.Handle;
import org.objectweb.asm.Label;
import org.objectweb.asm.MethodVisitor;
import org.objectweb.asm.Opcodes;
import org.objectweb.asm.RecordComponentVisitor;
import org.objectweb.asm.Type;
import org.objectweb.asm.TypePath;
public class UUIDEncodingAlgorithmDump implements Opcodes {

public static byte[] dump () throws Exception {

ClassWriter classWriter = new ClassWriter(0);
FieldVisitor fieldVisitor;
RecordComponentVisitor recordComponentVisitor;
MethodVisitor methodVisitor;
AnnotationVisitor annotationVisitor0;

classWriter.visit(V1_6, ACC_PUBLIC | ACC_SUPER, "com/sun/xml/fastinfoset/algorithm/UUIDEncodingAlgorithm", null, "com/sun/xml/fastinfoset/algorithm/LongEncodingAlgorithm", null);

classWriter.visitInnerClass("com/sun/xml/fastinfoset/algorithm/UUIDEncodingAlgorithm$1", null, null, 0);

classWriter.visitInnerClass("com/sun/xml/fastinfoset/algorithm/BuiltInEncodingAlgorithm$WordListener", "com/sun/xml/fastinfoset/algorithm/BuiltInEncodingAlgorithm", "WordListener", ACC_PUBLIC | ACC_STATIC | ACC_ABSTRACT | ACC_INTERFACE);

{
fieldVisitor = classWriter.visitField(ACC_PRIVATE, "_msb", "J", null, null);
fieldVisitor.visitEnd();
}
{
fieldVisitor = classWriter.visitField(ACC_PRIVATE, "_lsb", "J", null, null);
fieldVisitor.visitEnd();
}
{
methodVisitor = classWriter.visitMethod(ACC_PUBLIC, "<init>", "()V", null, null);
methodVisitor.visitCode();
methodVisitor.visitVarInsn(ALOAD, 0);
methodVisitor.visitMethodInsn(INVOKESPECIAL, "com/sun/xml/fastinfoset/algorithm/LongEncodingAlgorithm", "<init>", "()V", false);
methodVisitor.visitInsn(RETURN);
methodVisitor.visitMaxs(1, 1);
methodVisitor.visitEnd();
}
{
methodVisitor = classWriter.visitMethod(ACC_PUBLIC | ACC_FINAL, "getPrimtiveLengthFromOctetLength", "(I)I", null, new String[] { "org/jvnet/fastinfoset/EncodingAlgorithmException" });
methodVisitor.visitCode();
methodVisitor.visitVarInsn(ILOAD, 1);
methodVisitor.visitIntInsn(BIPUSH, 16);
methodVisitor.visitInsn(IREM);
Label label0 = new Label();
methodVisitor.visitJumpInsn(IFEQ, label0);
methodVisitor.visitTypeInsn(NEW, "org/jvnet/fastinfoset/EncodingAlgorithmException");
methodVisitor.visitInsn(DUP);
methodVisitor.visitMethodInsn(INVOKESTATIC, "com/sun/xml/fastinfoset/CommonResourceBundle", "getInstance", "()Lcom/sun/xml/fastinfoset/CommonResourceBundle;", false);
methodVisitor.visitLdcInsn("message.lengthNotMultipleOfUUID");
methodVisitor.visitInsn(ICONST_1);
methodVisitor.visitTypeInsn(ANEWARRAY, "java/lang/Object");
methodVisitor.visitInsn(DUP);
methodVisitor.visitInsn(ICONST_0);
methodVisitor.visitIntInsn(BIPUSH, 16);
methodVisitor.visitMethodInsn(INVOKESTATIC, "java/lang/Integer", "valueOf", "(I)Ljava/lang/Integer;", false);
methodVisitor.visitInsn(AASTORE);
methodVisitor.visitMethodInsn(INVOKEVIRTUAL, "com/sun/xml/fastinfoset/CommonResourceBundle", "getString", "(Ljava/lang/String;[Ljava/lang/Object;)Ljava/lang/String;", false);
methodVisitor.visitMethodInsn(INVOKESPECIAL, "org/jvnet/fastinfoset/EncodingAlgorithmException", "<init>", "(Ljava/lang/String;)V", false);
methodVisitor.visitInsn(ATHROW);
methodVisitor.visitLabel(label0);
methodVisitor.visitFrame(Opcodes.F_SAME, 0, null, 0, null);
methodVisitor.visitVarInsn(ILOAD, 1);
methodVisitor.visitIntInsn(BIPUSH, 8);
methodVisitor.visitInsn(IDIV);
methodVisitor.visitInsn(IRETURN);
methodVisitor.visitMaxs(8, 2);
methodVisitor.visitEnd();
}
{
methodVisitor = classWriter.visitMethod(ACC_PUBLIC | ACC_FINAL, "convertFromCharacters", "([CII)Ljava/lang/Object;", null, null);
methodVisitor.visitCode();
methodVisitor.visitVarInsn(ALOAD, 1);
methodVisitor.visitVarInsn(ILOAD, 2);
methodVisitor.visitVarInsn(ILOAD, 3);
methodVisitor.visitMethodInsn(INVOKESTATIC, "java/nio/CharBuffer", "wrap", "([CII)Ljava/nio/CharBuffer;", false);
methodVisitor.visitVarInsn(ASTORE, 4);
methodVisitor.visitTypeInsn(NEW, "java/util/ArrayList");
methodVisitor.visitInsn(DUP);
methodVisitor.visitMethodInsn(INVOKESPECIAL, "java/util/ArrayList", "<init>", "()V", false);
methodVisitor.visitVarInsn(ASTORE, 5);
methodVisitor.visitVarInsn(ALOAD, 0);
methodVisitor.visitVarInsn(ALOAD, 4);
methodVisitor.visitTypeInsn(NEW, "com/sun/xml/fastinfoset/algorithm/UUIDEncodingAlgorithm$1");
methodVisitor.visitInsn(DUP);
methodVisitor.visitVarInsn(ALOAD, 0);
methodVisitor.visitVarInsn(ALOAD, 4);
methodVisitor.visitVarInsn(ALOAD, 5);
methodVisitor.visitMethodInsn(INVOKESPECIAL, "com/sun/xml/fastinfoset/algorithm/UUIDEncodingAlgorithm$1", "<init>", "(Lcom/sun/xml/fastinfoset/algorithm/UUIDEncodingAlgorithm;Ljava/nio/CharBuffer;Ljava/util/List;)V", false);
methodVisitor.visitMethodInsn(INVOKEVIRTUAL, "com/sun/xml/fastinfoset/algorithm/UUIDEncodingAlgorithm", "matchWhiteSpaceDelimnatedWords", "(Ljava/nio/CharBuffer;Lcom/sun/xml/fastinfoset/algorithm/BuiltInEncodingAlgorithm$WordListener;)V", false);
methodVisitor.visitVarInsn(ALOAD, 0);
methodVisitor.visitVarInsn(ALOAD, 5);
methodVisitor.visitMethodInsn(INVOKEVIRTUAL, "com/sun/xml/fastinfoset/algorithm/UUIDEncodingAlgorithm", "generateArrayFromList", "(Ljava/util/List;)[J", false);
methodVisitor.visitInsn(ARETURN);
methodVisitor.visitMaxs(7, 6);
methodVisitor.visitEnd();
}
{
methodVisitor = classWriter.visitMethod(ACC_PUBLIC | ACC_FINAL, "convertToCharacters", "(Ljava/lang/Object;Ljava/lang/StringBuffer;)V", null, null);
methodVisitor.visitCode();
methodVisitor.visitVarInsn(ALOAD, 1);
methodVisitor.visitTypeInsn(INSTANCEOF, "[J");
Label label0 = new Label();
methodVisitor.visitJumpInsn(IFNE, label0);
methodVisitor.visitTypeInsn(NEW, "java/lang/IllegalArgumentException");
methodVisitor.visitInsn(DUP);
methodVisitor.visitMethodInsn(INVOKESTATIC, "com/sun/xml/fastinfoset/CommonResourceBundle", "getInstance", "()Lcom/sun/xml/fastinfoset/CommonResourceBundle;", false);
methodVisitor.visitLdcInsn("message.dataNotLongArray");
methodVisitor.visitMethodInsn(INVOKEVIRTUAL, "com/sun/xml/fastinfoset/CommonResourceBundle", "getString", "(Ljava/lang/String;)Ljava/lang/String;", false);
methodVisitor.visitMethodInsn(INVOKESPECIAL, "java/lang/IllegalArgumentException", "<init>", "(Ljava/lang/String;)V", false);
methodVisitor.visitInsn(ATHROW);
methodVisitor.visitLabel(label0);
methodVisitor.visitFrame(Opcodes.F_SAME, 0, null, 0, null);
methodVisitor.visitVarInsn(ALOAD, 1);
methodVisitor.visitTypeInsn(CHECKCAST, "[J");
methodVisitor.visitVarInsn(ASTORE, 3);
methodVisitor.visitVarInsn(ALOAD, 3);
methodVisitor.visitInsn(ARRAYLENGTH);
methodVisitor.visitInsn(ICONST_2);
methodVisitor.visitInsn(ISUB);
methodVisitor.visitVarInsn(ISTORE, 4);
methodVisitor.visitInsn(ICONST_0);
methodVisitor.visitVarInsn(ISTORE, 5);
Label label1 = new Label();
methodVisitor.visitLabel(label1);
methodVisitor.visitFrame(Opcodes.F_APPEND,3, new Object[] {"[J", Opcodes.INTEGER, Opcodes.INTEGER}, 0, null);
methodVisitor.visitVarInsn(ILOAD, 5);
methodVisitor.visitVarInsn(ILOAD, 4);
Label label2 = new Label();
methodVisitor.visitJumpInsn(IF_ICMPGT, label2);
methodVisitor.visitVarInsn(ALOAD, 2);
methodVisitor.visitVarInsn(ALOAD, 0);
methodVisitor.visitVarInsn(ALOAD, 3);
methodVisitor.visitVarInsn(ILOAD, 5);
methodVisitor.visitInsn(LALOAD);
methodVisitor.visitVarInsn(ALOAD, 3);
methodVisitor.visitVarInsn(ILOAD, 5);
methodVisitor.visitInsn(ICONST_1);
methodVisitor.visitInsn(IADD);
methodVisitor.visitInsn(LALOAD);
methodVisitor.visitMethodInsn(INVOKEVIRTUAL, "com/sun/xml/fastinfoset/algorithm/UUIDEncodingAlgorithm", "toUUIDString", "(JJ)Ljava/lang/String;", false);
methodVisitor.visitMethodInsn(INVOKEVIRTUAL, "java/lang/StringBuffer", "append", "(Ljava/lang/String;)Ljava/lang/StringBuffer;", false);
methodVisitor.visitInsn(POP);
methodVisitor.visitVarInsn(ILOAD, 5);
methodVisitor.visitVarInsn(ILOAD, 4);
Label label3 = new Label();
methodVisitor.visitJumpInsn(IF_ICMPEQ, label3);
methodVisitor.visitVarInsn(ALOAD, 2);
methodVisitor.visitIntInsn(BIPUSH, 32);
methodVisitor.visitMethodInsn(INVOKEVIRTUAL, "java/lang/StringBuffer", "append", "(C)Ljava/lang/StringBuffer;", false);
methodVisitor.visitInsn(POP);
methodVisitor.visitLabel(label3);
methodVisitor.visitFrame(Opcodes.F_SAME, 0, null, 0, null);
methodVisitor.visitIincInsn(5, 2);
methodVisitor.visitJumpInsn(GOTO, label1);
methodVisitor.visitLabel(label2);
methodVisitor.visitFrame(Opcodes.F_CHOP,1, null, 0, null);
methodVisitor.visitInsn(RETURN);
methodVisitor.visitMaxs(7, 6);
methodVisitor.visitEnd();
}
{
methodVisitor = classWriter.visitMethod(ACC_FINAL, "fromUUIDString", "(Ljava/lang/String;)V", null, null);
methodVisitor.visitCode();
methodVisitor.visitVarInsn(ALOAD, 1);
methodVisitor.visitLdcInsn("-");
methodVisitor.visitMethodInsn(INVOKEVIRTUAL, "java/lang/String", "split", "(Ljava/lang/String;)[Ljava/lang/String;", false);
methodVisitor.visitVarInsn(ASTORE, 2);
methodVisitor.visitVarInsn(ALOAD, 2);
methodVisitor.visitInsn(ARRAYLENGTH);
methodVisitor.visitInsn(ICONST_5);
Label label0 = new Label();
methodVisitor.visitJumpInsn(IF_ICMPEQ, label0);
methodVisitor.visitTypeInsn(NEW, "java/lang/IllegalArgumentException");
methodVisitor.visitInsn(DUP);
methodVisitor.visitMethodInsn(INVOKESTATIC, "com/sun/xml/fastinfoset/CommonResourceBundle", "getInstance", "()Lcom/sun/xml/fastinfoset/CommonResourceBundle;", false);
methodVisitor.visitLdcInsn("message.invalidUUID");
methodVisitor.visitInsn(ICONST_1);
methodVisitor.visitTypeInsn(ANEWARRAY, "java/lang/Object");
methodVisitor.visitInsn(DUP);
methodVisitor.visitInsn(ICONST_0);
methodVisitor.visitVarInsn(ALOAD, 1);
methodVisitor.visitInsn(AASTORE);
methodVisitor.visitMethodInsn(INVOKEVIRTUAL, "com/sun/xml/fastinfoset/CommonResourceBundle", "getString", "(Ljava/lang/String;[Ljava/lang/Object;)Ljava/lang/String;", false);
methodVisitor.visitMethodInsn(INVOKESPECIAL, "java/lang/IllegalArgumentException", "<init>", "(Ljava/lang/String;)V", false);
methodVisitor.visitInsn(ATHROW);
methodVisitor.visitLabel(label0);
methodVisitor.visitFrame(Opcodes.F_APPEND,1, new Object[] {"[Ljava/lang/String;"}, 0, null);
methodVisitor.visitInsn(ICONST_0);
methodVisitor.visitVarInsn(ISTORE, 3);
Label label1 = new Label();
methodVisitor.visitLabel(label1);
methodVisitor.visitFrame(Opcodes.F_APPEND,1, new Object[] {Opcodes.INTEGER}, 0, null);
methodVisitor.visitVarInsn(ILOAD, 3);
methodVisitor.visitInsn(ICONST_5);
Label label2 = new Label();
methodVisitor.visitJumpInsn(IF_ICMPGE, label2);
methodVisitor.visitVarInsn(ALOAD, 2);
methodVisitor.visitVarInsn(ILOAD, 3);
methodVisitor.visitTypeInsn(NEW, "java/lang/StringBuilder");
methodVisitor.visitInsn(DUP);
methodVisitor.visitMethodInsn(INVOKESPECIAL, "java/lang/StringBuilder", "<init>", "()V", false);
methodVisitor.visitLdcInsn("0x");
methodVisitor.visitMethodInsn(INVOKEVIRTUAL, "java/lang/StringBuilder", "append", "(Ljava/lang/String;)Ljava/lang/StringBuilder;", false);
methodVisitor.visitVarInsn(ALOAD, 2);
methodVisitor.visitVarInsn(ILOAD, 3);
methodVisitor.visitInsn(AALOAD);
methodVisitor.visitMethodInsn(INVOKEVIRTUAL, "java/lang/StringBuilder", "append", "(Ljava/lang/String;)Ljava/lang/StringBuilder;", false);
methodVisitor.visitMethodInsn(INVOKEVIRTUAL, "java/lang/StringBuilder", "toString", "()Ljava/lang/String;", false);
methodVisitor.visitInsn(AASTORE);
methodVisitor.visitIincInsn(3, 1);
methodVisitor.visitJumpInsn(GOTO, label1);
methodVisitor.visitLabel(label2);
methodVisitor.visitFrame(Opcodes.F_CHOP,1, null, 0, null);
methodVisitor.visitVarInsn(ALOAD, 0);
methodVisitor.visitVarInsn(ALOAD, 2);
methodVisitor.visitInsn(ICONST_0);
methodVisitor.visitInsn(AALOAD);
methodVisitor.visitIntInsn(BIPUSH, 16);
methodVisitor.visitMethodInsn(INVOKESTATIC, "java/lang/Long", "parseLong", "(Ljava/lang/String;I)J", false);
methodVisitor.visitFieldInsn(PUTFIELD, "com/sun/xml/fastinfoset/algorithm/UUIDEncodingAlgorithm", "_msb", "J");
methodVisitor.visitVarInsn(ALOAD, 0);
methodVisitor.visitInsn(DUP);
methodVisitor.visitFieldInsn(GETFIELD, "com/sun/xml/fastinfoset/algorithm/UUIDEncodingAlgorithm", "_msb", "J");
methodVisitor.visitIntInsn(BIPUSH, 16);
methodVisitor.visitInsn(LSHL);
methodVisitor.visitFieldInsn(PUTFIELD, "com/sun/xml/fastinfoset/algorithm/UUIDEncodingAlgorithm", "_msb", "J");
methodVisitor.visitVarInsn(ALOAD, 0);
methodVisitor.visitInsn(DUP);
methodVisitor.visitFieldInsn(GETFIELD, "com/sun/xml/fastinfoset/algorithm/UUIDEncodingAlgorithm", "_msb", "J");
methodVisitor.visitVarInsn(ALOAD, 2);
methodVisitor.visitInsn(ICONST_1);
methodVisitor.visitInsn(AALOAD);
methodVisitor.visitIntInsn(BIPUSH, 16);
methodVisitor.visitMethodInsn(INVOKESTATIC, "java/lang/Long", "parseLong", "(Ljava/lang/String;I)J", false);
methodVisitor.visitInsn(LOR);
methodVisitor.visitFieldInsn(PUTFIELD, "com/sun/xml/fastinfoset/algorithm/UUIDEncodingAlgorithm", "_msb", "J");
methodVisitor.visitVarInsn(ALOAD, 0);
methodVisitor.visitInsn(DUP);
methodVisitor.visitFieldInsn(GETFIELD, "com/sun/xml/fastinfoset/algorithm/UUIDEncodingAlgorithm", "_msb", "J");
methodVisitor.visitIntInsn(BIPUSH, 16);
methodVisitor.visitInsn(LSHL);
methodVisitor.visitFieldInsn(PUTFIELD, "com/sun/xml/fastinfoset/algorithm/UUIDEncodingAlgorithm", "_msb", "J");
methodVisitor.visitVarInsn(ALOAD, 0);
methodVisitor.visitInsn(DUP);
methodVisitor.visitFieldInsn(GETFIELD, "com/sun/xml/fastinfoset/algorithm/UUIDEncodingAlgorithm", "_msb", "J");
methodVisitor.visitVarInsn(ALOAD, 2);
methodVisitor.visitInsn(ICONST_2);
methodVisitor.visitInsn(AALOAD);
methodVisitor.visitIntInsn(BIPUSH, 16);
methodVisitor.visitMethodInsn(INVOKESTATIC, "java/lang/Long", "parseLong", "(Ljava/lang/String;I)J", false);
methodVisitor.visitInsn(LOR);
methodVisitor.visitFieldInsn(PUTFIELD, "com/sun/xml/fastinfoset/algorithm/UUIDEncodingAlgorithm", "_msb", "J");
methodVisitor.visitVarInsn(ALOAD, 0);
methodVisitor.visitVarInsn(ALOAD, 2);
methodVisitor.visitInsn(ICONST_3);
methodVisitor.visitInsn(AALOAD);
methodVisitor.visitIntInsn(BIPUSH, 16);
methodVisitor.visitMethodInsn(INVOKESTATIC, "java/lang/Long", "parseLong", "(Ljava/lang/String;I)J", false);
methodVisitor.visitFieldInsn(PUTFIELD, "com/sun/xml/fastinfoset/algorithm/UUIDEncodingAlgorithm", "_lsb", "J");
methodVisitor.visitVarInsn(ALOAD, 0);
methodVisitor.visitInsn(DUP);
methodVisitor.visitFieldInsn(GETFIELD, "com/sun/xml/fastinfoset/algorithm/UUIDEncodingAlgorithm", "_lsb", "J");
methodVisitor.visitIntInsn(BIPUSH, 48);
methodVisitor.visitInsn(LSHL);
methodVisitor.visitFieldInsn(PUTFIELD, "com/sun/xml/fastinfoset/algorithm/UUIDEncodingAlgorithm", "_lsb", "J");
methodVisitor.visitVarInsn(ALOAD, 0);
methodVisitor.visitInsn(DUP);
methodVisitor.visitFieldInsn(GETFIELD, "com/sun/xml/fastinfoset/algorithm/UUIDEncodingAlgorithm", "_lsb", "J");
methodVisitor.visitVarInsn(ALOAD, 2);
methodVisitor.visitInsn(ICONST_4);
methodVisitor.visitInsn(AALOAD);
methodVisitor.visitIntInsn(BIPUSH, 16);
methodVisitor.visitMethodInsn(INVOKESTATIC, "java/lang/Long", "parseLong", "(Ljava/lang/String;I)J", false);
methodVisitor.visitInsn(LOR);
methodVisitor.visitFieldInsn(PUTFIELD, "com/sun/xml/fastinfoset/algorithm/UUIDEncodingAlgorithm", "_lsb", "J");
methodVisitor.visitInsn(RETURN);
methodVisitor.visitMaxs(8, 4);
methodVisitor.visitEnd();
}
{
methodVisitor = classWriter.visitMethod(ACC_FINAL, "toUUIDString", "(JJ)Ljava/lang/String;", null, null);
methodVisitor.visitCode();
methodVisitor.visitTypeInsn(NEW, "java/lang/StringBuilder");
methodVisitor.visitInsn(DUP);
methodVisitor.visitMethodInsn(INVOKESPECIAL, "java/lang/StringBuilder", "<init>", "()V", false);
methodVisitor.visitVarInsn(ALOAD, 0);
methodVisitor.visitVarInsn(LLOAD, 1);
methodVisitor.visitIntInsn(BIPUSH, 32);
methodVisitor.visitInsn(LSHR);
methodVisitor.visitIntInsn(BIPUSH, 8);
methodVisitor.visitMethodInsn(INVOKEVIRTUAL, "com/sun/xml/fastinfoset/algorithm/UUIDEncodingAlgorithm", "digits", "(JI)Ljava/lang/String;", false);
methodVisitor.visitMethodInsn(INVOKEVIRTUAL, "java/lang/StringBuilder", "append", "(Ljava/lang/String;)Ljava/lang/StringBuilder;", false);
methodVisitor.visitLdcInsn("-");
methodVisitor.visitMethodInsn(INVOKEVIRTUAL, "java/lang/StringBuilder", "append", "(Ljava/lang/String;)Ljava/lang/StringBuilder;", false);
methodVisitor.visitVarInsn(ALOAD, 0);
methodVisitor.visitVarInsn(LLOAD, 1);
methodVisitor.visitIntInsn(BIPUSH, 16);
methodVisitor.visitInsn(LSHR);
methodVisitor.visitInsn(ICONST_4);
methodVisitor.visitMethodInsn(INVOKEVIRTUAL, "com/sun/xml/fastinfoset/algorithm/UUIDEncodingAlgorithm", "digits", "(JI)Ljava/lang/String;", false);
methodVisitor.visitMethodInsn(INVOKEVIRTUAL, "java/lang/StringBuilder", "append", "(Ljava/lang/String;)Ljava/lang/StringBuilder;", false);
methodVisitor.visitLdcInsn("-");
methodVisitor.visitMethodInsn(INVOKEVIRTUAL, "java/lang/StringBuilder", "append", "(Ljava/lang/String;)Ljava/lang/StringBuilder;", false);
methodVisitor.visitVarInsn(ALOAD, 0);
methodVisitor.visitVarInsn(LLOAD, 1);
methodVisitor.visitInsn(ICONST_4);
methodVisitor.visitMethodInsn(INVOKEVIRTUAL, "com/sun/xml/fastinfoset/algorithm/UUIDEncodingAlgorithm", "digits", "(JI)Ljava/lang/String;", false);
methodVisitor.visitMethodInsn(INVOKEVIRTUAL, "java/lang/StringBuilder", "append", "(Ljava/lang/String;)Ljava/lang/StringBuilder;", false);
methodVisitor.visitLdcInsn("-");
methodVisitor.visitMethodInsn(INVOKEVIRTUAL, "java/lang/StringBuilder", "append", "(Ljava/lang/String;)Ljava/lang/StringBuilder;", false);
methodVisitor.visitVarInsn(ALOAD, 0);
methodVisitor.visitVarInsn(LLOAD, 3);
methodVisitor.visitIntInsn(BIPUSH, 48);
methodVisitor.visitInsn(LSHR);
methodVisitor.visitInsn(ICONST_4);
methodVisitor.visitMethodInsn(INVOKEVIRTUAL, "com/sun/xml/fastinfoset/algorithm/UUIDEncodingAlgorithm", "digits", "(JI)Ljava/lang/String;", false);
methodVisitor.visitMethodInsn(INVOKEVIRTUAL, "java/lang/StringBuilder", "append", "(Ljava/lang/String;)Ljava/lang/StringBuilder;", false);
methodVisitor.visitLdcInsn("-");
methodVisitor.visitMethodInsn(INVOKEVIRTUAL, "java/lang/StringBuilder", "append", "(Ljava/lang/String;)Ljava/lang/StringBuilder;", false);
methodVisitor.visitVarInsn(ALOAD, 0);
methodVisitor.visitVarInsn(LLOAD, 3);
methodVisitor.visitIntInsn(BIPUSH, 12);
methodVisitor.visitMethodInsn(INVOKEVIRTUAL, "com/sun/xml/fastinfoset/algorithm/UUIDEncodingAlgorithm", "digits", "(JI)Ljava/lang/String;", false);
methodVisitor.visitMethodInsn(INVOKEVIRTUAL, "java/lang/StringBuilder", "append", "(Ljava/lang/String;)Ljava/lang/StringBuilder;", false);
methodVisitor.visitMethodInsn(INVOKEVIRTUAL, "java/lang/StringBuilder", "toString", "()Ljava/lang/String;", false);
methodVisitor.visitInsn(ARETURN);
methodVisitor.visitMaxs(5, 5);
methodVisitor.visitEnd();
}
{
methodVisitor = classWriter.visitMethod(ACC_FINAL, "digits", "(JI)Ljava/lang/String;", null, null);
methodVisitor.visitCode();
methodVisitor.visitInsn(LCONST_1);
methodVisitor.visitVarInsn(ILOAD, 3);
methodVisitor.visitInsn(ICONST_4);
methodVisitor.visitInsn(IMUL);
methodVisitor.visitInsn(LSHL);
methodVisitor.visitVarInsn(LSTORE, 4);
methodVisitor.visitVarInsn(LLOAD, 4);
methodVisitor.visitVarInsn(LLOAD, 1);
methodVisitor.visitVarInsn(LLOAD, 4);
methodVisitor.visitInsn(LCONST_1);
methodVisitor.visitInsn(LSUB);
methodVisitor.visitInsn(LAND);
methodVisitor.visitInsn(LOR);
methodVisitor.visitMethodInsn(INVOKESTATIC, "java/lang/Long", "toHexString", "(J)Ljava/lang/String;", false);
methodVisitor.visitInsn(ICONST_1);
methodVisitor.visitMethodInsn(INVOKEVIRTUAL, "java/lang/String", "substring", "(I)Ljava/lang/String;", false);
methodVisitor.visitInsn(ARETURN);
methodVisitor.visitMaxs(8, 6);
methodVisitor.visitEnd();
}
{
methodVisitor = classWriter.visitMethod(ACC_STATIC | ACC_SYNTHETIC, "access$000", "(Lcom/sun/xml/fastinfoset/algorithm/UUIDEncodingAlgorithm;)J", null, null);
methodVisitor.visitCode();
methodVisitor.visitVarInsn(ALOAD, 0);
methodVisitor.visitFieldInsn(GETFIELD, "com/sun/xml/fastinfoset/algorithm/UUIDEncodingAlgorithm", "_msb", "J");
methodVisitor.visitInsn(LRETURN);
methodVisitor.visitMaxs(2, 1);
methodVisitor.visitEnd();
}
{
methodVisitor = classWriter.visitMethod(ACC_STATIC | ACC_SYNTHETIC, "access$100", "(Lcom/sun/xml/fastinfoset/algorithm/UUIDEncodingAlgorithm;)J", null, null);
methodVisitor.visitCode();
methodVisitor.visitVarInsn(ALOAD, 0);
methodVisitor.visitFieldInsn(GETFIELD, "com/sun/xml/fastinfoset/algorithm/UUIDEncodingAlgorithm", "_lsb", "J");
methodVisitor.visitInsn(LRETURN);
methodVisitor.visitMaxs(2, 1);
methodVisitor.visitEnd();
}
classWriter.visitEnd();

return classWriter.toByteArray();
}
}
