package asm.org.apache.openejb.server.auth;
import org.objectweb.asm.AnnotationVisitor;
import org.objectweb.asm.Attribute;
import org.objectweb.asm.ClassReader;
import org.objectweb.asm.ClassWriter;
import org.objectweb.asm.ConstantDynamic;
import org.objectweb.asm.FieldVisitor;
import org.objectweb.asm.Handle;
import org.objectweb.asm.Label;
import org.objectweb.asm.MethodVisitor;
import org.objectweb.asm.Opcodes;
import org.objectweb.asm.RecordComponentVisitor;
import org.objectweb.asm.Type;
import org.objectweb.asm.TypePath;
public class NetmaskIPv6AddressPermissionDump implements Opcodes {

public static byte[] dump () throws Exception {

ClassWriter classWriter = new ClassWriter(0);
FieldVisitor fieldVisitor;
RecordComponentVisitor recordComponentVisitor;
MethodVisitor methodVisitor;
AnnotationVisitor annotationVisitor0;

classWriter.visit(V1_8, ACC_PUBLIC | ACC_SUPER, "org/apache/openejb/server/auth/NetmaskIPv6AddressPermission", null, "java/lang/Object", new String[] { "org/apache/openejb/server/auth/IPAddressPermission" });

{
fieldVisitor = classWriter.visitField(ACC_PRIVATE | ACC_FINAL | ACC_STATIC, "MASK_VALIDATOR", "Ljava/util/regex/Pattern;", null, null);
fieldVisitor.visitEnd();
}
{
fieldVisitor = classWriter.visitField(ACC_PRIVATE | ACC_FINAL, "networkAddressBytes", "[B", null, null);
fieldVisitor.visitEnd();
}
{
fieldVisitor = classWriter.visitField(ACC_PRIVATE | ACC_FINAL, "netmaskBytes", "[B", null, null);
fieldVisitor.visitEnd();
}
{
methodVisitor = classWriter.visitMethod(ACC_PUBLIC | ACC_STATIC, "canSupport", "(Ljava/lang/String;)Z", null, null);
methodVisitor.visitCode();
methodVisitor.visitFieldInsn(GETSTATIC, "org/apache/openejb/server/auth/NetmaskIPv6AddressPermission", "MASK_VALIDATOR", "Ljava/util/regex/Pattern;");
methodVisitor.visitVarInsn(ALOAD, 0);
methodVisitor.visitMethodInsn(INVOKEVIRTUAL, "java/util/regex/Pattern", "matcher", "(Ljava/lang/CharSequence;)Ljava/util/regex/Matcher;", false);
methodVisitor.visitVarInsn(ASTORE, 1);
methodVisitor.visitVarInsn(ALOAD, 1);
methodVisitor.visitMethodInsn(INVOKEVIRTUAL, "java/util/regex/Matcher", "matches", "()Z", false);
methodVisitor.visitInsn(IRETURN);
methodVisitor.visitMaxs(2, 2);
methodVisitor.visitEnd();
}
{
methodVisitor = classWriter.visitMethod(ACC_PUBLIC, "<init>", "(Ljava/lang/String;)V", null, null);
methodVisitor.visitCode();
methodVisitor.visitVarInsn(ALOAD, 0);
methodVisitor.visitMethodInsn(INVOKESPECIAL, "java/lang/Object", "<init>", "()V", false);
methodVisitor.visitFieldInsn(GETSTATIC, "org/apache/openejb/server/auth/NetmaskIPv6AddressPermission", "MASK_VALIDATOR", "Ljava/util/regex/Pattern;");
methodVisitor.visitVarInsn(ALOAD, 1);
methodVisitor.visitMethodInsn(INVOKEVIRTUAL, "java/util/regex/Pattern", "matcher", "(Ljava/lang/CharSequence;)Ljava/util/regex/Matcher;", false);
methodVisitor.visitVarInsn(ASTORE, 2);
methodVisitor.visitInsn(ICONST_0);
methodVisitor.visitVarInsn(ALOAD, 2);
methodVisitor.visitMethodInsn(INVOKEVIRTUAL, "java/util/regex/Matcher", "matches", "()Z", false);
Label label0 = new Label();
methodVisitor.visitJumpInsn(IF_ICMPNE, label0);
methodVisitor.visitTypeInsn(NEW, "java/lang/IllegalArgumentException");
methodVisitor.visitInsn(DUP);
methodVisitor.visitTypeInsn(NEW, "java/lang/StringBuilder");
methodVisitor.visitInsn(DUP);
methodVisitor.visitMethodInsn(INVOKESPECIAL, "java/lang/StringBuilder", "<init>", "()V", false);
methodVisitor.visitLdcInsn("Mask ");
methodVisitor.visitMethodInsn(INVOKEVIRTUAL, "java/lang/StringBuilder", "append", "(Ljava/lang/String;)Ljava/lang/StringBuilder;", false);
methodVisitor.visitVarInsn(ALOAD, 1);
methodVisitor.visitMethodInsn(INVOKEVIRTUAL, "java/lang/StringBuilder", "append", "(Ljava/lang/String;)Ljava/lang/StringBuilder;", false);
methodVisitor.visitLdcInsn(" does not match pattern ");
methodVisitor.visitMethodInsn(INVOKEVIRTUAL, "java/lang/StringBuilder", "append", "(Ljava/lang/String;)Ljava/lang/StringBuilder;", false);
methodVisitor.visitFieldInsn(GETSTATIC, "org/apache/openejb/server/auth/NetmaskIPv6AddressPermission", "MASK_VALIDATOR", "Ljava/util/regex/Pattern;");
methodVisitor.visitMethodInsn(INVOKEVIRTUAL, "java/util/regex/Pattern", "pattern", "()Ljava/lang/String;", false);
methodVisitor.visitMethodInsn(INVOKEVIRTUAL, "java/lang/StringBuilder", "append", "(Ljava/lang/String;)Ljava/lang/StringBuilder;", false);
methodVisitor.visitMethodInsn(INVOKEVIRTUAL, "java/lang/StringBuilder", "toString", "()Ljava/lang/String;", false);
methodVisitor.visitMethodInsn(INVOKESPECIAL, "java/lang/IllegalArgumentException", "<init>", "(Ljava/lang/String;)V", false);
methodVisitor.visitInsn(ATHROW);
methodVisitor.visitLabel(label0);
methodVisitor.visitFrame(Opcodes.F_FULL, 3, new Object[] {"org/apache/openejb/server/auth/NetmaskIPv6AddressPermission", "java/lang/String", "java/util/regex/Matcher"}, 0, new Object[] {});
methodVisitor.visitVarInsn(ALOAD, 0);
methodVisitor.visitIntInsn(BIPUSH, 16);
methodVisitor.visitIntInsn(NEWARRAY, T_BYTE);
methodVisitor.visitFieldInsn(PUTFIELD, "org/apache/openejb/server/auth/NetmaskIPv6AddressPermission", "networkAddressBytes", "[B");
methodVisitor.visitInsn(ICONST_0);
methodVisitor.visitVarInsn(ISTORE, 3);
methodVisitor.visitTypeInsn(NEW, "java/util/StringTokenizer");
methodVisitor.visitInsn(DUP);
methodVisitor.visitVarInsn(ALOAD, 2);
methodVisitor.visitInsn(ICONST_1);
methodVisitor.visitMethodInsn(INVOKEVIRTUAL, "java/util/regex/Matcher", "group", "(I)Ljava/lang/String;", false);
methodVisitor.visitLdcInsn(":");
methodVisitor.visitMethodInsn(INVOKESPECIAL, "java/util/StringTokenizer", "<init>", "(Ljava/lang/String;Ljava/lang/String;)V", false);
methodVisitor.visitVarInsn(ASTORE, 4);
Label label1 = new Label();
methodVisitor.visitLabel(label1);
methodVisitor.visitFrame(Opcodes.F_APPEND,2, new Object[] {Opcodes.INTEGER, "java/util/StringTokenizer"}, 0, null);
methodVisitor.visitVarInsn(ALOAD, 4);
methodVisitor.visitMethodInsn(INVOKEVIRTUAL, "java/util/StringTokenizer", "hasMoreTokens", "()Z", false);
Label label2 = new Label();
methodVisitor.visitJumpInsn(IFEQ, label2);
methodVisitor.visitVarInsn(ALOAD, 4);
methodVisitor.visitMethodInsn(INVOKEVIRTUAL, "java/util/StringTokenizer", "nextToken", "()Ljava/lang/String;", false);
methodVisitor.visitVarInsn(ASTORE, 5);
methodVisitor.visitVarInsn(ALOAD, 5);
methodVisitor.visitIntInsn(BIPUSH, 16);
methodVisitor.visitMethodInsn(INVOKESTATIC, "java/lang/Integer", "parseInt", "(Ljava/lang/String;I)I", false);
methodVisitor.visitVarInsn(ISTORE, 6);
methodVisitor.visitVarInsn(ALOAD, 0);
methodVisitor.visitFieldInsn(GETFIELD, "org/apache/openejb/server/auth/NetmaskIPv6AddressPermission", "networkAddressBytes", "[B");
methodVisitor.visitVarInsn(ILOAD, 3);
methodVisitor.visitIincInsn(3, 1);
methodVisitor.visitVarInsn(ILOAD, 6);
methodVisitor.visitLdcInsn(new Integer(65280));
methodVisitor.visitInsn(IAND);
methodVisitor.visitIntInsn(BIPUSH, 8);
methodVisitor.visitInsn(ISHR);
methodVisitor.visitInsn(I2B);
methodVisitor.visitInsn(BASTORE);
methodVisitor.visitVarInsn(ALOAD, 0);
methodVisitor.visitFieldInsn(GETFIELD, "org/apache/openejb/server/auth/NetmaskIPv6AddressPermission", "networkAddressBytes", "[B");
methodVisitor.visitVarInsn(ILOAD, 3);
methodVisitor.visitIincInsn(3, 1);
methodVisitor.visitVarInsn(ILOAD, 6);
methodVisitor.visitInsn(I2B);
methodVisitor.visitInsn(BASTORE);
methodVisitor.visitJumpInsn(GOTO, label1);
methodVisitor.visitLabel(label2);
methodVisitor.visitFrame(Opcodes.F_SAME, 0, null, 0, null);
methodVisitor.visitVarInsn(ALOAD, 0);
methodVisitor.visitIntInsn(BIPUSH, 16);
methodVisitor.visitIntInsn(NEWARRAY, T_BYTE);
methodVisitor.visitFieldInsn(PUTFIELD, "org/apache/openejb/server/auth/NetmaskIPv6AddressPermission", "netmaskBytes", "[B");
methodVisitor.visitVarInsn(ALOAD, 2);
methodVisitor.visitInsn(ICONST_4);
methodVisitor.visitMethodInsn(INVOKEVIRTUAL, "java/util/regex/Matcher", "group", "(I)Ljava/lang/String;", false);
methodVisitor.visitVarInsn(ASTORE, 5);
methodVisitor.visitInsn(ACONST_NULL);
methodVisitor.visitVarInsn(ALOAD, 5);
Label label3 = new Label();
methodVisitor.visitJumpInsn(IF_ACMPEQ, label3);
methodVisitor.visitVarInsn(ALOAD, 5);
methodVisitor.visitMethodInsn(INVOKESTATIC, "java/lang/Integer", "parseInt", "(Ljava/lang/String;)I", false);
methodVisitor.visitVarInsn(ISTORE, 6);
methodVisitor.visitVarInsn(ILOAD, 6);
methodVisitor.visitIntInsn(BIPUSH, 8);
methodVisitor.visitInsn(IDIV);
methodVisitor.visitVarInsn(ISTORE, 3);
methodVisitor.visitIntInsn(BIPUSH, 8);
methodVisitor.visitVarInsn(ILOAD, 6);
methodVisitor.visitIntInsn(BIPUSH, 8);
methodVisitor.visitInsn(IREM);
methodVisitor.visitInsn(ISUB);
methodVisitor.visitVarInsn(ISTORE, 7);
methodVisitor.visitInsn(ICONST_0);
methodVisitor.visitVarInsn(ISTORE, 8);
Label label4 = new Label();
methodVisitor.visitLabel(label4);
methodVisitor.visitFrame(Opcodes.F_FULL, 9, new Object[] {"org/apache/openejb/server/auth/NetmaskIPv6AddressPermission", "java/lang/String", "java/util/regex/Matcher", Opcodes.INTEGER, "java/util/StringTokenizer", "java/lang/String", Opcodes.INTEGER, Opcodes.INTEGER, Opcodes.INTEGER}, 0, new Object[] {});
methodVisitor.visitVarInsn(ILOAD, 8);
methodVisitor.visitVarInsn(ILOAD, 3);
Label label5 = new Label();
methodVisitor.visitJumpInsn(IF_ICMPGE, label5);
methodVisitor.visitVarInsn(ALOAD, 0);
methodVisitor.visitFieldInsn(GETFIELD, "org/apache/openejb/server/auth/NetmaskIPv6AddressPermission", "netmaskBytes", "[B");
methodVisitor.visitVarInsn(ILOAD, 8);
methodVisitor.visitInsn(ICONST_M1);
methodVisitor.visitInsn(BASTORE);
methodVisitor.visitIincInsn(8, 1);
methodVisitor.visitJumpInsn(GOTO, label4);
methodVisitor.visitLabel(label5);
methodVisitor.visitFrame(Opcodes.F_CHOP,1, null, 0, null);
methodVisitor.visitVarInsn(ALOAD, 0);
methodVisitor.visitFieldInsn(GETFIELD, "org/apache/openejb/server/auth/NetmaskIPv6AddressPermission", "netmaskBytes", "[B");
methodVisitor.visitVarInsn(ILOAD, 3);
methodVisitor.visitIntInsn(SIPUSH, 255);
methodVisitor.visitVarInsn(ILOAD, 7);
methodVisitor.visitInsn(ISHL);
methodVisitor.visitInsn(I2B);
methodVisitor.visitInsn(BASTORE);
Label label6 = new Label();
methodVisitor.visitJumpInsn(GOTO, label6);
methodVisitor.visitLabel(label3);
methodVisitor.visitFrame(Opcodes.F_CHOP,2, null, 0, null);
methodVisitor.visitInsn(ICONST_0);
methodVisitor.visitVarInsn(ISTORE, 3);
methodVisitor.visitTypeInsn(NEW, "java/util/StringTokenizer");
methodVisitor.visitInsn(DUP);
methodVisitor.visitVarInsn(ALOAD, 2);
methodVisitor.visitInsn(ICONST_5);
methodVisitor.visitMethodInsn(INVOKEVIRTUAL, "java/util/regex/Matcher", "group", "(I)Ljava/lang/String;", false);
methodVisitor.visitLdcInsn(":");
methodVisitor.visitMethodInsn(INVOKESPECIAL, "java/util/StringTokenizer", "<init>", "(Ljava/lang/String;Ljava/lang/String;)V", false);
methodVisitor.visitVarInsn(ASTORE, 4);
Label label7 = new Label();
methodVisitor.visitLabel(label7);
methodVisitor.visitFrame(Opcodes.F_SAME, 0, null, 0, null);
methodVisitor.visitVarInsn(ALOAD, 4);
methodVisitor.visitMethodInsn(INVOKEVIRTUAL, "java/util/StringTokenizer", "hasMoreTokens", "()Z", false);
methodVisitor.visitJumpInsn(IFEQ, label6);
methodVisitor.visitVarInsn(ALOAD, 4);
methodVisitor.visitMethodInsn(INVOKEVIRTUAL, "java/util/StringTokenizer", "nextToken", "()Ljava/lang/String;", false);
methodVisitor.visitVarInsn(ASTORE, 6);
methodVisitor.visitVarInsn(ALOAD, 6);
methodVisitor.visitIntInsn(BIPUSH, 16);
methodVisitor.visitMethodInsn(INVOKESTATIC, "java/lang/Integer", "parseInt", "(Ljava/lang/String;I)I", false);
methodVisitor.visitVarInsn(ISTORE, 7);
methodVisitor.visitVarInsn(ALOAD, 0);
methodVisitor.visitFieldInsn(GETFIELD, "org/apache/openejb/server/auth/NetmaskIPv6AddressPermission", "netmaskBytes", "[B");
methodVisitor.visitVarInsn(ILOAD, 3);
methodVisitor.visitIincInsn(3, 1);
methodVisitor.visitVarInsn(ILOAD, 7);
methodVisitor.visitLdcInsn(new Integer(65280));
methodVisitor.visitInsn(IAND);
methodVisitor.visitIntInsn(BIPUSH, 8);
methodVisitor.visitInsn(ISHR);
methodVisitor.visitInsn(I2B);
methodVisitor.visitInsn(BASTORE);
methodVisitor.visitVarInsn(ALOAD, 0);
methodVisitor.visitFieldInsn(GETFIELD, "org/apache/openejb/server/auth/NetmaskIPv6AddressPermission", "netmaskBytes", "[B");
methodVisitor.visitVarInsn(ILOAD, 3);
methodVisitor.visitIincInsn(3, 1);
methodVisitor.visitVarInsn(ILOAD, 7);
methodVisitor.visitInsn(I2B);
methodVisitor.visitInsn(BASTORE);
methodVisitor.visitJumpInsn(GOTO, label7);
methodVisitor.visitLabel(label6);
methodVisitor.visitFrame(Opcodes.F_SAME, 0, null, 0, null);
methodVisitor.visitInsn(RETURN);
methodVisitor.visitMaxs(4, 9);
methodVisitor.visitEnd();
}
{
methodVisitor = classWriter.visitMethod(ACC_PUBLIC, "implies", "(Ljava/net/InetAddress;)Z", null, null);
methodVisitor.visitCode();
methodVisitor.visitInsn(ICONST_0);
methodVisitor.visitVarInsn(ALOAD, 1);
methodVisitor.visitTypeInsn(INSTANCEOF, "java/net/Inet6Address");
Label label0 = new Label();
methodVisitor.visitJumpInsn(IF_ICMPNE, label0);
methodVisitor.visitInsn(ICONST_0);
methodVisitor.visitInsn(IRETURN);
methodVisitor.visitLabel(label0);
methodVisitor.visitFrame(Opcodes.F_SAME, 0, null, 0, null);
methodVisitor.visitVarInsn(ALOAD, 1);
methodVisitor.visitMethodInsn(INVOKEVIRTUAL, "java/net/InetAddress", "getAddress", "()[B", false);
methodVisitor.visitVarInsn(ASTORE, 2);
methodVisitor.visitInsn(ICONST_0);
methodVisitor.visitVarInsn(ISTORE, 3);
Label label1 = new Label();
methodVisitor.visitLabel(label1);
methodVisitor.visitFrame(Opcodes.F_APPEND,2, new Object[] {"[B", Opcodes.INTEGER}, 0, null);
methodVisitor.visitVarInsn(ILOAD, 3);
methodVisitor.visitIntInsn(BIPUSH, 16);
Label label2 = new Label();
methodVisitor.visitJumpInsn(IF_ICMPGE, label2);
methodVisitor.visitVarInsn(ALOAD, 0);
methodVisitor.visitFieldInsn(GETFIELD, "org/apache/openejb/server/auth/NetmaskIPv6AddressPermission", "netmaskBytes", "[B");
methodVisitor.visitVarInsn(ILOAD, 3);
methodVisitor.visitInsn(BALOAD);
methodVisitor.visitVarInsn(ALOAD, 2);
methodVisitor.visitVarInsn(ILOAD, 3);
methodVisitor.visitInsn(BALOAD);
methodVisitor.visitInsn(IAND);
methodVisitor.visitVarInsn(ALOAD, 0);
methodVisitor.visitFieldInsn(GETFIELD, "org/apache/openejb/server/auth/NetmaskIPv6AddressPermission", "networkAddressBytes", "[B");
methodVisitor.visitVarInsn(ILOAD, 3);
methodVisitor.visitInsn(BALOAD);
Label label3 = new Label();
methodVisitor.visitJumpInsn(IF_ICMPEQ, label3);
methodVisitor.visitInsn(ICONST_0);
methodVisitor.visitInsn(IRETURN);
methodVisitor.visitLabel(label3);
methodVisitor.visitFrame(Opcodes.F_SAME, 0, null, 0, null);
methodVisitor.visitIincInsn(3, 1);
methodVisitor.visitJumpInsn(GOTO, label1);
methodVisitor.visitLabel(label2);
methodVisitor.visitFrame(Opcodes.F_CHOP,1, null, 0, null);
methodVisitor.visitInsn(ICONST_1);
methodVisitor.visitInsn(IRETURN);
methodVisitor.visitMaxs(3, 4);
methodVisitor.visitEnd();
}
{
methodVisitor = classWriter.visitMethod(ACC_STATIC, "<clinit>", "()V", null, null);
methodVisitor.visitCode();
methodVisitor.visitLdcInsn("^(([a-fA-F0-9]{1,4}:){7}[a-fA-F0-9]{1,4})/((\\d{1,3})|(([a-fA-F0-9]{1,4}:){7}[a-fA-F0-9]{1,4}))$");
methodVisitor.visitMethodInsn(INVOKESTATIC, "java/util/regex/Pattern", "compile", "(Ljava/lang/String;)Ljava/util/regex/Pattern;", false);
methodVisitor.visitFieldInsn(PUTSTATIC, "org/apache/openejb/server/auth/NetmaskIPv6AddressPermission", "MASK_VALIDATOR", "Ljava/util/regex/Pattern;");
methodVisitor.visitInsn(RETURN);
methodVisitor.visitMaxs(1, 0);
methodVisitor.visitEnd();
}
classWriter.visitEnd();

return classWriter.toByteArray();
}
}
