package asm.javax.xml.transform.dom;
import org.objectweb.asm.AnnotationVisitor;
import org.objectweb.asm.Attribute;
import org.objectweb.asm.ClassReader;
import org.objectweb.asm.ClassWriter;
import org.objectweb.asm.ConstantDynamic;
import org.objectweb.asm.FieldVisitor;
import org.objectweb.asm.Handle;
import org.objectweb.asm.Label;
import org.objectweb.asm.MethodVisitor;
import org.objectweb.asm.Opcodes;
import org.objectweb.asm.RecordComponentVisitor;
import org.objectweb.asm.Type;
import org.objectweb.asm.TypePath;
public class DOMResultDump implements Opcodes {

public static byte[] dump () throws Exception {

ClassWriter classWriter = new ClassWriter(0);
FieldVisitor fieldVisitor;
RecordComponentVisitor recordComponentVisitor;
MethodVisitor methodVisitor;
AnnotationVisitor annotationVisitor0;

classWriter.visit(V1_1, ACC_PUBLIC | ACC_SUPER, "javax/xml/transform/dom/DOMResult", null, "java/lang/Object", new String[] { "javax/xml/transform/Result" });

{
fieldVisitor = classWriter.visitField(ACC_PUBLIC | ACC_FINAL | ACC_STATIC, "FEATURE", "Ljava/lang/String;", null, "http://javax.xml.transform.dom.DOMResult/feature");
fieldVisitor.visitEnd();
}
{
fieldVisitor = classWriter.visitField(ACC_PRIVATE, "node", "Lorg/w3c/dom/Node;", null, null);
fieldVisitor.visitEnd();
}
{
fieldVisitor = classWriter.visitField(ACC_PRIVATE, "nextSibling", "Lorg/w3c/dom/Node;", null, null);
fieldVisitor.visitEnd();
}
{
fieldVisitor = classWriter.visitField(ACC_PRIVATE, "systemId", "Ljava/lang/String;", null, null);
fieldVisitor.visitEnd();
}
{
methodVisitor = classWriter.visitMethod(ACC_PUBLIC, "<init>", "()V", null, null);
methodVisitor.visitCode();
methodVisitor.visitVarInsn(ALOAD, 0);
methodVisitor.visitMethodInsn(INVOKESPECIAL, "java/lang/Object", "<init>", "()V", false);
methodVisitor.visitVarInsn(ALOAD, 0);
methodVisitor.visitInsn(ACONST_NULL);
methodVisitor.visitFieldInsn(PUTFIELD, "javax/xml/transform/dom/DOMResult", "node", "Lorg/w3c/dom/Node;");
methodVisitor.visitVarInsn(ALOAD, 0);
methodVisitor.visitInsn(ACONST_NULL);
methodVisitor.visitFieldInsn(PUTFIELD, "javax/xml/transform/dom/DOMResult", "nextSibling", "Lorg/w3c/dom/Node;");
methodVisitor.visitVarInsn(ALOAD, 0);
methodVisitor.visitInsn(ACONST_NULL);
methodVisitor.visitFieldInsn(PUTFIELD, "javax/xml/transform/dom/DOMResult", "systemId", "Ljava/lang/String;");
methodVisitor.visitVarInsn(ALOAD, 0);
methodVisitor.visitInsn(ACONST_NULL);
methodVisitor.visitMethodInsn(INVOKEVIRTUAL, "javax/xml/transform/dom/DOMResult", "setNode", "(Lorg/w3c/dom/Node;)V", false);
methodVisitor.visitVarInsn(ALOAD, 0);
methodVisitor.visitInsn(ACONST_NULL);
methodVisitor.visitMethodInsn(INVOKEVIRTUAL, "javax/xml/transform/dom/DOMResult", "setNextSibling", "(Lorg/w3c/dom/Node;)V", false);
methodVisitor.visitVarInsn(ALOAD, 0);
methodVisitor.visitInsn(ACONST_NULL);
methodVisitor.visitMethodInsn(INVOKEVIRTUAL, "javax/xml/transform/dom/DOMResult", "setSystemId", "(Ljava/lang/String;)V", false);
methodVisitor.visitInsn(RETURN);
methodVisitor.visitMaxs(2, 1);
methodVisitor.visitEnd();
}
{
methodVisitor = classWriter.visitMethod(ACC_PUBLIC, "<init>", "(Lorg/w3c/dom/Node;)V", null, null);
methodVisitor.visitCode();
methodVisitor.visitVarInsn(ALOAD, 0);
methodVisitor.visitMethodInsn(INVOKESPECIAL, "java/lang/Object", "<init>", "()V", false);
methodVisitor.visitVarInsn(ALOAD, 0);
methodVisitor.visitInsn(ACONST_NULL);
methodVisitor.visitFieldInsn(PUTFIELD, "javax/xml/transform/dom/DOMResult", "node", "Lorg/w3c/dom/Node;");
methodVisitor.visitVarInsn(ALOAD, 0);
methodVisitor.visitInsn(ACONST_NULL);
methodVisitor.visitFieldInsn(PUTFIELD, "javax/xml/transform/dom/DOMResult", "nextSibling", "Lorg/w3c/dom/Node;");
methodVisitor.visitVarInsn(ALOAD, 0);
methodVisitor.visitInsn(ACONST_NULL);
methodVisitor.visitFieldInsn(PUTFIELD, "javax/xml/transform/dom/DOMResult", "systemId", "Ljava/lang/String;");
methodVisitor.visitVarInsn(ALOAD, 0);
methodVisitor.visitVarInsn(ALOAD, 1);
methodVisitor.visitMethodInsn(INVOKEVIRTUAL, "javax/xml/transform/dom/DOMResult", "setNode", "(Lorg/w3c/dom/Node;)V", false);
methodVisitor.visitVarInsn(ALOAD, 0);
methodVisitor.visitInsn(ACONST_NULL);
methodVisitor.visitMethodInsn(INVOKEVIRTUAL, "javax/xml/transform/dom/DOMResult", "setNextSibling", "(Lorg/w3c/dom/Node;)V", false);
methodVisitor.visitVarInsn(ALOAD, 0);
methodVisitor.visitInsn(ACONST_NULL);
methodVisitor.visitMethodInsn(INVOKEVIRTUAL, "javax/xml/transform/dom/DOMResult", "setSystemId", "(Ljava/lang/String;)V", false);
methodVisitor.visitInsn(RETURN);
methodVisitor.visitMaxs(2, 2);
methodVisitor.visitEnd();
}
{
methodVisitor = classWriter.visitMethod(ACC_PUBLIC, "<init>", "(Lorg/w3c/dom/Node;Ljava/lang/String;)V", null, null);
methodVisitor.visitCode();
methodVisitor.visitVarInsn(ALOAD, 0);
methodVisitor.visitMethodInsn(INVOKESPECIAL, "java/lang/Object", "<init>", "()V", false);
methodVisitor.visitVarInsn(ALOAD, 0);
methodVisitor.visitInsn(ACONST_NULL);
methodVisitor.visitFieldInsn(PUTFIELD, "javax/xml/transform/dom/DOMResult", "node", "Lorg/w3c/dom/Node;");
methodVisitor.visitVarInsn(ALOAD, 0);
methodVisitor.visitInsn(ACONST_NULL);
methodVisitor.visitFieldInsn(PUTFIELD, "javax/xml/transform/dom/DOMResult", "nextSibling", "Lorg/w3c/dom/Node;");
methodVisitor.visitVarInsn(ALOAD, 0);
methodVisitor.visitInsn(ACONST_NULL);
methodVisitor.visitFieldInsn(PUTFIELD, "javax/xml/transform/dom/DOMResult", "systemId", "Ljava/lang/String;");
methodVisitor.visitVarInsn(ALOAD, 0);
methodVisitor.visitVarInsn(ALOAD, 1);
methodVisitor.visitMethodInsn(INVOKEVIRTUAL, "javax/xml/transform/dom/DOMResult", "setNode", "(Lorg/w3c/dom/Node;)V", false);
methodVisitor.visitVarInsn(ALOAD, 0);
methodVisitor.visitInsn(ACONST_NULL);
methodVisitor.visitMethodInsn(INVOKEVIRTUAL, "javax/xml/transform/dom/DOMResult", "setNextSibling", "(Lorg/w3c/dom/Node;)V", false);
methodVisitor.visitVarInsn(ALOAD, 0);
methodVisitor.visitVarInsn(ALOAD, 2);
methodVisitor.visitMethodInsn(INVOKEVIRTUAL, "javax/xml/transform/dom/DOMResult", "setSystemId", "(Ljava/lang/String;)V", false);
methodVisitor.visitInsn(RETURN);
methodVisitor.visitMaxs(2, 3);
methodVisitor.visitEnd();
}
{
methodVisitor = classWriter.visitMethod(ACC_PUBLIC, "<init>", "(Lorg/w3c/dom/Node;Lorg/w3c/dom/Node;)V", null, null);
methodVisitor.visitCode();
methodVisitor.visitVarInsn(ALOAD, 0);
methodVisitor.visitMethodInsn(INVOKESPECIAL, "java/lang/Object", "<init>", "()V", false);
methodVisitor.visitVarInsn(ALOAD, 0);
methodVisitor.visitInsn(ACONST_NULL);
methodVisitor.visitFieldInsn(PUTFIELD, "javax/xml/transform/dom/DOMResult", "node", "Lorg/w3c/dom/Node;");
methodVisitor.visitVarInsn(ALOAD, 0);
methodVisitor.visitInsn(ACONST_NULL);
methodVisitor.visitFieldInsn(PUTFIELD, "javax/xml/transform/dom/DOMResult", "nextSibling", "Lorg/w3c/dom/Node;");
methodVisitor.visitVarInsn(ALOAD, 0);
methodVisitor.visitInsn(ACONST_NULL);
methodVisitor.visitFieldInsn(PUTFIELD, "javax/xml/transform/dom/DOMResult", "systemId", "Ljava/lang/String;");
methodVisitor.visitVarInsn(ALOAD, 2);
Label label0 = new Label();
methodVisitor.visitJumpInsn(IFNULL, label0);
methodVisitor.visitVarInsn(ALOAD, 1);
Label label1 = new Label();
methodVisitor.visitJumpInsn(IFNONNULL, label1);
methodVisitor.visitTypeInsn(NEW, "java/lang/IllegalArgumentException");
methodVisitor.visitInsn(DUP);
methodVisitor.visitLdcInsn("Cannot create a DOMResult when the nextSibling is contained by the \"null\" node.");
methodVisitor.visitMethodInsn(INVOKESPECIAL, "java/lang/IllegalArgumentException", "<init>", "(Ljava/lang/String;)V", false);
methodVisitor.visitInsn(ATHROW);
methodVisitor.visitLabel(label1);
methodVisitor.visitVarInsn(ALOAD, 1);
methodVisitor.visitVarInsn(ALOAD, 2);
methodVisitor.visitMethodInsn(INVOKEINTERFACE, "org/w3c/dom/Node", "compareDocumentPosition", "(Lorg/w3c/dom/Node;)S", true);
methodVisitor.visitIntInsn(BIPUSH, 16);
methodVisitor.visitInsn(IAND);
methodVisitor.visitJumpInsn(IFNE, label0);
methodVisitor.visitTypeInsn(NEW, "java/lang/IllegalArgumentException");
methodVisitor.visitInsn(DUP);
methodVisitor.visitLdcInsn("Cannot create a DOMResult when the nextSibling is not contained by the node.");
methodVisitor.visitMethodInsn(INVOKESPECIAL, "java/lang/IllegalArgumentException", "<init>", "(Ljava/lang/String;)V", false);
methodVisitor.visitInsn(ATHROW);
methodVisitor.visitLabel(label0);
methodVisitor.visitVarInsn(ALOAD, 0);
methodVisitor.visitVarInsn(ALOAD, 1);
methodVisitor.visitMethodInsn(INVOKEVIRTUAL, "javax/xml/transform/dom/DOMResult", "setNode", "(Lorg/w3c/dom/Node;)V", false);
methodVisitor.visitVarInsn(ALOAD, 0);
methodVisitor.visitVarInsn(ALOAD, 2);
methodVisitor.visitMethodInsn(INVOKEVIRTUAL, "javax/xml/transform/dom/DOMResult", "setNextSibling", "(Lorg/w3c/dom/Node;)V", false);
methodVisitor.visitVarInsn(ALOAD, 0);
methodVisitor.visitInsn(ACONST_NULL);
methodVisitor.visitMethodInsn(INVOKEVIRTUAL, "javax/xml/transform/dom/DOMResult", "setSystemId", "(Ljava/lang/String;)V", false);
methodVisitor.visitInsn(RETURN);
methodVisitor.visitMaxs(3, 3);
methodVisitor.visitEnd();
}
{
methodVisitor = classWriter.visitMethod(ACC_PUBLIC, "<init>", "(Lorg/w3c/dom/Node;Lorg/w3c/dom/Node;Ljava/lang/String;)V", null, null);
methodVisitor.visitCode();
methodVisitor.visitVarInsn(ALOAD, 0);
methodVisitor.visitMethodInsn(INVOKESPECIAL, "java/lang/Object", "<init>", "()V", false);
methodVisitor.visitVarInsn(ALOAD, 0);
methodVisitor.visitInsn(ACONST_NULL);
methodVisitor.visitFieldInsn(PUTFIELD, "javax/xml/transform/dom/DOMResult", "node", "Lorg/w3c/dom/Node;");
methodVisitor.visitVarInsn(ALOAD, 0);
methodVisitor.visitInsn(ACONST_NULL);
methodVisitor.visitFieldInsn(PUTFIELD, "javax/xml/transform/dom/DOMResult", "nextSibling", "Lorg/w3c/dom/Node;");
methodVisitor.visitVarInsn(ALOAD, 0);
methodVisitor.visitInsn(ACONST_NULL);
methodVisitor.visitFieldInsn(PUTFIELD, "javax/xml/transform/dom/DOMResult", "systemId", "Ljava/lang/String;");
methodVisitor.visitVarInsn(ALOAD, 2);
Label label0 = new Label();
methodVisitor.visitJumpInsn(IFNULL, label0);
methodVisitor.visitVarInsn(ALOAD, 1);
Label label1 = new Label();
methodVisitor.visitJumpInsn(IFNONNULL, label1);
methodVisitor.visitTypeInsn(NEW, "java/lang/IllegalArgumentException");
methodVisitor.visitInsn(DUP);
methodVisitor.visitLdcInsn("Cannot create a DOMResult when the nextSibling is contained by the \"null\" node.");
methodVisitor.visitMethodInsn(INVOKESPECIAL, "java/lang/IllegalArgumentException", "<init>", "(Ljava/lang/String;)V", false);
methodVisitor.visitInsn(ATHROW);
methodVisitor.visitLabel(label1);
methodVisitor.visitVarInsn(ALOAD, 1);
methodVisitor.visitVarInsn(ALOAD, 2);
methodVisitor.visitMethodInsn(INVOKEINTERFACE, "org/w3c/dom/Node", "compareDocumentPosition", "(Lorg/w3c/dom/Node;)S", true);
methodVisitor.visitIntInsn(BIPUSH, 16);
methodVisitor.visitInsn(IAND);
methodVisitor.visitJumpInsn(IFNE, label0);
methodVisitor.visitTypeInsn(NEW, "java/lang/IllegalArgumentException");
methodVisitor.visitInsn(DUP);
methodVisitor.visitLdcInsn("Cannot create a DOMResult when the nextSibling is not contained by the node.");
methodVisitor.visitMethodInsn(INVOKESPECIAL, "java/lang/IllegalArgumentException", "<init>", "(Ljava/lang/String;)V", false);
methodVisitor.visitInsn(ATHROW);
methodVisitor.visitLabel(label0);
methodVisitor.visitVarInsn(ALOAD, 0);
methodVisitor.visitVarInsn(ALOAD, 1);
methodVisitor.visitMethodInsn(INVOKEVIRTUAL, "javax/xml/transform/dom/DOMResult", "setNode", "(Lorg/w3c/dom/Node;)V", false);
methodVisitor.visitVarInsn(ALOAD, 0);
methodVisitor.visitVarInsn(ALOAD, 2);
methodVisitor.visitMethodInsn(INVOKEVIRTUAL, "javax/xml/transform/dom/DOMResult", "setNextSibling", "(Lorg/w3c/dom/Node;)V", false);
methodVisitor.visitVarInsn(ALOAD, 0);
methodVisitor.visitVarInsn(ALOAD, 3);
methodVisitor.visitMethodInsn(INVOKEVIRTUAL, "javax/xml/transform/dom/DOMResult", "setSystemId", "(Ljava/lang/String;)V", false);
methodVisitor.visitInsn(RETURN);
methodVisitor.visitMaxs(3, 4);
methodVisitor.visitEnd();
}
{
methodVisitor = classWriter.visitMethod(ACC_PUBLIC, "setNode", "(Lorg/w3c/dom/Node;)V", null, null);
methodVisitor.visitCode();
methodVisitor.visitVarInsn(ALOAD, 0);
methodVisitor.visitFieldInsn(GETFIELD, "javax/xml/transform/dom/DOMResult", "nextSibling", "Lorg/w3c/dom/Node;");
Label label0 = new Label();
methodVisitor.visitJumpInsn(IFNULL, label0);
methodVisitor.visitVarInsn(ALOAD, 1);
Label label1 = new Label();
methodVisitor.visitJumpInsn(IFNONNULL, label1);
methodVisitor.visitTypeInsn(NEW, "java/lang/IllegalStateException");
methodVisitor.visitInsn(DUP);
methodVisitor.visitLdcInsn("Cannot create a DOMResult when the nextSibling is contained by the \"null\" node.");
methodVisitor.visitMethodInsn(INVOKESPECIAL, "java/lang/IllegalStateException", "<init>", "(Ljava/lang/String;)V", false);
methodVisitor.visitInsn(ATHROW);
methodVisitor.visitLabel(label1);
methodVisitor.visitVarInsn(ALOAD, 1);
methodVisitor.visitVarInsn(ALOAD, 0);
methodVisitor.visitFieldInsn(GETFIELD, "javax/xml/transform/dom/DOMResult", "nextSibling", "Lorg/w3c/dom/Node;");
methodVisitor.visitMethodInsn(INVOKEINTERFACE, "org/w3c/dom/Node", "compareDocumentPosition", "(Lorg/w3c/dom/Node;)S", true);
methodVisitor.visitIntInsn(BIPUSH, 16);
methodVisitor.visitInsn(IAND);
methodVisitor.visitJumpInsn(IFNE, label0);
methodVisitor.visitTypeInsn(NEW, "java/lang/IllegalArgumentException");
methodVisitor.visitInsn(DUP);
methodVisitor.visitLdcInsn("Cannot create a DOMResult when the nextSibling is not contained by the node.");
methodVisitor.visitMethodInsn(INVOKESPECIAL, "java/lang/IllegalArgumentException", "<init>", "(Ljava/lang/String;)V", false);
methodVisitor.visitInsn(ATHROW);
methodVisitor.visitLabel(label0);
methodVisitor.visitVarInsn(ALOAD, 0);
methodVisitor.visitVarInsn(ALOAD, 1);
methodVisitor.visitFieldInsn(PUTFIELD, "javax/xml/transform/dom/DOMResult", "node", "Lorg/w3c/dom/Node;");
methodVisitor.visitInsn(RETURN);
methodVisitor.visitMaxs(3, 2);
methodVisitor.visitEnd();
}
{
methodVisitor = classWriter.visitMethod(ACC_PUBLIC, "getNode", "()Lorg/w3c/dom/Node;", null, null);
methodVisitor.visitCode();
methodVisitor.visitVarInsn(ALOAD, 0);
methodVisitor.visitFieldInsn(GETFIELD, "javax/xml/transform/dom/DOMResult", "node", "Lorg/w3c/dom/Node;");
methodVisitor.visitInsn(ARETURN);
methodVisitor.visitMaxs(1, 1);
methodVisitor.visitEnd();
}
{
methodVisitor = classWriter.visitMethod(ACC_PUBLIC, "setNextSibling", "(Lorg/w3c/dom/Node;)V", null, null);
methodVisitor.visitCode();
methodVisitor.visitVarInsn(ALOAD, 1);
Label label0 = new Label();
methodVisitor.visitJumpInsn(IFNULL, label0);
methodVisitor.visitVarInsn(ALOAD, 0);
methodVisitor.visitFieldInsn(GETFIELD, "javax/xml/transform/dom/DOMResult", "node", "Lorg/w3c/dom/Node;");
Label label1 = new Label();
methodVisitor.visitJumpInsn(IFNONNULL, label1);
methodVisitor.visitTypeInsn(NEW, "java/lang/IllegalStateException");
methodVisitor.visitInsn(DUP);
methodVisitor.visitLdcInsn("Cannot create a DOMResult when the nextSibling is contained by the \"null\" node.");
methodVisitor.visitMethodInsn(INVOKESPECIAL, "java/lang/IllegalStateException", "<init>", "(Ljava/lang/String;)V", false);
methodVisitor.visitInsn(ATHROW);
methodVisitor.visitLabel(label1);
methodVisitor.visitVarInsn(ALOAD, 0);
methodVisitor.visitFieldInsn(GETFIELD, "javax/xml/transform/dom/DOMResult", "node", "Lorg/w3c/dom/Node;");
methodVisitor.visitVarInsn(ALOAD, 1);
methodVisitor.visitMethodInsn(INVOKEINTERFACE, "org/w3c/dom/Node", "compareDocumentPosition", "(Lorg/w3c/dom/Node;)S", true);
methodVisitor.visitIntInsn(BIPUSH, 16);
methodVisitor.visitInsn(IAND);
methodVisitor.visitJumpInsn(IFNE, label0);
methodVisitor.visitTypeInsn(NEW, "java/lang/IllegalArgumentException");
methodVisitor.visitInsn(DUP);
methodVisitor.visitLdcInsn("Cannot create a DOMResult when the nextSibling is not contained by the node.");
methodVisitor.visitMethodInsn(INVOKESPECIAL, "java/lang/IllegalArgumentException", "<init>", "(Ljava/lang/String;)V", false);
methodVisitor.visitInsn(ATHROW);
methodVisitor.visitLabel(label0);
methodVisitor.visitVarInsn(ALOAD, 0);
methodVisitor.visitVarInsn(ALOAD, 1);
methodVisitor.visitFieldInsn(PUTFIELD, "javax/xml/transform/dom/DOMResult", "nextSibling", "Lorg/w3c/dom/Node;");
methodVisitor.visitInsn(RETURN);
methodVisitor.visitMaxs(3, 2);
methodVisitor.visitEnd();
}
{
methodVisitor = classWriter.visitMethod(ACC_PUBLIC, "getNextSibling", "()Lorg/w3c/dom/Node;", null, null);
methodVisitor.visitCode();
methodVisitor.visitVarInsn(ALOAD, 0);
methodVisitor.visitFieldInsn(GETFIELD, "javax/xml/transform/dom/DOMResult", "nextSibling", "Lorg/w3c/dom/Node;");
methodVisitor.visitInsn(ARETURN);
methodVisitor.visitMaxs(1, 1);
methodVisitor.visitEnd();
}
{
methodVisitor = classWriter.visitMethod(ACC_PUBLIC, "setSystemId", "(Ljava/lang/String;)V", null, null);
methodVisitor.visitCode();
methodVisitor.visitVarInsn(ALOAD, 0);
methodVisitor.visitVarInsn(ALOAD, 1);
methodVisitor.visitFieldInsn(PUTFIELD, "javax/xml/transform/dom/DOMResult", "systemId", "Ljava/lang/String;");
methodVisitor.visitInsn(RETURN);
methodVisitor.visitMaxs(2, 2);
methodVisitor.visitEnd();
}
{
methodVisitor = classWriter.visitMethod(ACC_PUBLIC, "getSystemId", "()Ljava/lang/String;", null, null);
methodVisitor.visitCode();
methodVisitor.visitVarInsn(ALOAD, 0);
methodVisitor.visitFieldInsn(GETFIELD, "javax/xml/transform/dom/DOMResult", "systemId", "Ljava/lang/String;");
methodVisitor.visitInsn(ARETURN);
methodVisitor.visitMaxs(1, 1);
methodVisitor.visitEnd();
}
classWriter.visitEnd();

return classWriter.toByteArray();
}
}
