package asm.org.bouncycastle.crypto.engines;
import org.objectweb.asm.AnnotationVisitor;
import org.objectweb.asm.Attribute;
import org.objectweb.asm.ClassReader;
import org.objectweb.asm.ClassWriter;
import org.objectweb.asm.ConstantDynamic;
import org.objectweb.asm.FieldVisitor;
import org.objectweb.asm.Handle;
import org.objectweb.asm.Label;
import org.objectweb.asm.MethodVisitor;
import org.objectweb.asm.Opcodes;
import org.objectweb.asm.RecordComponentVisitor;
import org.objectweb.asm.Type;
import org.objectweb.asm.TypePath;
public class Shacal2EngineDump implements Opcodes {

public static byte[] dump () throws Exception {

ClassWriter classWriter = new ClassWriter(0);
FieldVisitor fieldVisitor;
RecordComponentVisitor recordComponentVisitor;
MethodVisitor methodVisitor;
AnnotationVisitor annotationVisitor0;

classWriter.visit(V1_5, ACC_PUBLIC | ACC_SUPER, "org/bouncycastle/crypto/engines/Shacal2Engine", null, "java/lang/Object", new String[] { "org/bouncycastle/crypto/BlockCipher" });

{
fieldVisitor = classWriter.visitField(ACC_PRIVATE | ACC_FINAL | ACC_STATIC, "K", "[I", null, null);
fieldVisitor.visitEnd();
}
{
fieldVisitor = classWriter.visitField(ACC_PRIVATE | ACC_FINAL | ACC_STATIC, "BLOCK_SIZE", "I", null, new Integer(32));
fieldVisitor.visitEnd();
}
{
fieldVisitor = classWriter.visitField(ACC_PRIVATE, "forEncryption", "Z", null, null);
fieldVisitor.visitEnd();
}
{
fieldVisitor = classWriter.visitField(ACC_PRIVATE | ACC_FINAL | ACC_STATIC, "ROUNDS", "I", null, new Integer(64));
fieldVisitor.visitEnd();
}
{
fieldVisitor = classWriter.visitField(ACC_PRIVATE, "workingKey", "[I", null, null);
fieldVisitor.visitEnd();
}
{
methodVisitor = classWriter.visitMethod(ACC_PUBLIC, "<init>", "()V", null, null);
methodVisitor.visitCode();
methodVisitor.visitVarInsn(ALOAD, 0);
methodVisitor.visitMethodInsn(INVOKESPECIAL, "java/lang/Object", "<init>", "()V", false);
methodVisitor.visitVarInsn(ALOAD, 0);
methodVisitor.visitInsn(ICONST_0);
methodVisitor.visitFieldInsn(PUTFIELD, "org/bouncycastle/crypto/engines/Shacal2Engine", "forEncryption", "Z");
methodVisitor.visitVarInsn(ALOAD, 0);
methodVisitor.visitInsn(ACONST_NULL);
methodVisitor.visitFieldInsn(PUTFIELD, "org/bouncycastle/crypto/engines/Shacal2Engine", "workingKey", "[I");
methodVisitor.visitInsn(RETURN);
methodVisitor.visitMaxs(2, 1);
methodVisitor.visitEnd();
}
{
methodVisitor = classWriter.visitMethod(ACC_PUBLIC, "reset", "()V", null, null);
methodVisitor.visitCode();
methodVisitor.visitInsn(RETURN);
methodVisitor.visitMaxs(0, 1);
methodVisitor.visitEnd();
}
{
methodVisitor = classWriter.visitMethod(ACC_PUBLIC, "getAlgorithmName", "()Ljava/lang/String;", null, null);
methodVisitor.visitCode();
methodVisitor.visitLdcInsn("Shacal2");
methodVisitor.visitInsn(ARETURN);
methodVisitor.visitMaxs(1, 1);
methodVisitor.visitEnd();
}
{
methodVisitor = classWriter.visitMethod(ACC_PUBLIC, "getBlockSize", "()I", null, null);
methodVisitor.visitCode();
methodVisitor.visitIntInsn(BIPUSH, 32);
methodVisitor.visitInsn(IRETURN);
methodVisitor.visitMaxs(1, 1);
methodVisitor.visitEnd();
}
{
methodVisitor = classWriter.visitMethod(ACC_PUBLIC, "init", "(ZLorg/bouncycastle/crypto/CipherParameters;)V", null, new String[] { "java/lang/IllegalArgumentException" });
methodVisitor.visitCode();
methodVisitor.visitVarInsn(ALOAD, 2);
methodVisitor.visitTypeInsn(INSTANCEOF, "org/bouncycastle/crypto/params/KeyParameter");
Label label0 = new Label();
methodVisitor.visitJumpInsn(IFNE, label0);
methodVisitor.visitTypeInsn(NEW, "java/lang/IllegalArgumentException");
methodVisitor.visitInsn(DUP);
methodVisitor.visitLdcInsn("only simple KeyParameter expected.");
methodVisitor.visitMethodInsn(INVOKESPECIAL, "java/lang/IllegalArgumentException", "<init>", "(Ljava/lang/String;)V", false);
methodVisitor.visitInsn(ATHROW);
methodVisitor.visitLabel(label0);
methodVisitor.visitVarInsn(ALOAD, 0);
methodVisitor.visitVarInsn(ILOAD, 1);
methodVisitor.visitFieldInsn(PUTFIELD, "org/bouncycastle/crypto/engines/Shacal2Engine", "forEncryption", "Z");
methodVisitor.visitVarInsn(ALOAD, 0);
methodVisitor.visitIntInsn(BIPUSH, 64);
methodVisitor.visitIntInsn(NEWARRAY, T_INT);
methodVisitor.visitFieldInsn(PUTFIELD, "org/bouncycastle/crypto/engines/Shacal2Engine", "workingKey", "[I");
methodVisitor.visitVarInsn(ALOAD, 0);
methodVisitor.visitVarInsn(ALOAD, 2);
methodVisitor.visitTypeInsn(CHECKCAST, "org/bouncycastle/crypto/params/KeyParameter");
methodVisitor.visitMethodInsn(INVOKEVIRTUAL, "org/bouncycastle/crypto/params/KeyParameter", "getKey", "()[B", false);
methodVisitor.visitMethodInsn(INVOKEVIRTUAL, "org/bouncycastle/crypto/engines/Shacal2Engine", "setKey", "([B)V", false);
methodVisitor.visitInsn(RETURN);
methodVisitor.visitMaxs(3, 3);
methodVisitor.visitEnd();
}
{
methodVisitor = classWriter.visitMethod(ACC_PUBLIC, "setKey", "([B)V", null, null);
methodVisitor.visitCode();
methodVisitor.visitVarInsn(ALOAD, 1);
methodVisitor.visitInsn(ARRAYLENGTH);
Label label0 = new Label();
methodVisitor.visitJumpInsn(IFEQ, label0);
methodVisitor.visitVarInsn(ALOAD, 1);
methodVisitor.visitInsn(ARRAYLENGTH);
methodVisitor.visitIntInsn(BIPUSH, 64);
methodVisitor.visitJumpInsn(IF_ICMPGT, label0);
methodVisitor.visitVarInsn(ALOAD, 1);
methodVisitor.visitInsn(ARRAYLENGTH);
methodVisitor.visitIntInsn(BIPUSH, 16);
methodVisitor.visitJumpInsn(IF_ICMPLT, label0);
methodVisitor.visitVarInsn(ALOAD, 1);
methodVisitor.visitInsn(ARRAYLENGTH);
methodVisitor.visitIntInsn(BIPUSH, 8);
methodVisitor.visitInsn(IREM);
Label label1 = new Label();
methodVisitor.visitJumpInsn(IFEQ, label1);
methodVisitor.visitLabel(label0);
methodVisitor.visitTypeInsn(NEW, "java/lang/IllegalArgumentException");
methodVisitor.visitInsn(DUP);
methodVisitor.visitLdcInsn("Shacal2-key must be 16 - 64 bytes and multiple of 8");
methodVisitor.visitMethodInsn(INVOKESPECIAL, "java/lang/IllegalArgumentException", "<init>", "(Ljava/lang/String;)V", false);
methodVisitor.visitInsn(ATHROW);
methodVisitor.visitLabel(label1);
methodVisitor.visitVarInsn(ALOAD, 0);
methodVisitor.visitVarInsn(ALOAD, 1);
methodVisitor.visitVarInsn(ALOAD, 0);
methodVisitor.visitFieldInsn(GETFIELD, "org/bouncycastle/crypto/engines/Shacal2Engine", "workingKey", "[I");
methodVisitor.visitInsn(ICONST_0);
methodVisitor.visitInsn(ICONST_0);
methodVisitor.visitMethodInsn(INVOKESPECIAL, "org/bouncycastle/crypto/engines/Shacal2Engine", "bytes2ints", "([B[III)V", false);
methodVisitor.visitIntInsn(BIPUSH, 16);
methodVisitor.visitVarInsn(ISTORE, 2);
Label label2 = new Label();
methodVisitor.visitLabel(label2);
methodVisitor.visitVarInsn(ILOAD, 2);
methodVisitor.visitIntInsn(BIPUSH, 64);
Label label3 = new Label();
methodVisitor.visitJumpInsn(IF_ICMPGE, label3);
methodVisitor.visitVarInsn(ALOAD, 0);
methodVisitor.visitFieldInsn(GETFIELD, "org/bouncycastle/crypto/engines/Shacal2Engine", "workingKey", "[I");
methodVisitor.visitVarInsn(ILOAD, 2);
methodVisitor.visitVarInsn(ALOAD, 0);
methodVisitor.visitFieldInsn(GETFIELD, "org/bouncycastle/crypto/engines/Shacal2Engine", "workingKey", "[I");
methodVisitor.visitVarInsn(ILOAD, 2);
methodVisitor.visitInsn(ICONST_2);
methodVisitor.visitInsn(ISUB);
methodVisitor.visitInsn(IALOAD);
methodVisitor.visitIntInsn(BIPUSH, 17);
methodVisitor.visitInsn(IUSHR);
methodVisitor.visitVarInsn(ALOAD, 0);
methodVisitor.visitFieldInsn(GETFIELD, "org/bouncycastle/crypto/engines/Shacal2Engine", "workingKey", "[I");
methodVisitor.visitVarInsn(ILOAD, 2);
methodVisitor.visitInsn(ICONST_2);
methodVisitor.visitInsn(ISUB);
methodVisitor.visitInsn(IALOAD);
methodVisitor.visitIntInsn(BIPUSH, -17);
methodVisitor.visitInsn(ISHL);
methodVisitor.visitInsn(IOR);
methodVisitor.visitVarInsn(ALOAD, 0);
methodVisitor.visitFieldInsn(GETFIELD, "org/bouncycastle/crypto/engines/Shacal2Engine", "workingKey", "[I");
methodVisitor.visitVarInsn(ILOAD, 2);
methodVisitor.visitInsn(ICONST_2);
methodVisitor.visitInsn(ISUB);
methodVisitor.visitInsn(IALOAD);
methodVisitor.visitIntInsn(BIPUSH, 19);
methodVisitor.visitInsn(IUSHR);
methodVisitor.visitVarInsn(ALOAD, 0);
methodVisitor.visitFieldInsn(GETFIELD, "org/bouncycastle/crypto/engines/Shacal2Engine", "workingKey", "[I");
methodVisitor.visitVarInsn(ILOAD, 2);
methodVisitor.visitInsn(ICONST_2);
methodVisitor.visitInsn(ISUB);
methodVisitor.visitInsn(IALOAD);
methodVisitor.visitIntInsn(BIPUSH, -19);
methodVisitor.visitInsn(ISHL);
methodVisitor.visitInsn(IOR);
methodVisitor.visitInsn(IXOR);
methodVisitor.visitVarInsn(ALOAD, 0);
methodVisitor.visitFieldInsn(GETFIELD, "org/bouncycastle/crypto/engines/Shacal2Engine", "workingKey", "[I");
methodVisitor.visitVarInsn(ILOAD, 2);
methodVisitor.visitInsn(ICONST_2);
methodVisitor.visitInsn(ISUB);
methodVisitor.visitInsn(IALOAD);
methodVisitor.visitIntInsn(BIPUSH, 10);
methodVisitor.visitInsn(IUSHR);
methodVisitor.visitInsn(IXOR);
methodVisitor.visitVarInsn(ALOAD, 0);
methodVisitor.visitFieldInsn(GETFIELD, "org/bouncycastle/crypto/engines/Shacal2Engine", "workingKey", "[I");
methodVisitor.visitVarInsn(ILOAD, 2);
methodVisitor.visitIntInsn(BIPUSH, 7);
methodVisitor.visitInsn(ISUB);
methodVisitor.visitInsn(IALOAD);
methodVisitor.visitInsn(IADD);
methodVisitor.visitVarInsn(ALOAD, 0);
methodVisitor.visitFieldInsn(GETFIELD, "org/bouncycastle/crypto/engines/Shacal2Engine", "workingKey", "[I");
methodVisitor.visitVarInsn(ILOAD, 2);
methodVisitor.visitIntInsn(BIPUSH, 15);
methodVisitor.visitInsn(ISUB);
methodVisitor.visitInsn(IALOAD);
methodVisitor.visitIntInsn(BIPUSH, 7);
methodVisitor.visitInsn(IUSHR);
methodVisitor.visitVarInsn(ALOAD, 0);
methodVisitor.visitFieldInsn(GETFIELD, "org/bouncycastle/crypto/engines/Shacal2Engine", "workingKey", "[I");
methodVisitor.visitVarInsn(ILOAD, 2);
methodVisitor.visitIntInsn(BIPUSH, 15);
methodVisitor.visitInsn(ISUB);
methodVisitor.visitInsn(IALOAD);
methodVisitor.visitIntInsn(BIPUSH, -7);
methodVisitor.visitInsn(ISHL);
methodVisitor.visitInsn(IOR);
methodVisitor.visitVarInsn(ALOAD, 0);
methodVisitor.visitFieldInsn(GETFIELD, "org/bouncycastle/crypto/engines/Shacal2Engine", "workingKey", "[I");
methodVisitor.visitVarInsn(ILOAD, 2);
methodVisitor.visitIntInsn(BIPUSH, 15);
methodVisitor.visitInsn(ISUB);
methodVisitor.visitInsn(IALOAD);
methodVisitor.visitIntInsn(BIPUSH, 18);
methodVisitor.visitInsn(IUSHR);
methodVisitor.visitVarInsn(ALOAD, 0);
methodVisitor.visitFieldInsn(GETFIELD, "org/bouncycastle/crypto/engines/Shacal2Engine", "workingKey", "[I");
methodVisitor.visitVarInsn(ILOAD, 2);
methodVisitor.visitIntInsn(BIPUSH, 15);
methodVisitor.visitInsn(ISUB);
methodVisitor.visitInsn(IALOAD);
methodVisitor.visitIntInsn(BIPUSH, -18);
methodVisitor.visitInsn(ISHL);
methodVisitor.visitInsn(IOR);
methodVisitor.visitInsn(IXOR);
methodVisitor.visitVarInsn(ALOAD, 0);
methodVisitor.visitFieldInsn(GETFIELD, "org/bouncycastle/crypto/engines/Shacal2Engine", "workingKey", "[I");
methodVisitor.visitVarInsn(ILOAD, 2);
methodVisitor.visitIntInsn(BIPUSH, 15);
methodVisitor.visitInsn(ISUB);
methodVisitor.visitInsn(IALOAD);
methodVisitor.visitInsn(ICONST_3);
methodVisitor.visitInsn(IUSHR);
methodVisitor.visitInsn(IXOR);
methodVisitor.visitInsn(IADD);
methodVisitor.visitVarInsn(ALOAD, 0);
methodVisitor.visitFieldInsn(GETFIELD, "org/bouncycastle/crypto/engines/Shacal2Engine", "workingKey", "[I");
methodVisitor.visitVarInsn(ILOAD, 2);
methodVisitor.visitIntInsn(BIPUSH, 16);
methodVisitor.visitInsn(ISUB);
methodVisitor.visitInsn(IALOAD);
methodVisitor.visitInsn(IADD);
methodVisitor.visitInsn(IASTORE);
methodVisitor.visitIincInsn(2, 1);
methodVisitor.visitJumpInsn(GOTO, label2);
methodVisitor.visitLabel(label3);
methodVisitor.visitInsn(RETURN);
methodVisitor.visitMaxs(8, 3);
methodVisitor.visitEnd();
}
{
methodVisitor = classWriter.visitMethod(ACC_PRIVATE, "encryptBlock", "([BI[BI)V", null, null);
methodVisitor.visitCode();
methodVisitor.visitIntInsn(BIPUSH, 8);
methodVisitor.visitIntInsn(NEWARRAY, T_INT);
methodVisitor.visitVarInsn(ASTORE, 5);
methodVisitor.visitVarInsn(ALOAD, 0);
methodVisitor.visitVarInsn(ALOAD, 1);
methodVisitor.visitVarInsn(ALOAD, 5);
methodVisitor.visitVarInsn(ILOAD, 2);
methodVisitor.visitInsn(ICONST_0);
methodVisitor.visitMethodInsn(INVOKESPECIAL, "org/bouncycastle/crypto/engines/Shacal2Engine", "byteBlockToInts", "([B[III)V", false);
methodVisitor.visitInsn(ICONST_0);
methodVisitor.visitVarInsn(ISTORE, 6);
Label label0 = new Label();
methodVisitor.visitLabel(label0);
methodVisitor.visitVarInsn(ILOAD, 6);
methodVisitor.visitIntInsn(BIPUSH, 64);
Label label1 = new Label();
methodVisitor.visitJumpInsn(IF_ICMPGE, label1);
methodVisitor.visitVarInsn(ALOAD, 5);
methodVisitor.visitInsn(ICONST_4);
methodVisitor.visitInsn(IALOAD);
methodVisitor.visitIntInsn(BIPUSH, 6);
methodVisitor.visitInsn(IUSHR);
methodVisitor.visitVarInsn(ALOAD, 5);
methodVisitor.visitInsn(ICONST_4);
methodVisitor.visitInsn(IALOAD);
methodVisitor.visitIntInsn(BIPUSH, -6);
methodVisitor.visitInsn(ISHL);
methodVisitor.visitInsn(IOR);
methodVisitor.visitVarInsn(ALOAD, 5);
methodVisitor.visitInsn(ICONST_4);
methodVisitor.visitInsn(IALOAD);
methodVisitor.visitIntInsn(BIPUSH, 11);
methodVisitor.visitInsn(IUSHR);
methodVisitor.visitVarInsn(ALOAD, 5);
methodVisitor.visitInsn(ICONST_4);
methodVisitor.visitInsn(IALOAD);
methodVisitor.visitIntInsn(BIPUSH, -11);
methodVisitor.visitInsn(ISHL);
methodVisitor.visitInsn(IOR);
methodVisitor.visitInsn(IXOR);
methodVisitor.visitVarInsn(ALOAD, 5);
methodVisitor.visitInsn(ICONST_4);
methodVisitor.visitInsn(IALOAD);
methodVisitor.visitIntInsn(BIPUSH, 25);
methodVisitor.visitInsn(IUSHR);
methodVisitor.visitVarInsn(ALOAD, 5);
methodVisitor.visitInsn(ICONST_4);
methodVisitor.visitInsn(IALOAD);
methodVisitor.visitIntInsn(BIPUSH, -25);
methodVisitor.visitInsn(ISHL);
methodVisitor.visitInsn(IOR);
methodVisitor.visitInsn(IXOR);
methodVisitor.visitVarInsn(ALOAD, 5);
methodVisitor.visitInsn(ICONST_4);
methodVisitor.visitInsn(IALOAD);
methodVisitor.visitVarInsn(ALOAD, 5);
methodVisitor.visitInsn(ICONST_5);
methodVisitor.visitInsn(IALOAD);
methodVisitor.visitInsn(IAND);
methodVisitor.visitVarInsn(ALOAD, 5);
methodVisitor.visitInsn(ICONST_4);
methodVisitor.visitInsn(IALOAD);
methodVisitor.visitInsn(ICONST_M1);
methodVisitor.visitInsn(IXOR);
methodVisitor.visitVarInsn(ALOAD, 5);
methodVisitor.visitIntInsn(BIPUSH, 6);
methodVisitor.visitInsn(IALOAD);
methodVisitor.visitInsn(IAND);
methodVisitor.visitInsn(IXOR);
methodVisitor.visitInsn(IADD);
methodVisitor.visitVarInsn(ALOAD, 5);
methodVisitor.visitIntInsn(BIPUSH, 7);
methodVisitor.visitInsn(IALOAD);
methodVisitor.visitInsn(IADD);
methodVisitor.visitFieldInsn(GETSTATIC, "org/bouncycastle/crypto/engines/Shacal2Engine", "K", "[I");
methodVisitor.visitVarInsn(ILOAD, 6);
methodVisitor.visitInsn(IALOAD);
methodVisitor.visitInsn(IADD);
methodVisitor.visitVarInsn(ALOAD, 0);
methodVisitor.visitFieldInsn(GETFIELD, "org/bouncycastle/crypto/engines/Shacal2Engine", "workingKey", "[I");
methodVisitor.visitVarInsn(ILOAD, 6);
methodVisitor.visitInsn(IALOAD);
methodVisitor.visitInsn(IADD);
methodVisitor.visitVarInsn(ISTORE, 7);
methodVisitor.visitVarInsn(ALOAD, 5);
methodVisitor.visitIntInsn(BIPUSH, 7);
methodVisitor.visitVarInsn(ALOAD, 5);
methodVisitor.visitIntInsn(BIPUSH, 6);
methodVisitor.visitInsn(IALOAD);
methodVisitor.visitInsn(IASTORE);
methodVisitor.visitVarInsn(ALOAD, 5);
methodVisitor.visitIntInsn(BIPUSH, 6);
methodVisitor.visitVarInsn(ALOAD, 5);
methodVisitor.visitInsn(ICONST_5);
methodVisitor.visitInsn(IALOAD);
methodVisitor.visitInsn(IASTORE);
methodVisitor.visitVarInsn(ALOAD, 5);
methodVisitor.visitInsn(ICONST_5);
methodVisitor.visitVarInsn(ALOAD, 5);
methodVisitor.visitInsn(ICONST_4);
methodVisitor.visitInsn(IALOAD);
methodVisitor.visitInsn(IASTORE);
methodVisitor.visitVarInsn(ALOAD, 5);
methodVisitor.visitInsn(ICONST_4);
methodVisitor.visitVarInsn(ALOAD, 5);
methodVisitor.visitInsn(ICONST_3);
methodVisitor.visitInsn(IALOAD);
methodVisitor.visitVarInsn(ILOAD, 7);
methodVisitor.visitInsn(IADD);
methodVisitor.visitInsn(IASTORE);
methodVisitor.visitVarInsn(ALOAD, 5);
methodVisitor.visitInsn(ICONST_3);
methodVisitor.visitVarInsn(ALOAD, 5);
methodVisitor.visitInsn(ICONST_2);
methodVisitor.visitInsn(IALOAD);
methodVisitor.visitInsn(IASTORE);
methodVisitor.visitVarInsn(ALOAD, 5);
methodVisitor.visitInsn(ICONST_2);
methodVisitor.visitVarInsn(ALOAD, 5);
methodVisitor.visitInsn(ICONST_1);
methodVisitor.visitInsn(IALOAD);
methodVisitor.visitInsn(IASTORE);
methodVisitor.visitVarInsn(ALOAD, 5);
methodVisitor.visitInsn(ICONST_1);
methodVisitor.visitVarInsn(ALOAD, 5);
methodVisitor.visitInsn(ICONST_0);
methodVisitor.visitInsn(IALOAD);
methodVisitor.visitInsn(IASTORE);
methodVisitor.visitVarInsn(ALOAD, 5);
methodVisitor.visitInsn(ICONST_0);
methodVisitor.visitVarInsn(ILOAD, 7);
methodVisitor.visitVarInsn(ALOAD, 5);
methodVisitor.visitInsn(ICONST_0);
methodVisitor.visitInsn(IALOAD);
methodVisitor.visitInsn(ICONST_2);
methodVisitor.visitInsn(IUSHR);
methodVisitor.visitVarInsn(ALOAD, 5);
methodVisitor.visitInsn(ICONST_0);
methodVisitor.visitInsn(IALOAD);
methodVisitor.visitIntInsn(BIPUSH, -2);
methodVisitor.visitInsn(ISHL);
methodVisitor.visitInsn(IOR);
methodVisitor.visitVarInsn(ALOAD, 5);
methodVisitor.visitInsn(ICONST_0);
methodVisitor.visitInsn(IALOAD);
methodVisitor.visitIntInsn(BIPUSH, 13);
methodVisitor.visitInsn(IUSHR);
methodVisitor.visitVarInsn(ALOAD, 5);
methodVisitor.visitInsn(ICONST_0);
methodVisitor.visitInsn(IALOAD);
methodVisitor.visitIntInsn(BIPUSH, -13);
methodVisitor.visitInsn(ISHL);
methodVisitor.visitInsn(IOR);
methodVisitor.visitInsn(IXOR);
methodVisitor.visitVarInsn(ALOAD, 5);
methodVisitor.visitInsn(ICONST_0);
methodVisitor.visitInsn(IALOAD);
methodVisitor.visitIntInsn(BIPUSH, 22);
methodVisitor.visitInsn(IUSHR);
methodVisitor.visitVarInsn(ALOAD, 5);
methodVisitor.visitInsn(ICONST_0);
methodVisitor.visitInsn(IALOAD);
methodVisitor.visitIntInsn(BIPUSH, -22);
methodVisitor.visitInsn(ISHL);
methodVisitor.visitInsn(IOR);
methodVisitor.visitInsn(IXOR);
methodVisitor.visitInsn(IADD);
methodVisitor.visitVarInsn(ALOAD, 5);
methodVisitor.visitInsn(ICONST_0);
methodVisitor.visitInsn(IALOAD);
methodVisitor.visitVarInsn(ALOAD, 5);
methodVisitor.visitInsn(ICONST_2);
methodVisitor.visitInsn(IALOAD);
methodVisitor.visitInsn(IAND);
methodVisitor.visitVarInsn(ALOAD, 5);
methodVisitor.visitInsn(ICONST_0);
methodVisitor.visitInsn(IALOAD);
methodVisitor.visitVarInsn(ALOAD, 5);
methodVisitor.visitInsn(ICONST_3);
methodVisitor.visitInsn(IALOAD);
methodVisitor.visitInsn(IAND);
methodVisitor.visitInsn(IXOR);
methodVisitor.visitVarInsn(ALOAD, 5);
methodVisitor.visitInsn(ICONST_2);
methodVisitor.visitInsn(IALOAD);
methodVisitor.visitVarInsn(ALOAD, 5);
methodVisitor.visitInsn(ICONST_3);
methodVisitor.visitInsn(IALOAD);
methodVisitor.visitInsn(IAND);
methodVisitor.visitInsn(IXOR);
methodVisitor.visitInsn(IADD);
methodVisitor.visitInsn(IASTORE);
methodVisitor.visitIincInsn(6, 1);
methodVisitor.visitJumpInsn(GOTO, label0);
methodVisitor.visitLabel(label1);
methodVisitor.visitVarInsn(ALOAD, 0);
methodVisitor.visitVarInsn(ALOAD, 5);
methodVisitor.visitVarInsn(ALOAD, 3);
methodVisitor.visitVarInsn(ILOAD, 4);
methodVisitor.visitMethodInsn(INVOKESPECIAL, "org/bouncycastle/crypto/engines/Shacal2Engine", "ints2bytes", "([I[BI)V", false);
methodVisitor.visitInsn(RETURN);
methodVisitor.visitMaxs(7, 8);
methodVisitor.visitEnd();
}
{
methodVisitor = classWriter.visitMethod(ACC_PRIVATE, "decryptBlock", "([BI[BI)V", null, null);
methodVisitor.visitCode();
methodVisitor.visitIntInsn(BIPUSH, 8);
methodVisitor.visitIntInsn(NEWARRAY, T_INT);
methodVisitor.visitVarInsn(ASTORE, 5);
methodVisitor.visitVarInsn(ALOAD, 0);
methodVisitor.visitVarInsn(ALOAD, 1);
methodVisitor.visitVarInsn(ALOAD, 5);
methodVisitor.visitVarInsn(ILOAD, 2);
methodVisitor.visitInsn(ICONST_0);
methodVisitor.visitMethodInsn(INVOKESPECIAL, "org/bouncycastle/crypto/engines/Shacal2Engine", "byteBlockToInts", "([B[III)V", false);
methodVisitor.visitIntInsn(BIPUSH, 63);
methodVisitor.visitVarInsn(ISTORE, 6);
Label label0 = new Label();
methodVisitor.visitLabel(label0);
methodVisitor.visitVarInsn(ILOAD, 6);
methodVisitor.visitInsn(ICONST_M1);
Label label1 = new Label();
methodVisitor.visitJumpInsn(IF_ICMPLE, label1);
methodVisitor.visitVarInsn(ALOAD, 5);
methodVisitor.visitInsn(ICONST_0);
methodVisitor.visitInsn(IALOAD);
methodVisitor.visitVarInsn(ALOAD, 5);
methodVisitor.visitInsn(ICONST_1);
methodVisitor.visitInsn(IALOAD);
methodVisitor.visitInsn(ICONST_2);
methodVisitor.visitInsn(IUSHR);
methodVisitor.visitVarInsn(ALOAD, 5);
methodVisitor.visitInsn(ICONST_1);
methodVisitor.visitInsn(IALOAD);
methodVisitor.visitIntInsn(BIPUSH, -2);
methodVisitor.visitInsn(ISHL);
methodVisitor.visitInsn(IOR);
methodVisitor.visitVarInsn(ALOAD, 5);
methodVisitor.visitInsn(ICONST_1);
methodVisitor.visitInsn(IALOAD);
methodVisitor.visitIntInsn(BIPUSH, 13);
methodVisitor.visitInsn(IUSHR);
methodVisitor.visitVarInsn(ALOAD, 5);
methodVisitor.visitInsn(ICONST_1);
methodVisitor.visitInsn(IALOAD);
methodVisitor.visitIntInsn(BIPUSH, -13);
methodVisitor.visitInsn(ISHL);
methodVisitor.visitInsn(IOR);
methodVisitor.visitInsn(IXOR);
methodVisitor.visitVarInsn(ALOAD, 5);
methodVisitor.visitInsn(ICONST_1);
methodVisitor.visitInsn(IALOAD);
methodVisitor.visitIntInsn(BIPUSH, 22);
methodVisitor.visitInsn(IUSHR);
methodVisitor.visitVarInsn(ALOAD, 5);
methodVisitor.visitInsn(ICONST_1);
methodVisitor.visitInsn(IALOAD);
methodVisitor.visitIntInsn(BIPUSH, -22);
methodVisitor.visitInsn(ISHL);
methodVisitor.visitInsn(IOR);
methodVisitor.visitInsn(IXOR);
methodVisitor.visitInsn(ISUB);
methodVisitor.visitVarInsn(ALOAD, 5);
methodVisitor.visitInsn(ICONST_1);
methodVisitor.visitInsn(IALOAD);
methodVisitor.visitVarInsn(ALOAD, 5);
methodVisitor.visitInsn(ICONST_2);
methodVisitor.visitInsn(IALOAD);
methodVisitor.visitInsn(IAND);
methodVisitor.visitVarInsn(ALOAD, 5);
methodVisitor.visitInsn(ICONST_1);
methodVisitor.visitInsn(IALOAD);
methodVisitor.visitVarInsn(ALOAD, 5);
methodVisitor.visitInsn(ICONST_3);
methodVisitor.visitInsn(IALOAD);
methodVisitor.visitInsn(IAND);
methodVisitor.visitInsn(IXOR);
methodVisitor.visitVarInsn(ALOAD, 5);
methodVisitor.visitInsn(ICONST_2);
methodVisitor.visitInsn(IALOAD);
methodVisitor.visitVarInsn(ALOAD, 5);
methodVisitor.visitInsn(ICONST_3);
methodVisitor.visitInsn(IALOAD);
methodVisitor.visitInsn(IAND);
methodVisitor.visitInsn(IXOR);
methodVisitor.visitInsn(ISUB);
methodVisitor.visitVarInsn(ISTORE, 7);
methodVisitor.visitVarInsn(ALOAD, 5);
methodVisitor.visitInsn(ICONST_0);
methodVisitor.visitVarInsn(ALOAD, 5);
methodVisitor.visitInsn(ICONST_1);
methodVisitor.visitInsn(IALOAD);
methodVisitor.visitInsn(IASTORE);
methodVisitor.visitVarInsn(ALOAD, 5);
methodVisitor.visitInsn(ICONST_1);
methodVisitor.visitVarInsn(ALOAD, 5);
methodVisitor.visitInsn(ICONST_2);
methodVisitor.visitInsn(IALOAD);
methodVisitor.visitInsn(IASTORE);
methodVisitor.visitVarInsn(ALOAD, 5);
methodVisitor.visitInsn(ICONST_2);
methodVisitor.visitVarInsn(ALOAD, 5);
methodVisitor.visitInsn(ICONST_3);
methodVisitor.visitInsn(IALOAD);
methodVisitor.visitInsn(IASTORE);
methodVisitor.visitVarInsn(ALOAD, 5);
methodVisitor.visitInsn(ICONST_3);
methodVisitor.visitVarInsn(ALOAD, 5);
methodVisitor.visitInsn(ICONST_4);
methodVisitor.visitInsn(IALOAD);
methodVisitor.visitVarInsn(ILOAD, 7);
methodVisitor.visitInsn(ISUB);
methodVisitor.visitInsn(IASTORE);
methodVisitor.visitVarInsn(ALOAD, 5);
methodVisitor.visitInsn(ICONST_4);
methodVisitor.visitVarInsn(ALOAD, 5);
methodVisitor.visitInsn(ICONST_5);
methodVisitor.visitInsn(IALOAD);
methodVisitor.visitInsn(IASTORE);
methodVisitor.visitVarInsn(ALOAD, 5);
methodVisitor.visitInsn(ICONST_5);
methodVisitor.visitVarInsn(ALOAD, 5);
methodVisitor.visitIntInsn(BIPUSH, 6);
methodVisitor.visitInsn(IALOAD);
methodVisitor.visitInsn(IASTORE);
methodVisitor.visitVarInsn(ALOAD, 5);
methodVisitor.visitIntInsn(BIPUSH, 6);
methodVisitor.visitVarInsn(ALOAD, 5);
methodVisitor.visitIntInsn(BIPUSH, 7);
methodVisitor.visitInsn(IALOAD);
methodVisitor.visitInsn(IASTORE);
methodVisitor.visitVarInsn(ALOAD, 5);
methodVisitor.visitIntInsn(BIPUSH, 7);
methodVisitor.visitVarInsn(ILOAD, 7);
methodVisitor.visitFieldInsn(GETSTATIC, "org/bouncycastle/crypto/engines/Shacal2Engine", "K", "[I");
methodVisitor.visitVarInsn(ILOAD, 6);
methodVisitor.visitInsn(IALOAD);
methodVisitor.visitInsn(ISUB);
methodVisitor.visitVarInsn(ALOAD, 0);
methodVisitor.visitFieldInsn(GETFIELD, "org/bouncycastle/crypto/engines/Shacal2Engine", "workingKey", "[I");
methodVisitor.visitVarInsn(ILOAD, 6);
methodVisitor.visitInsn(IALOAD);
methodVisitor.visitInsn(ISUB);
methodVisitor.visitVarInsn(ALOAD, 5);
methodVisitor.visitInsn(ICONST_4);
methodVisitor.visitInsn(IALOAD);
methodVisitor.visitIntInsn(BIPUSH, 6);
methodVisitor.visitInsn(IUSHR);
methodVisitor.visitVarInsn(ALOAD, 5);
methodVisitor.visitInsn(ICONST_4);
methodVisitor.visitInsn(IALOAD);
methodVisitor.visitIntInsn(BIPUSH, -6);
methodVisitor.visitInsn(ISHL);
methodVisitor.visitInsn(IOR);
methodVisitor.visitVarInsn(ALOAD, 5);
methodVisitor.visitInsn(ICONST_4);
methodVisitor.visitInsn(IALOAD);
methodVisitor.visitIntInsn(BIPUSH, 11);
methodVisitor.visitInsn(IUSHR);
methodVisitor.visitVarInsn(ALOAD, 5);
methodVisitor.visitInsn(ICONST_4);
methodVisitor.visitInsn(IALOAD);
methodVisitor.visitIntInsn(BIPUSH, -11);
methodVisitor.visitInsn(ISHL);
methodVisitor.visitInsn(IOR);
methodVisitor.visitInsn(IXOR);
methodVisitor.visitVarInsn(ALOAD, 5);
methodVisitor.visitInsn(ICONST_4);
methodVisitor.visitInsn(IALOAD);
methodVisitor.visitIntInsn(BIPUSH, 25);
methodVisitor.visitInsn(IUSHR);
methodVisitor.visitVarInsn(ALOAD, 5);
methodVisitor.visitInsn(ICONST_4);
methodVisitor.visitInsn(IALOAD);
methodVisitor.visitIntInsn(BIPUSH, -25);
methodVisitor.visitInsn(ISHL);
methodVisitor.visitInsn(IOR);
methodVisitor.visitInsn(IXOR);
methodVisitor.visitInsn(ISUB);
methodVisitor.visitVarInsn(ALOAD, 5);
methodVisitor.visitInsn(ICONST_4);
methodVisitor.visitInsn(IALOAD);
methodVisitor.visitVarInsn(ALOAD, 5);
methodVisitor.visitInsn(ICONST_5);
methodVisitor.visitInsn(IALOAD);
methodVisitor.visitInsn(IAND);
methodVisitor.visitVarInsn(ALOAD, 5);
methodVisitor.visitInsn(ICONST_4);
methodVisitor.visitInsn(IALOAD);
methodVisitor.visitInsn(ICONST_M1);
methodVisitor.visitInsn(IXOR);
methodVisitor.visitVarInsn(ALOAD, 5);
methodVisitor.visitIntInsn(BIPUSH, 6);
methodVisitor.visitInsn(IALOAD);
methodVisitor.visitInsn(IAND);
methodVisitor.visitInsn(IXOR);
methodVisitor.visitInsn(ISUB);
methodVisitor.visitInsn(IASTORE);
methodVisitor.visitIincInsn(6, -1);
methodVisitor.visitJumpInsn(GOTO, label0);
methodVisitor.visitLabel(label1);
methodVisitor.visitVarInsn(ALOAD, 0);
methodVisitor.visitVarInsn(ALOAD, 5);
methodVisitor.visitVarInsn(ALOAD, 3);
methodVisitor.visitVarInsn(ILOAD, 4);
methodVisitor.visitMethodInsn(INVOKESPECIAL, "org/bouncycastle/crypto/engines/Shacal2Engine", "ints2bytes", "([I[BI)V", false);
methodVisitor.visitInsn(RETURN);
methodVisitor.visitMaxs(7, 8);
methodVisitor.visitEnd();
}
{
methodVisitor = classWriter.visitMethod(ACC_PUBLIC, "processBlock", "([BI[BI)I", null, new String[] { "org/bouncycastle/crypto/DataLengthException", "java/lang/IllegalStateException" });
methodVisitor.visitCode();
methodVisitor.visitVarInsn(ALOAD, 0);
methodVisitor.visitFieldInsn(GETFIELD, "org/bouncycastle/crypto/engines/Shacal2Engine", "workingKey", "[I");
Label label0 = new Label();
methodVisitor.visitJumpInsn(IFNONNULL, label0);
methodVisitor.visitTypeInsn(NEW, "java/lang/IllegalStateException");
methodVisitor.visitInsn(DUP);
methodVisitor.visitLdcInsn("Shacal2 not initialised");
methodVisitor.visitMethodInsn(INVOKESPECIAL, "java/lang/IllegalStateException", "<init>", "(Ljava/lang/String;)V", false);
methodVisitor.visitInsn(ATHROW);
methodVisitor.visitLabel(label0);
methodVisitor.visitVarInsn(ILOAD, 2);
methodVisitor.visitIntInsn(BIPUSH, 32);
methodVisitor.visitInsn(IADD);
methodVisitor.visitVarInsn(ALOAD, 1);
methodVisitor.visitInsn(ARRAYLENGTH);
Label label1 = new Label();
methodVisitor.visitJumpInsn(IF_ICMPLE, label1);
methodVisitor.visitTypeInsn(NEW, "org/bouncycastle/crypto/DataLengthException");
methodVisitor.visitInsn(DUP);
methodVisitor.visitLdcInsn("input buffer too short");
methodVisitor.visitMethodInsn(INVOKESPECIAL, "org/bouncycastle/crypto/DataLengthException", "<init>", "(Ljava/lang/String;)V", false);
methodVisitor.visitInsn(ATHROW);
methodVisitor.visitLabel(label1);
methodVisitor.visitVarInsn(ILOAD, 4);
methodVisitor.visitIntInsn(BIPUSH, 32);
methodVisitor.visitInsn(IADD);
methodVisitor.visitVarInsn(ALOAD, 3);
methodVisitor.visitInsn(ARRAYLENGTH);
Label label2 = new Label();
methodVisitor.visitJumpInsn(IF_ICMPLE, label2);
methodVisitor.visitTypeInsn(NEW, "org/bouncycastle/crypto/OutputLengthException");
methodVisitor.visitInsn(DUP);
methodVisitor.visitLdcInsn("output buffer too short");
methodVisitor.visitMethodInsn(INVOKESPECIAL, "org/bouncycastle/crypto/OutputLengthException", "<init>", "(Ljava/lang/String;)V", false);
methodVisitor.visitInsn(ATHROW);
methodVisitor.visitLabel(label2);
methodVisitor.visitVarInsn(ALOAD, 0);
methodVisitor.visitFieldInsn(GETFIELD, "org/bouncycastle/crypto/engines/Shacal2Engine", "forEncryption", "Z");
Label label3 = new Label();
methodVisitor.visitJumpInsn(IFEQ, label3);
methodVisitor.visitVarInsn(ALOAD, 0);
methodVisitor.visitVarInsn(ALOAD, 1);
methodVisitor.visitVarInsn(ILOAD, 2);
methodVisitor.visitVarInsn(ALOAD, 3);
methodVisitor.visitVarInsn(ILOAD, 4);
methodVisitor.visitMethodInsn(INVOKESPECIAL, "org/bouncycastle/crypto/engines/Shacal2Engine", "encryptBlock", "([BI[BI)V", false);
Label label4 = new Label();
methodVisitor.visitJumpInsn(GOTO, label4);
methodVisitor.visitLabel(label3);
methodVisitor.visitVarInsn(ALOAD, 0);
methodVisitor.visitVarInsn(ALOAD, 1);
methodVisitor.visitVarInsn(ILOAD, 2);
methodVisitor.visitVarInsn(ALOAD, 3);
methodVisitor.visitVarInsn(ILOAD, 4);
methodVisitor.visitMethodInsn(INVOKESPECIAL, "org/bouncycastle/crypto/engines/Shacal2Engine", "decryptBlock", "([BI[BI)V", false);
methodVisitor.visitLabel(label4);
methodVisitor.visitIntInsn(BIPUSH, 32);
methodVisitor.visitInsn(IRETURN);
methodVisitor.visitMaxs(5, 5);
methodVisitor.visitEnd();
}
{
methodVisitor = classWriter.visitMethod(ACC_PRIVATE, "byteBlockToInts", "([B[III)V", null, null);
methodVisitor.visitCode();
methodVisitor.visitVarInsn(ILOAD, 4);
methodVisitor.visitVarInsn(ISTORE, 5);
Label label0 = new Label();
methodVisitor.visitLabel(label0);
methodVisitor.visitVarInsn(ILOAD, 5);
methodVisitor.visitIntInsn(BIPUSH, 8);
Label label1 = new Label();
methodVisitor.visitJumpInsn(IF_ICMPGE, label1);
methodVisitor.visitVarInsn(ALOAD, 2);
methodVisitor.visitVarInsn(ILOAD, 5);
methodVisitor.visitVarInsn(ALOAD, 1);
methodVisitor.visitVarInsn(ILOAD, 3);
methodVisitor.visitIincInsn(3, 1);
methodVisitor.visitInsn(BALOAD);
methodVisitor.visitIntInsn(SIPUSH, 255);
methodVisitor.visitInsn(IAND);
methodVisitor.visitIntInsn(BIPUSH, 24);
methodVisitor.visitInsn(ISHL);
methodVisitor.visitVarInsn(ALOAD, 1);
methodVisitor.visitVarInsn(ILOAD, 3);
methodVisitor.visitIincInsn(3, 1);
methodVisitor.visitInsn(BALOAD);
methodVisitor.visitIntInsn(SIPUSH, 255);
methodVisitor.visitInsn(IAND);
methodVisitor.visitIntInsn(BIPUSH, 16);
methodVisitor.visitInsn(ISHL);
methodVisitor.visitInsn(IOR);
methodVisitor.visitVarInsn(ALOAD, 1);
methodVisitor.visitVarInsn(ILOAD, 3);
methodVisitor.visitIincInsn(3, 1);
methodVisitor.visitInsn(BALOAD);
methodVisitor.visitIntInsn(SIPUSH, 255);
methodVisitor.visitInsn(IAND);
methodVisitor.visitIntInsn(BIPUSH, 8);
methodVisitor.visitInsn(ISHL);
methodVisitor.visitInsn(IOR);
methodVisitor.visitVarInsn(ALOAD, 1);
methodVisitor.visitVarInsn(ILOAD, 3);
methodVisitor.visitIincInsn(3, 1);
methodVisitor.visitInsn(BALOAD);
methodVisitor.visitIntInsn(SIPUSH, 255);
methodVisitor.visitInsn(IAND);
methodVisitor.visitInsn(IOR);
methodVisitor.visitInsn(IASTORE);
methodVisitor.visitIincInsn(5, 1);
methodVisitor.visitJumpInsn(GOTO, label0);
methodVisitor.visitLabel(label1);
methodVisitor.visitInsn(RETURN);
methodVisitor.visitMaxs(5, 6);
methodVisitor.visitEnd();
}
{
methodVisitor = classWriter.visitMethod(ACC_PRIVATE, "bytes2ints", "([B[III)V", null, null);
methodVisitor.visitCode();
methodVisitor.visitVarInsn(ILOAD, 4);
methodVisitor.visitVarInsn(ISTORE, 5);
Label label0 = new Label();
methodVisitor.visitLabel(label0);
methodVisitor.visitVarInsn(ILOAD, 5);
methodVisitor.visitVarInsn(ALOAD, 1);
methodVisitor.visitInsn(ARRAYLENGTH);
methodVisitor.visitInsn(ICONST_4);
methodVisitor.visitInsn(IDIV);
Label label1 = new Label();
methodVisitor.visitJumpInsn(IF_ICMPGE, label1);
methodVisitor.visitVarInsn(ALOAD, 2);
methodVisitor.visitVarInsn(ILOAD, 5);
methodVisitor.visitVarInsn(ALOAD, 1);
methodVisitor.visitVarInsn(ILOAD, 3);
methodVisitor.visitIincInsn(3, 1);
methodVisitor.visitInsn(BALOAD);
methodVisitor.visitIntInsn(SIPUSH, 255);
methodVisitor.visitInsn(IAND);
methodVisitor.visitIntInsn(BIPUSH, 24);
methodVisitor.visitInsn(ISHL);
methodVisitor.visitVarInsn(ALOAD, 1);
methodVisitor.visitVarInsn(ILOAD, 3);
methodVisitor.visitIincInsn(3, 1);
methodVisitor.visitInsn(BALOAD);
methodVisitor.visitIntInsn(SIPUSH, 255);
methodVisitor.visitInsn(IAND);
methodVisitor.visitIntInsn(BIPUSH, 16);
methodVisitor.visitInsn(ISHL);
methodVisitor.visitInsn(IOR);
methodVisitor.visitVarInsn(ALOAD, 1);
methodVisitor.visitVarInsn(ILOAD, 3);
methodVisitor.visitIincInsn(3, 1);
methodVisitor.visitInsn(BALOAD);
methodVisitor.visitIntInsn(SIPUSH, 255);
methodVisitor.visitInsn(IAND);
methodVisitor.visitIntInsn(BIPUSH, 8);
methodVisitor.visitInsn(ISHL);
methodVisitor.visitInsn(IOR);
methodVisitor.visitVarInsn(ALOAD, 1);
methodVisitor.visitVarInsn(ILOAD, 3);
methodVisitor.visitIincInsn(3, 1);
methodVisitor.visitInsn(BALOAD);
methodVisitor.visitIntInsn(SIPUSH, 255);
methodVisitor.visitInsn(IAND);
methodVisitor.visitInsn(IOR);
methodVisitor.visitInsn(IASTORE);
methodVisitor.visitIincInsn(5, 1);
methodVisitor.visitJumpInsn(GOTO, label0);
methodVisitor.visitLabel(label1);
methodVisitor.visitInsn(RETURN);
methodVisitor.visitMaxs(5, 6);
methodVisitor.visitEnd();
}
{
methodVisitor = classWriter.visitMethod(ACC_PRIVATE, "ints2bytes", "([I[BI)V", null, null);
methodVisitor.visitCode();
methodVisitor.visitInsn(ICONST_0);
methodVisitor.visitVarInsn(ISTORE, 4);
Label label0 = new Label();
methodVisitor.visitLabel(label0);
methodVisitor.visitVarInsn(ILOAD, 4);
methodVisitor.visitVarInsn(ALOAD, 1);
methodVisitor.visitInsn(ARRAYLENGTH);
Label label1 = new Label();
methodVisitor.visitJumpInsn(IF_ICMPGE, label1);
methodVisitor.visitVarInsn(ALOAD, 2);
methodVisitor.visitVarInsn(ILOAD, 3);
methodVisitor.visitIincInsn(3, 1);
methodVisitor.visitVarInsn(ALOAD, 1);
methodVisitor.visitVarInsn(ILOAD, 4);
methodVisitor.visitInsn(IALOAD);
methodVisitor.visitIntInsn(BIPUSH, 24);
methodVisitor.visitInsn(IUSHR);
methodVisitor.visitInsn(I2B);
methodVisitor.visitInsn(BASTORE);
methodVisitor.visitVarInsn(ALOAD, 2);
methodVisitor.visitVarInsn(ILOAD, 3);
methodVisitor.visitIincInsn(3, 1);
methodVisitor.visitVarInsn(ALOAD, 1);
methodVisitor.visitVarInsn(ILOAD, 4);
methodVisitor.visitInsn(IALOAD);
methodVisitor.visitIntInsn(BIPUSH, 16);
methodVisitor.visitInsn(IUSHR);
methodVisitor.visitInsn(I2B);
methodVisitor.visitInsn(BASTORE);
methodVisitor.visitVarInsn(ALOAD, 2);
methodVisitor.visitVarInsn(ILOAD, 3);
methodVisitor.visitIincInsn(3, 1);
methodVisitor.visitVarInsn(ALOAD, 1);
methodVisitor.visitVarInsn(ILOAD, 4);
methodVisitor.visitInsn(IALOAD);
methodVisitor.visitIntInsn(BIPUSH, 8);
methodVisitor.visitInsn(IUSHR);
methodVisitor.visitInsn(I2B);
methodVisitor.visitInsn(BASTORE);
methodVisitor.visitVarInsn(ALOAD, 2);
methodVisitor.visitVarInsn(ILOAD, 3);
methodVisitor.visitIincInsn(3, 1);
methodVisitor.visitVarInsn(ALOAD, 1);
methodVisitor.visitVarInsn(ILOAD, 4);
methodVisitor.visitInsn(IALOAD);
methodVisitor.visitInsn(I2B);
methodVisitor.visitInsn(BASTORE);
methodVisitor.visitIincInsn(4, 1);
methodVisitor.visitJumpInsn(GOTO, label0);
methodVisitor.visitLabel(label1);
methodVisitor.visitInsn(RETURN);
methodVisitor.visitMaxs(4, 5);
methodVisitor.visitEnd();
}
{
methodVisitor = classWriter.visitMethod(ACC_STATIC, "<clinit>", "()V", null, null);
methodVisitor.visitCode();
methodVisitor.visitIntInsn(BIPUSH, 64);
methodVisitor.visitIntInsn(NEWARRAY, T_INT);
methodVisitor.visitInsn(DUP);
methodVisitor.visitInsn(ICONST_0);
methodVisitor.visitLdcInsn(new Integer(1116352408));
methodVisitor.visitInsn(IASTORE);
methodVisitor.visitInsn(DUP);
methodVisitor.visitInsn(ICONST_1);
methodVisitor.visitLdcInsn(new Integer(1899447441));
methodVisitor.visitInsn(IASTORE);
methodVisitor.visitInsn(DUP);
methodVisitor.visitInsn(ICONST_2);
methodVisitor.visitLdcInsn(new Integer(-1245643825));
methodVisitor.visitInsn(IASTORE);
methodVisitor.visitInsn(DUP);
methodVisitor.visitInsn(ICONST_3);
methodVisitor.visitLdcInsn(new Integer(-373957723));
methodVisitor.visitInsn(IASTORE);
methodVisitor.visitInsn(DUP);
methodVisitor.visitInsn(ICONST_4);
methodVisitor.visitLdcInsn(new Integer(961987163));
methodVisitor.visitInsn(IASTORE);
methodVisitor.visitInsn(DUP);
methodVisitor.visitInsn(ICONST_5);
methodVisitor.visitLdcInsn(new Integer(1508970993));
methodVisitor.visitInsn(IASTORE);
methodVisitor.visitInsn(DUP);
methodVisitor.visitIntInsn(BIPUSH, 6);
methodVisitor.visitLdcInsn(new Integer(-1841331548));
methodVisitor.visitInsn(IASTORE);
methodVisitor.visitInsn(DUP);
methodVisitor.visitIntInsn(BIPUSH, 7);
methodVisitor.visitLdcInsn(new Integer(-1424204075));
methodVisitor.visitInsn(IASTORE);
methodVisitor.visitInsn(DUP);
methodVisitor.visitIntInsn(BIPUSH, 8);
methodVisitor.visitLdcInsn(new Integer(-670586216));
methodVisitor.visitInsn(IASTORE);
methodVisitor.visitInsn(DUP);
methodVisitor.visitIntInsn(BIPUSH, 9);
methodVisitor.visitLdcInsn(new Integer(310598401));
methodVisitor.visitInsn(IASTORE);
methodVisitor.visitInsn(DUP);
methodVisitor.visitIntInsn(BIPUSH, 10);
methodVisitor.visitLdcInsn(new Integer(607225278));
methodVisitor.visitInsn(IASTORE);
methodVisitor.visitInsn(DUP);
methodVisitor.visitIntInsn(BIPUSH, 11);
methodVisitor.visitLdcInsn(new Integer(1426881987));
methodVisitor.visitInsn(IASTORE);
methodVisitor.visitInsn(DUP);
methodVisitor.visitIntInsn(BIPUSH, 12);
methodVisitor.visitLdcInsn(new Integer(1925078388));
methodVisitor.visitInsn(IASTORE);
methodVisitor.visitInsn(DUP);
methodVisitor.visitIntInsn(BIPUSH, 13);
methodVisitor.visitLdcInsn(new Integer(-2132889090));
methodVisitor.visitInsn(IASTORE);
methodVisitor.visitInsn(DUP);
methodVisitor.visitIntInsn(BIPUSH, 14);
methodVisitor.visitLdcInsn(new Integer(-1680079193));
methodVisitor.visitInsn(IASTORE);
methodVisitor.visitInsn(DUP);
methodVisitor.visitIntInsn(BIPUSH, 15);
methodVisitor.visitLdcInsn(new Integer(-1046744716));
methodVisitor.visitInsn(IASTORE);
methodVisitor.visitInsn(DUP);
methodVisitor.visitIntInsn(BIPUSH, 16);
methodVisitor.visitLdcInsn(new Integer(-459576895));
methodVisitor.visitInsn(IASTORE);
methodVisitor.visitInsn(DUP);
methodVisitor.visitIntInsn(BIPUSH, 17);
methodVisitor.visitLdcInsn(new Integer(-272742522));
methodVisitor.visitInsn(IASTORE);
methodVisitor.visitInsn(DUP);
methodVisitor.visitIntInsn(BIPUSH, 18);
methodVisitor.visitLdcInsn(new Integer(264347078));
methodVisitor.visitInsn(IASTORE);
methodVisitor.visitInsn(DUP);
methodVisitor.visitIntInsn(BIPUSH, 19);
methodVisitor.visitLdcInsn(new Integer(604807628));
methodVisitor.visitInsn(IASTORE);
methodVisitor.visitInsn(DUP);
methodVisitor.visitIntInsn(BIPUSH, 20);
methodVisitor.visitLdcInsn(new Integer(770255983));
methodVisitor.visitInsn(IASTORE);
methodVisitor.visitInsn(DUP);
methodVisitor.visitIntInsn(BIPUSH, 21);
methodVisitor.visitLdcInsn(new Integer(1249150122));
methodVisitor.visitInsn(IASTORE);
methodVisitor.visitInsn(DUP);
methodVisitor.visitIntInsn(BIPUSH, 22);
methodVisitor.visitLdcInsn(new Integer(1555081692));
methodVisitor.visitInsn(IASTORE);
methodVisitor.visitInsn(DUP);
methodVisitor.visitIntInsn(BIPUSH, 23);
methodVisitor.visitLdcInsn(new Integer(1996064986));
methodVisitor.visitInsn(IASTORE);
methodVisitor.visitInsn(DUP);
methodVisitor.visitIntInsn(BIPUSH, 24);
methodVisitor.visitLdcInsn(new Integer(-1740746414));
methodVisitor.visitInsn(IASTORE);
methodVisitor.visitInsn(DUP);
methodVisitor.visitIntInsn(BIPUSH, 25);
methodVisitor.visitLdcInsn(new Integer(-1473132947));
methodVisitor.visitInsn(IASTORE);
methodVisitor.visitInsn(DUP);
methodVisitor.visitIntInsn(BIPUSH, 26);
methodVisitor.visitLdcInsn(new Integer(-1341970488));
methodVisitor.visitInsn(IASTORE);
methodVisitor.visitInsn(DUP);
methodVisitor.visitIntInsn(BIPUSH, 27);
methodVisitor.visitLdcInsn(new Integer(-1084653625));
methodVisitor.visitInsn(IASTORE);
methodVisitor.visitInsn(DUP);
methodVisitor.visitIntInsn(BIPUSH, 28);
methodVisitor.visitLdcInsn(new Integer(-958395405));
methodVisitor.visitInsn(IASTORE);
methodVisitor.visitInsn(DUP);
methodVisitor.visitIntInsn(BIPUSH, 29);
methodVisitor.visitLdcInsn(new Integer(-710438585));
methodVisitor.visitInsn(IASTORE);
methodVisitor.visitInsn(DUP);
methodVisitor.visitIntInsn(BIPUSH, 30);
methodVisitor.visitLdcInsn(new Integer(113926993));
methodVisitor.visitInsn(IASTORE);
methodVisitor.visitInsn(DUP);
methodVisitor.visitIntInsn(BIPUSH, 31);
methodVisitor.visitLdcInsn(new Integer(338241895));
methodVisitor.visitInsn(IASTORE);
methodVisitor.visitInsn(DUP);
methodVisitor.visitIntInsn(BIPUSH, 32);
methodVisitor.visitLdcInsn(new Integer(666307205));
methodVisitor.visitInsn(IASTORE);
methodVisitor.visitInsn(DUP);
methodVisitor.visitIntInsn(BIPUSH, 33);
methodVisitor.visitLdcInsn(new Integer(773529912));
methodVisitor.visitInsn(IASTORE);
methodVisitor.visitInsn(DUP);
methodVisitor.visitIntInsn(BIPUSH, 34);
methodVisitor.visitLdcInsn(new Integer(1294757372));
methodVisitor.visitInsn(IASTORE);
methodVisitor.visitInsn(DUP);
methodVisitor.visitIntInsn(BIPUSH, 35);
methodVisitor.visitLdcInsn(new Integer(1396182291));
methodVisitor.visitInsn(IASTORE);
methodVisitor.visitInsn(DUP);
methodVisitor.visitIntInsn(BIPUSH, 36);
methodVisitor.visitLdcInsn(new Integer(1695183700));
methodVisitor.visitInsn(IASTORE);
methodVisitor.visitInsn(DUP);
methodVisitor.visitIntInsn(BIPUSH, 37);
methodVisitor.visitLdcInsn(new Integer(1986661051));
methodVisitor.visitInsn(IASTORE);
methodVisitor.visitInsn(DUP);
methodVisitor.visitIntInsn(BIPUSH, 38);
methodVisitor.visitLdcInsn(new Integer(-2117940946));
methodVisitor.visitInsn(IASTORE);
methodVisitor.visitInsn(DUP);
methodVisitor.visitIntInsn(BIPUSH, 39);
methodVisitor.visitLdcInsn(new Integer(-1838011259));
methodVisitor.visitInsn(IASTORE);
methodVisitor.visitInsn(DUP);
methodVisitor.visitIntInsn(BIPUSH, 40);
methodVisitor.visitLdcInsn(new Integer(-1564481375));
methodVisitor.visitInsn(IASTORE);
methodVisitor.visitInsn(DUP);
methodVisitor.visitIntInsn(BIPUSH, 41);
methodVisitor.visitLdcInsn(new Integer(-1474664885));
methodVisitor.visitInsn(IASTORE);
methodVisitor.visitInsn(DUP);
methodVisitor.visitIntInsn(BIPUSH, 42);
methodVisitor.visitLdcInsn(new Integer(-1035236496));
methodVisitor.visitInsn(IASTORE);
methodVisitor.visitInsn(DUP);
methodVisitor.visitIntInsn(BIPUSH, 43);
methodVisitor.visitLdcInsn(new Integer(-949202525));
methodVisitor.visitInsn(IASTORE);
methodVisitor.visitInsn(DUP);
methodVisitor.visitIntInsn(BIPUSH, 44);
methodVisitor.visitLdcInsn(new Integer(-778901479));
methodVisitor.visitInsn(IASTORE);
methodVisitor.visitInsn(DUP);
methodVisitor.visitIntInsn(BIPUSH, 45);
methodVisitor.visitLdcInsn(new Integer(-694614492));
methodVisitor.visitInsn(IASTORE);
methodVisitor.visitInsn(DUP);
methodVisitor.visitIntInsn(BIPUSH, 46);
methodVisitor.visitLdcInsn(new Integer(-200395387));
methodVisitor.visitInsn(IASTORE);
methodVisitor.visitInsn(DUP);
methodVisitor.visitIntInsn(BIPUSH, 47);
methodVisitor.visitLdcInsn(new Integer(275423344));
methodVisitor.visitInsn(IASTORE);
methodVisitor.visitInsn(DUP);
methodVisitor.visitIntInsn(BIPUSH, 48);
methodVisitor.visitLdcInsn(new Integer(430227734));
methodVisitor.visitInsn(IASTORE);
methodVisitor.visitInsn(DUP);
methodVisitor.visitIntInsn(BIPUSH, 49);
methodVisitor.visitLdcInsn(new Integer(506948616));
methodVisitor.visitInsn(IASTORE);
methodVisitor.visitInsn(DUP);
methodVisitor.visitIntInsn(BIPUSH, 50);
methodVisitor.visitLdcInsn(new Integer(659060556));
methodVisitor.visitInsn(IASTORE);
methodVisitor.visitInsn(DUP);
methodVisitor.visitIntInsn(BIPUSH, 51);
methodVisitor.visitLdcInsn(new Integer(883997877));
methodVisitor.visitInsn(IASTORE);
methodVisitor.visitInsn(DUP);
methodVisitor.visitIntInsn(BIPUSH, 52);
methodVisitor.visitLdcInsn(new Integer(958139571));
methodVisitor.visitInsn(IASTORE);
methodVisitor.visitInsn(DUP);
methodVisitor.visitIntInsn(BIPUSH, 53);
methodVisitor.visitLdcInsn(new Integer(1322822218));
methodVisitor.visitInsn(IASTORE);
methodVisitor.visitInsn(DUP);
methodVisitor.visitIntInsn(BIPUSH, 54);
methodVisitor.visitLdcInsn(new Integer(1537002063));
methodVisitor.visitInsn(IASTORE);
methodVisitor.visitInsn(DUP);
methodVisitor.visitIntInsn(BIPUSH, 55);
methodVisitor.visitLdcInsn(new Integer(1747873779));
methodVisitor.visitInsn(IASTORE);
methodVisitor.visitInsn(DUP);
methodVisitor.visitIntInsn(BIPUSH, 56);
methodVisitor.visitLdcInsn(new Integer(1955562222));
methodVisitor.visitInsn(IASTORE);
methodVisitor.visitInsn(DUP);
methodVisitor.visitIntInsn(BIPUSH, 57);
methodVisitor.visitLdcInsn(new Integer(2024104815));
methodVisitor.visitInsn(IASTORE);
methodVisitor.visitInsn(DUP);
methodVisitor.visitIntInsn(BIPUSH, 58);
methodVisitor.visitLdcInsn(new Integer(-2067236844));
methodVisitor.visitInsn(IASTORE);
methodVisitor.visitInsn(DUP);
methodVisitor.visitIntInsn(BIPUSH, 59);
methodVisitor.visitLdcInsn(new Integer(-1933114872));
methodVisitor.visitInsn(IASTORE);
methodVisitor.visitInsn(DUP);
methodVisitor.visitIntInsn(BIPUSH, 60);
methodVisitor.visitLdcInsn(new Integer(-1866530822));
methodVisitor.visitInsn(IASTORE);
methodVisitor.visitInsn(DUP);
methodVisitor.visitIntInsn(BIPUSH, 61);
methodVisitor.visitLdcInsn(new Integer(-1538233109));
methodVisitor.visitInsn(IASTORE);
methodVisitor.visitInsn(DUP);
methodVisitor.visitIntInsn(BIPUSH, 62);
methodVisitor.visitLdcInsn(new Integer(-1090935817));
methodVisitor.visitInsn(IASTORE);
methodVisitor.visitInsn(DUP);
methodVisitor.visitIntInsn(BIPUSH, 63);
methodVisitor.visitLdcInsn(new Integer(-965641998));
methodVisitor.visitInsn(IASTORE);
methodVisitor.visitFieldInsn(PUTSTATIC, "org/bouncycastle/crypto/engines/Shacal2Engine", "K", "[I");
methodVisitor.visitInsn(RETURN);
methodVisitor.visitMaxs(4, 0);
methodVisitor.visitEnd();
}
classWriter.visitEnd();

return classWriter.toByteArray();
}
}
