package asm.com.fasterxml.jackson.core.util;
import org.objectweb.asm.AnnotationVisitor;
import org.objectweb.asm.Attribute;
import org.objectweb.asm.ClassReader;
import org.objectweb.asm.ClassWriter;
import org.objectweb.asm.ConstantDynamic;
import org.objectweb.asm.FieldVisitor;
import org.objectweb.asm.Handle;
import org.objectweb.asm.Label;
import org.objectweb.asm.MethodVisitor;
import org.objectweb.asm.Opcodes;
import org.objectweb.asm.RecordComponentVisitor;
import org.objectweb.asm.Type;
import org.objectweb.asm.TypePath;
public class ByteArrayBuilderDump implements Opcodes {

public static byte[] dump () throws Exception {

ClassWriter classWriter = new ClassWriter(0);
FieldVisitor fieldVisitor;
RecordComponentVisitor recordComponentVisitor;
MethodVisitor methodVisitor;
AnnotationVisitor annotationVisitor0;

classWriter.visit(V1_6, ACC_PUBLIC | ACC_FINAL | ACC_SUPER, "com/fasterxml/jackson/core/util/ByteArrayBuilder", null, "java/io/OutputStream", null);

{
fieldVisitor = classWriter.visitField(ACC_PUBLIC | ACC_FINAL | ACC_STATIC, "NO_BYTES", "[B", null, null);
fieldVisitor.visitEnd();
}
{
fieldVisitor = classWriter.visitField(ACC_PRIVATE | ACC_FINAL | ACC_STATIC, "INITIAL_BLOCK_SIZE", "I", null, new Integer(500));
fieldVisitor.visitEnd();
}
{
fieldVisitor = classWriter.visitField(ACC_PRIVATE | ACC_FINAL | ACC_STATIC, "MAX_BLOCK_SIZE", "I", null, new Integer(131072));
fieldVisitor.visitEnd();
}
{
fieldVisitor = classWriter.visitField(ACC_FINAL | ACC_STATIC, "DEFAULT_BLOCK_ARRAY_SIZE", "I", null, new Integer(40));
fieldVisitor.visitEnd();
}
{
fieldVisitor = classWriter.visitField(ACC_PRIVATE | ACC_FINAL, "_bufferRecycler", "Lcom/fasterxml/jackson/core/util/BufferRecycler;", null, null);
fieldVisitor.visitEnd();
}
{
fieldVisitor = classWriter.visitField(ACC_PRIVATE | ACC_FINAL, "_pastBlocks", "Ljava/util/LinkedList;", "Ljava/util/LinkedList<[B>;", null);
fieldVisitor.visitEnd();
}
{
fieldVisitor = classWriter.visitField(ACC_PRIVATE, "_pastLen", "I", null, null);
fieldVisitor.visitEnd();
}
{
fieldVisitor = classWriter.visitField(ACC_PRIVATE, "_currBlock", "[B", null, null);
fieldVisitor.visitEnd();
}
{
fieldVisitor = classWriter.visitField(ACC_PRIVATE, "_currBlockPtr", "I", null, null);
fieldVisitor.visitEnd();
}
{
methodVisitor = classWriter.visitMethod(ACC_PUBLIC, "<init>", "()V", null, null);
methodVisitor.visitCode();
methodVisitor.visitVarInsn(ALOAD, 0);
methodVisitor.visitInsn(ACONST_NULL);
methodVisitor.visitMethodInsn(INVOKESPECIAL, "com/fasterxml/jackson/core/util/ByteArrayBuilder", "<init>", "(Lcom/fasterxml/jackson/core/util/BufferRecycler;)V", false);
methodVisitor.visitInsn(RETURN);
methodVisitor.visitMaxs(2, 1);
methodVisitor.visitEnd();
}
{
methodVisitor = classWriter.visitMethod(ACC_PUBLIC, "<init>", "(Lcom/fasterxml/jackson/core/util/BufferRecycler;)V", null, null);
methodVisitor.visitCode();
methodVisitor.visitVarInsn(ALOAD, 0);
methodVisitor.visitVarInsn(ALOAD, 1);
methodVisitor.visitIntInsn(SIPUSH, 500);
methodVisitor.visitMethodInsn(INVOKESPECIAL, "com/fasterxml/jackson/core/util/ByteArrayBuilder", "<init>", "(Lcom/fasterxml/jackson/core/util/BufferRecycler;I)V", false);
methodVisitor.visitInsn(RETURN);
methodVisitor.visitMaxs(3, 2);
methodVisitor.visitEnd();
}
{
methodVisitor = classWriter.visitMethod(ACC_PUBLIC, "<init>", "(I)V", null, null);
methodVisitor.visitCode();
methodVisitor.visitVarInsn(ALOAD, 0);
methodVisitor.visitInsn(ACONST_NULL);
methodVisitor.visitVarInsn(ILOAD, 1);
methodVisitor.visitMethodInsn(INVOKESPECIAL, "com/fasterxml/jackson/core/util/ByteArrayBuilder", "<init>", "(Lcom/fasterxml/jackson/core/util/BufferRecycler;I)V", false);
methodVisitor.visitInsn(RETURN);
methodVisitor.visitMaxs(3, 2);
methodVisitor.visitEnd();
}
{
methodVisitor = classWriter.visitMethod(ACC_PUBLIC, "<init>", "(Lcom/fasterxml/jackson/core/util/BufferRecycler;I)V", null, null);
methodVisitor.visitCode();
methodVisitor.visitVarInsn(ALOAD, 0);
methodVisitor.visitMethodInsn(INVOKESPECIAL, "java/io/OutputStream", "<init>", "()V", false);
methodVisitor.visitVarInsn(ALOAD, 0);
methodVisitor.visitTypeInsn(NEW, "java/util/LinkedList");
methodVisitor.visitInsn(DUP);
methodVisitor.visitMethodInsn(INVOKESPECIAL, "java/util/LinkedList", "<init>", "()V", false);
methodVisitor.visitFieldInsn(PUTFIELD, "com/fasterxml/jackson/core/util/ByteArrayBuilder", "_pastBlocks", "Ljava/util/LinkedList;");
methodVisitor.visitVarInsn(ALOAD, 0);
methodVisitor.visitVarInsn(ALOAD, 1);
methodVisitor.visitFieldInsn(PUTFIELD, "com/fasterxml/jackson/core/util/ByteArrayBuilder", "_bufferRecycler", "Lcom/fasterxml/jackson/core/util/BufferRecycler;");
methodVisitor.visitVarInsn(ALOAD, 0);
methodVisitor.visitVarInsn(ALOAD, 1);
Label label0 = new Label();
methodVisitor.visitJumpInsn(IFNONNULL, label0);
methodVisitor.visitVarInsn(ILOAD, 2);
methodVisitor.visitIntInsn(NEWARRAY, T_BYTE);
Label label1 = new Label();
methodVisitor.visitJumpInsn(GOTO, label1);
methodVisitor.visitLabel(label0);
methodVisitor.visitFrame(Opcodes.F_FULL, 3, new Object[] {"com/fasterxml/jackson/core/util/ByteArrayBuilder", "com/fasterxml/jackson/core/util/BufferRecycler", Opcodes.INTEGER}, 1, new Object[] {"com/fasterxml/jackson/core/util/ByteArrayBuilder"});
methodVisitor.visitVarInsn(ALOAD, 1);
methodVisitor.visitInsn(ICONST_2);
methodVisitor.visitMethodInsn(INVOKEVIRTUAL, "com/fasterxml/jackson/core/util/BufferRecycler", "allocByteBuffer", "(I)[B", false);
methodVisitor.visitLabel(label1);
methodVisitor.visitFrame(Opcodes.F_FULL, 3, new Object[] {"com/fasterxml/jackson/core/util/ByteArrayBuilder", "com/fasterxml/jackson/core/util/BufferRecycler", Opcodes.INTEGER}, 2, new Object[] {"com/fasterxml/jackson/core/util/ByteArrayBuilder", "[B"});
methodVisitor.visitFieldInsn(PUTFIELD, "com/fasterxml/jackson/core/util/ByteArrayBuilder", "_currBlock", "[B");
methodVisitor.visitInsn(RETURN);
methodVisitor.visitMaxs(3, 3);
methodVisitor.visitEnd();
}
{
methodVisitor = classWriter.visitMethod(ACC_PRIVATE, "<init>", "(Lcom/fasterxml/jackson/core/util/BufferRecycler;[BI)V", null, null);
methodVisitor.visitCode();
methodVisitor.visitVarInsn(ALOAD, 0);
methodVisitor.visitMethodInsn(INVOKESPECIAL, "java/io/OutputStream", "<init>", "()V", false);
methodVisitor.visitVarInsn(ALOAD, 0);
methodVisitor.visitTypeInsn(NEW, "java/util/LinkedList");
methodVisitor.visitInsn(DUP);
methodVisitor.visitMethodInsn(INVOKESPECIAL, "java/util/LinkedList", "<init>", "()V", false);
methodVisitor.visitFieldInsn(PUTFIELD, "com/fasterxml/jackson/core/util/ByteArrayBuilder", "_pastBlocks", "Ljava/util/LinkedList;");
methodVisitor.visitVarInsn(ALOAD, 0);
methodVisitor.visitInsn(ACONST_NULL);
methodVisitor.visitFieldInsn(PUTFIELD, "com/fasterxml/jackson/core/util/ByteArrayBuilder", "_bufferRecycler", "Lcom/fasterxml/jackson/core/util/BufferRecycler;");
methodVisitor.visitVarInsn(ALOAD, 0);
methodVisitor.visitVarInsn(ALOAD, 2);
methodVisitor.visitFieldInsn(PUTFIELD, "com/fasterxml/jackson/core/util/ByteArrayBuilder", "_currBlock", "[B");
methodVisitor.visitVarInsn(ALOAD, 0);
methodVisitor.visitVarInsn(ILOAD, 3);
methodVisitor.visitFieldInsn(PUTFIELD, "com/fasterxml/jackson/core/util/ByteArrayBuilder", "_currBlockPtr", "I");
methodVisitor.visitInsn(RETURN);
methodVisitor.visitMaxs(3, 4);
methodVisitor.visitEnd();
}
{
methodVisitor = classWriter.visitMethod(ACC_PUBLIC | ACC_STATIC, "fromInitial", "([BI)Lcom/fasterxml/jackson/core/util/ByteArrayBuilder;", null, null);
methodVisitor.visitCode();
methodVisitor.visitTypeInsn(NEW, "com/fasterxml/jackson/core/util/ByteArrayBuilder");
methodVisitor.visitInsn(DUP);
methodVisitor.visitInsn(ACONST_NULL);
methodVisitor.visitVarInsn(ALOAD, 0);
methodVisitor.visitVarInsn(ILOAD, 1);
methodVisitor.visitMethodInsn(INVOKESPECIAL, "com/fasterxml/jackson/core/util/ByteArrayBuilder", "<init>", "(Lcom/fasterxml/jackson/core/util/BufferRecycler;[BI)V", false);
methodVisitor.visitInsn(ARETURN);
methodVisitor.visitMaxs(5, 2);
methodVisitor.visitEnd();
}
{
methodVisitor = classWriter.visitMethod(ACC_PUBLIC, "reset", "()V", null, null);
methodVisitor.visitCode();
methodVisitor.visitVarInsn(ALOAD, 0);
methodVisitor.visitInsn(ICONST_0);
methodVisitor.visitFieldInsn(PUTFIELD, "com/fasterxml/jackson/core/util/ByteArrayBuilder", "_pastLen", "I");
methodVisitor.visitVarInsn(ALOAD, 0);
methodVisitor.visitInsn(ICONST_0);
methodVisitor.visitFieldInsn(PUTFIELD, "com/fasterxml/jackson/core/util/ByteArrayBuilder", "_currBlockPtr", "I");
methodVisitor.visitVarInsn(ALOAD, 0);
methodVisitor.visitFieldInsn(GETFIELD, "com/fasterxml/jackson/core/util/ByteArrayBuilder", "_pastBlocks", "Ljava/util/LinkedList;");
methodVisitor.visitMethodInsn(INVOKEVIRTUAL, "java/util/LinkedList", "isEmpty", "()Z", false);
Label label0 = new Label();
methodVisitor.visitJumpInsn(IFNE, label0);
methodVisitor.visitVarInsn(ALOAD, 0);
methodVisitor.visitFieldInsn(GETFIELD, "com/fasterxml/jackson/core/util/ByteArrayBuilder", "_pastBlocks", "Ljava/util/LinkedList;");
methodVisitor.visitMethodInsn(INVOKEVIRTUAL, "java/util/LinkedList", "clear", "()V", false);
methodVisitor.visitLabel(label0);
methodVisitor.visitFrame(Opcodes.F_SAME, 0, null, 0, null);
methodVisitor.visitInsn(RETURN);
methodVisitor.visitMaxs(2, 1);
methodVisitor.visitEnd();
}
{
methodVisitor = classWriter.visitMethod(ACC_PUBLIC, "size", "()I", null, null);
methodVisitor.visitCode();
methodVisitor.visitVarInsn(ALOAD, 0);
methodVisitor.visitFieldInsn(GETFIELD, "com/fasterxml/jackson/core/util/ByteArrayBuilder", "_pastLen", "I");
methodVisitor.visitVarInsn(ALOAD, 0);
methodVisitor.visitFieldInsn(GETFIELD, "com/fasterxml/jackson/core/util/ByteArrayBuilder", "_currBlockPtr", "I");
methodVisitor.visitInsn(IADD);
methodVisitor.visitInsn(IRETURN);
methodVisitor.visitMaxs(2, 1);
methodVisitor.visitEnd();
}
{
methodVisitor = classWriter.visitMethod(ACC_PUBLIC, "release", "()V", null, null);
methodVisitor.visitCode();
methodVisitor.visitVarInsn(ALOAD, 0);
methodVisitor.visitMethodInsn(INVOKEVIRTUAL, "com/fasterxml/jackson/core/util/ByteArrayBuilder", "reset", "()V", false);
methodVisitor.visitVarInsn(ALOAD, 0);
methodVisitor.visitFieldInsn(GETFIELD, "com/fasterxml/jackson/core/util/ByteArrayBuilder", "_bufferRecycler", "Lcom/fasterxml/jackson/core/util/BufferRecycler;");
Label label0 = new Label();
methodVisitor.visitJumpInsn(IFNULL, label0);
methodVisitor.visitVarInsn(ALOAD, 0);
methodVisitor.visitFieldInsn(GETFIELD, "com/fasterxml/jackson/core/util/ByteArrayBuilder", "_currBlock", "[B");
methodVisitor.visitJumpInsn(IFNULL, label0);
methodVisitor.visitVarInsn(ALOAD, 0);
methodVisitor.visitFieldInsn(GETFIELD, "com/fasterxml/jackson/core/util/ByteArrayBuilder", "_bufferRecycler", "Lcom/fasterxml/jackson/core/util/BufferRecycler;");
methodVisitor.visitInsn(ICONST_2);
methodVisitor.visitVarInsn(ALOAD, 0);
methodVisitor.visitFieldInsn(GETFIELD, "com/fasterxml/jackson/core/util/ByteArrayBuilder", "_currBlock", "[B");
methodVisitor.visitMethodInsn(INVOKEVIRTUAL, "com/fasterxml/jackson/core/util/BufferRecycler", "releaseByteBuffer", "(I[B)V", false);
methodVisitor.visitVarInsn(ALOAD, 0);
methodVisitor.visitInsn(ACONST_NULL);
methodVisitor.visitFieldInsn(PUTFIELD, "com/fasterxml/jackson/core/util/ByteArrayBuilder", "_currBlock", "[B");
methodVisitor.visitLabel(label0);
methodVisitor.visitFrame(Opcodes.F_SAME, 0, null, 0, null);
methodVisitor.visitInsn(RETURN);
methodVisitor.visitMaxs(3, 1);
methodVisitor.visitEnd();
}
{
methodVisitor = classWriter.visitMethod(ACC_PUBLIC, "append", "(I)V", null, null);
methodVisitor.visitCode();
methodVisitor.visitVarInsn(ALOAD, 0);
methodVisitor.visitFieldInsn(GETFIELD, "com/fasterxml/jackson/core/util/ByteArrayBuilder", "_currBlockPtr", "I");
methodVisitor.visitVarInsn(ALOAD, 0);
methodVisitor.visitFieldInsn(GETFIELD, "com/fasterxml/jackson/core/util/ByteArrayBuilder", "_currBlock", "[B");
methodVisitor.visitInsn(ARRAYLENGTH);
Label label0 = new Label();
methodVisitor.visitJumpInsn(IF_ICMPLT, label0);
methodVisitor.visitVarInsn(ALOAD, 0);
methodVisitor.visitMethodInsn(INVOKESPECIAL, "com/fasterxml/jackson/core/util/ByteArrayBuilder", "_allocMore", "()V", false);
methodVisitor.visitLabel(label0);
methodVisitor.visitFrame(Opcodes.F_SAME, 0, null, 0, null);
methodVisitor.visitVarInsn(ALOAD, 0);
methodVisitor.visitFieldInsn(GETFIELD, "com/fasterxml/jackson/core/util/ByteArrayBuilder", "_currBlock", "[B");
methodVisitor.visitVarInsn(ALOAD, 0);
methodVisitor.visitInsn(DUP);
methodVisitor.visitFieldInsn(GETFIELD, "com/fasterxml/jackson/core/util/ByteArrayBuilder", "_currBlockPtr", "I");
methodVisitor.visitInsn(DUP_X1);
methodVisitor.visitInsn(ICONST_1);
methodVisitor.visitInsn(IADD);
methodVisitor.visitFieldInsn(PUTFIELD, "com/fasterxml/jackson/core/util/ByteArrayBuilder", "_currBlockPtr", "I");
methodVisitor.visitVarInsn(ILOAD, 1);
methodVisitor.visitInsn(I2B);
methodVisitor.visitInsn(BASTORE);
methodVisitor.visitInsn(RETURN);
methodVisitor.visitMaxs(5, 2);
methodVisitor.visitEnd();
}
{
methodVisitor = classWriter.visitMethod(ACC_PUBLIC, "appendTwoBytes", "(I)V", null, null);
methodVisitor.visitCode();
methodVisitor.visitVarInsn(ALOAD, 0);
methodVisitor.visitFieldInsn(GETFIELD, "com/fasterxml/jackson/core/util/ByteArrayBuilder", "_currBlockPtr", "I");
methodVisitor.visitInsn(ICONST_1);
methodVisitor.visitInsn(IADD);
methodVisitor.visitVarInsn(ALOAD, 0);
methodVisitor.visitFieldInsn(GETFIELD, "com/fasterxml/jackson/core/util/ByteArrayBuilder", "_currBlock", "[B");
methodVisitor.visitInsn(ARRAYLENGTH);
Label label0 = new Label();
methodVisitor.visitJumpInsn(IF_ICMPGE, label0);
methodVisitor.visitVarInsn(ALOAD, 0);
methodVisitor.visitFieldInsn(GETFIELD, "com/fasterxml/jackson/core/util/ByteArrayBuilder", "_currBlock", "[B");
methodVisitor.visitVarInsn(ALOAD, 0);
methodVisitor.visitInsn(DUP);
methodVisitor.visitFieldInsn(GETFIELD, "com/fasterxml/jackson/core/util/ByteArrayBuilder", "_currBlockPtr", "I");
methodVisitor.visitInsn(DUP_X1);
methodVisitor.visitInsn(ICONST_1);
methodVisitor.visitInsn(IADD);
methodVisitor.visitFieldInsn(PUTFIELD, "com/fasterxml/jackson/core/util/ByteArrayBuilder", "_currBlockPtr", "I");
methodVisitor.visitVarInsn(ILOAD, 1);
methodVisitor.visitIntInsn(BIPUSH, 8);
methodVisitor.visitInsn(ISHR);
methodVisitor.visitInsn(I2B);
methodVisitor.visitInsn(BASTORE);
methodVisitor.visitVarInsn(ALOAD, 0);
methodVisitor.visitFieldInsn(GETFIELD, "com/fasterxml/jackson/core/util/ByteArrayBuilder", "_currBlock", "[B");
methodVisitor.visitVarInsn(ALOAD, 0);
methodVisitor.visitInsn(DUP);
methodVisitor.visitFieldInsn(GETFIELD, "com/fasterxml/jackson/core/util/ByteArrayBuilder", "_currBlockPtr", "I");
methodVisitor.visitInsn(DUP_X1);
methodVisitor.visitInsn(ICONST_1);
methodVisitor.visitInsn(IADD);
methodVisitor.visitFieldInsn(PUTFIELD, "com/fasterxml/jackson/core/util/ByteArrayBuilder", "_currBlockPtr", "I");
methodVisitor.visitVarInsn(ILOAD, 1);
methodVisitor.visitInsn(I2B);
methodVisitor.visitInsn(BASTORE);
Label label1 = new Label();
methodVisitor.visitJumpInsn(GOTO, label1);
methodVisitor.visitLabel(label0);
methodVisitor.visitFrame(Opcodes.F_SAME, 0, null, 0, null);
methodVisitor.visitVarInsn(ALOAD, 0);
methodVisitor.visitVarInsn(ILOAD, 1);
methodVisitor.visitIntInsn(BIPUSH, 8);
methodVisitor.visitInsn(ISHR);
methodVisitor.visitMethodInsn(INVOKEVIRTUAL, "com/fasterxml/jackson/core/util/ByteArrayBuilder", "append", "(I)V", false);
methodVisitor.visitVarInsn(ALOAD, 0);
methodVisitor.visitVarInsn(ILOAD, 1);
methodVisitor.visitMethodInsn(INVOKEVIRTUAL, "com/fasterxml/jackson/core/util/ByteArrayBuilder", "append", "(I)V", false);
methodVisitor.visitLabel(label1);
methodVisitor.visitFrame(Opcodes.F_SAME, 0, null, 0, null);
methodVisitor.visitInsn(RETURN);
methodVisitor.visitMaxs(5, 2);
methodVisitor.visitEnd();
}
{
methodVisitor = classWriter.visitMethod(ACC_PUBLIC, "appendThreeBytes", "(I)V", null, null);
methodVisitor.visitCode();
methodVisitor.visitVarInsn(ALOAD, 0);
methodVisitor.visitFieldInsn(GETFIELD, "com/fasterxml/jackson/core/util/ByteArrayBuilder", "_currBlockPtr", "I");
methodVisitor.visitInsn(ICONST_2);
methodVisitor.visitInsn(IADD);
methodVisitor.visitVarInsn(ALOAD, 0);
methodVisitor.visitFieldInsn(GETFIELD, "com/fasterxml/jackson/core/util/ByteArrayBuilder", "_currBlock", "[B");
methodVisitor.visitInsn(ARRAYLENGTH);
Label label0 = new Label();
methodVisitor.visitJumpInsn(IF_ICMPGE, label0);
methodVisitor.visitVarInsn(ALOAD, 0);
methodVisitor.visitFieldInsn(GETFIELD, "com/fasterxml/jackson/core/util/ByteArrayBuilder", "_currBlock", "[B");
methodVisitor.visitVarInsn(ALOAD, 0);
methodVisitor.visitInsn(DUP);
methodVisitor.visitFieldInsn(GETFIELD, "com/fasterxml/jackson/core/util/ByteArrayBuilder", "_currBlockPtr", "I");
methodVisitor.visitInsn(DUP_X1);
methodVisitor.visitInsn(ICONST_1);
methodVisitor.visitInsn(IADD);
methodVisitor.visitFieldInsn(PUTFIELD, "com/fasterxml/jackson/core/util/ByteArrayBuilder", "_currBlockPtr", "I");
methodVisitor.visitVarInsn(ILOAD, 1);
methodVisitor.visitIntInsn(BIPUSH, 16);
methodVisitor.visitInsn(ISHR);
methodVisitor.visitInsn(I2B);
methodVisitor.visitInsn(BASTORE);
methodVisitor.visitVarInsn(ALOAD, 0);
methodVisitor.visitFieldInsn(GETFIELD, "com/fasterxml/jackson/core/util/ByteArrayBuilder", "_currBlock", "[B");
methodVisitor.visitVarInsn(ALOAD, 0);
methodVisitor.visitInsn(DUP);
methodVisitor.visitFieldInsn(GETFIELD, "com/fasterxml/jackson/core/util/ByteArrayBuilder", "_currBlockPtr", "I");
methodVisitor.visitInsn(DUP_X1);
methodVisitor.visitInsn(ICONST_1);
methodVisitor.visitInsn(IADD);
methodVisitor.visitFieldInsn(PUTFIELD, "com/fasterxml/jackson/core/util/ByteArrayBuilder", "_currBlockPtr", "I");
methodVisitor.visitVarInsn(ILOAD, 1);
methodVisitor.visitIntInsn(BIPUSH, 8);
methodVisitor.visitInsn(ISHR);
methodVisitor.visitInsn(I2B);
methodVisitor.visitInsn(BASTORE);
methodVisitor.visitVarInsn(ALOAD, 0);
methodVisitor.visitFieldInsn(GETFIELD, "com/fasterxml/jackson/core/util/ByteArrayBuilder", "_currBlock", "[B");
methodVisitor.visitVarInsn(ALOAD, 0);
methodVisitor.visitInsn(DUP);
methodVisitor.visitFieldInsn(GETFIELD, "com/fasterxml/jackson/core/util/ByteArrayBuilder", "_currBlockPtr", "I");
methodVisitor.visitInsn(DUP_X1);
methodVisitor.visitInsn(ICONST_1);
methodVisitor.visitInsn(IADD);
methodVisitor.visitFieldInsn(PUTFIELD, "com/fasterxml/jackson/core/util/ByteArrayBuilder", "_currBlockPtr", "I");
methodVisitor.visitVarInsn(ILOAD, 1);
methodVisitor.visitInsn(I2B);
methodVisitor.visitInsn(BASTORE);
Label label1 = new Label();
methodVisitor.visitJumpInsn(GOTO, label1);
methodVisitor.visitLabel(label0);
methodVisitor.visitFrame(Opcodes.F_SAME, 0, null, 0, null);
methodVisitor.visitVarInsn(ALOAD, 0);
methodVisitor.visitVarInsn(ILOAD, 1);
methodVisitor.visitIntInsn(BIPUSH, 16);
methodVisitor.visitInsn(ISHR);
methodVisitor.visitMethodInsn(INVOKEVIRTUAL, "com/fasterxml/jackson/core/util/ByteArrayBuilder", "append", "(I)V", false);
methodVisitor.visitVarInsn(ALOAD, 0);
methodVisitor.visitVarInsn(ILOAD, 1);
methodVisitor.visitIntInsn(BIPUSH, 8);
methodVisitor.visitInsn(ISHR);
methodVisitor.visitMethodInsn(INVOKEVIRTUAL, "com/fasterxml/jackson/core/util/ByteArrayBuilder", "append", "(I)V", false);
methodVisitor.visitVarInsn(ALOAD, 0);
methodVisitor.visitVarInsn(ILOAD, 1);
methodVisitor.visitMethodInsn(INVOKEVIRTUAL, "com/fasterxml/jackson/core/util/ByteArrayBuilder", "append", "(I)V", false);
methodVisitor.visitLabel(label1);
methodVisitor.visitFrame(Opcodes.F_SAME, 0, null, 0, null);
methodVisitor.visitInsn(RETURN);
methodVisitor.visitMaxs(5, 2);
methodVisitor.visitEnd();
}
{
methodVisitor = classWriter.visitMethod(ACC_PUBLIC, "appendFourBytes", "(I)V", null, null);
methodVisitor.visitCode();
methodVisitor.visitVarInsn(ALOAD, 0);
methodVisitor.visitFieldInsn(GETFIELD, "com/fasterxml/jackson/core/util/ByteArrayBuilder", "_currBlockPtr", "I");
methodVisitor.visitInsn(ICONST_3);
methodVisitor.visitInsn(IADD);
methodVisitor.visitVarInsn(ALOAD, 0);
methodVisitor.visitFieldInsn(GETFIELD, "com/fasterxml/jackson/core/util/ByteArrayBuilder", "_currBlock", "[B");
methodVisitor.visitInsn(ARRAYLENGTH);
Label label0 = new Label();
methodVisitor.visitJumpInsn(IF_ICMPGE, label0);
methodVisitor.visitVarInsn(ALOAD, 0);
methodVisitor.visitFieldInsn(GETFIELD, "com/fasterxml/jackson/core/util/ByteArrayBuilder", "_currBlock", "[B");
methodVisitor.visitVarInsn(ALOAD, 0);
methodVisitor.visitInsn(DUP);
methodVisitor.visitFieldInsn(GETFIELD, "com/fasterxml/jackson/core/util/ByteArrayBuilder", "_currBlockPtr", "I");
methodVisitor.visitInsn(DUP_X1);
methodVisitor.visitInsn(ICONST_1);
methodVisitor.visitInsn(IADD);
methodVisitor.visitFieldInsn(PUTFIELD, "com/fasterxml/jackson/core/util/ByteArrayBuilder", "_currBlockPtr", "I");
methodVisitor.visitVarInsn(ILOAD, 1);
methodVisitor.visitIntInsn(BIPUSH, 24);
methodVisitor.visitInsn(ISHR);
methodVisitor.visitInsn(I2B);
methodVisitor.visitInsn(BASTORE);
methodVisitor.visitVarInsn(ALOAD, 0);
methodVisitor.visitFieldInsn(GETFIELD, "com/fasterxml/jackson/core/util/ByteArrayBuilder", "_currBlock", "[B");
methodVisitor.visitVarInsn(ALOAD, 0);
methodVisitor.visitInsn(DUP);
methodVisitor.visitFieldInsn(GETFIELD, "com/fasterxml/jackson/core/util/ByteArrayBuilder", "_currBlockPtr", "I");
methodVisitor.visitInsn(DUP_X1);
methodVisitor.visitInsn(ICONST_1);
methodVisitor.visitInsn(IADD);
methodVisitor.visitFieldInsn(PUTFIELD, "com/fasterxml/jackson/core/util/ByteArrayBuilder", "_currBlockPtr", "I");
methodVisitor.visitVarInsn(ILOAD, 1);
methodVisitor.visitIntInsn(BIPUSH, 16);
methodVisitor.visitInsn(ISHR);
methodVisitor.visitInsn(I2B);
methodVisitor.visitInsn(BASTORE);
methodVisitor.visitVarInsn(ALOAD, 0);
methodVisitor.visitFieldInsn(GETFIELD, "com/fasterxml/jackson/core/util/ByteArrayBuilder", "_currBlock", "[B");
methodVisitor.visitVarInsn(ALOAD, 0);
methodVisitor.visitInsn(DUP);
methodVisitor.visitFieldInsn(GETFIELD, "com/fasterxml/jackson/core/util/ByteArrayBuilder", "_currBlockPtr", "I");
methodVisitor.visitInsn(DUP_X1);
methodVisitor.visitInsn(ICONST_1);
methodVisitor.visitInsn(IADD);
methodVisitor.visitFieldInsn(PUTFIELD, "com/fasterxml/jackson/core/util/ByteArrayBuilder", "_currBlockPtr", "I");
methodVisitor.visitVarInsn(ILOAD, 1);
methodVisitor.visitIntInsn(BIPUSH, 8);
methodVisitor.visitInsn(ISHR);
methodVisitor.visitInsn(I2B);
methodVisitor.visitInsn(BASTORE);
methodVisitor.visitVarInsn(ALOAD, 0);
methodVisitor.visitFieldInsn(GETFIELD, "com/fasterxml/jackson/core/util/ByteArrayBuilder", "_currBlock", "[B");
methodVisitor.visitVarInsn(ALOAD, 0);
methodVisitor.visitInsn(DUP);
methodVisitor.visitFieldInsn(GETFIELD, "com/fasterxml/jackson/core/util/ByteArrayBuilder", "_currBlockPtr", "I");
methodVisitor.visitInsn(DUP_X1);
methodVisitor.visitInsn(ICONST_1);
methodVisitor.visitInsn(IADD);
methodVisitor.visitFieldInsn(PUTFIELD, "com/fasterxml/jackson/core/util/ByteArrayBuilder", "_currBlockPtr", "I");
methodVisitor.visitVarInsn(ILOAD, 1);
methodVisitor.visitInsn(I2B);
methodVisitor.visitInsn(BASTORE);
Label label1 = new Label();
methodVisitor.visitJumpInsn(GOTO, label1);
methodVisitor.visitLabel(label0);
methodVisitor.visitFrame(Opcodes.F_SAME, 0, null, 0, null);
methodVisitor.visitVarInsn(ALOAD, 0);
methodVisitor.visitVarInsn(ILOAD, 1);
methodVisitor.visitIntInsn(BIPUSH, 24);
methodVisitor.visitInsn(ISHR);
methodVisitor.visitMethodInsn(INVOKEVIRTUAL, "com/fasterxml/jackson/core/util/ByteArrayBuilder", "append", "(I)V", false);
methodVisitor.visitVarInsn(ALOAD, 0);
methodVisitor.visitVarInsn(ILOAD, 1);
methodVisitor.visitIntInsn(BIPUSH, 16);
methodVisitor.visitInsn(ISHR);
methodVisitor.visitMethodInsn(INVOKEVIRTUAL, "com/fasterxml/jackson/core/util/ByteArrayBuilder", "append", "(I)V", false);
methodVisitor.visitVarInsn(ALOAD, 0);
methodVisitor.visitVarInsn(ILOAD, 1);
methodVisitor.visitIntInsn(BIPUSH, 8);
methodVisitor.visitInsn(ISHR);
methodVisitor.visitMethodInsn(INVOKEVIRTUAL, "com/fasterxml/jackson/core/util/ByteArrayBuilder", "append", "(I)V", false);
methodVisitor.visitVarInsn(ALOAD, 0);
methodVisitor.visitVarInsn(ILOAD, 1);
methodVisitor.visitMethodInsn(INVOKEVIRTUAL, "com/fasterxml/jackson/core/util/ByteArrayBuilder", "append", "(I)V", false);
methodVisitor.visitLabel(label1);
methodVisitor.visitFrame(Opcodes.F_SAME, 0, null, 0, null);
methodVisitor.visitInsn(RETURN);
methodVisitor.visitMaxs(5, 2);
methodVisitor.visitEnd();
}
{
methodVisitor = classWriter.visitMethod(ACC_PUBLIC, "toByteArray", "()[B", null, null);
methodVisitor.visitCode();
methodVisitor.visitVarInsn(ALOAD, 0);
methodVisitor.visitFieldInsn(GETFIELD, "com/fasterxml/jackson/core/util/ByteArrayBuilder", "_pastLen", "I");
methodVisitor.visitVarInsn(ALOAD, 0);
methodVisitor.visitFieldInsn(GETFIELD, "com/fasterxml/jackson/core/util/ByteArrayBuilder", "_currBlockPtr", "I");
methodVisitor.visitInsn(IADD);
methodVisitor.visitVarInsn(ISTORE, 1);
methodVisitor.visitVarInsn(ILOAD, 1);
Label label0 = new Label();
methodVisitor.visitJumpInsn(IFNE, label0);
methodVisitor.visitFieldInsn(GETSTATIC, "com/fasterxml/jackson/core/util/ByteArrayBuilder", "NO_BYTES", "[B");
methodVisitor.visitInsn(ARETURN);
methodVisitor.visitLabel(label0);
methodVisitor.visitFrame(Opcodes.F_APPEND,1, new Object[] {Opcodes.INTEGER}, 0, null);
methodVisitor.visitVarInsn(ILOAD, 1);
methodVisitor.visitIntInsn(NEWARRAY, T_BYTE);
methodVisitor.visitVarInsn(ASTORE, 2);
methodVisitor.visitInsn(ICONST_0);
methodVisitor.visitVarInsn(ISTORE, 3);
methodVisitor.visitVarInsn(ALOAD, 0);
methodVisitor.visitFieldInsn(GETFIELD, "com/fasterxml/jackson/core/util/ByteArrayBuilder", "_pastBlocks", "Ljava/util/LinkedList;");
methodVisitor.visitMethodInsn(INVOKEVIRTUAL, "java/util/LinkedList", "iterator", "()Ljava/util/Iterator;", false);
methodVisitor.visitVarInsn(ASTORE, 4);
Label label1 = new Label();
methodVisitor.visitLabel(label1);
methodVisitor.visitFrame(Opcodes.F_APPEND,3, new Object[] {"[B", Opcodes.INTEGER, "java/util/Iterator"}, 0, null);
methodVisitor.visitVarInsn(ALOAD, 4);
methodVisitor.visitMethodInsn(INVOKEINTERFACE, "java/util/Iterator", "hasNext", "()Z", true);
Label label2 = new Label();
methodVisitor.visitJumpInsn(IFEQ, label2);
methodVisitor.visitVarInsn(ALOAD, 4);
methodVisitor.visitMethodInsn(INVOKEINTERFACE, "java/util/Iterator", "next", "()Ljava/lang/Object;", true);
methodVisitor.visitTypeInsn(CHECKCAST, "[B");
methodVisitor.visitVarInsn(ASTORE, 5);
methodVisitor.visitVarInsn(ALOAD, 5);
methodVisitor.visitInsn(ARRAYLENGTH);
methodVisitor.visitVarInsn(ISTORE, 6);
methodVisitor.visitVarInsn(ALOAD, 5);
methodVisitor.visitInsn(ICONST_0);
methodVisitor.visitVarInsn(ALOAD, 2);
methodVisitor.visitVarInsn(ILOAD, 3);
methodVisitor.visitVarInsn(ILOAD, 6);
methodVisitor.visitMethodInsn(INVOKESTATIC, "java/lang/System", "arraycopy", "(Ljava/lang/Object;ILjava/lang/Object;II)V", false);
methodVisitor.visitVarInsn(ILOAD, 3);
methodVisitor.visitVarInsn(ILOAD, 6);
methodVisitor.visitInsn(IADD);
methodVisitor.visitVarInsn(ISTORE, 3);
methodVisitor.visitJumpInsn(GOTO, label1);
methodVisitor.visitLabel(label2);
methodVisitor.visitFrame(Opcodes.F_CHOP,1, null, 0, null);
methodVisitor.visitVarInsn(ALOAD, 0);
methodVisitor.visitFieldInsn(GETFIELD, "com/fasterxml/jackson/core/util/ByteArrayBuilder", "_currBlock", "[B");
methodVisitor.visitInsn(ICONST_0);
methodVisitor.visitVarInsn(ALOAD, 2);
methodVisitor.visitVarInsn(ILOAD, 3);
methodVisitor.visitVarInsn(ALOAD, 0);
methodVisitor.visitFieldInsn(GETFIELD, "com/fasterxml/jackson/core/util/ByteArrayBuilder", "_currBlockPtr", "I");
methodVisitor.visitMethodInsn(INVOKESTATIC, "java/lang/System", "arraycopy", "(Ljava/lang/Object;ILjava/lang/Object;II)V", false);
methodVisitor.visitVarInsn(ILOAD, 3);
methodVisitor.visitVarInsn(ALOAD, 0);
methodVisitor.visitFieldInsn(GETFIELD, "com/fasterxml/jackson/core/util/ByteArrayBuilder", "_currBlockPtr", "I");
methodVisitor.visitInsn(IADD);
methodVisitor.visitVarInsn(ISTORE, 3);
methodVisitor.visitVarInsn(ILOAD, 3);
methodVisitor.visitVarInsn(ILOAD, 1);
Label label3 = new Label();
methodVisitor.visitJumpInsn(IF_ICMPEQ, label3);
methodVisitor.visitTypeInsn(NEW, "java/lang/RuntimeException");
methodVisitor.visitInsn(DUP);
methodVisitor.visitTypeInsn(NEW, "java/lang/StringBuilder");
methodVisitor.visitInsn(DUP);
methodVisitor.visitMethodInsn(INVOKESPECIAL, "java/lang/StringBuilder", "<init>", "()V", false);
methodVisitor.visitLdcInsn("Internal error: total len assumed to be ");
methodVisitor.visitMethodInsn(INVOKEVIRTUAL, "java/lang/StringBuilder", "append", "(Ljava/lang/String;)Ljava/lang/StringBuilder;", false);
methodVisitor.visitVarInsn(ILOAD, 1);
methodVisitor.visitMethodInsn(INVOKEVIRTUAL, "java/lang/StringBuilder", "append", "(I)Ljava/lang/StringBuilder;", false);
methodVisitor.visitLdcInsn(", copied ");
methodVisitor.visitMethodInsn(INVOKEVIRTUAL, "java/lang/StringBuilder", "append", "(Ljava/lang/String;)Ljava/lang/StringBuilder;", false);
methodVisitor.visitVarInsn(ILOAD, 3);
methodVisitor.visitMethodInsn(INVOKEVIRTUAL, "java/lang/StringBuilder", "append", "(I)Ljava/lang/StringBuilder;", false);
methodVisitor.visitLdcInsn(" bytes");
methodVisitor.visitMethodInsn(INVOKEVIRTUAL, "java/lang/StringBuilder", "append", "(Ljava/lang/String;)Ljava/lang/StringBuilder;", false);
methodVisitor.visitMethodInsn(INVOKEVIRTUAL, "java/lang/StringBuilder", "toString", "()Ljava/lang/String;", false);
methodVisitor.visitMethodInsn(INVOKESPECIAL, "java/lang/RuntimeException", "<init>", "(Ljava/lang/String;)V", false);
methodVisitor.visitInsn(ATHROW);
methodVisitor.visitLabel(label3);
methodVisitor.visitFrame(Opcodes.F_SAME, 0, null, 0, null);
methodVisitor.visitVarInsn(ALOAD, 0);
methodVisitor.visitFieldInsn(GETFIELD, "com/fasterxml/jackson/core/util/ByteArrayBuilder", "_pastBlocks", "Ljava/util/LinkedList;");
methodVisitor.visitMethodInsn(INVOKEVIRTUAL, "java/util/LinkedList", "isEmpty", "()Z", false);
Label label4 = new Label();
methodVisitor.visitJumpInsn(IFNE, label4);
methodVisitor.visitVarInsn(ALOAD, 0);
methodVisitor.visitMethodInsn(INVOKEVIRTUAL, "com/fasterxml/jackson/core/util/ByteArrayBuilder", "reset", "()V", false);
methodVisitor.visitLabel(label4);
methodVisitor.visitFrame(Opcodes.F_SAME, 0, null, 0, null);
methodVisitor.visitVarInsn(ALOAD, 2);
methodVisitor.visitInsn(ARETURN);
methodVisitor.visitMaxs(5, 7);
methodVisitor.visitEnd();
}
{
methodVisitor = classWriter.visitMethod(ACC_PUBLIC, "resetAndGetFirstSegment", "()[B", null, null);
methodVisitor.visitCode();
methodVisitor.visitVarInsn(ALOAD, 0);
methodVisitor.visitMethodInsn(INVOKEVIRTUAL, "com/fasterxml/jackson/core/util/ByteArrayBuilder", "reset", "()V", false);
methodVisitor.visitVarInsn(ALOAD, 0);
methodVisitor.visitFieldInsn(GETFIELD, "com/fasterxml/jackson/core/util/ByteArrayBuilder", "_currBlock", "[B");
methodVisitor.visitInsn(ARETURN);
methodVisitor.visitMaxs(1, 1);
methodVisitor.visitEnd();
}
{
methodVisitor = classWriter.visitMethod(ACC_PUBLIC, "finishCurrentSegment", "()[B", null, null);
methodVisitor.visitCode();
methodVisitor.visitVarInsn(ALOAD, 0);
methodVisitor.visitMethodInsn(INVOKESPECIAL, "com/fasterxml/jackson/core/util/ByteArrayBuilder", "_allocMore", "()V", false);
methodVisitor.visitVarInsn(ALOAD, 0);
methodVisitor.visitFieldInsn(GETFIELD, "com/fasterxml/jackson/core/util/ByteArrayBuilder", "_currBlock", "[B");
methodVisitor.visitInsn(ARETURN);
methodVisitor.visitMaxs(1, 1);
methodVisitor.visitEnd();
}
{
methodVisitor = classWriter.visitMethod(ACC_PUBLIC, "completeAndCoalesce", "(I)[B", null, null);
methodVisitor.visitCode();
methodVisitor.visitVarInsn(ALOAD, 0);
methodVisitor.visitVarInsn(ILOAD, 1);
methodVisitor.visitFieldInsn(PUTFIELD, "com/fasterxml/jackson/core/util/ByteArrayBuilder", "_currBlockPtr", "I");
methodVisitor.visitVarInsn(ALOAD, 0);
methodVisitor.visitMethodInsn(INVOKEVIRTUAL, "com/fasterxml/jackson/core/util/ByteArrayBuilder", "toByteArray", "()[B", false);
methodVisitor.visitInsn(ARETURN);
methodVisitor.visitMaxs(2, 2);
methodVisitor.visitEnd();
}
{
methodVisitor = classWriter.visitMethod(ACC_PUBLIC, "getCurrentSegment", "()[B", null, null);
methodVisitor.visitCode();
methodVisitor.visitVarInsn(ALOAD, 0);
methodVisitor.visitFieldInsn(GETFIELD, "com/fasterxml/jackson/core/util/ByteArrayBuilder", "_currBlock", "[B");
methodVisitor.visitInsn(ARETURN);
methodVisitor.visitMaxs(1, 1);
methodVisitor.visitEnd();
}
{
methodVisitor = classWriter.visitMethod(ACC_PUBLIC, "setCurrentSegmentLength", "(I)V", null, null);
methodVisitor.visitCode();
methodVisitor.visitVarInsn(ALOAD, 0);
methodVisitor.visitVarInsn(ILOAD, 1);
methodVisitor.visitFieldInsn(PUTFIELD, "com/fasterxml/jackson/core/util/ByteArrayBuilder", "_currBlockPtr", "I");
methodVisitor.visitInsn(RETURN);
methodVisitor.visitMaxs(2, 2);
methodVisitor.visitEnd();
}
{
methodVisitor = classWriter.visitMethod(ACC_PUBLIC, "getCurrentSegmentLength", "()I", null, null);
methodVisitor.visitCode();
methodVisitor.visitVarInsn(ALOAD, 0);
methodVisitor.visitFieldInsn(GETFIELD, "com/fasterxml/jackson/core/util/ByteArrayBuilder", "_currBlockPtr", "I");
methodVisitor.visitInsn(IRETURN);
methodVisitor.visitMaxs(1, 1);
methodVisitor.visitEnd();
}
{
methodVisitor = classWriter.visitMethod(ACC_PUBLIC, "write", "([B)V", null, null);
methodVisitor.visitCode();
methodVisitor.visitVarInsn(ALOAD, 0);
methodVisitor.visitVarInsn(ALOAD, 1);
methodVisitor.visitInsn(ICONST_0);
methodVisitor.visitVarInsn(ALOAD, 1);
methodVisitor.visitInsn(ARRAYLENGTH);
methodVisitor.visitMethodInsn(INVOKEVIRTUAL, "com/fasterxml/jackson/core/util/ByteArrayBuilder", "write", "([BII)V", false);
methodVisitor.visitInsn(RETURN);
methodVisitor.visitMaxs(4, 2);
methodVisitor.visitEnd();
}
{
methodVisitor = classWriter.visitMethod(ACC_PUBLIC, "write", "([BII)V", null, null);
methodVisitor.visitCode();
Label label0 = new Label();
methodVisitor.visitLabel(label0);
methodVisitor.visitFrame(Opcodes.F_SAME, 0, null, 0, null);
methodVisitor.visitVarInsn(ALOAD, 0);
methodVisitor.visitFieldInsn(GETFIELD, "com/fasterxml/jackson/core/util/ByteArrayBuilder", "_currBlock", "[B");
methodVisitor.visitInsn(ARRAYLENGTH);
methodVisitor.visitVarInsn(ALOAD, 0);
methodVisitor.visitFieldInsn(GETFIELD, "com/fasterxml/jackson/core/util/ByteArrayBuilder", "_currBlockPtr", "I");
methodVisitor.visitInsn(ISUB);
methodVisitor.visitVarInsn(ISTORE, 4);
methodVisitor.visitVarInsn(ILOAD, 4);
methodVisitor.visitVarInsn(ILOAD, 3);
methodVisitor.visitMethodInsn(INVOKESTATIC, "java/lang/Math", "min", "(II)I", false);
methodVisitor.visitVarInsn(ISTORE, 5);
methodVisitor.visitVarInsn(ILOAD, 5);
Label label1 = new Label();
methodVisitor.visitJumpInsn(IFLE, label1);
methodVisitor.visitVarInsn(ALOAD, 1);
methodVisitor.visitVarInsn(ILOAD, 2);
methodVisitor.visitVarInsn(ALOAD, 0);
methodVisitor.visitFieldInsn(GETFIELD, "com/fasterxml/jackson/core/util/ByteArrayBuilder", "_currBlock", "[B");
methodVisitor.visitVarInsn(ALOAD, 0);
methodVisitor.visitFieldInsn(GETFIELD, "com/fasterxml/jackson/core/util/ByteArrayBuilder", "_currBlockPtr", "I");
methodVisitor.visitVarInsn(ILOAD, 5);
methodVisitor.visitMethodInsn(INVOKESTATIC, "java/lang/System", "arraycopy", "(Ljava/lang/Object;ILjava/lang/Object;II)V", false);
methodVisitor.visitVarInsn(ILOAD, 2);
methodVisitor.visitVarInsn(ILOAD, 5);
methodVisitor.visitInsn(IADD);
methodVisitor.visitVarInsn(ISTORE, 2);
methodVisitor.visitVarInsn(ALOAD, 0);
methodVisitor.visitInsn(DUP);
methodVisitor.visitFieldInsn(GETFIELD, "com/fasterxml/jackson/core/util/ByteArrayBuilder", "_currBlockPtr", "I");
methodVisitor.visitVarInsn(ILOAD, 5);
methodVisitor.visitInsn(IADD);
methodVisitor.visitFieldInsn(PUTFIELD, "com/fasterxml/jackson/core/util/ByteArrayBuilder", "_currBlockPtr", "I");
methodVisitor.visitVarInsn(ILOAD, 3);
methodVisitor.visitVarInsn(ILOAD, 5);
methodVisitor.visitInsn(ISUB);
methodVisitor.visitVarInsn(ISTORE, 3);
methodVisitor.visitLabel(label1);
methodVisitor.visitFrame(Opcodes.F_APPEND,2, new Object[] {Opcodes.INTEGER, Opcodes.INTEGER}, 0, null);
methodVisitor.visitVarInsn(ILOAD, 3);
Label label2 = new Label();
methodVisitor.visitJumpInsn(IFGT, label2);
Label label3 = new Label();
methodVisitor.visitJumpInsn(GOTO, label3);
methodVisitor.visitLabel(label2);
methodVisitor.visitFrame(Opcodes.F_SAME, 0, null, 0, null);
methodVisitor.visitVarInsn(ALOAD, 0);
methodVisitor.visitMethodInsn(INVOKESPECIAL, "com/fasterxml/jackson/core/util/ByteArrayBuilder", "_allocMore", "()V", false);
methodVisitor.visitJumpInsn(GOTO, label0);
methodVisitor.visitLabel(label3);
methodVisitor.visitFrame(Opcodes.F_CHOP,2, null, 0, null);
methodVisitor.visitInsn(RETURN);
methodVisitor.visitMaxs(5, 6);
methodVisitor.visitEnd();
}
{
methodVisitor = classWriter.visitMethod(ACC_PUBLIC, "write", "(I)V", null, null);
methodVisitor.visitCode();
methodVisitor.visitVarInsn(ALOAD, 0);
methodVisitor.visitVarInsn(ILOAD, 1);
methodVisitor.visitMethodInsn(INVOKEVIRTUAL, "com/fasterxml/jackson/core/util/ByteArrayBuilder", "append", "(I)V", false);
methodVisitor.visitInsn(RETURN);
methodVisitor.visitMaxs(2, 2);
methodVisitor.visitEnd();
}
{
methodVisitor = classWriter.visitMethod(ACC_PUBLIC, "close", "()V", null, null);
methodVisitor.visitCode();
methodVisitor.visitInsn(RETURN);
methodVisitor.visitMaxs(0, 1);
methodVisitor.visitEnd();
}
{
methodVisitor = classWriter.visitMethod(ACC_PUBLIC, "flush", "()V", null, null);
methodVisitor.visitCode();
methodVisitor.visitInsn(RETURN);
methodVisitor.visitMaxs(0, 1);
methodVisitor.visitEnd();
}
{
methodVisitor = classWriter.visitMethod(ACC_PRIVATE, "_allocMore", "()V", null, null);
methodVisitor.visitCode();
methodVisitor.visitVarInsn(ALOAD, 0);
methodVisitor.visitFieldInsn(GETFIELD, "com/fasterxml/jackson/core/util/ByteArrayBuilder", "_pastLen", "I");
methodVisitor.visitVarInsn(ALOAD, 0);
methodVisitor.visitFieldInsn(GETFIELD, "com/fasterxml/jackson/core/util/ByteArrayBuilder", "_currBlock", "[B");
methodVisitor.visitInsn(ARRAYLENGTH);
methodVisitor.visitInsn(IADD);
methodVisitor.visitVarInsn(ISTORE, 1);
methodVisitor.visitVarInsn(ILOAD, 1);
Label label0 = new Label();
methodVisitor.visitJumpInsn(IFGE, label0);
methodVisitor.visitTypeInsn(NEW, "java/lang/IllegalStateException");
methodVisitor.visitInsn(DUP);
methodVisitor.visitLdcInsn("Maximum Java array size (2GB) exceeded by `ByteArrayBuilder`");
methodVisitor.visitMethodInsn(INVOKESPECIAL, "java/lang/IllegalStateException", "<init>", "(Ljava/lang/String;)V", false);
methodVisitor.visitInsn(ATHROW);
methodVisitor.visitLabel(label0);
methodVisitor.visitFrame(Opcodes.F_APPEND,1, new Object[] {Opcodes.INTEGER}, 0, null);
methodVisitor.visitVarInsn(ALOAD, 0);
methodVisitor.visitVarInsn(ILOAD, 1);
methodVisitor.visitFieldInsn(PUTFIELD, "com/fasterxml/jackson/core/util/ByteArrayBuilder", "_pastLen", "I");
methodVisitor.visitVarInsn(ALOAD, 0);
methodVisitor.visitFieldInsn(GETFIELD, "com/fasterxml/jackson/core/util/ByteArrayBuilder", "_pastLen", "I");
methodVisitor.visitInsn(ICONST_1);
methodVisitor.visitInsn(ISHR);
methodVisitor.visitIntInsn(SIPUSH, 1000);
methodVisitor.visitMethodInsn(INVOKESTATIC, "java/lang/Math", "max", "(II)I", false);
methodVisitor.visitVarInsn(ISTORE, 2);
methodVisitor.visitVarInsn(ILOAD, 2);
methodVisitor.visitLdcInsn(new Integer(131072));
Label label1 = new Label();
methodVisitor.visitJumpInsn(IF_ICMPLE, label1);
methodVisitor.visitLdcInsn(new Integer(131072));
methodVisitor.visitVarInsn(ISTORE, 2);
methodVisitor.visitLabel(label1);
methodVisitor.visitFrame(Opcodes.F_APPEND,1, new Object[] {Opcodes.INTEGER}, 0, null);
methodVisitor.visitVarInsn(ALOAD, 0);
methodVisitor.visitFieldInsn(GETFIELD, "com/fasterxml/jackson/core/util/ByteArrayBuilder", "_pastBlocks", "Ljava/util/LinkedList;");
methodVisitor.visitVarInsn(ALOAD, 0);
methodVisitor.visitFieldInsn(GETFIELD, "com/fasterxml/jackson/core/util/ByteArrayBuilder", "_currBlock", "[B");
methodVisitor.visitMethodInsn(INVOKEVIRTUAL, "java/util/LinkedList", "add", "(Ljava/lang/Object;)Z", false);
methodVisitor.visitInsn(POP);
methodVisitor.visitVarInsn(ALOAD, 0);
methodVisitor.visitVarInsn(ILOAD, 2);
methodVisitor.visitIntInsn(NEWARRAY, T_BYTE);
methodVisitor.visitFieldInsn(PUTFIELD, "com/fasterxml/jackson/core/util/ByteArrayBuilder", "_currBlock", "[B");
methodVisitor.visitVarInsn(ALOAD, 0);
methodVisitor.visitInsn(ICONST_0);
methodVisitor.visitFieldInsn(PUTFIELD, "com/fasterxml/jackson/core/util/ByteArrayBuilder", "_currBlockPtr", "I");
methodVisitor.visitInsn(RETURN);
methodVisitor.visitMaxs(3, 3);
methodVisitor.visitEnd();
}
{
methodVisitor = classWriter.visitMethod(ACC_STATIC, "<clinit>", "()V", null, null);
methodVisitor.visitCode();
methodVisitor.visitInsn(ICONST_0);
methodVisitor.visitIntInsn(NEWARRAY, T_BYTE);
methodVisitor.visitFieldInsn(PUTSTATIC, "com/fasterxml/jackson/core/util/ByteArrayBuilder", "NO_BYTES", "[B");
methodVisitor.visitInsn(RETURN);
methodVisitor.visitMaxs(1, 0);
methodVisitor.visitEnd();
}
classWriter.visitEnd();

return classWriter.toByteArray();
}
}
