package asm.org.metatype.sxc.util;
import org.objectweb.asm.AnnotationVisitor;
import org.objectweb.asm.Attribute;
import org.objectweb.asm.ClassReader;
import org.objectweb.asm.ClassWriter;
import org.objectweb.asm.ConstantDynamic;
import org.objectweb.asm.FieldVisitor;
import org.objectweb.asm.Handle;
import org.objectweb.asm.Label;
import org.objectweb.asm.MethodVisitor;
import org.objectweb.asm.Opcodes;
import org.objectweb.asm.RecordComponentVisitor;
import org.objectweb.asm.Type;
import org.objectweb.asm.TypePath;
public class Base64Dump implements Opcodes {

public static byte[] dump () throws Exception {

ClassWriter classWriter = new ClassWriter(0);
FieldVisitor fieldVisitor;
RecordComponentVisitor recordComponentVisitor;
MethodVisitor methodVisitor;
AnnotationVisitor annotationVisitor0;

classWriter.visit(V1_5, ACC_PUBLIC | ACC_SUPER, "org/metatype/sxc/util/Base64", null, "java/lang/Object", null);

{
fieldVisitor = classWriter.visitField(ACC_PRIVATE | ACC_FINAL | ACC_STATIC, "S_BASE64CHAR", "[C", null, null);
fieldVisitor.visitEnd();
}
{
fieldVisitor = classWriter.visitField(ACC_PRIVATE | ACC_FINAL | ACC_STATIC, "S_BASE64PAD", "C", null, new Integer(61));
fieldVisitor.visitEnd();
}
{
fieldVisitor = classWriter.visitField(ACC_PRIVATE | ACC_FINAL | ACC_STATIC, "S_DECODETABLE", "[B", null, null);
fieldVisitor.visitEnd();
}
{
methodVisitor = classWriter.visitMethod(ACC_PUBLIC, "<init>", "()V", null, null);
methodVisitor.visitCode();
methodVisitor.visitVarInsn(ALOAD, 0);
methodVisitor.visitMethodInsn(INVOKESPECIAL, "java/lang/Object", "<init>", "()V", false);
methodVisitor.visitInsn(RETURN);
methodVisitor.visitMaxs(1, 1);
methodVisitor.visitEnd();
}
{
methodVisitor = classWriter.visitMethod(ACC_PRIVATE | ACC_STATIC, "decode0", "([C[BI)I", null, null);
methodVisitor.visitCode();
methodVisitor.visitInsn(ICONST_3);
methodVisitor.visitVarInsn(ISTORE, 3);
methodVisitor.visitVarInsn(ALOAD, 0);
methodVisitor.visitInsn(ICONST_3);
methodVisitor.visitInsn(CALOAD);
methodVisitor.visitIntInsn(BIPUSH, 61);
Label label0 = new Label();
methodVisitor.visitJumpInsn(IF_ICMPNE, label0);
methodVisitor.visitInsn(ICONST_2);
methodVisitor.visitVarInsn(ISTORE, 3);
methodVisitor.visitLabel(label0);
methodVisitor.visitVarInsn(ALOAD, 0);
methodVisitor.visitInsn(ICONST_2);
methodVisitor.visitInsn(CALOAD);
methodVisitor.visitIntInsn(BIPUSH, 61);
Label label1 = new Label();
methodVisitor.visitJumpInsn(IF_ICMPNE, label1);
methodVisitor.visitInsn(ICONST_1);
methodVisitor.visitVarInsn(ISTORE, 3);
methodVisitor.visitLabel(label1);
methodVisitor.visitFieldInsn(GETSTATIC, "org/metatype/sxc/util/Base64", "S_DECODETABLE", "[B");
methodVisitor.visitVarInsn(ALOAD, 0);
methodVisitor.visitInsn(ICONST_0);
methodVisitor.visitInsn(CALOAD);
methodVisitor.visitInsn(BALOAD);
methodVisitor.visitVarInsn(ISTORE, 4);
methodVisitor.visitFieldInsn(GETSTATIC, "org/metatype/sxc/util/Base64", "S_DECODETABLE", "[B");
methodVisitor.visitVarInsn(ALOAD, 0);
methodVisitor.visitInsn(ICONST_1);
methodVisitor.visitInsn(CALOAD);
methodVisitor.visitInsn(BALOAD);
methodVisitor.visitVarInsn(ISTORE, 5);
methodVisitor.visitFieldInsn(GETSTATIC, "org/metatype/sxc/util/Base64", "S_DECODETABLE", "[B");
methodVisitor.visitVarInsn(ALOAD, 0);
methodVisitor.visitInsn(ICONST_2);
methodVisitor.visitInsn(CALOAD);
methodVisitor.visitInsn(BALOAD);
methodVisitor.visitVarInsn(ISTORE, 6);
methodVisitor.visitFieldInsn(GETSTATIC, "org/metatype/sxc/util/Base64", "S_DECODETABLE", "[B");
methodVisitor.visitVarInsn(ALOAD, 0);
methodVisitor.visitInsn(ICONST_3);
methodVisitor.visitInsn(CALOAD);
methodVisitor.visitInsn(BALOAD);
methodVisitor.visitVarInsn(ISTORE, 7);
methodVisitor.visitVarInsn(ILOAD, 3);
Label label2 = new Label();
Label label3 = new Label();
Label label4 = new Label();
Label label5 = new Label();
methodVisitor.visitTableSwitchInsn(1, 3, label5, new Label[] { label2, label3, label4 });
methodVisitor.visitLabel(label2);
methodVisitor.visitVarInsn(ALOAD, 1);
methodVisitor.visitVarInsn(ILOAD, 2);
methodVisitor.visitVarInsn(ILOAD, 4);
methodVisitor.visitInsn(ICONST_2);
methodVisitor.visitInsn(ISHL);
methodVisitor.visitIntInsn(SIPUSH, 252);
methodVisitor.visitInsn(IAND);
methodVisitor.visitVarInsn(ILOAD, 5);
methodVisitor.visitInsn(ICONST_4);
methodVisitor.visitInsn(ISHR);
methodVisitor.visitInsn(ICONST_3);
methodVisitor.visitInsn(IAND);
methodVisitor.visitInsn(IOR);
methodVisitor.visitInsn(I2B);
methodVisitor.visitInsn(BASTORE);
methodVisitor.visitInsn(ICONST_1);
methodVisitor.visitInsn(IRETURN);
methodVisitor.visitLabel(label3);
methodVisitor.visitVarInsn(ALOAD, 1);
methodVisitor.visitVarInsn(ILOAD, 2);
methodVisitor.visitIincInsn(2, 1);
methodVisitor.visitVarInsn(ILOAD, 4);
methodVisitor.visitInsn(ICONST_2);
methodVisitor.visitInsn(ISHL);
methodVisitor.visitIntInsn(SIPUSH, 252);
methodVisitor.visitInsn(IAND);
methodVisitor.visitVarInsn(ILOAD, 5);
methodVisitor.visitInsn(ICONST_4);
methodVisitor.visitInsn(ISHR);
methodVisitor.visitInsn(ICONST_3);
methodVisitor.visitInsn(IAND);
methodVisitor.visitInsn(IOR);
methodVisitor.visitInsn(I2B);
methodVisitor.visitInsn(BASTORE);
methodVisitor.visitVarInsn(ALOAD, 1);
methodVisitor.visitVarInsn(ILOAD, 2);
methodVisitor.visitVarInsn(ILOAD, 5);
methodVisitor.visitInsn(ICONST_4);
methodVisitor.visitInsn(ISHL);
methodVisitor.visitIntInsn(SIPUSH, 240);
methodVisitor.visitInsn(IAND);
methodVisitor.visitVarInsn(ILOAD, 6);
methodVisitor.visitInsn(ICONST_2);
methodVisitor.visitInsn(ISHR);
methodVisitor.visitIntInsn(BIPUSH, 15);
methodVisitor.visitInsn(IAND);
methodVisitor.visitInsn(IOR);
methodVisitor.visitInsn(I2B);
methodVisitor.visitInsn(BASTORE);
methodVisitor.visitInsn(ICONST_2);
methodVisitor.visitInsn(IRETURN);
methodVisitor.visitLabel(label4);
methodVisitor.visitVarInsn(ALOAD, 1);
methodVisitor.visitVarInsn(ILOAD, 2);
methodVisitor.visitIincInsn(2, 1);
methodVisitor.visitVarInsn(ILOAD, 4);
methodVisitor.visitInsn(ICONST_2);
methodVisitor.visitInsn(ISHL);
methodVisitor.visitIntInsn(SIPUSH, 252);
methodVisitor.visitInsn(IAND);
methodVisitor.visitVarInsn(ILOAD, 5);
methodVisitor.visitInsn(ICONST_4);
methodVisitor.visitInsn(ISHR);
methodVisitor.visitInsn(ICONST_3);
methodVisitor.visitInsn(IAND);
methodVisitor.visitInsn(IOR);
methodVisitor.visitInsn(I2B);
methodVisitor.visitInsn(BASTORE);
methodVisitor.visitVarInsn(ALOAD, 1);
methodVisitor.visitVarInsn(ILOAD, 2);
methodVisitor.visitIincInsn(2, 1);
methodVisitor.visitVarInsn(ILOAD, 5);
methodVisitor.visitInsn(ICONST_4);
methodVisitor.visitInsn(ISHL);
methodVisitor.visitIntInsn(SIPUSH, 240);
methodVisitor.visitInsn(IAND);
methodVisitor.visitVarInsn(ILOAD, 6);
methodVisitor.visitInsn(ICONST_2);
methodVisitor.visitInsn(ISHR);
methodVisitor.visitIntInsn(BIPUSH, 15);
methodVisitor.visitInsn(IAND);
methodVisitor.visitInsn(IOR);
methodVisitor.visitInsn(I2B);
methodVisitor.visitInsn(BASTORE);
methodVisitor.visitVarInsn(ALOAD, 1);
methodVisitor.visitVarInsn(ILOAD, 2);
methodVisitor.visitVarInsn(ILOAD, 6);
methodVisitor.visitIntInsn(BIPUSH, 6);
methodVisitor.visitInsn(ISHL);
methodVisitor.visitIntInsn(SIPUSH, 192);
methodVisitor.visitInsn(IAND);
methodVisitor.visitVarInsn(ILOAD, 7);
methodVisitor.visitIntInsn(BIPUSH, 63);
methodVisitor.visitInsn(IAND);
methodVisitor.visitInsn(IOR);
methodVisitor.visitInsn(I2B);
methodVisitor.visitInsn(BASTORE);
methodVisitor.visitInsn(ICONST_3);
methodVisitor.visitInsn(IRETURN);
methodVisitor.visitLabel(label5);
methodVisitor.visitTypeInsn(NEW, "java/lang/RuntimeException");
methodVisitor.visitInsn(DUP);
methodVisitor.visitLdcInsn("Couldn't decode.");
methodVisitor.visitMethodInsn(INVOKESPECIAL, "java/lang/RuntimeException", "<init>", "(Ljava/lang/String;)V", false);
methodVisitor.visitInsn(ATHROW);
methodVisitor.visitMaxs(5, 8);
methodVisitor.visitEnd();
}
{
methodVisitor = classWriter.visitMethod(ACC_PUBLIC | ACC_STATIC, "decode", "([CII)[B", null, null);
methodVisitor.visitCode();
methodVisitor.visitInsn(ICONST_4);
methodVisitor.visitIntInsn(NEWARRAY, T_CHAR);
methodVisitor.visitVarInsn(ASTORE, 3);
methodVisitor.visitInsn(ICONST_0);
methodVisitor.visitVarInsn(ISTORE, 4);
methodVisitor.visitVarInsn(ILOAD, 2);
methodVisitor.visitInsn(ICONST_4);
methodVisitor.visitInsn(IDIV);
methodVisitor.visitInsn(ICONST_3);
methodVisitor.visitInsn(IMUL);
methodVisitor.visitInsn(ICONST_3);
methodVisitor.visitInsn(IADD);
methodVisitor.visitIntInsn(NEWARRAY, T_BYTE);
methodVisitor.visitVarInsn(ASTORE, 5);
methodVisitor.visitInsn(ICONST_0);
methodVisitor.visitVarInsn(ISTORE, 6);
methodVisitor.visitVarInsn(ILOAD, 1);
methodVisitor.visitVarInsn(ISTORE, 7);
Label label0 = new Label();
methodVisitor.visitLabel(label0);
methodVisitor.visitVarInsn(ILOAD, 7);
methodVisitor.visitVarInsn(ILOAD, 1);
methodVisitor.visitVarInsn(ILOAD, 2);
methodVisitor.visitInsn(IADD);
Label label1 = new Label();
methodVisitor.visitJumpInsn(IF_ICMPGE, label1);
methodVisitor.visitVarInsn(ALOAD, 0);
methodVisitor.visitVarInsn(ILOAD, 7);
methodVisitor.visitInsn(CALOAD);
methodVisitor.visitVarInsn(ISTORE, 8);
methodVisitor.visitVarInsn(ILOAD, 8);
methodVisitor.visitIntInsn(BIPUSH, 61);
Label label2 = new Label();
methodVisitor.visitJumpInsn(IF_ICMPEQ, label2);
methodVisitor.visitVarInsn(ILOAD, 8);
methodVisitor.visitFieldInsn(GETSTATIC, "org/metatype/sxc/util/Base64", "S_DECODETABLE", "[B");
methodVisitor.visitInsn(ARRAYLENGTH);
Label label3 = new Label();
methodVisitor.visitJumpInsn(IF_ICMPGE, label3);
methodVisitor.visitFieldInsn(GETSTATIC, "org/metatype/sxc/util/Base64", "S_DECODETABLE", "[B");
methodVisitor.visitVarInsn(ILOAD, 8);
methodVisitor.visitInsn(BALOAD);
methodVisitor.visitIntInsn(BIPUSH, 127);
methodVisitor.visitJumpInsn(IF_ICMPEQ, label3);
methodVisitor.visitLabel(label2);
methodVisitor.visitVarInsn(ALOAD, 3);
methodVisitor.visitVarInsn(ILOAD, 4);
methodVisitor.visitIincInsn(4, 1);
methodVisitor.visitVarInsn(ILOAD, 8);
methodVisitor.visitInsn(CASTORE);
methodVisitor.visitVarInsn(ILOAD, 4);
methodVisitor.visitVarInsn(ALOAD, 3);
methodVisitor.visitInsn(ARRAYLENGTH);
methodVisitor.visitJumpInsn(IF_ICMPNE, label3);
methodVisitor.visitInsn(ICONST_0);
methodVisitor.visitVarInsn(ISTORE, 4);
methodVisitor.visitVarInsn(ILOAD, 6);
methodVisitor.visitVarInsn(ALOAD, 3);
methodVisitor.visitVarInsn(ALOAD, 5);
methodVisitor.visitVarInsn(ILOAD, 6);
methodVisitor.visitMethodInsn(INVOKESTATIC, "org/metatype/sxc/util/Base64", "decode0", "([C[BI)I", false);
methodVisitor.visitInsn(IADD);
methodVisitor.visitVarInsn(ISTORE, 6);
methodVisitor.visitLabel(label3);
methodVisitor.visitIincInsn(7, 1);
methodVisitor.visitJumpInsn(GOTO, label0);
methodVisitor.visitLabel(label1);
methodVisitor.visitVarInsn(ILOAD, 6);
methodVisitor.visitVarInsn(ALOAD, 5);
methodVisitor.visitInsn(ARRAYLENGTH);
Label label4 = new Label();
methodVisitor.visitJumpInsn(IF_ICMPNE, label4);
methodVisitor.visitVarInsn(ALOAD, 5);
methodVisitor.visitInsn(ARETURN);
methodVisitor.visitLabel(label4);
methodVisitor.visitVarInsn(ILOAD, 6);
methodVisitor.visitIntInsn(NEWARRAY, T_BYTE);
methodVisitor.visitVarInsn(ASTORE, 7);
methodVisitor.visitVarInsn(ALOAD, 5);
methodVisitor.visitInsn(ICONST_0);
methodVisitor.visitVarInsn(ALOAD, 7);
methodVisitor.visitInsn(ICONST_0);
methodVisitor.visitVarInsn(ILOAD, 6);
methodVisitor.visitMethodInsn(INVOKESTATIC, "java/lang/System", "arraycopy", "(Ljava/lang/Object;ILjava/lang/Object;II)V", false);
methodVisitor.visitVarInsn(ALOAD, 7);
methodVisitor.visitInsn(ARETURN);
methodVisitor.visitMaxs(5, 9);
methodVisitor.visitEnd();
}
{
methodVisitor = classWriter.visitMethod(ACC_PUBLIC | ACC_STATIC, "decode", "(Ljava/lang/String;)[B", null, null);
methodVisitor.visitCode();
methodVisitor.visitInsn(ICONST_4);
methodVisitor.visitIntInsn(NEWARRAY, T_CHAR);
methodVisitor.visitVarInsn(ASTORE, 1);
methodVisitor.visitInsn(ICONST_0);
methodVisitor.visitVarInsn(ISTORE, 2);
methodVisitor.visitVarInsn(ALOAD, 0);
methodVisitor.visitMethodInsn(INVOKEVIRTUAL, "java/lang/String", "length", "()I", false);
methodVisitor.visitInsn(ICONST_4);
methodVisitor.visitInsn(IDIV);
methodVisitor.visitInsn(ICONST_3);
methodVisitor.visitInsn(IMUL);
methodVisitor.visitInsn(ICONST_3);
methodVisitor.visitInsn(IADD);
methodVisitor.visitIntInsn(NEWARRAY, T_BYTE);
methodVisitor.visitVarInsn(ASTORE, 3);
methodVisitor.visitInsn(ICONST_0);
methodVisitor.visitVarInsn(ISTORE, 4);
methodVisitor.visitInsn(ICONST_0);
methodVisitor.visitVarInsn(ISTORE, 5);
Label label0 = new Label();
methodVisitor.visitLabel(label0);
methodVisitor.visitVarInsn(ILOAD, 5);
methodVisitor.visitVarInsn(ALOAD, 0);
methodVisitor.visitMethodInsn(INVOKEVIRTUAL, "java/lang/String", "length", "()I", false);
Label label1 = new Label();
methodVisitor.visitJumpInsn(IF_ICMPGE, label1);
methodVisitor.visitVarInsn(ALOAD, 0);
methodVisitor.visitVarInsn(ILOAD, 5);
methodVisitor.visitMethodInsn(INVOKEVIRTUAL, "java/lang/String", "charAt", "(I)C", false);
methodVisitor.visitVarInsn(ISTORE, 6);
methodVisitor.visitVarInsn(ILOAD, 6);
methodVisitor.visitIntInsn(BIPUSH, 61);
Label label2 = new Label();
methodVisitor.visitJumpInsn(IF_ICMPEQ, label2);
methodVisitor.visitVarInsn(ILOAD, 6);
methodVisitor.visitFieldInsn(GETSTATIC, "org/metatype/sxc/util/Base64", "S_DECODETABLE", "[B");
methodVisitor.visitInsn(ARRAYLENGTH);
Label label3 = new Label();
methodVisitor.visitJumpInsn(IF_ICMPGE, label3);
methodVisitor.visitFieldInsn(GETSTATIC, "org/metatype/sxc/util/Base64", "S_DECODETABLE", "[B");
methodVisitor.visitVarInsn(ILOAD, 6);
methodVisitor.visitInsn(BALOAD);
methodVisitor.visitIntInsn(BIPUSH, 127);
methodVisitor.visitJumpInsn(IF_ICMPEQ, label3);
methodVisitor.visitLabel(label2);
methodVisitor.visitVarInsn(ALOAD, 1);
methodVisitor.visitVarInsn(ILOAD, 2);
methodVisitor.visitIincInsn(2, 1);
methodVisitor.visitVarInsn(ILOAD, 6);
methodVisitor.visitInsn(CASTORE);
methodVisitor.visitVarInsn(ILOAD, 2);
methodVisitor.visitVarInsn(ALOAD, 1);
methodVisitor.visitInsn(ARRAYLENGTH);
methodVisitor.visitJumpInsn(IF_ICMPNE, label3);
methodVisitor.visitInsn(ICONST_0);
methodVisitor.visitVarInsn(ISTORE, 2);
methodVisitor.visitVarInsn(ILOAD, 4);
methodVisitor.visitVarInsn(ALOAD, 1);
methodVisitor.visitVarInsn(ALOAD, 3);
methodVisitor.visitVarInsn(ILOAD, 4);
methodVisitor.visitMethodInsn(INVOKESTATIC, "org/metatype/sxc/util/Base64", "decode0", "([C[BI)I", false);
methodVisitor.visitInsn(IADD);
methodVisitor.visitVarInsn(ISTORE, 4);
methodVisitor.visitLabel(label3);
methodVisitor.visitIincInsn(5, 1);
methodVisitor.visitJumpInsn(GOTO, label0);
methodVisitor.visitLabel(label1);
methodVisitor.visitVarInsn(ILOAD, 4);
methodVisitor.visitVarInsn(ALOAD, 3);
methodVisitor.visitInsn(ARRAYLENGTH);
Label label4 = new Label();
methodVisitor.visitJumpInsn(IF_ICMPNE, label4);
methodVisitor.visitVarInsn(ALOAD, 3);
methodVisitor.visitInsn(ARETURN);
methodVisitor.visitLabel(label4);
methodVisitor.visitVarInsn(ILOAD, 4);
methodVisitor.visitIntInsn(NEWARRAY, T_BYTE);
methodVisitor.visitVarInsn(ASTORE, 5);
methodVisitor.visitVarInsn(ALOAD, 3);
methodVisitor.visitInsn(ICONST_0);
methodVisitor.visitVarInsn(ALOAD, 5);
methodVisitor.visitInsn(ICONST_0);
methodVisitor.visitVarInsn(ILOAD, 4);
methodVisitor.visitMethodInsn(INVOKESTATIC, "java/lang/System", "arraycopy", "(Ljava/lang/Object;ILjava/lang/Object;II)V", false);
methodVisitor.visitVarInsn(ALOAD, 5);
methodVisitor.visitInsn(ARETURN);
methodVisitor.visitMaxs(5, 7);
methodVisitor.visitEnd();
}
{
methodVisitor = classWriter.visitMethod(ACC_PUBLIC | ACC_STATIC, "decode", "([CIILjava/io/OutputStream;)V", null, new String[] { "java/io/IOException" });
methodVisitor.visitCode();
methodVisitor.visitInsn(ICONST_4);
methodVisitor.visitIntInsn(NEWARRAY, T_CHAR);
methodVisitor.visitVarInsn(ASTORE, 4);
methodVisitor.visitInsn(ICONST_0);
methodVisitor.visitVarInsn(ISTORE, 5);
methodVisitor.visitInsn(ICONST_3);
methodVisitor.visitIntInsn(NEWARRAY, T_BYTE);
methodVisitor.visitVarInsn(ASTORE, 6);
methodVisitor.visitVarInsn(ILOAD, 1);
methodVisitor.visitVarInsn(ISTORE, 7);
Label label0 = new Label();
methodVisitor.visitLabel(label0);
methodVisitor.visitVarInsn(ILOAD, 7);
methodVisitor.visitVarInsn(ILOAD, 1);
methodVisitor.visitVarInsn(ILOAD, 2);
methodVisitor.visitInsn(IADD);
Label label1 = new Label();
methodVisitor.visitJumpInsn(IF_ICMPGE, label1);
methodVisitor.visitVarInsn(ALOAD, 0);
methodVisitor.visitVarInsn(ILOAD, 7);
methodVisitor.visitInsn(CALOAD);
methodVisitor.visitVarInsn(ISTORE, 8);
methodVisitor.visitVarInsn(ILOAD, 8);
methodVisitor.visitIntInsn(BIPUSH, 61);
Label label2 = new Label();
methodVisitor.visitJumpInsn(IF_ICMPEQ, label2);
methodVisitor.visitVarInsn(ILOAD, 8);
methodVisitor.visitFieldInsn(GETSTATIC, "org/metatype/sxc/util/Base64", "S_DECODETABLE", "[B");
methodVisitor.visitInsn(ARRAYLENGTH);
Label label3 = new Label();
methodVisitor.visitJumpInsn(IF_ICMPGE, label3);
methodVisitor.visitFieldInsn(GETSTATIC, "org/metatype/sxc/util/Base64", "S_DECODETABLE", "[B");
methodVisitor.visitVarInsn(ILOAD, 8);
methodVisitor.visitInsn(BALOAD);
methodVisitor.visitIntInsn(BIPUSH, 127);
methodVisitor.visitJumpInsn(IF_ICMPEQ, label3);
methodVisitor.visitLabel(label2);
methodVisitor.visitVarInsn(ALOAD, 4);
methodVisitor.visitVarInsn(ILOAD, 5);
methodVisitor.visitIincInsn(5, 1);
methodVisitor.visitVarInsn(ILOAD, 8);
methodVisitor.visitInsn(CASTORE);
methodVisitor.visitVarInsn(ILOAD, 5);
methodVisitor.visitVarInsn(ALOAD, 4);
methodVisitor.visitInsn(ARRAYLENGTH);
methodVisitor.visitJumpInsn(IF_ICMPNE, label3);
methodVisitor.visitInsn(ICONST_0);
methodVisitor.visitVarInsn(ISTORE, 5);
methodVisitor.visitVarInsn(ALOAD, 4);
methodVisitor.visitVarInsn(ALOAD, 6);
methodVisitor.visitInsn(ICONST_0);
methodVisitor.visitMethodInsn(INVOKESTATIC, "org/metatype/sxc/util/Base64", "decode0", "([C[BI)I", false);
methodVisitor.visitVarInsn(ISTORE, 9);
methodVisitor.visitVarInsn(ALOAD, 3);
methodVisitor.visitVarInsn(ALOAD, 6);
methodVisitor.visitInsn(ICONST_0);
methodVisitor.visitVarInsn(ILOAD, 9);
methodVisitor.visitMethodInsn(INVOKEVIRTUAL, "java/io/OutputStream", "write", "([BII)V", false);
methodVisitor.visitLabel(label3);
methodVisitor.visitIincInsn(7, 1);
methodVisitor.visitJumpInsn(GOTO, label0);
methodVisitor.visitLabel(label1);
methodVisitor.visitInsn(RETURN);
methodVisitor.visitMaxs(4, 10);
methodVisitor.visitEnd();
}
{
methodVisitor = classWriter.visitMethod(ACC_PUBLIC | ACC_STATIC, "decode", "(Ljava/lang/String;Ljava/io/OutputStream;)V", null, new String[] { "java/io/IOException" });
methodVisitor.visitCode();
methodVisitor.visitInsn(ICONST_4);
methodVisitor.visitIntInsn(NEWARRAY, T_CHAR);
methodVisitor.visitVarInsn(ASTORE, 2);
methodVisitor.visitInsn(ICONST_0);
methodVisitor.visitVarInsn(ISTORE, 3);
methodVisitor.visitInsn(ICONST_3);
methodVisitor.visitIntInsn(NEWARRAY, T_BYTE);
methodVisitor.visitVarInsn(ASTORE, 4);
methodVisitor.visitInsn(ICONST_0);
methodVisitor.visitVarInsn(ISTORE, 5);
Label label0 = new Label();
methodVisitor.visitLabel(label0);
methodVisitor.visitVarInsn(ILOAD, 5);
methodVisitor.visitVarInsn(ALOAD, 0);
methodVisitor.visitMethodInsn(INVOKEVIRTUAL, "java/lang/String", "length", "()I", false);
Label label1 = new Label();
methodVisitor.visitJumpInsn(IF_ICMPGE, label1);
methodVisitor.visitVarInsn(ALOAD, 0);
methodVisitor.visitVarInsn(ILOAD, 5);
methodVisitor.visitMethodInsn(INVOKEVIRTUAL, "java/lang/String", "charAt", "(I)C", false);
methodVisitor.visitVarInsn(ISTORE, 6);
methodVisitor.visitVarInsn(ILOAD, 6);
methodVisitor.visitIntInsn(BIPUSH, 61);
Label label2 = new Label();
methodVisitor.visitJumpInsn(IF_ICMPEQ, label2);
methodVisitor.visitVarInsn(ILOAD, 6);
methodVisitor.visitFieldInsn(GETSTATIC, "org/metatype/sxc/util/Base64", "S_DECODETABLE", "[B");
methodVisitor.visitInsn(ARRAYLENGTH);
Label label3 = new Label();
methodVisitor.visitJumpInsn(IF_ICMPGE, label3);
methodVisitor.visitFieldInsn(GETSTATIC, "org/metatype/sxc/util/Base64", "S_DECODETABLE", "[B");
methodVisitor.visitVarInsn(ILOAD, 6);
methodVisitor.visitInsn(BALOAD);
methodVisitor.visitIntInsn(BIPUSH, 127);
methodVisitor.visitJumpInsn(IF_ICMPEQ, label3);
methodVisitor.visitLabel(label2);
methodVisitor.visitVarInsn(ALOAD, 2);
methodVisitor.visitVarInsn(ILOAD, 3);
methodVisitor.visitIincInsn(3, 1);
methodVisitor.visitVarInsn(ILOAD, 6);
methodVisitor.visitInsn(CASTORE);
methodVisitor.visitVarInsn(ILOAD, 3);
methodVisitor.visitVarInsn(ALOAD, 2);
methodVisitor.visitInsn(ARRAYLENGTH);
methodVisitor.visitJumpInsn(IF_ICMPNE, label3);
methodVisitor.visitInsn(ICONST_0);
methodVisitor.visitVarInsn(ISTORE, 3);
methodVisitor.visitVarInsn(ALOAD, 2);
methodVisitor.visitVarInsn(ALOAD, 4);
methodVisitor.visitInsn(ICONST_0);
methodVisitor.visitMethodInsn(INVOKESTATIC, "org/metatype/sxc/util/Base64", "decode0", "([C[BI)I", false);
methodVisitor.visitVarInsn(ISTORE, 7);
methodVisitor.visitVarInsn(ALOAD, 1);
methodVisitor.visitVarInsn(ALOAD, 4);
methodVisitor.visitInsn(ICONST_0);
methodVisitor.visitVarInsn(ILOAD, 7);
methodVisitor.visitMethodInsn(INVOKEVIRTUAL, "java/io/OutputStream", "write", "([BII)V", false);
methodVisitor.visitLabel(label3);
methodVisitor.visitIincInsn(5, 1);
methodVisitor.visitJumpInsn(GOTO, label0);
methodVisitor.visitLabel(label1);
methodVisitor.visitInsn(RETURN);
methodVisitor.visitMaxs(4, 8);
methodVisitor.visitEnd();
}
{
methodVisitor = classWriter.visitMethod(ACC_PUBLIC | ACC_STATIC, "encode", "([B)Ljava/lang/String;", null, null);
methodVisitor.visitCode();
methodVisitor.visitVarInsn(ALOAD, 0);
methodVisitor.visitInsn(ICONST_0);
methodVisitor.visitVarInsn(ALOAD, 0);
methodVisitor.visitInsn(ARRAYLENGTH);
methodVisitor.visitMethodInsn(INVOKESTATIC, "org/metatype/sxc/util/Base64", "encode", "([BII)Ljava/lang/String;", false);
methodVisitor.visitInsn(ARETURN);
methodVisitor.visitMaxs(3, 1);
methodVisitor.visitEnd();
}
{
methodVisitor = classWriter.visitMethod(ACC_PUBLIC | ACC_STATIC, "encode", "([BII)Ljava/lang/String;", null, null);
methodVisitor.visitCode();
methodVisitor.visitVarInsn(ILOAD, 2);
Label label0 = new Label();
methodVisitor.visitJumpInsn(IFGT, label0);
methodVisitor.visitLdcInsn("");
methodVisitor.visitInsn(ARETURN);
methodVisitor.visitLabel(label0);
methodVisitor.visitVarInsn(ILOAD, 2);
methodVisitor.visitInsn(ICONST_3);
methodVisitor.visitInsn(IDIV);
methodVisitor.visitInsn(ICONST_4);
methodVisitor.visitInsn(IMUL);
methodVisitor.visitInsn(ICONST_4);
methodVisitor.visitInsn(IADD);
methodVisitor.visitIntInsn(NEWARRAY, T_CHAR);
methodVisitor.visitVarInsn(ASTORE, 3);
methodVisitor.visitVarInsn(ILOAD, 1);
methodVisitor.visitVarInsn(ISTORE, 4);
methodVisitor.visitInsn(ICONST_0);
methodVisitor.visitVarInsn(ISTORE, 5);
methodVisitor.visitVarInsn(ILOAD, 2);
methodVisitor.visitVarInsn(ILOAD, 1);
methodVisitor.visitInsn(ISUB);
methodVisitor.visitVarInsn(ISTORE, 6);
Label label1 = new Label();
methodVisitor.visitLabel(label1);
methodVisitor.visitVarInsn(ILOAD, 6);
methodVisitor.visitInsn(ICONST_3);
Label label2 = new Label();
methodVisitor.visitJumpInsn(IF_ICMPLT, label2);
methodVisitor.visitVarInsn(ALOAD, 0);
methodVisitor.visitVarInsn(ILOAD, 4);
methodVisitor.visitInsn(BALOAD);
methodVisitor.visitIntInsn(SIPUSH, 255);
methodVisitor.visitInsn(IAND);
methodVisitor.visitIntInsn(BIPUSH, 16);
methodVisitor.visitInsn(ISHL);
methodVisitor.visitVarInsn(ALOAD, 0);
methodVisitor.visitVarInsn(ILOAD, 4);
methodVisitor.visitInsn(ICONST_1);
methodVisitor.visitInsn(IADD);
methodVisitor.visitInsn(BALOAD);
methodVisitor.visitIntInsn(SIPUSH, 255);
methodVisitor.visitInsn(IAND);
methodVisitor.visitIntInsn(BIPUSH, 8);
methodVisitor.visitInsn(ISHL);
methodVisitor.visitInsn(IADD);
methodVisitor.visitVarInsn(ALOAD, 0);
methodVisitor.visitVarInsn(ILOAD, 4);
methodVisitor.visitInsn(ICONST_2);
methodVisitor.visitInsn(IADD);
methodVisitor.visitInsn(BALOAD);
methodVisitor.visitIntInsn(SIPUSH, 255);
methodVisitor.visitInsn(IAND);
methodVisitor.visitInsn(IADD);
methodVisitor.visitVarInsn(ISTORE, 7);
methodVisitor.visitVarInsn(ALOAD, 3);
methodVisitor.visitVarInsn(ILOAD, 5);
methodVisitor.visitIincInsn(5, 1);
methodVisitor.visitFieldInsn(GETSTATIC, "org/metatype/sxc/util/Base64", "S_BASE64CHAR", "[C");
methodVisitor.visitVarInsn(ILOAD, 7);
methodVisitor.visitIntInsn(BIPUSH, 18);
methodVisitor.visitInsn(ISHR);
methodVisitor.visitInsn(CALOAD);
methodVisitor.visitInsn(CASTORE);
methodVisitor.visitVarInsn(ALOAD, 3);
methodVisitor.visitVarInsn(ILOAD, 5);
methodVisitor.visitIincInsn(5, 1);
methodVisitor.visitFieldInsn(GETSTATIC, "org/metatype/sxc/util/Base64", "S_BASE64CHAR", "[C");
methodVisitor.visitVarInsn(ILOAD, 7);
methodVisitor.visitIntInsn(BIPUSH, 12);
methodVisitor.visitInsn(ISHR);
methodVisitor.visitIntInsn(BIPUSH, 63);
methodVisitor.visitInsn(IAND);
methodVisitor.visitInsn(CALOAD);
methodVisitor.visitInsn(CASTORE);
methodVisitor.visitVarInsn(ALOAD, 3);
methodVisitor.visitVarInsn(ILOAD, 5);
methodVisitor.visitIincInsn(5, 1);
methodVisitor.visitFieldInsn(GETSTATIC, "org/metatype/sxc/util/Base64", "S_BASE64CHAR", "[C");
methodVisitor.visitVarInsn(ILOAD, 7);
methodVisitor.visitIntInsn(BIPUSH, 6);
methodVisitor.visitInsn(ISHR);
methodVisitor.visitIntInsn(BIPUSH, 63);
methodVisitor.visitInsn(IAND);
methodVisitor.visitInsn(CALOAD);
methodVisitor.visitInsn(CASTORE);
methodVisitor.visitVarInsn(ALOAD, 3);
methodVisitor.visitVarInsn(ILOAD, 5);
methodVisitor.visitIincInsn(5, 1);
methodVisitor.visitFieldInsn(GETSTATIC, "org/metatype/sxc/util/Base64", "S_BASE64CHAR", "[C");
methodVisitor.visitVarInsn(ILOAD, 7);
methodVisitor.visitIntInsn(BIPUSH, 63);
methodVisitor.visitInsn(IAND);
methodVisitor.visitInsn(CALOAD);
methodVisitor.visitInsn(CASTORE);
methodVisitor.visitIincInsn(4, 3);
methodVisitor.visitIincInsn(6, -3);
methodVisitor.visitJumpInsn(GOTO, label1);
methodVisitor.visitLabel(label2);
methodVisitor.visitVarInsn(ILOAD, 6);
methodVisitor.visitInsn(ICONST_1);
Label label3 = new Label();
methodVisitor.visitJumpInsn(IF_ICMPNE, label3);
methodVisitor.visitVarInsn(ALOAD, 0);
methodVisitor.visitVarInsn(ILOAD, 4);
methodVisitor.visitInsn(BALOAD);
methodVisitor.visitIntInsn(SIPUSH, 255);
methodVisitor.visitInsn(IAND);
methodVisitor.visitVarInsn(ISTORE, 7);
methodVisitor.visitVarInsn(ALOAD, 3);
methodVisitor.visitVarInsn(ILOAD, 5);
methodVisitor.visitIincInsn(5, 1);
methodVisitor.visitFieldInsn(GETSTATIC, "org/metatype/sxc/util/Base64", "S_BASE64CHAR", "[C");
methodVisitor.visitVarInsn(ILOAD, 7);
methodVisitor.visitInsn(ICONST_2);
methodVisitor.visitInsn(ISHR);
methodVisitor.visitInsn(CALOAD);
methodVisitor.visitInsn(CASTORE);
methodVisitor.visitVarInsn(ALOAD, 3);
methodVisitor.visitVarInsn(ILOAD, 5);
methodVisitor.visitIincInsn(5, 1);
methodVisitor.visitFieldInsn(GETSTATIC, "org/metatype/sxc/util/Base64", "S_BASE64CHAR", "[C");
methodVisitor.visitVarInsn(ILOAD, 7);
methodVisitor.visitInsn(ICONST_4);
methodVisitor.visitInsn(ISHL);
methodVisitor.visitIntInsn(BIPUSH, 63);
methodVisitor.visitInsn(IAND);
methodVisitor.visitInsn(CALOAD);
methodVisitor.visitInsn(CASTORE);
methodVisitor.visitVarInsn(ALOAD, 3);
methodVisitor.visitVarInsn(ILOAD, 5);
methodVisitor.visitIincInsn(5, 1);
methodVisitor.visitIntInsn(BIPUSH, 61);
methodVisitor.visitInsn(CASTORE);
methodVisitor.visitVarInsn(ALOAD, 3);
methodVisitor.visitVarInsn(ILOAD, 5);
methodVisitor.visitIincInsn(5, 1);
methodVisitor.visitIntInsn(BIPUSH, 61);
methodVisitor.visitInsn(CASTORE);
Label label4 = new Label();
methodVisitor.visitJumpInsn(GOTO, label4);
methodVisitor.visitLabel(label3);
methodVisitor.visitVarInsn(ILOAD, 6);
methodVisitor.visitInsn(ICONST_2);
methodVisitor.visitJumpInsn(IF_ICMPNE, label4);
methodVisitor.visitVarInsn(ALOAD, 0);
methodVisitor.visitVarInsn(ILOAD, 4);
methodVisitor.visitInsn(BALOAD);
methodVisitor.visitIntInsn(SIPUSH, 255);
methodVisitor.visitInsn(IAND);
methodVisitor.visitIntInsn(BIPUSH, 8);
methodVisitor.visitInsn(ISHL);
methodVisitor.visitVarInsn(ALOAD, 0);
methodVisitor.visitVarInsn(ILOAD, 4);
methodVisitor.visitInsn(ICONST_1);
methodVisitor.visitInsn(IADD);
methodVisitor.visitInsn(BALOAD);
methodVisitor.visitIntInsn(SIPUSH, 255);
methodVisitor.visitInsn(IAND);
methodVisitor.visitInsn(IADD);
methodVisitor.visitVarInsn(ISTORE, 7);
methodVisitor.visitVarInsn(ALOAD, 3);
methodVisitor.visitVarInsn(ILOAD, 5);
methodVisitor.visitIincInsn(5, 1);
methodVisitor.visitFieldInsn(GETSTATIC, "org/metatype/sxc/util/Base64", "S_BASE64CHAR", "[C");
methodVisitor.visitVarInsn(ILOAD, 7);
methodVisitor.visitIntInsn(BIPUSH, 10);
methodVisitor.visitInsn(ISHR);
methodVisitor.visitInsn(CALOAD);
methodVisitor.visitInsn(CASTORE);
methodVisitor.visitVarInsn(ALOAD, 3);
methodVisitor.visitVarInsn(ILOAD, 5);
methodVisitor.visitIincInsn(5, 1);
methodVisitor.visitFieldInsn(GETSTATIC, "org/metatype/sxc/util/Base64", "S_BASE64CHAR", "[C");
methodVisitor.visitVarInsn(ILOAD, 7);
methodVisitor.visitInsn(ICONST_4);
methodVisitor.visitInsn(ISHR);
methodVisitor.visitIntInsn(BIPUSH, 63);
methodVisitor.visitInsn(IAND);
methodVisitor.visitInsn(CALOAD);
methodVisitor.visitInsn(CASTORE);
methodVisitor.visitVarInsn(ALOAD, 3);
methodVisitor.visitVarInsn(ILOAD, 5);
methodVisitor.visitIincInsn(5, 1);
methodVisitor.visitFieldInsn(GETSTATIC, "org/metatype/sxc/util/Base64", "S_BASE64CHAR", "[C");
methodVisitor.visitVarInsn(ILOAD, 7);
methodVisitor.visitInsn(ICONST_2);
methodVisitor.visitInsn(ISHL);
methodVisitor.visitIntInsn(BIPUSH, 63);
methodVisitor.visitInsn(IAND);
methodVisitor.visitInsn(CALOAD);
methodVisitor.visitInsn(CASTORE);
methodVisitor.visitVarInsn(ALOAD, 3);
methodVisitor.visitVarInsn(ILOAD, 5);
methodVisitor.visitIincInsn(5, 1);
methodVisitor.visitIntInsn(BIPUSH, 61);
methodVisitor.visitInsn(CASTORE);
methodVisitor.visitLabel(label4);
methodVisitor.visitTypeInsn(NEW, "java/lang/String");
methodVisitor.visitInsn(DUP);
methodVisitor.visitVarInsn(ALOAD, 3);
methodVisitor.visitInsn(ICONST_0);
methodVisitor.visitVarInsn(ILOAD, 5);
methodVisitor.visitMethodInsn(INVOKESPECIAL, "java/lang/String", "<init>", "([CII)V", false);
methodVisitor.visitInsn(ARETURN);
methodVisitor.visitMaxs(5, 8);
methodVisitor.visitEnd();
}
{
methodVisitor = classWriter.visitMethod(ACC_PUBLIC | ACC_STATIC, "encode", "([BIILjava/io/OutputStream;)V", null, new String[] { "java/io/IOException" });
methodVisitor.visitCode();
methodVisitor.visitVarInsn(ILOAD, 2);
Label label0 = new Label();
methodVisitor.visitJumpInsn(IFGT, label0);
methodVisitor.visitInsn(RETURN);
methodVisitor.visitLabel(label0);
methodVisitor.visitInsn(ICONST_4);
methodVisitor.visitIntInsn(NEWARRAY, T_BYTE);
methodVisitor.visitVarInsn(ASTORE, 4);
methodVisitor.visitVarInsn(ILOAD, 1);
methodVisitor.visitVarInsn(ISTORE, 5);
methodVisitor.visitVarInsn(ILOAD, 2);
methodVisitor.visitVarInsn(ILOAD, 1);
methodVisitor.visitInsn(ISUB);
methodVisitor.visitVarInsn(ISTORE, 6);
Label label1 = new Label();
methodVisitor.visitLabel(label1);
methodVisitor.visitVarInsn(ILOAD, 6);
methodVisitor.visitInsn(ICONST_3);
Label label2 = new Label();
methodVisitor.visitJumpInsn(IF_ICMPLT, label2);
methodVisitor.visitVarInsn(ALOAD, 0);
methodVisitor.visitVarInsn(ILOAD, 5);
methodVisitor.visitInsn(BALOAD);
methodVisitor.visitIntInsn(SIPUSH, 255);
methodVisitor.visitInsn(IAND);
methodVisitor.visitIntInsn(BIPUSH, 16);
methodVisitor.visitInsn(ISHL);
methodVisitor.visitVarInsn(ALOAD, 0);
methodVisitor.visitVarInsn(ILOAD, 5);
methodVisitor.visitInsn(ICONST_1);
methodVisitor.visitInsn(IADD);
methodVisitor.visitInsn(BALOAD);
methodVisitor.visitIntInsn(SIPUSH, 255);
methodVisitor.visitInsn(IAND);
methodVisitor.visitIntInsn(BIPUSH, 8);
methodVisitor.visitInsn(ISHL);
methodVisitor.visitInsn(IADD);
methodVisitor.visitVarInsn(ALOAD, 0);
methodVisitor.visitVarInsn(ILOAD, 5);
methodVisitor.visitInsn(ICONST_2);
methodVisitor.visitInsn(IADD);
methodVisitor.visitInsn(BALOAD);
methodVisitor.visitIntInsn(SIPUSH, 255);
methodVisitor.visitInsn(IAND);
methodVisitor.visitInsn(IADD);
methodVisitor.visitVarInsn(ISTORE, 7);
methodVisitor.visitVarInsn(ALOAD, 4);
methodVisitor.visitInsn(ICONST_0);
methodVisitor.visitFieldInsn(GETSTATIC, "org/metatype/sxc/util/Base64", "S_BASE64CHAR", "[C");
methodVisitor.visitVarInsn(ILOAD, 7);
methodVisitor.visitIntInsn(BIPUSH, 18);
methodVisitor.visitInsn(ISHR);
methodVisitor.visitInsn(CALOAD);
methodVisitor.visitInsn(I2B);
methodVisitor.visitInsn(BASTORE);
methodVisitor.visitVarInsn(ALOAD, 4);
methodVisitor.visitInsn(ICONST_1);
methodVisitor.visitFieldInsn(GETSTATIC, "org/metatype/sxc/util/Base64", "S_BASE64CHAR", "[C");
methodVisitor.visitVarInsn(ILOAD, 7);
methodVisitor.visitIntInsn(BIPUSH, 12);
methodVisitor.visitInsn(ISHR);
methodVisitor.visitIntInsn(BIPUSH, 63);
methodVisitor.visitInsn(IAND);
methodVisitor.visitInsn(CALOAD);
methodVisitor.visitInsn(I2B);
methodVisitor.visitInsn(BASTORE);
methodVisitor.visitVarInsn(ALOAD, 4);
methodVisitor.visitInsn(ICONST_2);
methodVisitor.visitFieldInsn(GETSTATIC, "org/metatype/sxc/util/Base64", "S_BASE64CHAR", "[C");
methodVisitor.visitVarInsn(ILOAD, 7);
methodVisitor.visitIntInsn(BIPUSH, 6);
methodVisitor.visitInsn(ISHR);
methodVisitor.visitIntInsn(BIPUSH, 63);
methodVisitor.visitInsn(IAND);
methodVisitor.visitInsn(CALOAD);
methodVisitor.visitInsn(I2B);
methodVisitor.visitInsn(BASTORE);
methodVisitor.visitVarInsn(ALOAD, 4);
methodVisitor.visitInsn(ICONST_3);
methodVisitor.visitFieldInsn(GETSTATIC, "org/metatype/sxc/util/Base64", "S_BASE64CHAR", "[C");
methodVisitor.visitVarInsn(ILOAD, 7);
methodVisitor.visitIntInsn(BIPUSH, 63);
methodVisitor.visitInsn(IAND);
methodVisitor.visitInsn(CALOAD);
methodVisitor.visitInsn(I2B);
methodVisitor.visitInsn(BASTORE);
methodVisitor.visitVarInsn(ALOAD, 3);
methodVisitor.visitVarInsn(ALOAD, 4);
methodVisitor.visitInsn(ICONST_0);
methodVisitor.visitInsn(ICONST_4);
methodVisitor.visitMethodInsn(INVOKEVIRTUAL, "java/io/OutputStream", "write", "([BII)V", false);
methodVisitor.visitIincInsn(5, 3);
methodVisitor.visitIincInsn(6, -3);
methodVisitor.visitJumpInsn(GOTO, label1);
methodVisitor.visitLabel(label2);
methodVisitor.visitVarInsn(ILOAD, 6);
methodVisitor.visitInsn(ICONST_1);
Label label3 = new Label();
methodVisitor.visitJumpInsn(IF_ICMPNE, label3);
methodVisitor.visitVarInsn(ALOAD, 0);
methodVisitor.visitVarInsn(ILOAD, 5);
methodVisitor.visitInsn(BALOAD);
methodVisitor.visitIntInsn(SIPUSH, 255);
methodVisitor.visitInsn(IAND);
methodVisitor.visitVarInsn(ISTORE, 7);
methodVisitor.visitVarInsn(ALOAD, 4);
methodVisitor.visitInsn(ICONST_0);
methodVisitor.visitFieldInsn(GETSTATIC, "org/metatype/sxc/util/Base64", "S_BASE64CHAR", "[C");
methodVisitor.visitVarInsn(ILOAD, 7);
methodVisitor.visitInsn(ICONST_2);
methodVisitor.visitInsn(ISHR);
methodVisitor.visitInsn(CALOAD);
methodVisitor.visitInsn(I2B);
methodVisitor.visitInsn(BASTORE);
methodVisitor.visitVarInsn(ALOAD, 4);
methodVisitor.visitInsn(ICONST_1);
methodVisitor.visitFieldInsn(GETSTATIC, "org/metatype/sxc/util/Base64", "S_BASE64CHAR", "[C");
methodVisitor.visitVarInsn(ILOAD, 7);
methodVisitor.visitInsn(ICONST_4);
methodVisitor.visitInsn(ISHL);
methodVisitor.visitIntInsn(BIPUSH, 63);
methodVisitor.visitInsn(IAND);
methodVisitor.visitInsn(CALOAD);
methodVisitor.visitInsn(I2B);
methodVisitor.visitInsn(BASTORE);
methodVisitor.visitVarInsn(ALOAD, 4);
methodVisitor.visitInsn(ICONST_2);
methodVisitor.visitIntInsn(BIPUSH, 61);
methodVisitor.visitInsn(BASTORE);
methodVisitor.visitVarInsn(ALOAD, 4);
methodVisitor.visitInsn(ICONST_3);
methodVisitor.visitIntInsn(BIPUSH, 61);
methodVisitor.visitInsn(BASTORE);
methodVisitor.visitVarInsn(ALOAD, 3);
methodVisitor.visitVarInsn(ALOAD, 4);
methodVisitor.visitInsn(ICONST_0);
methodVisitor.visitInsn(ICONST_4);
methodVisitor.visitMethodInsn(INVOKEVIRTUAL, "java/io/OutputStream", "write", "([BII)V", false);
Label label4 = new Label();
methodVisitor.visitJumpInsn(GOTO, label4);
methodVisitor.visitLabel(label3);
methodVisitor.visitVarInsn(ILOAD, 6);
methodVisitor.visitInsn(ICONST_2);
methodVisitor.visitJumpInsn(IF_ICMPNE, label4);
methodVisitor.visitVarInsn(ALOAD, 0);
methodVisitor.visitVarInsn(ILOAD, 5);
methodVisitor.visitInsn(BALOAD);
methodVisitor.visitIntInsn(SIPUSH, 255);
methodVisitor.visitInsn(IAND);
methodVisitor.visitIntInsn(BIPUSH, 8);
methodVisitor.visitInsn(ISHL);
methodVisitor.visitVarInsn(ALOAD, 0);
methodVisitor.visitVarInsn(ILOAD, 5);
methodVisitor.visitInsn(ICONST_1);
methodVisitor.visitInsn(IADD);
methodVisitor.visitInsn(BALOAD);
methodVisitor.visitIntInsn(SIPUSH, 255);
methodVisitor.visitInsn(IAND);
methodVisitor.visitInsn(IADD);
methodVisitor.visitVarInsn(ISTORE, 7);
methodVisitor.visitVarInsn(ALOAD, 4);
methodVisitor.visitInsn(ICONST_0);
methodVisitor.visitFieldInsn(GETSTATIC, "org/metatype/sxc/util/Base64", "S_BASE64CHAR", "[C");
methodVisitor.visitVarInsn(ILOAD, 7);
methodVisitor.visitIntInsn(BIPUSH, 10);
methodVisitor.visitInsn(ISHR);
methodVisitor.visitInsn(CALOAD);
methodVisitor.visitInsn(I2B);
methodVisitor.visitInsn(BASTORE);
methodVisitor.visitVarInsn(ALOAD, 4);
methodVisitor.visitInsn(ICONST_1);
methodVisitor.visitFieldInsn(GETSTATIC, "org/metatype/sxc/util/Base64", "S_BASE64CHAR", "[C");
methodVisitor.visitVarInsn(ILOAD, 7);
methodVisitor.visitInsn(ICONST_4);
methodVisitor.visitInsn(ISHR);
methodVisitor.visitIntInsn(BIPUSH, 63);
methodVisitor.visitInsn(IAND);
methodVisitor.visitInsn(CALOAD);
methodVisitor.visitInsn(I2B);
methodVisitor.visitInsn(BASTORE);
methodVisitor.visitVarInsn(ALOAD, 4);
methodVisitor.visitInsn(ICONST_2);
methodVisitor.visitFieldInsn(GETSTATIC, "org/metatype/sxc/util/Base64", "S_BASE64CHAR", "[C");
methodVisitor.visitVarInsn(ILOAD, 7);
methodVisitor.visitInsn(ICONST_2);
methodVisitor.visitInsn(ISHL);
methodVisitor.visitIntInsn(BIPUSH, 63);
methodVisitor.visitInsn(IAND);
methodVisitor.visitInsn(CALOAD);
methodVisitor.visitInsn(I2B);
methodVisitor.visitInsn(BASTORE);
methodVisitor.visitVarInsn(ALOAD, 4);
methodVisitor.visitInsn(ICONST_3);
methodVisitor.visitIntInsn(BIPUSH, 61);
methodVisitor.visitInsn(BASTORE);
methodVisitor.visitVarInsn(ALOAD, 3);
methodVisitor.visitVarInsn(ALOAD, 4);
methodVisitor.visitInsn(ICONST_0);
methodVisitor.visitInsn(ICONST_4);
methodVisitor.visitMethodInsn(INVOKEVIRTUAL, "java/io/OutputStream", "write", "([BII)V", false);
methodVisitor.visitLabel(label4);
methodVisitor.visitInsn(RETURN);
methodVisitor.visitMaxs(5, 8);
methodVisitor.visitEnd();
}
{
methodVisitor = classWriter.visitMethod(ACC_PUBLIC | ACC_STATIC, "encode", "([BIILjava/io/Writer;)V", null, new String[] { "java/io/IOException" });
methodVisitor.visitCode();
methodVisitor.visitVarInsn(ILOAD, 2);
Label label0 = new Label();
methodVisitor.visitJumpInsn(IFGT, label0);
methodVisitor.visitInsn(RETURN);
methodVisitor.visitLabel(label0);
methodVisitor.visitInsn(ICONST_4);
methodVisitor.visitIntInsn(NEWARRAY, T_CHAR);
methodVisitor.visitVarInsn(ASTORE, 4);
methodVisitor.visitVarInsn(ILOAD, 1);
methodVisitor.visitVarInsn(ISTORE, 5);
methodVisitor.visitVarInsn(ILOAD, 2);
methodVisitor.visitVarInsn(ILOAD, 1);
methodVisitor.visitInsn(ISUB);
methodVisitor.visitVarInsn(ISTORE, 6);
methodVisitor.visitInsn(ICONST_0);
methodVisitor.visitVarInsn(ISTORE, 7);
Label label1 = new Label();
methodVisitor.visitLabel(label1);
methodVisitor.visitVarInsn(ILOAD, 6);
methodVisitor.visitInsn(ICONST_3);
Label label2 = new Label();
methodVisitor.visitJumpInsn(IF_ICMPLT, label2);
methodVisitor.visitVarInsn(ALOAD, 0);
methodVisitor.visitVarInsn(ILOAD, 5);
methodVisitor.visitInsn(BALOAD);
methodVisitor.visitIntInsn(SIPUSH, 255);
methodVisitor.visitInsn(IAND);
methodVisitor.visitIntInsn(BIPUSH, 16);
methodVisitor.visitInsn(ISHL);
methodVisitor.visitVarInsn(ALOAD, 0);
methodVisitor.visitVarInsn(ILOAD, 5);
methodVisitor.visitInsn(ICONST_1);
methodVisitor.visitInsn(IADD);
methodVisitor.visitInsn(BALOAD);
methodVisitor.visitIntInsn(SIPUSH, 255);
methodVisitor.visitInsn(IAND);
methodVisitor.visitIntInsn(BIPUSH, 8);
methodVisitor.visitInsn(ISHL);
methodVisitor.visitInsn(IADD);
methodVisitor.visitVarInsn(ALOAD, 0);
methodVisitor.visitVarInsn(ILOAD, 5);
methodVisitor.visitInsn(ICONST_2);
methodVisitor.visitInsn(IADD);
methodVisitor.visitInsn(BALOAD);
methodVisitor.visitIntInsn(SIPUSH, 255);
methodVisitor.visitInsn(IAND);
methodVisitor.visitInsn(IADD);
methodVisitor.visitVarInsn(ISTORE, 8);
methodVisitor.visitVarInsn(ALOAD, 4);
methodVisitor.visitInsn(ICONST_0);
methodVisitor.visitFieldInsn(GETSTATIC, "org/metatype/sxc/util/Base64", "S_BASE64CHAR", "[C");
methodVisitor.visitVarInsn(ILOAD, 8);
methodVisitor.visitIntInsn(BIPUSH, 18);
methodVisitor.visitInsn(ISHR);
methodVisitor.visitInsn(CALOAD);
methodVisitor.visitInsn(CASTORE);
methodVisitor.visitVarInsn(ALOAD, 4);
methodVisitor.visitInsn(ICONST_1);
methodVisitor.visitFieldInsn(GETSTATIC, "org/metatype/sxc/util/Base64", "S_BASE64CHAR", "[C");
methodVisitor.visitVarInsn(ILOAD, 8);
methodVisitor.visitIntInsn(BIPUSH, 12);
methodVisitor.visitInsn(ISHR);
methodVisitor.visitIntInsn(BIPUSH, 63);
methodVisitor.visitInsn(IAND);
methodVisitor.visitInsn(CALOAD);
methodVisitor.visitInsn(CASTORE);
methodVisitor.visitVarInsn(ALOAD, 4);
methodVisitor.visitInsn(ICONST_2);
methodVisitor.visitFieldInsn(GETSTATIC, "org/metatype/sxc/util/Base64", "S_BASE64CHAR", "[C");
methodVisitor.visitVarInsn(ILOAD, 8);
methodVisitor.visitIntInsn(BIPUSH, 6);
methodVisitor.visitInsn(ISHR);
methodVisitor.visitIntInsn(BIPUSH, 63);
methodVisitor.visitInsn(IAND);
methodVisitor.visitInsn(CALOAD);
methodVisitor.visitInsn(CASTORE);
methodVisitor.visitVarInsn(ALOAD, 4);
methodVisitor.visitInsn(ICONST_3);
methodVisitor.visitFieldInsn(GETSTATIC, "org/metatype/sxc/util/Base64", "S_BASE64CHAR", "[C");
methodVisitor.visitVarInsn(ILOAD, 8);
methodVisitor.visitIntInsn(BIPUSH, 63);
methodVisitor.visitInsn(IAND);
methodVisitor.visitInsn(CALOAD);
methodVisitor.visitInsn(CASTORE);
methodVisitor.visitVarInsn(ALOAD, 3);
methodVisitor.visitVarInsn(ALOAD, 4);
methodVisitor.visitInsn(ICONST_0);
methodVisitor.visitInsn(ICONST_4);
methodVisitor.visitMethodInsn(INVOKEVIRTUAL, "java/io/Writer", "write", "([CII)V", false);
methodVisitor.visitIincInsn(5, 3);
methodVisitor.visitIincInsn(6, -3);
methodVisitor.visitIincInsn(7, 4);
methodVisitor.visitVarInsn(ILOAD, 7);
methodVisitor.visitIntInsn(BIPUSH, 76);
methodVisitor.visitInsn(IREM);
Label label3 = new Label();
methodVisitor.visitJumpInsn(IFNE, label3);
methodVisitor.visitVarInsn(ALOAD, 3);
methodVisitor.visitLdcInsn("\n");
methodVisitor.visitMethodInsn(INVOKEVIRTUAL, "java/io/Writer", "write", "(Ljava/lang/String;)V", false);
methodVisitor.visitLabel(label3);
methodVisitor.visitJumpInsn(GOTO, label1);
methodVisitor.visitLabel(label2);
methodVisitor.visitVarInsn(ILOAD, 6);
methodVisitor.visitInsn(ICONST_1);
Label label4 = new Label();
methodVisitor.visitJumpInsn(IF_ICMPNE, label4);
methodVisitor.visitVarInsn(ALOAD, 0);
methodVisitor.visitVarInsn(ILOAD, 5);
methodVisitor.visitInsn(BALOAD);
methodVisitor.visitIntInsn(SIPUSH, 255);
methodVisitor.visitInsn(IAND);
methodVisitor.visitVarInsn(ISTORE, 8);
methodVisitor.visitVarInsn(ALOAD, 4);
methodVisitor.visitInsn(ICONST_0);
methodVisitor.visitFieldInsn(GETSTATIC, "org/metatype/sxc/util/Base64", "S_BASE64CHAR", "[C");
methodVisitor.visitVarInsn(ILOAD, 8);
methodVisitor.visitInsn(ICONST_2);
methodVisitor.visitInsn(ISHR);
methodVisitor.visitInsn(CALOAD);
methodVisitor.visitInsn(CASTORE);
methodVisitor.visitVarInsn(ALOAD, 4);
methodVisitor.visitInsn(ICONST_1);
methodVisitor.visitFieldInsn(GETSTATIC, "org/metatype/sxc/util/Base64", "S_BASE64CHAR", "[C");
methodVisitor.visitVarInsn(ILOAD, 8);
methodVisitor.visitInsn(ICONST_4);
methodVisitor.visitInsn(ISHL);
methodVisitor.visitIntInsn(BIPUSH, 63);
methodVisitor.visitInsn(IAND);
methodVisitor.visitInsn(CALOAD);
methodVisitor.visitInsn(CASTORE);
methodVisitor.visitVarInsn(ALOAD, 4);
methodVisitor.visitInsn(ICONST_2);
methodVisitor.visitIntInsn(BIPUSH, 61);
methodVisitor.visitInsn(CASTORE);
methodVisitor.visitVarInsn(ALOAD, 4);
methodVisitor.visitInsn(ICONST_3);
methodVisitor.visitIntInsn(BIPUSH, 61);
methodVisitor.visitInsn(CASTORE);
methodVisitor.visitVarInsn(ALOAD, 3);
methodVisitor.visitVarInsn(ALOAD, 4);
methodVisitor.visitInsn(ICONST_0);
methodVisitor.visitInsn(ICONST_4);
methodVisitor.visitMethodInsn(INVOKEVIRTUAL, "java/io/Writer", "write", "([CII)V", false);
Label label5 = new Label();
methodVisitor.visitJumpInsn(GOTO, label5);
methodVisitor.visitLabel(label4);
methodVisitor.visitVarInsn(ILOAD, 6);
methodVisitor.visitInsn(ICONST_2);
methodVisitor.visitJumpInsn(IF_ICMPNE, label5);
methodVisitor.visitVarInsn(ALOAD, 0);
methodVisitor.visitVarInsn(ILOAD, 5);
methodVisitor.visitInsn(BALOAD);
methodVisitor.visitIntInsn(SIPUSH, 255);
methodVisitor.visitInsn(IAND);
methodVisitor.visitIntInsn(BIPUSH, 8);
methodVisitor.visitInsn(ISHL);
methodVisitor.visitVarInsn(ALOAD, 0);
methodVisitor.visitVarInsn(ILOAD, 5);
methodVisitor.visitInsn(ICONST_1);
methodVisitor.visitInsn(IADD);
methodVisitor.visitInsn(BALOAD);
methodVisitor.visitIntInsn(SIPUSH, 255);
methodVisitor.visitInsn(IAND);
methodVisitor.visitInsn(IADD);
methodVisitor.visitVarInsn(ISTORE, 8);
methodVisitor.visitVarInsn(ALOAD, 4);
methodVisitor.visitInsn(ICONST_0);
methodVisitor.visitFieldInsn(GETSTATIC, "org/metatype/sxc/util/Base64", "S_BASE64CHAR", "[C");
methodVisitor.visitVarInsn(ILOAD, 8);
methodVisitor.visitIntInsn(BIPUSH, 10);
methodVisitor.visitInsn(ISHR);
methodVisitor.visitInsn(CALOAD);
methodVisitor.visitInsn(CASTORE);
methodVisitor.visitVarInsn(ALOAD, 4);
methodVisitor.visitInsn(ICONST_1);
methodVisitor.visitFieldInsn(GETSTATIC, "org/metatype/sxc/util/Base64", "S_BASE64CHAR", "[C");
methodVisitor.visitVarInsn(ILOAD, 8);
methodVisitor.visitInsn(ICONST_4);
methodVisitor.visitInsn(ISHR);
methodVisitor.visitIntInsn(BIPUSH, 63);
methodVisitor.visitInsn(IAND);
methodVisitor.visitInsn(CALOAD);
methodVisitor.visitInsn(CASTORE);
methodVisitor.visitVarInsn(ALOAD, 4);
methodVisitor.visitInsn(ICONST_2);
methodVisitor.visitFieldInsn(GETSTATIC, "org/metatype/sxc/util/Base64", "S_BASE64CHAR", "[C");
methodVisitor.visitVarInsn(ILOAD, 8);
methodVisitor.visitInsn(ICONST_2);
methodVisitor.visitInsn(ISHL);
methodVisitor.visitIntInsn(BIPUSH, 63);
methodVisitor.visitInsn(IAND);
methodVisitor.visitInsn(CALOAD);
methodVisitor.visitInsn(CASTORE);
methodVisitor.visitVarInsn(ALOAD, 4);
methodVisitor.visitInsn(ICONST_3);
methodVisitor.visitIntInsn(BIPUSH, 61);
methodVisitor.visitInsn(CASTORE);
methodVisitor.visitVarInsn(ALOAD, 3);
methodVisitor.visitVarInsn(ALOAD, 4);
methodVisitor.visitInsn(ICONST_0);
methodVisitor.visitInsn(ICONST_4);
methodVisitor.visitMethodInsn(INVOKEVIRTUAL, "java/io/Writer", "write", "([CII)V", false);
methodVisitor.visitLabel(label5);
methodVisitor.visitInsn(RETURN);
methodVisitor.visitMaxs(5, 9);
methodVisitor.visitEnd();
}
{
methodVisitor = classWriter.visitMethod(ACC_STATIC, "<clinit>", "()V", null, null);
methodVisitor.visitCode();
methodVisitor.visitIntInsn(BIPUSH, 64);
methodVisitor.visitIntInsn(NEWARRAY, T_CHAR);
methodVisitor.visitInsn(DUP);
methodVisitor.visitInsn(ICONST_0);
methodVisitor.visitIntInsn(BIPUSH, 65);
methodVisitor.visitInsn(CASTORE);
methodVisitor.visitInsn(DUP);
methodVisitor.visitInsn(ICONST_1);
methodVisitor.visitIntInsn(BIPUSH, 66);
methodVisitor.visitInsn(CASTORE);
methodVisitor.visitInsn(DUP);
methodVisitor.visitInsn(ICONST_2);
methodVisitor.visitIntInsn(BIPUSH, 67);
methodVisitor.visitInsn(CASTORE);
methodVisitor.visitInsn(DUP);
methodVisitor.visitInsn(ICONST_3);
methodVisitor.visitIntInsn(BIPUSH, 68);
methodVisitor.visitInsn(CASTORE);
methodVisitor.visitInsn(DUP);
methodVisitor.visitInsn(ICONST_4);
methodVisitor.visitIntInsn(BIPUSH, 69);
methodVisitor.visitInsn(CASTORE);
methodVisitor.visitInsn(DUP);
methodVisitor.visitInsn(ICONST_5);
methodVisitor.visitIntInsn(BIPUSH, 70);
methodVisitor.visitInsn(CASTORE);
methodVisitor.visitInsn(DUP);
methodVisitor.visitIntInsn(BIPUSH, 6);
methodVisitor.visitIntInsn(BIPUSH, 71);
methodVisitor.visitInsn(CASTORE);
methodVisitor.visitInsn(DUP);
methodVisitor.visitIntInsn(BIPUSH, 7);
methodVisitor.visitIntInsn(BIPUSH, 72);
methodVisitor.visitInsn(CASTORE);
methodVisitor.visitInsn(DUP);
methodVisitor.visitIntInsn(BIPUSH, 8);
methodVisitor.visitIntInsn(BIPUSH, 73);
methodVisitor.visitInsn(CASTORE);
methodVisitor.visitInsn(DUP);
methodVisitor.visitIntInsn(BIPUSH, 9);
methodVisitor.visitIntInsn(BIPUSH, 74);
methodVisitor.visitInsn(CASTORE);
methodVisitor.visitInsn(DUP);
methodVisitor.visitIntInsn(BIPUSH, 10);
methodVisitor.visitIntInsn(BIPUSH, 75);
methodVisitor.visitInsn(CASTORE);
methodVisitor.visitInsn(DUP);
methodVisitor.visitIntInsn(BIPUSH, 11);
methodVisitor.visitIntInsn(BIPUSH, 76);
methodVisitor.visitInsn(CASTORE);
methodVisitor.visitInsn(DUP);
methodVisitor.visitIntInsn(BIPUSH, 12);
methodVisitor.visitIntInsn(BIPUSH, 77);
methodVisitor.visitInsn(CASTORE);
methodVisitor.visitInsn(DUP);
methodVisitor.visitIntInsn(BIPUSH, 13);
methodVisitor.visitIntInsn(BIPUSH, 78);
methodVisitor.visitInsn(CASTORE);
methodVisitor.visitInsn(DUP);
methodVisitor.visitIntInsn(BIPUSH, 14);
methodVisitor.visitIntInsn(BIPUSH, 79);
methodVisitor.visitInsn(CASTORE);
methodVisitor.visitInsn(DUP);
methodVisitor.visitIntInsn(BIPUSH, 15);
methodVisitor.visitIntInsn(BIPUSH, 80);
methodVisitor.visitInsn(CASTORE);
methodVisitor.visitInsn(DUP);
methodVisitor.visitIntInsn(BIPUSH, 16);
methodVisitor.visitIntInsn(BIPUSH, 81);
methodVisitor.visitInsn(CASTORE);
methodVisitor.visitInsn(DUP);
methodVisitor.visitIntInsn(BIPUSH, 17);
methodVisitor.visitIntInsn(BIPUSH, 82);
methodVisitor.visitInsn(CASTORE);
methodVisitor.visitInsn(DUP);
methodVisitor.visitIntInsn(BIPUSH, 18);
methodVisitor.visitIntInsn(BIPUSH, 83);
methodVisitor.visitInsn(CASTORE);
methodVisitor.visitInsn(DUP);
methodVisitor.visitIntInsn(BIPUSH, 19);
methodVisitor.visitIntInsn(BIPUSH, 84);
methodVisitor.visitInsn(CASTORE);
methodVisitor.visitInsn(DUP);
methodVisitor.visitIntInsn(BIPUSH, 20);
methodVisitor.visitIntInsn(BIPUSH, 85);
methodVisitor.visitInsn(CASTORE);
methodVisitor.visitInsn(DUP);
methodVisitor.visitIntInsn(BIPUSH, 21);
methodVisitor.visitIntInsn(BIPUSH, 86);
methodVisitor.visitInsn(CASTORE);
methodVisitor.visitInsn(DUP);
methodVisitor.visitIntInsn(BIPUSH, 22);
methodVisitor.visitIntInsn(BIPUSH, 87);
methodVisitor.visitInsn(CASTORE);
methodVisitor.visitInsn(DUP);
methodVisitor.visitIntInsn(BIPUSH, 23);
methodVisitor.visitIntInsn(BIPUSH, 88);
methodVisitor.visitInsn(CASTORE);
methodVisitor.visitInsn(DUP);
methodVisitor.visitIntInsn(BIPUSH, 24);
methodVisitor.visitIntInsn(BIPUSH, 89);
methodVisitor.visitInsn(CASTORE);
methodVisitor.visitInsn(DUP);
methodVisitor.visitIntInsn(BIPUSH, 25);
methodVisitor.visitIntInsn(BIPUSH, 90);
methodVisitor.visitInsn(CASTORE);
methodVisitor.visitInsn(DUP);
methodVisitor.visitIntInsn(BIPUSH, 26);
methodVisitor.visitIntInsn(BIPUSH, 97);
methodVisitor.visitInsn(CASTORE);
methodVisitor.visitInsn(DUP);
methodVisitor.visitIntInsn(BIPUSH, 27);
methodVisitor.visitIntInsn(BIPUSH, 98);
methodVisitor.visitInsn(CASTORE);
methodVisitor.visitInsn(DUP);
methodVisitor.visitIntInsn(BIPUSH, 28);
methodVisitor.visitIntInsn(BIPUSH, 99);
methodVisitor.visitInsn(CASTORE);
methodVisitor.visitInsn(DUP);
methodVisitor.visitIntInsn(BIPUSH, 29);
methodVisitor.visitIntInsn(BIPUSH, 100);
methodVisitor.visitInsn(CASTORE);
methodVisitor.visitInsn(DUP);
methodVisitor.visitIntInsn(BIPUSH, 30);
methodVisitor.visitIntInsn(BIPUSH, 101);
methodVisitor.visitInsn(CASTORE);
methodVisitor.visitInsn(DUP);
methodVisitor.visitIntInsn(BIPUSH, 31);
methodVisitor.visitIntInsn(BIPUSH, 102);
methodVisitor.visitInsn(CASTORE);
methodVisitor.visitInsn(DUP);
methodVisitor.visitIntInsn(BIPUSH, 32);
methodVisitor.visitIntInsn(BIPUSH, 103);
methodVisitor.visitInsn(CASTORE);
methodVisitor.visitInsn(DUP);
methodVisitor.visitIntInsn(BIPUSH, 33);
methodVisitor.visitIntInsn(BIPUSH, 104);
methodVisitor.visitInsn(CASTORE);
methodVisitor.visitInsn(DUP);
methodVisitor.visitIntInsn(BIPUSH, 34);
methodVisitor.visitIntInsn(BIPUSH, 105);
methodVisitor.visitInsn(CASTORE);
methodVisitor.visitInsn(DUP);
methodVisitor.visitIntInsn(BIPUSH, 35);
methodVisitor.visitIntInsn(BIPUSH, 106);
methodVisitor.visitInsn(CASTORE);
methodVisitor.visitInsn(DUP);
methodVisitor.visitIntInsn(BIPUSH, 36);
methodVisitor.visitIntInsn(BIPUSH, 107);
methodVisitor.visitInsn(CASTORE);
methodVisitor.visitInsn(DUP);
methodVisitor.visitIntInsn(BIPUSH, 37);
methodVisitor.visitIntInsn(BIPUSH, 108);
methodVisitor.visitInsn(CASTORE);
methodVisitor.visitInsn(DUP);
methodVisitor.visitIntInsn(BIPUSH, 38);
methodVisitor.visitIntInsn(BIPUSH, 109);
methodVisitor.visitInsn(CASTORE);
methodVisitor.visitInsn(DUP);
methodVisitor.visitIntInsn(BIPUSH, 39);
methodVisitor.visitIntInsn(BIPUSH, 110);
methodVisitor.visitInsn(CASTORE);
methodVisitor.visitInsn(DUP);
methodVisitor.visitIntInsn(BIPUSH, 40);
methodVisitor.visitIntInsn(BIPUSH, 111);
methodVisitor.visitInsn(CASTORE);
methodVisitor.visitInsn(DUP);
methodVisitor.visitIntInsn(BIPUSH, 41);
methodVisitor.visitIntInsn(BIPUSH, 112);
methodVisitor.visitInsn(CASTORE);
methodVisitor.visitInsn(DUP);
methodVisitor.visitIntInsn(BIPUSH, 42);
methodVisitor.visitIntInsn(BIPUSH, 113);
methodVisitor.visitInsn(CASTORE);
methodVisitor.visitInsn(DUP);
methodVisitor.visitIntInsn(BIPUSH, 43);
methodVisitor.visitIntInsn(BIPUSH, 114);
methodVisitor.visitInsn(CASTORE);
methodVisitor.visitInsn(DUP);
methodVisitor.visitIntInsn(BIPUSH, 44);
methodVisitor.visitIntInsn(BIPUSH, 115);
methodVisitor.visitInsn(CASTORE);
methodVisitor.visitInsn(DUP);
methodVisitor.visitIntInsn(BIPUSH, 45);
methodVisitor.visitIntInsn(BIPUSH, 116);
methodVisitor.visitInsn(CASTORE);
methodVisitor.visitInsn(DUP);
methodVisitor.visitIntInsn(BIPUSH, 46);
methodVisitor.visitIntInsn(BIPUSH, 117);
methodVisitor.visitInsn(CASTORE);
methodVisitor.visitInsn(DUP);
methodVisitor.visitIntInsn(BIPUSH, 47);
methodVisitor.visitIntInsn(BIPUSH, 118);
methodVisitor.visitInsn(CASTORE);
methodVisitor.visitInsn(DUP);
methodVisitor.visitIntInsn(BIPUSH, 48);
methodVisitor.visitIntInsn(BIPUSH, 119);
methodVisitor.visitInsn(CASTORE);
methodVisitor.visitInsn(DUP);
methodVisitor.visitIntInsn(BIPUSH, 49);
methodVisitor.visitIntInsn(BIPUSH, 120);
methodVisitor.visitInsn(CASTORE);
methodVisitor.visitInsn(DUP);
methodVisitor.visitIntInsn(BIPUSH, 50);
methodVisitor.visitIntInsn(BIPUSH, 121);
methodVisitor.visitInsn(CASTORE);
methodVisitor.visitInsn(DUP);
methodVisitor.visitIntInsn(BIPUSH, 51);
methodVisitor.visitIntInsn(BIPUSH, 122);
methodVisitor.visitInsn(CASTORE);
methodVisitor.visitInsn(DUP);
methodVisitor.visitIntInsn(BIPUSH, 52);
methodVisitor.visitIntInsn(BIPUSH, 48);
methodVisitor.visitInsn(CASTORE);
methodVisitor.visitInsn(DUP);
methodVisitor.visitIntInsn(BIPUSH, 53);
methodVisitor.visitIntInsn(BIPUSH, 49);
methodVisitor.visitInsn(CASTORE);
methodVisitor.visitInsn(DUP);
methodVisitor.visitIntInsn(BIPUSH, 54);
methodVisitor.visitIntInsn(BIPUSH, 50);
methodVisitor.visitInsn(CASTORE);
methodVisitor.visitInsn(DUP);
methodVisitor.visitIntInsn(BIPUSH, 55);
methodVisitor.visitIntInsn(BIPUSH, 51);
methodVisitor.visitInsn(CASTORE);
methodVisitor.visitInsn(DUP);
methodVisitor.visitIntInsn(BIPUSH, 56);
methodVisitor.visitIntInsn(BIPUSH, 52);
methodVisitor.visitInsn(CASTORE);
methodVisitor.visitInsn(DUP);
methodVisitor.visitIntInsn(BIPUSH, 57);
methodVisitor.visitIntInsn(BIPUSH, 53);
methodVisitor.visitInsn(CASTORE);
methodVisitor.visitInsn(DUP);
methodVisitor.visitIntInsn(BIPUSH, 58);
methodVisitor.visitIntInsn(BIPUSH, 54);
methodVisitor.visitInsn(CASTORE);
methodVisitor.visitInsn(DUP);
methodVisitor.visitIntInsn(BIPUSH, 59);
methodVisitor.visitIntInsn(BIPUSH, 55);
methodVisitor.visitInsn(CASTORE);
methodVisitor.visitInsn(DUP);
methodVisitor.visitIntInsn(BIPUSH, 60);
methodVisitor.visitIntInsn(BIPUSH, 56);
methodVisitor.visitInsn(CASTORE);
methodVisitor.visitInsn(DUP);
methodVisitor.visitIntInsn(BIPUSH, 61);
methodVisitor.visitIntInsn(BIPUSH, 57);
methodVisitor.visitInsn(CASTORE);
methodVisitor.visitInsn(DUP);
methodVisitor.visitIntInsn(BIPUSH, 62);
methodVisitor.visitIntInsn(BIPUSH, 43);
methodVisitor.visitInsn(CASTORE);
methodVisitor.visitInsn(DUP);
methodVisitor.visitIntInsn(BIPUSH, 63);
methodVisitor.visitIntInsn(BIPUSH, 47);
methodVisitor.visitInsn(CASTORE);
methodVisitor.visitFieldInsn(PUTSTATIC, "org/metatype/sxc/util/Base64", "S_BASE64CHAR", "[C");
methodVisitor.visitIntInsn(SIPUSH, 128);
methodVisitor.visitIntInsn(NEWARRAY, T_BYTE);
methodVisitor.visitFieldInsn(PUTSTATIC, "org/metatype/sxc/util/Base64", "S_DECODETABLE", "[B");
methodVisitor.visitInsn(ICONST_0);
methodVisitor.visitVarInsn(ISTORE, 0);
Label label0 = new Label();
methodVisitor.visitLabel(label0);
methodVisitor.visitVarInsn(ILOAD, 0);
methodVisitor.visitFieldInsn(GETSTATIC, "org/metatype/sxc/util/Base64", "S_DECODETABLE", "[B");
methodVisitor.visitInsn(ARRAYLENGTH);
Label label1 = new Label();
methodVisitor.visitJumpInsn(IF_ICMPGE, label1);
methodVisitor.visitFieldInsn(GETSTATIC, "org/metatype/sxc/util/Base64", "S_DECODETABLE", "[B");
methodVisitor.visitVarInsn(ILOAD, 0);
methodVisitor.visitIntInsn(BIPUSH, 127);
methodVisitor.visitInsn(BASTORE);
methodVisitor.visitIincInsn(0, 1);
methodVisitor.visitJumpInsn(GOTO, label0);
methodVisitor.visitLabel(label1);
methodVisitor.visitInsn(ICONST_0);
methodVisitor.visitVarInsn(ISTORE, 0);
Label label2 = new Label();
methodVisitor.visitLabel(label2);
methodVisitor.visitVarInsn(ILOAD, 0);
methodVisitor.visitFieldInsn(GETSTATIC, "org/metatype/sxc/util/Base64", "S_BASE64CHAR", "[C");
methodVisitor.visitInsn(ARRAYLENGTH);
Label label3 = new Label();
methodVisitor.visitJumpInsn(IF_ICMPGE, label3);
methodVisitor.visitFieldInsn(GETSTATIC, "org/metatype/sxc/util/Base64", "S_DECODETABLE", "[B");
methodVisitor.visitFieldInsn(GETSTATIC, "org/metatype/sxc/util/Base64", "S_BASE64CHAR", "[C");
methodVisitor.visitVarInsn(ILOAD, 0);
methodVisitor.visitInsn(CALOAD);
methodVisitor.visitVarInsn(ILOAD, 0);
methodVisitor.visitInsn(I2B);
methodVisitor.visitInsn(BASTORE);
methodVisitor.visitIincInsn(0, 1);
methodVisitor.visitJumpInsn(GOTO, label2);
methodVisitor.visitLabel(label3);
methodVisitor.visitInsn(RETURN);
methodVisitor.visitMaxs(4, 1);
methodVisitor.visitEnd();
}
classWriter.visitEnd();

return classWriter.toByteArray();
}
}
